Workbook
Name Base_Cost_of_Equity: Assumptions!$C$9
Name Benchmark_yield: Assumptions!$C$8
Name Entry_yield: Assumptions!$C$7
Name g: Assumptions!$C$4
Name HKDCNY: Assumptions!$C$13
Name HKDUSD: Assumptions!$C$12
Name Holding_Period: Assumptions!$C$5
Name k: Assumptions!$C$3
Name Target_return: Assumptions!$C$6

Sheet Assumptions
B2: Parameter | C2: Value | D2: Remarks
B3: Bank Cost of Equity (k) | C3: 0.1
B4: Long-term Growth (g) | C4: 0.02 | D4: Inflation rate as proxy for long term Growth
B5: Holding Period | C5: 3
B6: Target return | C6: 0.29465259
B7: Entry yield | C7: 0.20075184
B8: Benchmark yield | C8: 0.1174
B9: Base Cost of Equity | C9: 0.0725
B11: Forex | C11: Value | D11: Remarks
B12: HKDUSD | C12: 7.8
B13: HKDCNY | C13: 0.89
B18: Core Philosophy
B19: Fair P/TBV ≈ (ROTCE – g) ÷ (k – g)
B21: ROTCE = Core Net income ÷ Tangible common equity (goodwill & intangibles stripped out).
B22: TBV is Tangible Common Equity.
B23: Core net income is predictable, high-quality earnings from core operations (e.g., deposits and lending) rather than fluctuating trading activities,
B25: DuPont for ROTCE
B26: ROTCE = Net Profit Margin × Asset Turnover × Tangible Equity Multiplier
B28: Net Profit Margin = Core Net Income attributable to common shareholders / Total Revenue
B29: Asset Turnover = Total Revenue / Total Assets
B30: Tangible Equity Multiplier = Total Assets / Tangible Common Equity

Sheet Model
B2: Listing Symbol | C2: Official Chinese name | D2: Currency used in financial statements | E2: YYYY-MM-DD | F2: YYYY-MM-DD | G2: From End Date of Last Statement | H2: From End Date of Last Statement | I2: From the Last Annual Report | J2: From the Last Annual Report | K2: Latest | L2: From last Financial year (in trading currency) | N2: Net Interest Income / Interest - Earnings | O2: Operating Expenses / Operating Income | P2: Core Net income attributable to common shareholders ÷ Tangible common equity | Q2: Revenue/Total Assets | R2: Total Assets/TBV | S2: Core Net Income attributable to common shareholders / Total Revenue | T2: From latest balance sheet (2 Decimal) | U2: From last FY report | V2: Dividend/Earnings | W2: (ROTCE – g) ÷ (k – g) | X2: TBV * Fair TBV Multiple
B3: Company Info. | E3: Data | M3: Profibilities and Efficiency | W3: Valuation | Y3: @ Target Return | Z3: @Entry yield | AA3: @Benchmark yield | AB3: @Base equity cost | AC3: Market
B4: Primary Listing Symbol | C4: Name | D4: Report Currency | E4: Financial Year End (MM/DD) | F4: End Date of Last Statement (YYYY/MM/DD) | G4: Total Assets (in Millions) | H4: Tangible Common Equity (TBV) (in Millions) | I4: Revenue (in Millions) | J4: Last FY Core shareholders' Net Income (in Millions) | K4: Latest Share Outstanding | L4: Last FY Dividend per share | M4: CET1 | N4: Net Interest Margin | O4: Cost-to-Income Ratio | P4: ROTCE | Q4: Total Asset Turnover | R4: Tangible Equity Multiplier | S4: Core Net Income Margin | T4: Tangible Common Equity per Share | U4: Last FY Core shareholders' EPS | V4: Payout Ratio | W4: Fair TBV Multiple | X4: Fair Price in Trading Currency | Y4: Target Price | Z4: Entry Price | AA4: Sell Price | AB4: Exit Price | AC4: Lastest Market Price | AD4: Trading Currency | AE4: Forex Pair | AF4: Forex Rate | AG4: Dividend Yield
B5: 主要上市地代码 | C5: 公司名称 | D5: 财务报告使用的货币 | E5: 财年结束日期 | F5: 最新财报的截止日期 | G5: 总资产 | H5: 有形净资产 | I5: 收入 | J5: 核心净利润 | K5: 股数 | L5: 上一财年每股股息 | M5: 普通股一级资本比率 | N5: 净息差 | O5: 成本收入比 | P5: 有形普通股回报率 | Q5: 总资产周转率 | R5: 有形权益乘数 | S5: 核心净利率 | T5: 每股有形净资产 | U5: 上一个财年核心EPS | V5: 派息率 | W5: 公允市净率倍数 | X5: 隐含公允股价 | Y5: 目标价 | Z5: 买入价 | AA5: 卖出价 | AB5: 退出价 | AC5: 最新股价 | AD5: 交易货币 | AG5: 股息率
B6: HK:1398 / SH:601398 | C6: 工商银行 | D6: CNY | E6: 12/31 | F6: 45838 | G6: 48821746 | H6: 3969841 | I6: 820000 | J6: 366900 | K6: 356406000000 | L6: 0.308 | M6: 0.141 | N6: 0.0155 | O6: 0.2527 | P6: =J6/H6 -> 0.092421838 | Q6: =I6/G6 -> 0.016795794 | R6: =G6/H6 -> 12.298162 | S6: =J6/I6 -> 0.44743902 | T6: =H6/(K6/1000000)*$AF6 -> 11.138536 | U6: =J6/(K6/1000000)*$AF6 -> 1.0294439 | V6: =L6/U6 -> 0.29919065 | W6: =(P6-g)/(k-g) -> 0.90527297 | X6: =T6*W6 -> 10.083415 | Y6: =PV(Target_return,Holding_Period,-L6,-X6) -> 5.2103295 | Z6: =PV(Entry_yield,Holding_Period,-L6,-X6) -> 6.4723887 | AA6: =PV(Benchmark_yield,Holding_Period,-L6,-X6) -> 7.9704745 | AB6: =PV(Base_Cost_of_Equity,Holding_Period,-L6,-X6) -> 8.9782563 | AC6: 7.43 | AD6: CNY | AE6: =AD6&D6 -> CNYCNY | AF6: =IFERROR(VLOOKUP(AE6,Assumptions!B$12:C$13,2),1) -> 1 | AG6: =L6/AC6 -> 0.041453567
B7: HK:939 / SH:601939 | C7: 建设银行 | D7: CNY | E7: 12/31 | F7: 45838 | G7: 40571149 | H7: 3322127 | I7: 728570 | J7: 335577 | K7: 250011000000 | L7: 0.387 | M7: 0.1448 | N7: 0.0151 | O7: 0.2958 | P7: =J7/H7 -> 0.10101269 | Q7: =I7/G7 -> 0.017957835 | R7: =G7/H7 -> 12.212402 | S7: =J7/I7 -> 0.46059679 | T7: =H7/(K7/1000000)*$AF7 -> 13.287923 | U7: =J7/(K7/1000000)*$AF7 -> 1.3422489 | V7: =L7/U7 -> 0.28832208 | W7: =(P7-g)/(k-g) -> 1.0126587 | X7: =T7*W7 -> 13.456131 | Y7: =PV(Target_return,Holding_Period,-L7,-X7) -> 6.9091346 | Z7: =PV(Entry_yield,Holding_Period,-L7,-X7) -> 8.5867439 | AA7: =PV(Benchmark_yield,Holding_Period,-L7,-X7) -> 10.578499 | AB7: =PV(Base_Cost_of_Equity,Holding_Period,-L7,-X7) -> 11.918567 | AC7: 8.91 | AD7: CNY | AE7: =AD7&D7 -> CNYCNY | AF7: =IFERROR(VLOOKUP(AE7,Assumptions!B$12:C$13,2),1) -> 1 | AG7: =L7/AC7 -> 0.043434343
B8: HK:1288 / SH:601288 | C8: 农业银行 | D8: CNY | E8: 12/31 | F8: 45838 | G8: 43238135 | H8: 3090808 | I8: 711416 | J8: 282671 | K8: 349983000000 | L8: 0.238 | M8: 0.1163 | N8: 0.0142 | O8: 0.344 | P8: =J8/H8 -> 0.091455373 | Q8: =I8/G8 -> 0.016453439 | R8: =G8/H8 -> 13.989266 | S8: =J8/I8 -> 0.39733574 | T8: =H8/(K8/1000000)*$AF8 -> 8.8313089 | U8: =J8/(K8/1000000)*$AF8 -> 0.80767066 | V8: =L8/U8 -> 0.29467457 | W8: =(P8-g)/(k-g) -> 0.89319217 | X8: =T8*W8 -> 7.888056 | Y8: =PV(Target_return,Holding_Period,-L8,-X8) -> 4.0705535 | Z8: =PV(Entry_yield,Holding_Period,-L8,-X8) -> 5.0570308 | AA8: =PV(Benchmark_yield,Holding_Period,-L8,-X8) -> 6.2280457 | AB8: =PV(Base_Cost_of_Equity,Holding_Period,-L8,-X8) -> 7.0158255 | AC8: 6.96 | AD8: CNY | AE8: =AD8&D8 -> CNYCNY | AF8: =IFERROR(VLOOKUP(AE8,Assumptions!B$12:C$13,2),1) -> 1 | AG8: =L8/AC8 -> 0.034195402
B9: HK:3988 / SH:601988 | C9: 中国银行 | D9: CNY | E9: 12/31 | F9: 45838 | G9: 35061299 | H9: 2816231 | I9: 632771 | J9: 252700 | K9: 294388000000 | L9: 0.229 | M9: 0.122 | N9: 0.014 | O9: 0.2877 | P9: =J9/H9 -> 0.089729855 | Q9: =I9/G9 -> 0.018047563 | R9: =G9/H9 -> 12.449724 | S9: =J9/I9 -> 0.39935458 | T9: =H9/(K9/1000000)*$AF9 -> 9.566392 | U9: =J9/(K9/1000000)*$AF9 -> 0.85839097 | V9: =L9/U9 -> 0.2667782 | W9: =(P9-g)/(k-g) -> 0.87162319 | X9: =T9*W9 -> 8.3382891 | Y9: =PV(Target_return,Holding_Period,-L9,-X9) -> 4.2615655 | Z9: =PV(Entry_yield,Holding_Period,-L9,-X9) -> 5.2981572 | AA9: =PV(Benchmark_yield,Holding_Period,-L9,-X9) -> 6.5290415 | AB9: =PV(Base_Cost_of_Equity,Holding_Period,-L9,-X9) -> 7.3572744 | AC9: 5.38 | AD9: CNY | AE9: =AD9&D9 -> CNYCNY | AF9: =IFERROR(VLOOKUP(AE9,Assumptions!B$12:C$13,2),1) -> 1 | AG9: =L9/AC9 -> 0.042565056
B10: SH:601166 | C10: 兴业银行 | D10: CNY | E10: 12/31 | F10: 45838 | G10: 10510731 | H10: 766132 | I10: 212226 | J10: 77205 | K10: 20774000000 | L10: 1.06 | M10: 0.0975 | N10: 0.0172 | O10: 0.476 | P10: =J10/H10 -> 0.10077245 | Q10: =I10/G10 -> 0.020191364 | R10: =G10/H10 -> 13.719217 | S10: =J10/I10 -> 0.36378672 | T10: =H10/(K10/1000000)*$AF10 -> 36.879368 | U10: =J10/(K10/1000000)*$AF10 -> 3.7164244 | V10: =L10/U10 -> 0.28522039 | W10: =(P10-g)/(k-g) -> 1.0096556 | X10: =T10*W10 -> 37.235463 | Y10: =PV(Target_return,Holding_Period,-L10,-X10) -> 19.098842 | Z10: =PV(Entry_yield,Holding_Period,-L10,-X10) -> 23.738093 | AA10: =PV(Benchmark_yield,Holding_Period,-L10,-X10) -> 29.246264 | AB10: =PV(Base_Cost_of_Equity,Holding_Period,-L10,-X10) -> 32.952288 | AC10: 20.09 | AD10: CNY | AE10: =AD10&D10 -> CNYCNY | AF10: =IFERROR(VLOOKUP(AE10,Assumptions!B$12:C$13,2),1) -> 1 | AG10: =L10/AC10 -> 0.052762568
B11: HK:1658 / SH:601658 | C11: 邮政储蓄银行 | D11: CNY | E11: 12/31 | F11: 45838 | G11: 17084910 | H11: 1023006 | I11: 349133 | J11: 86479 | K11: 99161000000 | L11: 0.24 | M11: 0.0948 | N11: 0.0187 | O11: 0.252 | P11: =J11/H11 -> 0.084534206 | Q11: =I11/G11 -> 0.020435168 | R11: =G11/H11 -> 16.700694 | S11: =J11/I11 -> 0.24769644 | T11: =H11/(K11/1000000)*$AF11 -> 10.316616 | U11: =J11/(K11/1000000)*$AF11 -> 0.87210698 | V11: =L11/U11 -> 0.2751956 | W11: =(P11-g)/(k-g) -> 0.80667758 | X11: =T11*W11 -> 8.3221831 | Y11: =PV(Target_return,Holding_Period,-L11,-X11) -> 4.2742718 | Z11: =PV(Entry_yield,Holding_Period,-L11,-X11) -> 5.3119981 | AA11: =PV(Benchmark_yield,Holding_Period,-L11,-X11) -> 6.544036 | AB11: =PV(Base_Cost_of_Equity,Holding_Period,-L11,-X11) -> 7.372955 | AC11: 5.17 | AD11: CNY | AE11: =AD11&D11 -> CNYCNY | AF11: =IFERROR(VLOOKUP(AE11,Assumptions!B$12:C$13,2),1) -> 1 | AG11: =L11/AC11 -> 0.046421663
B12: HK:0005 | C12: HSBC | D12: USD | E12: 12/31 | F12: 45838 | G12: 3017048 | H12: 154295 | I12: 51910 | J12: 23730 | K12: 17918000000 | L12: =0.780688+0.779073+0.777313+2.791007 -> 5.128081 | M12: 0.149 | N12: 0.0145 | O12: 0.523 | P12: =J12/H12 -> 0.1537963 | Q12: =I12/G12 -> 0.01720556 | R12: =G12/H12 -> 19.553764 | S12: =J12/I12 -> 0.45713735 | T12: =H12/(K12/1000000)*$AF12 -> 67.16715 | U12: =J12/(K12/1000000)*$AF12 -> 10.330059 | V12: =L12/U12 -> 0.4964232 | W12: =(P12-g)/(k-g) -> 1.6724537 | X12: =T12*W12 -> 112.33395 | Y12: =PV(Target_return,Holding_Period,-L12,-X12) -> 61.150425 | Z12: =PV(Entry_yield,Holding_Period,-L12,-X12) -> 75.67554 | AA12: =PV(Benchmark_yield,Holding_Period,-L12,-X12) -> 92.888552 | AB12: =PV(Base_Cost_of_Equity,Holding_Period,-L12,-X12) -> 104.45469 | AC12: 130 | AD12: HKD | AE12: =AD12&D12 -> HKDUSD | AF12: =IFERROR(VLOOKUP(AE12,Assumptions!B$12:C$13,2),1) -> 7.8 | AG12: =L12/AC12 -> 0.039446777
