Workbook
Name Common_Shares: Thesis!$C$11
Name Equity_Cost: Valuation_Model!$C$5
Name Exchange_Rate: Thesis!$C$13
Name Market_Price: Thesis!$C$10
Name Reporting_currency: Thesis!$C$12
Name Terminal_Growth: Valuation_Model!$F$4

Sheet Thesis
B1: Investment Thesis for | C1: 六福珠宝 | D1: 0590.HK
B2: Model last updated: | C2: 45643 | E2: Status: Held
A3: Introduction
B4: Comapny Information
B5: Comp_Sector: | C5: C0003
B6: Review Interval: | C6: 8
B7: Review Date: | C7: =EOMONTH(EDATE(BS!C1,Thesis!C6),0) -> 45626
B9: =D1&" Stock Information" -> 0590.HK Stock Information
B10: Market Price: | C10: 15.68 | D10: HKD
B11: Number of Shares: | C11: 587107850
B12: Reporting Currency: | C12: HKD
B13: Exchange Rate: | C13: 1 | D13: =IF(C12=D10,D10,C12&"/"&D10) -> HKD
B14: Capitalization: | C14: =Thesis!C10*Thesis!C11/1000000 -> 9205.8511
A16: Stock Analysis
A18: ="1." -> 1. | B18: Adjusted FCFE Calculation
B19: Formula:
B20: Adjusted FCFE = Net Income + D&A – Maintenance Capex ± WCInv (if material).
B22: Variables | C22: =Data!C3 -> 1000
B23: Operating after-tax Profit = | C23: =Normalized_FCF!C11 -> 1080495.1 | D23: =C12 -> HKD
B24: Non-Operating after-tax Profit = | C24: =Normalized_FCF!C19 -> 190177
B25: Net Income = | C25: =C23+C24 -> 1270672.1
B27: Adjusted FCFE = | C27: =Normalized_FCF!C20 -> 1270672.1
B28: Adjusted FCFE per share = | C28: =C27/(Common_Shares/Data!C3) -> 2.1642908
B29: FCFE/Market Price = | C29: =C28/Market_Price -> 0.13802875
B31: Notes:
B32: 1. the model explicitly avoids aggressive growth assumptions and prioritizes downside protection.
B33: 2. Net borrowing is excluded (fixed at 0), and WCInv is only included if it materially distorts FCFE (>5% volatility).
B34: 3. Normalization: 5-year averages will smooth cyclicality for 590.HK.
A36: ="2." -> 2. | B36: Equity Cost of Capital (Buffett Method)
B37: Equity Cost of Capital (r) = | C37: 0.1
B39: Qualitative Adjustments
B40: Nonexistent moats | C40: 0 | D40: HK
B41: Weak balance sheets | C41: 0 | D41: Stable Business
B42: Poor management | C42: 0
B43: Qualitative Adjustments | C43: =SUM(C40:C42) -> 0
A45: ="3." -> 3. | B45: No-Growth DCF Valuation
B46: Key Metrics:
B47: Adjusted Earnings Yield = Adjusted FCFE / Market Cap.
B48: Intrinsic Value (No Growth) = Adjusted FCFE / Equity Cost of Capital.
B50: Decision Rule:
B51: Buy if Adjusted Earnings Yield > 7%
A53: ="4." -> 4. | B53: Growth Scenario Analysis
B54: Formula:
B55: g = (r × P - Adjusted FCFE) / (P + Adjusted FCFE)
B57: Phase Breakdown:
B58: High Growth: 5 years at 5%, then transitions to 3% perpetual growth.
B60: Scenario Analysis:
B61: Base Case
B62: Opertimistic Case
B63: Pessimistic Case
B65: Valuation
B66: the Equity Value will be conservatively realized
B67: over a holding period of | C67: 3
B68: Target Return | C68: 0.2
B69: Margin of Safety: | C69: =Scenarios!F71 -> -0.26862204
B71: Output:
B72: Buy price range incorporating a 15–20% margin of safety (e.g., HKD 10–14/share).
A74: ="5." -> 5. | B74: Equity Value Calculation
B75: Formula:
B76: Equity Value = Intrinsic Value (with user-selected implied g) + Non-operating Assets - Interest-bearing Debt
B78: Key Adjustments:
B79: Non-operating Assets: Include cash, marketable securities, real estate, etc., at market value.
B80: Debt: Subtract total interest-bearing debt (market value if distressed).
A82: Conclusion
B84: Scenarios | C84: HGR | D84: Value per share | E84: Probabilities
B85: Optimistic
B86: Base
B87: No Growth
B88: Pessimistic
B90: Price Target: | C90: =Scenarios!C71 -> 13.723744 | D90: =Reporting_currency -> HKD
A92: KEY EXCLUSIONS & LIMITATIONS
B93: Conservative Bias:
B94: Excludes net borrowing, potentially undervaluing firms with debt efficiency.
B96: Growth Constraints:
B97: Perpetual growth capped at 3%, penalizing high-growth companies.
B99: Subjective Adjustments:
B100: Non-operating assets and debt require manual review.

Sheet Data
B1: =Thesis!C12 -> HKD | C1: 45382 | D1: =EOMONTH(EDATE(C1,-12),0) -> 45016 | E1: =EOMONTH(EDATE(D1,-12),0) -> 44651 | F1: =EOMONTH(EDATE(E1,-12),0) -> 44286 | G1: =EOMONTH(EDATE(F1,-12),0) -> 43921 | H1: =EOMONTH(EDATE(G1,-12),0) -> 43555 | I1: =EOMONTH(EDATE(H1,-12),0) -> 43190 | J1: =EOMONTH(EDATE(I1,-12),0) -> 42825 | K1: =EOMONTH(EDATE(J1,-12),0) -> 42460 | ... M1: =EOMONTH(EDATE(L1,-12),0) -> 41729
B2: Data (Dirty)
B3: Income Statement | C3: 1000
B4: Sales | C4: 15325962 | D4: 11977844 | E4: 11737803 | F4: 8861335 | G4: 11233771 | H4: 15859990
B5: COGS | C5: 11151623 | D5: 8747447 | E5: 8503976 | F5: 6229020 | G5: 7910751 | H5: 11826154
B6: OPEX | C6: 2297566 | D6: 1867515 | E6: 1815111 | F6: 1694480 | G6: 2118252 | H6: 2416769
B7: Incl. Selling Expenses | C7: 2043459 | D7: 1517989 | E7: 1491293 | F7: 1412494
B8: R&D
B9: Interest Expense | C9: 59596 | D9: 20763 | E9: 23097 | F9: 28849 | G9: 63075 | H9: 34253
B10: Interest Income | C10: 28977 | D10: 33125 | E10: 87344 | F10: 63398
B11: Income Tax Paid | C11: 327166 | D11: 280664 | E11: 291296 | F11: 236303
B12: Reported Net Income | C12: 1767305 | D12: 1284757 | E12: 1392364 | F12: 1017335 | G12: 866315
B13: Non-controling Interests | C13: -9467 | D13: -30 | E13: -27 | F13: 1799 | G13: 1337 | H13: 10908
B15: Cash Flow Statement
B16: D&A | C16: 463424 | D16: 371724 | E16: 435672 | F16: 520888
B17: CAPX | C17: 676387 | D17: 107280 | E17: 455483 | F17: 138937
B18: WCInv | C18: 626583 | D18: 352099 | E18: 1045251 | F18: -818677
B19: Dividend per share | C19: 1.36 | D19: 1.1 | E19: 1.1 | F19: 1 | G19: 1 | H19: 1.15
B21: Balance Sheet
B22: ST AR | D22: 213823 | E22: 187711 | F22: 277338
B23: ST Inventory | D23: 8852611 | E23: 8769304 | F23: 7321614
B24: Total Liabilities | C24: 3990166 | D24: 2466431 | E24: 3908586 | F24: 2946772
B25: Total Equity | C25: 12863898 | D25: 12220942 | E25: 12078528 | F25: 11324224
B27: Other Data
B28: Contingent Liabilities | C28: =20356+1075000 -> 1095356 | D28: =24308+1075000 -> 1099308 | E28: =32736+1075000 -> 1107736 | F28: =47325+1075000 -> 1122325
B30: IS & CF Statements (Clean)
B31: Income Statement
B32: Sales | C32: =IF(C$4="","",C4) -> 15325962 | D32: =IF(D$4="","",D4) -> 11977844 | E32: =IF(E$4="","",E4) -> 11737803 | F32: =IF(F$4="","",F4) -> 8861335 | G32: =IF(G$4="","",G4) -> 11233771 | H32: =IF(H$4="","",H4) -> 15859990 | I32: =IF(I$4="","",I4) | J32: =IF(J$4="","",J4) | ... M32: =IF(M$4="","",M4)
B33: COGS | C33: =IF(C$4="","",-C5) -> -11151623 | D33: =IF(D$4="","",-D5) -> -8747447 | E33: =IF(E$4="","",-E5) -> -8503976 | F33: =IF(F$4="","",-F5) -> -6229020 | G33: =IF(G$4="","",-G5) -> -7910751 | H33: =IF(H$4="","",-H5) -> -11826154 | I33: =IF(I$4="","",-I5) | J33: =IF(J$4="","",-J5) | ... M33: =IF(M$4="","",-M5)
B34: Gross Margin | C34: =IF(C32="","",C32+C33) -> 4174339 | D34: =IF(D32="","",D32+D33) -> 3230397 | E34: =IF(E32="","",E32+E33) -> 3233827 | F34: =IF(F32="","",F32+F33) -> 2632315 | G34: =IF(G32="","",G32+G33) -> 3323020 | H34: =IF(H32="","",H32+H33) -> 4033836 | I34: =IF(I32="","",I32+I33) | J34: =IF(J32="","",J32+J33) | ... M34: =IF(M32="","",M32+M33)
B35: OPEX | C35: =IF(C$4="","",-C6) -> -2297566 | D35: =IF(D$4="","",-D6) -> -1867515 | E35: =IF(E$4="","",-E6) -> -1815111 | F35: =IF(F$4="","",-F6) -> -1694480 | G35: =IF(G$4="","",-G6) -> -2118252 | H35: =IF(H$4="","",-H6) -> -2416769 | I35: =IF(I$4="","",-I6) | J35: =IF(J$4="","",-J6) | ... M35: =IF(M$4="","",-M6)
B36: Incl. Selling Expenses | C36: =IF(C$4="","",-C7) -> -2043459 | D36: =IF(D$4="","",-D7) -> -1517989 | E36: =IF(E$4="","",-E7) -> -1491293 | F36: =IF(F$4="","",-F7) -> -1412494 | G36: =IF(G$4="","",-G7) -> 0 | H36: =IF(H$4="","",-H7) -> 0 | I36: =IF(I$4="","",-I7) | J36: =IF(J$4="","",-J7) | ... M36: =IF(M$4="","",-M7)
B37: Incl. Other Opex | C37: =IF(C$4="","",C35-C36) -> -254107 | D37: =IF(D$4="","",D35-D36) -> -349526 | E37: =IF(E$4="","",E35-E36) -> -323818 | F37: =IF(F$4="","",F35-F36) -> -281986 | G37: =IF(G$4="","",G35-G36) -> -2118252 | H37: =IF(H$4="","",H35-H36) -> -2416769 | I37: =IF(I$4="","",I35-I36) | J37: =IF(J$4="","",J35-J36) | ... M37: =IF(M$4="","",M35-M36)
B38: R&D | C38: =IF(C$4="","",-C8) -> 0 | D38: =IF(D$4="","",-D8) -> 0 | E38: =IF(E$4="","",-E8) -> 0 | F38: =IF(F$4="","",-F8) -> 0 | G38: =IF(G$4="","",-G8) -> 0 | H38: =IF(H$4="","",-H8) -> 0 | I38: =IF(I$4="","",-I8) | J38: =IF(J$4="","",-J8) | ... M38: =IF(M$4="","",-M8)
B39: EBIT | C39: =IF(C$4="","",C34+C35+C38) -> 1876773 | D39: =IF(D$4="","",D34+D35+D38) -> 1362882 | E39: =IF(E$4="","",E34+E35+E38) -> 1418716 | F39: =IF(F$4="","",F34+F35+F38) -> 937835 | G39: =IF(G$4="","",G34+G35+G38) -> 1204768 | H39: =IF(H$4="","",H34+H35+H38) -> 1617067 | I39: =IF(I$4="","",I34+I35+I38) | J39: =IF(J$4="","",J34+J35+J38) | ... M39: =IF(M$4="","",M34+M35+M38)
B40: Net Interest Income | C40: =IF(C$4="","",C41+C42) -> -30619 | D40: =IF(D$4="","",D41+D42) -> 12362 | E40: =IF(E$4="","",E41+E42) -> 64247 | F40: =IF(F$4="","",F41+F42) -> 34549 | G40: =IF(G$4="","",G41+G42) -> -63075 | H40: =IF(H$4="","",H41+H42) -> -34253 | I40: =IF(I$4="","",I41+I42) | J40: =IF(J$4="","",J41+J42) | ... M40: =IF(M$4="","",M41+M42)
B41: Incl. Interest Expense | C41: =IF(C$4="","",-C9) -> -59596 | D41: =IF(D$4="","",-D9) -> -20763 | E41: =IF(E$4="","",-E9) -> -23097 | F41: =IF(F$4="","",-F9) -> -28849 | G41: =IF(G$4="","",-G9) -> -63075 | H41: =IF(H$4="","",-H9) -> -34253 | I41: =IF(I$4="","",-I9) | J41: =IF(J$4="","",-J9) | ... M41: =IF(M$4="","",-M9)
B42: Incl. Interest Income | C42: =IF(C$4="","",C10) -> 28977 | D42: =IF(D$4="","",D10) -> 33125 | E42: =IF(E$4="","",E10) -> 87344 | F42: =IF(F$4="","",F10) -> 63398 | G42: =IF(G$4="","",G10) -> 0 | H42: =IF(H$4="","",H10) -> 0 | I42: =IF(I$4="","",I10) | J42: =IF(J$4="","",J10) | ... M42: =IF(M$4="","",M10)
B43: Non-Operating Income (Est.) | C43: =IF(C$4="","",C45-(C39+C40+C44)) -> 248317 | D43: =IF(D$4="","",D45-(D39+D40+D44)) -> 190177 | E43: =IF(E$4="","",E45-(E39+E40+E44)) -> 200697 | F43: =IF(F$4="","",F45-(F39+F40+F44)) -> 281254 | G43: =IF(G$4="","",G45-(G39+G40+G44)) -> -275378 | H43: =IF(H$4="","",H45-(H39+H40+H44)) -> -1582814 | I43: =IF(I$4="","",I45-(I39+I40+I44)) | J43: =IF(J$4="","",J45-(J39+J40+J44)) | ... M43: =IF(M$4="","",M45-(M39+M40+M44))
B44: Income Tax Paid | C44: =IF(C$4="","",-C11) -> -327166 | D44: =IF(D$4="","",-D11) -> -280664 | E44: =IF(E$4="","",-E11) -> -291296 | F44: =IF(F$4="","",-F11) -> -236303 | G44: =IF(G$4="","",-G11) -> 0 | H44: =IF(H$4="","",-H11) -> 0 | I44: =IF(I$4="","",-I11) | J44: =IF(J$4="","",-J11) | ... M44: =IF(M$4="","",-M11)
B45: Reported Net Income | C45: =IF(C$4="","",C12) -> 1767305 | D45: =IF(D$4="","",D12) -> 1284757 | E45: =IF(E$4="","",E12) -> 1392364 | F45: =IF(F$4="","",F12) -> 1017335 | G45: =IF(G$4="","",G12) -> 866315 | H45: =IF(H$4="","",H12) -> 0 | I45: =IF(I$4="","",I12) | J45: =IF(J$4="","",J12) | ... M45: =IF(M$4="","",M12)
B46: Non-controling Interests | C46: =IF(C$4="","",MIN(-C13,0)) -> 0 | D46: =IF(D$4="","",MIN(-D13,0)) -> 0 | E46: =IF(E$4="","",MIN(-E13,0)) -> 0 | F46: =IF(F$4="","",MIN(-F13,0)) -> -1799 | G46: =IF(G$4="","",MIN(-G13,0)) -> -1337 | H46: =IF(H$4="","",MIN(-H13,0)) -> -10908 | I46: =IF(I$4="","",MIN(-I13,0)) | J46: =IF(J$4="","",MIN(-J13,0)) | ... M46: =IF(M$4="","",MIN(-M13,0))
B48: Cash Flow Statement
B49: D&A | C49: =IF(C$4="","",-C16) -> -463424 | D49: =IF(D$4="","",-D16) -> -371724 | E49: =IF(E$4="","",-E16) -> -435672 | F49: =IF(F$4="","",-F16) -> -520888 | G49: =IF(G$4="","",-G16) -> 0 | H49: =IF(H$4="","",-H16) -> 0 | I49: =IF(I$4="","",-I16) | J49: =IF(J$4="","",-J16) | ... M49: =IF(M$4="","",-M16)
B50: CAPX | C50: =IF(C$4="","",-C17) -> -676387 | D50: =IF(D$4="","",-D17) -> -107280 | E50: =IF(E$4="","",-E17) -> -455483 | F50: =IF(F$4="","",-F17) -> -138937 | G50: =IF(G$4="","",-G17) -> 0 | H50: =IF(H$4="","",-H17) -> 0 | I50: =IF(I$4="","",-I17) | J50: =IF(J$4="","",-J17) | ... M50: =IF(M$4="","",-M17)
B51: WCInv | C51: =IF(C$4="","",-C18) -> -626583 | D51: =IF(D$4="","",-D18) -> -352099 | E51: =IF(E$4="","",-E18) -> -1045251 | F51: =IF(F$4="","",-F18) -> 818677 | G51: =IF(G$4="","",-G18) -> 0 | H51: =IF(H$4="","",-H18) -> 0 | I51: =IF(I$4="","",-I18) | J51: =IF(J$4="","",-J18) | ... M51: =IF(M$4="","",-M18)
B52: Dividend per share | C52: =IF(C$4="","",C19) -> 1.36 | D52: =IF(D$4="","",D19) -> 1.1 | E52: =IF(E$4="","",E19) -> 1.1 | F52: =IF(F$4="","",F19) -> 1 | G52: =IF(G$4="","",G19) -> 1 | H52: =IF(H$4="","",H19) -> 1.15 | I52: =IF(I$4="","",I19) | J52: =IF(J$4="","",J19) | ... M52: =IF(M$4="","",M19)
B54: YoY %
B55: =B32 -> Sales | C55: =IF(D$32="","",C32/D32-1) -> 0.27952593 | D55: =IF(E$32="","",D32/E32-1) -> 0.02045025 | E55: =IF(F$32="","",E32/F32-1) -> 0.32460888 | F55: =IF(G$32="","",F32/G32-1) -> -0.21118785 | G55: =IF(H$32="","",G32/H32-1) -> -0.29169117 | H55: =IF(I$32="","",H32/I32-1) | I55: =IF(J$32="","",I32/J32-1) | J55: =IF(K$32="","",J32/K32-1) | ... M55: =IF(N$32="","",M32/N32-1)
B56: =B39 -> EBIT | C56: =IF(D$32="","",C33/D33-1) -> 0.27484316 | D56: =IF(E$32="","",D33/E33-1) -> 0.028630255 | E56: =IF(F$32="","",E33/F33-1) -> 0.36521893 | F56: =IF(G$32="","",F33/G33-1) -> -0.21258803 | G56: =IF(H$32="","",G33/H33-1) -> -0.33107999 | H56: =IF(I$32="","",H33/I33-1) | I56: =IF(J$32="","",I33/J33-1) | J56: =IF(K$32="","",J33/K33-1) | ... M56: =IF(N$32="","",M33/N33-1)
B57: =B43 -> Non-Operating Income (Est.) | C57: =IF(D$32="","",C34/D34-1) -> 0.29220619 | D57: =IF(E$32="","",D34/E34-1) -> -0.0010606628 | E57: =IF(F$32="","",E34/F34-1) -> 0.22851065 | F57: =IF(G$32="","",F34/G34-1) -> -0.2078546 | G57: =IF(H$32="","",G34/H34-1) -> -0.17621341 | H57: =IF(I$32="","",H34/I34-1) | I57: =IF(J$32="","",I34/J34-1) | J57: =IF(K$32="","",J34/K34-1) | ... M57: =IF(N$32="","",M34/N34-1)
B58: =B45 -> Reported Net Income | C58: =IF(D$32="","",C35/D35-1) -> 0.23027981 | D58: =IF(E$32="","",D35/E35-1) -> 0.028870962 | E58: =IF(F$32="","",E35/F35-1) -> 0.071190572 | F58: =IF(G$32="","",F35/G35-1) -> -0.20005741 | G58: =IF(H$32="","",G35/H35-1) -> -0.12351905 | H58: =IF(I$32="","",H35/I35-1) | I58: =IF(J$32="","",I35/J35-1) | J58: =IF(K$32="","",J35/K35-1) | ... M58: =IF(N$32="","",M35/N35-1)
B59: =B46 -> Non-controling Interests | C59: =IF(D$32="","",C52/D52-1) -> 0.23636364 | D59: =IF(E$32="","",D52/E52-1) -> 0 | E59: =IF(F$32="","",E52/F52-1) -> 0.1 | F59: =IF(G$32="","",F52/G52-1) -> 0 | G59: =IF(H$32="","",G52/H52-1) -> -0.13043478 | H59: =IF(I$32="","",H52/I52-1) | I59: =IF(J$32="","",I52/J52-1) | J59: =IF(K$32="","",J52/K52-1) | ... M59: =IF(N$32="","",M52/N52-1)
B61: Balance Sheet (Clean)
B62: Balance Sheet
B63: Total Assets | C63: =IF(C$4="","",C66+C67) -> 16854064 | D63: =IF(D$4="","",D66+D67) -> 14687373 | E63: =IF(E$4="","",E66+E67) -> 15987114 | F63: =IF(F$4="","",F66+F67) -> 14270996 | G63: =IF(G$4="","",G66+G67) -> 0 | H63: =IF(H$4="","",H66+H67) -> 0 | I63: =IF(I$4="","",I66+I67) | J63: =IF(J$4="","",J66+J67) | ... M63: =IF(M$4="","",M66+M67)
B64: Incl. ST AR | C64: =IF(C$4="","",C22) -> 0 | D64: =IF(D$4="","",D22) -> 213823 | E64: =IF(E$4="","",E22) -> 187711 | F64: =IF(F$4="","",F22) -> 277338 | G64: =IF(G$4="","",G22) -> 0 | H64: =IF(H$4="","",H22) -> 0
B65: Incl. ST Inventory | C65: =IF(C$4="","",C23) -> 0 | D65: =IF(D$4="","",D23) -> 8852611 | E65: =IF(E$4="","",E23) -> 8769304 | F65: =IF(F$4="","",F23) -> 7321614 | G65: =IF(G$4="","",G23) -> 0 | H65: =IF(H$4="","",H23) -> 0
B66: Total Liabilities | C66: =IF(C$4="","",C24) -> 3990166 | D66: =IF(D$4="","",D24) -> 2466431 | E66: =IF(E$4="","",E24) -> 3908586 | F66: =IF(F$4="","",F24) -> 2946772 | G66: =IF(G$4="","",G24) -> 0 | H66: =IF(H$4="","",H24) -> 0 | I66: =IF(I$4="","",I24) | J66: =IF(J$4="","",J24) | ... M66: =IF(M$4="","",M24)
B67: Total Equity | C67: =IF(C$4="","",C25) -> 12863898 | D67: =IF(D$4="","",D25) -> 12220942 | E67: =IF(E$4="","",E25) -> 12078528 | F67: =IF(F$4="","",F25) -> 11324224 | G67: =IF(G$4="","",G25) -> 0 | H67: =IF(H$4="","",H25) -> 0 | I67: =IF(I$4="","",I25) | J67: =IF(J$4="","",J25) | ... M67: =IF(M$4="","",M25)

Sheet Normalized_FCF
B1: =Thesis!C12 -> HKD | C1: Normalized | G1: =Data!C1 -> 45382 | H1: =EOMONTH(EDATE(G1,-12),0) -> 45016 | I1: =EOMONTH(EDATE(H1,-12),0) -> 44651 | J1: =EOMONTH(EDATE(I1,-12),0) -> 44286 | K1: =EOMONTH(EDATE(J1,-12),0) -> 43921 | L1: =EOMONTH(EDATE(K1,-12),0) -> 43555 | M1: =EOMONTH(EDATE(L1,-12),0) -> 43190 | N1: =EOMONTH(EDATE(M1,-12),0) -> 42825 | O1: =EOMONTH(EDATE(N1,-12),0) -> 42460 | ... Q1: =EOMONTH(EDATE(P1,-12),0) -> 41729
B2: FCFE Analysis | E2: Notes
B3: Adjusted FCFE | C3: =Data!C3 -> 1000
B4: Sales | C4: =AVERAGE(G4:L4) -> 12499451 | E4: Historical Average | G4: =Data!C32 -> 15325962 | H4: =Data!D32 -> 11977844 | I4: =Data!E32 -> 11737803 | J4: =Data!F32 -> 8861335 | K4: =Data!G32 -> 11233771 | L4: =Data!H32 -> 15859990 | M4: =Data!I32 | N4: =Data!J32 | ... Q4: =Data!M32
B5: Variable Costs | C5: =C49 -> -10739108 | G5: =G49 -> -13195082 | H5: =H49 -> -10265436 | I5: =I49 -> -9995269 | J5: =J49 -> -7641514 | K5: =K49 -> -7910751 | L5: =L49 -> -11826154 | M5: =M49 | N5: =N49 | ... Q5: =Q49
B6: Contribution Margin | C6: =C4+C5 -> 1760343.1 | G6: =IF(G4="","",G4+G5) -> 2130880 | H6: =IF(H4="","",H4+H5) -> 1712408 | I6: =IF(I4="","",I4+I5) -> 1742534 | J6: =IF(J4="","",J4+J5) -> 1219821 | K6: =IF(K4="","",K4+K5) -> 3323020 | L6: =IF(L4="","",L4+L5) -> 4033836 | M6: =IF(M4="","",M4+M5) | N6: =IF(N4="","",N4+N5) | ... Q6: =IF(Q4="","",Q4+Q5)
B7: Fixed Costs | C7: =C52 -> -302359.25 | G7: =G52 -> -254107 | H7: =H52 -> -349526 | I7: =I52 -> -323818 | J7: =J52 -> -281986 | K7: =K52 -> -2118252 | L7: =L52 -> -2416769 | M7: =M52 | N7: =N52 | ... Q7: =Q52
B8: EBIT | C8: =C6+C7 -> 1457983.9 | G8: =IF(G$4="","",G6+G7) -> 1876773 | H8: =IF(H$4="","",H6+H7) -> 1362882 | I8: =IF(I$4="","",I6+I7) -> 1418716 | J8: =IF(J$4="","",J6+J7) -> 937835 | K8: =IF(K$4="","",K6+K7) -> 1204768 | L8: =IF(L$4="","",L6+L7) -> 1617067 | M8: =IF(M$4="","",M6+M7) | N8: =IF(N$4="","",N6+N7) | ... Q8: =IF(Q$4="","",Q6+Q7)
B9: Net Interest Income | C9: =C65 -> -30619 | G9: =G65 -> -30619 | H9: =H65 -> 12362 | I9: =I65 -> 64247 | J9: =J65 -> 34549 | K9: =K65 -> -63075 | L9: =L65 -> -34253 | M9: =M65 | N9: =N65 | ... Q9: =Q65
B10: Income Tax | C10: =-(C8+C9)*C38 -> -346869.76 | G10: =Data!C44 -> -327166 | H10: =Data!D44 -> -280664 | I10: =Data!E44 -> -291296 | J10: =Data!F44 -> -236303 | K10: =Data!G44 -> 0 | L10: =Data!H44 -> 0 | M10: =Data!I44 | N10: =Data!J44 | ... Q10: =Data!M44
B11: Operating Income | C11: =SUM(C8:C10) -> 1080495.1 | G11: =IF(G$4="","",SUM(G8:G10)) -> 1518988 | H11: =IF(H$4="","",SUM(H8:H10)) -> 1094580 | I11: =IF(I$4="","",SUM(I8:I10)) -> 1191667 | J11: =IF(J$4="","",SUM(J8:J10)) -> 736081 | K11: =IF(K$4="","",SUM(K8:K10)) -> 1141693 | L11: =IF(L$4="","",SUM(L8:L10)) -> 1582814 | M11: =IF(M$4="","",SUM(M8:M10)) | N11: =IF(N$4="","",SUM(N8:N10)) | ... Q11: =IF(Q$4="","",SUM(Q8:Q10))
B12: Add Back D&A | C12: =BS!$G$25*BS!C42 -> 463424 | G12: =IF(Data!C49="","",-Data!C49) -> 463424 | H12: =IF(Data!D49="","",-Data!D49) -> 371724 | I12: =IF(Data!E49="","",-Data!E49) -> 435672 | J12: =IF(Data!F49="","",-Data!F49) -> 520888 | K12: =IF(Data!G49="","",-Data!G49) -> 0 | L12: =IF(Data!H49="","",-Data!H49) -> 0 | M12: =IF(Data!I49="","",-Data!I49) | N12: =IF(Data!J49="","",-Data!J49) | ... Q12: =IF(Data!M49="","",-Data!M49)
B13: Maintenance Capex | C13: =-C4*C32 -> -463424 | G13: =Data!C50 -> -676387 | H13: =Data!D50 -> -107280 | I13: =Data!E50 -> -455483 | J13: =Data!F50 -> -138937 | K13: =Data!G50 -> 0 | L13: =Data!H50 -> 0 | M13: =Data!I50 | N13: =Data!J50 | ... Q13: =Data!M50
B14: Non-controling Interests | C14: =-C4*C34 -> 0 | G14: =Data!C46 -> 0 | H14: =Data!D46 -> 0 | I14: =Data!E46 -> 0 | J14: =Data!F46 -> -1799 | K14: =Data!G46 -> -1337 | L14: =Data!H46 -> -10908 | M14: =Data!I46 | N14: =Data!J46 | ... Q14: =Data!M46
B15: Op. FCFE Before WCInv | C15: =SUM(C11:C14) -> 1080495.1 | G15: =IF(G$4="","",SUM(G11:G14)) -> 1306025 | H15: =IF(H$4="","",SUM(H11:H14)) -> 1359024 | I15: =IF(I$4="","",SUM(I11:I14)) -> 1171856 | J15: =IF(J$4="","",SUM(J11:J14)) -> 1116233 | K15: =IF(K$4="","",SUM(K11:K14)) -> 1140356 | L15: =IF(L$4="","",SUM(L11:L14)) -> 1571906 | M15: =IF(M$4="","",SUM(M11:M14)) | N15: =IF(N$4="","",SUM(N11:N14)) | ... Q15: =IF(Q$4="","",SUM(Q11:Q14))
B16: WCInv | C16: =-C4*C33 -> 0 | E16: WCInv is excluded
B17: Net Borrowing | C17: 0 | E17: Net borrowing is excluded
B18: Op. FCFE | C18: =SUM(C15:C17) -> 1080495.1 | G18: =IF(G$4="","",SUM(G15:G17)) -> 1306025 | H18: =IF(H$4="","",SUM(H15:H17)) -> 1359024 | I18: =IF(I$4="","",SUM(I15:I17)) -> 1171856 | J18: =IF(J$4="","",SUM(J15:J17)) -> 1116233 | K18: =IF(K$4="","",SUM(K15:K17)) -> 1140356 | L18: =IF(L$4="","",SUM(L15:L17)) -> 1571906 | M18: =IF(M$4="","",SUM(M15:M17)) | N18: =IF(N$4="","",SUM(N15:N17)) | ... Q18: =IF(Q$4="","",SUM(Q15:Q17))
B19: Non-Operating Income | C19: =MIN(G19:J19) -> 190177 | E19: Stable Non-Operating Income | G19: =Data!C43 -> 248317 | H19: =Data!D43 -> 190177 | I19: =Data!E43 -> 200697 | J19: =Data!F43 -> 281254 | K19: =Data!G43 -> -275378 | L19: =Data!H43 -> -1582814 | M19: =Data!I43 | N19: =Data!J43 | ... Q19: =Data!M43
B20: Total FCFE | C20: =C18+C19 -> 1270672.1 | G20: =IF(G$4="","",G18+G19) -> 1554342 | H20: =IF(H$4="","",H18+H19) -> 1549201 | I20: =IF(I$4="","",I18+I19) -> 1372553 | J20: =IF(J$4="","",J18+J19) -> 1397487 | K20: =IF(K$4="","",K18+K19) -> 864978 | L20: =IF(L$4="","",L18+L19) -> -10908 | M20: =IF(M$4="","",M18+M19) | N20: =IF(N$4="","",N18+N19) | ... Q20: =IF(Q$4="","",Q18+Q19)
B22: % Sales
B23: Variable Costs | C23: =ABS(C5/C$4) -> 0.85916636 | G23: =IF(G$4="","",ABS(G5/G$4)) -> 0.86096272 | H23: =IF(H$4="","",ABS(H5/H$4)) -> 0.85703537 | I23: =IF(I$4="","",ABS(I5/I$4)) -> 0.85154513 | J23: =IF(J$4="","",ABS(J5/J$4)) -> 0.86234343 | K23: =IF(K$4="","",ABS(K5/K$4)) -> 0.70419372 | L23: =IF(L$4="","",ABS(L5/L$4)) -> 0.74565961 | M23: =IF(M$4="","",ABS(M5/M$4)) | N23: =IF(N$4="","",ABS(N5/N$4)) | ... Q23: =IF(Q$4="","",ABS(Q5/Q$4))
B24: Contribution Margin | C24: =ABS(C6/C$4) -> 0.14083364 | G24: =IF(G$4="","",ABS(G6/G$4)) -> 0.13903728 | H24: =IF(H$4="","",ABS(H6/H$4)) -> 0.14296463 | I24: =IF(I$4="","",ABS(I6/I$4)) -> 0.14845487 | J24: =IF(J$4="","",ABS(J6/J$4)) -> 0.13765657 | K24: =IF(K$4="","",ABS(K6/K$4)) -> 0.29580628 | L24: =IF(L$4="","",ABS(L6/L$4)) -> 0.25434039 | M24: =IF(M$4="","",ABS(M6/M$4)) | N24: =IF(N$4="","",ABS(N6/N$4)) | ... Q24: =IF(Q$4="","",ABS(Q6/Q$4))
B25: Fixed Costs | C25: =ABS(C7/C$4) -> 0.024189803 | G25: =IF(G$4="","",ABS(G7/G$4)) -> 0.016580166 | H25: =IF(H$4="","",ABS(H7/H$4)) -> 0.029181045 | I25: =IF(I$4="","",ABS(I7/I$4)) -> 0.027587616 | J25: =IF(J$4="","",ABS(J7/J$4)) -> 0.031822067 | K25: =IF(K$4="","",ABS(K7/K$4)) -> 0.18856108 | L25: =IF(L$4="","",ABS(L7/L$4)) -> 0.1523815 | M25: =IF(M$4="","",ABS(M7/M$4)) | N25: =IF(N$4="","",ABS(N7/N$4)) | ... Q25: =IF(Q$4="","",ABS(Q7/Q$4))
B26: EBIT | C26: =ABS(C8/C$4) -> 0.11664384 | G26: =IF(G$4="","",ABS(G8/G$4)) -> 0.12245711 | H26: =IF(H$4="","",ABS(H8/H$4)) -> 0.11378358 | I26: =IF(I$4="","",ABS(I8/I$4)) -> 0.12086725 | J26: =IF(J$4="","",ABS(J8/J$4)) -> 0.1058345 | K26: =IF(K$4="","",ABS(K8/K$4)) -> 0.1072452 | L26: =IF(L$4="","",ABS(L8/L$4)) -> 0.10195889 | M26: =IF(M$4="","",ABS(M8/M$4)) | N26: =IF(N$4="","",ABS(N8/N$4)) | ... Q26: =IF(Q$4="","",ABS(Q8/Q$4))
B27: Net Interest Income | C27: =ABS(C9/C$4) -> 0.0024496276 | G27: =IF(G$4="","",ABS(G9/G$4)) -> 0.0019978517 | H27: =IF(H$4="","",ABS(H9/H$4)) -> 0.0010320722 | I27: =IF(I$4="","",ABS(I9/I$4)) -> 0.0054735115 | J27: =IF(J$4="","",ABS(J9/J$4)) -> 0.0038988482 | K27: =IF(K$4="","",ABS(K9/K$4)) -> 0.0056147664 | L27: =IF(L$4="","",ABS(L9/L$4)) -> 0.0021597113 | M27: =IF(M$4="","",ABS(M9/M$4)) | N27: =IF(N$4="","",ABS(N9/N$4)) | ... Q27: =IF(Q$4="","",ABS(Q9/Q$4))
B28: Income Tax | C28: =ABS(C10/C$4) -> 0.0277508 | G28: =IF(G$4="","",ABS(G10/G$4)) -> 0.021347175 | H28: =IF(H$4="","",ABS(H10/H$4)) -> 0.02343193 | I28: =IF(I$4="","",ABS(I10/I$4)) -> 0.02481691 | J28: =IF(J$4="","",ABS(J10/J$4)) -> 0.026666749 | K28: =IF(K$4="","",ABS(K10/K$4)) -> 0 | L28: =IF(L$4="","",ABS(L10/L$4)) -> 0 | M28: =IF(M$4="","",ABS(M10/M$4)) | N28: =IF(N$4="","",ABS(N10/N$4)) | ... Q28: =IF(Q$4="","",ABS(Q10/Q$4))
B29: Operating Income | C29: =ABS(C11/C$4) -> 0.086443408 | G29: =IF(G$4="","",ABS(G11/G$4)) -> 0.099112082 | H29: =IF(H$4="","",ABS(H11/H$4)) -> 0.091383725 | I29: =IF(I$4="","",ABS(I11/I$4)) -> 0.10152385 | J29: =IF(J$4="","",ABS(J11/J$4)) -> 0.083066603 | K29: =IF(K$4="","",ABS(K11/K$4)) -> 0.10163043 | L29: =IF(L$4="","",ABS(L11/L$4)) -> 0.09979918 | M29: =IF(M$4="","",ABS(M11/M$4)) | N29: =IF(N$4="","",ABS(N11/N$4)) | ... Q29: =IF(Q$4="","",ABS(Q11/Q$4))
B30: Non-Operating Income | C30: =ABS(C19/C$4) -> 0.015214828 | G30: =IF(G$4="","",G19/G$4) -> 0.016202376 | H30: =IF(H$4="","",H19/H$4) -> 0.015877398 | I30: =IF(I$4="","",I19/I$4) -> 0.017098345 | J30: =IF(J$4="","",J19/J$4) -> 0.031739461 | K30: =IF(K$4="","",K19/K$4) -> -0.024513407 | L30: =IF(L$4="","",L19/L$4) -> -0.09979918 | M30: =IF(M$4="","",M19/M$4) | N30: =IF(N$4="","",N19/N$4) | ... Q30: =IF(Q$4="","",Q19/Q$4)
B31: Add Back D&A | C31: =ABS(C12/C$4) -> 0.037075549 | G31: =IF(G$4="","",G12/G$4) -> 0.030237841 | H31: =IF(H$4="","",H12/H$4) -> 0.0310343 | I31: =IF(I$4="","",I12/I$4) -> 0.037116997 | J31: =IF(J$4="","",J12/J$4) -> 0.058782114 | K31: =IF(K$4="","",K12/K$4) -> 0 | L31: =IF(L$4="","",L12/L$4) -> 0 | M31: =IF(M$4="","",M12/M$4) | N31: =IF(N$4="","",N12/N$4) | ... Q31: =IF(Q$4="","",Q12/Q$4)
B32: Maintenance Capex | C32: =MAX(AVERAGE(G32:J32),C31) -> 0.037075549 | E32: Historical Average or D&A | G32: =IF(G$4="","",-G13/G$4) -> 0.044133412 | H32: =IF(H$4="","",-H13/H$4) -> 0.0089565368 | I32: =IF(I$4="","",-I13/I$4) -> 0.038804792 | J32: =IF(J$4="","",-J13/J$4) -> 0.015679015 | K32: =IF(K$4="","",-K13/K$4) -> 0 | L32: =IF(L$4="","",-L13/L$4) -> 0 | M32: =IF(M$4="","",-M13/M$4) | N32: =IF(N$4="","",-N13/N$4) | ... Q32: =IF(Q$4="","",-Q13/Q$4)
B33: WCInv | C33: =MIN(AVERAGE(G33:J33)/2,0) -> 0 | E33: WCInv effect is reduced | G33: =IF(G$4="","",-G16/G$4) -> 0 | H33: =IF(H$4="","",-H16/H$4) -> 0 | I33: =IF(I$4="","",-I16/I$4) -> 0 | J33: =IF(J$4="","",-J16/J$4) -> 0 | K33: =IF(K$4="","",-K16/K$4) -> 0 | L33: =IF(L$4="","",-L16/L$4) -> 0 | M33: =IF(M$4="","",-M16/M$4) | N33: =IF(N$4="","",-N16/N$4) | ... Q33: =IF(Q$4="","",-Q16/Q$4)
B34: Non-controling Interests | C34: =IF(BS!G29<=0,0,BS!G29/BS!G30) -> 0 | G34: =IF(G$4="","",-G14/G$4) -> 0 | H34: =IF(H$4="","",-H14/H$4) -> 0 | I34: =IF(I$4="","",-I14/I$4) -> 0 | J34: =IF(J$4="","",-J14/J$4) -> 0.00020301681 | K34: =IF(K$4="","",-K14/K$4) -> 0.00011901613 | L34: =IF(L$4="","",-L14/L$4) -> 0.0006877684 | M34: =IF(M$4="","",-M14/M$4) | N34: =IF(N$4="","",-N14/N$4) | ... Q34: =IF(Q$4="","",-Q14/Q$4)
B35: FCFE | C35: =ABS(C20/C$4) -> 0.10165824 | G35: =IF(G$4="","",ABS(G20/G$4)) -> 0.10141889 | H35: =IF(H$4="","",ABS(H20/H$4)) -> 0.12933889 | I35: =IF(I$4="","",ABS(I20/I$4)) -> 0.1169344 | J35: =IF(J$4="","",ABS(J20/J$4)) -> 0.15770615 | K35: =IF(K$4="","",ABS(K20/K$4)) -> 0.076998009 | L35: =IF(L$4="","",ABS(L20/L$4)) -> 0.0006877684 | M35: =IF(M$4="","",ABS(M20/M$4)) | N35: =IF(N$4="","",ABS(N20/N$4)) | ... Q35: =IF(Q$4="","",ABS(Q20/Q$4))
B37: % Indicators
B38: % EBT of Income Tax | C38: =MAX(G38:J38) -> 0.24301408 | E38: Use the highest past tax rate | G38: =IF(G$4="","",-G10/(G8+G9)) -> 0.1772149 | H38: =IF(H$4="","",-H10/(H8+H9)) -> 0.20408306 | I38: =IF(I$4="","",-I10/(I8+I9)) -> 0.19642837 | J38: =IF(J$4="","",-J10/(J8+J9)) -> 0.24301408 | K38: =IF(K$4="","",-K10/(K8+K9)) -> 0 | L38: =IF(L$4="","",-L10/(L8+L9)) -> 0 | M38: =IF(M$4="","",-M10/(M8+M9)) | N38: =IF(N$4="","",-N10/(N8+N9)) | ... Q38: =IF(Q$4="","",-Q10/(Q8+Q9))
B39: FCFE/Market Price | C39: =C20*$C$3/(Market_Price*Common_Shares) -> 0.13802875 | G39: =IF(G$4="","",G20*$C$3/(Market_Price*Common_Shares)) -> 0.16884284 | H39: =IF(H$4="","",H20*$C$3/(Market_Price*Common_Shares)) -> 0.16828439 | I39: =IF(I$4="","",I20*$C$3/(Market_Price*Common_Shares)) -> 0.14909572 | J39: =IF(J$4="","",J20*$C$3/(Market_Price*Common_Shares)) -> 0.15180422 | K39: =IF(K$4="","",K20*$C$3/(Market_Price*Common_Shares)) -> 0.093959591 | L39: =IF(L$4="","",L20*$C$3/(Market_Price*Common_Shares)) -> -0.0011848986 | M39: =IF(M$4="","",M20*$C$3/(Market_Price*Common_Shares)) | N39: =IF(N$4="","",N20*$C$3/(Market_Price*Common_Shares)) | ... Q39: =IF(Q$4="","",Q20*$C$3/(Market_Price*Common_Shares))
B41: YoY Growth Rates
B42: Sales | C42: =C4/G4-1 -> -0.18442635 | G42: =IF(H4="","",G4/H4-1) -> 0.27952593 | H42: =IF(I4="","",H4/I4-1) -> 0.02045025 | I42: =IF(J4="","",I4/J4-1) -> 0.32460888 | J42: =IF(K4="","",J4/K4-1) -> -0.21118785 | K42: =IF(L4="","",K4/L4-1) -> -0.29169117 | L42: =IF(M4="","",L4/M4-1) | M42: =IF(N4="","",M4/N4-1) | N42: =IF(O4="","",N4/O4-1) | ... Q42: =IF(R4="","",Q4/R4-1)
B45: Detailed Analysis | E45: Notes
B46: Operating Costs
B47: COGS | C47: =-C4*C55 -> -9031319.1 | G47: =Data!C33 -> -11151623 | H47: =Data!D33 -> -8747447 | I47: =Data!E33 -> -8503976 | J47: =Data!F33 -> -6229020 | K47: =Data!G33 -> -7910751 | L47: =Data!H33 -> -11826154 | M47: =Data!I33 | N47: =Data!J33 | ... Q47: =Data!M33
B48: Selling Expenses | C48: =-C4*C56 -> -1707788.6 | G48: =Data!C36 -> -2043459 | H48: =Data!D36 -> -1517989 | I48: =Data!E36 -> -1491293 | J48: =Data!F36 -> -1412494 | K48: =Data!G36 -> 0 | L48: =Data!H36 -> 0 | M48: =Data!I36 | N48: =Data!J36 | ... Q48: =Data!M36
B49: Variable Costs | C49: =C47+C48 -> -10739108 | G49: =IF(G$4="","",G47+G48) -> -13195082 | H49: =IF(H$4="","",H47+H48) -> -10265436 | I49: =IF(I$4="","",I47+I48) -> -9995269 | J49: =IF(J$4="","",J47+J48) -> -7641514 | K49: =IF(K$4="","",K47+K48) -> -7910751 | L49: =IF(L$4="","",L47+L48) -> -11826154 | M49: =IF(M$4="","",M47+M48) | N49: =IF(N$4="","",N47+N48) | ... Q49: =IF(Q$4="","",Q47+Q48)
B50: Other Opex (Fixed Overhead) | C50: =AVERAGE(G50:J50) -> -302359.25 | E50: Historical Average | G50: =Data!C37 -> -254107 | H50: =Data!D37 -> -349526 | I50: =Data!E37 -> -323818 | J50: =Data!F37 -> -281986 | K50: =Data!G37 -> -2118252 | L50: =Data!H37 -> -2416769 | M50: =Data!I37 | N50: =Data!J37 | ... Q50: =Data!M37
B51: - R&D | C51: =AVERAGE(G51:J51) -> 0 | E51: Historical Average | G51: =Data!C38 -> 0 | H51: =Data!D38 -> 0 | I51: =Data!E38 -> 0 | J51: =Data!F38 -> 0 | K51: =Data!G38 -> 0 | L51: =Data!H38 -> 0 | M51: =Data!I38 | N51: =Data!J38 | ... Q51: =Data!M38
B52: Fixed Costs | C52: =C50+C51 -> -302359.25 | G52: =IF(G4="","",G50+G51) -> -254107 | H52: =IF(H4="","",H50+H51) -> -349526 | I52: =IF(I4="","",I50+I51) -> -323818 | J52: =IF(J4="","",J50+J51) -> -281986 | K52: =IF(K4="","",K50+K51) -> -2118252 | L52: =IF(L4="","",L50+L51) -> -2416769 | M52: =IF(M4="","",M50+M51) | N52: =IF(N4="","",N50+N51) | ... Q52: =IF(Q4="","",Q50+Q51)
B54: % Sales of Operating Costs
B55: COGS | C55: =AVERAGE(G55:L55) -> 0.72253727 | E55: Historical Average | G55: =IF(G$4="","",ABS(G47/G$4)) -> 0.72762956 | H55: =IF(H$4="","",ABS(H47/H$4)) -> 0.7303023 | I55: =IF(I$4="","",ABS(I47/I$4)) -> 0.72449469 | J55: =IF(J$4="","",ABS(J47/J$4)) -> 0.70294374 | K55: =IF(K$4="","",ABS(K47/K$4)) -> 0.70419372 | L55: =IF(L$4="","",ABS(L47/L$4)) -> 0.74565961 | M55: =IF(M$4="","",ABS(M47/M$4)) | N55: =IF(N$4="","",ABS(N47/N$4)) | ... Q55: =IF(Q$4="","",ABS(Q47/Q$4))
B56: =B48 -> Selling Expenses | C56: =AVERAGE(G56:J56) -> 0.13662909 | E56: Historical Average | G56: =IF(G$4="","",ABS(G48/G$4)) -> 0.13333316 | H56: =IF(H$4="","",ABS(H48/H$4)) -> 0.12673307 | I56: =IF(I$4="","",ABS(I48/I$4)) -> 0.12705044 | J56: =IF(J$4="","",ABS(J48/J$4)) -> 0.15939968 | K56: =IF(K$4="","",ABS(K48/K$4)) -> 0 | L56: =IF(L$4="","",ABS(L48/L$4)) -> 0 | M56: =IF(M$4="","",ABS(M48/M$4)) | N56: =IF(N$4="","",ABS(N48/N$4)) | ... Q56: =IF(Q$4="","",ABS(Q48/Q$4))
B57: Variable Costs | C57: =ABS(C49/$C$4) -> 0.85916636 | G57: =IF(G$4="","",ABS(G49/G$4)) -> 0.86096272 | H57: =IF(H$4="","",ABS(H49/H$4)) -> 0.85703537 | I57: =IF(I$4="","",ABS(I49/I$4)) -> 0.85154513 | J57: =IF(J$4="","",ABS(J49/J$4)) -> 0.86234343 | K57: =IF(K$4="","",ABS(K49/K$4)) -> 0.70419372 | L57: =IF(L$4="","",ABS(L49/L$4)) -> 0.74565961 | M57: =IF(M$4="","",ABS(M49/M$4)) | N57: =IF(N$4="","",ABS(N49/N$4)) | ... Q57: =IF(Q$4="","",ABS(Q49/Q$4))
B58: =B50 -> Other Opex (Fixed Overhead) | C58: =ABS(C50/$C$4) -> 0.024189803 | G58: =IF(G$4="","",ABS(G50/G$4)) -> 0.016580166 | H58: =IF(H$4="","",ABS(H50/H$4)) -> 0.029181045 | I58: =IF(I$4="","",ABS(I50/I$4)) -> 0.027587616 | J58: =IF(J$4="","",ABS(J50/J$4)) -> 0.031822067 | K58: =IF(K$4="","",ABS(K50/K$4)) -> 0.18856108 | L58: =IF(L$4="","",ABS(L50/L$4)) -> 0.1523815 | M58: =IF(M$4="","",ABS(M50/M$4)) | N58: =IF(N$4="","",ABS(N50/N$4)) | ... Q58: =IF(Q$4="","",ABS(Q50/Q$4))
B59: =B51 -> - R&D | C59: =ABS(C51/$C$4) -> 0 | G59: =IF(G$4="","",ABS(G51/G$4)) -> 0 | H59: =IF(H$4="","",ABS(H51/H$4)) -> 0 | I59: =IF(I$4="","",ABS(I51/I$4)) -> 0 | J59: =IF(J$4="","",ABS(J51/J$4)) -> 0 | K59: =IF(K$4="","",ABS(K51/K$4)) -> 0 | L59: =IF(L$4="","",ABS(L51/L$4)) -> 0 | M59: =IF(M$4="","",ABS(M51/M$4)) | N59: =IF(N$4="","",ABS(N51/N$4)) | ... Q59: =IF(Q$4="","",ABS(Q51/Q$4))
B60: Fixed Costs | C60: =ABS(C52/$C$4) -> 0.024189803 | G60: =IF(G$4="","",ABS(G52/G$4)) -> 0.016580166 | H60: =IF(H$4="","",ABS(H52/H$4)) -> 0.029181045 | I60: =IF(I$4="","",ABS(I52/I$4)) -> 0.027587616 | J60: =IF(J$4="","",ABS(J52/J$4)) -> 0.031822067 | K60: =IF(K$4="","",ABS(K52/K$4)) -> 0.18856108 | L60: =IF(L$4="","",ABS(L52/L$4)) -> 0.1523815 | M60: =IF(M$4="","",ABS(M52/M$4)) | N60: =IF(N$4="","",ABS(N52/N$4)) | ... Q60: =IF(Q$4="","",ABS(Q52/Q$4))
B62: Interest
B63: Interest Expense | C63: =-BS!G27*BS!C40 -> -59596 | G63: =Data!C41 -> -59596 | H63: =Data!D41 -> -20763 | I63: =Data!E41 -> -23097 | J63: =Data!F41 -> -28849 | K63: =Data!G41 -> -63075 | L63: =Data!H41 -> -34253 | M63: =Data!I41 | N63: =Data!J41 | ... Q63: =Data!M41
B64: Interest Income | C64: =BS!$G$24*BS!C41 -> 28977 | G64: =Data!C42 -> 28977 | H64: =Data!D42 -> 33125 | I64: =Data!E42 -> 87344 | J64: =Data!F42 -> 63398 | K64: =Data!G42 -> 0 | L64: =Data!H42 -> 0 | M64: =Data!I42 | N64: =Data!J42 | ... Q64: =Data!M42
B65: Net Interest Income | C65: =C63+C64 -> -30619 | G65: =IF(G4="","",G63+G64) -> -30619 | H65: =IF(H4="","",H63+H64) -> 12362 | I65: =IF(I4="","",I63+I64) -> 64247 | J65: =IF(J4="","",J63+J64) -> 34549 | K65: =IF(K4="","",K63+K64) -> -63075 | L65: =IF(L4="","",L63+L64) -> -34253 | M65: =IF(M4="","",M63+M64) | N65: =IF(N4="","",N63+N64) | ... Q65: =IF(Q4="","",Q63+Q64)
B67: Balance Sheet Analysis | E67: Notes
B68: Balance Sheet
B69: Total Assets | C69: =BS!G23 -> 16854064 | G69: =IF(G$4="","",G73+G72) -> 16854064 | H69: =IF(H$4="","",H73+H72) -> 14687373 | I69: =IF(I$4="","",I73+I72) -> 15987114 | J69: =IF(J$4="","",J73+J72) -> 14270996 | K69: =IF(K$4="","",K73+K72) -> 0 | L69: =IF(L$4="","",L73+L72) -> 0 | M69: =IF(M$4="","",M73+M72) | N69: =IF(N$4="","",N73+N72) | ... Q69: =IF(Q$4="","",Q73+Q72)
B70: Incl. ST AR | C70: =BS!C4 -> 265773 | G70: =IF(G$4="","",Data!D64) -> 213823 | H70: =IF(H$4="","",Data!E64) -> 187711 | I70: =IF(I$4="","",Data!F64) -> 277338 | J70: =IF(J$4="","",Data!G64) -> 0 | K70: =IF(K$4="","",Data!H64) -> 0 | L70: =IF(L$4="","",Data!I64) -> 0 | M70: =IF(M$4="","",Data!J64) | N70: =IF(N$4="","",Data!K64) | ... Q70: =IF(Q$4="","",Data!N64)
B71: Incl. ST Inventory | C71: =BS!C7+BS!C8 -> 9672256 | G71: =IF(G$4="","",Data!D65) -> 8852611 | H71: =IF(H$4="","",Data!E65) -> 8769304 | I71: =IF(I$4="","",Data!F65) -> 7321614 | J71: =IF(J$4="","",Data!G65) -> 0 | K71: =IF(K$4="","",Data!H65) -> 0 | L71: =IF(L$4="","",Data!I65) -> 0 | M71: =IF(M$4="","",Data!J65) | N71: =IF(N$4="","",Data!K65) | ... Q71: =IF(Q$4="","",Data!N65)
B72: Total Liabilities | C72: =BS!G26 -> 3990166 | G72: =Data!C66 -> 3990166 | H72: =Data!D66 -> 2466431 | I72: =Data!E66 -> 3908586 | J72: =Data!F66 -> 2946772 | K72: =Data!G66 -> 0 | L72: =Data!H66 -> 0 | M72: =Data!I66 | N72: =Data!J66 | ... Q72: =Data!M66
B73: Total Equity | C73: =BS!G28 -> 12863898 | G73: =Data!C67 -> 12863898 | H73: =Data!D67 -> 12220942 | I73: =Data!E67 -> 12078528 | J73: =Data!F67 -> 11324224 | K73: =Data!G67 -> 0 | L73: =Data!H67 -> 0 | M73: =Data!I67 | N73: =Data!J67 | ... Q73: =Data!M67
B75: % Sales
B76: ST_AR | C76: =C70/C$4 -> 0.021262774 | G76: =IF(G$4="","",G70/G$4) -> 0.013951685 | H76: =IF(H$4="","",H70/H$4) -> 0.015671518 | I76: =IF(I$4="","",I70/I$4) -> 0.023627761 | J76: =IF(J$4="","",J70/J$4) -> 0 | K76: =IF(K$4="","",K70/K$4) -> 0 | L76: =IF(L$4="","",L70/L$4) -> 0 | M76: =IF(M$4="","",M70/M$4) | N76: =IF(N$4="","",N70/N$4) | ... Q76: =IF(Q$4="","",Q70/Q$4)
B77: ST_Inventory | C77: =C71/C$4 -> 0.77381448 | G77: =IF(G$4="","",G71/G$4) -> 0.57762188 | H77: =IF(H$4="","",H71/H$4) -> 0.73212708 | I77: =IF(I$4="","",I71/I$4) -> 0.62376358 | J77: =IF(J$4="","",J71/J$4) -> 0 | K77: =IF(K$4="","",K71/K$4) -> 0 | L77: =IF(L$4="","",L71/L$4) -> 0 | M77: =IF(M$4="","",M71/M$4) | N77: =IF(N$4="","",N71/N$4) | ... Q77: =IF(Q$4="","",Q71/Q$4)
B79: Leverage
B80: Pre-tax Profit/Interest Expense | C80: =-C4/C63 -> 209.73641 | G80: =IF(G4="","",-G4/G63) -> 257.16427 | H80: =IF(H4="","",-H4/H63) -> 576.88407 | I80: =IF(I4="","",-I4/I63) -> 508.196 | J80: =IF(J4="","",-J4/J63) -> 307.16264 | K80: =IF(K4="","",-K4/K63) -> 178.1018 | L80: =IF(L4="","",-L4/L63) -> 463.02484 | M80: =IF(M4="","",-M4/M63) | N80: =IF(N4="","",-N4/N63) | ... Q80: =IF(Q4="","",-Q4/Q63)
B81: Equity / Total Assets | C81: =C73/C69 -> 0.763252 | G81: =IF(G73="","",G73/G69) -> 0.763252 | H81: =IF(H73="","",H73/H69) -> 0.83207133 | I81: =IF(I73="","",I73/I69) -> 0.75551647 | J81: =IF(J73="","",J73/J69) -> 0.79351322 | K81: =IF(K73="","",K73/K69) -> #DIV/0! | L81: =IF(L73="","",L73/L69) -> #DIV/0! | M81: =IF(M73="","",M73/M69) | N81: =IF(N73="","",N73/N69) | ... Q81: =IF(Q73="","",Q73/Q69)
B83: ROE | G83: =IFERROR(IF(#REF!*G85*(1/G81)=G87,"","Error"),"") | H83: =IFERROR(IF(#REF!*H85*(1/H81)=H87,"","Error"),"") | I83: =IFERROR(IF(#REF!*I85*(1/I81)=I87,"","Error"),"") | J83: =IFERROR(IF(#REF!*J85*(1/J81)=J87,"","Error"),"") | K83: =IFERROR(IF(#REF!*K85*(1/K81)=K87,"","Error"),"") | L83: =IFERROR(IF(#REF!*L85*(1/L81)=L87,"","Error"),"") | M83: =IFERROR(IF(#REF!*M85*(1/M81)=M87,"","Error"),"") | N83: =IFERROR(IF(#REF!*N85*(1/N81)=N87,"","Error"),"") | ... Q83: =IFERROR(IF(#REF!*Q85*(1/Q81)=Q87,"","Error"),"")
B84: EBIT/Sales | C84: =C26 -> 0.11664384 | G84: =G26 -> 0.12245711 | H84: =H26 -> 0.11378358 | I84: =I26 -> 0.12086725 | J84: =J26 -> 0.1058345 | K84: =K26 -> 0.1072452 | L84: =L26 -> 0.10195889 | M84: =M26 | N84: =N26 | ... Q84: =Q26
B85: Sales/Total Assets | C85: =C4/C69 -> 0.7416283 | G85: =IF(G4="","",G4/G69) -> 0.90933332 | H85: =IF(H4="","",H4/H69) -> 0.81551983 | I85: =IF(I4="","",I4/I69) -> 0.734204 | J85: =IF(J4="","",J4/J69) -> 0.62093319 | K85: =IF(K4="","",K4/K69) -> #DIV/0! | L85: =IF(L4="","",L4/L69) -> #DIV/0! | M85: =IF(M4="","",M4/M69) | N85: =IF(N4="","",N4/N69) | ... Q85: =IF(Q4="","",Q4/Q69)
B86: Total Assets/Equity | C86: =C69/C73 -> 1.3101833 | G86: =IF(G$4="","",G69/G73) -> 1.3101833 | H86: =IF(H$4="","",H69/H73) -> 1.20182 | I86: =IF(I$4="","",I69/I73) -> 1.3235979 | J86: =IF(J$4="","",J69/J73) -> 1.2602184 | K86: =IF(K$4="","",K69/K73) -> #DIV/0! | L86: =IF(L$4="","",L69/L73) -> #DIV/0! | M86: =IF(M$4="","",M69/M73) | N86: =IF(N$4="","",N69/N73) | ... Q86: =IF(Q$4="","",Q69/Q73)
B87: EBIT ROE | C87: =C8/C73 -> 0.1133392 | G87: =IF(G$4="","",G8/G73) -> 0.14589458 | H87: =IF(H$4="","",H8/H73) -> 0.11152021 | I87: =IF(I$4="","",I8/I73) -> 0.11745769 | J87: =IF(J$4="","",J8/J73) -> 0.082816712 | K87: =IF(K$4="","",K8/K73) -> #DIV/0! | L87: =IF(L$4="","",L8/L73) -> #DIV/0! | M87: =IF(M$4="","",M8/M73) | N87: =IF(N$4="","",N8/N73) | ... Q87: =IF(Q$4="","",Q8/Q73)
B89: Dividend Analysis | E89: Notes
B90: Dividend
B91: Dividend per share | C91: =G91 -> 1.36 | G91: =Data!C52 -> 1.36 | H91: =Data!D52 -> 1.1 | I91: =Data!E52 -> 1.1 | J91: =Data!F52 -> 1 | K91: =Data!G52 -> 1 | L91: =Data!H52 -> 1.15 | M91: =Data!I52 | N91: =Data!J52 | ... Q91: =Data!M52
B92: Dividend | C92: =C91*Common_Shares/$C$3 -> 798466.68 | G92: =IF(G$4="","",G91*Common_Shares/$C$3) -> 798466.68 | H92: =IF(H$4="","",H91*Common_Shares/$C$3) -> 645818.64 | I92: =IF(I$4="","",I91*Common_Shares/$C$3) -> 645818.64 | J92: =IF(J$4="","",J91*Common_Shares/$C$3) -> 587107.85 | K92: =IF(K$4="","",K91*Common_Shares/$C$3) -> 587107.85 | L92: =IF(L$4="","",L91*Common_Shares/$C$3) -> 675174.03 | M92: =IF(M$4="","",M91*Common_Shares/$C$3) | N92: =IF(N$4="","",N91*Common_Shares/$C$3) | ... Q92: =IF(Q$4="","",Q91*Common_Shares/$C$3)
B93: Dividend/FCFE before WCInv | C93: =C91/(C15*$C$3/Common_Shares) -> 0.73898221 | G93: =IF(G$4="","",G91/(G15*$C$3/Common_Shares)) -> 0.61137166 | H93: =IF(H$4="","",H91/(H15*$C$3/Common_Shares)) -> 0.47520767 | I93: =IF(I$4="","",I91/(I15*$C$3/Common_Shares)) -> 0.5511075 | J93: =IF(J$4="","",J91/(J15*$C$3/Common_Shares)) -> 0.52597249 | K93: =IF(K$4="","",K91/(K15*$C$3/Common_Shares)) -> 0.51484611 | L93: =IF(L$4="","",L91/(L15*$C$3/Common_Shares)) -> 0.4295257 | M93: =IF(M$4="","",M91/(M15*$C$3/Common_Shares)) | N93: =IF(N$4="","",N91/(N15*$C$3/Common_Shares)) | ... Q93: =IF(Q$4="","",Q91/(Q15*$C$3/Common_Shares))

Sheet BS
B1: Most Recent Quarter | C1: 45382 | F1: =IF(MONTH(C1)=MONTH(Normalized_FCF!G1),"FY","Quarter")&" Report" -> FY Report
B2: Last Balance Sheet
B3: Operating Assets | C3: Book Figure | D3: Valued @ | F3: Non-Operating Assets | G3: Book Figure | H3: Valued @
B4: ST AR | C4: 265773 | D4: 0.6 | F4: Cash and cash equivalents | G4: 1998219 | H4: 0.9
B5: Operating ST Financial Assets | C5: 0 | D5: 0.6 | F5: Restricted cash | G5: 0 | H5: 0.8
B6: Prepayments and Contract Assets | C6: 366595 | D6: 0.1 | F6: ST FV Investments | G6: 0 | H6: 0.6
B7: Inventory | C7: 9672256 | D7: 0.5 | F7: ST non-FV Investments | G7: 0 | H7: 0.5
B8: Operating Properties held for sale | C8: 0 | D8: 0.6 | F8: Properties held for sale | G8: 0 | H8: 0.6
B9: ST DTA | C9: 29465 | D9: 0.9 | F9: Properties under development | G9: 0 | H9: 0.6
B10: Other ST Assets | C10: 0 | D10: 0.05 | F10: Non-Operating ST Assets | G10: =SUM(G4:G9) -> 1998219 | H10: =G4*H4+G5*H5+G6*H6+G7*H7+G8*H8+G9*H9 -> 1798397.1
B11: Operating ST Assets | C11: =SUM(C4:C10) -> 10334089 | D11: =C4*D4+C5*D5+C6*D6+C7*D7+C8*D8+C9*D9+C10*D10 -> 5058769.8 | F11: LT Depositis | G11: 0 | H11: 0.8
B12: LT AR | C12: 103050 | D12: 0.4 | F12: LT FV Securities | G12: 0 | H12: 0.6
B13: Operating LT Financial Assets | C13: 0 | D13: 0.5 | F13: LT non-FV Securities | G13: 0 | H13: 0.5
B14: Operating Properties under development | C14: 0 | D14: 0.6 | F14: Investments in JV or associate | G14: 0 | H14: 0.1
B15: PP&E & Right of Use Assets | C15: 2522337 | D15: 0.1 | F15: Investment property | G15: 925726 | H15: 0.2
B16: Biological assets | C16: 0 | D16: 0.05 | F16: Properties under development | G16: 0 | H16: 0.1
B17: Intangible assets | C17: 538321 | D17: 0.05 | F17: Non-Operating LT Assets | G17: =SUM(G11:G16) -> 925726 | H17: =G11*H11+G12*H12+G13*H13+G14*H14+G15*H15+G16*H16 -> 185145.2
B18: LT DTA | C18: 154648 | D18: 0.9
B19: Other assets & Goodwill | C19: 277674 | D19: 0 | F19: Operating Assets | G19: =C11+C20 -> 13930119 | H19: =D11+D20 -> 5518322.8
B20: Operating LT Assets | C20: =SUM(C12:C19) -> 3596030 | D20: =C12*D12+C13*D13+C14*D14+C15*D15+C16*D16+C17*D17+C18*D18+C19*D19 -> 459552.95 | F20: Non-operating Assets | G20: =G10+G17 -> 2923945 | H20: =H10+H17 -> 1983542.3
B22: Liabilities | G22: Book | H22: Estimate
B23: ST Borrowing | C23: 1427805 | F23: Total Assets | G23: =G19+G20 -> 16854064 | H23: =H19+H20 -> 7501865
B24: ST Lease liabilities | C24: 287697 | F24: incl. Cash | G24: =G4+G5+G11 -> 1998219
B25: ST SH Loan | C25: 0 | F25: incl. Fixed Assets | G25: =SUM(C14:C17)+SUM(G15:G16) -> 3986384
B26: ST Financial Liabilities | C26: 0 | F26: Total Liabilities | G26: =Data!C24 -> 3990166
B27: ST Debt | C27: =SUM(C23:C26) -> 1715502 | F27: incl. Interest-bearing Debt | G27: =C27+C34 -> 2034922
B28: Other ST liabilities | C28: =C29-C27 -> 1801307 | F28: Total Equity | G28: 12863898
B29: Current Liabilities | C29: 3516809 | F29: Incl. Non-common Interest | G29: -26962
B30: LT Borrowing | C30: 0 | F30: Incl. Common Equity | G30: =G28-G29 -> 12890860
B31: LT Lease liabilities | C31: 319420
B32: LT SH Loan | C32: 0
B33: LT Financial Liabilities | C33: 0
B34: LT Debt | C34: =SUM(C30:C33) -> 319420
B35: Other LT liabilities | C35: =C36-C34 -> 153937
B36: Noncurrent Liabilities | C36: =G26-C29 -> 473357
B38: Balance Sheet Analysis
B39: Leverage % | C39: Normalized | D39: Latest | F39: Notes
B40: Interest Rate/Debt | C40: =D40 -> 0.029286626 | D40: =IF(Normalized_FCF!G4="","",ABS(Normalized_FCF!G63/BS!$G$27)) -> 0.029286626 | F40: Use Last year's rate
B41: Interest Yield/Cash | C41: 0.014501414 | D41: =IF(Normalized_FCF!G4="","",Normalized_FCF!G64/BS!$G$24) -> 0.014501414 | F41: Reference the market rate
B42: D&A/Fixed Assets | C42: =D42 -> 0.11625172 | D42: =Normalized_FCF!G12/BS!$G$25 -> 0.11625172 | F42: Same as Last year's D&A
B43: Fixed Assets/Total Assets | D43: =G25/G23 -> 0.23652361
B44: Debt/EBIT | D44: =BS!G27/Normalized_FCF!C8 -> 1.3957095
B46: Profibility % | C46: Normalized | D46: Latest
B47: Operating Asset Yield | C47: =Normalized_FCF!C18/G19 -> 0.077565391 | D47: =Normalized_FCF!G18/G19 -> 0.09375548
B48: Non-Operating Asset Yield | C48: =Normalized_FCF!C19/G20 -> 0.065041237 | D48: =Normalized_FCF!G19/G20 -> 0.084925332
B50: Realizable Value Analysis

Sheet Valuation_Model
B2: No-Growth DCF Valuation Analysis | H2: Notes
B3: No-Growth DCF Valuation | C3: =Normalized_FCF!C3 -> 1000 | E3: Special Assumption
B4: Adjusted FCFE | C4: =Normalized_FCF!C20 -> 1270672.1 | D4: =Reporting_currency -> HKD | E4: Terminal Growth Rate: | F4: 0
B5: /Equity Cost of Capital | C5: =Thesis!C37 -> 0.1 | E5: - Expects no significant growth at terminal years
B6: = Enterprise Value | C6: =(C4*(1+Terminal_Growth))/(Equity_Cost-Terminal_Growth) -> 12706721 | E6: - Avoids overvaluation.
B7: - Interest Bearing Debt | C7: =BS!G27 -> 2034922
B8: = Equity Value | C8: =C6-C7 -> 10671799
B9: Equity Value per share | C9: =(C8*Normalized_FCF!C3)/Common_Shares -> 18.176898
B11: Implied Growth Sensitivity Test
B12: FCFE Projection
B13: High Growth Period (HGP) | C13: =Scenarios!C25 -> -0.038
B14: High Growth Rate (HGR) | C14: =Scenarios!C24 -> 10
B15: Value Per Share | C15: =(F49-C7)/Common_Shares*C3 -> 15.699957 | D15: =IF(ROUND(C15,1)=ROUND(Scenarios!C29,1),"equals Market Price","a Current Projection") -> equals Market Price
B17: Year | C17: FCFE | D17: Growth Rates | E17: Discount Factor | F17: PV of FCFE
B18: 1 | C18: =C4*(1+D18) -> 1222386.6 | D18: =IF($C$14<B18,0,Valuation_Model!$C$13) -> -0.038 | E18: =IF($C$14<B18,0,1/(1+Equity_Cost)^B18) -> 0.90909091 | F18: =C18*E18 -> 1111260.5
B19: 2 | C19: =IF(ROW()-ROW($C$18)<$C$14, $C$18*(1+D19)^(ROW()-ROW($C$18)), 0) -> 1175935.9 | D19: =IF($C$14<B19,0,Valuation_Model!$C$13) -> -0.038 | E19: =IF($C$14<B19,0,1/(1+Equity_Cost)^B19) -> 0.82644628 | F19: =C19*E19 -> 971847.85
B20: 3 | C20: =IF(ROW()-ROW($C$18)<$C$14, $C$18*(1+D20)^(ROW()-ROW($C$18)), 0) -> 1131250.3 | D20: =IF($C$14<B20,0,Valuation_Model!$C$13) -> -0.038 | E20: =IF($C$14<B20,0,1/(1+Equity_Cost)^B20) -> 0.7513148 | F20: =C20*E20 -> 849925.12
B21: 4 | C21: =IF(ROW()-ROW($C$18)<$C$14, $C$18*(1+D21)^(ROW()-ROW($C$18)), 0) -> 1088262.8 | D21: =IF($C$14<B21,0,Valuation_Model!$C$13) -> -0.038 | E21: =IF($C$14<B21,0,1/(1+Equity_Cost)^B21) -> 0.68301346 | F21: =C21*E21 -> 743298.15
B22: 5 | C22: =IF(ROW()-ROW($C$18)<$C$14, $C$18*(1+D22)^(ROW()-ROW($C$18)), 0) -> 1046908.8 | D22: =IF($C$14<B22,0,Valuation_Model!$C$13) -> -0.038 | E22: =IF($C$14<B22,0,1/(1+Equity_Cost)^B22) -> 0.62092132 | F22: =C22*E22 -> 650048.02
B23: 6 | C23: =IF(ROW()-ROW($C$18)<$C$14, $C$18*(1+D23)^(ROW()-ROW($C$18)), 0) -> 1007126.3 | D23: =IF($C$14<B23,0,Valuation_Model!$C$13) -> -0.038 | E23: =IF($C$14<B23,0,1/(1+Equity_Cost)^B23) -> 0.56447393 | F23: =C23*E23 -> 568496.54
B24: 7 | C24: =IF(ROW()-ROW($C$18)<$C$14, $C$18*(1+D24)^(ROW()-ROW($C$18)), 0) -> 968855.5 | D24: =IF($C$14<B24,0,Valuation_Model!$C$13) -> -0.038 | E24: =IF($C$14<B24,0,1/(1+Equity_Cost)^B24) -> 0.51315812 | F24: =C24*E24 -> 497176.06
B25: 8 | C25: =IF(ROW()-ROW($C$18)<$C$14, $C$18*(1+D25)^(ROW()-ROW($C$18)), 0) -> 932038.99 | D25: =IF($C$14<B25,0,Valuation_Model!$C$13) -> -0.038 | E25: =IF($C$14<B25,0,1/(1+Equity_Cost)^B25) -> 0.46650738 | F25: =C25*E25 -> 434803.07
B26: 9 | C26: =IF(ROW()-ROW($C$18)<$C$14, $C$18*(1+D26)^(ROW()-ROW($C$18)), 0) -> 896621.51 | D26: =IF($C$14<B26,0,Valuation_Model!$C$13) -> -0.038 | E26: =IF($C$14<B26,0,1/(1+Equity_Cost)^B26) -> 0.42409762 | F26: =C26*E26 -> 380255.05
B27: 10 | C27: =IF(ROW()-ROW($C$18)<$C$14, $C$18*(1+D27)^(ROW()-ROW($C$18)), 0) -> 862549.89 | D27: =IF($C$14<B27,0,Valuation_Model!$C$13) -> -0.038 | E27: =IF($C$14<B27,0,1/(1+Equity_Cost)^B27) -> 0.38554329 | F27: =C27*E27 -> 332550.32
B28: 11 | C28: =IF(ROW()-ROW($C$18)<$C$14, $C$18*(1+D28)^(ROW()-ROW($C$18)), 0) -> 0 | D28: =IF($C$14<B28,0,Valuation_Model!$C$13) -> 0 | E28: =IF($C$14<B28,0,1/(1+Equity_Cost)^B28) -> 0 | F28: =C28*E28 -> 0
B29: 12 | C29: =IF(ROW()-ROW($C$18)<$C$14, $C$18*(1+D29)^(ROW()-ROW($C$18)), 0) -> 0 | D29: =IF($C$14<B29,0,Valuation_Model!$C$13) -> 0 | E29: =IF($C$14<B29,0,1/(1+Equity_Cost)^B29) -> 0 | F29: =C29*E29 -> 0
B30: 13 | C30: =IF(ROW()-ROW($C$18)<$C$14, $C$18*(1+D30)^(ROW()-ROW($C$18)), 0) -> 0 | D30: =IF($C$14<B30,0,Valuation_Model!$C$13) -> 0 | E30: =IF($C$14<B30,0,1/(1+Equity_Cost)^B30) -> 0 | F30: =C30*E30 -> 0
... B47: 30 | C47: =IF(ROW()-ROW($C$18)<$C$14, $C$18*(1+D47)^(ROW()-ROW($C$18)), 0) -> 0 | D47: =IF($C$14<B47,0,Valuation_Model!$C$13) -> 0 | E47: =IF($C$14<B47,0,1/(1+Equity_Cost)^B47) -> 0 | F47: =C47*E47 -> 0
B48: Terminal Year | C48: =C$18*(1+Terminal_Growth)^$C$14/Equity_Cost -> 12223866 | D48: =Terminal_Growth -> 0 | E48: =1/(1+Equity_Cost)^C14 -> 0.38554329 | F48: =C48*E48 -> 4712829.5
E49: Total PV | F49: =SUM(F18:F48) -> 11252490
B51: Sensitivity Analysis (Enterprise Value)
B52: =F49 -> 11252490 | C52: =C74 -> -0.15 | D52: =C73 -> 0 | E52: =C72 -> 0.03 | F52: =C71 -> 0.03
B53: 5 | C53: 9836413.4 | D53: 12706721 | E53: 13365143 | F53: 13365143
B54: 10 | C54: 8156502.5 | D54: 12706721 | E54: 14055352 | F54: 14055352
B55: 15 | C55: 6815544.7 | D55: 12706721 | E55: 14856838 | F55: 14856838
B56: 20 | C56: 5900851.7 | D56: 12706721 | E56: 15622934 | F56: 15622934
B57: 25 | C57: 5310290.3 | D57: 12706721 | E57: 16291844 | F57: 16291844
B58: 30 | C58: 4937369.2 | D58: 12706721 | E58: 16846271 | F58: 16846271
B60: Sensitivity Analysis (Equity Value per share)
C61: =C52 -> -0.15 | D61: =D52 -> 0 | E61: =E52 -> 0.03 | F61: =F52 -> 0.03
B62: 0 | C62: =D62 -> 18.176898 | D62: =E62 -> 18.176898 | E62: =C9 -> 18.176898 | F62: =E62 -> 18.176898
B63: =B53 -> 5 | C63: =(C53-$C$7)/Common_Shares*$C$3 -> 13.288004 | D63: =(D53-$C$7)/Common_Shares*$C$3 -> 18.176898 | E63: =(E53-$C$7)/Common_Shares*$C$3 -> 19.298363 | F63: =(F53-$C$7)/Common_Shares*$C$3 -> 19.298363
B64: =B54 -> 10 | C64: =(C54-$C$7)/Common_Shares*$C$3 -> 10.426671 | D64: =(D54-$C$7)/Common_Shares*$C$3 -> 18.176898 | E64: =(E54-$C$7)/Common_Shares*$C$3 -> 20.473972 | F64: =(F54-$C$7)/Common_Shares*$C$3 -> 20.473972
B65: =B55 -> 15 | C65: =(C55-$C$7)/Common_Shares*$C$3 -> 8.1426652 | D65: =(D55-$C$7)/Common_Shares*$C$3 -> 18.176898 | E65: =(E55-$C$7)/Common_Shares*$C$3 -> 21.839116 | F65: =(F55-$C$7)/Common_Shares*$C$3 -> 21.839116
B66: =B56 -> 20 | C66: =(C56-$C$7)/Common_Shares*$C$3 -> 6.5847011 | D66: =(D56-$C$7)/Common_Shares*$C$3 -> 18.176898 | E66: =(E56-$C$7)/Common_Shares*$C$3 -> 23.14398 | F66: =(F56-$C$7)/Common_Shares*$C$3 -> 23.14398
B67: =B57 -> 25 | C67: =(C57-$C$7)/Common_Shares*$C$3 -> 5.5788188 | D67: =(D57-$C$7)/Common_Shares*$C$3 -> 18.176898 | E67: =(E57-$C$7)/Common_Shares*$C$3 -> 24.28331 | F67: =(F57-$C$7)/Common_Shares*$C$3 -> 24.28331
B68: =B58 -> 30 | C68: =(C58-$C$7)/Common_Shares*$C$3 -> 4.9436354 | D68: =(D58-$C$7)/Common_Shares*$C$3 -> 18.176898 | E68: =(E58-$C$7)/Common_Shares*$C$3 -> 25.227646 | F68: =(F58-$C$7)/Common_Shares*$C$3 -> 25.227646
B70: Scenarios | C70: HGR | D70: HGP | E70: Value per share | F70: Probabilities
B71: Optimistic | C71: =Scenarios!C51 -> 0.03 | D71: =Scenarios!C50 -> 10 | E71: =INDEX(C$62:F$68, MATCH(D71, B$62:B$68, 0), MATCH(C71, C$61:F$61, 0)) -> 20.473972 | H71: MATCH(1%, C65:E65, 0) finds the column number for HGR = 1%.
B72: Base | C72: =Scenarios!C39 -> 0.03 | D72: =Scenarios!C38 -> 5 | E72: =INDEX(C$62:F$68, MATCH(D72, B$62:B$68, 0), MATCH(C72, C$61:F$61, 0)) -> 19.298363 | H72: MATCH(5, B66:B69, 0) finds the row number for HGP = 5.
B73: No Growth | C73: =Scenarios!C45 -> 0 | D73: =Scenarios!C44 -> 5 | E73: =INDEX(C$62:F$68, MATCH(D73, B$62:B$68, 0), MATCH(C73, C$61:F$61, 0)) -> 18.176898
B74: Pessimistic | C74: =Scenarios!C57 -> -0.15 | D74: =Scenarios!C56 -> 5 | E74: =INDEX(C$62:F$68, MATCH(D74, B$62:B$68, 0), MATCH(C74, C$61:F$61, 0)) -> 13.288004 | H74: INDEX(C66:E69, ...) retrieves the value from the specified range.
B75: =IF(VLOOKUP("No Growth",B71:E74,4,FALSE)>VLOOKUP("Base",B71:E74,4,FALSE),"Note: the No Growth value being higher than the Base or Optimistic values is unusual.","OK") -> OK

Sheet Scenarios
B2: Current Situation
B3: Selection
B4: Past Years Selected | C4: 4 | E4: Tie the business story into the three levers of value: FCFE, growth and risk.
B6: FCFE | C6: =Valuation_Model!C3 -> 1000 | E6: Prompt for Scenario Analysis
B7: Lastest | C7: =Normalized_FCF!G20 -> 1554342 | E7: Given 六福珠宝’s (0590.HK) normalized FCFE of HKD 1,270,672,000, please analyze its valuation assumptions under three scenarios (Base, Pessimistic, Optimistic) using a two-stage model, a growth stage and a terminal stage. Define the growth period, growth rates and probabilities for each scenario. Explain the rationale behind the probabilities. Summarize the business drivers and scenario narratives to align with the model’s inputs. For context only, the terminal value assumes 0% growth to prevent overvaluation. The finalized scenarios will be incorporated directly into the valuation framework.”
B8: Normalized | C8: =Normalized_FCF!C20 -> 1270672.1
B10: Growth Rate
B11: Sales Growth Rates | C11: =AVERAGE(Normalized_FCF!G42:INDEX(Normalized_FCF!G42:Q42, $C$4)) -> 0.1033493
B12: Op. FCFE Before WCInv
B13: Non-Operating Income
B15: Margin
B16: Contribution Margin
B17: Op. FCFE Before WCInv
B19: Objective Scenarios
B20: No Growth Scenario | E20: Business Story
B21: Value per share | C21: =Valuation_Model!E73 -> 18.176898 | D21: =Reporting_currency -> HKD | E21: Unbiased Scenario where the company FCFE has no growth and no risk.
B23: Market Scenario
B24: High Growth Period (HGP) | C24: 10
B25: High Growth Rate (HGR) | C25: -0.038
B26: Value per share | C26: =Valuation_Model!C15 -> 15.699957
B28: Reference Price Points
B29: Market Price | C29: =Market_Price -> 15.68
B30: 52 week High | C30: 13
B31: 52 week Low
B33: Subjective Scenarios
B34: Assumption
B35: High Growth Period (HGP) | C35: 5 | E35: For both Base and Pessimistic case, I would use 10 yrs to do forecast
B37: Base Case | E37: Business Story
B38: High Growth Period (HGP) | C38: =C35 -> 5
B39: High Growth Rate (HGR) | C39: 0.03
B40: Value per share | C40: =Valuation_Model!E72 -> 19.298363
B41: Probabilities | C41: 0.55
B43: Pessimistic Case | E43: Business Story
B44: High Growth Period (HGP) | C44: =C35 -> 5
B45: High Growth Rate (HGR) | C45: 0
B46: Value per share | C46: =Valuation_Model!E73 -> 18.176898 | D46: =Reporting_currency -> HKD
B47: Probabilities | C47: 0.15
B49: Optimistic Case | E49: Business Story
B50: High Growth Period (HGP) | C50: 10
B51: High Growth Rate (HGR) | C51: 0.03
B52: Value per share | C52: =Valuation_Model!E71 -> 20.473972 | D52: =Reporting_currency -> HKD
B53: Probabilities | C53: 0.2
B55: Devil's advocate Case | E55: Business Story
B56: High Growth Period (HGP) | C56: =C35 -> 5 | E56: There is always a chance the some devil's advocate is right and I'm wrong, so the probabilities should reflect this depending on how illogical this implied drivers are.
B57: High Growth Rate (HGR) | C57: -0.15
B58: Value per share | C58: =Valuation_Model!E74 -> 13.288004 | D58: =Reporting_currency -> HKD
B59: Probabilities | C59: =1-C41-C47-C53 -> 0.1
B61: Expected Value = | C61: =C41*C40+C59*C58+C46*C47+C53*C52 -> 18.764229 | D61: =Reporting_currency -> HKD
B63: Margin of Safety (MOS)
B64: Inputs | E64: Special Assumption
B65: Target Return | C65: =Thesis!C68 -> 0.2 | E65: the Equity Value will be conservatively realized | F65: =Thesis!C67 -> 3
B66: Annual Dividend per share | C66: =Normalized_FCF!C91 -> 1.36 | D66: =Reporting_currency -> HKD | E66: over a holding period of
B68: Output
B69: PV(Dividends) | C69: =PV(C65, F65, -C66, 0) -> 2.8648148
B70: PV(Equity Value) | C70: =C61/(1+C65)^F65 -> 10.858929
B71: Buy Below | C71: =C69+C70 -> 13.723744 | D71: =Reporting_currency -> HKD | E71: at a MOS of | F71: =(C71/C61-1) -> -0.26862204 | I71: Buy at < PV(dividends, 3yrs, r) + PV(Equity value, 3yrs, r)
B75: CAGR Calculator | C75: Initial Value (PV) | D75: Final Value (FV) | E75: # of Years
B76: Inputs = | C76: =Normalized_FCF!L8 -> 1617067 | D76: =Normalized_FCF!G8 -> 1876773 | E76: 6
B77: CAGR = | C77: =(D76/C76)^(1/E76)-1 -> 0.025133963
