Workbook
Name Common_Shares: Thesis!$C$7
Name Equity_Cost: Valuation_Model!$C$5
Name Exchange_Rate: Thesis!$C$17
Name Market_currency: Thesis!$D$6
Name Market_Price: Thesis!$C$6
Name Reporting_currency: Thesis!$C$16
Name Terminal_Growth: Valuation_Model!$F$4

Sheet Thesis
B1: Model last updated: | C1: 45730 | E1: Status in Portfolio: | F1: Held
A2: Executive Summary
B4: =D5&" Stock Information" -> 0083.HK Stock Information
B5: Company Name | C5: SINO LAND | D5: 0083.HK
B6: Market Price: | C6: 7.9 | D6: HKD
B7: Number of Shares: | C7: 8171879936
B8: Report Interval: | C8: 6
B9: Update Required After: | C9: =EOMONTH(EDATE(BS!C1,C8+2),0) -> 45716
B10: ="Capitalization ("&Market_currency&"):" -> Capitalization (HKD): | C10: =Thesis!C6*Thesis!C7/1000000 -> 64557.851
B12: Guidance Note: This valuation method estimates the equity value of a company through a five-step process. Each step is designed to systematically derive cash flows available to equity holders, discount them appropriately, and adjust for debt and non-operating assets.
B14: Valuation Overview
B15: Investment Type: | C15: =IF(Scenarios!C69="Y",Scenarios!B69,"")&IF(Scenarios!C70="Y",Scenarios!B70,"")&IF(Scenarios!C71="Y",Scenarios!B71,"")&" "&IF(Scenarios!C72="Y",Scenarios!B72,"") -> Negative Growth Asset Play
B16: Reporting Currency: | C16: HKD
B17: Exchange Rate: | C17: 1 | D17: =IF(C16=D6,D6,C16&"/"&D6) -> HKD
B18: Comp_Sector: | C18: C0003
B19: Target Annual Return: | C19: 0.2
B20: ="Target Buy Price ("&Market_currency&"):" -> Target Buy Price (HKD): | C20: =C127 -> 6.4501768 | D20: assuming a holding period of | E20: 3
B21: Market Annual Return: | C21: =Scenarios!C87 -> 0.11614149
A23: Step 1: Calculate FCFE
B25: FCFE represents the cash available to equity holders after accounting for operating expenses, reinvestments, taxes, and interest obligations.
B26: FCFE = (Normalized Operating EBIT + Depreciation & Amortization – Capital Expenditures) + Stable Non-Operating EBIT + Net Interest Income – Taxes – NCI’s Share of Profits – Working Capital Investment
B28: Key Components | C28: =Data!C3 -> 1000000
B29: • Normalized Operating EBIT: Earnings before interest and taxes from core business operations, adjusted to remove one-time or irregular items for a sustainable earnings base.
B30: Normalized Operating EBIT = | C30: =Normalized_FCF!C8 -> 2591.8203 | D30: =Reporting_currency -> HKD
B32: • Depreciation & Amortization (D&A): Non-cash expenses added back to reflect cash generated from operations. • Capital Expenditures (Capex): Cash outflows required to maintain or expand operational assets
B33: D&A = | C33: =Normalized_FCF!C9 -> 160 | D33: =Reporting_currency -> HKD
B34: Capex = | C34: =Normalized_FCF!C10 -> -160 | D34: =Reporting_currency -> HKD
B36: • Stable Non-Operating EBIT: Consistent earnings from non-core assets, such as fixed-income investments, dividend-paying stocks, or rental properties.
B37: Stable Non-Operating EBIT = | C37: =Normalized_FCF!C11 -> 639 | D37: =Reporting_currency -> HKD
B39: • Net Interest Income: Interest income minus interest expense
B40: Operating Interest Income = | C40: =Normalized_FCF!C48 -> 185.19539 | D40: =Reporting_currency -> HKD
B41: Interest Expense = | C41: =Normalized_FCF!C47 -> -43 | D41: =Reporting_currency -> HKD
B42: Net Interest Income = | C42: =Normalized_FCF!C12 -> 142.19539 | D42: =Reporting_currency -> HKD
B44: • NCI’s Share of Profits: NCI represents the portion of a subsidiary’s equity not owned by the parent company.
B45: Est. NCI’s Share of Profits = | C45: =Normalized_FCF!C15 -> -22.869708 | D45: =Reporting_currency -> HKD
B47: • Taxes: Tax = (Normalized Operating EBIT + Stable Non-Operating EBIT + Interest Income – Interest Expense) × Tax Rate
B48: Taxes = | C48: =Normalized_FCF!C14 -> -809.52376 | D48: =Reporting_currency -> HKD
B50: • Working Capital Investment (WCInv): WCInv is only included if it materially distorts FCFE.
B51: WCInv = | C51: =Normalized_FCF!C17 -> 0 | D51: =Reporting_currency -> HKD
B53: Note on Net Borrowing: In theory, principal repayments are accounted for through Net Borrowing. However, this model aims to avoid explicitly forecasting debt issuance or repayments. Instead, principal repayments are reflected in the Equity Value adjustment through interest-bearing debt.
B54: Purpose: This step ensures a comprehensive measure of cash flow by incorporating both operating and stable non-operating sources while accounting for taxes and reinvestment needs.
B56: Latest FCFE = | C56: =Normalized_FCF!G19 -> 2807.9686 | D56: =Reporting_currency -> HKD
B57: Normalized FCFE = | C57: =Normalized_FCF!C19 -> 2540.6222 | D57: =Reporting_currency -> HKD
B58: FCFE/Market Cap = | C58: =Normalized_FCF!C121 -> 0.039354194
B59: Dividend/Market Cap = | C59: =Normalized_FCF!C93 -> 0.073417722
A61: Step 2: Calculate Stable Income Value (SIV) Using FCFE
B63: The Stable Income Value (SIV) represents the present value of FCFE, assuming it grows at a constant rate indefinitely. This is calculated using the Gordon Growth Model:
B64: Stable Income Value = Normalized FCFE / (Cost of Equity – Terminal Growth Rate)
B66: Key Components
B67: Base Cost of Equity | C67: 0.08
B68: Business Model Risk Premium | C68: =IF(D68="Y",1%,0) -> 0.01 | D68: Y
B69: Management Risk Premium | C69: =IF(D69="Y",1%,0) -> 0 | D69: N
B70: Cost of Equity = | C70: =SUM(C67:C69) -> 0.09
B72: Note on Cost of Equity: Cost of Equity reflects the company’s risk profile, while target annual return is the investor’s hurdle rate.
B73: Note on Terminal Growth Rate: Setting g=0 can be a conservative assumption to avoid overestimating the stock’s value, especially if future growth is uncertain or unreliable.
B75: Terminal Growth Rate (g) = | C75: 0
B76: No Growth SIV Per Share = | C76: =Valuation_Model!C6*C28*Exchange_Rate/Common_Shares -> 3.4544237 | D76: =Market_currency -> HKD
A78: Step 3: Calculate Equity Value
B80: The Equity Value adjusts the stable income value for debt and incorporates non-operating resources available to equity holders. The formula is:
B81: Equity Value = Stable Income Value – Total Interest-Bearing Debt + Non-Operating Cash + Other Non-Operating Assets
B83: Key Components
B84: Note on debt: The total interest-bearing debt captures the principal repayments. Ideally, this amount should be discounted based on the repayment schedule. However, for simplicity and conservatism, this model uses the book value of the total interest-bearing debt.
B85: Total Interest-Bearing Debt = | C85: =Valuation_Model!C7 -> 3093 | D85: =Reporting_currency -> HKD
B86: Total Interest-Bearing Debt per share = | C86: =C85*C28*Exchange_Rate/Common_Shares -> 0.37849308 | D86: =Market_currency -> HKD
B88: • Non-Operating Cash: Excess cash not required for operations
B89: Total Cash = | C89: =BS!C66 -> 47679 | D89: =Reporting_currency -> HKD
B90: Est. Non-Operating Cash = | C90: =Valuation_Model!C8 -> 41505.82 | D90: =Reporting_currency -> HKD
B91: Est. Non-Operating Cash per share = | C91: =C90*C28*Exchange_Rate/Common_Shares -> 5.079103 | D91: =Market_currency -> HKD
B93: • Other Non-Operating Assets: Assets not contributing to FCFE (e.g., non-income-generating investments or properties)
B94: Other Non-Operating Assets = | C94: =Valuation_Model!C9 -> 7814.4 | D94: =Reporting_currency -> HKD
B95: Other Non-Operating Assets per share = | C95: =C94*C28*Exchange_Rate/Common_Shares -> 0.95625487 | D95: =Market_currency -> HKD
B97: Purpose: This step ensures the equity value reflects all resources available to shareholders by deducting debt and adding excess cash and non-operating assets, avoiding double-counting of income-generating assets.
B99: No Growth Equity Value per share = | C99: =Valuation_Model!C12 -> 9.1112885 | D99: =Market_currency -> HKD
A101: Step 4: Scenario Analysis
B103: Based on fundamental research, the following scenarios have been developed, considering driving factors of high growth periods (HGP) and high growth rates (HGR), along with their associated probabilities.
B105: Scenarios | C105: HGR | D105: HGP | E105: EV per share | F105: Probabilities
B106: =Valuation_Model!B74 -> Snowball Scenario | C106: =Valuation_Model!C74 -> 0.05 | D106: =Valuation_Model!D74 -> 15 | E106: =ROUND(Valuation_Model!E74,2)&" "&Market_currency -> 10.16 HKD | F106: =Valuation_Model!F74 -> 0.05
B107: =Valuation_Model!B75 -> Optimistic | C107: =Valuation_Model!C75 -> 0.02 | D107: =Valuation_Model!D75 -> 10 | E107: =ROUND(Valuation_Model!E75,2)&" "&Market_currency -> 9.34 HKD | F107: =Valuation_Model!F75 -> 0.225
B108: =Valuation_Model!B76 -> Base | C108: =Valuation_Model!C76 -> 0 | D108: =Valuation_Model!D76 -> 10 | E108: =ROUND(Valuation_Model!E76,2)&" "&Market_currency -> 9.11 HKD | F108: =Valuation_Model!F76 -> 0.495
B109: =Valuation_Model!B77 -> Pessimistic | C109: =Valuation_Model!C77 -> -0.05 | D109: =Valuation_Model!D77 -> 10 | E109: =ROUND(Valuation_Model!E77,2)&" "&Market_currency -> 8.62 HKD | F109: =Valuation_Model!F77 -> 0.18
B110: =Valuation_Model!B78 -> Devil's advocate | C110: =Valuation_Model!C78 -> -0.2 | D110: =Valuation_Model!D78 -> 15 | E110: =ROUND(Valuation_Model!E78,2)&" "&Market_currency -> 7.26 HKD | F110: =Valuation_Model!F78 -> 0.05
B112: Expected Equity Value = | C112: =Scenarios!C60 -> 9.0347055 | D112: =Market_currency -> HKD
B114: Note that this model prioritizes fundamental analysis when combined with supplementary market signal analysis. While market signal analysis predicts future trends, fundamental analysis interprets these trends and identifies relevant factors and possibilities.
A116: Step 5: Calculate Target Buy Price
B118: Assume the Equity Value will be realized over the holding period.
B119: Key Components
B120: Expected Holding period = | C120: =E20 -> 3
B121: Target Annual Return = | C121: =C19 -> 0.2
B122: Annual Dividend per share = | C122: =Scenarios!C77 -> 0.58 | D122: =Market_currency -> HKD
B124: Result
B125: ="PV("&C120&" yrs of Dividends)" -> PV(3 yrs of Dividends) | C125: =Scenarios!C81 -> 1.2217593
B126: ="+ PV(Equity Value realized at year "&C120&")" -> + PV(Equity Value realized at year 3) | C126: =Scenarios!C82 -> 5.2284175
B127: Buy Below: | C127: =Scenarios!C83 -> 6.4501768 | D127: =Reporting_currency -> HKD
B128: @ a Margin of Safety of | C128: =Scenarios!F83 -> -0.28606674

Sheet Data
B1: =Thesis!C16 -> HKD | C1: 45473 | D1: =EOMONTH(EDATE(C1,-12),0) -> 45107 | E1: =EOMONTH(EDATE(D1,-12),0) -> 44742 | F1: =EOMONTH(EDATE(E1,-12),0) -> 44377 | G1: =EOMONTH(EDATE(F1,-12),0) -> 44012 | H1: =EOMONTH(EDATE(G1,-12),0) -> 43646 | I1: =EOMONTH(EDATE(H1,-12),0) -> 43281 | J1: =EOMONTH(EDATE(I1,-12),0) -> 42916 | K1: =EOMONTH(EDATE(J1,-12),0) -> 42551 | ... M1: =EOMONTH(EDATE(L1,-12),0) -> 41820
B2: Data (Dirty)
B3: Income Statement | C3: 1000000
B4: Sales | C4: 8765 | D4: 11881
B5: COGS | C5: 5344 | D5: 6492
B6: OPEX | C6: 1084 | D6: 1129
B7: Incl. Selling Expenses
B8: R&D
B9: Share of JV or associate Results | C9: 639 | D9: 927
B10: Dividend or Interests from FA
B11: Investment property
B12: Interest Expense | C12: 43 | D12: 40.775368
B13: Interest Income | C13: 2340 | D13: 1390.8453
B14: Income Tax Paid | C14: 519 | D14: 860.83483
B15: Reported Net Income | C15: 4251 | D15: 5880
B16: Non-controling Interests | C16: -151 | D16: 31
B18: Cash Flow Statement
B19: D&A | C19: 160 | D19: 198
B20: CAPX | C20: 69 | D20: 108
B21: WCInv | C21: 910 | D21: 2541
B22: ="Dividend per share ("&Market_currency&")" -> Dividend per share (HKD) | C22: 0.58 | D22: 0.58
B24: Balance Sheet
B25: ST AR | D25: 7251
B26: ST Inventory | D26: 16389
B27: Total Liabilities | C27: 14028 | D27: 10902
B28: Total Equity | C28: 166316 | D28: 163105
B29: Non-common Interest
B31: Other Data
B32: Contingent Liabilities
B34: IS & CF Statements (Clean)
B35: Income Statement
B36: Sales | C36: =IF(C$4="","",C4) -> 8765 | D36: =IF(D$4="","",D4) -> 11881 | E36: =IF(E$4="","",E4) | F36: =IF(F$4="","",F4) | G36: =IF(G$4="","",G4) | H36: =IF(H$4="","",H4) | I36: =IF(I$4="","",I4) | J36: =IF(J$4="","",J4) | ... M36: =IF(M$4="","",M4)
B37: COGS | C37: =IF(C$4="","",-C5) -> -5344 | D37: =IF(D$4="","",-D5) -> -6492 | E37: =IF(E$4="","",-E5) | F37: =IF(F$4="","",-F5) | G37: =IF(G$4="","",-G5) | H37: =IF(H$4="","",-H5) | I37: =IF(I$4="","",-I5) | J37: =IF(J$4="","",-J5) | ... M37: =IF(M$4="","",-M5)
B38: Gross Margin | C38: =IF(C36="","",C36+C37) -> 3421 | D38: =IF(D36="","",D36+D37) -> 5389 | E38: =IF(E36="","",E36+E37) | F38: =IF(F36="","",F36+F37) | G38: =IF(G36="","",G36+G37) | H38: =IF(H36="","",H36+H37) | I38: =IF(I36="","",I36+I37) | J38: =IF(J36="","",J36+J37) | ... M38: =IF(M36="","",M36+M37)
B39: OPEX | C39: =IF(C$4="","",-C6) -> -1084 | D39: =IF(D$4="","",-D6) -> -1129 | E39: =IF(E$4="","",-E6) | F39: =IF(F$4="","",-F6) | G39: =IF(G$4="","",-G6) | H39: =IF(H$4="","",-H6) | I39: =IF(I$4="","",-I6) | J39: =IF(J$4="","",-J6) | ... M39: =IF(M$4="","",-M6)
B40: Incl. Selling Expenses | C40: =IF(C$4="","",-C7) -> 0 | D40: =IF(D$4="","",-D7) -> 0 | E40: =IF(E$4="","",-E7) | F40: =IF(F$4="","",-F7) | G40: =IF(G$4="","",-G7) | H40: =IF(H$4="","",-H7) | I40: =IF(I$4="","",-I7) | J40: =IF(J$4="","",-J7) | ... M40: =IF(M$4="","",-M7)
B41: Incl. Other Opex | C41: =IF(C$4="","",C39-C40) -> -1084 | D41: =IF(D$4="","",D39-D40) -> -1129 | E41: =IF(E$4="","",E39-E40) | F41: =IF(F$4="","",F39-F40) | G41: =IF(G$4="","",G39-G40) | H41: =IF(H$4="","",H39-H40) | I41: =IF(I$4="","",I39-I40) | J41: =IF(J$4="","",J39-J40) | ... M41: =IF(M$4="","",M39-M40)
B42: R&D | C42: =IF(C$4="","",-C8) -> 0 | D42: =IF(D$4="","",-D8) -> 0 | E42: =IF(E$4="","",-E8) | F42: =IF(F$4="","",-F8) | G42: =IF(G$4="","",-G8) | H42: =IF(H$4="","",-H8) | I42: =IF(I$4="","",-I8) | J42: =IF(J$4="","",-J8) | ... M42: =IF(M$4="","",-M8)
B43: Operating EBIT | C43: =IF(C$4="","",C38+C39+C42) -> 2337 | D43: =IF(D$4="","",D38+D39+D42) -> 4260 | E43: =IF(E$4="","",E38+E39+E42) | F43: =IF(F$4="","",F38+F39+F42) | G43: =IF(G$4="","",G38+G39+G42) | H43: =IF(H$4="","",H38+H39+H42) | I43: =IF(I$4="","",I38+I39+I42) | J43: =IF(J$4="","",J38+J39+J42) | ... M43: =IF(M$4="","",M38+M39+M42)
B44: Non-operating EBIT | C44: =IF(C$4="","",C47-C46-C45-C43) -> 136 | D44: =IF(D$4="","",D47-D46-D45-D43) -> 1130.7649 | E44: =IF(E$4="","",E47-E46-E45-E43) | F44: =IF(F$4="","",F47-F46-F45-F43) | G44: =IF(G$4="","",G47-G46-G45-G43) | H44: =IF(H$4="","",H47-H46-H45-H43) | I44: =IF(I$4="","",I47-I46-I45-I43) | J44: =IF(J$4="","",J47-J46-J45-J43) | ... M44: =IF(M$4="","",M47-M46-M45-M43)
B45: Net Interest Income | C45: =IF(C$4="","",C51+C52) -> 2297 | D45: =IF(D$4="","",D51+D52) -> 1350.0699 | E45: =IF(E$4="","",E51+E52) | F45: =IF(F$4="","",F51+F52) | G45: =IF(G$4="","",G51+G52) | H45: =IF(H$4="","",H51+H52) | I45: =IF(I$4="","",I51+I52) | J45: =IF(J$4="","",J51+J52) | ... M45: =IF(M$4="","",M51+M52)
B46: Income Tax Paid | C46: =IF(C$4="","",-C14) -> -519 | D46: =IF(D$4="","",-D14) -> -860.83483 | E46: =IF(E$4="","",-E14) | F46: =IF(F$4="","",-F14) | G46: =IF(G$4="","",-G14) | H46: =IF(H$4="","",-H14) | I46: =IF(I$4="","",-I14) | J46: =IF(J$4="","",-J14) | ... M46: =IF(M$4="","",-M14)
B47: Reported Net Income | C47: =IF(C$4="","",C15) -> 4251 | D47: =IF(D$4="","",D15) -> 5880 | E47: =IF(E$4="","",E15) | F47: =IF(F$4="","",F15) | G47: =IF(G$4="","",G15) | H47: =IF(H$4="","",H15) | I47: =IF(I$4="","",I15) | J47: =IF(J$4="","",J15) | ... M47: =IF(M$4="","",M15)
B48: Non-controling Interests | C48: =IF(C$4="","",MIN(-C16,0)) -> 0 | D48: =IF(D$4="","",MIN(-D16,0)) -> -31 | E48: =IF(E$4="","",MIN(-E16,0)) | F48: =IF(F$4="","",MIN(-F16,0)) | G48: =IF(G$4="","",MIN(-G16,0)) | H48: =IF(H$4="","",MIN(-H16,0)) | I48: =IF(I$4="","",MIN(-I16,0)) | J48: =IF(J$4="","",MIN(-J16,0)) | ... M48: =IF(M$4="","",MIN(-M16,0))
B50: Net Interest Income
B51: Interest Expense | C51: =IF(C$4="","",-C12) -> -43 | D51: =IF(D$4="","",-D12) -> -40.775368 | E51: =IF(E$4="","",-E12) | F51: =IF(F$4="","",-F12) | G51: =IF(G$4="","",-G12) | H51: =IF(H$4="","",-H12) | I51: =IF(I$4="","",-I12) | J51: =IF(J$4="","",-J12) | ... M51: =IF(M$4="","",-M12)
B52: Interest Income | C52: =IF(C$4="","",C13) -> 2340 | D52: =IF(D$4="","",D13) -> 1390.8453 | E52: =IF(E$4="","",E13) | F52: =IF(F$4="","",F13) | G52: =IF(G$4="","",G13) | H52: =IF(H$4="","",H13) | I52: =IF(I$4="","",I13) | J52: =IF(J$4="","",J13) | ... M52: =IF(M$4="","",M13)
B54: Non-operating EBIT
B55: Share of JV or associate Results | C55: =IF(C$4="","",C9) -> 639 | D55: =IF(D$4="","",D9) -> 927 | E55: =IF(E$4="","",E9) | F55: =IF(F$4="","",F9) | G55: =IF(G$4="","",G9) | H55: =IF(H$4="","",H9) | I55: =IF(I$4="","",I9) | J55: =IF(J$4="","",J9) | ... M55: =IF(M$4="","",M9)
B56: Dividend or Interests from FA | C56: =IF(C$4="","",C10) -> 0 | D56: =IF(D$4="","",D10) -> 0 | E56: =IF(E$4="","",E10) | F56: =IF(F$4="","",F10) | G56: =IF(G$4="","",G10) | H56: =IF(H$4="","",H10) | I56: =IF(I$4="","",I10) | J56: =IF(J$4="","",J10) | ... M56: =IF(M$4="","",M10)
B57: Investment property | C57: =IF(C$4="","",C11) -> 0 | D57: =IF(D$4="","",D11) -> 0 | E57: =IF(E$4="","",E11) | F57: =IF(F$4="","",F11) | G57: =IF(G$4="","",G11) | H57: =IF(H$4="","",H11) | I57: =IF(I$4="","",I11) | J57: =IF(J$4="","",J11) | ... M57: =IF(M$4="","",M11)
B58: Other Non-operating Income | C58: =IF(C$4="","",C44-C55-C56-C57) -> -503 | D58: =IF(D$4="","",D44-D55-D56-D57) -> 203.76489 | E58: =IF(E$4="","",E44-E55-E56-E57) | F58: =IF(F$4="","",F44-F55-F56-F57) | G58: =IF(G$4="","",G44-G55-G56-G57) | H58: =IF(H$4="","",H44-H55-H56-H57) | I58: =IF(I$4="","",I44-I55-I56-I57) | J58: =IF(J$4="","",J44-J55-J56-J57) | ... M58: =IF(M$4="","",M44-M55-M56-M57)
B60: Cash Flow Statement
B61: D&A | C61: =IF(C$4="","",-C19) -> -160 | D61: =IF(D$4="","",-D19) -> -198 | E61: =IF(E$4="","",-E19) | F61: =IF(F$4="","",-F19) | G61: =IF(G$4="","",-G19) | H61: =IF(H$4="","",-H19) | I61: =IF(I$4="","",-I19) | J61: =IF(J$4="","",-J19) | ... M61: =IF(M$4="","",-M19)
B62: CAPX | C62: =IF(C$4="","",-C20) -> -69 | D62: =IF(D$4="","",-D20) -> -108 | E62: =IF(E$4="","",-E20) | F62: =IF(F$4="","",-F20) | G62: =IF(G$4="","",-G20) | H62: =IF(H$4="","",-H20) | I62: =IF(I$4="","",-I20) | J62: =IF(J$4="","",-J20) | ... M62: =IF(M$4="","",-M20)
B63: WCInv | C63: =IF(C$4="","",-C21) -> -910 | D63: =IF(D$4="","",-D21) -> -2541 | E63: =IF(E$4="","",-E21) | F63: =IF(F$4="","",-F21) | G63: =IF(G$4="","",-G21) | H63: =IF(H$4="","",-H21) | I63: =IF(I$4="","",-I21) | J63: =IF(J$4="","",-J21) | ... M63: =IF(M$4="","",-M21)
B64: Dividend per share | C64: =IF(C$4="","",C22) -> 0.58 | D64: =IF(D$4="","",D22) -> 0.58 | E64: =IF(E$4="","",E22) | F64: =IF(F$4="","",F22) | G64: =IF(G$4="","",G22) | H64: =IF(H$4="","",H22) | I64: =IF(I$4="","",I22) | J64: =IF(J$4="","",J22) | ... M64: =IF(M$4="","",M22)
B66: YoY %
B67: =B36 -> Sales | C67: =IF(D$36="","",C36/D36-1) -> -0.26226749 | D67: =IF(E$36="","",D36/E36-1) | E67: =IF(F$36="","",E36/F36-1) | F67: =IF(G$36="","",F36/G36-1) | G67: =IF(H$36="","",G36/H36-1) | H67: =IF(I$36="","",H36/I36-1) | I67: =IF(J$36="","",I36/J36-1) | J67: =IF(K$36="","",J36/K36-1) | ... M67: =IF(N$36="","",M36/N36-1)
B68: =B43 -> Operating EBIT | C68: =IF(D$36="","",C37/D37-1) -> -0.17683303 | D68: =IF(E$36="","",D37/E37-1) | E68: =IF(F$36="","",E37/F37-1) | F68: =IF(G$36="","",F37/G37-1) | G68: =IF(H$36="","",G37/H37-1) | H68: =IF(I$36="","",H37/I37-1) | I68: =IF(J$36="","",I37/J37-1) | J68: =IF(K$36="","",J37/K37-1) | ... M68: =IF(N$36="","",M37/N37-1)
B69: =B58 -> Other Non-operating Income | C69: =IF(D$36="","",C38/D38-1) -> -0.36518835 | D69: =IF(E$36="","",D38/E38-1) | E69: =IF(F$36="","",E38/F38-1) | F69: =IF(G$36="","",F38/G38-1) | G69: =IF(H$36="","",G38/H38-1) | H69: =IF(I$36="","",H38/I38-1) | I69: =IF(J$36="","",I38/J38-1) | J69: =IF(K$36="","",J38/K38-1) | ... M69: =IF(N$36="","",M38/N38-1)
B70: =B47 -> Reported Net Income | C70: =IF(D$36="","",C39/D39-1) -> -0.039858282 | D70: =IF(E$36="","",D39/E39-1) | E70: =IF(F$36="","",E39/F39-1) | F70: =IF(G$36="","",F39/G39-1) | G70: =IF(H$36="","",G39/H39-1) | H70: =IF(I$36="","",H39/I39-1) | I70: =IF(J$36="","",I39/J39-1) | J70: =IF(K$36="","",J39/K39-1) | ... M70: =IF(N$36="","",M39/N39-1)
B71: =B48 -> Non-controling Interests | C71: =IF(D$36="","",C64/D64-1) -> 0 | D71: =IF(E$36="","",D64/E64-1) | E71: =IF(F$36="","",E64/F64-1) | F71: =IF(G$36="","",F64/G64-1) | G71: =IF(H$36="","",G64/H64-1) | H71: =IF(I$36="","",H64/I64-1) | I71: =IF(J$36="","",I64/J64-1) | J71: =IF(K$36="","",J64/K64-1) | ... M71: =IF(N$36="","",M64/N64-1)
B73: Balance Sheet (Clean)
B74: Balance Sheet
B75: Total Assets | C75: =IF(C$4="","",C78+C79) -> 180344 | D75: =IF(D$4="","",D78+D79) -> 174007 | E75: =IF(E$4="","",E78+E79) | F75: =IF(F$4="","",F78+F79) | G75: =IF(G$4="","",G78+G79) | H75: =IF(H$4="","",H78+H79) | I75: =IF(I$4="","",I78+I79) | J75: =IF(J$4="","",J78+J79) | ... M75: =IF(M$4="","",M78+M79)
B76: Incl. ST AR | C76: =IF(C$4="","",C25) -> 0 | D76: =IF(D$4="","",D25) -> 7251 | E76: =IF(E$4="","",E25) | F76: =IF(F$4="","",F25) | G76: =IF(G$4="","",G25) | H76: =IF(H$4="","",H25)
B77: Incl. ST Inventory | C77: =IF(C$4="","",C26) -> 0 | D77: =IF(D$4="","",D26) -> 16389 | E77: =IF(E$4="","",E26) | F77: =IF(F$4="","",F26) | G77: =IF(G$4="","",G26) | H77: =IF(H$4="","",H26)
B78: Total Liabilities | C78: =IF(C$4="","",C27) -> 14028 | D78: =IF(D$4="","",D27) -> 10902 | E78: =IF(E$4="","",E27) | F78: =IF(F$4="","",F27) | G78: =IF(G$4="","",G27) | H78: =IF(H$4="","",H27) | I78: =IF(I$4="","",I27) | J78: =IF(J$4="","",J27) | ... M78: =IF(M$4="","",M27)
B79: Total Equity | C79: =IF(C$4="","",C28) -> 166316 | D79: =IF(D$4="","",D28) -> 163105 | E79: =IF(E$4="","",E28) | F79: =IF(F$4="","",F28) | G79: =IF(G$4="","",G28) | H79: =IF(H$4="","",H28) | I79: =IF(I$4="","",I28) | J79: =IF(J$4="","",J28) | ... M79: =IF(M$4="","",M28)

Sheet BS
B1: Most Recent Quarter | C1: 45473 | F1: =IF(MONTH(C1)=MONTH(Normalized_FCF!G1),"FY","Quarter")&" Report" -> FY Report | H1: =Data!C3 -> 1000000
B2: Lastest Balance Sheet
B3: ST Operating Assets | C3: Book | D3: Valued @ | F3: ST Non-Operating Assets | G3: Book | H3: Valued @
B4: ST AR | C4: 8029 | D4: 0.6 | F4: Cash and cash equivalents | G4: 45665 | H4: 0.9
B5: Operating ST Financial Assets | C5: 0 | D5: 0.6 | F5: Restricted cash | G5: 2014 | H5: 0.7
B6: Inventory | C6: 9844 | D6: 0.5 | F6: Securities with stable income | G6: 156 | H6: 0.6
B7: Properties held for sale | C7: 5466 | D7: 0.6 | F7: Other Securities | G7: 0 | H7: 0.6
B8: Properties held for income | C8: 0 | D8: 0.6 | F8: Properties with stable income | G8: 0 | H8: 0.6
B9: Prepayments and Contract Assets | C9: 0 | D9: 0.1 | F9: Other Properties | G9: 0 | H9: 0.6
B10: ST DTA | C10: 10 | D10: 0.9
B11: Other ST Assets | C11: 0 | D11: 0.05
B12: Operating ST Assets | C12: =SUM(C4:C11) -> 23349 | D12: =C4*D4+C5*D5+C9*D9+C6*D6+C8*D8+C7*D7+C10*D10+C11*D11 -> 13028 | F12: Non-Operating ST Assets | G12: =SUM(G4:G9) -> 47835 | H12: =G4*H4+G5*H5+G6*H6+G7*H7+G8*H8+G9*H9 -> 42601.9
B14: LT Operating Assets | C14: Book | D14: Valued @ | F14: LT Non-Operating Assets | G14: Book | H14: Valued @
B15: LT AR | C15: 2757 | D15: 0.4 | F15: LT Depositis | G15: 0 | H15: 0.8
B16: Operating LT Financial Assets | C16: 0 | D16: 0.5 | F16: Securities with stable income | G16: 1373 | H16: 0.6
B17: Properties held for sale | C17: 67668 | D17: 0.6 | F17: Other Securities | G17: 13024 | H17: 0.6
B18: Properties held for income | C18: 0 | D18: 0.6 | F18: JV or associate with stable income | G18: 23696 | H18: 0.1
B19: PP&E & Right of Use Assets | C19: 1284 | D19: 0.1 | F19: Other JV or associate | G19: 0 | H19: 0.1
B20: Biological assets | C20: 0 | D20: 0.05 | F20: Properties with stable income | G20: 0 | H20: 0.2
B21: Intangible assets | C21: 0 | D21: 0.05 | F21: Other Properties | G21: 0 | H21: 0.1
B22: LT DTA | C22: 10 | D22: 0.9
B23: Other assets & Goodwill | C23: 0 | D23: 0
B24: Operating LT Assets | C24: =SUM(C15:C23) -> 71719 | D24: =C15*D15+C16*D16+C18*D18+C17*D17+C19*D19+C20*D20+C21*D21+C22*D22+C23*D23 -> 41841 | F24: Non-Operating LT Assets | G24: =SUM(G15:G21) -> 38093 | H24: =G15*H15+G16*H16+G17*H17+G18*H18+G19*H19+G20*H20+G21*H21 -> 11007.8
B26: ST Liabilities | C26: Book | F26: BS Summary | G26: Book | H26: Valued @
B27: ST Borrowing | C27: 967 | F27: Total Equity | G27: =G32-G30 -> 167107 | H27: =H32-G30 -> 94589.7
B28: ST Lease liabilities | C28: 37 | F28: Incl. Minority Interest (NCI) | G28: 519
B29: ST SH Loan | C29: 0 | F29: Incl. Common Equity | G29: =G27-G28 -> 166588 | H29: =H27-G28 -> 94070.7
B30: ST Financial Liabilities | C30: 0 | F30: Total Liabilities | G30: =C33+C42 -> 13889
B31: ST Interest-bearing Debt | C31: =SUM(C27:C30) -> 1004 | F31: incl. Interest-bearing Debt | G31: =C31+C40 -> 3093
B32: Other ST liabilities | C32: =C33-C31 -> 8048 | F32: Total Assets | G32: =G35+G40 -> 180996 | H32: =H35+H40 -> 108478.7
B33: Current Liabilities | C33: 9052
F34: Assets Summary | G34: Book | H34: Valued @
B35: LT Liabilities | C35: Book | F35: Operating Assets | G35: =C12+C24 -> 95068 | H35: =D12+D24 -> 54869
B36: LT Borrowing | C36: 832 | F36: incl. AR | G36: =C4+C15 -> 10786
B37: LT Lease liabilities | C37: 27 | F37: incl. inventory | G37: =C6 -> 9844
B38: LT SH Loan | C38: 1230 | F38: incl. Properties held for sale | G38: =C7+C17 -> 73134
B39: LT Financial Liabilities | C39: 0 | F39: incl. Fixed Assets | G39: =C7+C17+C19+C20 -> 74418 | H39: =C7*D7+C17*D17+C19*D19+C20*D20 -> 44008.8
B40: LT Interest-bearing Debt | C40: =SUM(C36:C39) -> 2089 | F40: Non-operating Assets | G40: =G12+G24 -> 85928 | H40: =H12+H24 -> 53609.7
B41: Other LT liabilities | C41: =C42-C40 -> 2748 | F41: incl. Assets with stable income | G41: =C70 -> 72904 | H41: =H40-H42 -> 45795.3
B42: Noncurrent Liabilities | C42: 4837 | F42: incl. Other Assets | G42: =C82 -> 13024 | H42: =D82 -> 7814.4
B44: Balance Sheet Analysis
B45: Asset Value Stress Test | C45: Book | D45: Stress Test | F45: Notes
B46: Equity | C46: =G29 -> 166588 | D46: =H29 -> 94070.7
B47: ="Equity per share ("&Market_currency&")" -> Equity per share (HKD) | C47: =C46*H1/Common_Shares*Exchange_Rate -> 20.385517 | D47: =D46*H1/Common_Shares*Exchange_Rate -> 11.511513
B49: Leverage % | C49: Normalized | D49: Latest
B50: Debt/EBIT | C50: =G31/Normalized_FCF!C8 -> 1.1933698 | D50: =G31/Normalized_FCF!G8 -> 1.3234917
B51: Common Equity/Total Asset | D51: =G29/G32 -> 0.92039603
B53: Profibility % | C53: Normalized | D53: Latest
B54: Operating Asset Yield | C54: =Normalized_FCF!C8/G35 -> 0.027262804 | D54: =Normalized_FCF!G8/G35 -> 0.024582404
B55: Non-Operating Asset Yield | C55: =Normalized_FCF!C11/G40 -> 0.0074364584 | D55: =Normalized_FCF!G11/G40 -> 0.0074364584
B57: Reinvestment % | C57: Normalized | D57: Latest
B58: D&A/Fixed Assets | D58: =Normalized_FCF!G9/BS!$G$39 -> 0.0021500175
B59: Fixed Assets/Total Assets | D59: =G39/G32 -> 0.41115826
B61: NCI % | C61: Estimate | D61: Latest
B62: Est. of NCI Ownership Percentage | C62: =IF(G28<=0,0,G28/G29) -> 0.0031154705 | D62: =G28/G29 -> 0.0031154705 | F62: Rough Estimate only
B64: Non-operating Assets Analysis
B65: Non-operating Assets with stable income | C65: Book | D65: Non-Operating | F65: Notes
B66: Cash | C66: =G4+G5+G15 -> 47679 | D66: =C66-D75 -> 41505.82 | F66: Non-Operating Cash is the Excess cash not required for operations
B67: Securities with stable income | C67: =G6+G16 -> 1529
B68: JV or associate with stable income | C68: =G18 -> 23696
B69: Properties with stable income | C69: =G8+G20 -> 0
B70: Non-operating Assets with stable income | C70: =SUM(C66:C69) -> 72904
B72: Cash Management Analysis | C72: Latest | D72: Normalized
B73: Monthly Operating Expenses | C73: =(Normalized_FCF!G25+Normalized_FCF!G35)/12 -> -535.66667 | D73: =(Normalized_FCF!C25+Normalized_FCF!C35)/12 -> -514.43165
B74: Operating Expenses Multiple (months) | C74: =-$C$66/C73 -> 89.008712 | D74: =-$C$66/D73 -> 92.682868 | F74: Companies typically need cash to cover 1 to 2 months of operating expenses
B75: Operating Cash Requirement | D75: =MAX(-D73*D76,G5) -> 6173.1797 | F75: 1x for stable businesses, 2x for for volatile ones
B76: Operating Cash Multiple (months) | D76: =IF(D74<=3,1,IF(D74>18,IF(D74>36,12,6),2)) -> 12 | F76: Rough Estimate
B78: Other Non-operating Assets | C78: Book | D78: Valued @
B79: Other Securities | C79: =G7+G17 -> 13024 | D79: =G7*H7+G17*H17 -> 7814.4
B80: Other JV or associate | C80: =G19 -> 0 | D80: =G19*H19 -> 0
B81: Other Properties | C81: =G9+G21 -> 0 | D81: =G9*H9+G21*H21 -> 0
B82: Other Non-operating Assets | C82: =SUM(C79:C81) -> 13024 | D82: =SUM(D79:D81) -> 7814.4
B84: Non-FCF Value of the Equity Value
B85: Non-FCF Value | D85: Per-Share
B86: Interest-bearing Debt | C86: =-Valuation_Model!C7*Exchange_Rate -> -3093 | D86: =C86*$H$1/Common_Shares -> -0.37849308 | E86: =Market_currency -> HKD
B87: Non-operating Cash | C87: =Valuation_Model!C8*Exchange_Rate -> 41505.82 | D87: =C87*$H$1/Common_Shares -> 5.079103 | E87: =Market_currency -> HKD
B88: Other Non-operating Assets | C88: =Valuation_Model!C9*Exchange_Rate -> 7814.4 | D88: =C88*$H$1/Common_Shares -> 0.95625487 | E88: =Market_currency -> HKD
B89: Total Non-FCF Value | C89: =SUM(C86:C88) -> 46227.22 | D89: =SUM(D86:D88) -> 5.6568648 | E89: =Market_currency -> HKD

Sheet Normalized_FCF
B1: =Thesis!C16 -> HKD | C1: Normalized | G1: =Data!C1 -> 45473 | H1: =EOMONTH(EDATE(G1,-12),0) -> 45107 | I1: =EOMONTH(EDATE(H1,-12),0) -> 44742 | J1: =EOMONTH(EDATE(I1,-12),0) -> 44377 | K1: =EOMONTH(EDATE(J1,-12),0) -> 44012 | L1: =EOMONTH(EDATE(K1,-12),0) -> 43646 | M1: =EOMONTH(EDATE(L1,-12),0) -> 43281 | N1: =EOMONTH(EDATE(M1,-12),0) -> 42916 | O1: =EOMONTH(EDATE(N1,-12),0) -> 42551 | ... Q1: =EOMONTH(EDATE(P1,-12),0) -> 41820
B2: FCFE Analysis | E2: Notes
B3: FCFE | C3: =Data!C3 -> 1000000
B4: Sales | C4: =G4 -> 8765 | G4: =Data!C36 -> 8765 | H4: =Data!D36 -> 11881 | I4: =Data!E36 | J4: =Data!F36 | K4: =Data!G36 | L4: =Data!H36 | M4: =Data!I36 | N4: =Data!J36 | ... Q4: =Data!M36
B5: Variable Costs | C5: =C25 -> -5066.6797 | G5: =G25 -> -5344 | H5: =H25 -> -6492 | I5: =I25 | J5: =J25 | K5: =K25 | L5: =L25 | M5: =M25 | N5: =N25 | ... Q5: =Q25
B6: Contribution Margin | C6: =C4+C5 -> 3698.3203 | G6: =IF(G4="","",G4+G5) -> 3421 | H6: =IF(H4="","",H4+H5) -> 5389 | I6: =IF(I4="","",I4+I5) | J6: =IF(J4="","",J4+J5) | K6: =IF(K4="","",K4+K5) | L6: =IF(L4="","",L4+L5) | M6: =IF(M4="","",M4+M5) | N6: =IF(N4="","",N4+N5) | ... Q6: =IF(Q4="","",Q4+Q5)
B7: Fixed Costs | C7: =C35 -> -1106.5 | G7: =G35 -> -1084 | H7: =H35 -> -1129 | I7: =I35 | J7: =J35 | K7: =K35 | L7: =L35 | M7: =M35 | N7: =N35 | ... Q7: =Q35
B8: Operating EBIT | C8: =C6+C7 -> 2591.8203 | G8: =IF(G$4="","",G6+G7) -> 2337 | H8: =IF(H$4="","",H6+H7) -> 4260 | I8: =IF(I$4="","",I6+I7) | J8: =IF(J$4="","",J6+J7) | K8: =IF(K$4="","",K6+K7) | L8: =IF(L$4="","",L6+L7) | M8: =IF(M$4="","",M6+M7) | N8: =IF(N$4="","",N6+N7) | ... Q8: =IF(Q$4="","",Q6+Q7)
B9: Add Back D&A | C9: =BS!$G$39*BS!D58 -> 160 | G9: =IF(Data!C61="","",-Data!C61) -> 160 | H9: =IF(Data!D61="","",-Data!D61) -> 198 | I9: =IF(Data!E61="","",-Data!E61) | J9: =IF(Data!F61="","",-Data!F61) | K9: =IF(Data!G61="","",-Data!G61) | L9: =IF(Data!H61="","",-Data!H61) | M9: =IF(Data!I61="","",-Data!I61) | N9: =IF(Data!J61="","",-Data!J61) | ... Q9: =IF(Data!M61="","",-Data!M61)
B10: Maintenance Capex | C10: =-C4*C78 -> -160 | G10: =Data!C62 -> -69 | H10: =Data!D62 -> -108 | I10: =Data!E62 | J10: =Data!F62 | K10: =Data!G62 | L10: =Data!H62 | M10: =Data!I62 | N10: =Data!J62 | ... Q10: =Data!M62
B11: Stable Non-Operating EBIT | C11: =C63 -> 639 | G11: =G61 -> 639 | H11: =H61 -> 927 | I11: =I61 | J11: =J61 | K11: =K61 | L11: =L61 | M11: =M61 | N11: =N61 | ... Q11: =Q61
B12: Net Interest Income | C12: =C50 -> 142.19539 | G12: =G50 -> 259.96861 | H12: =H50 -> 139.30261 | I12: =I50 | J12: =J50 | K12: =K50 | L12: =L50 | M12: =M50 | N12: =N50 | ... Q12: =Q50
B13: Pre-tax Profit | C13: =SUM(C8:C12) -> 3373.0157 | G13: =IF(G$4="","",SUM(G8:G12)) -> 3326.9686 | H13: =IF(H$4="","",SUM(H8:H12)) -> 5416.3026 | I13: =IF(I$4="","",SUM(I8:I12)) | J13: =IF(J$4="","",SUM(J8:J12)) | K13: =IF(K$4="","",SUM(K8:K12)) | L13: =IF(L$4="","",SUM(L8:L12)) | M13: =IF(M$4="","",SUM(M8:M12)) | N13: =IF(N$4="","",SUM(N8:N12)) | ... Q13: =IF(Q$4="","",SUM(Q8:Q12))
B14: Income Tax | C14: =-SUM(C8+C11,C12)*C43 -> -809.52376 | G14: =Data!C46 -> -519 | H14: =Data!D46 -> -860.83483 | I14: =Data!E46 | J14: =Data!F46 | K14: =Data!G46 | L14: =Data!H46 | M14: =Data!I46 | N14: =Data!J46 | ... Q14: =Data!M46
B15: NCI’s Share of Profits | C15: =-C4*C83 -> -22.869708 | G15: =Data!C48 -> 0 | H15: =Data!D48 -> -31 | I15: =Data!E48 | J15: =Data!F48 | K15: =Data!G48 | L15: =Data!H48 | M15: =Data!I48 | N15: =Data!J48 | ... Q15: =Data!M48
B16: After-tax Profit | C16: =SUM(C13:C15) -> 2540.6222 | G16: =IF(G$4="","",SUM(G13:G15)) -> 2807.9686 | H16: =IF(H$4="","",SUM(H13:H15)) -> 4524.4678 | I16: =IF(I$4="","",SUM(I13:I15)) | J16: =IF(J$4="","",SUM(J13:J15)) | K16: =IF(K$4="","",SUM(K13:K15)) | L16: =IF(L$4="","",SUM(L13:L15)) | M16: =IF(M$4="","",SUM(M13:M15)) | N16: =IF(N$4="","",SUM(N13:N15)) | ... Q16: =IF(Q$4="","",SUM(Q13:Q15))
B17: WCInv | C17: =-C4*C85 -> 0 | E17: WCInv is by default excluded
B18: Net Borrowing | C18: 0 | E18: Net borrowing is excluded
B19: FCFE | C19: =C16+C17 -> 2540.6222 | G19: =IF(G$4="","",G16+G17) -> 2807.9686 | H19: =IF(H$4="","",H16+H17) -> 4524.4678 | I19: =IF(I$4="","",I16+I17) | J19: =IF(J$4="","",J16+J17) | K19: =IF(K$4="","",K16+K17) | L19: =IF(L$4="","",L16+L17) | M19: =IF(M$4="","",M16+M17) | N19: =IF(N$4="","",N16+N17) | ... Q19: =IF(Q$4="","",Q16+Q17)
B21: Operating Cost Structure | E21: Notes
B22: Variable Costs
B23: COGS | C23: =-C4*C28 -> -5066.6797 | G23: =Data!C37 -> -5344 | H23: =Data!D37 -> -6492 | I23: =Data!E37 | J23: =Data!F37 | K23: =Data!G37 | L23: =Data!H37 | M23: =Data!I37 | N23: =Data!J37 | ... Q23: =Data!M37
B24: Selling Expenses | C24: =-C4*C29 -> 0 | G24: =Data!C40 -> 0 | H24: =Data!D40 -> 0 | I24: =Data!E40 | J24: =Data!F40 | K24: =Data!G40 | L24: =Data!H40 | M24: =Data!I40 | N24: =Data!J40 | ... Q24: =Data!M40
B25: Variable Costs | C25: =C23+C24 -> -5066.6797 | G25: =IF(G$4="","",G23+G24) -> -5344 | H25: =IF(H$4="","",H23+H24) -> -6492 | I25: =IF(I$4="","",I23+I24) | J25: =IF(J$4="","",J23+J24) | K25: =IF(K$4="","",K23+K24) | L25: =IF(L$4="","",L23+L24) | M25: =IF(M$4="","",M23+M24) | N25: =IF(N$4="","",N23+N24) | ... Q25: =IF(Q$4="","",Q23+Q24)
B27: Variable Costs % of Sales
B28: COGS | C28: =AVERAGE(G28:H28) -> 0.57805816 | E28: Historical Average | G28: =IF(G$4="","",ABS(G23/G$4)) -> 0.60969766 | H28: =IF(H$4="","",ABS(H23/H$4)) -> 0.54641865 | I28: =IF(I$4="","",ABS(I23/I$4)) | J28: =IF(J$4="","",ABS(J23/J$4)) | K28: =IF(K$4="","",ABS(K23/K$4)) | L28: =IF(L$4="","",ABS(L23/L$4)) | M28: =IF(M$4="","",ABS(M23/M$4)) | N28: =IF(N$4="","",ABS(N23/N$4)) | ... Q28: =IF(Q$4="","",ABS(Q23/Q$4))
B29: =B24 -> Selling Expenses | C29: =AVERAGE(G29:J29) -> 0 | E29: Historical Average | G29: =IF(G$4="","",ABS(G24/G$4)) -> 0 | H29: =IF(H$4="","",ABS(H24/H$4)) -> 0 | I29: =IF(I$4="","",ABS(I24/I$4)) | J29: =IF(J$4="","",ABS(J24/J$4)) | K29: =IF(K$4="","",ABS(K24/K$4)) | L29: =IF(L$4="","",ABS(L24/L$4)) | M29: =IF(M$4="","",ABS(M24/M$4)) | N29: =IF(N$4="","",ABS(N24/N$4)) | ... Q29: =IF(Q$4="","",ABS(Q24/Q$4))
B30: Variable Costs | C30: =ABS(C25/$C$4) -> 0.57805816 | G30: =IF(G$4="","",ABS(G25/G$4)) -> 0.60969766 | H30: =IF(H$4="","",ABS(H25/H$4)) -> 0.54641865 | I30: =IF(I$4="","",ABS(I25/I$4)) | J30: =IF(J$4="","",ABS(J25/J$4)) | K30: =IF(K$4="","",ABS(K25/K$4)) | L30: =IF(L$4="","",ABS(L25/L$4)) | M30: =IF(M$4="","",ABS(M25/M$4)) | N30: =IF(N$4="","",ABS(N25/N$4)) | ... Q30: =IF(Q$4="","",ABS(Q25/Q$4))
B32: Fixed Costs
B33: G&A and other Opex | C33: =AVERAGE(G33:H33) -> -1106.5 | E33: Historical Average | G33: =Data!C41 -> -1084 | H33: =Data!D41 -> -1129 | I33: =Data!E41 | J33: =Data!F41 | K33: =Data!G41 | L33: =Data!H41 | M33: =Data!I41 | N33: =Data!J41 | ... Q33: =Data!M41
B34: R&D | C34: =AVERAGE(G34:J34) -> 0 | E34: Historical Average | G34: =Data!C42 -> 0 | H34: =Data!D42 -> 0 | I34: =Data!E42 | J34: =Data!F42 | K34: =Data!G42 | L34: =Data!H42 | M34: =Data!I42 | N34: =Data!J42 | ... Q34: =Data!M42
B35: Fixed Costs | C35: =C33+C34 -> -1106.5 | G35: =IF(G4="","",G33+G34) -> -1084 | H35: =IF(H4="","",H33+H34) -> -1129 | I35: =IF(I4="","",I33+I34) | J35: =IF(J4="","",J33+J34) | K35: =IF(K4="","",K33+K34) | L35: =IF(L4="","",L33+L34) | M35: =IF(M4="","",M33+M34) | N35: =IF(N4="","",N33+N34) | ... Q35: =IF(Q4="","",Q33+Q34)
B37: Fixed Costs % of Sales
B38: =B33 -> G&A and other Opex | C38: =ABS(C33/$C$4) -> 0.12624073 | G38: =IF(G$4="","",ABS(G33/G$4)) -> 0.1236737 | H38: =IF(H$4="","",ABS(H33/H$4)) -> 0.095025671 | I38: =IF(I$4="","",ABS(I33/I$4)) | J38: =IF(J$4="","",ABS(J33/J$4)) | K38: =IF(K$4="","",ABS(K33/K$4)) | L38: =IF(L$4="","",ABS(L33/L$4)) | M38: =IF(M$4="","",ABS(M33/M$4)) | N38: =IF(N$4="","",ABS(N33/N$4)) | ... Q38: =IF(Q$4="","",ABS(Q33/Q$4))
B39: =B34 -> R&D | C39: =ABS(C34/$C$4) -> 0 | G39: =IF(G$4="","",ABS(G34/G$4)) -> 0 | H39: =IF(H$4="","",ABS(H34/H$4)) -> 0 | I39: =IF(I$4="","",ABS(I34/I$4)) | J39: =IF(J$4="","",ABS(J34/J$4)) | K39: =IF(K$4="","",ABS(K34/K$4)) | L39: =IF(L$4="","",ABS(L34/L$4)) | M39: =IF(M$4="","",ABS(M34/M$4)) | N39: =IF(N$4="","",ABS(N34/N$4)) | ... Q39: =IF(Q$4="","",ABS(Q34/Q$4))
B40: Fixed Costs | C40: =ABS(C35/$C$4) -> 0.12624073 | G40: =IF(G$4="","",ABS(G35/G$4)) -> 0.1236737 | H40: =IF(H$4="","",ABS(H35/H$4)) -> 0.095025671 | I40: =IF(I$4="","",ABS(I35/I$4)) | J40: =IF(J$4="","",ABS(J35/J$4)) | K40: =IF(K$4="","",ABS(K35/K$4)) | L40: =IF(L$4="","",ABS(L35/L$4)) | M40: =IF(M$4="","",ABS(M35/M$4)) | N40: =IF(N$4="","",ABS(N35/N$4)) | ... Q40: =IF(Q$4="","",ABS(Q35/Q$4))
B42: Tax % of Pre-tax Profit
B43: Income Tax Rate | C43: 0.24 | E43: Use the highest past tax rate | G43: =IF(G$4="","",-G14/SUM(G8+G11,G12)) -> 0.16038474 | H43: =IF(H$4="","",-H14/SUM(H8+H11,H12)) -> 0.16161959 | I43: =IF(I$4="","",-I14/SUM(I8+I11,I12)) | J43: =IF(J$4="","",-J14/SUM(J8+J11,J12)) | K43: =IF(K$4="","",-K14/SUM(K8+K11,K12)) | L43: =IF(L$4="","",-L14/SUM(L8+L11,L12)) | M43: =IF(M$4="","",-M14/SUM(M8+M11,M12)) | N43: =IF(N$4="","",-N14/SUM(N8+N11,N12)) | ... Q43: =IF(Q$4="","",-Q14/SUM(Q8+Q11,Q12))
B45: Non-operating Income | E45: Notes
B46: Interest
B47: Interest Expense | C47: =-BS!G31*Normalized_FCF!C54 -> -43 | G47: =Data!C51 -> -43 | H47: =Data!D51 -> -40.775368 | I47: =Data!E51 | J47: =Data!F51 | K47: =Data!G51 | L47: =Data!H51 | M47: =Data!I51 | N47: =Data!J51 | ... Q47: =Data!M51
B48: Operating Interest Income | C48: =BS!D75*C53 -> 185.19539 | G48: =IF(G$4="","",($C$48/$C$49)*G49) -> 302.96861 | H48: =IF(H$4="","",($C$48/$C$49)*H49) -> 180.07798 | I48: =IF(I$4="","",($C$48/$C$49)*I49) | J48: =IF(J$4="","",($C$48/$C$49)*J49) | K48: =IF(K$4="","",($C$48/$C$49)*K49) | L48: =IF(L$4="","",($C$48/$C$49)*L49) | M48: =IF(M$4="","",($C$48/$C$49)*M49) | N48: =IF(N$4="","",($C$48/$C$49)*N49) | ... Q48: =IF(Q$4="","",($C$48/$C$49)*Q49)
B49: From Interest Income | C49: =BS!$C$66*C53 -> 1430.37 | G49: =Data!C52 -> 2340 | H49: =Data!D52 -> 1390.8453 | I49: =Data!E52 | J49: =Data!F52 | K49: =Data!G52 | L49: =Data!H52 | M49: =Data!I52 | N49: =Data!J52 | ... Q49: =Data!M52
B50: Net Interest Income | C50: =C47+C48 -> 142.19539 | G50: =IF(G$4="","",(G47+G48)) -> 259.96861 | H50: =IF(H$4="","",(H47+H48)) -> 139.30261 | I50: =IF(I$4="","",(I47+I48)) | J50: =IF(J$4="","",(J47+J48)) | K50: =IF(K$4="","",(K47+K48)) | L50: =IF(L$4="","",(L47+L48)) | M50: =IF(M$4="","",(M47+M48)) | N50: =IF(N$4="","",(N47+N48)) | ... Q50: =IF(Q$4="","",(Q47+Q48))
B52: % Interest | G52: Latest Asset Value
B53: Interest Yield/Cash | C53: 0.03 | E53: Reference the market rate | G53: =IF(Normalized_FCF!G4="","",Normalized_FCF!G49/BS!$C$66) -> 0.049078211
B54: Interest Rate/Debt | C54: =G54 -> 0.01390236 | E54: Use Last year's rate | G54: =IFERROR(ABS(Normalized_FCF!G47/BS!$G$31),0) -> 0.01390236
B55: Pre-tax Profit/Interest Expense | C55: =-C8/C47 -> 60.27489 | G55: =IF(G4="","",-G8/G47) -> 54.348837 | H55: =IF(H4="","",-H8/H47) -> 104.47484 | I55: =IF(I4="","",-I8/I47) | J55: =IF(J4="","",-J8/J47) | K55: =IF(K4="","",-K8/K47) | L55: =IF(L4="","",-L8/L47) | M55: =IF(M4="","",-M8/M47) | N55: =IF(N4="","",-N8/N47) | ... Q55: =IF(Q4="","",-Q8/Q47)
B57: Non-operating EBIT | G57: Latest Asset Value
B58: Dividend or Interests from FA | C58: =BS!$C79*C66 -> 0 | G58: =Data!C56 -> 0 | H58: =Data!D56 -> 0 | I58: =Data!E56 | J58: =Data!F56 | K58: =Data!G56 | L58: =Data!H56 | M58: =Data!I56 | N58: =Data!J56 | ... Q58: =Data!M56
B59: Share of JV or associate Results | C59: =BS!$C68*C67 -> 639 | G59: =Data!C55 -> 639 | H59: =Data!D55 -> 927 | I59: =Data!E55 | J59: =Data!F55 | K59: =Data!G55 | L59: =Data!H55 | M59: =Data!I55 | N59: =Data!J55 | ... Q59: =Data!M55
B60: Investment property | C60: =BS!$C81*C68 -> 0 | G60: =Data!C57 -> 0 | H60: =Data!D57 -> 0 | I60: =Data!E57 | J60: =Data!F57 | K60: =Data!G57 | L60: =Data!H57 | M60: =Data!I57 | N60: =Data!J57 | ... Q60: =Data!M57
B61: Stable Non-Operating EBIT | C61: =SUM(C58:C60) -> 639 | G61: =IF(G4="","",SUM(G58:G60)) -> 639 | H61: =IF(H4="","",SUM(H58:H60)) -> 927 | I61: =IF(I4="","",SUM(I58:I60)) | J61: =IF(J4="","",SUM(J58:J60)) | K61: =IF(K4="","",SUM(K58:K60)) | L61: =IF(L4="","",SUM(L58:L60)) | M61: =IF(M4="","",SUM(M58:M60)) | N61: =IF(N4="","",SUM(N58:N60)) | ... Q61: =IF(Q4="","",SUM(Q58:Q60))
B62: Other Non-operating Income | C62: 0 | E62: Assume 0 | G62: =Data!C58 -> -503 | H62: =Data!D58 -> 203.76489 | I62: =Data!E58 | J62: =Data!F58 | K62: =Data!G58 | L62: =Data!H58 | M62: =Data!I58 | N62: =Data!J58 | ... Q62: =Data!M58
B63: Total Non-Operating EBIT | C63: =C61+C62 -> 639 | G63: =IF(G4="","",G61+G62) -> 136 | H63: =IF(H4="","",H61+H62) -> 1130.7649 | I63: =IF(I4="","",I61+I62) | J63: =IF(J4="","",J61+J62) | K63: =IF(K4="","",K61+K62) | L63: =IF(L4="","",L61+L62) | M63: =IF(M4="","",M61+M62) | N63: =IF(N4="","",N61+N62) | ... Q63: =IF(Q4="","",Q61+Q62)
B65: Non-operating Asset Yield % | G65: Latest Asset Value
B66: Dividend or Interests from FA | C66: =G66 -> 0 | G66: =IFERROR(G58/BS!$C$67,0) -> 0
B67: JV or associate | C67: =G67 -> 0.026966577 | G67: =IFERROR(G59/BS!$C$68,0) -> 0.026966577
B68: Investment property | C68: =G68 -> 0 | G68: =IFERROR(G60/BS!$C$81,0) -> 0
B69: Stable Non-Operating EBIT | C69: =C61/BS!C70 -> 0.0087649512 | G69: =G61/BS!C70 -> 0.0087649512
B71: P&L & Dividend Analysis | E71: Notes
B72: P&L % Sales
B73: Variable Costs | C73: =ABS(C5/C$4) -> 0.57805816 | G73: =IF(G$4="","",ABS(G5/G$4)) -> 0.60969766 | H73: =IF(H$4="","",ABS(H5/H$4)) -> 0.54641865 | I73: =IF(I$4="","",ABS(I5/I$4)) | J73: =IF(J$4="","",ABS(J5/J$4)) | K73: =IF(K$4="","",ABS(K5/K$4)) | L73: =IF(L$4="","",ABS(L5/L$4)) | M73: =IF(M$4="","",ABS(M5/M$4)) | N73: =IF(N$4="","",ABS(N5/N$4)) | ... Q73: =IF(Q$4="","",ABS(Q5/Q$4))
B74: Contribution Margin | C74: =ABS(C6/C$4) -> 0.42194184 | G74: =IF(G$4="","",ABS(G6/G$4)) -> 0.39030234 | H74: =IF(H$4="","",ABS(H6/H$4)) -> 0.45358135 | I74: =IF(I$4="","",ABS(I6/I$4)) | J74: =IF(J$4="","",ABS(J6/J$4)) | K74: =IF(K$4="","",ABS(K6/K$4)) | L74: =IF(L$4="","",ABS(L6/L$4)) | M74: =IF(M$4="","",ABS(M6/M$4)) | N74: =IF(N$4="","",ABS(N6/N$4)) | ... Q74: =IF(Q$4="","",ABS(Q6/Q$4))
B75: Fixed Costs | C75: =ABS(C7/C$4) -> 0.12624073 | G75: =IF(G$4="","",ABS(G7/G$4)) -> 0.1236737 | H75: =IF(H$4="","",ABS(H7/H$4)) -> 0.095025671 | I75: =IF(I$4="","",ABS(I7/I$4)) | J75: =IF(J$4="","",ABS(J7/J$4)) | K75: =IF(K$4="","",ABS(K7/K$4)) | L75: =IF(L$4="","",ABS(L7/L$4)) | M75: =IF(M$4="","",ABS(M7/M$4)) | N75: =IF(N$4="","",ABS(N7/N$4)) | ... Q75: =IF(Q$4="","",ABS(Q7/Q$4))
B76: Operating EBIT | C76: =ABS(C8/C$4) -> 0.29570111 | G76: =IF(G$4="","",ABS(G8/G$4)) -> 0.26662864 | H76: =IF(H$4="","",ABS(H8/H$4)) -> 0.35855568 | I76: =IF(I$4="","",ABS(I8/I$4)) | J76: =IF(J$4="","",ABS(J8/J$4)) | K76: =IF(K$4="","",ABS(K8/K$4)) | L76: =IF(L$4="","",ABS(L8/L$4)) | M76: =IF(M$4="","",ABS(M8/M$4)) | N76: =IF(N$4="","",ABS(N8/N$4)) | ... Q76: =IF(Q$4="","",ABS(Q8/Q$4))
B77: Add Back D&A | C77: =ABS(C9/C$4) -> 0.018254421 | G77: =IF(G$4="","",G9/G$4) -> 0.018254421 | H77: =IF(H$4="","",H9/H$4) -> 0.016665264 | I77: =IF(I$4="","",I9/I$4) | J77: =IF(J$4="","",J9/J$4) | K77: =IF(K$4="","",K9/K$4) | L77: =IF(L$4="","",L9/L$4) | M77: =IF(M$4="","",M9/M$4) | N77: =IF(N$4="","",N9/N$4) | ... Q77: =IF(Q$4="","",Q9/Q$4)
B78: Maintenance Capex | C78: =MAX(AVERAGE(G78:J78),C77) -> 0.018254421 | E78: Historical Average or D&A | G78: =IF(G$4="","",-G10/G$4) -> 0.0078722191 | H78: =IF(H$4="","",-H10/H$4) -> 0.0090901439 | I78: =IF(I$4="","",-I10/I$4) | J78: =IF(J$4="","",-J10/J$4) | K78: =IF(K$4="","",-K10/K$4) | L78: =IF(L$4="","",-L10/L$4) | M78: =IF(M$4="","",-M10/M$4) | N78: =IF(N$4="","",-N10/N$4) | ... Q78: =IF(Q$4="","",-Q10/Q$4)
B79: Non-Operating EBIT | C79: =ABS(C11/C$4) -> 0.072903594 | G79: =IF(G$4="","",G11/G$4) -> 0.072903594 | H79: =IF(H$4="","",H11/H$4) -> 0.078023735 | I79: =IF(I$4="","",I11/I$4) | J79: =IF(J$4="","",J11/J$4) | K79: =IF(K$4="","",K11/K$4) | L79: =IF(L$4="","",L11/L$4) | M79: =IF(M$4="","",M11/M$4) | N79: =IF(N$4="","",N11/N$4) | ... Q79: =IF(Q$4="","",Q11/Q$4)
B80: Net Interest Income | C80: =ABS(C12/C$4) -> 0.016223091 | G80: =IF(G$4="","",ABS(G12/G$4)) -> 0.029659853 | H80: =IF(H$4="","",ABS(H12/H$4)) -> 0.011724822 | I80: =IF(I$4="","",ABS(I12/I$4)) | J80: =IF(J$4="","",ABS(J12/J$4)) | K80: =IF(K$4="","",ABS(K12/K$4)) | L80: =IF(L$4="","",ABS(L12/L$4)) | M80: =IF(M$4="","",ABS(M12/M$4)) | N80: =IF(N$4="","",ABS(N12/N$4)) | ... Q80: =IF(Q$4="","",ABS(Q12/Q$4))
B81: Pre-tax Profit | C81: =C13/C4 -> 0.3848278 | G81: =IF(G$4="","",G13/G$4) -> 0.37957429 | H81: =IF(H$4="","",H13/H$4) -> 0.45587935 | I81: =IF(I$4="","",I13/I$4) | J81: =IF(J$4="","",J13/J$4) | K81: =IF(K$4="","",K13/K$4) | L81: =IF(L$4="","",L13/L$4) | M81: =IF(M$4="","",M13/M$4) | N81: =IF(N$4="","",N13/N$4) | ... Q81: =IF(Q$4="","",Q13/Q$4)
B82: Income Tax | C82: =ABS(C14/C$4) -> 0.092358672 | G82: =IF(G$4="","",ABS(G14/G$4)) -> 0.059212778 | H82: =IF(H$4="","",ABS(H14/H$4)) -> 0.072454745 | I82: =IF(I$4="","",ABS(I14/I$4)) | J82: =IF(J$4="","",ABS(J14/J$4)) | K82: =IF(K$4="","",ABS(K14/K$4)) | L82: =IF(L$4="","",ABS(L14/L$4)) | M82: =IF(M$4="","",ABS(M14/M$4)) | N82: =IF(N$4="","",ABS(N14/N$4)) | ... Q82: =IF(Q$4="","",ABS(Q14/Q$4))
B83: =B15 -> NCI’s Share of Profits | C83: =MIN(BS!C62,MAX(G83:K83)) -> 0.002609208 | G83: =IF(G$4="","",-G15/G$4) -> 0 | H83: =IF(H$4="","",-H15/H$4) -> 0.002609208 | I83: =IF(I$4="","",-I15/I$4) | J83: =IF(J$4="","",-J15/J$4) | K83: =IF(K$4="","",-K15/K$4) | L83: =IF(L$4="","",-L15/L$4) | M83: =IF(M$4="","",-M15/M$4) | N83: =IF(N$4="","",-N15/N$4) | ... Q83: =IF(Q$4="","",-Q15/Q$4)
B84: After-tax Profit | C84: =ABS(C16/C$4) -> 0.28985992 | G84: =IF(G$4="","",ABS(G16/G$4)) -> 0.32036151 | H84: =IF(H$4="","",ABS(H16/H$4)) -> 0.3808154 | I84: =IF(I$4="","",ABS(I16/I$4)) | J84: =IF(J$4="","",ABS(J16/J$4)) | K84: =IF(K$4="","",ABS(K16/K$4)) | L84: =IF(L$4="","",ABS(L16/L$4)) | M84: =IF(M$4="","",ABS(M16/M$4)) | N84: =IF(N$4="","",ABS(N16/N$4)) | ... Q84: =IF(Q$4="","",ABS(Q16/Q$4))
B85: WCInv | C85: 0 | E85: =E17 -> WCInv is by default excluded
B86: Net Borrowing | C86: 0 | E86: =E18 -> Net borrowing is excluded
B87: Total FCFE | C87: =ABS(C19/C$4) -> 0.28985992 | G87: =IF(G$4="","",ABS(G19/G$4)) -> 0.32036151 | H87: =IF(H$4="","",ABS(H19/H$4)) -> 0.3808154 | I87: =IF(I$4="","",ABS(I19/I$4)) | J87: =IF(J$4="","",ABS(J19/J$4)) | K87: =IF(K$4="","",ABS(K19/K$4)) | L87: =IF(L$4="","",ABS(L19/L$4)) | M87: =IF(M$4="","",ABS(M19/M$4)) | N87: =IF(N$4="","",ABS(N19/N$4)) | ... Q87: =IF(Q$4="","",ABS(Q19/Q$4))
B89: Dividends
B90: ="Dividend per share ("&Market_currency&")" -> Dividend per share (HKD) | C90: =G90 -> 0.58 | G90: =Data!C64 -> 0.58 | H90: =Data!D64 -> 0.58 | I90: =Data!E64 | J90: =Data!F64 | K90: =Data!G64 | L90: =Data!H64 | M90: =Data!I64 | N90: =Data!J64 | ... Q90: =Data!M64
B91: ="Dividend ("&Market_currency&")" -> Dividend (HKD) | C91: =C90*Common_Shares/$C$3 -> 4739.6904 | G91: =IF(G$4="","",G90*Common_Shares/$C$3) -> 4739.6904 | H91: =IF(H$4="","",H90*Common_Shares/$C$3) -> 4739.6904 | I91: =IF(I$4="","",I90*Common_Shares/$C$3) | J91: =IF(J$4="","",J90*Common_Shares/$C$3) | K91: =IF(K$4="","",K90*Common_Shares/$C$3) | L91: =IF(L$4="","",L90*Common_Shares/$C$3) | M91: =IF(M$4="","",M90*Common_Shares/$C$3) | N91: =IF(N$4="","",N90*Common_Shares/$C$3) | ... Q91: =IF(Q$4="","",Q90*Common_Shares/$C$3)
B92: Payout Ratio | C92: =C90/(C19*$C$3/Common_Shares) -> 1.8655628 | G92: =IF(G$4="","",G90/(G19*$C$3/Common_Shares)) -> 1.6879428 | H92: =IF(H$4="","",H90/(H19*$C$3/Common_Shares)) -> 1.0475686 | I92: =IF(I$4="","",I90/(I19*$C$3/Common_Shares)) | J92: =IF(J$4="","",J90/(J19*$C$3/Common_Shares)) | K92: =IF(K$4="","",K90/(K19*$C$3/Common_Shares)) | L92: =IF(L$4="","",L90/(L19*$C$3/Common_Shares)) | M92: =IF(M$4="","",M90/(M19*$C$3/Common_Shares)) | N92: =IF(N$4="","",N90/(N19*$C$3/Common_Shares)) | ... Q92: =IF(Q$4="","",Q90/(Q19*$C$3/Common_Shares))
B93: Dividend Yield | C93: =C90/Market_Price -> 0.073417722 | G93: =IF(G$4="","",G90/Market_Price) -> 0.073417722 | H93: =IF(H$4="","",H90/Market_Price) -> 0.073417722 | I93: =IF(I$4="","",I90/Market_Price) | J93: =IF(J$4="","",J90/Market_Price) | K93: =IF(K$4="","",K90/Market_Price) | L93: =IF(L$4="","",L90/Market_Price) | M93: =IF(M$4="","",M90/Market_Price) | N93: =IF(N$4="","",N90/Market_Price) | ... Q93: =IF(Q$4="","",Q90/Market_Price)
B95: YoY %
B96: Sales | C96: =C4/G4-1 -> 0 | G96: =IF(H4="","",G4/H4-1) -> -0.26226749 | H96: =IF(I4="","",H4/I4-1) | I96: =IF(J4="","",I4/J4-1) | J96: =IF(K4="","",J4/K4-1) | K96: =IF(L4="","",K4/L4-1) | L96: =IF(M4="","",L4/M4-1) | M96: =IF(N4="","",M4/N4-1) | N96: =IF(O4="","",N4/O4-1) | ... Q96: =IF(R4="","",Q4/R4-1)
B97: Pre-tax Profit | C97: =C13/G13-1 -> 0.013840538 | G97: =IF(H5="","",G13/H13-1) -> -0.38574913 | H97: =IF(I5="","",H13/I13-1) | I97: =IF(J5="","",I13/J13-1) | J97: =IF(K5="","",J13/K13-1) | K97: =IF(L5="","",K13/L13-1) | L97: =IF(M5="","",L13/M13-1) | M97: =IF(N5="","",M13/N13-1) | N97: =IF(O5="","",N13/O13-1) | ... Q97: =IF(R5="","",Q13/R13-1)
B99: Operating Efficiency Analysis | E99: Notes
B100: Balance Sheet | G100: Latest Asset Value
B101: Total Assets | C101: =BS!G32 -> 180996 | G101: =IF(G$4="","",G105+G104) -> 180344 | H101: =IF(H$4="","",H105+H104) -> 174007 | I101: =IF(I$4="","",I105+I104) | J101: =IF(J$4="","",J105+J104) | K101: =IF(K$4="","",K105+K104) | L101: =IF(L$4="","",L105+L104) | M101: =IF(M$4="","",M105+M104) | N101: =IF(N$4="","",N105+N104) | ... Q101: =IF(Q$4="","",Q105+Q104)
B102: Incl. AR | C102: =BS!C4 -> 8029 | G102: =IF(G$4="","",Data!D76) -> 7251 | H102: =IF(H$4="","",Data!E76) | I102: =IF(I$4="","",Data!F76) | J102: =IF(J$4="","",Data!G76) | K102: =IF(K$4="","",Data!H76) | L102: =IF(L$4="","",Data!I76) | M102: =IF(M$4="","",Data!J76) | N102: =IF(N$4="","",Data!K76) | ... Q102: =IF(Q$4="","",Data!N76)
B103: Incl. Inventory | C103: =BS!C6+BS!C7 -> 15310 | G103: =IF(G$4="","",Data!D77) -> 16389 | H103: =IF(H$4="","",Data!E77) | I103: =IF(I$4="","",Data!F77) | J103: =IF(J$4="","",Data!G77) | K103: =IF(K$4="","",Data!H77) | L103: =IF(L$4="","",Data!I77) | M103: =IF(M$4="","",Data!J77) | N103: =IF(N$4="","",Data!K77) | ... Q103: =IF(Q$4="","",Data!N77)
B104: Total Liabilities | C104: =BS!G30 -> 13889 | G104: =Data!C78 -> 14028 | H104: =Data!D78 -> 10902 | I104: =Data!E78 | J104: =Data!F78 | K104: =Data!G78 | L104: =Data!H78 | M104: =Data!I78 | N104: =Data!J78 | ... Q104: =Data!M78
B105: Total Equity | C105: =BS!G27 -> 167107 | G105: =Data!C79 -> 166316 | H105: =Data!D79 -> 163105 | I105: =Data!E79 | J105: =Data!F79 | K105: =Data!G79 | L105: =Data!H79 | M105: =Data!I79 | N105: =Data!J79 | ... Q105: =Data!M79
B107: Operating Asset % of Sales | G107: Latest Asset Value
B108: AR | C108: =C102/C$4 -> 0.91602966 | G108: =IF(G$4="","",G102/G$4) -> 0.82726754 | H108: =IF(H$4="","",H102/H$4) -> #VALUE! | I108: =IF(I$4="","",I102/I$4) | J108: =IF(J$4="","",J102/J$4) | K108: =IF(K$4="","",K102/K$4) | L108: =IF(L$4="","",L102/L$4) | M108: =IF(M$4="","",M102/M$4) | N108: =IF(N$4="","",N102/N$4) | ... Q108: =IF(Q$4="","",Q102/Q$4)
B109: Inventory | C109: =C103/C$4 -> 1.7467199 | G109: =IF(G$4="","",G103/G$4) -> 1.8698232 | H109: =IF(H$4="","",H103/H$4) -> #VALUE! | I109: =IF(I$4="","",I103/I$4) | J109: =IF(J$4="","",J103/J$4) | K109: =IF(K$4="","",K103/K$4) | L109: =IF(L$4="","",L103/L$4) | M109: =IF(M$4="","",M103/M$4) | N109: =IF(N$4="","",N103/N$4) | ... Q109: =IF(Q$4="","",Q103/Q$4)
B110: Properties held for sale | C110: =BS!$G$38/C$4 -> 8.3438677 | G110: =BS!$G$38/G$4 -> 8.3438677
B112: ROE | G112: =IFERROR(IF(#REF!*G114*(1/#REF!)=G116,"","Error"),"") | H112: =IFERROR(IF(#REF!*H114*(1/#REF!)=H116,"","Error"),"") | I112: =IFERROR(IF(#REF!*I114*(1/#REF!)=I116,"","Error"),"") | J112: =IFERROR(IF(#REF!*J114*(1/#REF!)=J116,"","Error"),"") | K112: =IFERROR(IF(#REF!*K114*(1/#REF!)=K116,"","Error"),"") | L112: =IFERROR(IF(#REF!*L114*(1/#REF!)=L116,"","Error"),"") | M112: =IFERROR(IF(#REF!*M114*(1/#REF!)=M116,"","Error"),"") | N112: =IFERROR(IF(#REF!*N114*(1/#REF!)=N116,"","Error"),"") | ... Q112: =IFERROR(IF(#REF!*Q114*(1/#REF!)=Q116,"","Error"),"")
B113: Pre-tax Profit/Sales | C113: =C81 -> 0.3848278 | G113: =G81 -> 0.37957429 | H113: =H81 -> 0.45587935 | I113: =I81 | J113: =J81 | K113: =K81 | L113: =L81 | M113: =M81 | N113: =N81 | ... Q113: =Q81
B114: Sales/Total Assets | C114: =C4/C101 -> 0.048426485 | G114: =IF(G4="","",G4/G101) -> 0.048601561 | H114: =IF(H4="","",H4/H101) -> 0.068278862 | I114: =IF(I4="","",I4/I101) | J114: =IF(J4="","",J4/J101) | K114: =IF(K4="","",K4/K101) | L114: =IF(L4="","",L4/L101) | M114: =IF(M4="","",M4/M101) | N114: =IF(N4="","",N4/N101) | ... Q114: =IF(Q4="","",Q4/Q101)
B115: Total Assets/Equity | C115: =C101/C105 -> 1.0831144 | G115: =IF(G$4="","",G101/G105) -> 1.0843455 | H115: =IF(H$4="","",H101/H105) -> 1.0668404 | I115: =IF(I$4="","",I101/I105) | J115: =IF(J$4="","",J101/J105) | K115: =IF(K$4="","",K101/K105) | L115: =IF(L$4="","",L101/L105) | M115: =IF(M$4="","",M101/M105) | N115: =IF(N$4="","",N101/N105) | ... Q115: =IF(Q$4="","",Q101/Q105)
...

Sheet Valuation_Model
B2: No-Growth DCF Valuation | H2: Notes
B3: No-Growth DCF | C3: =Normalized_FCF!C3 -> 1000000 | E3: Special Assumption
B4: Adjusted FCFE | C4: =Normalized_FCF!C19 -> 2540.6222 | D4: =Reporting_currency -> HKD | E4: Terminal Growth Rate (g): | F4: =Thesis!C75 -> 0
B5: /Equity Cost of Capital | C5: =Thesis!C70 -> 0.09
B6: Stable Income Value | C6: =(C4*(1+Terminal_Growth))/(Equity_Cost-Terminal_Growth) -> 28229.135 | D6: =Reporting_currency -> HKD | E6: Conservative Valuation: Setting g=0 can be a conservative assumption to avoid overestimating the stock’s value, especially if future growth is uncertain or unreliable.
B7: - Interest-bearing Debt | C7: =BS!G31 -> 3093 | D7: =Reporting_currency -> HKD
B8: + Non-operating Cash | C8: =BS!D66 -> 41505.82 | D8: =Reporting_currency -> HKD
B9: + Other Non-operating Assets | C9: =BS!H42 -> 7814.4 | D9: =Reporting_currency -> HKD
B10: Equity Value | C10: =C6-C7+C8+C9 -> 74456.356 | D10: =Reporting_currency -> HKD
B11: * Exchange rate | C11: =Exchange_Rate -> 1 | D11: =Thesis!D17 -> HKD
B12: Equity Value per share | C12: =(C10*C3)/Common_Shares*C11 -> 9.1112885 | D12: =Market_currency -> HKD
B14: Implied Growth Scenario Analysis
B15: FCFE Projection
B16: High Growth Period (HGP) | C16: =Scenarios!C65 -> -0.0073
B17: High Growth Rate (HGR) | C17: =Scenarios!C64 -> 10
B18: Value Per Share | C18: =(F52-C7+C8+C9)*Exchange_Rate/Common_Shares*C3 -> 9.0321281 | D18: =Market_currency -> HKD
B20: Year | C20: FCFE | D20: Growth Rates | E20: Discount Factor | F20: PV of FCFE
B21: 1 | C21: =C4*(1+D21) -> 2522.0756 | D21: =IF($C$17<B21,0,Valuation_Model!$C$16) -> -0.0073 | E21: =IF($C$17<B21,0,1/(1+Equity_Cost)^B21) -> 0.91743119 | F21: =C21*E21 -> 2313.8309
B22: 2 | C22: =IF(ROW()-ROW($C$21)<$C$17, $C$21*(1+D22)^(ROW()-ROW($C$21)), 0) -> 2503.6645 | D22: =IF($C$17<B22,0,Valuation_Model!$C$16) -> -0.0073 | E22: =IF($C$17<B22,0,1/(1+Equity_Cost)^B22) -> 0.84167999 | F22: =C22*E22 -> 2107.2843
B23: 3 | C23: =IF(ROW()-ROW($C$21)<$C$17, $C$21*(1+D23)^(ROW()-ROW($C$21)), 0) -> 2485.3877 | D23: =IF($C$17<B23,0,Valuation_Model!$C$16) -> -0.0073 | E23: =IF($C$17<B23,0,1/(1+Equity_Cost)^B23) -> 0.77218348 | F23: =C23*E23 -> 1919.1754
B24: 4 | C24: =IF(ROW()-ROW($C$21)<$C$17, $C$21*(1+D24)^(ROW()-ROW($C$21)), 0) -> 2467.2444 | D24: =IF($C$17<B24,0,Valuation_Model!$C$16) -> -0.0073 | E24: =IF($C$17<B24,0,1/(1+Equity_Cost)^B24) -> 0.70842521 | F24: =C24*E24 -> 1747.8581
B25: 5 | C25: =IF(ROW()-ROW($C$21)<$C$17, $C$21*(1+D25)^(ROW()-ROW($C$21)), 0) -> 2449.2335 | D25: =IF($C$17<B25,0,Valuation_Model!$C$16) -> -0.0073 | E25: =IF($C$17<B25,0,1/(1+Equity_Cost)^B25) -> 0.64993139 | F25: =C25*E25 -> 1591.8337
B26: 6 | C26: =IF(ROW()-ROW($C$21)<$C$17, $C$21*(1+D26)^(ROW()-ROW($C$21)), 0) -> 2431.3541 | D26: =IF($C$17<B26,0,Valuation_Model!$C$16) -> -0.0073 | E26: =IF($C$17<B26,0,1/(1+Equity_Cost)^B26) -> 0.59626733 | F26: =C26*E26 -> 1449.737
B27: 7 | C27: =IF(ROW()-ROW($C$21)<$C$17, $C$21*(1+D27)^(ROW()-ROW($C$21)), 0) -> 2413.6052 | D27: =IF($C$17<B27,0,Valuation_Model!$C$16) -> -0.0073 | E27: =IF($C$17<B27,0,1/(1+Equity_Cost)^B27) -> 0.54703424 | F27: =C27*E27 -> 1320.3247
B28: 8 | C28: =IF(ROW()-ROW($C$21)<$C$17, $C$21*(1+D28)^(ROW()-ROW($C$21)), 0) -> 2395.9859 | D28: =IF($C$17<B28,0,Valuation_Model!$C$16) -> -0.0073 | E28: =IF($C$17<B28,0,1/(1+Equity_Cost)^B28) -> 0.50186628 | F28: =C28*E28 -> 1202.4645
B29: 9 | C29: =IF(ROW()-ROW($C$21)<$C$17, $C$21*(1+D29)^(ROW()-ROW($C$21)), 0) -> 2378.4952 | D29: =IF($C$17<B29,0,Valuation_Model!$C$16) -> -0.0073 | E29: =IF($C$17<B29,0,1/(1+Equity_Cost)^B29) -> 0.46042778 | F29: =C29*E29 -> 1095.1253
B30: 10 | C30: =IF(ROW()-ROW($C$21)<$C$17, $C$21*(1+D30)^(ROW()-ROW($C$21)), 0) -> 2361.1322 | D30: =IF($C$17<B30,0,Valuation_Model!$C$16) -> -0.0073 | E30: =IF($C$17<B30,0,1/(1+Equity_Cost)^B30) -> 0.42241081 | F30: =C30*E30 -> 997.36776
B31: 11 | C31: =IF(ROW()-ROW($C$21)<$C$17, $C$21*(1+D31)^(ROW()-ROW($C$21)), 0) -> 0 | D31: =IF($C$17<B31,0,Valuation_Model!$C$16) -> 0 | E31: =IF($C$17<B31,0,1/(1+Equity_Cost)^B31) -> 0 | F31: =C31*E31 -> 0
B32: 12 | C32: =IF(ROW()-ROW($C$21)<$C$17, $C$21*(1+D32)^(ROW()-ROW($C$21)), 0) -> 0 | D32: =IF($C$17<B32,0,Valuation_Model!$C$16) -> 0 | E32: =IF($C$17<B32,0,1/(1+Equity_Cost)^B32) -> 0 | F32: =C32*E32 -> 0
B33: 13 | C33: =IF(ROW()-ROW($C$21)<$C$17, $C$21*(1+D33)^(ROW()-ROW($C$21)), 0) -> 0 | D33: =IF($C$17<B33,0,Valuation_Model!$C$16) -> 0 | E33: =IF($C$17<B33,0,1/(1+Equity_Cost)^B33) -> 0 | F33: =C33*E33 -> 0
... B50: 30 | C50: =IF(ROW()-ROW($C$21)<$C$17, $C$21*(1+D50)^(ROW()-ROW($C$21)), 0) -> 0 | D50: =IF($C$17<B50,0,Valuation_Model!$C$16) -> 0 | E50: =IF($C$17<B50,0,1/(1+Equity_Cost)^B50) -> 0 | F50: =C50*E50 -> 0
B51: Terminal Year | C51: =C$21*(1+Terminal_Growth)^$C$17/Equity_Cost -> 28023.063 | D51: =Terminal_Growth -> 0 | E51: =1/(1+Equity_Cost)^C17 -> 0.42241081 | F51: =C51*E51 -> 11837.245
E52: Total PV | F52: =SUM(F21:F51) -> 27582.246
B54: Sensitivity Analysis (Enterprise Value)
A55: =F52 -> 27582.246 | B55: =C78 -> -0.2 | C55: =C77 -> -0.05 | D55: =C76 -> 0 | E55: =C75 -> 0.02 | F55: =C74 -> 0.05
A56: 5 | B56: 20193.593 | C56: 25999.545 | D56: 28229.135 | E56: 29169.389 | F56: 30635.527
A57: 10 | B57: 16230.164 | C57: 24207.81 | D57: 28229.135 | E57: 30120.812 | F57: 33324.021
A58: 15 | B58: 13140.891 | C58: 22409.643 | D58: 28229.135 | E58: 31246.687 | F58: 36765.067
A59: 20 | B59: 11023.755 | C59: 20922.287 | D59: 28229.135 | E59: 32342.61 | F59: 40406.434
A60: 25 | B60: 9624.4797 | C60: 19795.346 | D60: 28229.135 | E60: 33316.212 | F60: 43938.451
A61: 30 | B61: 8710.0886 | C61: 18982.315 | D61: 28229.135 | E61: 34136.51 | F61: 47200.696
B63: Sensitivity Analysis (Equity Value per share)
B64: =B55 -> -0.2 | C64: =C55 -> -0.05 | D64: =D55 -> 0 | E64: =E55 -> 0.02 | F64: =F55 -> 0.05
A65: 0 | B65: =C12 -> 9.1112885 | C65: =C12 -> 9.1112885 | D65: =C12 -> 9.1112885 | E65: =C12 -> 9.1112885 | F65: =C12 -> 9.1112885
A66: =A56 -> 5 | B66: =(B56-$C$7+$C$8+$C$9)/Common_Shares*$C$3*Exchange_Rate -> 8.1279722 | C66: =(C56-$C$7+$C$8+$C$9)/Common_Shares*$C$3*Exchange_Rate -> 8.8384517 | D66: =(D56-$C$7+$C$8+$C$9)/Common_Shares*$C$3*Exchange_Rate -> 9.1112885 | E66: =(E56-$C$7+$C$8+$C$9)/Common_Shares*$C$3*Exchange_Rate -> 9.2263481 | F66: =(F56-$C$7+$C$8+$C$9)/Common_Shares*$C$3*Exchange_Rate -> 9.4057607
A67: =A57 -> 10 | B67: =(B57-$C$7+$C$8+$C$9)/Common_Shares*$C$3*Exchange_Rate -> 7.642964 | C67: =(C57-$C$7+$C$8+$C$9)/Common_Shares*$C$3*Exchange_Rate -> 8.6191955 | D67: =(D57-$C$7+$C$8+$C$9)/Common_Shares*$C$3*Exchange_Rate -> 9.1112885 | E67: =(E57-$C$7+$C$8+$C$9)/Common_Shares*$C$3*Exchange_Rate -> 9.3427746 | F67: =(F57-$C$7+$C$8+$C$9)/Common_Shares*$C$3*Exchange_Rate -> 9.7347541
A68: =A58 -> 15 | B68: =(B58-$C$7+$C$8+$C$9)/Common_Shares*$C$3*Exchange_Rate -> 7.264927 | C68: =(C58-$C$7+$C$8+$C$9)/Common_Shares*$C$3*Exchange_Rate -> 8.3991522 | D68: =(D58-$C$7+$C$8+$C$9)/Common_Shares*$C$3*Exchange_Rate -> 9.1112885 | E68: =(E58-$C$7+$C$8+$C$9)/Common_Shares*$C$3*Exchange_Rate -> 9.4805489 | F68: =(F58-$C$7+$C$8+$C$9)/Common_Shares*$C$3*Exchange_Rate -> 10.155838
A69: =A59 -> 20 | B69: =(B59-$C$7+$C$8+$C$9)/Common_Shares*$C$3*Exchange_Rate -> 7.0058512 | C69: =(C59-$C$7+$C$8+$C$9)/Common_Shares*$C$3*Exchange_Rate -> 8.2171431 | D69: =(D59-$C$7+$C$8+$C$9)/Common_Shares*$C$3*Exchange_Rate -> 9.1112885 | E69: =(E59-$C$7+$C$8+$C$9)/Common_Shares*$C$3*Exchange_Rate -> 9.6146579 | F69: =(F59-$C$7+$C$8+$C$9)/Common_Shares*$C$3*Exchange_Rate -> 10.601435
A70: =A60 -> 25 | B70: =(B60-$C$7+$C$8+$C$9)/Common_Shares*$C$3*Exchange_Rate -> 6.8346207 | C70: =(C60-$C$7+$C$8+$C$9)/Common_Shares*$C$3*Exchange_Rate -> 8.0792384 | D70: =(D60-$C$7+$C$8+$C$9)/Common_Shares*$C$3*Exchange_Rate -> 9.1112885 | E70: =(E60-$C$7+$C$8+$C$9)/Common_Shares*$C$3*Exchange_Rate -> 9.7337985 | F70: =(F60-$C$7+$C$8+$C$9)/Common_Shares*$C$3*Exchange_Rate -> 11.033651
A71: =A61 -> 30 | B71: =(B61-$C$7+$C$8+$C$9)/Common_Shares*$C$3*Exchange_Rate -> 6.7227259 | C71: =(C61-$C$7+$C$8+$C$9)/Common_Shares*$C$3*Exchange_Rate -> 7.9797471 | D71: =(D61-$C$7+$C$8+$C$9)/Common_Shares*$C$3*Exchange_Rate -> 9.1112885 | E71: =(E61-$C$7+$C$8+$C$9)/Common_Shares*$C$3*Exchange_Rate -> 9.834179 | F71: =(F61-$C$7+$C$8+$C$9)/Common_Shares*$C$3*Exchange_Rate -> 11.432855
B73: Scenarios | C73: HGR | D73: HGP | E73: Value per share | F73: Probabilities
B74: =Scenarios!B54 -> Snowball Scenario | C74: =Scenarios!C56 -> 0.05 | D74: =Scenarios!C55 -> 15 | E74: =INDEX(B$65:F$71, MATCH(D74, A$65:A$71, 0), MATCH(C74, B$64:F$64, 0)) -> 10.155838 | F74: =Scenarios!C58 -> 0.05
B75: =Scenarios!B36 -> Optimistic | C75: =Scenarios!C38 -> 0.02 | D75: =Scenarios!C37 -> 10 | E75: =INDEX(B$65:F$71, MATCH(D75, A$65:A$71, 0), MATCH(C75, B$64:F$64, 0)) -> 9.3427746 | F75: =Scenarios!C40*(1-F$74-F$78) -> 0.225
B76: =Scenarios!B24 -> Base | C76: =Scenarios!C26 -> 0 | D76: =Scenarios!C25 -> 10 | E76: =INDEX(B$65:F$71, MATCH(D76, A$65:A$71, 0), MATCH(C76, B$64:F$64, 0)) -> 9.1112885 | F76: =Scenarios!C28*(1-F$74-F$78) -> 0.495
B77: =Scenarios!B30 -> Pessimistic | C77: =Scenarios!C32 -> -0.05 | D77: =Scenarios!C31 -> 10 | E77: =INDEX(B$65:F$71, MATCH(D77, A$65:A$71, 0), MATCH(C77, B$64:F$64, 0)) -> 8.6191955 | F77: =Scenarios!C34*(1-F$74-F$78) -> 0.18
B78: =Scenarios!B48 -> Devil's advocate | C78: =Scenarios!C50 -> -0.2 | D78: =Scenarios!C49 -> 15 | E78: =INDEX(B$65:F$71, MATCH(D78, A$65:A$71, 0), MATCH(C78, B$64:F$64, 0)) -> 7.264927 | F78: =Scenarios!C52 -> 0.05
B80: Note of the formulas: | C80: MATCH(1%, C65:E65, 0) finds the column number for HGR = 1%.
C81: MATCH(5, B66:B69, 0) finds the row number for HGP = 5.
C82: INDEX(C66:E69, ...) retrieves the value from the specified range.

Sheet Scenarios
B2: Current Situation | H2: Warning: Do Not Remove this logic
B3: Selection | H3: 0 | I3: =-Market_Price -> -7.9
B4: Past Years Selected | C4: 3 | E4: Tie the business story into the three levers of value: FCFE, growth and risk. | H4: 1 | I4: =IF(ROW()-3 < $C$76, $C$77, IF(ROW()-3 = $C$76, $C$77 + $C$60, "")) -> 0.58
H5: 2 | I5: =IF(ROW()-3 < $C$76, $C$77, IF(ROW()-3 = $C$76, $C$77 + $C$60, "")) -> 0.58
B6: Latest | C6: =Valuation_Model!C3 -> 1000000 | E6: Prompt for fundamental Analysis | H6: 3 | I6: =IF(ROW()-3 < $C$76, $C$77, IF(ROW()-3 = $C$76, $C$77 + $C$60, "")) -> 9.6147055
B7: EBIT | C7: =Normalized_FCF!G8 -> 2337 | D7: =Reporting_currency -> HKD | E7: ="Please develop three logical "&C18&"-year scenarios (Base Case, Pessimistic Case, Optimistic Case) and two extreme "&C46&"-year scenarios (Success Scenario, Devil’s Advocate Scenario) for "&Thesis!C5&"("&Thesis!D5&"). Each scenario should include the Compound Growth Rate, the Probability Assessment, and the Business Narrative." -> Please develop three logical 10-year scenarios (Base Case, Pessimistic Case, Optimistic Case) and two extreme 15-year scenarios (Success Scenario, Devil’s Advocate Scenario) for SINO LAND(0083.HK). Each scenario should include the Compound Growth Rate, the Probability Assessment, and the Business Narrative. | H7: 4 | I7: =IF(ROW()-3 < $C$76, $C$77, IF(ROW()-3 = $C$76, $C$77 + $C$60, ""))
B8: FCFE | C8: =Normalized_FCF!G19 -> 2807.9686 | D8: =Reporting_currency -> HKD | H8: 5 | I8: =IF(ROW()-3 < $C$76, $C$77, IF(ROW()-3 = $C$76, $C$77 + $C$60, ""))
B9: Normalized | C9: =Normalized_FCF!C19 -> 2540.6222 | D9: =Reporting_currency -> HKD | H9: 6 | I9: =IF(ROW()-3 < $C$76, $C$77, IF(ROW()-3 = $C$76, $C$77 + $C$60, ""))
H10: 7 | I10: =IF(ROW()-3 < $C$76, $C$77, IF(ROW()-3 = $C$76, $C$77 + $C$60, ""))
B11: CAGR | H11: 8 | I11: =IF(ROW()-3 < $C$76, $C$77, IF(ROW()-3 = $C$76, $C$77 + $C$60, ""))
B12: Sales | C12: =(Normalized_FCF!G4/OFFSET(Normalized_FCF!G4, 0, $C$4))^(1/$C$4) - 1 -> #VALUE! | H12: 9 | I12: =IF(ROW()-3 < $C$76, $C$77, IF(ROW()-3 = $C$76, $C$77 + $C$60, ""))
B13: Operating EBIT | C13: =(Normalized_FCF!G8/OFFSET(Normalized_FCF!G8, 0, $C$4))^(1/$C$4) - 1 -> #VALUE! | H13: 10 | I13: =IF(ROW()-3 < $C$76, $C$77, IF(ROW()-3 = $C$76, $C$77 + $C$60, ""))
B14: FCFE | C14: =(Normalized_FCF!G19/OFFSET(Normalized_FCF!G19, 0, $C$4))^(1/$C$4) - 1 -> #VALUE!
B16: General Scenarios
B17: Assumption | E17: Guidance Note
B18: High Growth Period (HGP) | C18: 10 | E18: Fundamental analysis and market signal analysis should be combined, with fundamental analysis given priority and market signal analysis serving as a supplement. Market signal analysis predicts a company's future trend, while fundamental analysis interprets the trend and identifies relevant fundamental factors and possibilities.
B20: Reference
B21: Market Price | C21: =Market_Price -> 7.9 | D21: =Market_currency -> HKD
B22: No Growth Value per share | C22: =Valuation_Model!C12 -> 9.1112885 | D22: =Market_currency -> HKD
B24: Base | E24: Business Story
B25: High Growth Period (HGP) | C25: =C18 -> 10
B26: High Growth Rate (HGR) | C26: 0
B27: Value per share | C27: =Valuation_Model!E76 -> 9.1112885 | D27: =Market_currency -> HKD
B28: Probabilities | C28: 0.55
B30: Pessimistic | E30: Business Story
B31: High Growth Period (HGP) | C31: =C18 -> 10
B32: High Growth Rate (HGR) | C32: -0.05
B33: Value per share | C33: =Valuation_Model!E77 -> 8.6191955 | D33: =Market_currency -> HKD
B34: Probabilities | C34: 0.2
B36: Optimistic | E36: Business Story
B37: High Growth Period (HGP) | C37: =C18 -> 10
B38: High Growth Rate (HGR) | C38: 0.02
B39: Value per share | C39: =Valuation_Model!E75 -> 9.3427746 | D39: =Market_currency -> HKD
B40: Probabilities | C40: =1-C28-C34 -> 0.25
B42: Expected Value = | C42: =C27*C28+C33*C34+C39*C40 -> 9.0707414 | D42: =Market_currency -> HKD
B44: Extreme Scenarios
B45: Assumption
B46: High Growth Period (HGP) | C46: 15
B48: Devil's advocate | E48: Business Story
B49: High Growth Period (HGP) | C49: =C46 -> 15
B50: High Growth Rate (HGR) | C50: -0.2
B51: Value per share | C51: =Valuation_Model!E78 -> 7.264927 | D51: =Market_currency -> HKD
B52: Probabilities | C52: 0.05
B54: Snowball Scenario | E54: Business Story
B55: High Growth Period (HGP) | C55: =C46 -> 15
B56: High Growth Rate (HGR) | C56: 0.05
B57: Value per share | C57: =Valuation_Model!E74 -> 10.155838 | D57: =Market_currency -> HKD
B58: Probabilities | C58: 0.05
B60: Expected Value = | C60: =C51*C52+C57*C58+C42*(1-C52-C58) -> 9.0347055 | D60: =Market_currency -> HKD | E60: is assumed to be materialized in | F60: =Thesis!E20 -> 3
B62: Categorize the investment
B63: Equity Value Driving Factors | E63: Note on Manual Adjustments
B64: High Growth Period (HGP) | C64: 10 | E64: Always use 10yrs to identify the HGR
B65: High Growth Rate (HGR) | C65: -0.0073 | E65: Use Excel Goal Seek to find the HGR
B66: Equity Value per share | C66: =Valuation_Model!C18 -> 9.0321281 | D66: =Market_currency -> HKD | E66: Set to Expected Equity Value
B68: Type of Investment | E68: Note on the logic
B69: Negative Growth | C69: =IF(C60<C22,"Y","N") -> Y
B70: Low Growth | C70: =IF(C69="Y","N",IF(C65>8%,"N","Y")) -> N | E70: >8% is Categorized as High Growth
B71: High Growth | C71: =IF(C65>8%,"Y","N") -> N
B72: Asset Play | C72: =IF(F72>50%,"Y","N") -> Y | E72: The Non-FCF Value is of the Expected Value, at | F72: =BS!D89/C60 -> 0.62612609
B74: Margin of Safety (MOS)
B75: Inputs
B76: Expected Holding Period | C76: =F60 -> 3
B77: Annual Dividend per share | C77: =Normalized_FCF!C90 -> 0.58 | D77: =Market_currency -> HKD
B79: Target Price Output
B80: @Target Annual Return | C80: =Thesis!C121 -> 0.2
B81: PV(Dividends) | C81: =PV(C80, C76, -C77, 0) -> 1.2217593
B82: PV(Equity Value) | C82: =C60/(1+C80)^C76 -> 5.2284175
B83: Buy Below | C83: =C81+C82 -> 6.4501768 | D83: =Market_currency -> HKD | E83: at a MOS of | F83: =(C83/C60-1) -> -0.28606674
B85: Current Return Output
B86: @Market Price | C86: =Market_Price -> 7.9 | D86: =Market_currency -> HKD
B87: Annual Return | C87: =IRR(OFFSET($I$3, 0, 0, $C$76 + 1, 1)) -> 0.11614149
E89: Inputs Legend
E90: Font Color | F90: Fact or Verified Data
E91: Font Color | F91: Subjective Driving Factors
E92: Font Color | F92: Subjective Non-Driving Factors
