Workbook
Name Common_Shares: Thesis!$C$6
Name Equity_Cost: Thesis!$C$86
Name Exchange_Rate: Thesis!$C$16
Name Market_currency: Thesis!$C$13
Name Market_Price: Thesis!$C$12
Name Reporting_currency: Thesis!$C$25
Name scaling_factor: Data!$C$3
Name Terminal_Growth: Thesis!$C$92
Name valuation_method: Thesis!$E$21

Sheet Thesis
B1: Model last updated: | C1: 45730 | D1: INT | E1: Selected: | F1: Y
A2: Executive Summary
B4: Company Information
B5: Company Name | C5: SINO LAND
B6: Number of Shares: | C6: 8171879936
B7: Report Interval: | C7: 12
B8: Update Required After: | C8: =EOMONTH(EDATE(BS!C1,C7+2),0) -> 45900
B10: Listing Information
B11: Symbol: | C11: 0083.HK
B12: Market Price: | C12: 8.15
B13: Market Currency | C13: HKD
B14: Capitalization: | C14: =Thesis!C12*Common_Shares/1000000 -> 66600.821 | D14: =IF(D11="","",Thesis!D12*Common_Shares/1000000)
B15: Forex Symbol: | C15: =IF(C25=C13,C13,C25&"/"&C13) -> HKD | D15: =IF(D11="","",IF(C25=D13,D13,C25&"/"&D13))
B16: Exchange Rate: | C16: 1
B18: Guidance Note: This model determines a target buy price consistent with defined investment criteria. It follows a logical progression: establishing current sustainable earnings, adjusting for financial structure, incorporating growth scenarios, and finally applying the investor’s required return.
B20: Valuation Overview
B21: Growth Classification: | C21: =IF(Scenarios!C69="Y",Scenarios!B69,"")&IF(Scenarios!C70="Y",Scenarios!B70,"")&IF(Scenarios!C71="Y",Scenarios!B71,"")&" "&IF(Scenarios!C72="Y",Scenarios!B72,"") -> Negative Growth Asset Play | D21: Valuation Method | E21: DCF
B22: Comp_Sector: | C22: RES_01 | D22: =IF(valuation_method="DDM","DDM Terminal Value","")
B23: Business Model Risk Premium: | C23: Y
B24: Management Risk Premium: | C24: N
B25: Reporting Currency: | C25: HKD | D25: =IF(D11="","",Market_currency&"/"&D13&":") | E25: =IF(D11="","",1/Exchange_Rate*D16)
B26: ="Expected Equity Value ("&C13&") :" -> Expected Equity Value (HKD) : | C26: =C132 -> 9.3641571 | D26: Market Implied Annual Return: | E26: =Scenarios!C87 -> 0.1155057
B28: Valuation Outputs | C28: =C145&" ("&Market_currency&")" -> 0083.HK (HKD) | D28: =IF(D11="","",D145&" ("&D13&")") | E28: Holding Period | F28: 3
B29: Target Price | C29: =C149 -> 4.6237469 | D29: =D149 | E29: Target return | F29: 0.3674
B30: Entry Price | C30: =C157 -> 6.3792497 | D30: =D157 | E30: Entry yield | F30: 0.2174
B31: Sell Price | C31: =C165 -> 9.0460821 | D31: =D165 | E31: Base equity cost | F31: 0.075
B32: Exit Price | C32: =C173 -> 8.1111667 | D32: =D173 | E32: Benchmark yield | F32: 0.1174
A34: Step 1: Establishing the Company’s Sustainable Earning Power (Calculating Normalized FCFE)
B36: Goal: To quantify the underlying FCFE the business consistently generates for its equity owners, stripping away temporary fluctuations or accounting choices.The FCFE/Market Cap yield gives a direct measure of this cash generation relative to the current market price.
B37: FCFE = (Normalized Operating EBIT + Depreciation & Amortization – Capital Expenditures) + Stable Non-Operating EBIT + Net Interest Income – Taxes – NCI’s Share of Profits – Working Capital Investment
B39: Key Components | C39: =scaling_factor -> 1000000
B40: • Normalized Operating EBIT: Earnings before interest and taxes from core business operations, adjusted to remove one-time or irregular items for a sustainable earnings base.
B41: Normalized Operating EBIT = | C41: =Normalized_FCF!C8 -> 2591.8203 | D41: =Reporting_currency -> HKD
B43: • Depreciation & Amortization (D&A): Non-cash expenses added back to reflect cash generated from operations. • Capital Expenditures (Capex): Cash outflows required to maintain or expand operational assets
B44: D&A = | C44: =Normalized_FCF!C9 -> 160 | D44: =Reporting_currency -> HKD
B45: Capex = | C45: =Normalized_FCF!C10 -> -160 | D45: =Reporting_currency -> HKD
B47: • Stable Non-Operating EBIT: Consistent earnings from non-core assets, such as fixed-income investments, dividend-paying stocks, or rental properties.
B48: Stable Non-Operating EBIT = | C48: =Normalized_FCF!C11 -> 639 | D48: =Reporting_currency -> HKD
B50: • Net Interest Income: Interest income minus interest expense
B51: Operating Interest Income = | C51: =Normalized_FCF!C48 -> 163.69305 | D51: =Reporting_currency -> HKD
B52: Interest Expense = | C52: =Normalized_FCF!C47 -> -43 | D52: =Reporting_currency -> HKD
B53: Net Interest Income = | C53: =Normalized_FCF!C12 -> 120.69305 | D53: =Reporting_currency -> HKD
B55: • NCI’s Share of Profits: NCI represents the portion of a subsidiary’s equity not owned by the parent company.
B56: Est. NCI’s Share of Profits = | C56: =Normalized_FCF!C15 -> -22.869708 | D56: =Reporting_currency -> HKD
B58: • Taxes: Tax = (Normalized Operating EBIT + Stable Non-Operating EBIT + Interest Income – Interest Expense) × Tax Rate
B59: Taxes = | C59: =Normalized_FCF!C14 -> -804.36319 | D59: =Reporting_currency -> HKD
B61: • Working Capital Investment (WCInv): WCInv is only included if it materially distorts FCFE.
B62: WCInv = | C62: =Normalized_FCF!C17 -> 0 | D62: =Reporting_currency -> HKD
B64: Note on Net Borrowing: In theory, principal repayments are accounted for through Net Borrowing. However, this model aims to avoid explicitly forecasting debt issuance or repayments. Instead, principal repayments are reflected in the Equity Value adjustment through interest-bearing debt.
B65: Insight: This step ensures a comprehensive measure of cash flow by incorporating both operating and stable non-operating sources while accounting for taxes and reinvestment needs.
B67: Latest FCFE = | C67: =Normalized_FCF!G19 -> 2772.7921 | D67: =Reporting_currency -> HKD
B68: Normalized FCFE = | C68: =Normalized_FCF!C19 -> 2524.2804 | D68: =Reporting_currency -> HKD
B69: Normalized FCFE/Market Cap = | C69: =Normalized_FCF!C125 -> 0.037901641
B70: Dividend/Market Cap = | C70: =Normalized_FCF!C93 -> 0.071165644 | E70: Payout Ratio: | F70: =Normalized_FCF!C92 -> 1.8776402
B72: DuPont Analysis | C72: Normalized | D72: Latest
B73: ROE = | C73: =Normalized_FCF!C120 -> 0.020056092 | D73: =Normalized_FCF!G120 -> 0.019698708
B74: =Normalized_FCF!B117 -> Pre-tax Profit/Sales | C74: =Normalized_FCF!C117 -> 0.38237459 | D74: =Normalized_FCF!G117 -> 0.37556099
B75: =Normalized_FCF!B118 -> Sales/Total Assets | C75: =Normalized_FCF!C118 -> 0.048426485 | D75: =Normalized_FCF!G118 -> 0.048426485
B76: =Normalized_FCF!B119 -> Total Assets/Equity | C76: =Normalized_FCF!C119 -> 1.0831144 | D76: =Normalized_FCF!G119 -> 1.0831144
A78: Step 2: The No-Growth Baseline (Calculating Stable Income Value)
B80: Goal: To determine the intrinsic value of the company’s equity if the Normalized FCFE (calculated in Step 1) were to remain constant perpetually, with zero future growth. This establishes a baseline value derived solely from the current sustainable earnings power.
B81: Stable Income Value = Normalized FCFE / (Cost of Equity – Terminal Growth Rate)
B83: Key Components
B84: Base Cost of Equity | C84: =F31 -> 0.075
B85: Risk Premium | C85: =IF(C23="Y",1%,0)+IF(C24="Y",1%,0) -> 0.01
B86: Cost of Equity = | C86: =F31+C85 -> 0.085
B88: Note:
B89: Cost of Equity: Cost of Equity reflects the company’s risk profile and represents the minimum return the investor requires for taking on the general risk of owning this type of business, while the target annual return serves as the investor’s hurdle rate.
B90: Terminal Growth Rate: Setting g=0% is a conservative assumption, valuing the company based only on its current demonstrated earning power without relying on potentially optimistic future growth projections.
B92: Terminal Growth Rate (g) = | C92: 0
B93: No Growth SIV Per Share = | C93: =DCF!C6*scaling_factor*Exchange_Rate/Common_Shares -> 3.6340985 | D93: =Market_currency -> HKD
A95: Step 3: Adjusting for Financial Structure (Calculating No Growth Equity Value)
B97: Goal: To refine the Stable Income Value (SIV) by incorporating the company’s balance sheet structure.
B98: Equity Value = Stable Income Value – Total Interest-Bearing Debt + Non-Operating Cash + Other Non-Operating Assets
B100: Key Components
B101: Note on debt: The total interest-bearing debt captures the principal repayments. Ideally, this amount should be discounted based on the repayment schedule. However, for simplicity and conservatism, this model uses the book value of the total interest-bearing debt.
B102: Total Interest-Bearing Debt = | C102: =DCF!C7 -> 3093 | D102: =Reporting_currency -> HKD
B103: Total Interest-Bearing Debt per share = | C103: =C102*scaling_factor*Exchange_Rate/Common_Shares -> 0.37849308 | D103: =Market_currency -> HKD
B104: Debt to Equity Ratio = | C104: =BS!G31/BS!G27 -> 0.018509099
B105: Debt to EBIT Ratio = | C105: =BS!C50 -> 1.1933698
B107: • Non-Operating Cash: Excess cash not required for operations
B108: Total Cash = | C108: =BS!C66 -> 47679 | D108: =Reporting_currency -> HKD
B109: Est. Non-Operating Cash = | C109: =DCF!C8 -> 42222.565 | D109: =Reporting_currency -> HKD
B110: Est. Non-Operating Cash per share = | C110: =C109*scaling_factor*Exchange_Rate/Common_Shares -> 5.1668117 | D110: =Market_currency -> HKD
B112: • Other Non-Operating Assets: Assets not contributing to FCFE (e.g., non-income-generating investments or properties)
B113: Other Non-Operating Assets = | C113: =DCF!C9 -> 7814.4 | D113: =Reporting_currency -> HKD
B114: Other Non-Operating Assets per share = | C114: =C113*scaling_factor*Exchange_Rate/Common_Shares -> 0.95625487 | D114: =Market_currency -> HKD
B116: Insight: The No Growth Equity Value per share represents an estimate of the company’s intrinsic worth based on its current sustainable operations and net financial position, before factoring in any future growth potential. It serves as a fundamentally anchored valuation baseline.
B118: No Growth Equity Value per share = | C118: =IF(valuation_method="DCF",DCF!C12,DDM!C7) -> 9.378672 | D118: =Market_currency -> HKD
B119: Est. Realizable Value | C119: =BS!D47 -> 11.511513 | D119: =Market_currency -> HKD
A121: Step 4: Incorporating Future Potential & Risk (Scenario Analysis)
B123: Goal: To estimate the company’s intrinsic value by considering plausible future scenarios beyond the static no-growth assumption. Based on fundamental research, each scenario defines high growth periods (HGP), high growth rates (HGR), and its probability.
B125: Scenarios | C125: HGR | D125: HGP | E125: EV per share | F125: Probabilities
B126: =DCF!B74 -> Snowball Scenario | C126: =DCF!C74 -> 0.05 | D126: =DCF!D74 -> 15 | E126: =ROUND(IF(valuation_method="DCF",DCF!E74,DDM!E69),2)&" "&Market_currency -> 10.47 HKD | F126: =DCF!F74 -> 0.05
B127: =DCF!B75 -> Optimistic | C127: =DCF!C75 -> 0.02 | D127: =DCF!D75 -> 10 | E127: =ROUND(IF(valuation_method="DCF",DCF!E75,DDM!E70),2)&" "&Market_currency -> 9.62 HKD | F127: =DCF!F75 -> 0.18
B128: =DCF!B76 -> Base | C128: =DCF!C76 -> 0 | D128: =DCF!D76 -> 10 | E128: =ROUND(IF(valuation_method="DCF",DCF!E76,DDM!E71),2)&" "&Market_currency -> 9.38 HKD | F128: =DCF!F76 -> 0.495
B129: =DCF!B77 -> Pessimistic | C129: =DCF!C77 -> -0.02 | D129: =DCF!D77 -> 10 | E129: =ROUND(IF(valuation_method="DCF",DCF!E77,DDM!E72),2)&" "&Market_currency -> 9.16 HKD | F129: =DCF!F77 -> 0.225
B130: =DCF!B78 -> Devil's advocate | C130: =DCF!C78 -> -0.1 | D130: =DCF!D78 -> 15 | E130: =ROUND(IF(valuation_method="DCF",DCF!E78,DDM!E73),2)&" "&Market_currency -> 8.12 HKD | F130: =DCF!F78 -> 0.05
B132: Expected Equity Value = | C132: =Scenarios!C60 -> 9.3641571 | D132: =Market_currency -> HKD
B134: Insight: Significant market volatility is analyzed as an indicator of the range of market-perceived outcomes, including extremes that define boundaries for scenarios like "Snowball" or "Devil’s Advocate." Scenario Analysis then filters these using fundamental reasoning to evaluate their likelihood.
...

Sheet Data
B1: =Thesis!C25 -> HKD | C1: 45473 | D1: =EOMONTH(EDATE(C1,-12),0) -> 45107 | E1: =EOMONTH(EDATE(D1,-12),0) -> 44742 | F1: =EOMONTH(EDATE(E1,-12),0) -> 44377 | G1: =EOMONTH(EDATE(F1,-12),0) -> 44012 | H1: =EOMONTH(EDATE(G1,-12),0) -> 43646 | I1: =EOMONTH(EDATE(H1,-12),0) -> 43281 | J1: =EOMONTH(EDATE(I1,-12),0) -> 42916 | K1: =EOMONTH(EDATE(J1,-12),0) -> 42551 | ... M1: =EOMONTH(EDATE(L1,-12),0) -> 41820
B2: Data (Dirty)
B3: Income Statement | C3: 1000000
B4: Sales | C4: 8765 | D4: 11881 | E4: 15650.563 | F4: 24433.372 | G4: 5887
B5: COGS | C5: 5344 | D5: 6492 | E5: 7482.8818 | F5: 11196.896 | G5: 2437
B6: OPEX | C6: 1084 | D6: 1129 | E6: 867.48328 | F6: 823.28128
B7: Incl. Selling Expenses
B8: R&D
B9: Share of JV or associate Results | C9: 639 | D9: 927
B10: Dividend or Interests from FA
B11: Investment property
B12: Interest Expense | C12: 43 | D12: 40.775368 | E12: 49.197794 | F12: 81.763175
B13: Interest Income | C13: 2340 | D13: 1390.8453 | E13: 337.25969 | F13: 572.18514
B14: Income Tax Paid | C14: 519 | D14: 860.83483 | E14: 1349.1075 | F14: 2530.7695
B15: Reported Net Income | C15: 4251 | D15: 5880 | E15: 5735.3965 | F15: 9646.037
B16: Non-controling Interests | C16: -151 | D16: 31
B18: Cash Flow Statement
B19: D&A | C19: 160 | D19: 198 | E19: 181.018 | F19: 186.147
B20: CAPX | C20: 69 | D20: 108
B21: WCInv | C21: 910 | D21: 2541
B22: CFO
B23: CFI
B24: CFF
B25: ="Dividend per share ("&Market_currency&")" -> Dividend per share (HKD) | C25: 0.58 | D25: 0.58 | E25: 0.57
B27: Balance Sheet | C27: Latest Asset Value
B28: ST AR | C28: =BS!C4 -> 8029 | D28: 7251
B29: ST Inventory | C29: =BS!C6 -> 9844 | D29: 16389
B30: Total Liabilities | C30: =BS!C33+BS!C42 -> 13889 | D30: 10902
B31: Total Equity | C31: =BS!G27 -> 167107 | D31: 163105
B32: Non-common Interest | C32: =BS!G28 -> 519
B34: IS & CF Statements (Clean)
B35: Income Statement
B36: Sales | C36: =IF(C$4="","",C4) -> 8765 | D36: =IF(D$4="","",D4) -> 11881 | E36: =IF(E$4="","",E4) -> 15650.563 | F36: =IF(F$4="","",F4) -> 24433.372 | G36: =IF(G$4="","",G4) -> 5887 | H36: =IF(H$4="","",H4) | I36: =IF(I$4="","",I4) | J36: =IF(J$4="","",J4) | ... M36: =IF(M$4="","",M4)
B37: COGS | C37: =IF(C$4="","",-C5) -> -5344 | D37: =IF(D$4="","",-D5) -> -6492 | E37: =IF(E$4="","",-E5) -> -7482.8818 | F37: =IF(F$4="","",-F5) -> -11196.896 | G37: =IF(G$4="","",-G5) -> -2437 | H37: =IF(H$4="","",-H5) | I37: =IF(I$4="","",-I5) | J37: =IF(J$4="","",-J5) | ... M37: =IF(M$4="","",-M5)
B38: Gross Margin | C38: =IF(C36="","",C36+C37) -> 3421 | D38: =IF(D36="","",D36+D37) -> 5389 | E38: =IF(E36="","",E36+E37) -> 8167.6816 | F38: =IF(F36="","",F36+F37) -> 13236.475 | G38: =IF(G36="","",G36+G37) -> 3450 | H38: =IF(H36="","",H36+H37) | I38: =IF(I36="","",I36+I37) | J38: =IF(J36="","",J36+J37) | ... M38: =IF(M36="","",M36+M37)
B39: OPEX | C39: =IF(C$4="","",-C6) -> -1084 | D39: =IF(D$4="","",-D6) -> -1129 | E39: =IF(E$4="","",-E6) -> -867.48328 | F39: =IF(F$4="","",-F6) -> -823.28128 | G39: =IF(G$4="","",-G6) -> 0 | H39: =IF(H$4="","",-H6) | I39: =IF(I$4="","",-I6) | J39: =IF(J$4="","",-J6) | ... M39: =IF(M$4="","",-M6)
B40: Incl. Selling Expenses | C40: =IF(C$4="","",-C7) -> 0 | D40: =IF(D$4="","",-D7) -> 0 | E40: =IF(E$4="","",-E7) -> 0 | F40: =IF(F$4="","",-F7) -> 0 | G40: =IF(G$4="","",-G7) -> 0 | H40: =IF(H$4="","",-H7) | I40: =IF(I$4="","",-I7) | J40: =IF(J$4="","",-J7) | ... M40: =IF(M$4="","",-M7)
B41: Incl. Other Opex | C41: =IF(C$4="","",C39-C40) -> -1084 | D41: =IF(D$4="","",D39-D40) -> -1129 | E41: =IF(E$4="","",E39-E40) -> -867.48328 | F41: =IF(F$4="","",F39-F40) -> -823.28128 | G41: =IF(G$4="","",G39-G40) -> 0 | H41: =IF(H$4="","",H39-H40) | I41: =IF(I$4="","",I39-I40) | J41: =IF(J$4="","",J39-J40) | ... M41: =IF(M$4="","",M39-M40)
B42: R&D | C42: =IF(C$4="","",-C8) -> 0 | D42: =IF(D$4="","",-D8) -> 0 | E42: =IF(E$4="","",-E8) -> 0 | F42: =IF(F$4="","",-F8) -> 0 | G42: =IF(G$4="","",-G8) -> 0 | H42: =IF(H$4="","",-H8) | I42: =IF(I$4="","",-I8) | J42: =IF(J$4="","",-J8) | ... M42: =IF(M$4="","",-M8)
B43: Operating EBIT | C43: =IF(C$4="","",C38+C39+C42) -> 2337 | D43: =IF(D$4="","",D38+D39+D42) -> 4260 | E43: =IF(E$4="","",E38+E39+E42) -> 7300.1983 | F43: =IF(F$4="","",F38+F39+F42) -> 12413.194 | G43: =IF(G$4="","",G38+G39+G42) -> 3450 | H43: =IF(H$4="","",H38+H39+H42) | I43: =IF(I$4="","",I38+I39+I42) | J43: =IF(J$4="","",J38+J39+J42) | ... M43: =IF(M$4="","",M38+M39+M42)
B44: Non-operating EBIT | C44: =IF(C$4="","",C47-C46-C45-C43) -> 136 | D44: =IF(D$4="","",D47-D46-D45-D43) -> 1130.7649 | E44: =IF(E$4="","",E47-E46-E45-E43) -> -503.75613 | F44: =IF(F$4="","",F47-F46-F45-F43) -> -726.80948 | G44: =IF(G$4="","",G47-G46-G45-G43) -> -3450 | H44: =IF(H$4="","",H47-H46-H45-H43) | I44: =IF(I$4="","",I47-I46-I45-I43) | J44: =IF(J$4="","",J47-J46-J45-J43) | ... M44: =IF(M$4="","",M47-M46-M45-M43)
B45: Net Interest Income | C45: =IF(C$4="","",C51+C52) -> 2297 | D45: =IF(D$4="","",D51+D52) -> 1350.0699 | E45: =IF(E$4="","",E51+E52) -> 288.0619 | F45: =IF(F$4="","",F51+F52) -> 490.42197 | G45: =IF(G$4="","",G51+G52) -> 0 | H45: =IF(H$4="","",H51+H52) | I45: =IF(I$4="","",I51+I52) | J45: =IF(J$4="","",J51+J52) | ... M45: =IF(M$4="","",M51+M52)
B46: Income Tax Paid | C46: =IF(C$4="","",-C14) -> -519 | D46: =IF(D$4="","",-D14) -> -860.83483 | E46: =IF(E$4="","",-E14) -> -1349.1075 | F46: =IF(F$4="","",-F14) -> -2530.7695 | G46: =IF(G$4="","",-G14) -> 0 | H46: =IF(H$4="","",-H14) | I46: =IF(I$4="","",-I14) | J46: =IF(J$4="","",-J14) | ... M46: =IF(M$4="","",-M14)
B47: Reported Net Income | C47: =IF(C$4="","",C15) -> 4251 | D47: =IF(D$4="","",D15) -> 5880 | E47: =IF(E$4="","",E15) -> 5735.3965 | F47: =IF(F$4="","",F15) -> 9646.037 | G47: =IF(G$4="","",G15) -> 0 | H47: =IF(H$4="","",H15) | I47: =IF(I$4="","",I15) | J47: =IF(J$4="","",J15) | ... M47: =IF(M$4="","",M15)
B48: Non-controling Interests | C48: =IF(C$4="","",MIN(-C16,0)) -> 0 | D48: =IF(D$4="","",MIN(-D16,0)) -> -31 | E48: =IF(E$4="","",MIN(-E16,0)) -> 0 | F48: =IF(F$4="","",MIN(-F16,0)) -> 0 | G48: =IF(G$4="","",MIN(-G16,0)) -> 0 | H48: =IF(H$4="","",MIN(-H16,0)) | I48: =IF(I$4="","",MIN(-I16,0)) | J48: =IF(J$4="","",MIN(-J16,0)) | ... M48: =IF(M$4="","",MIN(-M16,0))
B50: Net Interest Income
B51: Interest Expense | C51: =IF(C$4="","",-C12) -> -43 | D51: =IF(D$4="","",-D12) -> -40.775368 | E51: =IF(E$4="","",-E12) -> -49.197794 | F51: =IF(F$4="","",-F12) -> -81.763175 | G51: =IF(G$4="","",-G12) -> 0 | H51: =IF(H$4="","",-H12) | I51: =IF(I$4="","",-I12) | J51: =IF(J$4="","",-J12) | ... M51: =IF(M$4="","",-M12)
B52: Interest Income | C52: =IF(C$4="","",C13) -> 2340 | D52: =IF(D$4="","",D13) -> 1390.8453 | E52: =IF(E$4="","",E13) -> 337.25969 | F52: =IF(F$4="","",F13) -> 572.18514 | G52: =IF(G$4="","",G13) -> 0 | H52: =IF(H$4="","",H13) | I52: =IF(I$4="","",I13) | J52: =IF(J$4="","",J13) | ... M52: =IF(M$4="","",M13)
B54: Non-operating EBIT
B55: Share of JV or associate Results | C55: =IF(C$4="","",C9) -> 639 | D55: =IF(D$4="","",D9) -> 927 | E55: =IF(E$4="","",E9) -> 0 | F55: =IF(F$4="","",F9) -> 0 | G55: =IF(G$4="","",G9) -> 0 | H55: =IF(H$4="","",H9) | I55: =IF(I$4="","",I9) | J55: =IF(J$4="","",J9) | ... M55: =IF(M$4="","",M9)
B56: Dividend or Interests from FA | C56: =IF(C$4="","",C10) -> 0 | D56: =IF(D$4="","",D10) -> 0 | E56: =IF(E$4="","",E10) -> 0 | F56: =IF(F$4="","",F10) -> 0 | G56: =IF(G$4="","",G10) -> 0 | H56: =IF(H$4="","",H10) | I56: =IF(I$4="","",I10) | J56: =IF(J$4="","",J10) | ... M56: =IF(M$4="","",M10)
B57: Investment property | C57: =IF(C$4="","",C11) -> 0 | D57: =IF(D$4="","",D11) -> 0 | E57: =IF(E$4="","",E11) -> 0 | F57: =IF(F$4="","",F11) -> 0 | G57: =IF(G$4="","",G11) -> 0 | H57: =IF(H$4="","",H11) | I57: =IF(I$4="","",I11) | J57: =IF(J$4="","",J11) | ... M57: =IF(M$4="","",M11)
B58: Other Non-operating Income | C58: =IF(C$4="","",C44-C55-C56-C57) -> -503 | D58: =IF(D$4="","",D44-D55-D56-D57) -> 203.76489 | E58: =IF(E$4="","",E44-E55-E56-E57) -> -503.75613 | F58: =IF(F$4="","",F44-F55-F56-F57) -> -726.80948 | G58: =IF(G$4="","",G44-G55-G56-G57) -> -3450 | H58: =IF(H$4="","",H44-H55-H56-H57) | I58: =IF(I$4="","",I44-I55-I56-I57) | J58: =IF(J$4="","",J44-J55-J56-J57) | ... M58: =IF(M$4="","",M44-M55-M56-M57)
B60: Cash Flow Statement
B61: D&A | C61: =IF(C$4="","",-C19) -> -160 | D61: =IF(D$4="","",-D19) -> -198 | E61: =IF(E$4="","",-E19) -> -181.018 | F61: =IF(F$4="","",-F19) -> -186.147 | G61: =IF(G$4="","",-G19) -> 0 | H61: =IF(H$4="","",-H19) | I61: =IF(I$4="","",-I19) | J61: =IF(J$4="","",-J19) | ... M61: =IF(M$4="","",-M19)
B62: CAPX | C62: =IF(C$4="","",IF(C20=0,C61,-C20)) -> -69 | D62: =IF(D$4="","",IF(D20=0,D61,-D20)) -> -108 | E62: =IF(E$4="","",IF(E20=0,E61,-E20)) -> -181.018 | F62: =IF(F$4="","",IF(F20=0,F61,-F20)) -> -186.147 | G62: =IF(G$4="","",IF(G20=0,G61,-G20)) -> 0 | H62: =IF(H$4="","",IF(H20=0,H61,-H20)) | I62: =IF(I$4="","",IF(I20=0,I61,-I20)) | J62: =IF(J$4="","",IF(J20=0,J61,-J20)) | ... M62: =IF(M$4="","",IF(M20=0,M61,-M20))
B63: WCInv | C63: =IF(C$4="","",-C21) -> -910 | D63: =IF(D$4="","",-D21) -> -2541 | E63: =IF(E$4="","",-E21) -> 0 | F63: =IF(F$4="","",-F21) -> 0 | G63: =IF(G$4="","",-G21) -> 0 | H63: =IF(H$4="","",-H21) | I63: =IF(I$4="","",-I21) | J63: =IF(J$4="","",-J21) | ... M63: =IF(M$4="","",-M21)
B64: Net Change in Cash | C64: =IF(C$4="","",C22+C23+C24) -> 0 | D64: =IF(D$4="","",D22+D23+D24) -> 0 | E64: =IF(E$4="","",E22+E23+E24) -> 0 | F64: =IF(F$4="","",F22+F23+F24) -> 0 | G64: =IF(G$4="","",G22+G23+G24) -> 0 | H64: =IF(H$4="","",H22+H23+H24) | I64: =IF(I$4="","",I22+I23+I24) | J64: =IF(J$4="","",J22+J23+J24) | ... M64: =IF(M$4="","",M22+M23+M24)
B65: Dividend per share | C65: =IF(C$4="","",C25) -> 0.58 | D65: =IF(D$4="","",D25) -> 0.58 | E65: =IF(E$4="","",E25) -> 0.57 | F65: =IF(F$4="","",F25) -> 0 | G65: =IF(G$4="","",G25) -> 0 | H65: =IF(H$4="","",H25) | I65: =IF(I$4="","",I25) | J65: =IF(J$4="","",J25) | ... M65: =IF(M$4="","",M25)
B67: YoY %
B68: =B36 -> Sales | C68: =IF(D$36="","",C36/D36-1) -> -0.26226749 | D68: =IF(E$36="","",D36/E36-1) -> -0.240858 | E68: =IF(F$36="","",E36/F36-1) -> -0.35945953 | F68: =IF(G$36="","",F36/G36-1) -> 3.1503944 | G68: =IF(H$36="","",G36/H36-1) | H68: =IF(I$36="","",H36/I36-1) | I68: =IF(J$36="","",I36/J36-1) | J68: =IF(K$36="","",J36/K36-1) | ... M68: =IF(N$36="","",M36/N36-1)
B69: Gross Margin | C69: =IF(D$36="","",C38/D38-1) -> -0.36518835 | D69: =IF(E$36="","",D38/E38-1) -> -0.34020444 | E69: =IF(F$36="","",E38/F38-1) -> -0.38294135 | F69: =IF(G$36="","",F38/G38-1) -> 2.8366595 | G69: =IF(H$36="","",G38/H38-1) | H69: =IF(I$36="","",H38/I38-1) | I69: =IF(J$36="","",I38/J38-1) | J69: =IF(K$36="","",J38/K38-1) | ... M69: =IF(N$36="","",M38/N38-1)
B70: =B43 -> Operating EBIT | C70: =IF(D$36="","",C43/D43-1) -> -0.45140845 | D70: =IF(E$36="","",D43/E43-1) -> -0.41645421 | E70: =IF(F$36="","",E43/F43-1) -> -0.41190009 | F70: =IF(G$36="","",F43/G43-1) -> 2.5980273 | G70: =IF(H$36="","",G43/H43-1) | H70: =IF(I$36="","",H43/I43-1) | I70: =IF(J$36="","",I43/J43-1) | J70: =IF(K$36="","",J43/K43-1) | ... M70: =IF(N$36="","",M43/N43-1)
B71: Non-operating EBIT | C71: =IF(D$36="","",C44/D44-1) -> -0.87972743 | D71: =IF(E$36="","",D44/E44-1) -> -3.2446673 | E71: =IF(F$36="","",E44/F44-1) -> -0.30689384 | F71: =IF(G$36="","",F44/G44-1) -> -0.78933058 | G71: =IF(H$36="","",G44/H44-1) | H71: =IF(I$36="","",H44/I44-1) | I71: =IF(J$36="","",I44/J44-1) | J71: =IF(K$36="","",J44/K44-1) | ... M71: =IF(N$36="","",M44/N44-1)
B72: =B47 -> Reported Net Income | C72: =IF(D$36="","",C47/D47-1) -> -0.27704082 | D72: =IF(E$36="","",D47/E47-1) -> 0.025212459 | E72: =IF(F$36="","",E47/F47-1) -> -0.40541421 | F72: =IF(G$36="","",F47/G47-1) -> #DIV/0! | G72: =IF(H$36="","",G47/H47-1) | H72: =IF(I$36="","",H47/I47-1) | I72: =IF(J$36="","",I47/J47-1) | J72: =IF(K$36="","",J47/K47-1) | ... M72: =IF(N$36="","",M47/N47-1)
B74: Balance Sheet (Clean)
B75: Balance Sheet
B76: Total Assets | C76: =IF(C$4="","",C79+C80) -> 180996 | D76: =IF(D$4="","",D79+D80) -> 174007 | E76: =IF(E$4="","",E79+E80) -> 0 | F76: =IF(F$4="","",F79+F80) -> 0 | G76: =IF(G$4="","",G79+G80) -> 0 | H76: =IF(H$4="","",H79+H80) | I76: =IF(I$4="","",I79+I80) | J76: =IF(J$4="","",J79+J80) | ... M76: =IF(M$4="","",M79+M80)
B77: Incl. ST AR | C77: =IF(C$4="","",C28) -> 8029 | D77: =IF(D$4="","",D28) -> 7251 | E77: =IF(E$4="","",E28) -> 0 | F77: =IF(F$4="","",F28) -> 0 | G77: =IF(G$4="","",G28) -> 0 | H77: =IF(H$4="","",H28)
B78: Incl. ST Inventory | C78: =IF(C$4="","",C29) -> 9844 | D78: =IF(D$4="","",D29) -> 16389 | E78: =IF(E$4="","",E29) -> 0 | F78: =IF(F$4="","",F29) -> 0 | G78: =IF(G$4="","",G29) -> 0 | H78: =IF(H$4="","",H29)
B79: Total Liabilities | C79: =IF(C$4="","",C30) -> 13889 | D79: =IF(D$4="","",D30) -> 10902 | E79: =IF(E$4="","",E30) -> 0 | F79: =IF(F$4="","",F30) -> 0 | G79: =IF(G$4="","",G30) -> 0 | H79: =IF(H$4="","",H30) | I79: =IF(I$4="","",I30) | J79: =IF(J$4="","",J30) | ... M79: =IF(M$4="","",M30)
B80: Total Equity | C80: =IF(C$4="","",C31) -> 167107 | D80: =IF(D$4="","",D31) -> 163105 | E80: =IF(E$4="","",E31) -> 0 | F80: =IF(F$4="","",F31) -> 0 | G80: =IF(G$4="","",G31) -> 0 | H80: =IF(H$4="","",H31) | I80: =IF(I$4="","",I31) | J80: =IF(J$4="","",J31) | ... M80: =IF(M$4="","",M31)

Sheet BS
B1: Most Recent Quarter | C1: 45473 | F1: =IF(MONTH(C1)=MONTH(Normalized_FCF!G1),"FY","Quarter")&" Report" -> FY Report | H1: =scaling_factor -> 1000000
B2: Lastest Balance Sheet
B3: ST Operating Assets | C3: Book | D3: Valued @ | F3: ST Non-Operating Assets | G3: Book | H3: Valued @
B4: ST AR | C4: 8029 | D4: 0.6 | F4: Cash and cash equivalents | G4: 45665 | H4: 0.9
B5: Operating ST Financial Assets | C5: 0 | D5: 0.6 | F5: Restricted cash | G5: 2014 | H5: 0.7
B6: Inventory | C6: 9844 | D6: 0.5 | F6: Securities with stable income | G6: 156 | H6: 0.6
B7: Properties held for sale | C7: 5466 | D7: 0.6 | F7: Other Securities | G7: 0 | H7: 0.6
B8: Properties held for income | C8: 0 | D8: 0.6 | F8: Properties with stable income | G8: 0 | H8: 0.6
B9: Prepayments and Contract Assets | C9: 0 | D9: 0.1 | F9: Other Properties | G9: 0 | H9: 0.6
B10: ST DTA | C10: 10 | D10: 0.9
B11: Other ST Assets | C11: 0 | D11: 0.05
B12: Operating ST Assets | C12: =SUM(C4:C11) -> 23349 | D12: =C4*D4+C5*D5+C9*D9+C6*D6+C8*D8+C7*D7+C10*D10+C11*D11 -> 13028 | F12: Non-Operating ST Assets | G12: =SUM(G4:G9) -> 47835 | H12: =G4*H4+G5*H5+G6*H6+G7*H7+G8*H8+G9*H9 -> 42601.9
B14: LT Operating Assets | C14: Book | D14: Valued @ | F14: LT Non-Operating Assets | G14: Book | H14: Valued @
B15: LT AR | C15: 2757 | D15: 0.4 | F15: LT Depositis | G15: 0 | H15: 0.8
B16: Operating LT Financial Assets | C16: 0 | D16: 0.5 | F16: Securities with stable income | G16: 1373 | H16: 0.6
B17: Properties held for sale | C17: 67668 | D17: 0.6 | F17: Other Securities | G17: 13024 | H17: 0.6
B18: Properties held for income | C18: 0 | D18: 0.6 | F18: JV or associate with stable income | G18: 23696 | H18: 0.1
B19: PP&E & Right of Use Assets | C19: 1284 | D19: 0.1 | F19: Other JV or associate | G19: 0 | H19: 0.1
B20: Biological assets | C20: 0 | D20: 0.05 | F20: Properties with stable income | G20: 0 | H20: 0.2
B21: Intangible assets | C21: 0 | D21: 0.05 | F21: Other Properties | G21: 0 | H21: 0.1
B22: LT DTA | C22: 10 | D22: 0.9
B23: Other assets & Goodwill | C23: 0 | D23: 0
B24: Operating LT Assets | C24: =SUM(C15:C23) -> 71719 | D24: =C15*D15+C16*D16+C18*D18+C17*D17+C19*D19+C20*D20+C21*D21+C22*D22+C23*D23 -> 41841 | F24: Non-Operating LT Assets | G24: =SUM(G15:G21) -> 38093 | H24: =G15*H15+G16*H16+G17*H17+G18*H18+G19*H19+G20*H20+G21*H21 -> 11007.8
B26: ST Liabilities | C26: Book | F26: BS Summary | G26: Book | H26: Valued @
B27: ST Borrowing | C27: 967 | F27: Total Equity | G27: =G32-G30 -> 167107 | H27: =H32-G30 -> 94589.7
B28: ST Lease liabilities | C28: 37 | F28: Incl. Minority Interest (NCI) | G28: 519
B29: ST SH Loan | C29: 0 | F29: Incl. Common Equity | G29: =G27-G28 -> 166588 | H29: =H27-G28 -> 94070.7
B30: ST Financial Liabilities | C30: 0 | F30: Total Liabilities | G30: =C33+C42 -> 13889
B31: ST Interest-bearing Debt | C31: =SUM(C27:C30) -> 1004 | F31: incl. Interest-bearing Debt | G31: =C31+C40 -> 3093
B32: Other ST liabilities | C32: =C33-C31 -> 8048 | F32: Total Assets | G32: =G35+G40 -> 180996 | H32: =H35+H40 -> 108478.7
B33: Current Liabilities | C33: 9052
F34: Assets Summary | G34: Book | H34: Valued @
B35: LT Liabilities | C35: Book | F35: Operating Assets | G35: =C12+C24 -> 95068 | H35: =D12+D24 -> 54869
B36: LT Borrowing | C36: 832 | F36: incl. AR | G36: =C4+C15 -> 10786
B37: LT Lease liabilities | C37: 27 | F37: incl. inventory | G37: =C6 -> 9844
B38: LT SH Loan | C38: 1230 | F38: incl. Properties held for sale | G38: =C7+C17 -> 73134
B39: LT Financial Liabilities | C39: 0 | F39: incl. Fixed Assets | G39: =C7+C17+C19+C20 -> 74418 | H39: =C7*D7+C17*D17+C19*D19+C20*D20 -> 44008.8
B40: LT Interest-bearing Debt | C40: =SUM(C36:C39) -> 2089 | F40: Non-operating Assets | G40: =G12+G24 -> 85928 | H40: =H12+H24 -> 53609.7
B41: Other LT liabilities | C41: =C42-C40 -> 2748 | F41: incl. Assets with stable income | G41: =C70 -> 72904 | H41: =H40-H42 -> 45795.3
B42: Noncurrent Liabilities | C42: 4837 | F42: incl. Other Assets | G42: =C82 -> 13024 | H42: =D82 -> 7814.4
B44: Balance Sheet Analysis
B45: Asset Value Stress Test | C45: Book | D45: Est. Realizable Value | F45: Notes
B46: Equity | C46: =G29 -> 166588 | D46: =H29 -> 94070.7
B47: ="Equity per share ("&Market_currency&")" -> Equity per share (HKD) | C47: =C46*H1/Common_Shares*Exchange_Rate -> 20.385517 | D47: =D46*H1/Common_Shares*Exchange_Rate -> 11.511513
B49: Leverage % | C49: Normalized | D49: Latest
B50: Debt/EBIT | C50: =G31/Normalized_FCF!C8 -> 1.1933698 | D50: =G31/Normalized_FCF!G8 -> 1.3234917
B51: Common Equity/Total Asset | D51: =G29/G32 -> 0.92039603
B53: Profibility % | C53: Normalized | D53: Latest
B54: Operating Asset Yield | C54: =Normalized_FCF!C8/G35 -> 0.027262804 | D54: =Normalized_FCF!G8/G35 -> 0.024582404
B55: Non-Operating Asset Yield | C55: =Normalized_FCF!C11/G40 -> 0.0074364584 | D55: =Normalized_FCF!G11/G40 -> 0.0074364584
B57: Reinvestment % | C57: Normalized | D57: Latest
B58: D&A/Fixed Assets | D58: =Normalized_FCF!G9/BS!$G$39 -> 0.0021500175
B59: Fixed Assets/Total Assets | D59: =G39/G32 -> 0.41115826
B61: NCI % | C61: Estimate | D61: Latest
B62: Est. of NCI Ownership Percentage | C62: =IF(G28<=0,0,G28/G29) -> 0.0031154705 | D62: =G28/G29 -> 0.0031154705 | F62: Rough Estimate only
B64: Non-operating Assets Analysis
B65: Non-operating Assets with stable income | C65: Book | D65: Non-Operating | F65: Notes
B66: Cash | C66: =G4+G5+G15 -> 47679 | D66: =C66-D75 -> 42222.565 | F66: Non-Operating Cash is the Excess cash not required for operations
B67: Securities with stable income | C67: =G6+G16 -> 1529
B68: JV or associate with stable income | C68: =G18 -> 23696
B69: Properties with stable income | C69: =G8+G20 -> 0
B70: Non-operating Assets with stable income | C70: =SUM(C66:C69) -> 72904
B72: Cash Management Analysis | C72: Latest | D72: Normalized
B73: Monthly Operating Expenses | C73: =(Normalized_FCF!G25+Normalized_FCF!G35-Normalized_FCF!G91)/12 -> -930.64086 | D73: =(Normalized_FCF!C25+Normalized_FCF!C35-Normalized_FCF!C91)/12 -> -909.40584 | F73: Variable + Fixed Costs & Dividends
B74: Operating Expenses Multiple (months) | C74: =-$C$66/C73 -> 51.232438 | D74: =-$C$66/D73 -> 52.428737 | F74: Companies typically need cash to cover 1 to 2 months of operating expenses
B75: Operating Cash Requirement | D75: =MAX(-D73*D76,G5) -> 5456.4351 | F75: 1x for stable businesses, 2x for for volatile ones, 6x for cash hoarders
B76: Operating Cash Multiple (months) | D76: =IF(D74<=3,1,IF(D74>18,6,2)) -> 6 | F76: Rough Estimate
B78: Other Non-operating Assets | C78: Book | D78: Valued @
B79: Other Securities | C79: =G7+G17 -> 13024 | D79: =G7*H7+G17*H17 -> 7814.4
B80: Other JV or associate | C80: =G19 -> 0 | D80: =G19*H19 -> 0
B81: Other Properties | C81: =G9+G21 -> 0 | D81: =G9*H9+G21*H21 -> 0
B82: Other Non-operating Assets | C82: =SUM(C79:C81) -> 13024 | D82: =SUM(D79:D81) -> 7814.4
B84: Non-FCF Value of the Equity Value
B85: Non-FCF Value | D85: Per-Share
B86: Interest-bearing Debt | C86: =-DCF!C7*Exchange_Rate -> -3093 | D86: =C86*scaling_factor/Common_Shares -> -0.37849308 | E86: =Market_currency -> HKD
B87: Non-operating Cash | C87: =DCF!C8*Exchange_Rate -> 42222.565 | D87: =C87*scaling_factor/Common_Shares -> 5.1668117 | E87: =Market_currency -> HKD
B88: Other Non-operating Assets | C88: =DCF!C9*Exchange_Rate -> 7814.4 | D88: =C88*scaling_factor/Common_Shares -> 0.95625487 | E88: =Market_currency -> HKD
B89: Total Non-FCF Value | C89: =SUM(C86:C88) -> 46943.965 | D89: =SUM(D86:D88) -> 5.7445735 | E89: =Market_currency -> HKD

Sheet Normalized_FCF
B1: =Thesis!C25 -> HKD | C1: Normalized | G1: =Data!C1 -> 45473 | H1: =EOMONTH(EDATE(G1,-12),0) -> 45107 | I1: =EOMONTH(EDATE(H1,-12),0) -> 44742 | J1: =EOMONTH(EDATE(I1,-12),0) -> 44377 | K1: =EOMONTH(EDATE(J1,-12),0) -> 44012 | L1: =EOMONTH(EDATE(K1,-12),0) -> 43646 | M1: =EOMONTH(EDATE(L1,-12),0) -> 43281 | N1: =EOMONTH(EDATE(M1,-12),0) -> 42916 | O1: =EOMONTH(EDATE(N1,-12),0) -> 42551 | ... Q1: =EOMONTH(EDATE(P1,-12),0) -> 41820
B2: FCFE Analysis | E2: Notes
B3: FCFE | C3: =scaling_factor -> 1000000
B4: Sales | C4: =G4 -> 8765 | G4: =Data!C36 -> 8765 | H4: =Data!D36 -> 11881 | I4: =Data!E36 -> 15650.563 | J4: =Data!F36 -> 24433.372 | K4: =Data!G36 -> 5887 | L4: =Data!H36 | M4: =Data!I36 | N4: =Data!J36 | ... Q4: =Data!M36
B5: Variable Costs | C5: =C25 -> -5066.6797 | G5: =G25 -> -5344 | H5: =H25 -> -6492 | I5: =I25 -> -7482.8818 | J5: =J25 -> -11196.896 | K5: =K25 -> -2437 | L5: =L25 | M5: =M25 | N5: =N25 | ... Q5: =Q25
B6: Contribution Margin | C6: =C4+C5 -> 3698.3203 | G6: =IF(G4="","",G4+G5) -> 3421 | H6: =IF(H4="","",H4+H5) -> 5389 | I6: =IF(I4="","",I4+I5) -> 8167.6816 | J6: =IF(J4="","",J4+J5) -> 13236.475 | K6: =IF(K4="","",K4+K5) -> 3450 | L6: =IF(L4="","",L4+L5) | M6: =IF(M4="","",M4+M5) | N6: =IF(N4="","",N4+N5) | ... Q6: =IF(Q4="","",Q4+Q5)
B7: Fixed Costs | C7: =C35 -> -1106.5 | G7: =G35 -> -1084 | H7: =H35 -> -1129 | I7: =I35 -> -867.48328 | J7: =J35 -> -823.28128 | K7: =K35 -> 0 | L7: =L35 | M7: =M35 | N7: =N35 | ... Q7: =Q35
B8: Operating EBIT | C8: =C6+C7 -> 2591.8203 | G8: =IF(G$4="","",G6+G7) -> 2337 | H8: =IF(H$4="","",H6+H7) -> 4260 | I8: =IF(I$4="","",I6+I7) -> 7300.1983 | J8: =IF(J$4="","",J6+J7) -> 12413.194 | K8: =IF(K$4="","",K6+K7) -> 3450 | L8: =IF(L$4="","",L6+L7) | M8: =IF(M$4="","",M6+M7) | N8: =IF(N$4="","",N6+N7) | ... Q8: =IF(Q$4="","",Q6+Q7)
B9: Add Back D&A | C9: =BS!$G$39*BS!D58 -> 160 | G9: =IF(Data!C61="","",-Data!C61) -> 160 | H9: =IF(Data!D61="","",-Data!D61) -> 198 | I9: =IF(Data!E61="","",-Data!E61) -> 181.018 | J9: =IF(Data!F61="","",-Data!F61) -> 186.147 | K9: =IF(Data!G61="","",-Data!G61) -> 0 | L9: =IF(Data!H61="","",-Data!H61) | M9: =IF(Data!I61="","",-Data!I61) | N9: =IF(Data!J61="","",-Data!J61) | ... Q9: =IF(Data!M61="","",-Data!M61)
B10: Maintenance Capex | C10: =-C4*C78 -> -160 | G10: =Data!C62 -> -69 | H10: =Data!D62 -> -108 | I10: =Data!E62 -> -181.018 | J10: =Data!F62 -> -186.147 | K10: =Data!G62 -> 0 | L10: =Data!H62 | M10: =Data!I62 | N10: =Data!J62 | ... Q10: =Data!M62
B11: Stable Non-Operating EBIT | C11: =C63 -> 639 | G11: =G61 -> 639 | H11: =H61 -> 927 | I11: =I61 -> 0 | J11: =J61 -> 0 | K11: =K61 -> 0 | L11: =L61 | M11: =M61 | N11: =N61 | ... Q11: =Q61
B12: Net Interest Income | C12: =C50 -> 120.69305 | G12: =G50 -> 224.79207 | H12: =H50 -> 118.39444 | I12: =I50 -> -10.601439 | J12: =J50 -> -16.281704 | K12: =K50 -> 0 | L12: =L50 | M12: =M50 | N12: =N50 | ... Q12: =Q50
B13: Pre-tax Profit | C13: =SUM(C8:C12) -> 3351.5133 | G13: =IF(G$4="","",SUM(G8:G12)) -> 3291.7921 | H13: =IF(H$4="","",SUM(H8:H12)) -> 5395.3944 | I13: =IF(I$4="","",SUM(I8:I12)) -> 7289.5968 | J13: =IF(J$4="","",SUM(J8:J12)) -> 12396.912 | K13: =IF(K$4="","",SUM(K8:K12)) -> 3450 | L13: =IF(L$4="","",SUM(L8:L12)) | M13: =IF(M$4="","",SUM(M8:M12)) | N13: =IF(N$4="","",SUM(N8:N12)) | ... Q13: =IF(Q$4="","",SUM(Q8:Q12))
B14: Income Tax | C14: =-SUM(C8+C11,C12)*C43 -> -804.36319 | G14: =Data!C46 -> -519 | H14: =Data!D46 -> -860.83483 | I14: =Data!E46 -> -1349.1075 | J14: =Data!F46 -> -2530.7695 | K14: =Data!G46 -> 0 | L14: =Data!H46 | M14: =Data!I46 | N14: =Data!J46 | ... Q14: =Data!M46
B15: NCI’s Share of Profits | C15: =-C4*C83 -> -22.869708 | G15: =Data!C48 -> 0 | H15: =Data!D48 -> -31 | I15: =Data!E48 -> 0 | J15: =Data!F48 -> 0 | K15: =Data!G48 -> 0 | L15: =Data!H48 | M15: =Data!I48 | N15: =Data!J48 | ... Q15: =Data!M48
B16: After-tax Profit | C16: =SUM(C13:C15) -> 2524.2804 | G16: =IF(G$4="","",SUM(G13:G15)) -> 2772.7921 | H16: =IF(H$4="","",SUM(H13:H15)) -> 4503.5596 | I16: =IF(I$4="","",SUM(I13:I15)) -> 5940.4893 | J16: =IF(J$4="","",SUM(J13:J15)) -> 9866.1428 | K16: =IF(K$4="","",SUM(K13:K15)) -> 3450 | L16: =IF(L$4="","",SUM(L13:L15)) | M16: =IF(M$4="","",SUM(M13:M15)) | N16: =IF(N$4="","",SUM(N13:N15)) | ... Q16: =IF(Q$4="","",SUM(Q13:Q15))
B17: WCInv | C17: =-C4*C85 -> 0 | E17: WCInv is by default excluded
B18: Net Borrowing | C18: 0 | E18: Net borrowing is excluded
B19: FCFE | C19: =C16+C17 -> 2524.2804 | G19: =IF(G$4="","",G16+G17) -> 2772.7921 | H19: =IF(H$4="","",H16+H17) -> 4503.5596 | I19: =IF(I$4="","",I16+I17) -> 5940.4893 | J19: =IF(J$4="","",J16+J17) -> 9866.1428 | K19: =IF(K$4="","",K16+K17) -> 3450 | L19: =IF(L$4="","",L16+L17) | M19: =IF(M$4="","",M16+M17) | N19: =IF(N$4="","",N16+N17) | ... Q19: =IF(Q$4="","",Q16+Q17)
B21: Operating Cost Structure | E21: Notes
B22: Variable Costs
B23: COGS | C23: =-C4*C28 -> -5066.6797 | G23: =Data!C37 -> -5344 | H23: =Data!D37 -> -6492 | I23: =Data!E37 -> -7482.8818 | J23: =Data!F37 -> -11196.896 | K23: =Data!G37 -> -2437 | L23: =Data!H37 | M23: =Data!I37 | N23: =Data!J37 | ... Q23: =Data!M37
B24: Selling Expenses | C24: =-C4*C29 -> 0 | G24: =Data!C40 -> 0 | H24: =Data!D40 -> 0 | I24: =Data!E40 -> 0 | J24: =Data!F40 -> 0 | K24: =Data!G40 -> 0 | L24: =Data!H40 | M24: =Data!I40 | N24: =Data!J40 | ... Q24: =Data!M40
B25: Variable Costs | C25: =C23+C24 -> -5066.6797 | G25: =IF(G$4="","",G23+G24) -> -5344 | H25: =IF(H$4="","",H23+H24) -> -6492 | I25: =IF(I$4="","",I23+I24) -> -7482.8818 | J25: =IF(J$4="","",J23+J24) -> -11196.896 | K25: =IF(K$4="","",K23+K24) -> -2437 | L25: =IF(L$4="","",L23+L24) | M25: =IF(M$4="","",M23+M24) | N25: =IF(N$4="","",N23+N24) | ... Q25: =IF(Q$4="","",Q23+Q24)
B27: Variable Costs % of Sales
B28: COGS | C28: =AVERAGE(G28:H28) -> 0.57805816 | E28: Historical Average | G28: =IF(G$4="","",ABS(G23/G$4)) -> 0.60969766 | H28: =IF(H$4="","",ABS(H23/H$4)) -> 0.54641865 | I28: =IF(I$4="","",ABS(I23/I$4)) -> 0.4781222 | J28: =IF(J$4="","",ABS(J23/J$4)) -> 0.45826244 | K28: =IF(K$4="","",ABS(K23/K$4)) -> 0.41396297 | L28: =IF(L$4="","",ABS(L23/L$4)) | M28: =IF(M$4="","",ABS(M23/M$4)) | N28: =IF(N$4="","",ABS(N23/N$4)) | ... Q28: =IF(Q$4="","",ABS(Q23/Q$4))
B29: =B24 -> Selling Expenses | C29: =AVERAGE(G29:J29) -> 0 | E29: Historical Average | G29: =IF(G$4="","",ABS(G24/G$4)) -> 0 | H29: =IF(H$4="","",ABS(H24/H$4)) -> 0 | I29: =IF(I$4="","",ABS(I24/I$4)) -> 0 | J29: =IF(J$4="","",ABS(J24/J$4)) -> 0 | K29: =IF(K$4="","",ABS(K24/K$4)) -> 0 | L29: =IF(L$4="","",ABS(L24/L$4)) | M29: =IF(M$4="","",ABS(M24/M$4)) | N29: =IF(N$4="","",ABS(N24/N$4)) | ... Q29: =IF(Q$4="","",ABS(Q24/Q$4))
B30: Variable Costs | C30: =ABS(C25/$C$4) -> 0.57805816 | G30: =IF(G$4="","",ABS(G25/G$4)) -> 0.60969766 | H30: =IF(H$4="","",ABS(H25/H$4)) -> 0.54641865 | I30: =IF(I$4="","",ABS(I25/I$4)) -> 0.4781222 | J30: =IF(J$4="","",ABS(J25/J$4)) -> 0.45826244 | K30: =IF(K$4="","",ABS(K25/K$4)) -> 0.41396297 | L30: =IF(L$4="","",ABS(L25/L$4)) | M30: =IF(M$4="","",ABS(M25/M$4)) | N30: =IF(N$4="","",ABS(N25/N$4)) | ... Q30: =IF(Q$4="","",ABS(Q25/Q$4))
B32: Fixed Costs
B33: G&A and other Opex | C33: =AVERAGE(G33:H33) -> -1106.5 | E33: Historical Average | G33: =Data!C41 -> -1084 | H33: =Data!D41 -> -1129 | I33: =Data!E41 -> -867.48328 | J33: =Data!F41 -> -823.28128 | K33: =Data!G41 -> 0 | L33: =Data!H41 | M33: =Data!I41 | N33: =Data!J41 | ... Q33: =Data!M41
B34: R&D | C34: =AVERAGE(G34:J34) -> 0 | E34: Historical Average | G34: =Data!C42 -> 0 | H34: =Data!D42 -> 0 | I34: =Data!E42 -> 0 | J34: =Data!F42 -> 0 | K34: =Data!G42 -> 0 | L34: =Data!H42 | M34: =Data!I42 | N34: =Data!J42 | ... Q34: =Data!M42
B35: Fixed Costs | C35: =C33+C34 -> -1106.5 | G35: =IF(G4="","",G33+G34) -> -1084 | H35: =IF(H4="","",H33+H34) -> -1129 | I35: =IF(I4="","",I33+I34) -> -867.48328 | J35: =IF(J4="","",J33+J34) -> -823.28128 | K35: =IF(K4="","",K33+K34) -> 0 | L35: =IF(L4="","",L33+L34) | M35: =IF(M4="","",M33+M34) | N35: =IF(N4="","",N33+N34) | ... Q35: =IF(Q4="","",Q33+Q34)
B37: Fixed Costs % of Sales
B38: =B33 -> G&A and other Opex | C38: =ABS(C33/$C$4) -> 0.12624073 | G38: =IF(G$4="","",ABS(G33/G$4)) -> 0.1236737 | H38: =IF(H$4="","",ABS(H33/H$4)) -> 0.095025671 | I38: =IF(I$4="","",ABS(I33/I$4)) -> 0.055428246 | J38: =IF(J$4="","",ABS(J33/J$4)) -> 0.033694952 | K38: =IF(K$4="","",ABS(K33/K$4)) -> 0 | L38: =IF(L$4="","",ABS(L33/L$4)) | M38: =IF(M$4="","",ABS(M33/M$4)) | N38: =IF(N$4="","",ABS(N33/N$4)) | ... Q38: =IF(Q$4="","",ABS(Q33/Q$4))
B39: =B34 -> R&D | C39: =ABS(C34/$C$4) -> 0 | G39: =IF(G$4="","",ABS(G34/G$4)) -> 0 | H39: =IF(H$4="","",ABS(H34/H$4)) -> 0 | I39: =IF(I$4="","",ABS(I34/I$4)) -> 0 | J39: =IF(J$4="","",ABS(J34/J$4)) -> 0 | K39: =IF(K$4="","",ABS(K34/K$4)) -> 0 | L39: =IF(L$4="","",ABS(L34/L$4)) | M39: =IF(M$4="","",ABS(M34/M$4)) | N39: =IF(N$4="","",ABS(N34/N$4)) | ... Q39: =IF(Q$4="","",ABS(Q34/Q$4))
B40: Fixed Costs | C40: =ABS(C35/$C$4) -> 0.12624073 | G40: =IF(G$4="","",ABS(G35/G$4)) -> 0.1236737 | H40: =IF(H$4="","",ABS(H35/H$4)) -> 0.095025671 | I40: =IF(I$4="","",ABS(I35/I$4)) -> 0.055428246 | J40: =IF(J$4="","",ABS(J35/J$4)) -> 0.033694952 | K40: =IF(K$4="","",ABS(K35/K$4)) -> 0 | L40: =IF(L$4="","",ABS(L35/L$4)) | M40: =IF(M$4="","",ABS(M35/M$4)) | N40: =IF(N$4="","",ABS(N35/N$4)) | ... Q40: =IF(Q$4="","",ABS(Q35/Q$4))
B42: Tax % of Pre-tax Profit
B43: Income Tax Rate | C43: 0.24 | E43: Use the highest past tax rate | G43: =IF(G$4="","",-G14/SUM(G8+G11,G12)) -> 0.16214737 | H43: =IF(H$4="","",-H14/SUM(H8+H11,H12)) -> 0.16225652 | I43: =IF(I$4="","",-I14/SUM(I8+I11,I12)) -> 0.18507299 | J43: =IF(J$4="","",-J14/SUM(J8+J11,J12)) -> 0.20414515 | K43: =IF(K$4="","",-K14/SUM(K8+K11,K12)) -> 0 | L43: =IF(L$4="","",-L14/SUM(L8+L11,L12)) | M43: =IF(M$4="","",-M14/SUM(M8+M11,M12)) | N43: =IF(N$4="","",-N14/SUM(N8+N11,N12)) | ... Q43: =IF(Q$4="","",-Q14/SUM(Q8+Q11,Q12))
B45: Non-operating Income | E45: Notes
B46: Interest
B47: Interest Expense | C47: =-BS!G31*Normalized_FCF!C54 -> -43 | G47: =Data!C51 -> -43 | H47: =Data!D51 -> -40.775368 | I47: =Data!E51 -> -49.197794 | J47: =Data!F51 -> -81.763175 | K47: =Data!G51 -> 0 | L47: =Data!H51 | M47: =Data!I51 | N47: =Data!J51 | ... Q47: =Data!M51
B48: Operating Interest Income | C48: =BS!D75*C53 -> 163.69305 | G48: =IFERROR(IF(G$4="","",($C$48/$C$49)*G49),0) -> 267.79207 | H48: =IFERROR(IF(H$4="","",($C$48/$C$49)*H49),0) -> 159.1698 | I48: =IFERROR(IF(I$4="","",($C$48/$C$49)*I49),0) -> 38.596355 | J48: =IFERROR(IF(J$4="","",($C$48/$C$49)*J49),0) -> 65.481471 | K48: =IFERROR(IF(K$4="","",($C$48/$C$49)*K49),0) -> 0 | L48: =IFERROR(IF(L$4="","",($C$48/$C$49)*L49),0) | M48: =IFERROR(IF(M$4="","",($C$48/$C$49)*M49),0) | N48: =IFERROR(IF(N$4="","",($C$48/$C$49)*N49),0) | ... Q48: =IFERROR(IF(Q$4="","",($C$48/$C$49)*Q49),0)
B49: From Interest Income | C49: =BS!$C$66*C53 -> 1430.37 | G49: =Data!C52 -> 2340 | H49: =Data!D52 -> 1390.8453 | I49: =Data!E52 -> 337.25969 | J49: =Data!F52 -> 572.18514 | K49: =Data!G52 -> 0 | L49: =Data!H52 | M49: =Data!I52 | N49: =Data!J52 | ... Q49: =Data!M52
B50: Net Interest Income | C50: =C47+C48 -> 120.69305 | G50: =IF(G$4="","",(G47+G48)) -> 224.79207 | H50: =IF(H$4="","",(H47+H48)) -> 118.39444 | I50: =IF(I$4="","",(I47+I48)) -> -10.601439 | J50: =IF(J$4="","",(J47+J48)) -> -16.281704 | K50: =IF(K$4="","",(K47+K48)) -> 0 | L50: =IF(L$4="","",(L47+L48)) | M50: =IF(M$4="","",(M47+M48)) | N50: =IF(N$4="","",(N47+N48)) | ... Q50: =IF(Q$4="","",(Q47+Q48))
B52: % Interest | G52: Latest Asset Value
B53: Interest Yield/Cash | C53: 0.03 | E53: Reference the market rate | G53: =IF(Normalized_FCF!G4="","",Normalized_FCF!G49/BS!$C$66) -> 0.049078211
B54: Interest Rate/Debt | C54: =G54 -> 0.01390236 | E54: Use Last year's rate | G54: =IFERROR(ABS(Normalized_FCF!G47/BS!$G$31),0) -> 0.01390236
B55: Pre-tax Profit/Interest Expense | C55: =-C8/C47 -> 60.27489 | G55: =IF(G4="","",-G8/G47) -> 54.348837 | H55: =IF(H4="","",-H8/H47) -> 104.47484 | I55: =IF(I4="","",-I8/I47) -> 148.38467 | J55: =IF(J4="","",-J8/J47) -> 151.81888 | K55: =IF(K4="","",-K8/K47) -> #DIV/0! | L55: =IF(L4="","",-L8/L47) | M55: =IF(M4="","",-M8/M47) | N55: =IF(N4="","",-N8/N47) | ... Q55: =IF(Q4="","",-Q8/Q47)
B57: Non-operating EBIT | G57: Latest Asset Value
B58: Dividend or Interests from FA | C58: =BS!$C67*C66 -> 0 | G58: =Data!C56 -> 0 | H58: =Data!D56 -> 0 | I58: =Data!E56 -> 0 | J58: =Data!F56 -> 0 | K58: =Data!G56 -> 0 | L58: =Data!H56 | M58: =Data!I56 | N58: =Data!J56 | ... Q58: =Data!M56
B59: Share of JV or associate Results | C59: =BS!$C68*C67 -> 639 | G59: =Data!C55 -> 639 | H59: =Data!D55 -> 927 | I59: =Data!E55 -> 0 | J59: =Data!F55 -> 0 | K59: =Data!G55 -> 0 | L59: =Data!H55 | M59: =Data!I55 | N59: =Data!J55 | ... Q59: =Data!M55
B60: Investment property | C60: =BS!$C69*C68 -> 0 | G60: =Data!C57 -> 0 | H60: =Data!D57 -> 0 | I60: =Data!E57 -> 0 | J60: =Data!F57 -> 0 | K60: =Data!G57 -> 0 | L60: =Data!H57 | M60: =Data!I57 | N60: =Data!J57 | ... Q60: =Data!M57
B61: Stable Non-Operating EBIT | C61: =SUM(C58:C60) -> 639 | G61: =IF(G4="","",SUM(G58:G60)) -> 639 | H61: =IF(H4="","",SUM(H58:H60)) -> 927 | I61: =IF(I4="","",SUM(I58:I60)) -> 0 | J61: =IF(J4="","",SUM(J58:J60)) -> 0 | K61: =IF(K4="","",SUM(K58:K60)) -> 0 | L61: =IF(L4="","",SUM(L58:L60)) | M61: =IF(M4="","",SUM(M58:M60)) | N61: =IF(N4="","",SUM(N58:N60)) | ... Q61: =IF(Q4="","",SUM(Q58:Q60))
B62: Other Non-operating Income | C62: 0 | E62: Assume 0 | G62: =Data!C58 -> -503 | H62: =Data!D58 -> 203.76489 | I62: =Data!E58 -> -503.75613 | J62: =Data!F58 -> -726.80948 | K62: =Data!G58 -> -3450 | L62: =Data!H58 | M62: =Data!I58 | N62: =Data!J58 | ... Q62: =Data!M58
B63: Total Non-Operating EBIT | C63: =C61+C62 -> 639 | G63: =IF(G4="","",G61+G62) -> 136 | H63: =IF(H4="","",H61+H62) -> 1130.7649 | I63: =IF(I4="","",I61+I62) -> -503.75613 | J63: =IF(J4="","",J61+J62) -> -726.80948 | K63: =IF(K4="","",K61+K62) -> -3450 | L63: =IF(L4="","",L61+L62) | M63: =IF(M4="","",M61+M62) | N63: =IF(N4="","",N61+N62) | ... Q63: =IF(Q4="","",Q61+Q62)
B65: Non-operating Asset Yield % | G65: Latest Asset Value
B66: Dividend or Interests from FA | C66: =G66 -> 0 | G66: =IFERROR(G58/BS!$C$67,0) -> 0
B67: JV or associate | C67: =G67 -> 0.026966577 | G67: =IFERROR(G59/BS!$C$68,0) -> 0.026966577
B68: Investment property | C68: =G68 -> 0 | G68: =IFERROR(G60/BS!$C$69,0) -> 0
B69: Stable Non-Operating EBIT | C69: =C61/BS!C70 -> 0.0087649512 | G69: =G61/BS!C70 -> 0.0087649512
B71: P&L & Dividend Analysis | E71: Notes
B72: P&L % Sales
B73: Variable Costs | C73: =ABS(C5/C$4) -> 0.57805816 | G73: =IF(G$4="","",ABS(G5/G$4)) -> 0.60969766 | H73: =IF(H$4="","",ABS(H5/H$4)) -> 0.54641865 | I73: =IF(I$4="","",ABS(I5/I$4)) -> 0.4781222 | J73: =IF(J$4="","",ABS(J5/J$4)) -> 0.45826244 | K73: =IF(K$4="","",ABS(K5/K$4)) -> 0.41396297 | L73: =IF(L$4="","",ABS(L5/L$4)) | M73: =IF(M$4="","",ABS(M5/M$4)) | N73: =IF(N$4="","",ABS(N5/N$4)) | ... Q73: =IF(Q$4="","",ABS(Q5/Q$4))
B74: Contribution Margin | C74: =ABS(C6/C$4) -> 0.42194184 | G74: =IF(G$4="","",ABS(G6/G$4)) -> 0.39030234 | H74: =IF(H$4="","",ABS(H6/H$4)) -> 0.45358135 | I74: =IF(I$4="","",ABS(I6/I$4)) -> 0.5218778 | J74: =IF(J$4="","",ABS(J6/J$4)) -> 0.54173756 | K74: =IF(K$4="","",ABS(K6/K$4)) -> 0.58603703 | L74: =IF(L$4="","",ABS(L6/L$4)) | M74: =IF(M$4="","",ABS(M6/M$4)) | N74: =IF(N$4="","",ABS(N6/N$4)) | ... Q74: =IF(Q$4="","",ABS(Q6/Q$4))
B75: Fixed Costs | C75: =ABS(C7/C$4) -> 0.12624073 | G75: =IF(G$4="","",ABS(G7/G$4)) -> 0.1236737 | H75: =IF(H$4="","",ABS(H7/H$4)) -> 0.095025671 | I75: =IF(I$4="","",ABS(I7/I$4)) -> 0.055428246 | J75: =IF(J$4="","",ABS(J7/J$4)) -> 0.033694952 | K75: =IF(K$4="","",ABS(K7/K$4)) -> 0 | L75: =IF(L$4="","",ABS(L7/L$4)) | M75: =IF(M$4="","",ABS(M7/M$4)) | N75: =IF(N$4="","",ABS(N7/N$4)) | ... Q75: =IF(Q$4="","",ABS(Q7/Q$4))
B76: Operating EBIT | C76: =ABS(C8/C$4) -> 0.29570111 | G76: =IF(G$4="","",ABS(G8/G$4)) -> 0.26662864 | H76: =IF(H$4="","",ABS(H8/H$4)) -> 0.35855568 | I76: =IF(I$4="","",ABS(I8/I$4)) -> 0.46644955 | J76: =IF(J$4="","",ABS(J8/J$4)) -> 0.50804261 | K76: =IF(K$4="","",ABS(K8/K$4)) -> 0.58603703 | L76: =IF(L$4="","",ABS(L8/L$4)) | M76: =IF(M$4="","",ABS(M8/M$4)) | N76: =IF(N$4="","",ABS(N8/N$4)) | ... Q76: =IF(Q$4="","",ABS(Q8/Q$4))
B77: Add Back D&A | C77: =ABS(C9/C$4) -> 0.018254421 | G77: =IF(G$4="","",G9/G$4) -> 0.018254421 | H77: =IF(H$4="","",H9/H$4) -> 0.016665264 | I77: =IF(I$4="","",I9/I$4) -> 0.011566229 | J77: =IF(J$4="","",J9/J$4) -> 0.0076185555 | K77: =IF(K$4="","",K9/K$4) -> 0 | L77: =IF(L$4="","",L9/L$4) | M77: =IF(M$4="","",M9/M$4) | N77: =IF(N$4="","",N9/N$4) | ... Q77: =IF(Q$4="","",Q9/Q$4)
B78: Maintenance Capex | C78: =MAX(AVERAGE(G78:J78),C77) -> 0.018254421 | E78: Historical Average or D&A | G78: =IF(G$4="","",-G10/G$4) -> 0.0078722191 | H78: =IF(H$4="","",-H10/H$4) -> 0.0090901439 | I78: =IF(I$4="","",-I10/I$4) -> 0.011566229 | J78: =IF(J$4="","",-J10/J$4) -> 0.0076185555 | K78: =IF(K$4="","",-K10/K$4) -> 0 | L78: =IF(L$4="","",-L10/L$4) | M78: =IF(M$4="","",-M10/M$4) | N78: =IF(N$4="","",-N10/N$4) | ... Q78: =IF(Q$4="","",-Q10/Q$4)
B79: Non-Operating EBIT | C79: =ABS(C11/C$4) -> 0.072903594 | G79: =IF(G$4="","",G11/G$4) -> 0.072903594 | H79: =IF(H$4="","",H11/H$4) -> 0.078023735 | I79: =IF(I$4="","",I11/I$4) -> 0 | J79: =IF(J$4="","",J11/J$4) -> 0 | K79: =IF(K$4="","",K11/K$4) -> 0 | L79: =IF(L$4="","",L11/L$4) | M79: =IF(M$4="","",M11/M$4) | N79: =IF(N$4="","",N11/N$4) | ... Q79: =IF(Q$4="","",Q11/Q$4)
B80: Net Interest Income | C80: =ABS(C12/C$4) -> 0.013769886 | G80: =IF(G$4="","",ABS(G12/G$4)) -> 0.025646557 | H80: =IF(H$4="","",ABS(H12/H$4)) -> 0.0099650228 | I80: =IF(I$4="","",ABS(I12/I$4)) -> 0.00067738386 | J80: =IF(J$4="","",ABS(J12/J$4)) -> 0.00066637155 | K80: =IF(K$4="","",ABS(K12/K$4)) -> 0 | L80: =IF(L$4="","",ABS(L12/L$4)) | M80: =IF(M$4="","",ABS(M12/M$4)) | N80: =IF(N$4="","",ABS(N12/N$4)) | ... Q80: =IF(Q$4="","",ABS(Q12/Q$4))
B81: Pre-tax Profit | C81: =C13/C4 -> 0.38237459 | G81: =IF(G$4="","",G13/G$4) -> 0.37556099 | H81: =IF(H$4="","",H13/H$4) -> 0.45411956 | I81: =IF(I$4="","",I13/I$4) -> 0.46577217 | J81: =IF(J$4="","",J13/J$4) -> 0.50737624 | K81: =IF(K$4="","",K13/K$4) -> 0.58603703 | L81: =IF(L$4="","",L13/L$4) | M81: =IF(M$4="","",M13/M$4) | N81: =IF(N$4="","",N13/N$4) | ... Q81: =IF(Q$4="","",Q13/Q$4)
B82: Income Tax | C82: =ABS(C14/C$4) -> 0.091769902 | G82: =IF(G$4="","",ABS(G14/G$4)) -> 0.059212778 | H82: =IF(H$4="","",ABS(H14/H$4)) -> 0.072454745 | I82: =IF(I$4="","",ABS(I14/I$4)) -> 0.086201849 | J82: =IF(J$4="","",ABS(J14/J$4)) -> 0.1035784 | K82: =IF(K$4="","",ABS(K14/K$4)) -> 0 | L82: =IF(L$4="","",ABS(L14/L$4)) | M82: =IF(M$4="","",ABS(M14/M$4)) | N82: =IF(N$4="","",ABS(N14/N$4)) | ... Q82: =IF(Q$4="","",ABS(Q14/Q$4))
B83: =B15 -> NCI’s Share of Profits | C83: =MIN(BS!C62,MAX(G83:K83)) -> 0.002609208 | G83: =IF(G$4="","",-G15/G$4) -> 0 | H83: =IF(H$4="","",-H15/H$4) -> 0.002609208 | I83: =IF(I$4="","",-I15/I$4) -> 0 | J83: =IF(J$4="","",-J15/J$4) -> 0 | K83: =IF(K$4="","",-K15/K$4) -> 0 | L83: =IF(L$4="","",-L15/L$4) | M83: =IF(M$4="","",-M15/M$4) | N83: =IF(N$4="","",-N15/N$4) | ... Q83: =IF(Q$4="","",-Q15/Q$4)
B84: After-tax Profit | C84: =ABS(C16/C$4) -> 0.28799548 | G84: =IF(G$4="","",ABS(G16/G$4)) -> 0.31634821 | H84: =IF(H$4="","",ABS(H16/H$4)) -> 0.3790556 | I84: =IF(I$4="","",ABS(I16/I$4)) -> 0.37957032 | J84: =IF(J$4="","",ABS(J16/J$4)) -> 0.40379784 | K84: =IF(K$4="","",ABS(K16/K$4)) -> 0.58603703 | L84: =IF(L$4="","",ABS(L16/L$4)) | M84: =IF(M$4="","",ABS(M16/M$4)) | N84: =IF(N$4="","",ABS(N16/N$4)) | ... Q84: =IF(Q$4="","",ABS(Q16/Q$4))
B85: WCInv | C85: 0 | E85: =E17 -> WCInv is by default excluded
B86: Net Borrowing | C86: 0 | E86: =E18 -> Net borrowing is excluded
B87: Total FCFE | C87: =ABS(C19/C$4) -> 0.28799548 | G87: =IF(G$4="","",ABS(G19/G$4)) -> 0.31634821 | H87: =IF(H$4="","",ABS(H19/H$4)) -> 0.3790556 | I87: =IF(I$4="","",ABS(I19/I$4)) -> 0.37957032 | J87: =IF(J$4="","",ABS(J19/J$4)) -> 0.40379784 | K87: =IF(K$4="","",ABS(K19/K$4)) -> 0.58603703 | L87: =IF(L$4="","",ABS(L19/L$4)) | M87: =IF(M$4="","",ABS(M19/M$4)) | N87: =IF(N$4="","",ABS(N19/N$4)) | ... Q87: =IF(Q$4="","",ABS(Q19/Q$4))
B89: Dividends
B90: ="Dividend per share ("&Market_currency&")" -> Dividend per share (HKD) | C90: =G90 -> 0.58 | G90: =Data!C65 -> 0.58 | H90: =Data!D65 -> 0.58 | I90: =Data!E65 -> 0.57 | J90: =Data!F65 -> 0 | K90: =Data!G65 -> 0 | L90: =Data!H65 | M90: =Data!I65 | N90: =Data!J65 | ... Q90: =Data!M65
B91: ="Dividend ("&Market_currency&")" -> Dividend (HKD) | C91: =C90*Common_Shares/scaling_factor -> 4739.6904 | G91: =IF(G$4="","",G90*Common_Shares/scaling_factor) -> 4739.6904 | H91: =IF(H$4="","",H90*Common_Shares/scaling_factor) -> 4739.6904 | I91: =IF(I$4="","",I90*Common_Shares/scaling_factor) -> 4657.9716 | J91: =IF(J$4="","",J90*Common_Shares/scaling_factor) -> 0 | K91: =IF(K$4="","",K90*Common_Shares/scaling_factor) -> 0 | L91: =IF(L$4="","",L90*Common_Shares/scaling_factor) | M91: =IF(M$4="","",M90*Common_Shares/scaling_factor) | N91: =IF(N$4="","",N90*Common_Shares/scaling_factor) | ... Q91: =IF(Q$4="","",Q90*Common_Shares/scaling_factor)
B92: Payout Ratio | C92: =C90/(C19*scaling_factor/Common_Shares) -> 1.8776402 | G92: =IF(G$4="","",G90/(G19*scaling_factor/Common_Shares)) -> 1.7093566 | H92: =IF(H$4="","",H90/(H19*scaling_factor/Common_Shares)) -> 1.052432 | I92: =IF(I$4="","",I90/(I19*scaling_factor/Common_Shares)) -> 0.7841057 | J92: =IF(J$4="","",J90/(J19*scaling_factor/Common_Shares)) -> 0 | K92: =IF(K$4="","",K90/(K19*scaling_factor/Common_Shares)) -> 0 | L92: =IF(L$4="","",L90/(L19*scaling_factor/Common_Shares)) | M92: =IF(M$4="","",M90/(M19*scaling_factor/Common_Shares)) | N92: =IF(N$4="","",N90/(N19*scaling_factor/Common_Shares)) | ... Q92: =IF(Q$4="","",Q90/(Q19*scaling_factor/Common_Shares))
B93: Dividend Yield | C93: =C90/Market_Price -> 0.071165644 | G93: =IF(G$4="","",G90/Market_Price) -> 0.071165644 | H93: =IF(H$4="","",H90/Market_Price) -> 0.071165644 | I93: =IF(I$4="","",I90/Market_Price) -> 0.06993865 | J93: =IF(J$4="","",J90/Market_Price) -> 0 | K93: =IF(K$4="","",K90/Market_Price) -> 0 | L93: =IF(L$4="","",L90/Market_Price) | M93: =IF(M$4="","",M90/Market_Price) | N93: =IF(N$4="","",N90/Market_Price) | ... Q93: =IF(Q$4="","",Q90/Market_Price)
B95: YoY %
B96: Sales | C96: =C4/G4-1 -> 0 | G96: =IF(H4="","",G4/H4-1) -> -0.26226749 | H96: =IF(I4="","",H4/I4-1) -> -0.240858 | I96: =IF(J4="","",I4/J4-1) -> -0.35945953 | J96: =IF(K4="","",J4/K4-1) -> 3.1503944 | K96: =IF(L4="","",K4/L4-1) | L96: =IF(M4="","",L4/M4-1) | M96: =IF(N4="","",M4/N4-1) | N96: =IF(O4="","",N4/O4-1) | ... Q96: =IF(R4="","",Q4/R4-1)
B97: Pre-tax Profit | C97: =C13/G13-1 -> 0.018142471 | G97: =IF(H5="","",G13/H13-1) -> -0.38988852 | H97: =IF(I5="","",H13/I13-1) -> -0.25985009 | I97: =IF(J5="","",I13/J13-1) -> -0.41198287 | J97: =IF(K5="","",J13/K13-1) -> 2.5933079 | K97: =IF(L5="","",K13/L13-1) | L97: =IF(M5="","",L13/M13-1) | M97: =IF(N5="","",M13/N13-1) | N97: =IF(O5="","",N13/O13-1) | ... Q97: =IF(R5="","",Q13/R13-1)
B99: Operating Efficiency Analysis | E99: Notes
B100: Balance Sheet | G100: Latest Asset Value
B101: Total Assets | C101: =BS!G32 -> 180996 | G101: =IF(G$4="","",G105+G104) -> 180996 | H101: =IF(H$4="","",H105+H104) -> 174007 | I101: =IF(I$4="","",I105+I104) -> 0 | J101: =IF(J$4="","",J105+J104) -> 0 | K101: =IF(K$4="","",K105+K104) -> 0 | L101: =IF(L$4="","",L105+L104) | M101: =IF(M$4="","",M105+M104) | N101: =IF(N$4="","",N105+N104) | ... Q101: =IF(Q$4="","",Q105+Q104)
B102: Incl. AR | C102: =BS!C4 -> 8029 | G102: =IF(G$4="","",Data!D77) -> 7251 | H102: =IF(H$4="","",Data!E77) -> 0 | I102: =IF(I$4="","",Data!F77) -> 0 | J102: =IF(J$4="","",Data!G77) -> 0 | K102: =IF(K$4="","",Data!H77) | L102: =IF(L$4="","",Data!I77) | M102: =IF(M$4="","",Data!J77) | N102: =IF(N$4="","",Data!K77) | ... Q102: =IF(Q$4="","",Data!N77)
B103: Incl. Inventory | C103: =BS!C6+BS!C7 -> 15310 | G103: =IF(G$4="","",Data!D78) -> 16389 | H103: =IF(H$4="","",Data!E78) -> 0 | I103: =IF(I$4="","",Data!F78) -> 0 | J103: =IF(J$4="","",Data!G78) -> 0 | K103: =IF(K$4="","",Data!H78) | L103: =IF(L$4="","",Data!I78) | M103: =IF(M$4="","",Data!J78) | N103: =IF(N$4="","",Data!K78) | ... Q103: =IF(Q$4="","",Data!N78)
B104: Total Liabilities | C104: =BS!G30 -> 13889 | G104: =Data!C79 -> 13889 | H104: =Data!D79 -> 10902 | I104: =Data!E79 -> 0 | J104: =Data!F79 -> 0 | K104: =Data!G79 -> 0 | L104: =Data!H79 | M104: =Data!I79 | N104: =Data!J79 | ... Q104: =Data!M79
B105: Total Equity | C105: =BS!G27 -> 167107 | G105: =Data!C80 -> 167107 | H105: =Data!D80 -> 163105 | I105: =Data!E80 -> 0 | J105: =Data!F80 -> 0 | K105: =Data!G80 -> 0 | L105: =Data!H80 | M105: =Data!I80 | N105: =Data!J80 | ... Q105: =Data!M80
B107: Operating Asset % of Sales | G107: Latest Asset Value
B108: AR | C108: =C102/C$4 -> 0.91602966 | G108: =IF(G$4="","",G102/G$4) -> 0.82726754 | H108: =IF(H$4="","",H102/H$4) -> 0 | I108: =IF(I$4="","",I102/I$4) -> 0 | J108: =IF(J$4="","",J102/J$4) -> 0 | K108: =IF(K$4="","",K102/K$4) -> #VALUE! | L108: =IF(L$4="","",L102/L$4) | M108: =IF(M$4="","",M102/M$4) | N108: =IF(N$4="","",N102/N$4) | ... Q108: =IF(Q$4="","",Q102/Q$4)
B109: Inventory | C109: =C103/C$4 -> 1.7467199 | G109: =IF(G$4="","",G103/G$4) -> 1.8698232 | H109: =IF(H$4="","",H103/H$4) -> 0 | I109: =IF(I$4="","",I103/I$4) -> 0 | J109: =IF(J$4="","",J103/J$4) -> 0 | K109: =IF(K$4="","",K103/K$4) -> #VALUE! | L109: =IF(L$4="","",L103/L$4) | M109: =IF(M$4="","",M103/M$4) | N109: =IF(N$4="","",N103/N$4) | ... Q109: =IF(Q$4="","",Q103/Q$4)
B110: Properties held for sale | C110: =BS!$G$38/C$4 -> 8.3438677 | G110: =BS!$G$38/G$4 -> 8.3438677
B112: Cash Flow Statement
B113: CFO/Net Income | G113: =IF(G$4="","",Data!C$22/Data!C15) -> 0 | H113: =IF(H$4="","",Data!D$22/Data!D15) -> 0 | I113: =IF(I$4="","",Data!E$22/Data!E15) -> 0 | J113: =IF(J$4="","",Data!F$22/Data!F15) -> 0 | K113: =IF(K$4="","",Data!G$22/Data!G15) -> #DIV/0! | L113: =IF(L$4="","",Data!H$22/Data!H15) | M113: =IF(M$4="","",Data!I$22/Data!I15) | N113: =IF(N$4="","",Data!J$22/Data!J15) | ... Q113: =IF(Q$4="","",Data!M$22/Data!M15)
B114: CFO/FCFE | G114: =IF(G$4="","",Data!C$22/G19) -> 0 | H114: =IF(H$4="","",Data!D$22/H19) -> 0 | I114: =IF(I$4="","",Data!E$22/I19) -> 0 | J114: =IF(J$4="","",Data!F$22/J19) -> 0 | K114: =IF(K$4="","",Data!G$22/K19) -> 0 | L114: =IF(L$4="","",Data!H$22/L19) | M114: =IF(M$4="","",Data!I$22/M19) | N114: =IF(N$4="","",Data!J$22/N19) | ... Q114: =IF(Q$4="","",Data!M$22/Q19)
B116: ROE | G116: =IFERROR(IF(#REF!*G118*(1/#REF!)=G120,"","Error"),"") | H116: =IFERROR(IF(#REF!*H118*(1/#REF!)=H120,"","Error"),"") | I116: =IFERROR(IF(#REF!*I118*(1/#REF!)=I120,"","Error"),"") | J116: =IFERROR(IF(#REF!*J118*(1/#REF!)=J120,"","Error"),"") | K116: =IFERROR(IF(#REF!*K118*(1/#REF!)=K120,"","Error"),"") | L116: =IFERROR(IF(#REF!*L118*(1/#REF!)=L120,"","Error"),"") | M116: =IFERROR(IF(#REF!*M118*(1/#REF!)=M120,"","Error"),"") | N116: =IFERROR(IF(#REF!*N118*(1/#REF!)=N120,"","Error"),"") | ... Q116: =IFERROR(IF(#REF!*Q118*(1/#REF!)=Q120,"","Error"),"")
...

Sheet DCF
B2: No-Growth DCF Valuation | H2: Notes
B3: No-Growth DCF | C3: =scaling_factor -> 1000000 | E3: Special Assumption
B4: Adjusted FCFE | C4: =Normalized_FCF!C19 -> 2524.2804 | D4: =Reporting_currency -> HKD | E4: Terminal Growth Rate (g): | F4: =Terminal_Growth -> 0
B5: /Equity Cost of Capital | C5: =Equity_Cost -> 0.085
B6: Stable Income Value | C6: =(C4*(1+Terminal_Growth))/(Equity_Cost-Terminal_Growth) -> 29697.417 | D6: =Reporting_currency -> HKD | E6: Conservative Valuation: Setting g=0 can be a conservative assumption to avoid overestimating the stock’s value, especially if future growth is uncertain or unreliable.
B7: - Interest-bearing Debt | C7: =BS!G31 -> 3093 | D7: =Reporting_currency -> HKD
B8: + Non-operating Cash | C8: =BS!D66 -> 42222.565 | D8: =Reporting_currency -> HKD
B9: + Other Non-operating Assets | C9: =BS!H42 -> 7814.4 | D9: =Reporting_currency -> HKD
B10: Equity Value | C10: =C6-C7+C8+C9 -> 76641.382 | D10: =Reporting_currency -> HKD
B11: * Exchange rate | C11: =Exchange_Rate -> 1 | D11: =Thesis!C15 -> HKD
B12: Equity Value per share | C12: =(C10*scaling_factor)/Common_Shares*Exchange_Rate -> 9.378672 | D12: =Market_currency -> HKD
B14: Implied Growth Scenario Analysis
B15: FCFE Projection
B16: High Growth Period (HGP) | C16: =Scenarios!C65 -> -0.0015334906
B17: High Growth Rate (HGR) | C17: =Scenarios!C64 -> 10
B18: Value Per Share | C18: =(F52-C7+C8+C9)*Exchange_Rate/Common_Shares*scaling_factor -> 9.3612446 | D18: =Market_currency -> HKD
B20: Year | C20: FCFE | D20: Growth Rates | E20: Discount Factor | F20: PV of FCFE
B21: 1 | C21: =C4*(1+D21) -> 2520.4094 | D21: =IF($C$17<B21,0,DCF!$C$16) -> -0.0015334906 | E21: =IF($C$17<B21,0,1/(1+Equity_Cost)^B21) -> 0.92165899 | F21: =C21*E21 -> 2322.958
B22: 2 | C22: =IF(ROW()-ROW($C$21)<$C$17, $C$21*(1+D22)^(ROW()-ROW($C$21)), 0) -> 2516.5444 | D22: =IF($C$17<B22,0,DCF!$C$16) -> -0.0015334906 | E22: =IF($C$17<B22,0,1/(1+Equity_Cost)^B22) -> 0.84945529 | F22: =C22*E22 -> 2137.692
B23: 3 | C23: =IF(ROW()-ROW($C$21)<$C$17, $C$21*(1+D23)^(ROW()-ROW($C$21)), 0) -> 2512.6853 | D23: =IF($C$17<B23,0,DCF!$C$16) -> -0.0015334906 | E23: =IF($C$17<B23,0,1/(1+Equity_Cost)^B23) -> 0.7829081 | F23: =C23*E23 -> 1967.2017
B24: 4 | C24: =IF(ROW()-ROW($C$21)<$C$17, $C$21*(1+D24)^(ROW()-ROW($C$21)), 0) -> 2508.8321 | D24: =IF($C$17<B24,0,DCF!$C$16) -> -0.0015334906 | E24: =IF($C$17<B24,0,1/(1+Equity_Cost)^B24) -> 0.72157428 | F24: =C24*E24 -> 1810.3088
B25: 5 | C25: =IF(ROW()-ROW($C$21)<$C$17, $C$21*(1+D25)^(ROW()-ROW($C$21)), 0) -> 2504.9849 | D25: =IF($C$17<B25,0,DCF!$C$16) -> -0.0015334906 | E25: =IF($C$17<B25,0,1/(1+Equity_Cost)^B25) -> 0.66504542 | F25: =C25*E25 -> 1665.9287
B26: 6 | C26: =IF(ROW()-ROW($C$21)<$C$17, $C$21*(1+D26)^(ROW()-ROW($C$21)), 0) -> 2501.1435 | D26: =IF($C$17<B26,0,DCF!$C$16) -> -0.0015334906 | E26: =IF($C$17<B26,0,1/(1+Equity_Cost)^B26) -> 0.61294509 | F26: =C26*E26 -> 1533.0636
B27: 7 | C27: =IF(ROW()-ROW($C$21)<$C$17, $C$21*(1+D27)^(ROW()-ROW($C$21)), 0) -> 2497.308 | D27: =IF($C$17<B27,0,DCF!$C$16) -> -0.0015334906 | E27: =IF($C$17<B27,0,1/(1+Equity_Cost)^B27) -> 0.56492635 | F27: =C27*E27 -> 1410.7951
B28: 8 | C28: =IF(ROW()-ROW($C$21)<$C$17, $C$21*(1+D28)^(ROW()-ROW($C$21)), 0) -> 2493.4784 | D28: =IF($C$17<B28,0,DCF!$C$16) -> -0.0015334906 | E28: =IF($C$17<B28,0,1/(1+Equity_Cost)^B28) -> 0.52066945 | F28: =C28*E28 -> 1298.278
B29: 9 | C29: =IF(ROW()-ROW($C$21)<$C$17, $C$21*(1+D29)^(ROW()-ROW($C$21)), 0) -> 2489.6547 | D29: =IF($C$17<B29,0,DCF!$C$16) -> -0.0015334906 | E29: =IF($C$17<B29,0,1/(1+Equity_Cost)^B29) -> 0.47987968 | F29: =C29*E29 -> 1194.7347
B30: 10 | C30: =IF(ROW()-ROW($C$21)<$C$17, $C$21*(1+D30)^(ROW()-ROW($C$21)), 0) -> 2485.8368 | D30: =IF($C$17<B30,0,DCF!$C$16) -> -0.0015334906 | E30: =IF($C$17<B30,0,1/(1+Equity_Cost)^B30) -> 0.44228542 | F30: =C30*E30 -> 1099.4494
B31: 11 | C31: =IF(ROW()-ROW($C$21)<$C$17, $C$21*(1+D31)^(ROW()-ROW($C$21)), 0) -> 0 | D31: =IF($C$17<B31,0,DCF!$C$16) -> 0 | E31: =IF($C$17<B31,0,1/(1+Equity_Cost)^B31) -> 0 | F31: =C31*E31 -> 0
B32: 12 | C32: =IF(ROW()-ROW($C$21)<$C$17, $C$21*(1+D32)^(ROW()-ROW($C$21)), 0) -> 0 | D32: =IF($C$17<B32,0,DCF!$C$16) -> 0 | E32: =IF($C$17<B32,0,1/(1+Equity_Cost)^B32) -> 0 | F32: =C32*E32 -> 0
B33: 13 | C33: =IF(ROW()-ROW($C$21)<$C$17, $C$21*(1+D33)^(ROW()-ROW($C$21)), 0) -> 0 | D33: =IF($C$17<B33,0,DCF!$C$16) -> 0 | E33: =IF($C$17<B33,0,1/(1+Equity_Cost)^B33) -> 0 | F33: =C33*E33 -> 0
... B50: 30 | C50: =IF(ROW()-ROW($C$21)<$C$17, $C$21*(1+D50)^(ROW()-ROW($C$21)), 0) -> 0 | D50: =IF($C$17<B50,0,DCF!$C$16) -> 0 | E50: =IF($C$17<B50,0,1/(1+Equity_Cost)^B50) -> 0 | F50: =C50*E50 -> 0
B51: Terminal Year | C51: =C$21*(1+Terminal_Growth)^$C$17/Equity_Cost -> 29651.876 | D51: =Terminal_Growth -> 0 | E51: =1/(1+Equity_Cost)^C17 -> 0.44228542 | F51: =C51*E51 -> 13114.592
E52: Total PV | F52: =SUM(F21:F51) -> 29555.002
B54: Sensitivity Analysis (Enterprise Value)
A55: =F52 -> 29555.002 | B55: =C78 -> -0.1 | C55: =C77 -> -0.02 | D55: =C76 -> 0 | E55: =C75 -> 0.02 | F55: =C74 -> 0.05
A56: 5 | B56: 25232.901 | C56: 28752.053 | D56: 29697.417 | E56: 30671.415 | F56: 32188.893
A57: 10 | B57: 22207.735 | C57: 27917.91 | D57: 29697.417 | E57: 31652.779 | F57: 34962.383
A58: 15 | B58: 19398.255 | C58: 27002.216 | D58: 29697.417 | E58: 32840.425 | F58: 38592.768
A59: 20 | B59: 17216.6 | C59: 26176.253 | D59: 29697.417 | E59: 34023.09 | F59: 42522.973
A60: 25 | B60: 15642.697 | C60: 25496.51 | D60: 29697.417 | E60: 35098.055 | F60: 46423.357
A61: 30 | B61: 14547.676 | C61: 24966.036 | D61: 29697.417 | E61: 36024.746 | F61: 50109.352
B63: Sensitivity Analysis (Equity Value per share)
B64: =B55 -> -0.1 | C64: =C55 -> -0.02 | D64: =D55 -> 0 | E64: =E55 -> 0.02 | F64: =F55 -> 0.05
A65: 0 | B65: =C12 -> 9.378672 | C65: =C12 -> 9.378672 | D65: =C12 -> 9.378672 | E65: =C12 -> 9.378672 | F65: =C12 -> 9.378672
A66: =A56 -> 5 | B66: =(B56-$C$7+$C$8+$C$9)/Common_Shares*$C$3*Exchange_Rate -> 8.8323454 | C66: =(C56-$C$7+$C$8+$C$9)/Common_Shares*$C$3*Exchange_Rate -> 9.262987 | D66: =(D56-$C$7+$C$8+$C$9)/Common_Shares*$C$3*Exchange_Rate -> 9.378672 | E66: =(E56-$C$7+$C$8+$C$9)/Common_Shares*$C$3*Exchange_Rate -> 9.4978611 | F66: =(F56-$C$7+$C$8+$C$9)/Common_Shares*$C$3*Exchange_Rate -> 9.6835562
A67: =A57 -> 10 | B67: =(B57-$C$7+$C$8+$C$9)/Common_Shares*$C$3*Exchange_Rate -> 8.4621532 | C67: =(C57-$C$7+$C$8+$C$9)/Common_Shares*$C$3*Exchange_Rate -> 9.1609122 | D67: =(D57-$C$7+$C$8+$C$9)/Common_Shares*$C$3*Exchange_Rate -> 9.378672 | E67: =(E57-$C$7+$C$8+$C$9)/Common_Shares*$C$3*Exchange_Rate -> 9.6179514 | F67: =(F57-$C$7+$C$8+$C$9)/Common_Shares*$C$3*Exchange_Rate -> 10.022951
A68: =A58 -> 15 | B68: =(B58-$C$7+$C$8+$C$9)/Common_Shares*$C$3*Exchange_Rate -> 8.1183547 | C68: =(C58-$C$7+$C$8+$C$9)/Common_Shares*$C$3*Exchange_Rate -> 9.0488579 | D68: =(D58-$C$7+$C$8+$C$9)/Common_Shares*$C$3*Exchange_Rate -> 9.378672 | E68: =(E58-$C$7+$C$8+$C$9)/Common_Shares*$C$3*Exchange_Rate -> 9.7632847 | F68: =(F58-$C$7+$C$8+$C$9)/Common_Shares*$C$3*Exchange_Rate -> 10.467204
A69: =A59 -> 20 | B69: =(B59-$C$7+$C$8+$C$9)/Common_Shares*$C$3*Exchange_Rate -> 7.8513837 | C69: =(C59-$C$7+$C$8+$C$9)/Common_Shares*$C$3*Exchange_Rate -> 8.9477841 | D69: =(D59-$C$7+$C$8+$C$9)/Common_Shares*$C$3*Exchange_Rate -> 9.378672 | E69: =(E59-$C$7+$C$8+$C$9)/Common_Shares*$C$3*Exchange_Rate -> 9.9080084 | F69: =(F59-$C$7+$C$8+$C$9)/Common_Shares*$C$3*Exchange_Rate -> 10.948146
A70: =A60 -> 25 | B70: =(B60-$C$7+$C$8+$C$9)/Common_Shares*$C$3*Exchange_Rate -> 7.6587838 | C70: =(C60-$C$7+$C$8+$C$9)/Common_Shares*$C$3*Exchange_Rate -> 8.8646034 | D70: =(D60-$C$7+$C$8+$C$9)/Common_Shares*$C$3*Exchange_Rate -> 9.378672 | E70: =(E60-$C$7+$C$8+$C$9)/Common_Shares*$C$3*Exchange_Rate -> 10.039553 | F70: =(F60-$C$7+$C$8+$C$9)/Common_Shares*$C$3*Exchange_Rate -> 11.42544
A71: =A61 -> 30 | B71: =(B61-$C$7+$C$8+$C$9)/Common_Shares*$C$3*Exchange_Rate -> 7.5247852 | C71: =(C61-$C$7+$C$8+$C$9)/Common_Shares*$C$3*Exchange_Rate -> 8.7996888 | D71: =(D61-$C$7+$C$8+$C$9)/Common_Shares*$C$3*Exchange_Rate -> 9.378672 | E71: =(E61-$C$7+$C$8+$C$9)/Common_Shares*$C$3*Exchange_Rate -> 10.152953 | F71: =(F61-$C$7+$C$8+$C$9)/Common_Shares*$C$3*Exchange_Rate -> 11.876498
B73: Scenarios | C73: HGR | D73: HGP | E73: Value per share | F73: Probabilities
B74: =Scenarios!B54 -> Snowball Scenario | C74: =Scenarios!C56 -> 0.05 | D74: =Scenarios!C55 -> 15 | E74: =INDEX(B$65:F$71, MATCH(D74, A$65:A$71, 0), MATCH(C74, B$64:F$64, 0)) -> 10.467204 | F74: =Scenarios!C58 -> 0.05
B75: =Scenarios!B36 -> Optimistic | C75: =Scenarios!C38 -> 0.02 | D75: =Scenarios!C37 -> 10 | E75: =INDEX(B$65:F$71, MATCH(D75, A$65:A$71, 0), MATCH(C75, B$64:F$64, 0)) -> 9.6179514 | F75: =Scenarios!C40*(1-F$74-F$78) -> 0.18
B76: =Scenarios!B24 -> Base | C76: =Scenarios!C26 -> 0 | D76: =Scenarios!C25 -> 10 | E76: =INDEX(B$65:F$71, MATCH(D76, A$65:A$71, 0), MATCH(C76, B$64:F$64, 0)) -> 9.378672 | F76: =Scenarios!C28*(1-F$74-F$78) -> 0.495
B77: =Scenarios!B30 -> Pessimistic | C77: =Scenarios!C32 -> -0.02 | D77: =Scenarios!C31 -> 10 | E77: =INDEX(B$65:F$71, MATCH(D77, A$65:A$71, 0), MATCH(C77, B$64:F$64, 0)) -> 9.1609122 | F77: =Scenarios!C34*(1-F$74-F$78) -> 0.225
B78: =Scenarios!B48 -> Devil's advocate | C78: =Scenarios!C50 -> -0.1 | D78: =Scenarios!C49 -> 15 | E78: =INDEX(B$65:F$71, MATCH(D78, A$65:A$71, 0), MATCH(C78, B$64:F$64, 0)) -> 8.1183547 | F78: =Scenarios!C52 -> 0.05
B80: Note of the formulas: | C80: MATCH(1%, C65:E65, 0) finds the column number for HGR = 1%.
C81: MATCH(5, B66:B69, 0) finds the row number for HGP = 5.
C82: INDEX(C66:E69, ...) retrieves the value from the specified range.

Sheet DDM
B2: No-Growth DDM Valuation | H2: Notes
B3: No-Growth DDM | C3: =scaling_factor -> 1000000 | E3: Special Assumption
B4: Dividend | C4: =Normalized_FCF!C91 -> 4739.6904 | D4: =Market_currency -> HKD | E4: Terminal Growth Rate (g): | F4: =Thesis!E22 -> 0
B5: /Equity Cost of Capital | C5: =Equity_Cost -> 0.085
B6: Dividend Value | C6: =(C4*(1+Terminal_Growth))/(Equity_Cost-Terminal_Growth) -> 55761.063 | D6: =Reporting_currency -> HKD
B7: Dividend Value per share | C7: =(C6*scaling_factor)/Common_Shares*Exchange_Rate -> 6.8235294 | D7: =Market_currency -> HKD
B9: Implied Growth Scenario Analysis
B10: FCFE Projection
B11: High Growth Period (HGP) | C11: =Scenarios!C65 -> -0.0015334906
B12: High Growth Rate (HGR) | C12: =Scenarios!C64 -> 10
B13: Value Per Share | C13: =F47/Common_Shares*scaling_factor -> 6.7908071 | D13: =Market_currency -> HKD
B15: Year | C15: Dividends | D15: Growth Rates | E15: Discount Factor | F15: PV of Dividends
B16: 1 | C16: =C4*(1+D16) -> 4732.4221 | D16: =IF($C$12<B16,0,DDM!$C$11) -> -0.0015334906 | E16: =IF($C$12<B16,0,1/(1+Equity_Cost)^B16) -> 0.92165899 | F16: =C16*E16 -> 4361.6793
B17: 2 | C17: =IF(ROW()-ROW($C$16)<$C$12, $C$16*(1+D17)^(ROW()-ROW($C$16)), 0) -> 4725.165 | D17: =IF($C$12<B17,0,DDM!$C$11) -> -0.0015334906 | E17: =IF($C$12<B17,0,1/(1+Equity_Cost)^B17) -> 0.84945529 | F17: =C17*E17 -> 4013.8164
B18: 3 | C18: =IF(ROW()-ROW($C$16)<$C$12, $C$16*(1+D18)^(ROW()-ROW($C$16)), 0) -> 4717.919 | D18: =IF($C$12<B18,0,DDM!$C$11) -> -0.0015334906 | E18: =IF($C$12<B18,0,1/(1+Equity_Cost)^B18) -> 0.7829081 | F18: =C18*E18 -> 3693.697
B19: 4 | C19: =IF(ROW()-ROW($C$16)<$C$12, $C$16*(1+D19)^(ROW()-ROW($C$16)), 0) -> 4710.6841 | D19: =IF($C$12<B19,0,DDM!$C$11) -> -0.0015334906 | E19: =IF($C$12<B19,0,1/(1+Equity_Cost)^B19) -> 0.72157428 | F19: =C19*E19 -> 3399.1085
B20: 5 | C20: =IF(ROW()-ROW($C$16)<$C$12, $C$16*(1+D20)^(ROW()-ROW($C$16)), 0) -> 4703.4603 | D20: =IF($C$12<B20,0,DDM!$C$11) -> -0.0015334906 | E20: =IF($C$12<B20,0,1/(1+Equity_Cost)^B20) -> 0.66504542 | F20: =C20*E20 -> 3128.0147
B21: 6 | C21: =IF(ROW()-ROW($C$16)<$C$12, $C$16*(1+D21)^(ROW()-ROW($C$16)), 0) -> 4696.2476 | D21: =IF($C$12<B21,0,DDM!$C$11) -> -0.0015334906 | E21: =IF($C$12<B21,0,1/(1+Equity_Cost)^B21) -> 0.61294509 | F21: =C21*E21 -> 2878.5419
B22: 7 | C22: =IF(ROW()-ROW($C$16)<$C$12, $C$16*(1+D22)^(ROW()-ROW($C$16)), 0) -> 4689.0459 | D22: =IF($C$12<B22,0,DDM!$C$11) -> -0.0015334906 | E22: =IF($C$12<B22,0,1/(1+Equity_Cost)^B22) -> 0.56492635 | F22: =C22*E22 -> 2648.9656
B23: 8 | C23: =IF(ROW()-ROW($C$16)<$C$12, $C$16*(1+D23)^(ROW()-ROW($C$16)), 0) -> 4681.8553 | D23: =IF($C$12<B23,0,DDM!$C$11) -> -0.0015334906 | E23: =IF($C$12<B23,0,1/(1+Equity_Cost)^B23) -> 0.52066945 | F23: =C23*E23 -> 2437.699
B24: 9 | C24: =IF(ROW()-ROW($C$16)<$C$12, $C$16*(1+D24)^(ROW()-ROW($C$16)), 0) -> 4674.6757 | D24: =IF($C$12<B24,0,DDM!$C$11) -> -0.0015334906 | E24: =IF($C$12<B24,0,1/(1+Equity_Cost)^B24) -> 0.47987968 | F24: =C24*E24 -> 2243.2819
B25: 10 | C25: =IF(ROW()-ROW($C$16)<$C$12, $C$16*(1+D25)^(ROW()-ROW($C$16)), 0) -> 4667.5072 | D25: =IF($C$12<B25,0,DDM!$C$11) -> -0.0015334906 | E25: =IF($C$12<B25,0,1/(1+Equity_Cost)^B25) -> 0.44228542 | F25: =C25*E25 -> 2064.3703
B26: 11 | C26: =IF(ROW()-ROW($C$16)<$C$12, $C$16*(1+D26)^(ROW()-ROW($C$16)), 0) -> 0 | D26: =IF($C$12<B26,0,DDM!$C$11) -> 0 | E26: =IF($C$12<B26,0,1/(1+Equity_Cost)^B26) -> 0 | F26: =C26*E26 -> 0
B27: 12 | C27: =IF(ROW()-ROW($C$16)<$C$12, $C$16*(1+D27)^(ROW()-ROW($C$16)), 0) -> 0 | D27: =IF($C$12<B27,0,DDM!$C$11) -> 0 | E27: =IF($C$12<B27,0,1/(1+Equity_Cost)^B27) -> 0 | F27: =C27*E27 -> 0
B28: 13 | C28: =IF(ROW()-ROW($C$16)<$C$12, $C$16*(1+D28)^(ROW()-ROW($C$16)), 0) -> 0 | D28: =IF($C$12<B28,0,DDM!$C$11) -> 0 | E28: =IF($C$12<B28,0,1/(1+Equity_Cost)^B28) -> 0 | F28: =C28*E28 -> 0
... B45: 30 | C45: =IF(ROW()-ROW($C$16)<$C$12, $C$16*(1+D45)^(ROW()-ROW($C$16)), 0) -> 0 | D45: =IF($C$12<B45,0,DDM!$C$11) -> 0 | E45: =IF($C$12<B45,0,1/(1+Equity_Cost)^B45) -> 0 | F45: =C45*E45 -> 0
B46: Terminal Year | C46: =C$16*(1+F4)^$C$12/Equity_Cost -> 55675.554 | D46: =Terminal_Growth -> 0 | E46: =1/(1+Equity_Cost)^C12 -> 0.44228542 | F46: =C46*E46 -> 24624.486
E47: Total PV | F47: =SUM(F16:F46) -> 55493.66
B49: Sensitivity Analysis (Enterprise Value)
A50: =F47 -> 55493.66 | B50: =C73 -> -0.1 | C50: =C72 -> -0.02 | D50: =C71 -> 0 | E50: =C70 -> 0.02 | F50: =C69 -> 0.05
A51: 5 | B51: 47378.309 | C51: 53986.01 | D51: 55761.063 | E51: 57589.882 | F51: 60439.16
A52: 10 | B52: 41698.136 | C52: 52419.789 | D52: 55761.063 | E52: 59432.531 | F52: 65646.776
A53: 15 | B53: 36422.943 | C53: 50700.446 | D53: 55761.063 | E53: 61662.502 | F53: 72463.332
A54: 20 | B54: 32326.58 | C54: 49149.584 | D54: 55761.063 | E54: 63883.122 | F54: 79842.844
A55: 25 | B55: 29371.356 | C55: 47873.271 | D55: 55761.063 | E55: 65901.519 | F55: 87166.361
A56: 30 | B56: 27315.301 | C56: 46877.232 | D56: 55761.063 | E56: 67641.511 | F56: 94087.333
B58: Sensitivity Analysis (Equity Value per share)
B59: =B50 -> -0.1 | C59: =C50 -> -0.02 | D59: =D50 -> 0 | E59: =E50 -> 0.02 | F59: =F50 -> 0.05
A60: 0 | B60: =C7 -> 6.8235294 | C60: =C7 -> 6.8235294 | D60: =C7 -> 6.8235294 | E60: =C7 -> 6.8235294 | F60: =C7 -> 6.8235294
A61: =A51 -> 5 | B61: =B51/Common_Shares*$C$3*Exchange_Rate -> 5.7977246 | C61: =C51/Common_Shares*$C$3*Exchange_Rate -> 6.6063146 | D61: =D51/Common_Shares*$C$3*Exchange_Rate -> 6.8235294 | E61: =E51/Common_Shares*$C$3*Exchange_Rate -> 7.0473236 | F61: =F51/Common_Shares*$C$3*Exchange_Rate -> 7.3959922
A62: =A52 -> 10 | B62: =B52/Common_Shares*$C$3*Exchange_Rate -> 5.1026369 | C62: =C52/Common_Shares*$C$3*Exchange_Rate -> 6.4146548 | D62: =D52/Common_Shares*$C$3*Exchange_Rate -> 6.8235294 | E62: =E52/Common_Shares*$C$3*Exchange_Rate -> 7.2728101 | F62: =F52/Common_Shares*$C$3*Exchange_Rate -> 8.0332527
A63: =A53 -> 15 | B63: =B53/Common_Shares*$C$3*Exchange_Rate -> 4.457107 | C63: =C53/Common_Shares*$C$3*Exchange_Rate -> 6.2042573 | D63: =D53/Common_Shares*$C$3*Exchange_Rate -> 6.8235294 | E63: =E53/Common_Shares*$C$3*Exchange_Rate -> 7.5456936 | F63: =F53/Common_Shares*$C$3*Exchange_Rate -> 8.8674005
A64: =A54 -> 20 | B64: =B54/Common_Shares*$C$3*Exchange_Rate -> 3.9558315 | C64: =C54/Common_Shares*$C$3*Exchange_Rate -> 6.014477 | D64: =D54/Common_Shares*$C$3*Exchange_Rate -> 6.8235294 | E64: =E54/Common_Shares*$C$3*Exchange_Rate -> 7.8174328 | F64: =F54/Common_Shares*$C$3*Exchange_Rate -> 9.7704377
A65: =A55 -> 25 | B65: =B55/Common_Shares*$C$3*Exchange_Rate -> 3.5941982 | C65: =C55/Common_Shares*$C$3*Exchange_Rate -> 5.8582935 | D65: =D55/Common_Shares*$C$3*Exchange_Rate -> 6.8235294 | E65: =E55/Common_Shares*$C$3*Exchange_Rate -> 8.0644258 | F65: =F55/Common_Shares*$C$3*Exchange_Rate -> 10.666623
A66: =A56 -> 30 | B66: =B56/Common_Shares*$C$3*Exchange_Rate -> 3.342597 | C66: =C56/Common_Shares*$C$3*Exchange_Rate -> 5.7364073 | D66: =D56/Common_Shares*$C$3*Exchange_Rate -> 6.8235294 | E66: =E56/Common_Shares*$C$3*Exchange_Rate -> 8.27735 | F66: =F56/Common_Shares*$C$3*Exchange_Rate -> 11.513548
B68: Scenarios | C68: HGR | D68: HGP | E68: Value per share | F68: Probabilities
B69: =Scenarios!B54 -> Snowball Scenario | C69: =Scenarios!C56 -> 0.05 | D69: =Scenarios!C55 -> 15 | E69: =INDEX(B$60:F$66, MATCH(D69, A$60:A$66, 0), MATCH(C69, B$59:F$59, 0)) -> 8.8674005 | F69: =Scenarios!C58 -> 0.05
B70: =Scenarios!B36 -> Optimistic | C70: =Scenarios!C38 -> 0.02 | D70: =Scenarios!C37 -> 10 | E70: =INDEX(B$60:F$66, MATCH(D70, A$60:A$66, 0), MATCH(C70, B$59:F$59, 0)) -> 7.2728101 | F70: =Scenarios!C40*(1-F$69-F$73) -> 0.18
B71: =Scenarios!B24 -> Base | C71: =Scenarios!C26 -> 0 | D71: =Scenarios!C25 -> 10 | E71: =INDEX(B$60:F$66, MATCH(D71, A$60:A$66, 0), MATCH(C71, B$59:F$59, 0)) -> 6.8235294 | F71: =Scenarios!C28*(1-F$69-F$73) -> 0.495
B72: =Scenarios!B30 -> Pessimistic | C72: =Scenarios!C32 -> -0.02 | D72: =Scenarios!C31 -> 10 | E72: =INDEX(B$60:F$66, MATCH(D72, A$60:A$66, 0), MATCH(C72, B$59:F$59, 0)) -> 6.4146548 | F72: =Scenarios!C34*(1-F$69-F$73) -> 0.225
B73: =Scenarios!B48 -> Devil's advocate | C73: =Scenarios!C50 -> -0.1 | D73: =Scenarios!C49 -> 15 | E73: =INDEX(B$60:F$66, MATCH(D73, A$60:A$66, 0), MATCH(C73, B$59:F$59, 0)) -> 4.457107 | F73: =Scenarios!C52 -> 0.05
B75: Note of the formulas: | C75: MATCH(1%, C65:E65, 0) finds the column number for HGR = 1%.
C76: MATCH(5, B66:B69, 0) finds the row number for HGP = 5.
C77: INDEX(C66:E69, ...) retrieves the value from the specified range.

Sheet Scenarios
B2: Current Situation | H2: Warning: Do Not Remove this logic
B3: Selection | H3: 0 | I3: =-Market_Price -> -8.15
B4: Past Years Selected | C4: 3 | E4: Tie the business story into the three levers of value: FCFE, growth and risk. | H4: 1 | I4: =IF(ROW()-3 < $C$76, $C$77, IF(ROW()-3 = $C$76, $C$77 + $C$60, "")) -> 0.58
H5: 2 | I5: =IF(ROW()-3 < $C$76, $C$77, IF(ROW()-3 = $C$76, $C$77 + $C$60, "")) -> 0.58
B6: Latest | C6: =DCF!C3 -> 1000000 | E6: Prompt for fundamental Analysis | H6: 3 | I6: =IF(ROW()-3 < $C$76, $C$77, IF(ROW()-3 = $C$76, $C$77 + $C$60, "")) -> 9.9441571
B7: EBIT | C7: =Normalized_FCF!G8 -> 2337 | D7: =Reporting_currency -> HKD | E7: ="Please develop three logical "&C18&"-year scenarios (Base Case, Pessimistic Case, Optimistic Case) and two extreme "&C46&"-year scenarios (Success Scenario, Devil’s Advocate Scenario) for "&Thesis!C5&"("&Thesis!C11&"). Each scenario should include the Compound Growth Rate, the Probability Assessment, and the Business Narrative." -> Please develop three logical 10-year scenarios (Base Case, Pessimistic Case, Optimistic Case) and two extreme 15-year scenarios (Success Scenario, Devil’s Advocate Scenario) for SINO LAND(0083.HK). Each scenario should include the Compound Growth Rate, the Probability Assessment, and the Business Narrative. | H7: 4 | I7: =IF(ROW()-3 < $C$76, $C$77, IF(ROW()-3 = $C$76, $C$77 + $C$60, ""))
B8: FCFE | C8: =Normalized_FCF!G19 -> 2772.7921 | D8: =Reporting_currency -> HKD | H8: 5 | I8: =IF(ROW()-3 < $C$76, $C$77, IF(ROW()-3 = $C$76, $C$77 + $C$60, ""))
B9: Normalized | C9: =Normalized_FCF!C19 -> 2524.2804 | D9: =Reporting_currency -> HKD | H9: 6 | I9: =IF(ROW()-3 < $C$76, $C$77, IF(ROW()-3 = $C$76, $C$77 + $C$60, ""))
H10: 7 | I10: =IF(ROW()-3 < $C$76, $C$77, IF(ROW()-3 = $C$76, $C$77 + $C$60, ""))
B11: YoY CAGR | H11: 8 | I11: =IF(ROW()-3 < $C$76, $C$77, IF(ROW()-3 = $C$76, $C$77 + $C$60, ""))
B12: Sales | C12: =(Normalized_FCF!G4/OFFSET(Normalized_FCF!G4, 0, $C$4))^(1/$C$4) - 1 -> -0.28945841 | H12: 9 | I12: =IF(ROW()-3 < $C$76, $C$77, IF(ROW()-3 = $C$76, $C$77 + $C$60, ""))
B13: Operating EBIT | C13: =(Normalized_FCF!G8/OFFSET(Normalized_FCF!G8, 0, $C$4))^(1/$C$4) - 1 -> -0.42686307 | H13: 10 | I13: =IF(ROW()-3 < $C$76, $C$77, IF(ROW()-3 = $C$76, $C$77 + $C$60, ""))
B14: FCFE | C14: =(Normalized_FCF!G19/OFFSET(Normalized_FCF!G19, 0, $C$4))^(1/$C$4) - 1 -> -0.34497687
B16: General Scenarios
B17: Assumption | E17: Guidance Note
B18: High Growth Period (HGP) | C18: 10 | E18: Fundamental analysis and market signal analysis should be combined, with fundamental analysis given priority and market signal analysis serving as a supplement. Market signal analysis predicts a company's future trend, while fundamental analysis interprets the trend and identifies relevant fundamental factors and possibilities.
B20: Reference
B21: Market Price | C21: =Market_Price -> 8.15 | D21: =Market_currency -> HKD
B22: No Growth Value per share | C22: =IF(valuation_method="DCF",DCF!C12,DDM!C7) -> 9.378672 | D22: =Market_currency -> HKD
B24: Base | E24: Business Story
B25: High Growth Period (HGP) | C25: =C18 -> 10
B26: High Growth Rate (HGR) | C26: 0
B27: Value per share | C27: =IF(valuation_method="DCF",DCF!E76,DDM!E71) -> 9.378672 | D27: =Market_currency -> HKD
B28: Probabilities | C28: 0.55
B30: Pessimistic | E30: Business Story
B31: High Growth Period (HGP) | C31: =C18 -> 10
B32: High Growth Rate (HGR) | C32: -0.02
B33: Value per share | C33: =IF(valuation_method="DCF",DCF!E77,DDM!E72) -> 9.1609122 | D33: =Market_currency -> HKD
B34: Probabilities | C34: 0.25
B36: Optimistic | E36: Business Story
B37: High Growth Period (HGP) | C37: =C18 -> 10
B38: High Growth Rate (HGR) | C38: 0.02
B39: Value per share | C39: =IF(valuation_method="DCF",DCF!E75,DDM!E70) -> 9.6179514 | D39: =Market_currency -> HKD
B40: Probabilities | C40: =1-C28-C34 -> 0.2
B42: Expected Value = | C42: =C27*C28+C33*C34+C39*C40 -> 9.3720879 | D42: =Market_currency -> HKD
B44: Extreme Scenarios
B45: Assumption
B46: High Growth Period (HGP) | C46: 15
B48: Devil's advocate | E48: Business Story
B49: High Growth Period (HGP) | C49: =C46 -> 15
B50: High Growth Rate (HGR) | C50: -0.1
B51: Value per share | C51: =IF(valuation_method="DCF",DCF!E78,DDM!E73) -> 8.1183547 | D51: =Market_currency -> HKD
B52: Probabilities | C52: 0.05
B54: Snowball Scenario | E54: Business Story
B55: High Growth Period (HGP) | C55: =C46 -> 15
B56: High Growth Rate (HGR) | C56: 0.05
B57: Value per share | C57: =IF(valuation_method="DCF",DCF!E74,DDM!E69) -> 10.467204 | D57: =Market_currency -> HKD
B58: Probabilities | C58: 0.05
B60: Expected Value = | C60: =C51*C52+C57*C58+C42*(1-C52-C58) -> 9.3641571 | D60: =Market_currency -> HKD | E60: is assumed to be materialized in | F60: =Thesis!F28 -> 3
B62: Growth Classification
B63: Equity Value Driving Factors | E63: Note on Manual Adjustments
B64: High Growth Period (HGP) | C64: =C18 -> 10 | E64: Use general Scenarios' HGP assumption
B65: High Growth Rate (HGR) | C65: -0.0015334906 | E65: Use Excel Goal Seek to find the HGR
B66: Equity Value per share | C66: =IF(valuation_method="DCF",DCF!C18,DDM!C13) -> 9.3612446 | D66: =Market_currency -> HKD | E66: Set to Expected Equity Value
B68: Type of Company | E68: Note on the logic
B69: Negative Growth | C69: =IF(C60<C22,"Y","N") -> Y
B70: Low Growth | C70: =IF(C69="Y","N",IF(C65>8%,"N","Y")) -> N | E70: >8% is Categorized as High Growth
B71: High Growth | C71: =IF(C65>8%,"Y","N") -> N
B72: Asset Play | C72: =IF(F72>50%,"Y","N") -> Y | E72: The Non-FCF Value is of the Expected Value, at | F72: =BS!D89/C60 -> 0.61346403
B74: Margin of Safety (MOS)
B75: Inputs
B76: Expected Holding Period | C76: =F60 -> 3
B77: Annual Dividend per share | C77: =Normalized_FCF!C90 -> 0.58 | D77: =Market_currency -> HKD
B79: Target Price Output
B80: @Target Annual Return | C80: =Thesis!F29 -> 0.3674
B81: PV(Dividends) | C81: =PV(C80, C76, -C77, 0) -> 0.96121041
B82: PV(Equity Value) | C82: =C60/(1+C80)^C76 -> 3.6625365
B83: Buy Below | C83: =C81+C82 -> 4.6237469 | D83: =Market_currency -> HKD | E83: at a MOS of | F83: =(1-C83/C60) -> 0.50622924
B85: Current Return Output
B86: @Market Price | C86: =Market_Price -> 8.15 | D86: =Market_currency -> HKD
B87: Annual Return | C87: =IRR(OFFSET($I$3, 0, 0, $C$76 + 1, 1)) -> 0.1155057
B89: Entry Price Output
B90: @ Entry Yield | C90: =Thesis!F30 -> 0.2174
B91: PV(Dividends) | C91: =PV(C90, C76, -C77, 0) -> 1.1892325
B92: PV(Equity Value) | C92: =C60/(1+C90)^C76 -> 5.1900172
B93: Buy Below | C93: =C91+C92 -> 6.3792497 | D93: =Market_currency -> HKD | E93: at a MOS of | F93: =(1-C93/C60) -> 0.31875879
B95: Sell Price Output
B96: @Selling Yield | C96: =Thesis!F31 -> 0.075
B97: PV(Dividends) | C97: =PV(C96, C76, -C77, 0) -> 1.5083049
B98: PV(Equity Value) | C98: =C60/(1+C96)^C76 -> 7.5377772
B99: Sell Above | C99: =C97+C98 -> 9.0460821 | D99: HKD | E99: at a MOS of | F99: =(1-C99/C60) -> 0.033967279
B101: Exit Price Output
B102: @Benchmark Yield | C102: =Thesis!F32 -> 0.1174
B103: PV(Dividends) | C103: =PV(C102, C76, -C77, 0) -> 1.3993098
B104: PV(Equity Value) | C104: =C60/(1+C102)^C76 -> 6.7118569
B105: Sell Above | C105: =C103+C104 -> 8.1111667 | D105: HKD | E105: at a MOS of | F105: =(1-C105/C66) -> 0.13353758
E107: Inputs Legend
E108: Font Color | F108: Fact or Verified Data
E109: Font Color | F109: Subjective Driving Factors
E110: Font Color | F110: Subjective Non-Driving Factors
