Workbook
Name Common_Shares: Thesis!$C$11
Name Equity_Cost: Valuation_Model!$C$5
Name Exchange_Rate: Thesis!$C$13
Name Market_currency: Thesis!$D$10
Name Market_Price: Thesis!$C$10
Name Reporting_currency: Thesis!$C$12
Name Terminal_Growth: Valuation_Model!$F$4

Sheet Thesis
B1: Investment Thesis for | C1: 周生生 | D1: 0116.HK
B2: Model last updated: | C2: 45643 | E2: Status: Not Held
A3: Introduction
B4: Comapny Information
B5: Comp_Sector: | C5: C0003
B6: Review Interval: | C6: 8
B7: Review Date: | C7: =EOMONTH(EDATE(BS!C1,Thesis!C6),0) -> 45716
B9: =D1&" Stock Information" -> 0116.HK Stock Information
B10: Market Price: | C10: 7 | D10: HKD
B11: Number of Shares: | C11: 677426000
B12: Reporting Currency: | C12: HKD
B13: Exchange Rate: | C13: 1 | D13: =IF(C12=D10,D10,C12&"/"&D10) -> HKD
B14: Capitalization: | C14: =Thesis!C10*Thesis!C11/1000000 -> 4741.982
A16: Step 1: Calculate FCFE
A18: ="1." -> 1. | B18: Adjusted FCFE Calculation
B19: Formula:
B20: Adjusted FCFE = Net Income + D&A – Maintenance Capex ± WCInv (if material).
B22: Variables | C22: =Data!C3 -> 1000
B23: Operating after-tax Profit = | C23: =Normalized_FCF!C16 -> 336835.71 | D23: =C12 -> HKD
B24: Non-Operating after-tax Profit = | C24: =Normalized_FCF!C11 -> 0
B25: Net Income = | C25: =C23+C24 -> 336835.71
B27: Adjusted FCFE = | C27: =Normalized_FCF!C19 -> 336835.71
B28: Adjusted FCFE per share = | C28: =C27/(Common_Shares/Data!C3) -> 0.49722878
B29: FCFE/Market Price = | C29: =C28/Market_Price -> 0.071032683
B31: Notes:
B32: 1. the model explicitly avoids aggressive growth assumptions and prioritizes downside protection.
B33: 2. Net borrowing is excluded (fixed at 0), and WCInv is only included if it materially distorts FCFE (>5% volatility).
B34: 3. Normalization: 5-year averages will smooth cyclicality for 590.HK.
A36: ="2." -> 2. | B36: Equity Cost of Capital (Buffett Method)
B37: Equity Cost of Capital (r) = | C37: 0.1
B39: Qualitative Adjustments
B40: Nonexistent moats | C40: 0 | D40: HK
B41: Weak balance sheets | C41: 0 | D41: Stable Business
B42: Poor management | C42: 0
B43: Qualitative Adjustments | C43: =SUM(C40:C42) -> 0
A45: ="3." -> 3. | B45: No-Growth DCF Valuation
B46: Key Metrics:
B47: Adjusted Earnings Yield = Adjusted FCFE / Market Cap.
B48: Intrinsic Value (No Growth) = Adjusted FCFE / Equity Cost of Capital.
B50: Decision Rule:
B51: Buy if Adjusted Earnings Yield > 7%
A53: ="4." -> 4. | B53: Growth Scenario Analysis
B54: Formula:
B55: g = (r × P - Adjusted FCFE) / (P + Adjusted FCFE)
B57: Phase Breakdown:
B58: High Growth: 5 years at 5%, then transitions to 3% perpetual growth.
B60: Scenario Analysis:
B61: Base Case
B62: Opertimistic Case
B63: Pessimistic Case
B65: Valuation
B66: the Equity Value will be conservatively realized
B67: over a holding period of | C67: 3
B68: Target Return | C68: 0.2
B69: Margin of Safety: | C69: =Scenarios!F83 -> -0.2026625
B71: Output:
B72: Buy price range incorporating a 15–20% margin of safety (e.g., HKD 10–14/share).
A74: ="5." -> 5. | B74: Equity Value Calculation
B75: Formula:
B76: Equity Value = Intrinsic Value (with user-selected implied g) + Non-operating Assets - Interest-bearing Debt
B78: Key Adjustments:
B79: Non-operating Assets: Include cash, marketable securities, real estate, etc., at market value.
B80: Debt: Subtract total interest-bearing debt (market value if distressed).
A82: Conclusion
B84: Scenarios | C84: HGR | D84: Value per share | E84: Probabilities
B85: Optimistic
B86: Base
B87: No Growth
B88: Pessimistic
B90: Price Target: | C90: =Scenarios!C83 -> 4.2251801 | D90: =Reporting_currency -> HKD
A92: KEY EXCLUSIONS & LIMITATIONS
B93: Conservative Bias:
B94: Excludes net borrowing, potentially undervaluing firms with debt efficiency.
B96: Growth Constraints:
B97: Perpetual growth capped at 3%, penalizing high-growth companies.
B99: Subjective Adjustments:
B100: Non-operating assets and debt require manual review.

Sheet Data
B1: =Thesis!C12 -> HKD | C1: 45291 | D1: =EOMONTH(EDATE(C1,-12),0) -> 44926 | E1: =EOMONTH(EDATE(D1,-12),0) -> 44561 | F1: =EOMONTH(EDATE(E1,-12),0) -> 44196 | G1: =EOMONTH(EDATE(F1,-12),0) -> 43830 | H1: =EOMONTH(EDATE(G1,-12),0) -> 43465 | I1: =EOMONTH(EDATE(H1,-12),0) -> 43100 | J1: =EOMONTH(EDATE(I1,-12),0) -> 42735 | K1: =EOMONTH(EDATE(J1,-12),0) -> 42369 | ... M1: =EOMONTH(EDATE(L1,-12),0) -> 41639
B2: Data (Dirty)
B3: Income Statement | C3: 1000
B4: Sales | C4: 25013339 | D4: 19751940 | E4: 21987559 | F4: 14997541 | G4: 17736226 | H4: 18806342 | I4: 59156.4 | J4: 51245.5
B5: COGS | C5: 18409837 | D5: 15140010 | E5: 16431474 | F5: 10877614 | G5: 12958750 | H5: 14175208 | I5: 42943 | J5: 36282.8
B6: OPEX | C6: 5225366 | D6: 4709830 | E6: 4571128 | F6: 3136777 | G6: 3470831 | H6: 3388718 | I6: 10960.1 | J6: 10347.1
B7: Incl. Selling Expenses
B8: R&D
B9: Share of JV or associate Results
B10: Dividend or Interests from FA
B11: Investment property
B12: Interest Expense | C12: 129899 | D12: 81860 | E12: 60486 | F12: 76137 | G12: 89162 | H12: 36991 | I12: 243.7 | J12: 236.6
B13: Interest Income | C13: 183.1 | D13: 227.8
B14: Income Tax Paid
B15: Reported Net Income | D15: -10604 | E15: -3488 | F15: 0 | G15: 0 | H15: 0 | I15: 108.4 | J15: 95.8
B16: Non-controling Interests | C16: -13497 | D16: -10604 | E16: -3488 | F16: 0 | G16: 0 | H16: 0
B18: Cash Flow Statement
B19: D&A
B20: CAPX
B21: WCInv
B22: ="Dividend per share ("&Market_currency&")" -> Dividend per share (HKD) | C22: 0.55
B24: Balance Sheet
B25: ST AR
B26: ST Inventory
B27: Total Liabilities | C27: 6730302 | D27: 6780629 | E27: 5345297 | F27: 4807353
B28: Total Equity | C28: 12167429 | D28: 11870228 | E28: 12743461 | F28: 12019114
B29: Non-common Interest | C29: -40166 | D29: -20315 | E29: -9659 | F29: 0
B31: Other Data
B32: Contingent Liabilities | C32: 229911 | D32: 119344 | E32: 219055 | F32: 94344
B34: IS & CF Statements (Clean)
B35: Income Statement
B36: Sales | C36: =IF(C$4="","",C4) -> 25013339 | D36: =IF(D$4="","",D4) -> 19751940 | E36: =IF(E$4="","",E4) -> 21987559 | F36: =IF(F$4="","",F4) -> 14997541 | G36: =IF(G$4="","",G4) -> 17736226 | H36: =IF(H$4="","",H4) -> 18806342 | I36: =IF(I$4="","",I4) -> 59156.4 | J36: =IF(J$4="","",J4) -> 51245.5 | ... M36: =IF(M$4="","",M4)
B37: COGS | C37: =IF(C$4="","",-C5) -> -18409837 | D37: =IF(D$4="","",-D5) -> -15140010 | E37: =IF(E$4="","",-E5) -> -16431474 | F37: =IF(F$4="","",-F5) -> -10877614 | G37: =IF(G$4="","",-G5) -> -12958750 | H37: =IF(H$4="","",-H5) -> -14175208 | I37: =IF(I$4="","",-I5) -> -42943 | J37: =IF(J$4="","",-J5) -> -36282.8 | ... M37: =IF(M$4="","",-M5)
B38: Gross Margin | C38: =IF(C36="","",C36+C37) -> 6603502 | D38: =IF(D36="","",D36+D37) -> 4611930 | E38: =IF(E36="","",E36+E37) -> 5556085 | F38: =IF(F36="","",F36+F37) -> 4119927 | G38: =IF(G36="","",G36+G37) -> 4777476 | H38: =IF(H36="","",H36+H37) -> 4631134 | I38: =IF(I36="","",I36+I37) -> 16213.4 | J38: =IF(J36="","",J36+J37) -> 14962.7 | ... M38: =IF(M36="","",M36+M37)
B39: OPEX | C39: =IF(C$4="","",-C6) -> -5225366 | D39: =IF(D$4="","",-D6) -> -4709830 | E39: =IF(E$4="","",-E6) -> -4571128 | F39: =IF(F$4="","",-F6) -> -3136777 | G39: =IF(G$4="","",-G6) -> -3470831 | H39: =IF(H$4="","",-H6) -> -3388718 | I39: =IF(I$4="","",-I6) -> -10960.1 | J39: =IF(J$4="","",-J6) -> -10347.1 | ... M39: =IF(M$4="","",-M6)
B40: Incl. Selling Expenses | C40: =IF(C$4="","",-C7) -> 0 | D40: =IF(D$4="","",-D7) -> 0 | E40: =IF(E$4="","",-E7) -> 0 | F40: =IF(F$4="","",-F7) -> 0 | G40: =IF(G$4="","",-G7) -> 0 | H40: =IF(H$4="","",-H7) -> 0 | I40: =IF(I$4="","",-I7) -> 0 | J40: =IF(J$4="","",-J7) -> 0 | ... M40: =IF(M$4="","",-M7)
B41: Incl. Other Opex | C41: =IF(C$4="","",C39-C40) -> -5225366 | D41: =IF(D$4="","",D39-D40) -> -4709830 | E41: =IF(E$4="","",E39-E40) -> -4571128 | F41: =IF(F$4="","",F39-F40) -> -3136777 | G41: =IF(G$4="","",G39-G40) -> -3470831 | H41: =IF(H$4="","",H39-H40) -> -3388718 | I41: =IF(I$4="","",I39-I40) -> -10960.1 | J41: =IF(J$4="","",J39-J40) -> -10347.1 | ... M41: =IF(M$4="","",M39-M40)
B42: R&D | C42: =IF(C$4="","",-C8) -> 0 | D42: =IF(D$4="","",-D8) -> 0 | E42: =IF(E$4="","",-E8) -> 0 | F42: =IF(F$4="","",-F8) -> 0 | G42: =IF(G$4="","",-G8) -> 0 | H42: =IF(H$4="","",-H8) -> 0 | I42: =IF(I$4="","",-I8) -> 0 | J42: =IF(J$4="","",-J8) -> 0 | ... M42: =IF(M$4="","",-M8)
B43: Operating EBIT | C43: =IF(C$4="","",C38+C39+C42) -> 1378136 | D43: =IF(D$4="","",D38+D39+D42) -> -97900 | E43: =IF(E$4="","",E38+E39+E42) -> 984957 | F43: =IF(F$4="","",F38+F39+F42) -> 983150 | G43: =IF(G$4="","",G38+G39+G42) -> 1306645 | H43: =IF(H$4="","",H38+H39+H42) -> 1242416 | I43: =IF(I$4="","",I38+I39+I42) -> 5253.3 | J43: =IF(J$4="","",J38+J39+J42) -> 4615.6 | ... M43: =IF(M$4="","",M38+M39+M42)
B44: Non-operating EBIT | C44: =IF(C$4="","",C47-C46-C45-C43) -> -1248420.1 | D44: =IF(D$4="","",D47-D46-D45-D43) -> 168928.2 | E44: =IF(E$4="","",E47-E46-E45-E43) -> -927959 | F44: =IF(F$4="","",F47-F46-F45-F43) -> -907013 | G44: =IF(G$4="","",G47-G46-G45-G43) -> -1217483 | H44: =IF(H$4="","",H47-H46-H45-H43) -> -1205425 | I44: =IF(I$4="","",I47-I46-I45-I43) -> -4901.2 | J44: =IF(J$4="","",J47-J46-J45-J43) -> -4283.2 | ... M44: =IF(M$4="","",M47-M46-M45-M43)
B45: Net Interest Income | C45: =IF(C$4="","",C51+C52) -> -129715.9 | D45: =IF(D$4="","",D51+D52) -> -81632.2 | E45: =IF(E$4="","",E51+E52) -> -60486 | F45: =IF(F$4="","",F51+F52) -> -76137 | G45: =IF(G$4="","",G51+G52) -> -89162 | H45: =IF(H$4="","",H51+H52) -> -36991 | I45: =IF(I$4="","",I51+I52) -> -243.7 | J45: =IF(J$4="","",J51+J52) -> -236.6 | ... M45: =IF(M$4="","",M51+M52)
B46: Income Tax Paid | C46: =IF(C$4="","",-C14) -> 0 | D46: =IF(D$4="","",-D14) -> 0 | E46: =IF(E$4="","",-E14) -> 0 | F46: =IF(F$4="","",-F14) -> 0 | G46: =IF(G$4="","",-G14) -> 0 | H46: =IF(H$4="","",-H14) -> 0 | I46: =IF(I$4="","",-I14) -> 0 | J46: =IF(J$4="","",-J14) -> 0 | ... M46: =IF(M$4="","",-M14)
B47: Reported Net Income | C47: =IF(C$4="","",C15) -> 0 | D47: =IF(D$4="","",D15) -> -10604 | E47: =IF(E$4="","",E15) -> -3488 | F47: =IF(F$4="","",F15) -> 0 | G47: =IF(G$4="","",G15) -> 0 | H47: =IF(H$4="","",H15) -> 0 | I47: =IF(I$4="","",I15) -> 108.4 | J47: =IF(J$4="","",J15) -> 95.8 | ... M47: =IF(M$4="","",M15)
B48: Non-controling Interests | C48: =IF(C$4="","",MIN(-C16,0)) -> 0 | D48: =IF(D$4="","",MIN(-D16,0)) -> 0 | E48: =IF(E$4="","",MIN(-E16,0)) -> 0 | F48: =IF(F$4="","",MIN(-F16,0)) -> 0 | G48: =IF(G$4="","",MIN(-G16,0)) -> 0 | H48: =IF(H$4="","",MIN(-H16,0)) -> 0 | I48: =IF(I$4="","",MIN(-I16,0)) -> 0 | J48: =IF(J$4="","",MIN(-J16,0)) -> 0 | ... M48: =IF(M$4="","",MIN(-M16,0))
B50: Net Interest Income
B51: Interest Expense | C51: =IF(C$4="","",-C12) -> -129899 | D51: =IF(D$4="","",-D12) -> -81860 | E51: =IF(E$4="","",-E12) -> -60486 | F51: =IF(F$4="","",-F12) -> -76137 | G51: =IF(G$4="","",-G12) -> -89162 | H51: =IF(H$4="","",-H12) -> -36991 | I51: =IF(I$4="","",-I12) -> -243.7 | J51: =IF(J$4="","",-J12) -> -236.6 | ... M51: =IF(M$4="","",-M12)
B52: Interest Income | C52: =IF(C$4="","",C13) -> 183.1 | D52: =IF(D$4="","",D13) -> 227.8 | E52: =IF(E$4="","",E13) -> 0 | F52: =IF(F$4="","",F13) -> 0 | G52: =IF(G$4="","",G13) -> 0 | H52: =IF(H$4="","",H13) -> 0 | I52: =IF(I$4="","",I13) -> 0 | J52: =IF(J$4="","",J13) -> 0 | ... M52: =IF(M$4="","",M13)
B54: Non-operating EBIT
B55: Share of JV or associate Results | C55: =IF(C$4="","",C9) -> 0 | D55: =IF(D$4="","",D9) -> 0 | E55: =IF(E$4="","",E9) -> 0 | F55: =IF(F$4="","",F9) -> 0 | G55: =IF(G$4="","",G9) -> 0 | H55: =IF(H$4="","",H9) -> 0 | I55: =IF(I$4="","",I9) -> 0 | J55: =IF(J$4="","",J9) -> 0 | ... M55: =IF(M$4="","",M9)
B56: Dividend or Interests from FA | C56: =IF(C$4="","",C10) -> 0 | D56: =IF(D$4="","",D10) -> 0 | E56: =IF(E$4="","",E10) -> 0 | F56: =IF(F$4="","",F10) -> 0 | G56: =IF(G$4="","",G10) -> 0 | H56: =IF(H$4="","",H10) -> 0 | I56: =IF(I$4="","",I10) -> 0 | J56: =IF(J$4="","",J10) -> 0 | ... M56: =IF(M$4="","",M10)
B57: Investment property | C57: =IF(C$4="","",C11) -> 0 | D57: =IF(D$4="","",D11) -> 0 | E57: =IF(E$4="","",E11) -> 0 | F57: =IF(F$4="","",F11) -> 0 | G57: =IF(G$4="","",G11) -> 0 | H57: =IF(H$4="","",H11) -> 0 | I57: =IF(I$4="","",I11) -> 0 | J57: =IF(J$4="","",J11) -> 0 | ... M57: =IF(M$4="","",M11)
B58: Other Non-operating Income | C58: =IF(C$4="","",C44-C55-C56-C57) -> -1248420.1 | D58: =IF(D$4="","",D44-D55-D56-D57) -> 168928.2 | E58: =IF(E$4="","",E44-E55-E56-E57) -> -927959 | F58: =IF(F$4="","",F44-F55-F56-F57) -> -907013 | G58: =IF(G$4="","",G44-G55-G56-G57) -> -1217483 | H58: =IF(H$4="","",H44-H55-H56-H57) -> -1205425 | I58: =IF(I$4="","",I44-I55-I56-I57) -> -4901.2 | J58: =IF(J$4="","",J44-J55-J56-J57) -> -4283.2 | ... M58: =IF(M$4="","",M44-M55-M56-M57)
B60: Cash Flow Statement
B61: D&A | C61: =IF(C$4="","",-C19) -> 0 | D61: =IF(D$4="","",-D19) -> 0 | E61: =IF(E$4="","",-E19) -> 0 | F61: =IF(F$4="","",-F19) -> 0 | G61: =IF(G$4="","",-G19) -> 0 | H61: =IF(H$4="","",-H19) -> 0 | I61: =IF(I$4="","",-I19) -> 0 | J61: =IF(J$4="","",-J19) -> 0 | ... M61: =IF(M$4="","",-M19)
B62: CAPX | C62: =IF(C$4="","",-C20) -> 0 | D62: =IF(D$4="","",-D20) -> 0 | E62: =IF(E$4="","",-E20) -> 0 | F62: =IF(F$4="","",-F20) -> 0 | G62: =IF(G$4="","",-G20) -> 0 | H62: =IF(H$4="","",-H20) -> 0 | I62: =IF(I$4="","",-I20) -> 0 | J62: =IF(J$4="","",-J20) -> 0 | ... M62: =IF(M$4="","",-M20)
B63: WCInv | C63: =IF(C$4="","",-C21) -> 0 | D63: =IF(D$4="","",-D21) -> 0 | E63: =IF(E$4="","",-E21) -> 0 | F63: =IF(F$4="","",-F21) -> 0 | G63: =IF(G$4="","",-G21) -> 0 | H63: =IF(H$4="","",-H21) -> 0 | I63: =IF(I$4="","",-I21) -> 0 | J63: =IF(J$4="","",-J21) -> 0 | ... M63: =IF(M$4="","",-M21)
B64: Dividend per share | C64: =IF(C$4="","",C22) -> 0.55 | D64: =IF(D$4="","",D22) -> 0 | E64: =IF(E$4="","",E22) -> 0 | F64: =IF(F$4="","",F22) -> 0 | G64: =IF(G$4="","",G22) -> 0 | H64: =IF(H$4="","",H22) -> 0 | I64: =IF(I$4="","",I22) -> 0 | J64: =IF(J$4="","",J22) -> 0 | ... M64: =IF(M$4="","",M22)
B66: YoY %
B67: =B36 -> Sales | C67: =IF(D$36="","",C36/D36-1) -> 0.26637378 | D67: =IF(E$36="","",D36/E36-1) -> -0.10167654 | E67: =IF(F$36="","",E36/F36-1) -> 0.46607761 | F67: =IF(G$36="","",F36/G36-1) -> -0.15441194 | G67: =IF(H$36="","",G36/H36-1) -> -0.056901869 | H67: =IF(I$36="","",H36/I36-1) -> 316.90883 | I67: =IF(J$36="","",I36/J36-1) -> 0.15437258 | J67: =IF(K$36="","",J36/K36-1) | ... M67: =IF(N$36="","",M36/N36-1)
B68: =B43 -> Operating EBIT | C68: =IF(D$36="","",C37/D37-1) -> 0.21597258 | D68: =IF(E$36="","",D37/E37-1) -> -0.078596966 | E68: =IF(F$36="","",E37/F37-1) -> 0.51057704 | F68: =IF(G$36="","",F37/G37-1) -> -0.16059697 | G68: =IF(H$36="","",G37/H37-1) -> -0.085815884 | H68: =IF(I$36="","",H37/I37-1) -> 329.09357 | I68: =IF(J$36="","",I37/J37-1) -> 0.18356356 | J68: =IF(K$36="","",J37/K37-1) | ... M68: =IF(N$36="","",M37/N37-1)
B69: =B58 -> Other Non-operating Income | C69: =IF(D$36="","",C38/D38-1) -> 0.43183049 | D69: =IF(E$36="","",D38/E38-1) -> -0.16993171 | E69: =IF(F$36="","",E38/F38-1) -> 0.34858822 | F69: =IF(G$36="","",F38/G38-1) -> -0.13763523 | G69: =IF(H$36="","",G38/H38-1) -> 0.031599604 | H69: =IF(I$36="","",H38/I38-1) -> 284.6362 | I69: =IF(J$36="","",I38/J38-1) -> 0.083587855 | J69: =IF(K$36="","",J38/K38-1) | ... M69: =IF(N$36="","",M38/N38-1)
B70: =B47 -> Reported Net Income | C70: =IF(D$36="","",C39/D39-1) -> 0.10945958 | D70: =IF(E$36="","",D39/E39-1) -> 0.030343058 | E70: =IF(F$36="","",E39/F39-1) -> 0.45726904 | F70: =IF(G$36="","",F39/G39-1) -> -0.096246115 | G70: =IF(H$36="","",G39/H39-1) -> 0.024231287 | H70: =IF(I$36="","",H39/I39-1) -> 308.18678 | I70: =IF(J$36="","",I39/J39-1) -> 0.059243653 | J70: =IF(K$36="","",J39/K39-1) | ... M70: =IF(N$36="","",M39/N39-1)
B71: =B48 -> Non-controling Interests | C71: =IF(D$36="","",C64/D64-1) -> #DIV/0! | D71: =IF(E$36="","",D64/E64-1) -> #DIV/0! | E71: =IF(F$36="","",E64/F64-1) -> #DIV/0! | F71: =IF(G$36="","",F64/G64-1) -> #DIV/0! | G71: =IF(H$36="","",G64/H64-1) -> #DIV/0! | H71: =IF(I$36="","",H64/I64-1) -> #DIV/0! | I71: =IF(J$36="","",I64/J64-1) -> #DIV/0! | J71: =IF(K$36="","",J64/K64-1) | ... M71: =IF(N$36="","",M64/N64-1)
B73: Balance Sheet (Clean)
B74: Balance Sheet
B75: Total Assets | C75: =IF(C$4="","",C78+C79) -> 18897731 | D75: =IF(D$4="","",D78+D79) -> 18650857 | E75: =IF(E$4="","",E78+E79) -> 18088758 | F75: =IF(F$4="","",F78+F79) -> 16826467 | G75: =IF(G$4="","",G78+G79) -> 0 | H75: =IF(H$4="","",H78+H79) -> 0 | I75: =IF(I$4="","",I78+I79) -> 0 | J75: =IF(J$4="","",J78+J79) -> 0 | ... M75: =IF(M$4="","",M78+M79)
B76: Incl. ST AR | C76: =IF(C$4="","",C25) -> 0 | D76: =IF(D$4="","",D25) -> 0 | E76: =IF(E$4="","",E25) -> 0 | F76: =IF(F$4="","",F25) -> 0 | G76: =IF(G$4="","",G25) -> 0 | H76: =IF(H$4="","",H25) -> 0
B77: Incl. ST Inventory | C77: =IF(C$4="","",C26) -> 0 | D77: =IF(D$4="","",D26) -> 0 | E77: =IF(E$4="","",E26) -> 0 | F77: =IF(F$4="","",F26) -> 0 | G77: =IF(G$4="","",G26) -> 0 | H77: =IF(H$4="","",H26) -> 0
B78: Total Liabilities | C78: =IF(C$4="","",C27) -> 6730302 | D78: =IF(D$4="","",D27) -> 6780629 | E78: =IF(E$4="","",E27) -> 5345297 | F78: =IF(F$4="","",F27) -> 4807353 | G78: =IF(G$4="","",G27) -> 0 | H78: =IF(H$4="","",H27) -> 0 | I78: =IF(I$4="","",I27) -> 0 | J78: =IF(J$4="","",J27) -> 0 | ... M78: =IF(M$4="","",M27)
B79: Total Equity | C79: =IF(C$4="","",C28) -> 12167429 | D79: =IF(D$4="","",D28) -> 11870228 | E79: =IF(E$4="","",E28) -> 12743461 | F79: =IF(F$4="","",F28) -> 12019114 | G79: =IF(G$4="","",G28) -> 0 | H79: =IF(H$4="","",H28) -> 0 | I79: =IF(I$4="","",I28) -> 0 | J79: =IF(J$4="","",J28) -> 0 | ... M79: =IF(M$4="","",M28)

Sheet Normalized_FCF
B1: =Thesis!C12 -> HKD | C1: Normalized | G1: =Data!C1 -> 45291 | H1: =EOMONTH(EDATE(G1,-12),0) -> 44926 | I1: =EOMONTH(EDATE(H1,-12),0) -> 44561 | J1: =EOMONTH(EDATE(I1,-12),0) -> 44196 | K1: =EOMONTH(EDATE(J1,-12),0) -> 43830 | L1: =EOMONTH(EDATE(K1,-12),0) -> 43465 | M1: =EOMONTH(EDATE(L1,-12),0) -> 43100 | N1: =EOMONTH(EDATE(M1,-12),0) -> 42735 | O1: =EOMONTH(EDATE(N1,-12),0) -> 42369 | ... Q1: =EOMONTH(EDATE(P1,-12),0) -> 41639
B2: FCFE Analysis | E2: Notes
B3: Adjusted FCFE | C3: =Data!C3 -> 1000
B4: Sales | C4: =AVERAGE(G4:I4) -> 22250946 | G4: =Data!C36 -> 25013339 | H4: =Data!D36 -> 19751940 | I4: =Data!E36 -> 21987559 | J4: =Data!F36 -> 14997541 | K4: =Data!G36 -> 17736226 | L4: =Data!H36 -> 18806342 | M4: =Data!I36 -> 59156.4 | N4: =Data!J36 -> 51245.5 | ... Q4: =Data!M36
B5: Variable Costs | C5: =C25 -> -16716115 | G5: =G25 -> -18409837 | H5: =H25 -> -15140010 | I5: =I25 -> -16431474 | J5: =J25 -> -10877614 | K5: =K25 -> -12958750 | L5: =L25 -> -14175208 | M5: =M25 -> -42943 | N5: =N25 -> -36282.8 | ... Q5: =Q25
B6: Contribution Margin | C6: =C4+C5 -> 5534830.8 | G6: =IF(G4="","",G4+G5) -> 6603502 | H6: =IF(H4="","",H4+H5) -> 4611930 | I6: =IF(I4="","",I4+I5) -> 5556085 | J6: =IF(J4="","",J4+J5) -> 4119927 | K6: =IF(K4="","",K4+K5) -> 4777476 | L6: =IF(L4="","",L4+L5) -> 4631134 | M6: =IF(M4="","",M4+M5) -> 16213.4 | N6: =IF(N4="","",N4+N5) -> 14962.7 | ... Q6: =IF(Q4="","",Q4+Q5)
B7: Fixed Costs | C7: =C35 -> -4967598 | G7: =G35 -> -5225366 | H7: =H35 -> -4709830 | I7: =I35 -> -4571128 | J7: =J35 -> -3136777 | K7: =K35 -> -3470831 | L7: =L35 -> -3388718 | M7: =M35 -> -10960.1 | N7: =N35 -> -10347.1 | ... Q7: =Q35
B8: Operating EBIT | C8: =C6+C7 -> 567232.79 | G8: =IF(G$4="","",G6+G7) -> 1378136 | H8: =IF(H$4="","",H6+H7) -> -97900 | I8: =IF(I$4="","",I6+I7) -> 984957 | J8: =IF(J$4="","",J6+J7) -> 983150 | K8: =IF(K$4="","",K6+K7) -> 1306645 | L8: =IF(L$4="","",L6+L7) -> 1242416 | M8: =IF(M$4="","",M6+M7) -> 5253.3 | N8: =IF(N$4="","",N6+N7) -> 4615.6 | ... Q8: =IF(Q$4="","",Q6+Q7)
B9: Add Back D&A | C9: =BS!$G$39*BS!D59 -> 0 | G9: =IF(Data!C61="","",-Data!C61) -> 0 | H9: =IF(Data!D61="","",-Data!D61) -> 0 | I9: =IF(Data!E61="","",-Data!E61) -> 0 | J9: =IF(Data!F61="","",-Data!F61) -> 0 | K9: =IF(Data!G61="","",-Data!G61) -> 0 | L9: =IF(Data!H61="","",-Data!H61) -> 0 | M9: =IF(Data!I61="","",-Data!I61) -> 0 | N9: =IF(Data!J61="","",-Data!J61) -> 0 | ... Q9: =IF(Data!M61="","",-Data!M61)
B10: Maintenance Capex | C10: =-C4*C77 -> 0 | G10: =Data!C62 -> 0 | H10: =Data!D62 -> 0 | I10: =Data!E62 -> 0 | J10: =Data!F62 -> 0 | K10: =Data!G62 -> 0 | L10: =Data!H62 -> 0 | M10: =Data!I62 -> 0 | N10: =Data!J62 -> 0 | ... Q10: =Data!M62
B11: Non-Operating EBIT | C11: =C62 -> 0 | E11: Stable Non-Operating CF | G11: =G62 -> -1248420.1 | H11: =H62 -> 168928.2 | I11: =I62 -> -927959 | J11: =J62 -> -907013 | K11: =K62 -> -1217483 | L11: =L62 -> -1205425 | M11: =M62 -> -4901.2 | N11: =N62 -> -4283.2 | ... Q11: =Q62
B12: Net Interest Income | C12: =C49 -> -129783.82 | G12: =G49 -> -129715.9 | H12: =H49 -> -81632.2 | I12: =I49 -> -60486 | J12: =J49 -> -76137 | K12: =K49 -> -89162 | L12: =L49 -> -36991 | M12: =M49 -> -243.7 | N12: =N49 -> -236.6 | ... Q12: =Q49
B13: Pre-tax Profit | C13: =SUM(C8:C12) -> 437448.97 | G13: =IF(G$4="","",SUM(G8:G12)) -> 0 | H13: =IF(H$4="","",SUM(H8:H12)) -> -10604 | I13: =IF(I$4="","",SUM(I8:I12)) -> -3488 | J13: =IF(J$4="","",SUM(J8:J12)) -> 0 | K13: =IF(K$4="","",SUM(K8:K12)) -> 0 | L13: =IF(L$4="","",SUM(L8:L12)) -> 0 | M13: =IF(M$4="","",SUM(M8:M12)) -> 108.4 | N13: =IF(N$4="","",SUM(N8:N12)) -> 95.8 | ... Q13: =IF(Q$4="","",SUM(Q8:Q12))
B14: Income Tax | C14: =-C13*C43 -> -100613.26 | G14: =Data!C46 -> 0 | H14: =Data!D46 -> 0 | I14: =Data!E46 -> 0 | J14: =Data!F46 -> 0 | K14: =Data!G46 -> 0 | L14: =Data!H46 -> 0 | M14: =Data!I46 -> 0 | N14: =Data!J46 -> 0 | ... Q14: =Data!M46
B15: Non-controling Interests | C15: =-C4*C82 -> 0 | G15: =Data!C48 -> 0 | H15: =Data!D48 -> 0 | I15: =Data!E48 -> 0 | J15: =Data!F48 -> 0 | K15: =Data!G48 -> 0 | L15: =Data!H48 -> 0 | M15: =Data!I48 -> 0 | N15: =Data!J48 -> 0 | ... Q15: =Data!M48
B16: After-tax Profit | C16: =SUM(C13:C15) -> 336835.71 | G16: =IF(G$4="","",SUM(G13:G15)) -> 0 | H16: =IF(H$4="","",SUM(H13:H15)) -> -10604 | I16: =IF(I$4="","",SUM(I13:I15)) -> -3488 | J16: =IF(J$4="","",SUM(J13:J15)) -> 0 | K16: =IF(K$4="","",SUM(K13:K15)) -> 0 | L16: =IF(L$4="","",SUM(L13:L15)) -> 0 | M16: =IF(M$4="","",SUM(M13:M15)) -> 108.4 | N16: =IF(N$4="","",SUM(N13:N15)) -> 95.8 | ... Q16: =IF(Q$4="","",SUM(Q13:Q15))
B17: WCInv | C17: =-C4*C84 -> 0 | E17: WCInv is excluded
B18: Net Borrowing | C18: =-C4*C85 -> 0 | E18: Net borrowing is excluded
B19: Total FCFE | C19: =SUM(C16:C18) -> 336835.71 | G19: =IF(G$4="","",SUM(G16:G18)) -> 0 | H19: =IF(H$4="","",SUM(H16:H18)) -> -10604 | I19: =IF(I$4="","",SUM(I16:I18)) -> -3488 | J19: =IF(J$4="","",SUM(J16:J18)) -> 0 | K19: =IF(K$4="","",SUM(K16:K18)) -> 0 | L19: =IF(L$4="","",SUM(L16:L18)) -> 0 | M19: =IF(M$4="","",SUM(M16:M18)) -> 108.4 | N19: =IF(N$4="","",SUM(N16:N18)) -> 95.8 | ... Q19: =IF(Q$4="","",SUM(Q16:Q18))
B21: Operating Cost Structure | E21: Notes
B22: Variable Costs
B23: COGS | C23: =-C4*C28 -> -16716115 | G23: =Data!C37 -> -18409837 | H23: =Data!D37 -> -15140010 | I23: =Data!E37 -> -16431474 | J23: =Data!F37 -> -10877614 | K23: =Data!G37 -> -12958750 | L23: =Data!H37 -> -14175208 | M23: =Data!I37 -> -42943 | N23: =Data!J37 -> -36282.8 | ... Q23: =Data!M37
B24: Selling Expenses | C24: =-C4*C29 -> 0 | G24: =Data!C40 -> 0 | H24: =Data!D40 -> 0 | I24: =Data!E40 -> 0 | J24: =Data!F40 -> 0 | K24: =Data!G40 -> 0 | L24: =Data!H40 -> 0 | M24: =Data!I40 -> 0 | N24: =Data!J40 -> 0 | ... Q24: =Data!M40
B25: Variable Costs | C25: =C23+C24 -> -16716115 | G25: =IF(G$4="","",G23+G24) -> -18409837 | H25: =IF(H$4="","",H23+H24) -> -15140010 | I25: =IF(I$4="","",I23+I24) -> -16431474 | J25: =IF(J$4="","",J23+J24) -> -10877614 | K25: =IF(K$4="","",K23+K24) -> -12958750 | L25: =IF(L$4="","",L23+L24) -> -14175208 | M25: =IF(M$4="","",M23+M24) -> -42943 | N25: =IF(N$4="","",N23+N24) -> -36282.8 | ... Q25: =IF(Q$4="","",Q23+Q24)
B27: Variable Costs % of Sales
B28: COGS | C28: =AVERAGE(G28:H28) -> 0.75125414 | E28: Historical Average | G28: =IF(G$4="","",ABS(G23/G$4)) -> 0.73600078 | H28: =IF(H$4="","",ABS(H23/H$4)) -> 0.76650749 | I28: =IF(I$4="","",ABS(I23/I$4)) -> 0.74730778 | J28: =IF(J$4="","",ABS(J23/J$4)) -> 0.72529317 | K28: =IF(K$4="","",ABS(K23/K$4)) -> 0.7306374 | L28: =IF(L$4="","",ABS(L23/L$4)) -> 0.75374616 | M28: =IF(M$4="","",ABS(M23/M$4)) -> 0.72592315 | N28: =IF(N$4="","",ABS(N23/N$4)) -> 0.70801924 | ... Q28: =IF(Q$4="","",ABS(Q23/Q$4))
B29: =B24 -> Selling Expenses | C29: =AVERAGE(G29:H29) -> 0 | E29: Historical Average | G29: =IF(G$4="","",ABS(G24/G$4)) -> 0 | H29: =IF(H$4="","",ABS(H24/H$4)) -> 0 | I29: =IF(I$4="","",ABS(I24/I$4)) -> 0 | J29: =IF(J$4="","",ABS(J24/J$4)) -> 0 | K29: =IF(K$4="","",ABS(K24/K$4)) -> 0 | L29: =IF(L$4="","",ABS(L24/L$4)) -> 0 | M29: =IF(M$4="","",ABS(M24/M$4)) -> 0 | N29: =IF(N$4="","",ABS(N24/N$4)) -> 0 | ... Q29: =IF(Q$4="","",ABS(Q24/Q$4))
B30: Variable Costs | C30: =ABS(C25/$C$4) -> 0.75125414 | G30: =IF(G$4="","",ABS(G25/G$4)) -> 0.73600078 | H30: =IF(H$4="","",ABS(H25/H$4)) -> 0.76650749 | I30: =IF(I$4="","",ABS(I25/I$4)) -> 0.74730778 | J30: =IF(J$4="","",ABS(J25/J$4)) -> 0.72529317 | K30: =IF(K$4="","",ABS(K25/K$4)) -> 0.7306374 | L30: =IF(L$4="","",ABS(L25/L$4)) -> 0.75374616 | M30: =IF(M$4="","",ABS(M25/M$4)) -> 0.72592315 | N30: =IF(N$4="","",ABS(N25/N$4)) -> 0.70801924 | ... Q30: =IF(Q$4="","",ABS(Q25/Q$4))
B32: Fixed Costs
B33: G&A and other Opex | C33: =AVERAGE(G33:H33) -> -4967598 | E33: Historical Average | G33: =Data!C41 -> -5225366 | H33: =Data!D41 -> -4709830 | I33: =Data!E41 -> -4571128 | J33: =Data!F41 -> -3136777 | K33: =Data!G41 -> -3470831 | L33: =Data!H41 -> -3388718 | M33: =Data!I41 -> -10960.1 | N33: =Data!J41 -> -10347.1 | ... Q33: =Data!M41
B34: R&D | C34: =AVERAGE(G34:J34) -> 0 | E34: Historical Average | G34: =Data!C42 -> 0 | H34: =Data!D42 -> 0 | I34: =Data!E42 -> 0 | J34: =Data!F42 -> 0 | K34: =Data!G42 -> 0 | L34: =Data!H42 -> 0 | M34: =Data!I42 -> 0 | N34: =Data!J42 -> 0 | ... Q34: =Data!M42
B35: Fixed Costs | C35: =C33+C34 -> -4967598 | G35: =IF(G4="","",G33+G34) -> -5225366 | H35: =IF(H4="","",H33+H34) -> -4709830 | I35: =IF(I4="","",I33+I34) -> -4571128 | J35: =IF(J4="","",J33+J34) -> -3136777 | K35: =IF(K4="","",K33+K34) -> -3470831 | L35: =IF(L4="","",L33+L34) -> -3388718 | M35: =IF(M4="","",M33+M34) -> -10960.1 | N35: =IF(N4="","",N33+N34) -> -10347.1 | ... Q35: =IF(Q4="","",Q33+Q34)
B37: Fixed Costs % of Sales
B38: =B33 -> G&A and other Opex | C38: =ABS(C33/$C$4) -> 0.22325334 | G38: =IF(G$4="","",ABS(G33/G$4)) -> 0.20890318 | H38: =IF(H$4="","",ABS(H33/H$4)) -> 0.23844898 | I38: =IF(I$4="","",ABS(I33/I$4)) -> 0.20789611 | J38: =IF(J$4="","",ABS(J33/J$4)) -> 0.20915275 | K38: =IF(K$4="","",ABS(K33/K$4)) -> 0.19569163 | L38: =IF(L$4="","",ABS(L33/L$4)) -> 0.18019017 | M38: =IF(M$4="","",ABS(M33/M$4)) -> 0.18527328 | N38: =IF(N$4="","",ABS(N33/N$4)) -> 0.20191236 | ... Q38: =IF(Q$4="","",ABS(Q33/Q$4))
B39: =B34 -> R&D | C39: =ABS(C34/$C$4) -> 0 | G39: =IF(G$4="","",ABS(G34/G$4)) -> 0 | H39: =IF(H$4="","",ABS(H34/H$4)) -> 0 | I39: =IF(I$4="","",ABS(I34/I$4)) -> 0 | J39: =IF(J$4="","",ABS(J34/J$4)) -> 0 | K39: =IF(K$4="","",ABS(K34/K$4)) -> 0 | L39: =IF(L$4="","",ABS(L34/L$4)) -> 0 | M39: =IF(M$4="","",ABS(M34/M$4)) -> 0 | N39: =IF(N$4="","",ABS(N34/N$4)) -> 0 | ... Q39: =IF(Q$4="","",ABS(Q34/Q$4))
B40: Fixed Costs | C40: =ABS(C35/$C$4) -> 0.22325334 | G40: =IF(G$4="","",ABS(G35/G$4)) -> 0.20890318 | H40: =IF(H$4="","",ABS(H35/H$4)) -> 0.23844898 | I40: =IF(I$4="","",ABS(I35/I$4)) -> 0.20789611 | J40: =IF(J$4="","",ABS(J35/J$4)) -> 0.20915275 | K40: =IF(K$4="","",ABS(K35/K$4)) -> 0.19569163 | L40: =IF(L$4="","",ABS(L35/L$4)) -> 0.18019017 | M40: =IF(M$4="","",ABS(M35/M$4)) -> 0.18527328 | N40: =IF(N$4="","",ABS(N35/N$4)) -> 0.20191236 | ... Q40: =IF(Q$4="","",ABS(Q35/Q$4))
B42: Tax % of Pre-tax Profit
B43: Income Tax Rate | C43: 0.23 | E43: Use the highest past tax rate | G43: =IF(G$4="","",-G14/G16) -> #DIV/0! | H43: =IF(H$4="","",-H14/H16) -> 0 | I43: =IF(I$4="","",-I14/I16) -> 0 | J43: =IF(J$4="","",-J14/J16) -> #DIV/0! | K43: =IF(K$4="","",-K14/K16) -> #DIV/0! | L43: =IF(L$4="","",-L14/L16) -> #DIV/0! | M43: =IF(M$4="","",-M14/M16) -> 0 | N43: =IF(N$4="","",-N14/N16) -> 0 | ... Q43: =IF(Q$4="","",-Q14/Q16)
B45: Non-operating Income | E45: Notes
B46: Interest
B47: Interest Expense | C47: =-BS!G31*Normalized_FCF!C53 -> -129899 | G47: =Data!C51 -> -129899 | H47: =Data!D51 -> -81860 | I47: =Data!E51 -> -60486 | J47: =Data!F51 -> -76137 | K47: =Data!G51 -> -89162 | L47: =Data!H51 -> -36991 | M47: =Data!I51 -> -243.7 | N47: =Data!J51 -> -236.6 | ... Q47: =Data!M51
B48: Interest Income | C48: =BS!$C$65*C52 -> 115.179 | G48: =Data!C52 -> 183.1 | H48: =Data!D52 -> 227.8 | I48: =Data!E52 -> 0 | J48: =Data!F52 -> 0 | K48: =Data!G52 -> 0 | L48: =Data!H52 -> 0 | M48: =Data!I52 -> 0 | N48: =Data!J52 -> 0 | ... Q48: =Data!M52
B49: Net Interest Income | C49: =C47+C48 -> -129783.82 | G49: =IF(G4="","",G47+G48) -> -129715.9 | H49: =IF(H4="","",H47+H48) -> -81632.2 | I49: =IF(I4="","",I47+I48) -> -60486 | J49: =IF(J4="","",J47+J48) -> -76137 | K49: =IF(K4="","",K47+K48) -> -89162 | L49: =IF(L4="","",L47+L48) -> -36991 | M49: =IF(M4="","",M47+M48) -> -243.7 | N49: =IF(N4="","",N47+N48) -> -236.6 | ... Q49: =IF(Q4="","",Q47+Q48)
B51: % Interest | G51: Latest Asset Value
B52: Interest Yield/Cash | C52: 0.03 | E52: Reference the market rate | G52: =IF(Normalized_FCF!G4="","",Normalized_FCF!G48/BS!$C$65) -> 0.047690985
B53: Interest Rate/Debt | C53: =Normalized_FCF!G53 -> 4.3824391 | E53: Use Last year's rate | G53: =IFERROR(ABS(Normalized_FCF!G47/BS!$G$31),0) -> 4.3824391
B54: Pre-tax Profit/Interest Expense | C54: =-C8/C47 -> 4.3667218 | G54: =IF(G4="","",-G8/G47) -> 10.609289 | H54: =IF(H4="","",-H8/H47) -> -1.1959443 | I54: =IF(I4="","",-I8/I47) -> 16.284049 | J54: =IF(J4="","",-J8/J47) -> 12.912907 | K54: =IF(K4="","",-K8/K47) -> 14.65473 | L54: =IF(L4="","",-L8/L47) -> 33.586981 | M54: =IF(M4="","",-M8/M47) -> 21.556422 | N54: =IF(N4="","",-N8/N47) -> 19.50803 | ... Q54: =IF(Q4="","",-Q8/Q47)
B56: Non-operating EBIT | G56: Latest Asset Value
B57: Dividend or Interests from FA | C57: =BS!$C72*C65 -> 0 | G57: =Data!C56 -> 0 | H57: =Data!D56 -> 0 | I57: =Data!E56 -> 0 | J57: =Data!F56 -> 0 | K57: =Data!G56 -> 0 | L57: =Data!H56 -> 0 | M57: =Data!I56 -> 0 | N57: =Data!J56 -> 0 | ... Q57: =Data!M56
B58: Share of JV or associate Results | C58: =BS!$C67*C66 -> 0 | G58: =Data!C55 -> 0 | H58: =Data!D55 -> 0 | I58: =Data!E55 -> 0 | J58: =Data!F55 -> 0 | K58: =Data!G55 -> 0 | L58: =Data!H55 -> 0 | M58: =Data!I55 -> 0 | N58: =Data!J55 -> 0 | ... Q58: =Data!M55
B59: Investment property | C59: =BS!$C74*C67 -> 0 | G59: =Data!C57 -> 0 | H59: =Data!D57 -> 0 | I59: =Data!E57 -> 0 | J59: =Data!F57 -> 0 | K59: =Data!G57 -> 0 | L59: =Data!H57 -> 0 | M59: =Data!I57 -> 0 | N59: =Data!J57 -> 0 | ... Q59: =Data!M57
B60: Stable Non-Operating EBIT | C60: =SUM(C57:C59) -> 0 | G60: =IF(G4="","",SUM(G57:G59)) -> 0 | H60: =IF(H4="","",SUM(H57:H59)) -> 0 | I60: =IF(I4="","",SUM(I57:I59)) -> 0 | J60: =IF(J4="","",SUM(J57:J59)) -> 0 | K60: =IF(K4="","",SUM(K57:K59)) -> 0 | L60: =IF(L4="","",SUM(L57:L59)) -> 0 | M60: =IF(M4="","",SUM(M57:M59)) -> 0 | N60: =IF(N4="","",SUM(N57:N59)) -> 0 | ... Q60: =IF(Q4="","",SUM(Q57:Q59))
B61: Other Non-operating Income | C61: 0 | E61: Assume 0 | G61: =Data!C58 -> -1248420.1 | H61: =Data!D58 -> 168928.2 | I61: =Data!E58 -> -927959 | J61: =Data!F58 -> -907013 | K61: =Data!G58 -> -1217483 | L61: =Data!H58 -> -1205425 | M61: =Data!I58 -> -4901.2 | N61: =Data!J58 -> -4283.2 | ... Q61: =Data!M58
B62: Total Non-Operating EBIT | C62: =C60+C61 -> 0 | G62: =IF(G4="","",G60+G61) -> -1248420.1 | H62: =IF(H4="","",H60+H61) -> 168928.2 | I62: =IF(I4="","",I60+I61) -> -927959 | J62: =IF(J4="","",J60+J61) -> -907013 | K62: =IF(K4="","",K60+K61) -> -1217483 | L62: =IF(L4="","",L60+L61) -> -1205425 | M62: =IF(M4="","",M60+M61) -> -4901.2 | N62: =IF(N4="","",N60+N61) -> -4283.2 | ... Q62: =IF(Q4="","",Q60+Q61)
B64: Non-operating Asset Yield % | G64: Latest Asset Value
B65: Dividend or Interests from FA | C65: =G65 -> 0 | G65: =IFERROR(G57/BS!$C$66,0) -> 0
B66: JV or associate | C66: =G66 -> 0 | G66: =IFERROR(G58/BS!$C$67,0) -> 0
B67: Investment property | C67: =G67 -> 0 | G67: =IFERROR(G59/BS!$C$74,0) -> 0
B68: Stable Non-Operating EBIT | C68: =C60/BS!C69 -> 0 | G68: =G60/BS!C69 -> 0
B70: P&L & Dividend Analysis | E70: Notes
B71: P&L % Sales
B72: Variable Costs | C72: =ABS(C5/C$4) -> 0.75125414 | G72: =IF(G$4="","",ABS(G5/G$4)) -> 0.73600078 | H72: =IF(H$4="","",ABS(H5/H$4)) -> 0.76650749 | I72: =IF(I$4="","",ABS(I5/I$4)) -> 0.74730778 | J72: =IF(J$4="","",ABS(J5/J$4)) -> 0.72529317 | K72: =IF(K$4="","",ABS(K5/K$4)) -> 0.7306374 | L72: =IF(L$4="","",ABS(L5/L$4)) -> 0.75374616 | M72: =IF(M$4="","",ABS(M5/M$4)) -> 0.72592315 | N72: =IF(N$4="","",ABS(N5/N$4)) -> 0.70801924 | ... Q72: =IF(Q$4="","",ABS(Q5/Q$4))
B73: Contribution Margin | C73: =ABS(C6/C$4) -> 0.24874586 | G73: =IF(G$4="","",ABS(G6/G$4)) -> 0.26399922 | H73: =IF(H$4="","",ABS(H6/H$4)) -> 0.23349251 | I73: =IF(I$4="","",ABS(I6/I$4)) -> 0.25269222 | J73: =IF(J$4="","",ABS(J6/J$4)) -> 0.27470683 | K73: =IF(K$4="","",ABS(K6/K$4)) -> 0.2693626 | L73: =IF(L$4="","",ABS(L6/L$4)) -> 0.24625384 | M73: =IF(M$4="","",ABS(M6/M$4)) -> 0.27407685 | N73: =IF(N$4="","",ABS(N6/N$4)) -> 0.29198076 | ... Q73: =IF(Q$4="","",ABS(Q6/Q$4))
B74: Fixed Costs | C74: =ABS(C7/C$4) -> 0.22325334 | G74: =IF(G$4="","",ABS(G7/G$4)) -> 0.20890318 | H74: =IF(H$4="","",ABS(H7/H$4)) -> 0.23844898 | I74: =IF(I$4="","",ABS(I7/I$4)) -> 0.20789611 | J74: =IF(J$4="","",ABS(J7/J$4)) -> 0.20915275 | K74: =IF(K$4="","",ABS(K7/K$4)) -> 0.19569163 | L74: =IF(L$4="","",ABS(L7/L$4)) -> 0.18019017 | M74: =IF(M$4="","",ABS(M7/M$4)) -> 0.18527328 | N74: =IF(N$4="","",ABS(N7/N$4)) -> 0.20191236 | ... Q74: =IF(Q$4="","",ABS(Q7/Q$4))
B75: Operating EBIT | C75: =ABS(C8/C$4) -> 0.025492525 | G75: =IF(G$4="","",ABS(G8/G$4)) -> 0.055096043 | H75: =IF(H$4="","",ABS(H8/H$4)) -> 0.0049564752 | I75: =IF(I$4="","",ABS(I8/I$4)) -> 0.044796105 | J75: =IF(J$4="","",ABS(J8/J$4)) -> 0.06555408 | K75: =IF(K$4="","",ABS(K8/K$4)) -> 0.073670971 | L75: =IF(L$4="","",ABS(L8/L$4)) -> 0.066063671 | M75: =IF(M$4="","",ABS(M8/M$4)) -> 0.088803578 | N75: =IF(N$4="","",ABS(N8/N$4)) -> 0.090068396 | ... Q75: =IF(Q$4="","",ABS(Q8/Q$4))
B76: Add Back D&A | C76: =ABS(C9/C$4) -> 0 | G76: =IF(G$4="","",G9/G$4) -> 0 | H76: =IF(H$4="","",H9/H$4) -> 0 | I76: =IF(I$4="","",I9/I$4) -> 0 | J76: =IF(J$4="","",J9/J$4) -> 0 | K76: =IF(K$4="","",K9/K$4) -> 0 | L76: =IF(L$4="","",L9/L$4) -> 0 | M76: =IF(M$4="","",M9/M$4) -> 0 | N76: =IF(N$4="","",N9/N$4) -> 0 | ... Q76: =IF(Q$4="","",Q9/Q$4)
B77: Maintenance Capex | C77: =MAX(AVERAGE(G77:J77),C76) -> 0 | E77: Historical Average or D&A | G77: =IF(G$4="","",-G10/G$4) -> 0 | H77: =IF(H$4="","",-H10/H$4) -> 0 | I77: =IF(I$4="","",-I10/I$4) -> 0 | J77: =IF(J$4="","",-J10/J$4) -> 0 | K77: =IF(K$4="","",-K10/K$4) -> 0 | L77: =IF(L$4="","",-L10/L$4) -> 0 | M77: =IF(M$4="","",-M10/M$4) -> 0 | N77: =IF(N$4="","",-N10/N$4) -> 0 | ... Q77: =IF(Q$4="","",-Q10/Q$4)
B78: Non-Operating EBIT | C78: =ABS(C11/C$4) -> 0 | G78: =IF(G$4="","",G11/G$4) -> -0.049910174 | H78: =IF(H$4="","",H11/H$4) -> 0.0085524865 | I78: =IF(I$4="","",I11/I$4) -> -0.042203821 | J78: =IF(J$4="","",J11/J$4) -> -0.060477448 | K78: =IF(K$4="","",K11/K$4) -> -0.068643859 | L78: =IF(L$4="","",L11/L$4) -> -0.064096729 | M78: =IF(M$4="","",M11/M$4) -> -0.08285156 | N78: =IF(N$4="","",N11/N$4) -> -0.083581973 | ... Q78: =IF(Q$4="","",Q11/Q$4)
B79: Net Interest Income | C79: =ABS(C12/C$4) -> 0.0058327327 | G79: =IF(G$4="","",ABS(G12/G$4)) -> 0.005185869 | H79: =IF(H$4="","",ABS(H12/H$4)) -> 0.00413287 | I79: =IF(I$4="","",ABS(I12/I$4)) -> 0.0027509193 | J79: =IF(J$4="","",ABS(J12/J$4)) -> 0.0050766322 | K79: =IF(K$4="","",ABS(K12/K$4)) -> 0.0050271123 | L79: =IF(L$4="","",ABS(L12/L$4)) -> 0.0019669429 | M79: =IF(M$4="","",ABS(M12/M$4)) -> 0.0041195881 | N79: =IF(N$4="","",ABS(N12/N$4)) -> 0.0046169908 | ... Q79: =IF(Q$4="","",ABS(Q12/Q$4))
B80: Pre-tax Profit | C80: =C13/C4 -> 0.019659792 | G80: =IF(G$4="","",G13/G$4) -> 0 | H80: =IF(H$4="","",H13/H$4) -> -0.00053685866 | I80: =IF(I$4="","",I13/I$4) -> -0.00015863516 | J80: =IF(J$4="","",J13/J$4) -> 0 | K80: =IF(K$4="","",K13/K$4) -> 0 | L80: =IF(L$4="","",L13/L$4) -> 0 | M80: =IF(M$4="","",M13/M$4) -> 0.0018324306 | N80: =IF(N$4="","",N13/N$4) -> 0.0018694324 | ... Q80: =IF(Q$4="","",Q13/Q$4)
B81: Income Tax | C81: =ABS(C14/C$4) -> 0.0045217521 | G81: =IF(G$4="","",ABS(G14/G$4)) -> 0 | H81: =IF(H$4="","",ABS(H14/H$4)) -> 0 | I81: =IF(I$4="","",ABS(I14/I$4)) -> 0 | J81: =IF(J$4="","",ABS(J14/J$4)) -> 0 | K81: =IF(K$4="","",ABS(K14/K$4)) -> 0 | L81: =IF(L$4="","",ABS(L14/L$4)) -> 0 | M81: =IF(M$4="","",ABS(M14/M$4)) -> 0 | N81: =IF(N$4="","",ABS(N14/N$4)) -> 0 | ... Q81: =IF(Q$4="","",ABS(Q14/Q$4))
B82: Non-controling Interests | C82: =MIN(BS!D47,MAX(G82:K82)) -> 0 | G82: =IF(G$4="","",-G15/G$4) -> 0 | H82: =IF(H$4="","",-H15/H$4) -> 0 | I82: =IF(I$4="","",-I15/I$4) -> 0 | J82: =IF(J$4="","",-J15/J$4) -> 0 | K82: =IF(K$4="","",-K15/K$4) -> 0 | L82: =IF(L$4="","",-L15/L$4) -> 0 | M82: =IF(M$4="","",-M15/M$4) -> 0 | N82: =IF(N$4="","",-N15/N$4) -> 0 | ... Q82: =IF(Q$4="","",-Q15/Q$4)
B83: After-tax Profit | C83: =ABS(C16/C$4) -> 0.01513804 | G83: =IF(G$4="","",ABS(G16/G$4)) -> 0 | H83: =IF(H$4="","",ABS(H16/H$4)) -> 0.00053685866 | I83: =IF(I$4="","",ABS(I16/I$4)) -> 0.00015863516 | J83: =IF(J$4="","",ABS(J16/J$4)) -> 0 | K83: =IF(K$4="","",ABS(K16/K$4)) -> 0 | L83: =IF(L$4="","",ABS(L16/L$4)) -> 0 | M83: =IF(M$4="","",ABS(M16/M$4)) -> 0.0018324306 | N83: =IF(N$4="","",ABS(N16/N$4)) -> 0.0018694324 | ... Q83: =IF(Q$4="","",ABS(Q16/Q$4))
B84: WCInv | C84: =MIN(AVERAGE(G84:J84)/2,0) -> 0 | E84: =E17 -> WCInv is excluded | G84: =IF(G$4="","",-G17/G$4) -> 0 | H84: =IF(H$4="","",-H17/H$4) -> 0 | I84: =IF(I$4="","",-I17/I$4) -> 0 | J84: =IF(J$4="","",-J17/J$4) -> 0 | K84: =IF(K$4="","",-K17/K$4) -> 0 | L84: =IF(L$4="","",-L17/L$4) -> 0 | M84: =IF(M$4="","",-M17/M$4) -> 0 | N84: =IF(N$4="","",-N17/N$4) -> 0 | ... Q84: =IF(Q$4="","",-Q17/Q$4)
B85: Net Borrowing | C85: 0 | E85: =E18 -> Net borrowing is excluded
B86: Total FCFE | C86: =ABS(C19/C$4) -> 0.01513804 | G86: =IF(G$4="","",ABS(G19/G$4)) -> 0 | H86: =IF(H$4="","",ABS(H19/H$4)) -> 0.00053685866 | I86: =IF(I$4="","",ABS(I19/I$4)) -> 0.00015863516 | J86: =IF(J$4="","",ABS(J19/J$4)) -> 0 | K86: =IF(K$4="","",ABS(K19/K$4)) -> 0 | L86: =IF(L$4="","",ABS(L19/L$4)) -> 0 | M86: =IF(M$4="","",ABS(M19/M$4)) -> 0.0018324306 | N86: =IF(N$4="","",ABS(N19/N$4)) -> 0.0018694324 | ... Q86: =IF(Q$4="","",ABS(Q19/Q$4))
B88: Dividends
B89: Dividend per share | C89: =G89 -> 0.55 | G89: =Data!C64 -> 0.55 | H89: =Data!D64 -> 0 | I89: =Data!E64 -> 0 | J89: =Data!F64 -> 0 | K89: =Data!G64 -> 0 | L89: =Data!H64 -> 0 | M89: =Data!I64 -> 0 | N89: =Data!J64 -> 0 | ... Q89: =Data!M64
B90: Dividend | C90: =C89*Common_Shares/$C$3 -> 372584.3 | G90: =IF(G$4="","",G89*Common_Shares/$C$3) -> 372584.3 | H90: =IF(H$4="","",H89*Common_Shares/$C$3) -> 0 | I90: =IF(I$4="","",I89*Common_Shares/$C$3) -> 0 | J90: =IF(J$4="","",J89*Common_Shares/$C$3) -> 0 | K90: =IF(K$4="","",K89*Common_Shares/$C$3) -> 0 | L90: =IF(L$4="","",L89*Common_Shares/$C$3) -> 0 | M90: =IF(M$4="","",M89*Common_Shares/$C$3) -> 0 | N90: =IF(N$4="","",N89*Common_Shares/$C$3) -> 0 | ... Q90: =IF(Q$4="","",Q89*Common_Shares/$C$3)
B91: Payout Ratio | C91: =C89/(C19*$C$3/Common_Shares) -> 1.1061307 | G91: =IF(G$4="","",G89/(G19*$C$3/Common_Shares)) -> #DIV/0! | H91: =IF(H$4="","",H89/(H19*$C$3/Common_Shares)) -> 0 | I91: =IF(I$4="","",I89/(I19*$C$3/Common_Shares)) -> 0 | J91: =IF(J$4="","",J89/(J19*$C$3/Common_Shares)) -> #DIV/0! | K91: =IF(K$4="","",K89/(K19*$C$3/Common_Shares)) -> #DIV/0! | L91: =IF(L$4="","",L89/(L19*$C$3/Common_Shares)) -> #DIV/0! | M91: =IF(M$4="","",M89/(M19*$C$3/Common_Shares)) -> 0 | N91: =IF(N$4="","",N89/(N19*$C$3/Common_Shares)) -> 0 | ... Q91: =IF(Q$4="","",Q89/(Q19*$C$3/Common_Shares))
B93: YoY %
B94: Sales | C94: =C4/G4-1 -> -0.1104368 | G94: =IF(H4="","",G4/H4-1) -> 0.26637378 | H94: =IF(I4="","",H4/I4-1) -> -0.10167654 | I94: =IF(J4="","",I4/J4-1) -> 0.46607761 | J94: =IF(K4="","",J4/K4-1) -> -0.15441194 | K94: =IF(L4="","",K4/L4-1) -> -0.056901869 | L94: =IF(M4="","",L4/M4-1) -> 316.90883 | M94: =IF(N4="","",M4/N4-1) -> 0.15437258 | N94: =IF(O4="","",N4/O4-1) | ... Q94: =IF(R4="","",Q4/R4-1)
B95: Pre-tax Profit | C95: =C13/G13-1 -> #DIV/0! | G95: =IF(H5="","",G13/H13-1) -> -1 | H95: =IF(I5="","",H13/I13-1) -> 2.0401376 | I95: =IF(J5="","",I13/J13-1) -> #DIV/0! | J95: =IF(K5="","",J13/K13-1) -> #DIV/0! | K95: =IF(L5="","",K13/L13-1) -> #DIV/0! | L95: =IF(M5="","",L13/M13-1) -> -1 | M95: =IF(N5="","",M13/N13-1) -> 0.13152401 | N95: =IF(O5="","",N13/O13-1) | ... Q95: =IF(R5="","",Q13/R13-1)
B97: Operating Efficiency Analysis | E97: Notes
B98: Balance Sheet | G98: Latest Asset Value
B99: Total Assets | C99: =BS!G32 -> 86862.7 | G99: =IF(G$4="","",G103+G102) -> 18897731 | H99: =IF(H$4="","",H103+H102) -> 18650857 | I99: =IF(I$4="","",I103+I102) -> 18088758 | J99: =IF(J$4="","",J103+J102) -> 16826467 | K99: =IF(K$4="","",K103+K102) -> 0 | L99: =IF(L$4="","",L103+L102) -> 0 | M99: =IF(M$4="","",M103+M102) -> 0 | N99: =IF(N$4="","",N103+N102) -> 0 | ... Q99: =IF(Q$4="","",Q103+Q102)
B100: Incl. AR | C100: =BS!C4 -> 5848.8 | G100: =IF(G$4="","",Data!D76) -> 0 | H100: =IF(H$4="","",Data!E76) -> 0 | I100: =IF(I$4="","",Data!F76) -> 0 | J100: =IF(J$4="","",Data!G76) -> 0 | K100: =IF(K$4="","",Data!H76) -> 0 | L100: =IF(L$4="","",Data!I76) -> 0 | M100: =IF(M$4="","",Data!J76) -> 0 | N100: =IF(N$4="","",Data!K76) -> 0 | ... Q100: =IF(Q$4="","",Data!N76)
B101: Incl. Inventory | C101: =BS!C6+BS!C7 -> 67632 | G101: =IF(G$4="","",Data!D77) -> 0 | H101: =IF(H$4="","",Data!E77) -> 0 | I101: =IF(I$4="","",Data!F77) -> 0 | J101: =IF(J$4="","",Data!G77) -> 0 | K101: =IF(K$4="","",Data!H77) -> 0 | L101: =IF(L$4="","",Data!I77) -> 0 | M101: =IF(M$4="","",Data!J77) -> 0 | N101: =IF(N$4="","",Data!K77) -> 0 | ... Q101: =IF(Q$4="","",Data!N77)
B102: Total Liabilities | C102: =BS!G30 -> 60481 | G102: =Data!C78 -> 6730302 | H102: =Data!D78 -> 6780629 | I102: =Data!E78 -> 5345297 | J102: =Data!F78 -> 4807353 | K102: =Data!G78 -> 0 | L102: =Data!H78 -> 0 | M102: =Data!I78 -> 0 | N102: =Data!J78 -> 0 | ... Q102: =Data!M78
B103: Total Equity | C103: =BS!G27 -> 26381.7 | G103: =Data!C79 -> 12167429 | H103: =Data!D79 -> 11870228 | I103: =Data!E79 -> 12743461 | J103: =Data!F79 -> 12019114 | K103: =Data!G79 -> 0 | L103: =Data!H79 -> 0 | M103: =Data!I79 -> 0 | N103: =Data!J79 -> 0 | ... Q103: =Data!M79
B105: Operating Asset % of Sales | G105: Latest Asset Value
B106: AR | C106: =C100/C$4 -> 0.00026285624 | G106: =IF(G$4="","",G100/G$4) -> 0 | H106: =IF(H$4="","",H100/H$4) -> 0 | I106: =IF(I$4="","",I100/I$4) -> 0 | J106: =IF(J$4="","",J100/J$4) -> 0 | K106: =IF(K$4="","",K100/K$4) -> 0 | L106: =IF(L$4="","",L100/L$4) -> 0 | M106: =IF(M$4="","",M100/M$4) -> 0 | N106: =IF(N$4="","",N100/N$4) -> 0 | ... Q106: =IF(Q$4="","",Q100/Q$4)
B107: Inventory | C107: =C101/C$4 -> 0.0030395112 | G107: =IF(G$4="","",G101/G$4) -> 0 | H107: =IF(H$4="","",H101/H$4) -> 0 | I107: =IF(I$4="","",I101/I$4) -> 0 | J107: =IF(J$4="","",J101/J$4) -> 0 | K107: =IF(K$4="","",K101/K$4) -> 0 | L107: =IF(L$4="","",L101/L$4) -> 0 | M107: =IF(M$4="","",M101/M$4) -> 0 | N107: =IF(N$4="","",N101/N$4) -> 0 | ... Q107: =IF(Q$4="","",Q101/Q$4)
B108: Properties held for sale | C108: =BS!$G$38/C$4 -> 0 | G108: =BS!$G$38/G$4 -> 0
B110: ROE | G110: =IFERROR(IF(#REF!*G112*(1/#REF!)=G114,"","Error"),"") | H110: =IFERROR(IF(#REF!*H112*(1/#REF!)=H114,"","Error"),"") | I110: =IFERROR(IF(#REF!*I112*(1/#REF!)=I114,"","Error"),"") | J110: =IFERROR(IF(#REF!*J112*(1/#REF!)=J114,"","Error"),"") | K110: =IFERROR(IF(#REF!*K112*(1/#REF!)=K114,"","Error"),"") | L110: =IFERROR(IF(#REF!*L112*(1/#REF!)=L114,"","Error"),"") | M110: =IFERROR(IF(#REF!*M112*(1/#REF!)=M114,"","Error"),"") | N110: =IFERROR(IF(#REF!*N112*(1/#REF!)=N114,"","Error"),"") | ... Q110: =IFERROR(IF(#REF!*Q112*(1/#REF!)=Q114,"","Error"),"")
B111: Pre-tax Profit/Sales | C111: =C80 -> 0.019659792 | G111: =G80 -> 0 | H111: =H80 -> -0.00053685866 | I111: =I80 -> -0.00015863516 | J111: =J80 -> 0 | K111: =K80 -> 0 | L111: =L80 -> 0 | M111: =M80 -> 0.0018324306 | N111: =N80 -> 0.0018694324 | ... Q111: =Q80
B112: Sales/Total Assets | C112: =C4/C99 -> 256.16227 | G112: =IF(G4="","",G4/G99) -> 1.323616 | H112: =IF(H4="","",H4/H99) -> 1.0590366 | I112: =IF(I4="","",I4/I99) -> 1.2155372 | J112: =IF(J4="","",J4/J99) -> 0.89130659 | K112: =IF(K4="","",K4/K99) -> #DIV/0! | L112: =IF(L4="","",L4/L99) -> #DIV/0! | M112: =IF(M4="","",M4/M99) -> #DIV/0! | N112: =IF(N4="","",N4/N99) -> #DIV/0! | ... Q112: =IF(Q4="","",Q4/Q99)
B113: Total Assets/Equity | C113: =C99/C103 -> 3.2925361 | G113: =IF(G$4="","",G99/G103) -> 1.5531408 | H113: =IF(H$4="","",H99/H103) -> 1.5712299 | I113: =IF(I$4="","",I99/I103) -> 1.4194541 | J113: =IF(J$4="","",J99/J103) -> 1.3999757 | K113: =IF(K$4="","",K99/K103) -> #DIV/0! | L113: =IF(L$4="","",L99/L103) -> #DIV/0! | M113: =IF(M$4="","",M99/M103) -> #DIV/0! | N113: =IF(N$4="","",N99/N103) -> #DIV/0! | ... Q113: =IF(Q$4="","",Q99/Q103)
B114: Pre-tax Profit ROE | C114: =C8/C103 -> 21.500995 | G114: =IF(G$4="","",G8/G103) -> 0.11326436 | H114: =IF(H$4="","",H8/H103) -> -0.0082475248 | I114: =IF(I$4="","",I8/I103) -> 0.077291169 | J114: =IF(J$4="","",J8/J103) -> 0.081798875 | K114: =IF(K$4="","",K8/K103) -> #DIV/0! | L114: =IF(L$4="","",L8/L103) -> #DIV/0! | M114: =IF(M$4="","",M8/M103) -> #DIV/0! | N114: =IF(N$4="","",N8/N103) -> #DIV/0! | ... Q114: =IF(Q$4="","",Q8/Q103)
B116: Market Price Attractiveness | E116: Notes
...

Sheet BS
B1: Most Recent Quarter | C1: 45473 | F1: =IF(MONTH(C1)=MONTH(Normalized_FCF!G1),"FY","Quarter")&" Report" -> Quarter Report | H1: =Data!C3 -> 1000
B2: Lastest Balance Sheet
B3: ST Operating Assets | C3: Book | D3: Valued @ | F3: ST Non-Operating Assets | G3: Book | H3: Valued @
B4: ST AR | C4: =5822.2+0.5+26.1 -> 5848.8 | D4: 0.6 | F4: Cash and cash equivalents | G4: 3839.3 | H4: 0.9
B5: Operating ST Financial Assets | C5: 0 | D5: 0.6 | F5: Restricted cash | G5: 0 | H5: 0
B6: Inventory | C6: 67632 | D6: 0.5 | F6: Securities with stable income | G6: 1.5 | H6: 0.6
B7: Properties held for sale | C7: 0 | D7: 0.6 | F7: Other Securities | G7: 0 | H7: 0.6
B8: Properties held for income | C8: 0 | D8: 0.6 | F8: Properties with stable income | G8: 0 | H8: 0.6
B9: Prepayments and Contract Assets | C9: 0 | D9: 0.1 | F9: Other Properties | G9: 0 | H9: 0.6
B10: ST DTA | C10: 2.3 | D10: 0.9
B11: Other ST Assets | C11: 0 | D11: 0.05
B12: Operating ST Assets | C12: =SUM(C4:C11) -> 73483.1 | D12: =C4*D4+C5*D5+C9*D9+C6*D6+C8*D8+C7*D7+C10*D10+C11*D11 -> 37327.35 | F12: Non-Operating ST Assets | G12: =SUM(G4:G9) -> 3840.8 | H12: =G4*H4+G5*H5+G6*H6+G7*H7+G8*H8+G9*H9 -> 3456.27
B14: LT Operating Assets | C14: Book | D14: Valued @ | F14: LT Non-Operating Assets | G14: Book | H14: Valued @
B15: LT AR | C15: 4.8 | D15: 0.4 | F15: LT Depositis | G15: 0 | H15: 0.8
B16: Operating LT Financial Assets | C16: =1520.1 -> 1520.1 | D16: 0.5 | F16: Securities with stable income | G16: 0 | H16: 0.6
B17: Properties held for sale | C17: 0 | D17: 0.6 | F17: Other Securities | G17: 63.2 | H17: 0.6
B18: Properties held for income | C18: 0 | D18: 0.6 | F18: JV or associate with stable income | G18: =41.5+40 -> 81.5 | H18: 0.1
B19: PP&E & Right of Use Assets | C19: =4063.1+1656.3+785.2 -> 6504.6 | D19: 0.1 | F19: Other JV or associate | G19: 0 | H19: 0.1
B20: Biological assets | C20: 0 | D20: 0.05 | F20: Properties with stable income | G20: 0 | H20: 0.2
B21: Intangible assets | C21: 7.7 | D21: 0.05 | F21: Other Properties | G21: 387 | H21: 0.1
B22: LT DTA | C22: 969.9 | D22: 0.9
B23: Other assets & Goodwill | C23: 0 | D23: 0 | F23: Non-Operating LT Assets | G23: =SUM(G15:G21) -> 531.7 | H23: =G15*H15+G16*H16+G17*H17+G18*H18+G19*H19+G20*H20+G21*H21 -> 84.77
B24: Operating LT Assets | C24: =SUM(C15:C23) -> 9007.1 | D24: =C15*D15+C16*D16+C18*D18+C17*D17+C19*D19+C20*D20+C21*D21+C22*D22+C23*D23 -> 2285.725
B26: ST Liabilities | C26: Book | F26: BS Summary | G26: Book | H26: Valued @
B27: ST Borrowing | C27: =2658.1+24506.6 -> 27164.7 | F27: Total Equity | G27: =G32-G30 -> 26381.7 | H27: =H32-G30 -> -17326.885
B28: ST Lease liabilities | C28: 662.5 | F28: Incl. Non-common Interest | G28: 1036.4
B29: ST SH Loan | C29: 0 | F29: Incl. Common Equity | G29: =G27-G28 -> 25345.3 | H29: =H27-G28 -> -18363.285
B30: ST Financial Liabilities | C30: 0 | F30: Total Liabilities | G30: =C33+C42 -> 60481
B31: ST Interest-bearing Debt | C31: =SUM(C27:C30) -> 27827.2 | F31: incl. Interest-bearing Debt | G31: =C31+C40 -> 29640.8
B32: Other ST liabilities | C32: =C33-C31 -> 30241.6 | F32: Total Assets | G32: =G35+G40 -> 86862.7 | H32: =H35+H40 -> 43154.115
B33: Current Liabilities | C33: 58068.8
F34: Assets Summary | G34: Book | H34: Valued @
B35: LT Liabilities | C35: Book | F35: Operating Assets | G35: =C12+C24 -> 82490.2 | H35: =D12+D24 -> 39613.075
B36: LT Borrowing | C36: 1297.9 | F36: incl. AR | G36: =C4+C15 -> 5853.6
B37: LT Lease liabilities | C37: 515.7 | F37: incl. inventory | G37: =C6 -> 67632
B38: LT SH Loan | C38: 0 | F38: incl. Properties held for sale | G38: =C7+C17 -> 0
B39: LT Financial Liabilities | C39: 0 | F39: incl. Fixed Assets | G39: =C7+C17+C19+C20 -> 6504.6 | H39: =C7*D7+C17*D17+C19*D19+C20*D20 -> 650.46
B40: LT Interest-bearing Debt | C40: =SUM(C36:C39) -> 1813.6 | F40: Non-operating Assets | G40: =G12+G23 -> 4372.5 | H40: =H12+H23 -> 3541.04
B41: Other LT liabilities | C41: =C42-C40 -> 598.6 | F41: incl. Assets with stable income | G41: =C69 -> 3922.3 | H41: =H40-H42 -> 3464.42
B42: Noncurrent Liabilities | C42: 2412.2 | F42: incl. Other Assets | G42: =C75 -> 450.2 | H42: =D75 -> 76.62
B44: Balance Sheet Analysis
B45: Asset Value | C45: Book | D45: Estimate | F45: Notes
B46: ="Equity per share ("&Market_currency&")" -> Equity per share (HKD) | C46: =G29*H1/Common_Shares*Exchange_Rate -> 0.037414123 | D46: =H29*H1/Common_Shares*Exchange_Rate -> -0.027107441
B47: Non-common Interest/Total Equity | C47: =G28/G29 -> 0.040891211 | D47: =IF(G28<=0,0,G28/G29) -> 0.040891211
B49: Leverage % | C49: Normalized | D49: Latest
B50: Debt/EBIT | C50: =G31/Normalized_FCF!C8 -> 0.052255089 | D50: =G31/Normalized_FCF!G8 -> 0.021507892
B51: Debt per share (HKD) | D51: =G31*H1/Common_Shares -> 0.043755037
B52: Common Equity/Total Asset | D52: =G29/G32 -> 0.29178577
B54: Profibility % | C54: Normalized | D54: Latest
B55: Operating Asset Yield | C55: =Normalized_FCF!C8/G35 -> 6.8763658 | D55: =Normalized_FCF!G8/G35 -> 16.706663
B56: Non-Operating Asset Yield | C56: =Normalized_FCF!C11/G40 -> 0 | D56: =Normalized_FCF!G11/G40 -> -285.51632
B58: Reinvestment % | C58: Normalized | D58: Latest
B59: D&A/Fixed Assets | D59: =Normalized_FCF!G9/BS!$G$39 -> 0 | F59: Same as Last year's D&A
B60: Fixed Assets/Total Assets | D60: =G39/G32 -> 0.074883696
B63: Non-operating Assets Analysis
B64: Non-operating Assets with stable income | C64: Book | D64: Valued @
B65: Cash | C65: =G4+G5+G15 -> 3839.3 | D65: =G4*H4+G5*H5+G15*H15 -> 3455.37 | F65: Non-Operating Cash is the Excess cash not required for operations
B66: Securities with stable income | C66: =G6+G16 -> 1.5
B67: JV or associate with stable income | C67: =G18 -> 81.5
B68: Properties with stable income | C68: =G8+G20 -> 0
B69: Non-operating Assets with stable income | C69: =SUM(C65:C68) -> 3922.3
B71: Other Non-operating Assets | C71: Book | D71: Estimate
B72: Other Securities | C72: =G7+G17 -> 63.2 | D72: =G7*H7+G17*H17 -> 37.92
B73: Other JV or associate | C73: =G19 -> 0 | D73: =G19*H19 -> 0
B74: Other Properties | C74: =G9+G21 -> 387 | D74: =G9*H9+G21*H21 -> 38.7
B75: Other Non-operating Assets | C75: =SUM(C72:C74) -> 450.2 | D75: =SUM(D72:D74) -> 76.62

Sheet Valuation_Model
B2: No-Growth DCF Valuation | H2: Notes
B3: No-Growth DCF | C3: =Normalized_FCF!C3 -> 1000 | E3: Special Assumption
B4: Adjusted FCFE | C4: =Normalized_FCF!C19 -> 336835.71 | D4: =Reporting_currency -> HKD | E4: Terminal Growth Rate: | F4: 0
B5: /Equity Cost of Capital | C5: =Thesis!C37 -> 0.1 | E5: - Expects no significant growth at terminal years
B6: Stable Income Value | C6: =(C4*(1+Terminal_Growth))/(Equity_Cost-Terminal_Growth) -> 3368357.1 | D6: =Reporting_currency -> HKD | E6: - Avoids overvaluation.
B7: - Interest-bearing Debt | C7: =BS!G31 -> 29640.8 | D7: =Reporting_currency -> HKD
B8: + Non-operating Cash | C8: =BS!D65 -> 3455.37 | D8: =Reporting_currency -> HKD
B9: + Other Non-operating Assets | C9: =BS!H42 -> 76.62 | D9: =Reporting_currency -> HKD
B10: Equity Value | C10: =C6-C7+C8+C9 -> 3342248.2 | D10: =Reporting_currency -> HKD
B11: * Exchange rate | C11: =Exchange_Rate -> 1 | D11: =Thesis!D13 -> HKD
B12: Equity Value per share | C12: =(C10*C3)/Common_Shares*C11 -> 4.9337466 | D12: =Market_currency -> HKD
B14: Implied Growth Scenario Analysis
B15: FCFE Projection
B16: High Growth Period (HGP) | C16: =Scenarios!C25 -> 0.12
B17: High Growth Rate (HGR) | C17: =Scenarios!C24 -> 15
B18: Value Per Share | C18: =(F52-C7+C8+C9)/Common_Shares*C3 -> 9.9356524 | D18: =IF(ROUND(C18,1)=ROUND(Scenarios!C29,1),"equals Market Price","a Current Projection") -> a Current Projection
B20: Year | C20: FCFE | D20: Growth Rates | E20: Discount Factor | F20: PV of FCFE
B21: 1 | C21: =C4*(1+D21) -> 377255.99 | D21: =IF($C$17<B21,0,Valuation_Model!$C$16) -> 0.12 | E21: =IF($C$17<B21,0,1/(1+Equity_Cost)^B21) -> 0.90909091 | F21: =C21*E21 -> 342959.99
B22: 2 | C22: =IF(ROW()-ROW($C$21)<$C$17, $C$21*(1+D22)^(ROW()-ROW($C$21)), 0) -> 422526.71 | D22: =IF($C$17<B22,0,Valuation_Model!$C$16) -> 0.12 | E22: =IF($C$17<B22,0,1/(1+Equity_Cost)^B22) -> 0.82644628 | F22: =C22*E22 -> 349195.63
B23: 3 | C23: =IF(ROW()-ROW($C$21)<$C$17, $C$21*(1+D23)^(ROW()-ROW($C$21)), 0) -> 473229.91 | D23: =IF($C$17<B23,0,Valuation_Model!$C$16) -> 0.12 | E23: =IF($C$17<B23,0,1/(1+Equity_Cost)^B23) -> 0.7513148 | F23: =C23*E23 -> 355544.64
B24: 4 | C24: =IF(ROW()-ROW($C$21)<$C$17, $C$21*(1+D24)^(ROW()-ROW($C$21)), 0) -> 530017.5 | D24: =IF($C$17<B24,0,Valuation_Model!$C$16) -> 0.12 | E24: =IF($C$17<B24,0,1/(1+Equity_Cost)^B24) -> 0.68301346 | F24: =C24*E24 -> 362009.09
B25: 5 | C25: =IF(ROW()-ROW($C$21)<$C$17, $C$21*(1+D25)^(ROW()-ROW($C$21)), 0) -> 593619.6 | D25: =IF($C$17<B25,0,Valuation_Model!$C$16) -> 0.12 | E25: =IF($C$17<B25,0,1/(1+Equity_Cost)^B25) -> 0.62092132 | F25: =C25*E25 -> 368591.07
B26: 6 | C26: =IF(ROW()-ROW($C$21)<$C$17, $C$21*(1+D26)^(ROW()-ROW($C$21)), 0) -> 664853.96 | D26: =IF($C$17<B26,0,Valuation_Model!$C$16) -> 0.12 | E26: =IF($C$17<B26,0,1/(1+Equity_Cost)^B26) -> 0.56447393 | F26: =C26*E26 -> 375292.73
B27: 7 | C27: =IF(ROW()-ROW($C$21)<$C$17, $C$21*(1+D27)^(ROW()-ROW($C$21)), 0) -> 744636.43 | D27: =IF($C$17<B27,0,Valuation_Model!$C$16) -> 0.12 | E27: =IF($C$17<B27,0,1/(1+Equity_Cost)^B27) -> 0.51315812 | F27: =C27*E27 -> 382116.23
B28: 8 | C28: =IF(ROW()-ROW($C$21)<$C$17, $C$21*(1+D28)^(ROW()-ROW($C$21)), 0) -> 833992.8 | D28: =IF($C$17<B28,0,Valuation_Model!$C$16) -> 0.12 | E28: =IF($C$17<B28,0,1/(1+Equity_Cost)^B28) -> 0.46650738 | F28: =C28*E28 -> 389063.8
B29: 9 | C29: =IF(ROW()-ROW($C$21)<$C$17, $C$21*(1+D29)^(ROW()-ROW($C$21)), 0) -> 934071.94 | D29: =IF($C$17<B29,0,Valuation_Model!$C$16) -> 0.12 | E29: =IF($C$17<B29,0,1/(1+Equity_Cost)^B29) -> 0.42409762 | F29: =C29*E29 -> 396137.69
B30: 10 | C30: =IF(ROW()-ROW($C$21)<$C$17, $C$21*(1+D30)^(ROW()-ROW($C$21)), 0) -> 1046160.6 | D30: =IF($C$17<B30,0,Valuation_Model!$C$16) -> 0.12 | E30: =IF($C$17<B30,0,1/(1+Equity_Cost)^B30) -> 0.38554329 | F30: =C30*E30 -> 403340.19
B31: 11 | C31: =IF(ROW()-ROW($C$21)<$C$17, $C$21*(1+D31)^(ROW()-ROW($C$21)), 0) -> 1171699.8 | D31: =IF($C$17<B31,0,Valuation_Model!$C$16) -> 0.12 | E31: =IF($C$17<B31,0,1/(1+Equity_Cost)^B31) -> 0.3504939 | F31: =C31*E31 -> 410673.65
B32: 12 | C32: =IF(ROW()-ROW($C$21)<$C$17, $C$21*(1+D32)^(ROW()-ROW($C$21)), 0) -> 1312303.8 | D32: =IF($C$17<B32,0,Valuation_Model!$C$16) -> 0.12 | E32: =IF($C$17<B32,0,1/(1+Equity_Cost)^B32) -> 0.31863082 | F32: =C32*E32 -> 418140.44
B33: 13 | C33: =IF(ROW()-ROW($C$21)<$C$17, $C$21*(1+D33)^(ROW()-ROW($C$21)), 0) -> 1469780.3 | D33: =IF($C$17<B33,0,Valuation_Model!$C$16) -> 0.12 | E33: =IF($C$17<B33,0,1/(1+Equity_Cost)^B33) -> 0.28966438 | F33: =C33*E33 -> 425742.99
... B50: 30 | C50: =IF(ROW()-ROW($C$21)<$C$17, $C$21*(1+D50)^(ROW()-ROW($C$21)), 0) -> 0 | D50: =IF($C$17<B50,0,Valuation_Model!$C$16) -> 0 | E50: =IF($C$17<B50,0,1/(1+Equity_Cost)^B50) -> 0 | F50: =C50*E50 -> 0
B51: Terminal Year | C51: =C$21*(1+Terminal_Growth)^$C$17/Equity_Cost -> 3772559.9 | D51: =Terminal_Growth -> 0 | E51: =1/(1+Equity_Cost)^C17 -> 0.23939205 | F51: =C51*E51 -> 903120.85
E52: Total PV | F52: =SUM(F21:F51) -> 6756778
B54: Sensitivity Analysis (Enterprise Value)
A55: =F52 -> 6756778 | B55: =C78 -> -0.05 | C55: =C77 -> 0 | D55: =C76 -> 0.02 | E55: =C75 -> 0.1 | F55: =C74 -> 0.1
A56: 5 | B56: 3095247.6 | C56: 3368357.1 | D56: 3483780.3 | E56: 3984811.7 | F56: 3984811.7
A57: 10 | B57: 2874560.7 | C57: 3368357.1 | D57: 3600894.5 | E57: 4796869.3 | F57: 4796869.3
A58: 15 | B58: 2662733.1 | C58: 3368357.1 | D58: 3733444.6 | E58: 5939529.3 | F58: 5939529.3
A59: 20 | B59: 2495267.4 | C59: 3368357.1 | D59: 3856764.9 | E59: 7287467.4 | F59: 7287467.4
A60: 25 | B60: 2374017.9 | C60: 3368357.1 | D60: 3961456.3 | E60: 8762867.1 | F60: 8762867.1
A61: 30 | B61: 2290435.8 | C61: 3368357.1 | D61: 4045738.4 | E61: 10317410 | F61: 10317410
B63: Sensitivity Analysis (Equity Value per share)
B64: =B55 -> -0.05 | C64: =C55 -> 0 | D64: =D55 -> 0.02 | E64: =E55 -> 0.1 | F64: =F55 -> 0.1
A65: 0 | B65: =C12 -> 4.9337466 | C65: =C12 -> 4.9337466 | D65: =C12 -> 4.9337466 | E65: =C12 -> 4.9337466 | F65: =C12 -> 4.9337466
A66: =A56 -> 5 | B66: =(B56-$C$7+$C$8+$C$9)/Common_Shares*$C$3*Exchange_Rate -> 4.5305891 | C66: =(C56-$C$7+$C$8+$C$9)/Common_Shares*$C$3*Exchange_Rate -> 4.9337466 | D66: =(D56-$C$7+$C$8+$C$9)/Common_Shares*$C$3*Exchange_Rate -> 5.1041316 | E66: =(E56-$C$7+$C$8+$C$9)/Common_Shares*$C$3*Exchange_Rate -> 5.8437422 | F66: =(F56-$C$7+$C$8+$C$9)/Common_Shares*$C$3*Exchange_Rate -> 5.8437422
A67: =A57 -> 10 | B67: =(B57-$C$7+$C$8+$C$9)/Common_Shares*$C$3*Exchange_Rate -> 4.2048163 | C67: =(C57-$C$7+$C$8+$C$9)/Common_Shares*$C$3*Exchange_Rate -> 4.9337466 | D67: =(D57-$C$7+$C$8+$C$9)/Common_Shares*$C$3*Exchange_Rate -> 5.2770129 | E67: =(E57-$C$7+$C$8+$C$9)/Common_Shares*$C$3*Exchange_Rate -> 7.0424821 | F67: =(F57-$C$7+$C$8+$C$9)/Common_Shares*$C$3*Exchange_Rate -> 7.0424821
A68: =A58 -> 15 | B68: =(B58-$C$7+$C$8+$C$9)/Common_Shares*$C$3*Exchange_Rate -> 3.8921214 | C68: =(C58-$C$7+$C$8+$C$9)/Common_Shares*$C$3*Exchange_Rate -> 4.9337466 | D68: =(D58-$C$7+$C$8+$C$9)/Common_Shares*$C$3*Exchange_Rate -> 5.47268 | E68: =(E58-$C$7+$C$8+$C$9)/Common_Shares*$C$3*Exchange_Rate -> 8.7292493 | F68: =(F58-$C$7+$C$8+$C$9)/Common_Shares*$C$3*Exchange_Rate -> 8.7292493
A69: =A59 -> 20 | B69: =(B59-$C$7+$C$8+$C$9)/Common_Shares*$C$3*Exchange_Rate -> 3.6449126 | C69: =(C59-$C$7+$C$8+$C$9)/Common_Shares*$C$3*Exchange_Rate -> 4.9337466 | D69: =(D59-$C$7+$C$8+$C$9)/Common_Shares*$C$3*Exchange_Rate -> 5.6547225 | E69: =(E59-$C$7+$C$8+$C$9)/Common_Shares*$C$3*Exchange_Rate -> 10.719043 | F69: =(F59-$C$7+$C$8+$C$9)/Common_Shares*$C$3*Exchange_Rate -> 10.719043
A70: =A60 -> 25 | B70: =(B60-$C$7+$C$8+$C$9)/Common_Shares*$C$3*Exchange_Rate -> 3.4659271 | C70: =(C60-$C$7+$C$8+$C$9)/Common_Shares*$C$3*Exchange_Rate -> 4.9337466 | D70: =(D60-$C$7+$C$8+$C$9)/Common_Shares*$C$3*Exchange_Rate -> 5.8092655 | E70: =(E60-$C$7+$C$8+$C$9)/Common_Shares*$C$3*Exchange_Rate -> 12.896993 | F70: =(F60-$C$7+$C$8+$C$9)/Common_Shares*$C$3*Exchange_Rate -> 12.896993
A71: =A61 -> 30 | B71: =(B61-$C$7+$C$8+$C$9)/Common_Shares*$C$3*Exchange_Rate -> 3.3425452 | C71: =(C61-$C$7+$C$8+$C$9)/Common_Shares*$C$3*Exchange_Rate -> 4.9337466 | D71: =(D61-$C$7+$C$8+$C$9)/Common_Shares*$C$3*Exchange_Rate -> 5.9336808 | E71: =(E61-$C$7+$C$8+$C$9)/Common_Shares*$C$3*Exchange_Rate -> 15.191772 | F71: =(F61-$C$7+$C$8+$C$9)/Common_Shares*$C$3*Exchange_Rate -> 15.191772
B73: Scenarios | C73: HGR | D73: HGP | E73: Value per share | F73: Capitialization
B74: =Scenarios!B67 -> Revaluation | C74: =Scenarios!C69 -> 0.1 | D74: =Scenarios!C68 -> 10 | E74: =INDEX(B$65:F$71, MATCH(D74, A$65:A$71, 0), MATCH(C74, B$64:F$64, 0)) -> 7.0424821 | F74: =E74*Common_Shares/1000000 -> 4770.7605
B75: =Scenarios!B49 -> Optimistic | C75: =Scenarios!C51 -> 0.1 | D75: =Scenarios!C50 -> 5 | E75: =INDEX(B$65:F$71, MATCH(D75, A$65:A$71, 0), MATCH(C75, B$64:F$64, 0)) -> 5.8437422 | F75: =E75*Common_Shares/1000000 -> 3958.7029 | H75: MATCH(1%, C65:E65, 0) finds the column number for HGR = 1%.
B76: =Scenarios!B37 -> Base | C76: =Scenarios!C39 -> 0.02 | D76: =Scenarios!C38 -> 5 | E76: =INDEX(B$65:F$71, MATCH(D76, A$65:A$71, 0), MATCH(C76, B$64:F$64, 0)) -> 5.1041316 | F76: =E76*Common_Shares/1000000 -> 3457.6715 | H76: MATCH(5, B66:B69, 0) finds the row number for HGP = 5.
B77: =Scenarios!B43 -> Pessimistic | C77: =Scenarios!C45 -> 0 | D77: =Scenarios!C44 -> 5 | E77: =INDEX(B$65:F$71, MATCH(D77, A$65:A$71, 0), MATCH(C77, B$64:F$64, 0)) -> 4.9337466 | F77: =E77*Common_Shares/1000000 -> 3342.2482 | H77: INDEX(C66:E69, ...) retrieves the value from the specified range.
B78: =Scenarios!B61 -> Devil's advocate | C78: =Scenarios!C63 -> -0.05 | D78: =Scenarios!C62 -> 10 | E78: =INDEX(B$65:F$71, MATCH(D78, A$65:A$71, 0), MATCH(C78, B$64:F$64, 0)) -> 4.2048163 | F78: =E78*Common_Shares/1000000 -> 2848.4519

Sheet Scenarios
B2: Current Situation
B3: Selection
B4: Past Years Selected | C4: 4 | E4: Tie the business story into the three levers of value: FCFE, growth and risk.
B6: FCFE | C6: =Valuation_Model!C3 -> 1000 | E6: Prompt for Scenario Analysis
B7: Lastest | C7: =Normalized_FCF!G19 -> 0 | E7: Given 六福珠宝’s (0590.HK) normalized FCFE of HKD 1,270,672,000, please analyze its valuation assumptions under three scenarios (Base, Pessimistic, Optimistic) using a two-stage model, a growth stage and a terminal stage. Define the growth period, growth rates and probabilities for each scenario. Explain the rationale behind the probabilities. Summarize the business drivers and scenario narratives to align with the model’s inputs. For context only, the terminal value assumes 0% growth to prevent overvaluation. The finalized scenarios will be incorporated directly into the valuation framework.”
B8: Normalized | C8: =Normalized_FCF!C19 -> 336835.71
B10: Growth Rate
B11: Sales Growth Rates | C11: =AVERAGE(Normalized_FCF!G94:INDEX(Normalized_FCF!G94:Q94, $C$4)) -> 0.11909073
B12: Op. FCFE Before WCInv
B13: Non-Operating Income
B15: Margin
B16: Contribution Margin
B17: Op. FCFE Before WCInv
B19: Objective Scenarios
B20: No Growth Scenario | E20: Business Story
B21: Value per share | C21: =Valuation_Model!E77 -> 4.9337466 | D21: =Reporting_currency -> HKD | E21: Unbiased Scenario where the company FCFE has no growth and no risk.
B23: Market Scenario
B24: High Growth Period (HGP) | C24: 15
B25: High Growth Rate (HGR) | C25: 0.12
B26: Value per share | C26: =Valuation_Model!C18 -> 9.9356524
B28: Reference Price Points
B29: Market Price | C29: =Market_Price -> 7
B30: 52 week High | C30: 13
B31: 52 week Low
B33: General Scenarios
B34: Assumption
B35: High Growth Period (HGP) | C35: 5
B37: Base | E37: Business Story
B38: High Growth Period (HGP) | C38: =C35 -> 5
B39: High Growth Rate (HGR) | C39: 0.02
B40: Value per share | C40: =Valuation_Model!E76 -> 5.1041316 | D40: =Market_currency -> HKD
B41: Probabilities | C41: 0.6
B43: Pessimistic | E43: Business Story
B44: High Growth Period (HGP) | C44: =C35 -> 5
B45: High Growth Rate (HGR) | C45: 0
B46: Value per share | C46: =Valuation_Model!E77 -> 4.9337466 | D46: =Market_currency -> HKD
B47: Probabilities | C47: 0.2
B49: Optimistic | E49: Business Story
B50: High Growth Period (HGP) | C50: =C35 -> 5
B51: High Growth Rate (HGR) | C51: 0.1
B52: Value per share | C52: =Valuation_Model!E75 -> 5.8437422 | D52: =Market_currency -> HKD
B53: Probabilities | C53: =1-C41-C47 -> 0.2
B55: Expected Value = | C55: =C40*C41+C46*C47+C52*C53 -> 5.2179768 | D55: =Market_currency -> HKD
B57: Extreme Scenarios
B58: Assumption
B59: High Growth Period (HGP) | C59: 10
B61: Devil's advocate | E61: Business Story
B62: High Growth Period (HGP) | C62: =C59 -> 10 | E62: There is always a chance the some devil's advocate is right and I'm wrong, so the probabilities should reflect this depending on how illogical this implied drivers are.
B63: High Growth Rate (HGR) | C63: -0.05
B64: Value per share | C64: =Valuation_Model!E78 -> 4.2048163 | D64: =Market_currency -> HKD
B65: Probabilities | C65: 0.1
B67: Revaluation | E67: Business Story
B68: High Growth Period (HGP) | C68: =C59 -> 10
B69: High Growth Rate (HGR) | C69: 0.1
B70: Value per share | C70: =Valuation_Model!E74 -> 7.0424821 | D70: =Market_currency -> HKD
B71: Probabilities | C71: 0.1
B73: Expected Value = | C73: =C64*C65+C70*C71+C55*(1-C65-C71) -> 5.2991112 | D73: =Market_currency -> HKD
B75: Margin of Safety (MOS)
B76: Inputs | E76: Special Assumption
B77: Target Return | C77: =Thesis!C68 -> 0.2 | E77: the Equity Value will be conservatively realized | F77: =Thesis!C67 -> 3
B78: Annual Dividend per share | C78: =Normalized_FCF!C89 -> 0.55 | D78: =Market_currency -> HKD | E78: over a holding period of
B80: Output
B81: PV(Dividends) | C81: =PV(C77, F77, -C78, 0) -> 1.1585648
B82: PV(Equity Value) | C82: =C73/(1+C77)^F77 -> 3.0666153
B83: Buy Below | C83: =C81+C82 -> 4.2251801 | D83: =Market_currency -> HKD | E83: at a MOS of | F83: =(C83/C73-1) -> -0.2026625 | I83: Buy at < PV(dividends, 3yrs, r) + PV(Equity value, 3yrs, r)
B87: CAGR Calculator | C87: Initial Value (PV) | D87: Final Value (FV) | E87: # of Years
B88: Inputs = | C88: =Normalized_FCF!L8 -> 1242416 | D88: =Normalized_FCF!G8 -> 1378136 | E88: 6
B89: CAGR = | C89: =(D88/C88)^(1/E88)-1 -> 0.017429144
