Workbook
Name Common_Shares: Thesis!$C$12
Name Exchange_Rate: Thesis!$C$14

Sheet Thesis
B1: Investment Thesis for | C1: =Inputs!C95 -> 六福珠宝 | D1: =Inputs!C94 -> 0590.HK
B2: Model last updated: | C2: 45643
A3: Introduction
B4: Comapny Information
B5: Comp_Type: | C5: Superior Cycl.
B6: Comp_Sector: | C6: =Inputs!C99 -> C0003
B7: Review Interval: | C7: 8
B8: Review Date: | C8: =EOMONTH(EDATE(Fin_Analysis!D9,Thesis!C7),0) -> 45626
B10: =D1&" Stock Information" -> 0590.HK Stock Information
B11: Current Price: | C11: 13.82 | D11: HKD
B12: Number of Shares: | C12: =Inputs!C100 -> 587107850
B13: Reporting Currency: | C13: =Inputs!C101 -> HKD
B14: Exchange Rate: | C14: 1 | D14: =IF(C13=Thesis!D11,Thesis!D11,C13&"/"&Thesis!D11) -> HKD
B15: Capitalization: | C15: =Thesis!C11*Thesis!C12/1000000 -> 8113.8305
A17: Stock Analysis
A19: ="1." -> 1. | B19: Normalized Income Calculation
B20: Formula:
B21: Variable Cost = COGS + Selling and Distribution Costs + Other Variable Operating Expenses
B26: Net Income = Variable Cost + Fixed Cost
A30: ="1." -> 1. | B30: Adjusted FCFE Calculation
B31: Formula:
B32: Adjusted FCFE = Net Income + D&A – Maintenance Capex ± WCInv (if material).
B34: Variables
B35: Net Income =
B38: Notes:
B39: 1. the model explicitly avoids aggressive growth assumptions and prioritizes downside protection.
B40: 2. Net borrowing is excluded (fixed at 0), and WCInv is only included if it materially distorts FCFE (>5% volatility).
B41: 3. Normalization: 5-year averages will smooth cyclicality for 590.HK.
A43: ="2." -> 2. | B43: Equity Cost of Capital (Buffett Method)
B44: Assumptions:
B45: Risk-Free Rate | C45: HK | D45: =IF(C45="CN",Dashboard!C12,IF(C45="US",Dashboard!C7,IF(C45="HK",Dashboard!D7,Dashboard!D12))) -> 0.075
B46: Base ERP | C46: Stable Business | D46: =IF(LEFT(C46,1)="S",4%,IF(LEFT(C46,1)="M",6%,8%)) -> 0.04
B48: Qualitative Adjustments (2% for each):
B49: Durable moats
B50: Weak balance sheets
B51: Poor management
B53: Formula:
B54: Equity Cost(r) = 4.5% (Risk-Free) + 3.5% (ERP) – 1% (Moat) = 7%.
A56: ="3." -> 3. | B56: No-Growth DCF Valuation
B57: Key Metrics:
B58: Adjusted Earnings Yield = Adjusted FCFE / Market Cap.
B59: Intrinsic Value (No Growth) = Adjusted FCFE / Equity Cost of Capital.
B61: Decision Rule:
B62: Buy if Adjusted Earnings Yield > 7%
A64: ="4." -> 4. | B64: Growth Scenario Analysis
B65: Formula:
B66: g = (r × P - Adjusted FCFE) / (P + Adjusted FCFE)
B68: Phase Breakdown:
B69: High Growth: 5 years at 5%, then transitions to 3% perpetual growth.
B71: Scenario Analysis:
B72: Base Case
B73: Opertimistic Case
B74: Pessimistic Case
B76: Valuation
A78: ="5." -> 5. | B78: Stress Testing
B79: Variables Adjusted:
B80: Equity Cost of Capital: ±1.5% (e.g., 5.5%–8.5%).
B81: Growth Rate: ±1.5% (e.g., 1.5%–4.5%).
B82: Maintenance Capex: ±20%.
B84: Margin of Safety: | C84: 15–20%
B86: Output:
B87: Buy price range incorporating a 15–20% margin of safety (e.g., HKD 10–14/share).
A89: ="6." -> 6. | B89: Equity Value Calculation
B90: Formula:
B91: Equity Value = Intrinsic Value (with user-selected implied g) + Non-operating Assets - Interest-bearing Debt
B93: Key Adjustments:
B94: Non-operating Assets: Include cash, marketable securities, real estate, etc., at market value.
B95: Debt: Subtract total interest-bearing debt (market value if distressed).
A97: Conclusion
B98: Price Target:
B100: Catalysts:
B101: Stable FCFE generation
B102: Low leverage
B103: Strong non-operating assets
B105: Risks:
B106: Cyclicality in WCInv
B107: Rising debt levels
B108: Overstated competitive moat
A110: KEY EXCLUSIONS & LIMITATIONS
B111: Conservative Bias:
B112: Excludes net borrowing, potentially undervaluing firms with debt efficiency.
B114: Growth Constraints:
B115: Perpetual growth capped at 3%, penalizing high-growth companies.
B117: Subjective Adjustments:
B118: Non-operating assets and debt require manual review.
B123: Categories | C123: Items | D123: Results
B124: Sales | C124: Divisional Sales | D124: Total Sales
B125: Variable Costs | C125: COGS | D125: Total Variable Costs
C126: Selling and Distribution Costs
C127: Other Variable Operating Expenses
B128: Contribution Margin | C128: Total Sales - Total Variable Costs | D128: Contribution Margin
B129: Fixed Costs | C129: Administrative and General Expenses | D129: Pre-tax Profit (EBT)
C130: Other Fixed Operating Expenses
C131: Interest Expense
B132: Income Tax Expense | C132: Tax Rate | D132: Net Income
B133: Adjustments | C133: D&A | D133: FCFF
C134: Capex - D&A
C135: ΔWC
B137: Component | C137: Amount ($) | D137: Percentage of Sales
B138: Sales Revenue | C138: 1000 | D138: =C138/$C$138 -> 1
...

Sheet Inputs
C1: =C102 -> 45382 | D1: =EOMONTH(EDATE(C1,-12),0) -> 45016 | E1: =EOMONTH(EDATE(D1,-12),0) -> 44651 | F1: =EOMONTH(EDATE(E1,-12),0) -> 44286 | G1: =EOMONTH(EDATE(F1,-12),0) -> 43921 | H1: =EOMONTH(EDATE(G1,-12),0) -> 43555 | I1: =EOMONTH(EDATE(H1,-12),0) -> 43190 | J1: =EOMONTH(EDATE(I1,-12),0) -> 42825 | K1: =EOMONTH(EDATE(J1,-12),0) -> 42460 | ... M1: =EOMONTH(EDATE(L1,-12),0) -> 41729
B2: Financial Statements Inputs
B3: Income Statement
B4: Sales | C4: 15325962 | D4: 11977844 | E4: 11737803 | F4: 8861335 | G4: 11233771 | H4: 15859990
B5: COGS | C5: -11151623 | D5: -8747447 | E5: -8503976 | F5: -6229020 | G5: -7910751 | H5: -11826154 | I5: 0 | J5: 0 | K5: 0 | L5: 0 | M5: 0
B6: Selling and Marketing Expenses | C6: -2043459 | D6: -1517989 | E6: -1491293 | F6: -1412494
B7: Other Variable Operating Expenses
B8: OPEX | C8: -2297566 | D8: -1867515 | E8: -1815111 | F8: -1694480 | G8: -2118252 | H8: -2416769 | I8: 0 | J8: 0 | K8: 0 | L8: 0 | M8: 0
B9: R&D
B10: Interest Expense | C10: -59596 | D10: -20763 | E10: -23097 | F10: -28849 | G10: -63075 | H10: -34253 | I10: 0 | J10: 0 | K10: 0 | L10: 0 | M10: 0
B11: Income Tax Paid
B12: Reported Net Income | C12: 1767305 | D12: 1284757 | E12: 1392364 | F12: 1017335 | G12: 866315
B13: Non-controling Interests | C13: 9467 | D13: 30 | E13: 27 | F13: -1799 | G13: -1337 | H13: -10908 | I13: 0 | J13: 0 | K13: 0 | L13: 0 | M13: 0
B15: Cash Flow Statement
B16: D&A | C16: 456554 | D16: 373191
B17: CAPX | C17: 676387 | D17: 107280 | E17: 455483 | F17: 138937
B18: WCInv | C18: 626583 | D18: 352099 | E18: 1045251 | F18: -818677
B20: Balance Sheet
B21: Total Liabilities | C21: 3990166 | D21: 2466431 | E21: 3908586 | F21: 2946772
B22: Total Equity | C22: 12863898 | D22: 12220942 | E22: 12078528 | F22: 11324224
B23: ST AR | D23: 213823 | E23: 187711 | F23: 277338
B24: ST Inventory | D24: 8852611 | E24: 8769304 | F24: 7321614
B26: Other Data
B27: Contingent Liabilities | C27: =20356+1075000 -> 1095356 | D27: =24308+1075000 -> 1099308 | E27: =32736+1075000 -> 1107736 | F27: =47325+1075000 -> 1122325
B28: Dividend per share | C28: =0.72+0.64 -> 1.36 | D28: =0.55+0.55 -> 1.1 | E28: =0.55+0.55 -> 1.1 | F28: =0.5+0.5 -> 1 | G28: =0.5+0.5 -> 1 | H28: =0.6+0.55 -> 1.15
B29: Dividend Yield | C29: =IF(C28="","",C28*Exchange_Rate/Thesis!$C$11) -> 0.098408104 | D29: =IF(D28="","",D28*Exchange_Rate/Thesis!$C$11) -> 0.07959479 | E29: =IF(E28="","",E28*Exchange_Rate/Thesis!$C$11) -> 0.07959479 | F29: =IF(F28="","",F28*Exchange_Rate/Thesis!$C$11) -> 0.0723589 | G29: =IF(G28="","",G28*Exchange_Rate/Thesis!$C$11) -> 0.0723589 | H29: =IF(H28="","",H28*Exchange_Rate/Thesis!$C$11) -> 0.083212735 | I29: =IF(I28="","",I28*Exchange_Rate/Thesis!$C$11) | J29: =IF(J28="","",J28*Exchange_Rate/Thesis!$C$11) | ... M29: =IF(M28="","",M28*Exchange_Rate/Thesis!$C$11)
B31: ="Last Balance Sheet"&IF(SUM(C32:C56)=C21+C22,"","- Error") -> Last Balance Sheet | C31: Book Figure | D31: Valued @ | E31: is_OP
B32: Cash and cash equivalents | C32: 1998219 | D32: 0.9
B33: Restricted cash | D33: 0.8
B34: ST AR | C34: 265773 | D34: =D35 -> 0.6
B35: ST FV Investments | D35: 0.6
B36: ST non-FV Investments | D36: 0.5
B37: Operating ST Financial Assets | D37: =D34 -> 0.6
B38: Prepayments or Contract Assets | C38: 366595 | D38: 0.1
B39: Inventory | C39: 9672256 | D39: =D36 -> 0.5
B40: Properties held for sale | D40: =D34 -> 0.6 | E40: N
B41: Properties under development | D41: 0.6 | E41: Y
B42: ST DTA | C42: 29465 | D42: =D32 -> 0.9
B43: Other ST Assets | D43: =D54 -> 0.05
B44: LT Depositis | D44: =D33 -> 0.8
B45: LT FV Securities | D45: =D35 -> 0.6
B46: LT non-FV Securities | D46: =D36 -> 0.5
B47: Operating LT Financial Assets | D47: =D46 -> 0.5
B48: LT AR or Prepayments | C48: 103050 | D48: 0.4
B49: Investments in JV or associate | D49: 0.1 | E49: N
B50: Investment property | C50: 925726 | D50: 0.2 | E50: N
B51: Properties under development | D51: =D49 -> 0.1 | E51: Y
B52: PP&E & Right of Use Assets | C52: 2522337 | D52: =D49 -> 0.1
B53: Biological assets | D53: =D54 -> 0.05
B54: Intangible assets | C54: 538321 | D54: 0.05
B55: LT DTA | C55: 154648 | D55: =D42 -> 0.9
B56: Other assets & Goodwill | C56: 277674 | D56: 0
B57: ST Borrowing | C57: 1427805
B58: ST Lease liabilities | C58: 287697
B59: ST SH Loan
B60: ST Financial Liabilities
B61: Current Liabilities | C61: 3516809
B62: LT Borrowing
B63: LT Lease liabilities | C63: 319420
B64: LT SH Loan
B65: LT Financial Liabilities
B66: + MV of the Options
B67: + Preference Shares
B68: Valuation method | C68: Profit | D68: 0.02
B70: Non-common Interest | C70: -26962
B73: Normalized FCFE Analysis | C73: =C1 -> 45382 | E73: Pessimistic Case | F73: Base Case
B74: ="(Numbers in "&Data!E77&Thesis!C13&")" -> (Numbers in 1000HKD) | C74: Base Year | E74: Normalized Year | F74: Normalized Year
B75: Sales | C75: =C4 -> 15325962 | E75: =C75*0.8 -> 12260770 | F75: =C75*0.9 -> 13793366
B76: - COGS | C76: =C5 -> -11151623 | D76: =C76/C75 -> -0.72762956 | E76: =E75*D76 -> -8921298.4 | F76: =F75*D76 -> -10036461
B77: - (OPEX + R&D) = | C77: =C8+C9 -> -2297566 | D77: =C77/C75 -> -0.14991333 | E77: =E75*16.54% -> 2027931.3 | F77: =F75*16.54% -> 2281422.7
B78: - Interest Expense | C78: =C10 -> -59596 | D78: =C78/C75 -> -0.003888565 | F78: =F75*D78 -> -53636.4
B79: - (CAPX - D&A) | C79: =ABS(MAX(C17,0)-C16) -> 219833 | D79: =C79/C75 -> 0.01434383 | E79: =E75*1% -> 122607.7 | F79: =F75*1% -> 137933.66
B80: - WCINv | C80: =MAX(C18,0) -> 626583 | D80: =C80/C75 -> 0.040883763 | F80: =F75*2.5% -> 344834.15
B81: - Non-controling Interests | C81: =MAX(C13,0)/(1-C106) -> 12622.667 | D81: =C81/C75 -> 0.00082361333 | F81: =F75*D81 -> 11360.4
B82: Dividend per share | C82: =C28 -> 1.36 | E82: 1 | F82: =0.55+0.55 -> 1.1
B85: 1. Consumer monopoly? | C85: Strongly agree
B86: 3. Upward earnings trend? | C86: unclear
B87: 4. Stable margin and ROE? | C87: agree
B88: 5. Can earnings be sustained? | C88: agree
B89: 6. No big MCX-D&A required? | C89: Strongly agree
B90: If you had access to billions of dollars and your pick of the top fifty managers in the country, could you start a business and successfully compete with the business in question? | C90: Consumer Monopoly
B92: Inputs
B94: Symbol: | C94: 0590.HK
B95: Name: | C95: 六福珠宝
B96: Model last updated: | C96: 45643
B97: Next Review Date: | C97: 8
B98: Watchlist | C98: Superior Cycl.
B99: Comp_Group: | C99: C0003
B100: Number of Shares: | C100: 587107850
B101: Reporting Currency: | C101: HKD
B102: Year of the last 10k = | C102: 45382
B103: Unit = | C103: 1000
B104: Most Recent Quarter | C104: 45382
B105: Choice of Discount Rate | C105: HK
B106: Tax Rate | C106: 0.25 | E106: https://pages.stern.nyu.edu/~adamodar/New_Home_Page/datafile/countrytaxrates.html
B107: If Holding | C107: HOLD

Sheet Data
B1: ="("&Inputs!C103&" "&Thesis!C13&")" -> (1000 HKD) | C1: Normalized | E1: =E76 -> 45382 | F1: =EOMONTH(EDATE(E1,-12),0) -> 45016 | G1: =EOMONTH(EDATE(F1,-12),0) -> 44651 | H1: =EOMONTH(EDATE(G1,-12),0) -> 44286 | I1: =EOMONTH(EDATE(H1,-12),0) -> 43921 | J1: =EOMONTH(EDATE(I1,-12),0) -> 43555 | K1: =EOMONTH(EDATE(J1,-12),0) -> 43190 | L1: =EOMONTH(EDATE(K1,-12),0) -> 42825 | M1: =EOMONTH(EDATE(L1,-12),0) -> 42460 | ... O1: =EOMONTH(EDATE(N1,-12),0) -> 41729
B2: Financials
B3: Adjusted FCFE
B4: Sales | C4: =AVERAGE(E4:H4) -> 11975736 | E4: =IF(Inputs!C4=""," ",Inputs!C4) -> 15325962 | F4: =IF(Inputs!D4="","",Inputs!D4) -> 11977844 | G4: =IF(Inputs!E4="","",Inputs!E4) -> 11737803 | H4: =IF(Inputs!F4="","",Inputs!F4) -> 8861335 | I4: =IF(Inputs!G4="","",Inputs!G4) -> 11233771 | J4: =IF(Inputs!H4="","",Inputs!H4) -> 15859990 | K4: =IF(Inputs!I4="","",Inputs!I4) | L4: =IF(Inputs!J4="","",Inputs!J4) | M4: =IF(Inputs!K4="","",Inputs!K4) | ... O4: =IF(Inputs!M4="","",Inputs!M4)
B5: COGS | C5: =-C4*C19 -> -8652915.6 | E5: =IF(Inputs!C5="","",Inputs!C5) -> -11151623 | F5: =IF(Inputs!D5="","",Inputs!D5) -> -8747447 | G5: =IF(Inputs!E5="","",Inputs!E5) -> -8503976 | H5: =IF(Inputs!F5="","",Inputs!F5) -> -6229020 | I5: =IF(Inputs!G5="","",Inputs!G5) -> -7910751 | J5: =IF(Inputs!H5="","",Inputs!H5) -> -11826154 | K5: =IF(Inputs!I5="","",Inputs!I5) -> 0 | L5: =IF(Inputs!J5="","",Inputs!J5) -> 0 | ... O5: =IF(Inputs!M5="","",Inputs!M5) -> 0
B6: Gross Profit | C6: =C4+C5 -> 3322820.4 | E6: =IF(E4="","",E4+E5) -> 4174339 | F6: =IF(F4="","",F4+F5) -> 3230397 | G6: =IF(G4="","",G4+G5) -> 3233827 | H6: =IF(H4="","",H4+H5) -> 2632315 | I6: =IF(I4="","",I4+I5) -> 3323020 | J6: =IF(J4="","",J4+J5) -> 4033836 | K6: =IF(K4="","",K4+K5) | L6: =IF(L4="","",L4+L5) | ... O6: =IF(O4="","",O4+O5)
B7: Selling and Marketing Expenses | E7: =IF(Inputs!C6="","",Inputs!C6) -> -2043459 | F7: =IF(Inputs!D6="","",Inputs!D6) -> -1517989 | G7: =IF(Inputs!E6="","",Inputs!E6) -> -1491293 | H7: =IF(Inputs!F6="","",Inputs!F6) -> -1412494 | I7: =IF(Inputs!G6="","",Inputs!G6) | J7: =IF(Inputs!H6="","",Inputs!H6) | K7: =IF(Inputs!I6="","",Inputs!I6) | L7: =IF(Inputs!J6="","",Inputs!J6) | ... O7: =IF(Inputs!M6="","",Inputs!M6)
B8: Other Variable Operating Expenses | E8: =IF(Inputs!C7="",0,Inputs!C7) -> 0 | F8: =IF(Inputs!D7="",0,Inputs!D7) -> 0 | G8: =IF(Inputs!E7="",0,Inputs!E7) -> 0 | H8: =IF(Inputs!F7="",0,Inputs!F7) -> 0 | I8: =IF(Inputs!G7="",0,Inputs!G7) -> 0 | J8: =IF(Inputs!H7="",0,Inputs!H7) -> 0 | K8: =IF(Inputs!I7="",0,Inputs!I7) -> 0 | L8: =IF(Inputs!J7="",0,Inputs!J7) -> 0 | ... O8: =IF(Inputs!M7="",0,Inputs!M7) -> 0
B9: Contribution Margin | E9: =IF(E4="","",E6+E7+E8) -> 2130880 | F9: =IF(F4="","",F6+F7+F8) -> 1712408 | G9: =IF(G4="","",G6+G7+G8) -> 1742534 | H9: =IF(H4="","",H6+H7+H8) -> 1219821 | I9: =IF(I4="","",I6+I7+I8) -> #VALUE! | J9: =IF(J4="","",J6+J7+J8) -> #VALUE!
B10: Other Operating Expenses | E10: =IF(Inputs!C8="","",Inputs!C8-E7) -> -254107 | F10: =IF(Inputs!D8="","",Inputs!D8-F7) -> -349526 | G10: =IF(Inputs!E8="","",Inputs!E8-G7) -> -323818 | H10: =IF(Inputs!F8="","",Inputs!F8-H7) -> -281986 | I10: =IF(Inputs!G8="","",Inputs!G8-I7) -> #VALUE! | J10: =IF(Inputs!H8="","",Inputs!H8-J7) -> #VALUE! | K10: =IF(Inputs!I8="","",Inputs!I8) -> 0 | L10: =IF(Inputs!J8="","",Inputs!J8) -> 0 | M10: =IF(Inputs!K8="","",Inputs!K8) -> 0 | N10: =IF(Inputs!L8="","",Inputs!L8) -> 0 | O10: =IF(Inputs!M8="","",Inputs!M8) -> 0
B11: - R&D | E11: 0 | F11: =IF(Inputs!D9="","",Inputs!D9) | G11: =IF(Inputs!E9="","",Inputs!E9) | H11: =IF(Inputs!F9="","",Inputs!F9) | I11: =IF(Inputs!G9="","",Inputs!G9) | J11: =IF(Inputs!H9="","",Inputs!H9) | K11: =IF(Inputs!I9="","",Inputs!I9) | L11: =IF(Inputs!J9="","",Inputs!J9) | M11: =IF(Inputs!K9="","",Inputs!K9) | ... O11: =IF(Inputs!M9="","",Inputs!M9)
B12: - Pre-tax Non-controling Interests | E12: =IF(Inputs!C13="","",MAX(Inputs!C13,0)/(1-Fin_Analysis!$I$84)) -> 12622.667 | F12: =IF(Inputs!D13="","",MAX(Inputs!D13,0)/(1-Fin_Analysis!$I$84)) -> 40 | G12: =IF(Inputs!E13="","",MAX(Inputs!E13,0)/(1-Fin_Analysis!$I$84)) -> 36 | H12: =IF(Inputs!F13="","",MAX(Inputs!F13,0)/(1-Fin_Analysis!$I$84)) -> 0 | I12: =IF(Inputs!G13="","",MAX(Inputs!G13,0)/(1-Fin_Analysis!$I$84)) -> 0 | J12: =IF(Inputs!H13="","",MAX(Inputs!H13,0)/(1-Fin_Analysis!$I$84)) -> 0 | K12: =IF(Inputs!I13="","",MAX(Inputs!I13,0)/(1-Fin_Analysis!$I$84)) -> 0 | L12: =IF(Inputs!J13="","",MAX(Inputs!J13,0)/(1-Fin_Analysis!$I$84)) -> 0 | ... O12: =IF(Inputs!M13="","",MAX(Inputs!M13,0)/(1-Fin_Analysis!$I$84)) -> 0
B13: EBIT | E13: =E9+E10+E11+E12 -> 1889395.7 | F13: =IF(F4="","",F6-F10-MAX(F11,0)-MAX(F12,0)) -> 3579883 | G13: =IF(G4="","",G6-G10-MAX(G11,0)-MAX(G12,0)) -> 3557609 | H13: =IF(H4="","",H6-H10-MAX(H11,0)-MAX(H12,0)) -> 2914301 | I13: =IF(I4="","",I6-I10-MAX(I11,0)-MAX(I12,0)) -> #VALUE! | J13: =IF(J4="","",J6-J10-MAX(J11,0)-MAX(J12,0)) -> #VALUE! | K13: =IF(K4="","",K6-K10-MAX(K11,0)-MAX(K12,0)) | L13: =IF(L4="","",L6-L10-MAX(L11,0)-MAX(L12,0)) | M13: =IF(M4="","",M6-M10-MAX(M11,0)-MAX(M12,0)) | ... O13: =IF(O4="","",O6-O10-MAX(O11,0)-MAX(O12,0))
B14: Non-Operating Net Income | E14: =IF(E15="","",E15-E13) -> -122090.67 | F14: =IF(F15="","",F15-F13) -> -2295126 | G14: =IF(G15="","",G15-G13) -> -2165245 | H14: =IF(H15="","",H15-H13) -> -1896966 | I14: =IF(I15="","",I15-I13) -> #VALUE! | J14: =IF(J15="","",J15-J13) | K14: =IF(K15="","",K15-K13) | L14: =IF(L15="","",L15-L13) | ... O14: =IF(O15="","",O15-O13)
B15: Reported Net Income | E15: =IF(Inputs!C12="","",Inputs!C12) -> 1767305 | F15: =IF(Inputs!D12="","",Inputs!D12) -> 1284757 | G15: =IF(Inputs!E12="","",Inputs!E12) -> 1392364 | H15: =IF(Inputs!F12="","",Inputs!F12) -> 1017335 | I15: =IF(Inputs!G12="","",Inputs!G12) -> 866315 | J15: =IF(Inputs!H12="","",Inputs!H12) | K15: =IF(Inputs!I12="","",Inputs!I12) | L15: =IF(Inputs!J12="","",Inputs!J12) | ... O15: =IF(Inputs!M12="","",Inputs!M12)
B16: - ΔWC | E16: =IF(Inputs!C18="","",Inputs!C18) -> 626583 | F16: =IF(Inputs!D18="","",Inputs!D18) -> 352099 | G16: =IF(Inputs!E18="","",Inputs!E18) -> 1045251 | H16: =IF(Inputs!F18="","",Inputs!F18) -> -818677 | I16: =IF(Inputs!G18="","",Inputs!G18) | J16: =IF(Inputs!H18="","",Inputs!H18) | K16: =IF(Inputs!I18="","",Inputs!I18) | L16: =IF(Inputs!J18="","",Inputs!J18) | ... O16: =IF(Inputs!M18="","",Inputs!M18)
B18: % Sales
B19: COGS | C19: =AVERAGE(E19:J19) -> 0.72253727 | E19: =IF(E4="","",-E5/E4) -> 0.72762956 | F19: =IF(F4="","",-F5/F4) -> 0.7303023 | G19: =IF(G4="","",-G5/G4) -> 0.72449469 | H19: =IF(H4="","",-H5/H4) -> 0.70294374 | I19: =IF(I4="","",-I5/I4) -> 0.70419372 | J19: =IF(J4="","",-J5/J4) -> 0.74565961 | K19: =IF(K4="","",-K5/K4) | L19: =IF(L4="","",-L5/L4) | ... O19: =IF(O4="","",-O5/O4)
B20: Gross Profit | C20: =C6/C4 -> 0.27746273 | E20: =IF(E4="","",E6/E4) -> 0.27237044 | F20: =IF(F4="","",F6/F4) -> 0.2696977 | G20: =IF(G4="","",G6/G4) -> 0.27550531 | H20: =IF(H4="","",H6/H4) -> 0.29705626 | I20: =IF(I4="","",I6/I4) -> 0.29580628 | J20: =IF(J4="","",J6/J4) -> 0.25434039 | K20: =IF(K4="","",K6/K4) | L20: =IF(L4="","",L6/L4) | ... O20: =IF(O4="","",O6/O4)
B21: Selling and Marketing Expenses
B22: Other Variable Operating Expenses
B23: Contribution Margin | E23: =E9/E4 -> 0.13903728 | F23: =F9/F4 -> 0.14296463 | G23: =G9/G4 -> 0.14845487 | H23: =H9/H4 -> 0.13765657 | I23: =I9/I4 -> #VALUE! | J23: =J9/J4 -> #VALUE!
B24: Other Operating Expenses | E24: =IF(E4="","",(-(E10-E21-E22)/E4)) -> 0.016580166 | F24: =IF(F4="","",(-(F10-F21-F22)/F4)) -> 0.029181045 | G24: =IF(G4="","",(-(G10-G21-G22)/G4)) -> 0.027587616 | H24: =IF(H4="","",(-(H10-H21-H22)/H4)) -> 0.031822067 | I24: =IF(I4="","",(-(I10-I21-I22)/I4)) -> #VALUE! | J24: =IF(J4="","",(-(J10-J21-J22)/J4)) -> #VALUE! | K24: =IF(K4="","",(-(K10-K21-K22)/K4)) | L24: =IF(L4="","",(-(L10-L21-L22)/L4)) | ... O24: =IF(O4="","",(-(O10-O21-O22)/O4))
B25: R&D | E25: =IF(E4="","",MAX(E11,0)/E4) -> 0 | F25: =IF(F4="","",MAX(F11,0)/F4) -> 0 | G25: =IF(G4="","",MAX(G11,0)/G4) -> 0 | H25: =IF(H4="","",MAX(H11,0)/H4) -> 0 | I25: =IF(I4="","",MAX(I11,0)/I4) -> 0 | J25: =IF(J4="","",MAX(J11,0)/J4) -> 0 | K25: =IF(K4="","",MAX(K11,0)/K4) | L25: =IF(L4="","",MAX(L11,0)/L4) | ... O25: =IF(O4="","",MAX(O11,0)/O4)
B26: EBIT Margin | E26: =E13/E4 -> 0.12328072 | F26: =F13/F4 -> 0.29887541 | G26: =G13/G4 -> 0.30308985 | H26: =H13/H4 -> 0.32887832 | I26: =I13/I4 -> #VALUE! | J26: =J13/J4 -> #VALUE!
B27: Interest/Sales | E27: =IF(E4="","",MAX(E32,0)/E4) -> 0 | F27: =IF(F4="","",MAX(F32,0)/F4) -> 0 | G27: =IF(G4="","",MAX(G32,0)/G4) -> 0 | H27: =IF(H4="","",MAX(H32,0)/H4) -> 0 | I27: =IF(I4="","",MAX(I32,0)/I4) -> 0 | J27: =IF(J4="","",MAX(J32,0)/J4) -> 0 | K27: =IF(K4="","",MAX(K32,0)/K4) | L27: =IF(L4="","",MAX(L32,0)/L4) | ... O27: =IF(O4="","",MAX(O32,0)/O4)
B28: EBT Margin
B29: WCInv | E29: =IF(E4="","",MAX(E16,0)/E4) -> 0.040883763 | F29: =IF(F4="","",MAX(F16,0)/F4) -> 0.029395858 | G29: =IF(G4="","",MAX(G16,0)/G4) -> 0.08904997 | H29: =IF(H4="","",MAX(H16,0)/H4) -> 0 | I29: =IF(I4="","",MAX(I16,0)/I4) -> 0 | J29: =IF(J4="","",MAX(J16,0)/J4) -> 0 | K29: =IF(K4="","",MAX(K16,0)/K4) | L29: =IF(L4="","",MAX(L16,0)/L4) | ... O29: =IF(O4="","",MAX(O16,0)/O4)
B30: (CAPX-D&A)/Sales | E30: =IF(E4="","",ABS(MAX(E34,0)-MAX(E33,0))/E4) -> 0.011995462 | F30: =IF(F4="","",ABS(MAX(F34,0)-MAX(F33,0))/F4) -> 0.024948814 | G30: =IF(G4="","",ABS(MAX(G34,0)-MAX(G33,0))/G4) -> 0.00079989415 | H30: =IF(H4="","",ABS(MAX(H34,0)-MAX(H33,0))/H4) -> 0.045986637 | I30: =IF(I4="","",ABS(MAX(I34,0)-MAX(I33,0))/I4) -> 0.054955455 | J30: =IF(J4="","",ABS(MAX(J34,0)-MAX(J33,0))/J4) -> 0 | K30: =IF(K4="","",ABS(MAX(K34,0)-MAX(K33,0))/K4) | L30: =IF(L4="","",ABS(MAX(L34,0)-MAX(L33,0))/L4) | ... O30: =IF(O4="","",ABS(MAX(O34,0)-MAX(O33,0))/O4)
B31: Pre-tax Minority Interests | E31: =IF(E4="","",MAX(E12,0)/E4) -> 0.00082361333 | F31: =IF(F4="","",MAX(F12,0)/F4) -> 3.3394992e-06 | G31: =IF(G4="","",MAX(G12,0)/G4) -> 3.0670135e-06 | H31: =IF(H4="","",MAX(H12,0)/H4) -> 0 | I31: =IF(I4="","",MAX(I12,0)/I4) -> 0 | J31: =IF(J4="","",MAX(J12,0)/J4) -> 0 | K31: =IF(K4="","",MAX(K12,0)/K4) | L31: =IF(L4="","",MAX(L12,0)/L4) | ... O31: =IF(O4="","",MAX(O12,0)/O4)
B32: - Interest Expense | E32: =IF(Inputs!C10="","",Inputs!C10) -> -59596 | F32: =IF(Inputs!D10="","",Inputs!D10) -> -20763 | G32: =IF(Inputs!E10="","",Inputs!E10) -> -23097 | H32: =IF(Inputs!F10="","",Inputs!F10) -> -28849 | I32: =IF(Inputs!G10="","",Inputs!G10) -> -63075 | J32: =IF(Inputs!H10="","",Inputs!H10) -> -34253 | K32: =IF(Inputs!I10="","",Inputs!I10) -> 0 | L32: =IF(Inputs!J10="","",Inputs!J10) -> 0 | ... O32: =IF(Inputs!M10="","",Inputs!M10) -> 0
B33: + D&A | E33: 492545 | F33: 406113 | G33: 464872 | H33: 546440 | I33: 617357 | K33: =IF(Inputs!I16="","",Inputs!I16) | L33: =IF(Inputs!J16="","",Inputs!J16) | M33: =IF(Inputs!K16="","",Inputs!K16) | N33: =IF(Inputs!L16="","",Inputs!L16) | O33: =IF(Inputs!M16="","",Inputs!M16)
B34: - CAPX | E34: =IF(Inputs!C17="","",Inputs!C17) -> 676387 | F34: =IF(Inputs!D17="","",Inputs!D17) -> 107280 | G34: =IF(Inputs!E17="","",Inputs!E17) -> 455483 | H34: =IF(Inputs!F17="","",Inputs!F17) -> 138937 | I34: =IF(Inputs!G17="","",Inputs!G17) | J34: =IF(Inputs!H17="","",Inputs!H17) | K34: =IF(Inputs!I17="","",Inputs!I17) | L34: =IF(Inputs!J17="","",Inputs!J17) | ... O34: =IF(Inputs!M17="","",Inputs!M17)
B35: Est. Pre-tax FCF | E35: =IF(E4="","",E13-MAX(E16,0)-MAX(E32,0)-ABS(MAX(E34,0)-MAX(E33,0))) -> 1078970.7 | F35: =IF(F4="","",F13-MAX(F16,0)-MAX(F32,0)-ABS(MAX(F34,0)-MAX(F33,0))) -> 2928951 | G35: =IF(G4="","",G13-MAX(G16,0)-MAX(G32,0)-ABS(MAX(G34,0)-MAX(G33,0))) -> 2502969 | H35: =IF(H4="","",H13-MAX(H16,0)-MAX(H32,0)-ABS(MAX(H34,0)-MAX(H33,0))) -> 2506798 | I35: =IF(I4="","",I13-MAX(I16,0)-MAX(I32,0)-ABS(MAX(I34,0)-MAX(I33,0))) -> #VALUE! | J35: =IF(J4="","",J13-MAX(J16,0)-MAX(J32,0)-ABS(MAX(J34,0)-MAX(J33,0))) -> #VALUE! | K35: =IF(K4="","",K13-MAX(K16,0)-MAX(K32,0)-ABS(MAX(K34,0)-MAX(K33,0))) | L35: =IF(L4="","",L13-MAX(L16,0)-MAX(L32,0)-ABS(MAX(L34,0)-MAX(L33,0))) | ... O35: =IF(O4="","",O13-MAX(O16,0)-MAX(O32,0)-ABS(MAX(O34,0)-MAX(O33,0)))
B36: After-tax Profit Margin | E36: =IF(E4="","",E37/E4) -> 0.052801123 | F36: =IF(F4="","",F37/F4) -> 0.18339805 | G36: =IF(G4="","",G37/G4) -> 0.15992999 | H36: =IF(H4="","",H37/H4) -> 0.21216876 | I36: =IF(I4="","",I37/I4) -> #VALUE! | J36: =IF(J4="","",J37/J4) -> #VALUE! | K36: =IF(K4="","",K37/K4) | L36: =IF(L4="","",L37/L4) | ... O36: =IF(O4="","",O37/O4)
B37: Est. After-tax FCF | E37: =IF(E4="","",E35*(1-Fin_Analysis!$I$84)) -> 809228 | F37: =IF(F4="","",F35*(1-Fin_Analysis!$I$84)) -> 2196713.2 | G37: =IF(G4="","",G35*(1-Fin_Analysis!$I$84)) -> 1877226.8 | H37: =IF(H4="","",H35*(1-Fin_Analysis!$I$84)) -> 1880098.5 | I37: =IF(I4="","",I35*(1-Fin_Analysis!$I$84)) -> #VALUE! | J37: =IF(J4="","",J35*(1-Fin_Analysis!$I$84)) -> #VALUE! | K37: =IF(K4="","",K35*(1-Fin_Analysis!$I$84)) | L37: =IF(L4="","",L35*(1-Fin_Analysis!$I$84)) | ... O37: =IF(O4="","",O35*(1-Fin_Analysis!$I$84))
B38: After-tax Profit Growth | E38: =IF(F37="","",IF(ABS(E37+F37)=ABS(E37)+ABS(F37),IF(E37<0,-1,1)*(E37-F37)/F37,"Turn")) -> -0.63161874 | F38: =IF(G37="","",IF(ABS(F37+G37)=ABS(F37)+ABS(G37),IF(F37<0,-1,1)*(F37-G37)/G37,"Turn")) -> 0.17019068 | G38: =IF(H37="","",IF(ABS(G37+H37)=ABS(G37)+ABS(H37),IF(G37<0,-1,1)*(G37-H37)/H37,"Turn")) -> -0.0015274466 | H38: =IF(I37="","",IF(ABS(H37+I37)=ABS(H37)+ABS(I37),IF(H37<0,-1,1)*(H37-I37)/I37,"Turn")) -> #VALUE! | I38: =IF(J37="","",IF(ABS(I37+J37)=ABS(I37)+ABS(J37),IF(I37<0,-1,1)*(I37-J37)/J37,"Turn")) -> #VALUE! | J38: =IF(K37="","",IF(ABS(J37+K37)=ABS(J37)+ABS(K37),IF(J37<0,-1,1)*(J37-K37)/K37,"Turn")) | K38: =IF(L37="","",IF(ABS(K37+L37)=ABS(K37)+ABS(L37),IF(K37<0,-1,1)*(K37-L37)/L37,"Turn")) | L38: =IF(M37="","",IF(ABS(L37+M37)=ABS(L37)+ABS(M37),IF(L37<0,-1,1)*(L37-M37)/M37,"Turn")) | ... N38: =IF(O37="","",IF(ABS(N37+O37)=ABS(N37)+ABS(O37),IF(N37<0,-1,1)*(N37-O37)/O37,"Turn")) | O38: =IF(#REF!="","",IF(ABS(O37+#REF!)=ABS(O37)+ABS(#REF!),IF(O37<0,-1,1)*(O37-#REF!)/#REF!,"Turn")) -> #REF!
B40: % Sales
B41: EBIT/Sales | E41: =IF(E13="","",E13/E4) -> 0.12328072 | F41: =IF(F13="","",F13/F4) -> 0.29887541 | G41: =IF(G13="","",G13/G4) -> 0.30308985 | H41: =IF(H13="","",H13/H4) -> 0.32887832 | I41: =IF(I13="","",I13/I4) -> #VALUE! | J41: =IF(J13="","",J13/J4) -> #VALUE! | K41: =IF(K13="","",K13/K4) | L41: =IF(L13="","",L13/L4) | ... O41: =IF(O13="","",O13/O4)
B42: D&A/Sales | E42: =IF(OR(E4="",E33=""),"",E33/E4) -> 0.03213795 | F42: =IF(OR(F4="",F33=""),"",F33/F4) -> 0.033905351 | G42: =IF(OR(G4="",G33=""),"",G33/G4) -> 0.039604686 | H42: =IF(OR(H4="",H33=""),"",H33/H4) -> 0.061665652 | I42: =IF(OR(I4="",I33=""),"",I33/I4) -> 0.054955455 | J42: =IF(OR(J4="",J33=""),"",J33/J4) | K42: =IF(OR(K4="",K33=""),"",K33/K4) | L42: =IF(OR(L4="",L33=""),"",L33/L4) | ... O42: =IF(OR(O4="",O33=""),"",O33/O4)
B43: CAPX/Sales | E43: =IF(E4="","",MAX(E34,0)/E4) -> 0.044133412 | F43: =IF(F4="","",MAX(F34,0)/F4) -> 0.0089565368 | G43: =IF(G4="","",MAX(G34,0)/G4) -> 0.038804792 | H43: =IF(H4="","",MAX(H34,0)/H4) -> 0.015679015 | I43: =IF(I4="","",MAX(I34,0)/I4) -> 0 | J43: =IF(J4="","",MAX(J34,0)/J4) -> 0 | K43: =IF(K4="","",MAX(K34,0)/K4) | L43: =IF(L4="","",MAX(L34,0)/L4) | ... O43: =IF(O4="","",MAX(O34,0)/O4)
B44: Pre-tax Profit/Sales | E44: =IF(E4="","",E35/E4) -> 0.070401497 | F44: =IF(F4="","",F35/F4) -> 0.24453074 | G44: =IF(G4="","",G35/G4) -> 0.21323999 | H44: =IF(H4="","",H35/H4) -> 0.28289169 | I44: =IF(I4="","",I35/I4) -> #VALUE! | J44: =IF(J4="","",J35/J4) -> #VALUE! | K44: =IF(K4="","",K35/K4) | L44: =IF(L4="","",L35/L4) | ... O44: =IF(O4="","",O35/O4)
B46: YoY
B47: Sales Growth Rate | E47: =IF(F4="","",E4/F4-1) -> 0.27952593 | F47: =IF(G4="","",F4/G4-1) -> 0.02045025 | G47: =IF(H4="","",G4/H4-1) -> 0.32460888 | H47: =IF(I4="","",H4/I4-1) -> -0.21118785 | I47: =IF(J4="","",I4/J4-1) -> -0.29169117 | J47: =IF(K4="","",J4/K4-1) | K47: =IF(L4="","",K4/L4-1) | L47: =IF(M4="","",L4/M4-1) | ... N47: =IF(O4="","",N4/O4-1) | O47: =IF(P3="","",O4/P3-1)
B48: EBIT Growth | E48: =IF(F13="","",IF(ABS(E13+F13)=ABS(E13)+ABS(F13),IF(E13<0,-1,1)*(E13-F13)/F13,"Turn")) -> -0.4722186 | F48: =IF(G13="","",IF(ABS(F13+G13)=ABS(F13)+ABS(G13),IF(F13<0,-1,1)*(F13-G13)/G13,"Turn")) -> 0.0062609466 | G48: =IF(H13="","",IF(ABS(G13+H13)=ABS(G13)+ABS(H13),IF(G13<0,-1,1)*(G13-H13)/H13,"Turn")) -> 0.22074178 | H48: =IF(I13="","",IF(ABS(H13+I13)=ABS(H13)+ABS(I13),IF(H13<0,-1,1)*(H13-I13)/I13,"Turn")) -> #VALUE! | I48: =IF(J13="","",IF(ABS(I13+J13)=ABS(I13)+ABS(J13),IF(I13<0,-1,1)*(I13-J13)/J13,"Turn")) -> #VALUE! | J48: =IF(K13="","",IF(ABS(J13+K13)=ABS(J13)+ABS(K13),IF(J13<0,-1,1)*(J13-K13)/K13,"Turn")) | K48: =IF(L13="","",IF(ABS(K13+L13)=ABS(K13)+ABS(L13),IF(K13<0,-1,1)*(K13-L13)/L13,"Turn")) | L48: =IF(M13="","",IF(ABS(L13+M13)=ABS(L13)+ABS(M13),IF(L13<0,-1,1)*(L13-M13)/M13,"Turn")) | ... O48: =IF(P13="","",IF(ABS(O13+P13)=ABS(O13)+ABS(P13),IF(O13<0,-1,1)*(O13-P13)/P13,"Turn"))
B50: Balance Sheet
B51: Total Assets | E51: =IF(E55="","",E55+E54) -> 16854064 | F51: =IF(F55="","",F55+F54) -> 14687373 | G51: =IF(G55="","",G55+G54) -> 15987114 | H51: =IF(H55="","",H55+H54) -> 14270996 | I51: =IF(I55="","",I55+I54) | J51: =IF(J55="","",J55+J54) | K51: =IF(K55="","",K55+K54) | L51: =IF(L55="","",L55+L54) | ... O51: =IF(O55="","",O55+O54)
B52: ST AR | E52: =Fin_Analysis!C13 -> 265773 | F52: =IF(Inputs!D23="","",Inputs!D23) -> 213823 | G52: =IF(Inputs!E23="","",Inputs!E23) -> 187711 | H52: =IF(Inputs!F23="","",Inputs!F23) -> 277338 | I52: =IF(Inputs!G23="","",Inputs!G23) | J52: =IF(Inputs!H23="","",Inputs!H23) | K52: =IF(Inputs!I23="","",Inputs!I23) | L52: =IF(Inputs!J23="","",Inputs!J23) | M52: =IF(Inputs!K23="","",Inputs!K23) | ... O52: =IF(Inputs!M23="","",Inputs!M23)
B53: ST Inventory | E53: =Fin_Analysis!C18 -> 9672256 | F53: =IF(Inputs!D24="","",Inputs!D24) -> 8852611 | G53: =IF(Inputs!E24="","",Inputs!E24) -> 8769304 | H53: =IF(Inputs!F24="","",Inputs!F24) -> 7321614 | I53: =IF(Inputs!G24="","",Inputs!G24) | J53: =IF(Inputs!H24="","",Inputs!H24) | K53: =IF(Inputs!I24="","",Inputs!I24) | L53: =IF(Inputs!J24="","",Inputs!J24) | M53: =IF(Inputs!K24="","",Inputs!K24) | ... O53: =IF(Inputs!M24="","",Inputs!M24)
B54: Total Liabilities | E54: =Inputs!C21 -> 3990166 | F54: =IF(Inputs!D21="","",Inputs!D21) -> 2466431 | G54: =IF(Inputs!E21="","",Inputs!E21) -> 3908586 | H54: =IF(Inputs!F21="","",Inputs!F21) -> 2946772 | I54: =IF(Inputs!G21="","",Inputs!G21) | J54: =IF(Inputs!H21="","",Inputs!H21) | K54: =IF(Inputs!I21="","",Inputs!I21) | L54: =IF(Inputs!J21="","",Inputs!J21) | M54: =IF(Inputs!K21="","",Inputs!K21) | ... O54: =IF(Inputs!M21="","",Inputs!M21)
B55: Total Equity | E55: =Inputs!C22 -> 12863898 | F55: =IF(Inputs!D22="","",Inputs!D22) -> 12220942 | G55: =IF(Inputs!E22="","",Inputs!E22) -> 12078528 | H55: =IF(Inputs!F22="","",Inputs!F22) -> 11324224 | I55: =IF(Inputs!G22="","",Inputs!G22) | J55: =IF(Inputs!H22="","",Inputs!H22) | K55: =IF(Inputs!I22="","",Inputs!I22) | L55: =IF(Inputs!J22="","",Inputs!J22) | M55: =IF(Inputs!K22="","",Inputs!K22) | ... O55: =IF(Inputs!M22="","",Inputs!M22)
B57: % Sales | E57: # In general, the higher the accounts receivable, the higher the inventory, and the lower the fixed assets, the lower the asset turnover ratio.
B58: ST_AR / Sales | E58: =IF(E52="","",E52/E4) -> 0.017341358 | F58: =IF(F52="","",F52/F4) -> 0.017851543 | G58: =IF(G52="","",G52/G4) -> 0.015992005 | H58: =IF(H52="","",H52/H4) -> 0.031297542 | I58: =IF(I52="","",I52/I4) | J58: =IF(J52="","",J52/J4) | K58: =IF(K52="","",K52/K4) | L58: =IF(L52="","",L52/L4) | ... O58: =IF(O52="","",O52/O4)
B59: ST_Inventory / Sales | E59: =IF(E53="","",E53/E4) -> 0.6311027 | F59: =IF(F53="","",F53/F4) -> 0.73908218 | G59: =IF(G53="","",G53/G4) -> 0.74709927 | H59: =IF(H53="","",H53/H4) -> 0.82624277 | I59: =IF(I53="","",I53/I4) | J59: =IF(J53="","",J53/J4) | K59: =IF(K53="","",K53/K4) | L59: =IF(L53="","",L53/L4) | ... O59: =IF(O53="","",O53/O4)
B60: ΔWC/Δsales | E60: =IF(F4="","",E16/(E4-F4)) -> 0.18714484 | F60: =IF(G4="","",F16/(F4-G4)) -> 1.4668286 | G60: =IF(H4="","",G16/(G4-H4)) -> 0.36338002 | H60: =IF(I4="","",H16/(H4-I4)) -> 0.34507864 | I60: =IF(J4="","",I16/(I4-J4)) -> #VALUE! | J60: =IF(K4="","",J16/(J4-K4)) | K60: =IF(L4="","",K16/(K4-L4)) | L60: =IF(M4="","",L16/(L4-M4)) | ... N60: =IF(O4="","",N16/(N4-O4)) | O60: =IF(P3="","",O16/(O4-P3))
B62: % Total Assets
B63: Sales/Total_Assets | E63: =IF(E4="","",E4/E51) -> 0.90933332 | F63: =IF(F4="","",F4/F51) -> 0.81551983 | G63: =IF(G4="","",G4/G51) -> 0.734204 | H63: =IF(H4="","",H4/H51) -> 0.62093319 | I63: =IF(I4="","",I4/I51) -> #VALUE! | J63: =IF(J4="","",J4/J51) -> #VALUE! | K63: =IF(K4="","",K4/K51) | L63: =IF(L4="","",L4/L51) | ... O63: =IF(O4="","",O4/O51)
B64: Common_Equity / Total Assets | E64: =IF(E55="","",E55/E51) -> 0.763252 | F64: =IF(F55="","",F55/F51) -> 0.83207133 | G64: =IF(G55="","",G55/G51) -> 0.75551647 | H64: =IF(H55="","",H55/H51) -> 0.79351322 | I64: =IF(I55="","",I55/I51) | J64: =IF(J55="","",J55/J51) | K64: =IF(K55="","",K55/K51) | L64: =IF(L55="","",L55/L51) | ... O64: =IF(O55="","",O55/O51)
B65: Contin. Liabilities / Total Assets | E65: =IF(E55="","",IF(Inputs!C27=0,0,Inputs!C27/E51)) -> 0.064990616 | F65: =IF(F55="","",IF(Inputs!D27=0,0,Inputs!D27/F51)) -> 0.074847149 | G65: =IF(G55="","",IF(Inputs!E27=0,0,Inputs!E27/G51)) -> 0.069289304 | H65: =IF(H55="","",IF(Inputs!F27=0,0,Inputs!F27/H51)) -> 0.078643775 | I65: =IF(I55="","",IF(Inputs!G27=0,0,Inputs!G27/I51)) | J65: =IF(J55="","",IF(Inputs!H27=0,0,Inputs!H27/J51)) | K65: =IF(K55="","",IF(Inputs!I27=0,0,Inputs!I27/K51)) | L65: =IF(L55="","",IF(Inputs!J27=0,0,Inputs!J27/L51)) | ... O65: =IF(O55="","",IF(Inputs!M27=0,0,Inputs!M27/O51))
B67: Leverage Analysis
B68: Pre-tax Profit / Total Debt | E68: =IF(OR(E35="",#REF!=""),"",IF(#REF!<=0,"-",E35/#REF!)) -> #REF! | F68: =IF(OR(F35="",#REF!=""),"",IF(#REF!<=0,"-",F35/#REF!)) -> #REF! | G68: =IF(OR(G35="",#REF!=""),"",IF(#REF!<=0,"-",G35/#REF!)) -> #REF! | H68: =IF(OR(H35="",#REF!=""),"",IF(#REF!<=0,"-",H35/#REF!)) -> #REF! | I68: =IF(OR(I35="",#REF!=""),"",IF(#REF!<=0,"-",I35/#REF!)) -> #VALUE! | J68: =IF(OR(J35="",#REF!=""),"",IF(#REF!<=0,"-",J35/#REF!)) -> #VALUE! | K68: =IF(OR(K35="",#REF!=""),"",IF(#REF!<=0,"-",K35/#REF!)) -> #REF! | L68: =IF(OR(L35="",#REF!=""),"",IF(#REF!<=0,"-",L35/#REF!)) -> #REF! | ... O68: =IF(OR(O35="",#REF!=""),"",IF(#REF!<=0,"-",O35/#REF!)) -> #REF!
B69: Interest / Pre-tax Profit | E69: =IF(E35="","",IF(MAX(E32,0)<=0,"-",E32/E35)) -> - | F69: =IF(F35="","",IF(MAX(F32,0)<=0,"-",F32/F35)) -> - | G69: =IF(G35="","",IF(MAX(G32,0)<=0,"-",G32/G35)) -> - | H69: =IF(H35="","",IF(MAX(H32,0)<=0,"-",H32/H35)) -> - | I69: =IF(I35="","",IF(MAX(I32,0)<=0,"-",I32/I35)) -> #VALUE! | J69: =IF(J35="","",IF(MAX(J32,0)<=0,"-",J32/J35)) -> #VALUE! | K69: =IF(K35="","",IF(MAX(K32,0)<=0,"-",K32/K35)) | L69: =IF(L35="","",IF(MAX(L32,0)<=0,"-",L32/L35)) | ... O69: =IF(O35="","",IF(MAX(O32,0)<=0,"-",O32/O35))
B71: ROE | E71: =IFERROR(IF(E41*E63*(1/E64)=E72,"","Error"),"") | F71: =IFERROR(IF(F41*F63*(1/F64)=F72,"","Error"),"") | G71: =IFERROR(IF(G41*G63*(1/G64)=G72,"","Error"),"") | H71: =IFERROR(IF(H41*H63*(1/H64)=H72,"","Error"),"") | I71: =IFERROR(IF(I41*I63*(1/I64)=I72,"","Error"),"") | J71: =IFERROR(IF(J41*J63*(1/J64)=J72,"","Error"),"") | K71: =IFERROR(IF(K41*K63*(1/K64)=K72,"","Error"),"") | L71: =IFERROR(IF(L41*L63*(1/L64)=L72,"","Error"),"") | ... O71: =IFERROR(IF(O41*O63*(1/O64)=O72,"","Error"),"")
B72: EBIT ROE | E72: =IF(E13="","",E13/(E55-#REF!)) -> #REF! | F72: =IF(F13="","",F13/(F55-#REF!)) -> #REF! | G72: =IF(G13="","",G13/(G55-#REF!)) -> #REF! | H72: =IF(H13="","",H13/(H55-#REF!)) -> #REF! | I72: =IF(I13="","",I13/(I55-#REF!)) -> #VALUE! | J72: =IF(J13="","",J13/(J55-#REF!)) -> #VALUE! | K72: =IF(K13="","",K13/(K55-#REF!)) | L72: =IF(L13="","",L13/(L55-#REF!)) | ... O72: =IF(O13="","",O13/(O55-#REF!))
B73: Pre-tax ROE | E73: =IF(E35="","",E35/(E55-#REF!)) -> #REF! | F73: =IF(F35="","",F35/(F55-#REF!)) -> #REF! | G73: =IF(G35="","",G35/(G55-#REF!)) -> #REF! | H73: =IF(H35="","",H35/(H55-#REF!)) -> #REF! | I73: =IF(I35="","",I35/(I55-#REF!)) -> #VALUE! | J73: =IF(J35="","",J35/(J55-#REF!)) -> #VALUE! | K73: =IF(K35="","",K35/(K55-#REF!)) | L73: =IF(L35="","",L35/(L55-#REF!)) | ... O73: =IF(O35="","",O35/(O55-#REF!))
B75: Company Statement Inputs | G75: CAGR Calculator | H75: Initial Value (PV) | I75: Final Value (FV) | J75: # of Years
B76: Year of the last 10k = | E76: =Inputs!C102 -> 45382 | G76: Inputs = | H76: =J13 -> #VALUE! | I76: =E13 -> 1889395.7 | J76: 6
B77: Unit = | E77: =Inputs!C103 -> 1000 | F77: =Thesis!C13 -> HKD | G77: CAGR = | H77: =(I76/H76)^(1/J76)-1 -> #VALUE!

Sheet Dashboard
B2: Company Info: | G2: =IF(Inputs!C107="","",Inputs!C107) -> HOLD
B4: Market Yields | F4: Notes
B5: US Riskfree | C5: 0.042 | F5: https://fred.stlouisfed.org/series/DGS10
B6: US BBB Bond yield | C6: 0.0523 | D6: HK | F6: https://fred.stlouisfed.org/series/BAMLC0A4CBBBEY
B7: Discount Rate (US) | C7: 0.07 | D7: 0.075
B9: CN Riskfree | C9: 0.0181 | F9: https://tradingeconomics.com/china/government-bond-yield
B10: CN Onshore BBB- Bond yield | C10: 0.065 | F10: https://iftp.chinamoney.com.cn/chinese/scsjzqxx/
B11: CN Offshore BBB- Bond yield | C11: 0.16 | D11: =Inputs!C105 -> HK | F11: https://yield.chinabond.com.cn/cbweb-mn/yield_main?locale=en_US
B12: Discount Rate (CN) | C12: 0.08
B14: ROE & Cost Structure | F14: Target
B15: EBIT ROE | C15: =C16*C17*C18 -> 0.14687583 | F15: Target Return | G15: 0.15 | H15: 4
B16: EBIT Margin | C16: =Data!E41 -> 0.12328072
B17: Asset Turnover Ratio | C17: =Data!E63 -> 0.90933332 | F17: Price Indicators
B18: Leverage Ratio | C18: =1/Data!E64 -> 1.3101833 | F18: PB Ratio | G18: =Thesis!C11/(Data!E55*Data!E77/Common_Shares*Exchange_Rate) -> 0.63074431
B19: Interest Expense | C19: =Fin_Analysis!I81 -> -0.003888565 | F19: Normalized PE Ratio | G19: =Thesis!C11/(Fin_Analysis!H86*Thesis!C14) -> 0.51253012
B20: Normalized ΔWC | C20: =Fin_Analysis!I80 -> 0.025 | F20: Normalized Payout Ratio | G20: =Fin_Analysis!I88 -> 0.040794727
B21: Normalized CAPX-D&A | C21: =Fin_Analysis!I80+Fin_Analysis!I82 -> 0.035 | F21: Normalized D/P | G21: =Fin_Analysis!H88*Exchange_Rate/Thesis!C11 -> 0.07959479
B23: Valuation Output: | C23: Lower | D23: Upper | F23: Mid | G23: Base Case Valuation
B24: Value Range | C24: =IF(Fin_Analysis!C117="Profit",Fin_Analysis!D109,IF(Fin_Analysis!C117="Dividend",Fin_Analysis!D112,Fin_Analysis!D115)) -> 13927.52 | D24: =G24*(1+G15) -> 32020.428 | F24: =IF(Fin_Analysis!C117="Profit",Fin_Analysis!F109,IF(Fin_Analysis!C117="Dividend",Fin_Analysis!F112,Fin_Analysis!F115)) -> 17593.959 | G24: =IF(Fin_Analysis!C117="Profit",Fin_Analysis!I109,IF(Fin_Analysis!C117="Dividend",Fin_Analysis!I112,Fin_Analysis!I115)) -> 27843.851
B26: Earnings Power Checklist
B27: Present
B28: 1. Consumer monopoly? | C28: =Inputs!C85 -> Strongly agree
B29: 2. Conservatively financed? | C29: =IF(AND(OR(Fin_Analysis!I26<0.8,Fin_Analysis!I46<0.6),Data!E68<0.8),"Strongly disagree", IF(AND(OR(Fin_Analysis!I26<1,Fin_Analysis!I46<0.8),Data!E68<1),"unclear", IF(AND(OR(Fin_Analysis!I26<1.4,Fin_Analysis!I46<1.2),Data!E68<1.4),"agree","Strongly agree"))) -> #REF!
B30: Market Yields
B31: 3. Upward earnings trend? | C31: =Inputs!C86 -> unclear
B32: 4. Stable margin and ROE? | C32: =Inputs!C87 -> agree
B33: Future
B34: 5. Can earnings be sustained? | C34: =Inputs!C88 -> agree
B35: 6. No big MCX-D&A required? | C35: =Inputs!C89 -> Strongly agree
B37: Consumer Monopoly Test
B38: If you had access to billions of dollars and your pick of the top fifty managers in the country, could you start a business and successfully compete with the business in question? | C38: =Inputs!C90 -> Consumer Monopoly

Sheet Fin_Analysis
B2: Asset Model Output | K2: Note
B3: Total Equity per books = | D3: =Inputs!C22 -> 12863898 | E3: =IF((C49-I49)=D3,"", "Error!") | H3: Common Equity = | I3: =D3-D4 -> 12890860
B4: Non-common Interest = | D4: =Inputs!C70 -> -26962
E5: Discount | H5: Book Current Ratio | I5: =C28/I28 -> 3.5066755
B6: ="Adj. Net Asset in "&Thesis!C13 -> Adj. Net Asset in HKD | D6: =(E49-I49-E53) -> 3511699.1 | E6: =1-D6/D3 -> 0.72701128 | H6: Book Quick Ratio | I6: =(C24+C25)/I28 -> 0.74800394
B7: ="Adj. Net Asset per Shares in "&Thesis!D11 -> Adj. Net Asset per Shares in HKD | D7: =MAX((D6*Exchange_Rate*Data!E77)/Common_Shares, 0) -> 5.9813526 | E7: =Thesis!D11 -> HKD | H7: Book Cash Ratio | I7: =C24/I28 -> 0.64376314
B9: Most Recent Quarter Inputs | D9: =Inputs!C104 -> 45382 | E9: =IF(MONTH(D9)=MONTH(Data!E76),"FY","Quarter") -> FY
B10: Assets | C10: Book Figure | D10: Valued @ | E10: Ajusted Valuation | F10: is_OP | H10: Liabilities | I10: Book Figure
B11: Cash and cash equivalents | C11: =Inputs!C32 -> 1998219 | D11: =Inputs!D32 -> 0.9 | E11: =C11*D11 -> 1798397.1 | H11: ST Borrowing | I11: =Inputs!C57 -> 1427805
B12: Restricted cash | C12: =Inputs!C33 -> 0 | D12: =Inputs!D33 -> 0.8 | E12: =C12*D12 -> 0 | H12: ST Lease liabilities | I12: =Inputs!C58 -> 287697
B13: ST AR | C13: =Inputs!C34 -> 265773 | D13: =Inputs!D34 -> 0.6 | E13: =C13*D13 -> 159463.8 | H13: ST SH Loan | I13: =Inputs!C59 -> 0
B14: ST FV Investments | C14: =Inputs!C35 -> 0 | D14: =Inputs!D35 -> 0.6 | E14: =C14*D14 -> 0 | H14: ST Financial Liabilities | I14: =Inputs!C60 -> 0
B15: ST non-FV Investments | C15: =Inputs!C36 -> 0 | D15: =Inputs!D36 -> 0.5 | E15: =C15*D15 -> 0 | H15: ST Debt | I15: =SUM(I11:I14) -> 1715502
B16: Operating ST Financial Assets | C16: =Inputs!C37 -> 0 | D16: =Inputs!D37 -> 0.6 | E16: =C16*D16 -> 0
B17: Prepayments and Contract Assets | C17: =Inputs!C38 -> 366595 | D17: =Inputs!D38 -> 0.1 | E17: =C17*D17 -> 36659.5
B18: Inventory | C18: =Inputs!C39 -> 9672256 | D18: =Inputs!D39 -> 0.5 | E18: =C18*D18 -> 4836128
B19: Properties held for sale | C19: =Inputs!C40 -> 0 | D19: =Inputs!D40 -> 0.6 | E19: =C19*D19 -> 0 | F19: =Inputs!E40 -> N | G19: =IF(F19="Y",0,1) -> 1
B20: Properties under development | C20: =Inputs!C41 -> 0 | D20: =Inputs!D41 -> 0.6 | E20: =C20*D20 -> 0 | F20: =Inputs!E41 -> Y | G20: =IF(F20="Y",0,1) -> 0
B21: ST DTA | C21: =Inputs!C42 -> 29465 | D21: =Inputs!D42 -> 0.9 | E21: =C21*D21 -> 26518.5
B22: Other ST Assets | C22: =Inputs!C43 -> 0 | D22: =Inputs!D43 -> 0.05 | E22: =C22*D22 -> 0 | H22: Other ST liabilities | I22: =I28-SUM(I11:I14) -> 1801307
F23: %
B24: ST Core-Monetary Asset | C24: =SUM(C11:C14) -> 2263992 | D24: =IF(E24=0,0,E24/C24) -> 0.86478261 | E24: =SUM(E11:E14) -> 1957860.9 | F24: =E24/$E$28 -> 0.28552038
B25: ST Noncore-Monetary Asset | C25: =SUM(C15:C17) -> 366595 | D25: =IF(E25=0,0,E25/C25) -> 0.1 | E25: =SUM(E15:E17) -> 36659.5 | F25: =E25/$E$28 -> 0.0053461583 | H25: ST Current Ratio | I25: =E28/I28 -> 1.9498264
B26: ST Tangible Assets | C26: =C18+C19+C20 -> 9672256 | D26: =IF(E26=0,0,E26/C26) -> 0.5 | E26: =E18+E19+E20 -> 4836128 | F26: =E26/$E$28 -> 0.70526619 | H26: ST Cash-debt Ratio | I26: =E24/($I$28-I22) -> 1.1412758 | J26: =IF(I26<1,"Liquidity Problem!","")
B27: ST Non-tangible Assets | C27: =C21+C22 -> 29465 | D27: =IF(E27=0,0,E27/C27) -> 0.9 | E27: =E21+E22 -> 26518.5 | F27: =E27/$E$28 -> 0.0038672677 | H27: ST Quick Ratio | I27: =(E25+E24)/$I$28 -> 0.56713924 | J27: =IF(OR(I27<0.75,C28<I28),"Liquidity Issue!","") -> Liquidity Issue!
B28: Current Assets | C28: =SUM(C11:C22) -> 12332308 | D28: =E28/C28 -> 0.55603273 | E28: =SUM(E24:E27) -> 6857166.9 | H28: Current Liabilities | I28: =Inputs!C61 -> 3516809 | J28: =IF(J26="",1,0)+IF(J27="",1,0)+IF(J46="",1,0)+IF(J47="",1,0) -> 2
F29: is_OP
B30: LT Depositis | C30: =Inputs!C44 -> 0 | D30: =Inputs!D44 -> 0.8 | E30: 0 | H30: LT Borrowing | I30: =Inputs!C62 -> 0
B31: LT FV Securities | C31: =Inputs!C45 -> 0 | D31: =Inputs!D45 -> 0.6 | E31: =C31*D31 -> 0 | H31: LT Lease liabilities | I31: =Inputs!C63 -> 319420
B32: LT non-FV Securities | C32: =Inputs!C46 -> 0 | D32: =Inputs!D46 -> 0.5 | E32: =C32*D32 -> 0 | H32: LT SH Loan | I32: =Inputs!C64 -> 0
B33: Operating LT Financial Assets | C33: =Inputs!C47 -> 0 | D33: =Inputs!D47 -> 0.5 | E33: =C33*D33 -> 0 | G33: =IF(F33="Y",0,1) -> 1 | H33: LT Financial Liabilities | I33: =Inputs!C65 -> 0
B34: LT AR | C34: =Inputs!C48 -> 103050 | D34: =Inputs!D48 -> 0.4 | E34: =C34*D34 -> 41220 | H34: LT Debt | I34: =SUM(I30:I33) -> 319420
B35: Investments in JV or associate | C35: =Inputs!C49 -> 0 | D35: =Inputs!D49 -> 0.1 | E35: =C35*D35 -> 0 | F35: =Inputs!E49 -> N | G35: =IF(F35="Y",0,1) -> 1
B36: Investment property | C36: =Inputs!C50 -> 925726 | D36: =Inputs!D50 -> 0.2 | E36: =C36*D36 -> 185145.2 | F36: =Inputs!E50 -> N | G36: =IF(F36="Y",0,1) -> 1
B37: Properties under development | C37: =Inputs!C51 -> 0 | D37: =Inputs!D51 -> 0.1 | E37: =C37*D37 -> 0 | F37: =Inputs!E51 -> Y | G37: =IF(F37="Y",0,1) -> 0
B38: PP&E & Right of Use Assets | C38: =Inputs!C52 -> 2522337 | D38: =Inputs!D52 -> 0.1 | E38: =C38*D38 -> 252233.7
B39: Biological assets | C39: =Inputs!C53 -> 0 | D39: =Inputs!D53 -> 0.05 | E39: =C39*D39 -> 0
B40: Intangible assets | C40: =Inputs!C54 -> 538321 | D40: =Inputs!D54 -> 0.05 | E40: =C40*D40 -> 26916.05
B41: LT DTA | C41: =Inputs!C55 -> 154648 | D41: =Inputs!D55 -> 0.9 | E41: =C41*D41 -> 139183.2
B42: Other assets & Goodwill | C42: =Inputs!C56 -> 277674 | D42: =Inputs!D56 -> 0 | E42: =C42*D42 -> 0 | H42: Other LT liabilities | I42: =I48-SUM(I30:I33) -> 153937
B44: LT Core-Monetary Asset | C44: =SUM(C30:C31) -> 0 | D44: =IF(E44=0,0,E44/C44) -> 0 | E44: =SUM(E30:E31) -> 0
B45: LT Noncore-Monetary Asset | C45: =SUM(C32:C35) -> 103050 | D45: =IF(E45=0,0,E45/C45) -> 0.4 | E45: =SUM(E32:E35) -> 41220
B46: LT Tangible Assets | C46: =C36+C37+C38+C39 -> 3448063 | D46: =IF(E46=0,0,E46/C46) -> 0.12684771 | E46: =E36+E37+E38+E39 -> 437378.9 | H46: LT Cash-debt Ratio | I46: =(E44+E24)/E64 -> 0.96213069 | J46: =IF(I46<1,"Liquidity Problem!","") -> Liquidity Problem!
B47: LT Non-tangible Assets | C47: =C40+C41+C42 -> 970643 | D47: =IF(E47=0,0,E47/C47) -> 0.17112291 | E47: =E40+E41+E42 -> 166099.25 | H47: LT Quick Ratio | I47: =(E44+E45+E24+E25)/$I$49 -> 0.5101894 | J47: =IF(OR(I47<0.5,C49<I49),"Liquidity Issue!","")
B48: Noncurrent Assets | C48: =SUM(C30:C42) -> 4521756 | D48: =E48/C48 -> 0.14257694 | E48: =SUM(E30:E42) -> 644698.15 | H48: Noncurrent Liabilities | I48: =I49-I28 -> 473357
B49: Total Assets | C49: =Inputs!C22+Inputs!C21 -> 16854064 | D49: =E49/C49 -> 0.44510719 | E49: =E28+E48 -> 7501865.1 | H49: Total Liabilities | I49: =Inputs!C21 -> 3990166
B51: Balance Sheet items Adjustments
B52: 1. MV of Noncommon Interest | D52: =IF(E53=D4,"BV of the MI","P/B Approach") -> P/B Approach | K52: Note
B53: Noncommon Interest | C53: =MAX(D4,0) -> 0 | D53: =IF(E53=0, 0,E53/C53) -> 0 | E53: =IF(C53=0,0,MAX(C53,C53*Dashboard!G18)) -> 0
B55: 2. Total Debt + PS + Options
B56: + Interest Bearing Debt | D56: =I15+I34 -> 2034922
B57: + MV of the Options | D57: =Inputs!C66 -> 0 | K57: // If avg exercise price > current price, then assume 0
B58: + Preference Shares | D58: =Inputs!C67 -> 0
B60: 3. Non-operating Assets | D60: Value @ | H60: Nonop Assets Valuation
B61: Non-operating Assets | C61: =C14+C15+(C19*G19)+(C20*G20)+C31+C32+(C35*G35)+(C36*G36)+(C37*G37) -> 925726 | D61: =IF(E61=0,0,E61/C61) -> 0.2 | E61: =E14+E15+(E19*G19)+(E20*G20)+E31+E32+(E35*G35)+(E36*G36)+(E37*G37) -> 185145.2 | H61: Nonop Assets per share | I61: =C108*Data!$E$77/Common_Shares -> -0.087513223
B62: Non-operating Cash | C62: =C11+C30 -> 1998219 | D62: =IF(E62=0,0,E62/C62) -> 0.9 | E62: =E11+E30 -> 1798397.1 | H62: Reinvest Nonop @ | I62: =IF(OR(C101="CN",C101="HK"),Dashboard!C9,Dashboard!C5) -> 0.0181
B63: Non-operating Assets | C63: =C61+C62 -> 2923945 | D63: =IF(E63=0,0,E63/C63) -> 0.6783788 | E63: =E61+E62 -> 1983542.3 | H63: Net Nonop Assets FV | I63: =IF(I61>0,FV(I62,D102,0,-I61),I61) -> -0.087513223
B64: - (Total Debt + PS + Options) | E64: =D56+D57+D58 -> 2034922 | H64: Net Nonop Assets PV | I64: =IF(I61>0,PV(C103,D102,0,-I63),I61) -> -0.087513223
B65: Net Non-operating Assets | C65: =C63-E64 -> 889023 | D65: =IF(E65=0,0,E65/C65) -> -0.057793443 | E65: =E63-E64 -> -51379.7
B67: 4. Operating Assets | D67: Value @
B68: Operating Assets | C68: =C49-C63 -> 13930119 | D68: =IF(E68=0,0,E68/C68) -> 0.39614326 | E68: =E49-E63 -> 5518322.8
B69: - Non-intreset-bearing Debt | E69: =I49-E64 -> 1955244
B70: Net Operating Assets | C70: =C68-E69 -> 11974875 | D70: =IF(E70=0,0,E70/C70) -> 0.29754622 | E70: =E68-E69 -> 3563078.8
B72: Normalized FCFE Analysis | C72: =Data!E1 -> 45382 | E72: Pessimistic Case | H72: Base Case | K72: Note
B73: ="(Numbers in "&Data!E77&Thesis!C13&")" -> (Numbers in 1000HKD) | C73: Base Year | E73: Normalized Year | H73: Normalized Year
B74: Sales | C74: =Data!E4 -> 15325962 | E74: =Inputs!E75 -> 12260770 | H74: =Inputs!F75 -> 13793366
B75: - COGS | C75: =Data!E5 -> -11151623 | D75: =C75/$C$74 -> -0.72762956 | E75: =Inputs!E76 -> -8921298.4 | F75: =E75/E74 -> -0.72762956 | H75: =Inputs!F76 -> -10036461 | I75: =H75/$H$74 -> -0.72762956
B76: Gross profit = | C76: =C74-C75 -> 26477585 | E76: =E74-E75 -> 21182068 | H76: =H74-H75 -> 23829826
B77: - (OPEX + R&D) = | C77: =Data!E10+MAX(Data!E11,0) -> -254107 | E77: =Inputs!E77 -> 2027931.3 | F77: =E77/E74 -> 0.1654 | H77: =Inputs!F77 -> 2281422.7 | I77: =H77/$H$74 -> 0.1654
B78: - Non-controling Interests | C78: =MAX(Data!E12,0) -> 12622.667 | D78: =C78/$C$74 -> 0.00082361333 | E78: =E74*F78 -> 10098.133 | F78: =I78 -> 0.00082361333 | H78: =Inputs!F81 -> 11360.4 | I78: =H78/$H$74 -> 0.00082361333
B79: EBIT = | C79: =C76-C77-C78 -> 26719069 | D79: =C79/C74 -> 1.7433861 | E79: =E76-E77-E78 -> 19144039 | F79: =E79/E74 -> 1.5614059 | H79: =H76-H77-H78 -> 21537043 | I79: =H79/H74 -> 1.5614059
B80: - ΔWC | C80: =MAX(Data!E16,0) -> 626583 | D80: =C80/$C$74 -> 0.040883763 | E80: =E74*F80 -> 306519.24 | F80: =I80 -> 0.025 | H80: =Inputs!F80 -> 344834.15 | I80: =H80/$H$74 -> 0.025 | K80: https://pages.stern.nyu.edu/~adamodar/New_Home_Page/datafile/wcdata.html
B81: - Interest Expense | C81: =MAX(Data!E32,0) -> 0 | D81: =C81/$C$74 -> 0 | E81: =E74*F81 -> -47676.8 | F81: =I81 -> -0.003888565 | H81: =Inputs!F78 -> -53636.4 | I81: =H81/$H$74 -> -0.003888565
B82: - (CAPX - D&A) | C82: =ABS(MAX(Data!E34,0)-MAX(Data!E33,0)) -> 183842 | D82: =C82/$C$74 -> 0.011995462 | E82: =Inputs!E79 -> 122607.7 | F82: =E82/E74 -> 0.01 | H82: =Inputs!F79 -> 137933.66 | I82: =H82/$H$74 -> 0.01
B83: Pre-tax Profit = | C83: =C79-C81-C82-C80 -> 25908644 | D83: =C83/$C$74 -> 1.6905069 | E83: =E79-E81-E82-E80 -> 18762588 | F83: =E83/E74 -> 1.5302945 | H83: =H79-H81-H82-H80 -> 21107912 | I83: =H83/$H$74 -> 1.5302945
B84: Tax Rate | D84: =I84 -> 0.25 | F84: =I84 -> 0.25 | I84: =Inputs!C106 -> 0.25
B85: After-tax Profit = | C85: =C83*(1-I84) -> 19431483 | D85: =C85/$C$74 -> 1.2678802 | E85: =E83*(1-F84) -> 14071941 | F85: =E85/E74 -> 1.1477209 | H85: =H83*(1-I84) -> 15830934 | I85: =H85/$H$74 -> 1.1477209
B86: EPS | C86: =C85*Data!E77/Common_Shares -> 33.096957 | E86: =E85*Data!E77/Common_Shares -> 23.968239 | H86: =H85*Data!E77/Common_Shares -> 26.964269
B87: E/P Initial Rate of Retrun | C87: =C86*Exchange_Rate/Thesis!C11 -> 2.3948594 | E87: =E86*Exchange_Rate/Thesis!C11 -> 1.7343154 | H87: =H86*Exchange_Rate/Thesis!C11 -> 1.9511048
B88: Dividend per share | C88: =Inputs!C28 -> 1.36 | D88: =C88/C86 -> 0.041091391 | E88: =Inputs!E82 -> 1 | F88: =E88/E86 -> 0.04172188 | H88: =Inputs!F82 -> 1.1 | I88: =H88/H86 -> 0.040794727
B89: D/P Dividend Yield | C89: =C88*Exchange_Rate/Thesis!C11 -> 0.098408104 | E89: =E88*Exchange_Rate/Thesis!C11 -> 0.0723589 | H89: =H88*Exchange_Rate/Thesis!C11 -> 0.07959479
B91: % of Revenue
B92: COGS | C92: =C75/C74 -> -0.72762956
B93: Gross Proift | C93: =C76/C74 -> 1.7276296
B94: OPEX + R&D | C94: =C77/$C$74 -> -0.016580166
B95: Non-controling Interests
B100: ="Valuation Drivers in "&Thesis!D11 -> Valuation Drivers in HKD | K100: Note:
B101: External Drivers | C101: =Inputs!C105 -> HK | D101: Internal Drivers | E101: Pessimistic Case | H101: Base Case
B102: =C101&" Discount Rate" -> HK Discount Rate | C102: =IF(C101="CN",Dashboard!C12,IF(C101="US",Dashboard!C7,IF(C101="HK",Dashboard!D7,Dashboard!D12))) -> 0.075 | D102: =Dashboard!H15 -> 4 | E102: E/P Future Value is | F102: =FV(E87,D102,0,-(E86/(C102-D103)))*Exchange_Rate -> 24359.473 | H102: E/P Future Value is | I102: =FV(H87,D102,0,-(H86/(C102-D103)))*Exchange_Rate -> 37184.72
B103: Target Return | C103: =Dashboard!G15 -> 0.15 | D103: =Inputs!D68 -> 0.02 | E103: D/P Future Value is | F103: =FV(E89,D102,0,-(E88/(C102-D103)))*Exchange_Rate -> 24.043515 | H103: D/P Future Value is | I103: =FV(H89,D102,0,-(H88/(C102-D103)))*Exchange_Rate -> 27.168966
B105: ="Valuation in "&Thesis!D11 -> Valuation in HKD | C105: =Thesis!D11 -> HKD | D105: Lower | E105: =E72 -> Pessimistic Case | F105: Mid | H105: =H72 -> Base Case | I105: Valuation
B106: Operating Equity Valuation | C106: =H106*Common_Shares/Data!E77 -> 1.2482197e+10 | E106: =PV(C103,D102,0,-F102) -> 13927.608 | H106: =PV(C103,D102,0,-I102) -> 21260.485 | I106: =PV(C102,D102,0,-I102) -> 27843.938
B107: - Noncommon Interest | C107: =-E53*Exchange_Rate -> 0 | H107: =C107*Data!$E$77/Common_Shares -> 0
B108: + Net Non-Operating Valuation | C108: =(E65+IF(E70<0,E70,0))*Exchange_Rate -> -51379.7 | E108: =IF(H108>0,I64,H108) -> -0.087513223 | H108: =I64 -> -0.087513223
B109: Valuation | D109: =MIN(F109*(1-C103),E109) -> 13927.52 | E109: =MAX(E106+H107+E108,0) -> 13927.52 | F109: =(E109+H109)/2 -> 17593.959 | H109: =MAX(H106+H107+H108,0) -> 21260.397 | I109: =MAX(I106+H107+H108,0) -> 27843.851
B111: Dividend method | D111: Lower | E111: =E105 -> Pessimistic Case | F111: Mid | H111: =H105 -> Base Case | I111: Valuation
B112: Operating Equity Valuation | D112: =MIN(F112*(1-C103),E112) -> 12.444383 | E112: =PV(C103,D102,0,-F103) -> 13.746958 | F112: =(E112+H112)/2 -> 14.640451 | H112: =PV(C103,D102,0,-I103) -> 15.533945 | I112: =PV(C102,D102,0,-I103) -> 20.344136
B114: Avg of E and D method | D114: Lower | E114: =E105 -> Pessimistic Case | F114: Mid | H114: =H105 -> Base Case | I114: Valuation
B115: Avg Valuation | D115: =(D109+D112)/2 -> 6969.9823 | E115: =(E109+E112)/2 -> 6970.6336 | F115: =(F109+F112)/2 -> 8804.2995 | H115: =(H109+H112)/2 -> 10637.965 | I115: =(I109+I112)/2 -> 13932.097
B117: Selecting the Valuation method | C117: =Inputs!C68 -> Profit
