Workbook
Name Common_Shares: Thesis!$C$9
Name dividend_tax_rate: Normalized_FCF!$C$91
Name Equity_Cost: Thesis!$C$101
Name Exchange_Rate: Thesis!$E$16
Name FV_adjustments: DCF!$F$7
Name Holding_Period: Thesis!$E$21
Name Market_currency: Thesis!$C$7
Name Market_Price: Thesis!$C$8
Name Reporting_currency: Thesis!$E$17
Name scaling_factor: Data!$C$3
Name Terminal_Growth: Thesis!$C$17

Sheet Thesis
A2: Executive Summary
E3: Last Updated: | F3: 45930
B4: Company: | C4: 首钢资源 | E4: Portfolio: | F4: INT
B5: Symbol: | C5: 0639.HK | E5: Selected: | F5: Y
B6: Comp_Sector: | C6: MAT_01
B7: Market Currency: | C7: HKD
B8: Market Price: | C8: 3.16
B9: Number of Shares: | C9: 5091065770
B10: Market Capitalization: | C10: =Thesis!C8*Common_Shares/1000000 -> 16087.768 | D10: Implied Annual Return: | E10: =Scenarios!F34 -> 0.17337144
B12: Guidance Note: This model evaluates the company using a structured investment process to determine its intrinsic value and target prices. It focuses on sustainable FCF capacity, adjusts for financial structure, incorporates growth scenarios, and calculates expected returns based on the derived intrinsic value.
B14: =Scenarios!B39&" Valuation Conclusion" -> 1-stage DCF Valuation Conclusion
B15: Business Model Risk Premium: | C15: N | D15: Forex Symbol: | E15: =IF(E17=C7,C7,E17&"/"&C7) -> HKD
B16: Management Risk Premium: | C16: N | D16: Exchange Rate: | E16: 1
B17: Terminal Growth Rate (g) | C17: 0 | D17: Reporting Currency: | E17: HKD
B18: ="Expected Equity Value ("&C7&") :" -> Expected Equity Value (HKD) : | C18: =C125 -> 4.1464286 | D18: Report Interval: | E18: 6
B19: Growth Classification: | C19: =IF(Scenarios!C50="Y",Scenarios!B50,"")&IF(Scenarios!C51="Y",Scenarios!B51,"")&IF(Scenarios!C52="Y",Scenarios!B52,"")&" "&IF(Scenarios!C53="Y",Scenarios!B53,"") -> Negative Growth | D19: Update Required After: | E19: =EOMONTH(EDATE(BS!C1,E18+2),0) -> 46081
B21: Price Targets | C21: =C138&" ("&Market_currency&")" -> (HKD) | D21: Holding Period | E21: 3
B22: Target Price | C22: =E140 -> 2.4048565 | D22: @Target return | E22: 0.29465259
B23: Entry Price | C23: =E141 -> 2.9631301 | D23: @Entry yield | E23: 0.20075184
B24: Exit Price | C24: =E144 -> 3.6233986 | D24: @Benchmark yield | E24: 0.1174
B25: Sell Price | C25: =E145 -> 4.0664479 | D25: @Base equity cost | E25: 0.0725
A27: Step 1: Establishing the Company’s Sustainable Earning Power (Calculating Normalized FCFE)
B29: Goal: To quantify the underlying FCFE the business consistently generates, stripping away temporary fluctuations or accounting choices.
B30: FCFE = (Normalized Operating EBIT + Depreciation & Amortization – Capital Expenditures) + Stable Non-Operating EBIT + Net Interest Income – Taxes – NCI’s Share of Profits – Working Capital Investment
B32: Key Components | C32: =scaling_factor -> 1000
B33: • Normalized Operating EBIT: Earnings before interest and taxes from core business operations, adjusted to remove one-time or irregular items for a sustainable earnings base.
B34: Normalized Operating EBIT = | C34: =Normalized_FCF!C8 -> 1900909.5 | D34: =Reporting_currency -> HKD
B36: • Depreciation & Amortization (D&A): Non-cash expenses added back to reflect cash generated from operations. • Capital Expenditures (Capex): Cash outflows required to maintain or expand operational assets
B37: D&A = | C37: =Normalized_FCF!C15 -> 0 | D37: =Reporting_currency -> HKD
B38: Capex = | C38: =Normalized_FCF!C16 -> 0 | D38: =Reporting_currency -> HKD
B40: • Stable Non-Operating EBIT: Consistent earnings from non-core assets, such as fixed-income investments, dividend-paying stocks, or rental properties.
B41: Stable Non-Operating EBIT = | C41: =Normalized_FCF!C9 -> 0 | D41: =Reporting_currency -> HKD
B43: • Net Interest Income: Interest income minus interest expense
B44: Operating Interest Income = | C44: =Normalized_FCF!C46 -> 12533.131 | D44: =Reporting_currency -> HKD
B45: Interest Expense = | C45: =Normalized_FCF!C45 -> -2620.62 | D45: =Reporting_currency -> HKD
B46: Net Interest Income = | C46: =Normalized_FCF!C10 -> 9912.5106 | D46: =Reporting_currency -> HKD
B48: • NCI’s Share of Profits: NCI represents the portion of a subsidiary’s equity not owned by the parent company.
B49: Est. NCI’s Share of Profits = | C49: =Normalized_FCF!C13 -> -335976.4 | D49: =Reporting_currency -> HKD
B51: • Taxes: Tax = (Normalized Operating EBIT + Stable Non-Operating EBIT + Interest Income – Interest Expense) × Tax Rate
B52: Taxes = | C52: =Normalized_FCF!C12 -> -477705.51 | D52: =Reporting_currency -> HKD
B54: • Working Capital Investment (WCInv): WCInv is only included if it materially distorts FCFE.
B55: WCInv = | C55: =Normalized_FCF!C17 -> 0 | D55: =Reporting_currency -> HKD
B57: Note on Net Borrowing: In theory, principal repayments are accounted for through Net Borrowing. However, this model aims to avoid explicitly forecasting debt issuance or repayments. Instead, principal repayments are reflected in the Equity Value adjustment through interest-bearing debt.
B58: Insight: This step ensures a comprehensive measure of cash flow by incorporating both operating and stable non-operating sources while accounting for taxes and reinvestment needs.
B60: Latest FCFE = | C60: =Normalized_FCF!G19 -> 1274305 | D60: =Reporting_currency -> HKD
B61: Normalized FCFE = | C61: =Normalized_FCF!C19 -> 1097140.1 | D61: =Reporting_currency -> HKD
B62: Normalized FCFE/Market Cap = | C62: =Normalized_FCF!C124 -> 0.068197163
B63: After tax Dividend/Market Cap = | C63: =Normalized_FCF!C92 -> 0.085443038 | E63: Payout Ratio: | F63: =Normalized_FCF!C90 -> 1.3920918
B65: DuPont Analysis | C65: Normalized | D65: Latest
B66: ROE = | C66: =Normalized_FCF!C119 -> 0.10109497 | D66: =Normalized_FCF!G119 -> 0.12200966
B67: =Normalized_FCF!B116 -> Pre-tax Profit/Sales | C67: =Normalized_FCF!C116 -> 0.41984093 | D67: =Normalized_FCF!G116 -> 0.45602847
B68: =Normalized_FCF!B117 -> Sales/Total Assets | C68: =Normalized_FCF!C117 -> 0.1983239 | D68: =Normalized_FCF!G117 -> 0.22035989
B69: =Normalized_FCF!B118 -> Total Assets/Equity | C69: =Normalized_FCF!C118 -> 1.2141427 | D69: =Normalized_FCF!G118 -> 1.2141427
A71: Step 2: Fair Value adjustments
B73: Goal: Determine the FV adjustments needed to derive the equity value, considering the capital structure.
B74: FV adjustmets = Non-Operating Cash + Other Non-Operating Assets – Total Interest-Bearing Debt
B76: Key Components
B77: Note on debt: The total interest-bearing debt captures the principal repayments. Ideally, this amount should be discounted based on the repayment schedule. However, for simplicity and conservatism, this model uses the book value of the total interest-bearing debt.
B78: Total Interest-Bearing Debt = | C78: =DCF!F4 -> -43677 | D78: =Reporting_currency -> HKD
B79: Total Interest-Bearing Debt per share = | C79: =C78*scaling_factor*Exchange_Rate/Common_Shares -> -0.0085791467 | D79: =Market_currency -> HKD
B80: Debt to Equity Ratio = | C80: =IF(BS!G31/BS!G27>300%,"nm",BS!G31/BS!G27) -> 0.0023107987
B81: Debt to EBIT Ratio = | C81: =IF(BS!C50>30,"nm",BS!C50) -> 0.022976896
B83: • Non-Operating Cash: Excess cash not required for operations
B84: Est. Non-Operating Cash = | C84: =DCF!F5 -> 8029573.9 | D84: =Reporting_currency -> HKD
B85: Total Cash = | C85: =BS!C66 -> 10118429 | D85: =Reporting_currency -> HKD
B86: Est. Non-Operating Cash per share = | C86: =C84*scaling_factor*Exchange_Rate/Common_Shares -> 1.5771892 | D86: =Market_currency -> HKD
B88: • Other Non-Operating Assets: Assets not contributing to FCFE (e.g., non-income-generating investments or properties)
B89: Other Non-Operating Assets = | C89: =DCF!F6 -> 263512.2 | D89: =Reporting_currency -> HKD
B90: Other Non-Operating Assets per share = | C90: =C89*scaling_factor*Exchange_Rate/Common_Shares -> 0.051759732 | D90: =Market_currency -> HKD
B92: FV adjustments per share = | C92: =DCF!F8 -> 1.6203698 | D92: =Market_currency -> HKD
A94: Step 3: Values from No-Growth Model and Growth Model
B96: Goal: Calculate the intrinsic value under the assumption that normalized FCFE remains steady, considering both zero-growth and growth scenarios.
B97: Enterprise Value = Normalized FCFE / (Cost of Equity - Terminal Growth Rate)
B98: Equity Value = Enterprise Value - FV adjustment
B100: Key Components
B101: Cost of Equity = | C101: =E25+C103 -> 0.0725
B102: Base Cost of Equity | C102: =E25 -> 0.0725
B103: Risk Premium | C103: =IF(C15="Y",1%,0)+IF(C16="Y",1%,0) -> 0
B104: Terminal Growth Rate (g) = | C104: =Terminal_Growth -> 0
B106: Note:
B107: Cost of Equity: Cost of Equity reflects the company’s risk profile and represents the minimum return the investor requires for taking on the general risk of owning this type of business, while the target annual return serves as the investor’s hurdle rate.
B108: Terminal Growth Rate: Setting g=0% is a conservative assumption, valuing the company based only on its current demonstrated earning power without relying on potentially optimistic future growth projections.
B110: a. From No-Growth Model
B111: Est. (Net Asset) Realizable Value = | C111: =BS!D47 -> 0.79833937 | D111: =Market_currency -> HKD
B112: No Growth Equity Value per share = | C112: =DCF!C11 -> 4.5928254 | D112: =Market_currency -> HKD
B114: Insight: The No Growth Equity Value per share represents an estimate of the company’s intrinsic worth based on its current sustainable operations and net financial position, before factoring in any future growth potential. It serves as a fundamentally anchored valuation baseline.
B116: b. From Growth Model
B117: Scenarios | C117: HGR | D117: EV per share | E117: Probabilities | F117: Implied Return
B118: =DCF!B90&" ("&DCF!D90&"yrs)" -> Snowball Scenario (3yrs) | C118: =DCF!C90 -> -0.3 | D118: =ROUND(DCF!E90,2)&" "&Market_currency -> 2.75 HKD | E118: =DCF!F90 -> 0.15 | F118: =RATE(Holding_Period,Scenarios!C$58,-DCF!E90,C$18) -> 0.23313799
B119: =DCF!B91&" ("&DCF!D91&"yrs)" -> Optimistic (3yrs) | C119: =DCF!C91 -> 0.02 | D119: =ROUND(DCF!E91,2)&" "&Market_currency -> 4.76 HKD | E119: =DCF!F91 -> 0.16 | F119: =RATE(Holding_Period,Scenarios!C$58,-DCF!E91,C$18) -> 0.01425905
B120: =DCF!B92&" ("&DCF!D92&"yrs)" -> Base (3yrs) | C120: =DCF!C92 -> 0 | D120: =ROUND(DCF!E92,2)&" "&Market_currency -> 4.59 HKD | E120: =DCF!F92 -> 0.44 | F120: =RATE(Holding_Period,Scenarios!C$58,-DCF!E92,C$18) -> 0.027256442
B121: =DCF!B93&" ("&DCF!D93&"yrs)" -> Pessimistic (3yrs) | C121: =DCF!C93 -> -0.15 | D121: =ROUND(DCF!E93,2)&" "&Market_currency -> 3.52 HKD | E121: =DCF!F93 -> 0.2 | F121: =RATE(Holding_Period,Scenarios!C$58,-DCF!E93,C$18) -> 0.12889461
B122: =DCF!B94&" ("&DCF!D94&"yrs)" -> Devil's advocate (3yrs) | C122: =DCF!C94 -> 0.04 | D122: =ROUND(DCF!E94,2)&" "&Market_currency -> 4.94 HKD | E122: =DCF!F94 -> 0.05 | F122: =RATE(Holding_Period,Scenarios!C$58,-DCF!E94,C$18) -> 0.0014231494
B124: Goal: Estimate intrinsic value by modeling plausible FCFE/Dividend, high growth periods (HGP), and high growth rates (HGR) scenarios, weighted by probability.
B125: Expected Equity Value = | C125: =Scenarios!C36 -> 4.1464286 | D125: =Market_currency -> HKD
B127: Insight: Significant market volatility is analyzed as an indicator of the range of market-perceived outcomes, including extremes that define boundaries for scenarios like "Snowball" or "Devil’s Advocate." Scenario Analysis then filters these using fundamental reasoning to evaluate their likelihood.
A129: Step 4: Determining Investment Decisions
B131: Goal: To translate our estimate of the company’s intrinsic value (from Step 4) into a concrete buy price that meets the specific investment requirements.
B132: Calculation Logic: Discount future dividends and the expected equity value at the target return rates.
B134: Key Components
...

Sheet Data
B1: =Thesis!E17 -> HKD | C1: 45657 | D1: =EOMONTH(EDATE(C1,-12),0) -> 45291 | E1: =EOMONTH(EDATE(D1,-12),0) -> 44926 | F1: =EOMONTH(EDATE(E1,-12),0) -> 44561 | G1: =EOMONTH(EDATE(F1,-12),0) -> 44196 | H1: =EOMONTH(EDATE(G1,-12),0) -> 43830 | I1: =EOMONTH(EDATE(H1,-12),0) -> 43465 | J1: =EOMONTH(EDATE(I1,-12),0) -> 43100 | K1: =EOMONTH(EDATE(J1,-12),0) -> 42735 | ... M1: =EOMONTH(EDATE(L1,-12),0) -> 42004
B2: Data (Dirty)
B3: Income Statement | C3: 1000
B4: Sales | C4: 5057000 | D4: 5891068 | E4: 8214719 | F4: 7075818 | G4: 3996951 | H4: 3869308 | I4: 3686176 | J4: 3471922 | K4: 1809885 | L4: 1996629
B5: COGS | C5: 2468686 | D5: 2425040 | E5: 2925125 | F5: 2681244 | G5: 2127744 | H5: 1880565 | I5: 1785634 | J5: 1596518 | K5: 1202842 | L5: 1508441
B6: OPEX | C6: 318991 | D6: 415858 | E6: 556324 | F6: 477644 | G6: 498500 | H6: 432342 | I6: 413972 | J6: 408672 | K6: 371167 | L6: 543649
B7: Incl. Selling Expenses | C7: 110092 | D7: 214562 | E7: 348512 | F7: 269741 | G7: 316586 | H7: 250051 | I7: 208621 | J7: 206638 | K7: 167412 | L7: 201907
B8: R&D
B9: Share of JV or associate Results
B10: Dividend or Interests from FA
B11: Investment property
B12: Interest Expense | C12: 1746 | D12: 2921 | E12: 1360 | F12: 1275
B13: Interest Income | C13: 186780 | D13: 173638 | E13: 107067 | F13: 69578
B14: Income Tax Paid | C14: 710922 | D14: 917979 | E14: 1317738 | F14: 1071328 | G14: 425331 | H14: 456674 | I14: 487781 | J14: 465034 | K14: 76600 | L14: -124459
B15: Reported Net Income | C15: 1814975 | D15: 2300938 | E15: 3308155 | F15: 3060831 | G15: 1187283 | H15: 1176141 | I15: 1151928 | J15: 1182584 | K15: 67656 | L15: -711475
B16: Non-controling Interests | C16: 320909 | D16: 411691 | E16: 592781 | F16: 522336 | G16: 107242 | H16: 35728 | I16: 51440 | J16: 101935 | K16: -44139 | L16: -295004
B18: Cash Flow Statement
B19: D&A
B20: CAPX
B21: WCInv
B22: CFO | C22: 2369874 | D22: 4543011 | E22: 3847566 | F22: 3858089 | G22: 836818 | H22: 1922241 | I22: 1642851 | J22: 1535692 | K22: 222071 | L22: 821391
B23: CFI | C23: -182373 | D23: 759311 | E23: -1150823 | F23: -1949086 | G23: 226332 | H23: -727776 | I23: -319345 | J23: 266424 | K23: 377546 | L23: 571097
B24: CFF | C24: -971717 | D24: -2342230 | E24: -2819292 | F24: -913829 | G24: -1490643 | H24: -893331 | I24: -1135313 | J24: -317532 | K24: -1060796 | L24: -1009824
B25: ="Dividend per share ("&Market_currency&")" -> Dividend per share (HKD) | C25: =0.21+0.09 -> 0.3 | D25: =0.18+0.1 -> 0.28 | E25: =0.28+0.15 -> 0.43
B27: Balance Sheet | C27: Latest Asset Value
B28: ST AR | C28: =BS!C4 -> 537904 | D28: 687833 | E28: 2889765 | F28: 3144251 | G28: 2049144 | H28: 1797319 | I28: 2248182 | J28: 2297795 | K28: 1943651 | L28: 1757738
B29: ST Inventory | C29: =BS!C6 -> 137638 | D29: 125636 | E29: 42046 | F29: 142658 | G29: 131170 | H29: 123530 | I29: 130069 | J29: 195983 | K29: 198599 | L29: 167312
B30: Total Liabilities | C30: =BS!C33+BS!C42 -> 4047566 | D30: 4021026 | E30: 4786265 | F30: 5631759 | G30: 4142576 | H30: 4426398 | I30: 4475236 | J30: 4318962 | K30: 3438763 | L30: 3683389
B31: Total Equity | C31: =BS!G27 -> 18901257 | D31: 18470518 | E31: 18677219 | F31: 19148218 | G31: 17291070 | H31: 17046312 | I31: 16775806 | J31: 17375683 | K31: 15665693 | L31: 17044280
B32: Non-common Interest | C32: =BS!G28 -> 2421183 | D32: 2188672 | E32: 1908542 | F32: 1848135 | G32: 1453904 | H32: 1364732 | I32: 1391690 | J32: 1440871 | K32: 1146669 | L32: 1253165
B34: IS & CF Statements (Clean)
B35: Income Statement
B36: Sales | C36: =IF(C$4="","",C4) -> 5057000 | D36: =IF(D$4="","",D4) -> 5891068 | E36: =IF(E$4="","",E4) -> 8214719 | F36: =IF(F$4="","",F4) -> 7075818 | G36: =IF(G$4="","",G4) -> 3996951 | H36: =IF(H$4="","",H4) -> 3869308 | I36: =IF(I$4="","",I4) -> 3686176 | J36: =IF(J$4="","",J4) -> 3471922 | ... M36: =IF(M$4="","",M4)
B37: COGS | C37: =IF(C$4="","",-C5) -> -2468686 | D37: =IF(D$4="","",-D5) -> -2425040 | E37: =IF(E$4="","",-E5) -> -2925125 | F37: =IF(F$4="","",-F5) -> -2681244 | G37: =IF(G$4="","",-G5) -> -2127744 | H37: =IF(H$4="","",-H5) -> -1880565 | I37: =IF(I$4="","",-I5) -> -1785634 | J37: =IF(J$4="","",-J5) -> -1596518 | ... M37: =IF(M$4="","",-M5)
B38: Gross Margin | C38: =IF(C36="","",C36+C37) -> 2588314 | D38: =IF(D36="","",D36+D37) -> 3466028 | E38: =IF(E36="","",E36+E37) -> 5289594 | F38: =IF(F36="","",F36+F37) -> 4394574 | G38: =IF(G36="","",G36+G37) -> 1869207 | H38: =IF(H36="","",H36+H37) -> 1988743 | I38: =IF(I36="","",I36+I37) -> 1900542 | J38: =IF(J36="","",J36+J37) -> 1875404 | ... M38: =IF(M36="","",M36+M37)
B39: OPEX | C39: =IF(C$4="","",-C6) -> -318991 | D39: =IF(D$4="","",-D6) -> -415858 | E39: =IF(E$4="","",-E6) -> -556324 | F39: =IF(F$4="","",-F6) -> -477644 | G39: =IF(G$4="","",-G6) -> -498500 | H39: =IF(H$4="","",-H6) -> -432342 | I39: =IF(I$4="","",-I6) -> -413972 | J39: =IF(J$4="","",-J6) -> -408672 | ... M39: =IF(M$4="","",-M6)
B40: Incl. Selling Expenses | C40: =IF(C$4="","",-C7) -> -110092 | D40: =IF(D$4="","",-D7) -> -214562 | E40: =IF(E$4="","",-E7) -> -348512 | F40: =IF(F$4="","",-F7) -> -269741 | G40: =IF(G$4="","",-G7) -> -316586 | H40: =IF(H$4="","",-H7) -> -250051 | I40: =IF(I$4="","",-I7) -> -208621 | J40: =IF(J$4="","",-J7) -> -206638 | ... M40: =IF(M$4="","",-M7)
B41: Incl. Other Opex | C41: =IF(C$4="","",C39-C40) -> -208899 | D41: =IF(D$4="","",D39-D40) -> -201296 | E41: =IF(E$4="","",E39-E40) -> -207812 | F41: =IF(F$4="","",F39-F40) -> -207903 | G41: =IF(G$4="","",G39-G40) -> -181914 | H41: =IF(H$4="","",H39-H40) -> -182291 | I41: =IF(I$4="","",I39-I40) -> -205351 | J41: =IF(J$4="","",J39-J40) -> -202034 | ... M41: =IF(M$4="","",M39-M40)
B42: R&D | C42: =IF(C$4="","",-C8) -> 0 | D42: =IF(D$4="","",-D8) -> 0 | E42: =IF(E$4="","",-E8) -> 0 | F42: =IF(F$4="","",-F8) -> 0 | G42: =IF(G$4="","",-G8) -> 0 | H42: =IF(H$4="","",-H8) -> 0 | I42: =IF(I$4="","",-I8) -> 0 | J42: =IF(J$4="","",-J8) -> 0 | ... M42: =IF(M$4="","",-M8)
B43: Operating EBIT | C43: =IF(C$4="","",C38+C39+C42) -> 2269323 | D43: =IF(D$4="","",D38+D39+D42) -> 3050170 | E43: =IF(E$4="","",E38+E39+E42) -> 4733270 | F43: =IF(F$4="","",F38+F39+F42) -> 3916930 | G43: =IF(G$4="","",G38+G39+G42) -> 1370707 | H43: =IF(H$4="","",H38+H39+H42) -> 1556401 | I43: =IF(I$4="","",I38+I39+I42) -> 1486570 | J43: =IF(J$4="","",J38+J39+J42) -> 1466732 | ... M43: =IF(M$4="","",M38+M39+M42)
B44: Non-operating EBIT | C44: =IF(C$4="","",C47-C46-C45-C43) -> 71540 | D44: =IF(D$4="","",D47-D46-D45-D43) -> -1970 | E44: =IF(E$4="","",E47-E46-E45-E43) -> -213084 | F44: =IF(F$4="","",F47-F46-F45-F43) -> 146926 | G44: =IF(G$4="","",G47-G46-G45-G43) -> 241907 | H44: =IF(H$4="","",H47-H46-H45-H43) -> 76414 | I44: =IF(I$4="","",I47-I46-I45-I43) -> 153139 | J44: =IF(J$4="","",J47-J46-J45-J43) -> 180886 | ... M44: =IF(M$4="","",M47-M46-M45-M43)
B45: Net Interest Income | C45: =IF(C$4="","",C51+C52) -> 185034 | D45: =IF(D$4="","",D51+D52) -> 170717 | E45: =IF(E$4="","",E51+E52) -> 105707 | F45: =IF(F$4="","",F51+F52) -> 68303 | G45: =IF(G$4="","",G51+G52) -> 0 | H45: =IF(H$4="","",H51+H52) -> 0 | I45: =IF(I$4="","",I51+I52) -> 0 | J45: =IF(J$4="","",J51+J52) -> 0 | ... M45: =IF(M$4="","",M51+M52)
B46: Income Tax Paid | C46: =IF(C$4="","",-C14) -> -710922 | D46: =IF(D$4="","",-D14) -> -917979 | E46: =IF(E$4="","",-E14) -> -1317738 | F46: =IF(F$4="","",-F14) -> -1071328 | G46: =IF(G$4="","",-G14) -> -425331 | H46: =IF(H$4="","",-H14) -> -456674 | I46: =IF(I$4="","",-I14) -> -487781 | J46: =IF(J$4="","",-J14) -> -465034 | ... M46: =IF(M$4="","",-M14)
B47: Reported Net Income | C47: =IF(C$4="","",C15) -> 1814975 | D47: =IF(D$4="","",D15) -> 2300938 | E47: =IF(E$4="","",E15) -> 3308155 | F47: =IF(F$4="","",F15) -> 3060831 | G47: =IF(G$4="","",G15) -> 1187283 | H47: =IF(H$4="","",H15) -> 1176141 | I47: =IF(I$4="","",I15) -> 1151928 | J47: =IF(J$4="","",J15) -> 1182584 | ... M47: =IF(M$4="","",M15)
B48: Non-controling Interests | C48: =IF(C$4="","",MIN(-C16,0)) -> -320909 | D48: =IF(D$4="","",MIN(-D16,0)) -> -411691 | E48: =IF(E$4="","",MIN(-E16,0)) -> -592781 | F48: =IF(F$4="","",MIN(-F16,0)) -> -522336 | G48: =IF(G$4="","",MIN(-G16,0)) -> -107242 | H48: =IF(H$4="","",MIN(-H16,0)) -> -35728 | I48: =IF(I$4="","",MIN(-I16,0)) -> -51440 | J48: =IF(J$4="","",MIN(-J16,0)) -> -101935 | ... M48: =IF(M$4="","",MIN(-M16,0))
B50: Net Interest Income
B51: Interest Expense | C51: =IF(C$4="","",-C12) -> -1746 | D51: =IF(D$4="","",-D12) -> -2921 | E51: =IF(E$4="","",-E12) -> -1360 | F51: =IF(F$4="","",-F12) -> -1275 | G51: =IF(G$4="","",-G12) -> 0 | H51: =IF(H$4="","",-H12) -> 0 | I51: =IF(I$4="","",-I12) -> 0 | J51: =IF(J$4="","",-J12) -> 0 | ... M51: =IF(M$4="","",-M12)
B52: Interest Income | C52: =IF(C$4="","",C13) -> 186780 | D52: =IF(D$4="","",D13) -> 173638 | E52: =IF(E$4="","",E13) -> 107067 | F52: =IF(F$4="","",F13) -> 69578 | G52: =IF(G$4="","",G13) -> 0 | H52: =IF(H$4="","",H13) -> 0 | I52: =IF(I$4="","",I13) -> 0 | J52: =IF(J$4="","",J13) -> 0 | ... M52: =IF(M$4="","",M13)
B54: Non-operating EBIT
B55: Share of JV or associate Results | C55: =IF(C$4="","",C9) -> 0 | D55: =IF(D$4="","",D9) -> 0 | E55: =IF(E$4="","",E9) -> 0 | F55: =IF(F$4="","",F9) -> 0 | G55: =IF(G$4="","",G9) -> 0 | H55: =IF(H$4="","",H9) -> 0 | I55: =IF(I$4="","",I9) -> 0 | J55: =IF(J$4="","",J9) -> 0 | ... M55: =IF(M$4="","",M9)
B56: Dividend or Interests from FA | C56: =IF(C$4="","",C10) -> 0 | D56: =IF(D$4="","",D10) -> 0 | E56: =IF(E$4="","",E10) -> 0 | F56: =IF(F$4="","",F10) -> 0 | G56: =IF(G$4="","",G10) -> 0 | H56: =IF(H$4="","",H10) -> 0 | I56: =IF(I$4="","",I10) -> 0 | J56: =IF(J$4="","",J10) -> 0 | ... M56: =IF(M$4="","",M10)
B57: Investment property | C57: =IF(C$4="","",C11) -> 0 | D57: =IF(D$4="","",D11) -> 0 | E57: =IF(E$4="","",E11) -> 0 | F57: =IF(F$4="","",F11) -> 0 | G57: =IF(G$4="","",G11) -> 0 | H57: =IF(H$4="","",H11) -> 0 | I57: =IF(I$4="","",I11) -> 0 | J57: =IF(J$4="","",J11) -> 0 | ... M57: =IF(M$4="","",M11)
B58: Other Non-operating Income | C58: =IF(C$4="","",C44-C55-C56-C57) -> 71540 | D58: =IF(D$4="","",D44-D55-D56-D57) -> -1970 | E58: =IF(E$4="","",E44-E55-E56-E57) -> -213084 | F58: =IF(F$4="","",F44-F55-F56-F57) -> 146926 | G58: =IF(G$4="","",G44-G55-G56-G57) -> 241907 | H58: =IF(H$4="","",H44-H55-H56-H57) -> 76414 | I58: =IF(I$4="","",I44-I55-I56-I57) -> 153139 | J58: =IF(J$4="","",J44-J55-J56-J57) -> 180886 | ... M58: =IF(M$4="","",M44-M55-M56-M57)
B60: Cash Flow Statement
B61: D&A | C61: =IF(C$4="","",-C19) -> 0 | D61: =IF(D$4="","",-D19) -> 0 | E61: =IF(E$4="","",-E19) -> 0 | F61: =IF(F$4="","",-F19) -> 0 | G61: =IF(G$4="","",-G19) -> 0 | H61: =IF(H$4="","",-H19) -> 0 | I61: =IF(I$4="","",-I19) -> 0 | J61: =IF(J$4="","",-J19) -> 0 | ... M61: =IF(M$4="","",-M19)
B62: CAPX | C62: =IF(C$4="","",IF(C20=0,C61,-C20)) -> 0 | D62: =IF(D$4="","",IF(D20=0,D61,-D20)) -> 0 | E62: =IF(E$4="","",IF(E20=0,E61,-E20)) -> 0 | F62: =IF(F$4="","",IF(F20=0,F61,-F20)) -> 0 | G62: =IF(G$4="","",IF(G20=0,G61,-G20)) -> 0 | H62: =IF(H$4="","",IF(H20=0,H61,-H20)) -> 0 | I62: =IF(I$4="","",IF(I20=0,I61,-I20)) -> 0 | J62: =IF(J$4="","",IF(J20=0,J61,-J20)) -> 0 | ... M62: =IF(M$4="","",IF(M20=0,M61,-M20))
B63: WCInv | C63: =IF(C$4="","",-C21) -> 0 | D63: =IF(D$4="","",-D21) -> 0 | E63: =IF(E$4="","",-E21) -> 0 | F63: =IF(F$4="","",-F21) -> 0 | G63: =IF(G$4="","",-G21) -> 0 | H63: =IF(H$4="","",-H21) -> 0 | I63: =IF(I$4="","",-I21) -> 0 | J63: =IF(J$4="","",-J21) -> 0 | ... M63: =IF(M$4="","",-M21)
B64: Net Change in Cash | C64: =IF(C$4="","",C22+C23+C24) -> 1215784 | D64: =IF(D$4="","",D22+D23+D24) -> 2960092 | E64: =IF(E$4="","",E22+E23+E24) -> -122549 | F64: =IF(F$4="","",F22+F23+F24) -> 995174 | G64: =IF(G$4="","",G22+G23+G24) -> -427493 | H64: =IF(H$4="","",H22+H23+H24) -> 301134 | I64: =IF(I$4="","",I22+I23+I24) -> 188193 | J64: =IF(J$4="","",J22+J23+J24) -> 1484584 | ... M64: =IF(M$4="","",M22+M23+M24)
B65: Dividend per share | C65: =IF(C$4="","",C25) -> 0.3 | D65: =IF(D$4="","",D25) -> 0.28 | E65: =IF(E$4="","",E25) -> 0.43 | F65: =IF(F$4="","",F25) -> 0 | G65: =IF(G$4="","",G25) -> 0 | H65: =IF(H$4="","",H25) -> 0 | I65: =IF(I$4="","",I25) -> 0 | J65: =IF(J$4="","",J25) -> 0 | ... M65: =IF(M$4="","",M25)
B67: YoY %
B68: =B36 -> Sales | C68: =IF(D$36="","",C36/D36-1) -> -0.1415818 | D68: =IF(E$36="","",D36/E36-1) -> -0.28286433 | E68: =IF(F$36="","",E36/F36-1) -> 0.1609568 | F68: =IF(G$36="","",F36/G36-1) -> 0.77030391 | G68: =IF(H$36="","",G36/H36-1) -> 0.032988586 | H68: =IF(I$36="","",H36/I36-1) -> 0.049680753 | I68: =IF(J$36="","",I36/J36-1) -> 0.061710488 | J68: =IF(K$36="","",J36/K36-1) -> 0.91831083 | ... M68: =IF(N$36="","",M36/N36-1)
B69: Gross Margin | C69: =IF(D$36="","",C38/D38-1) -> -0.25323338 | D69: =IF(E$36="","",D38/E38-1) -> -0.34474593 | E69: =IF(F$36="","",E38/F38-1) -> 0.20366479 | F69: =IF(G$36="","",F38/G38-1) -> 1.3510366 | G69: =IF(H$36="","",G38/H38-1) -> -0.060106308 | H69: =IF(I$36="","",H38/I38-1) -> 0.04640834 | I69: =IF(J$36="","",I38/J38-1) -> 0.013404045 | J69: =IF(K$36="","",J38/K38-1) -> 2.0894088 | ... M69: =IF(N$36="","",M38/N38-1)
B70: =B43 -> Operating EBIT | C70: =IF(D$36="","",C43/D43-1) -> -0.25600114 | D70: =IF(E$36="","",D43/E43-1) -> -0.35558926 | E70: =IF(F$36="","",E43/F43-1) -> 0.20841322 | F70: =IF(G$36="","",F43/G43-1) -> 1.8575983 | G70: =IF(H$36="","",G43/H43-1) -> -0.11930987 | H70: =IF(I$36="","",H43/I43-1) -> 0.046974579 | I70: =IF(J$36="","",I43/J43-1) -> 0.013525307 | J70: =IF(K$36="","",J43/K43-1) -> 5.2182333 | ... M70: =IF(N$36="","",M43/N43-1)
B71: Non-operating EBIT | C71: =IF(D$36="","",C44/D44-1) -> -37.314721 | D71: =IF(E$36="","",D44/E44-1) -> -0.99075482 | E71: =IF(F$36="","",E44/F44-1) -> -2.4502811 | F71: =IF(G$36="","",F44/G44-1) -> -0.39263436 | G71: =IF(H$36="","",G44/H44-1) -> 2.1657419 | H71: =IF(I$36="","",H44/I44-1) -> -0.50101542 | I71: =IF(J$36="","",I44/J44-1) -> -0.15339496 | J71: =IF(K$36="","",J44/K44-1) -> -2.9743069 | ... M71: =IF(N$36="","",M44/N44-1)
B72: =B47 -> Reported Net Income | C72: =IF(D$36="","",C47/D47-1) -> -0.21120213 | D72: =IF(E$36="","",D47/E47-1) -> -0.30446488 | E72: =IF(F$36="","",E47/F47-1) -> 0.080802893 | F72: =IF(G$36="","",F47/G47-1) -> 1.578013 | G72: =IF(H$36="","",G47/H47-1) -> 0.009473354 | H72: =IF(I$36="","",H47/I47-1) -> 0.021019543 | I72: =IF(J$36="","",I47/J47-1) -> -0.025922894 | J72: =IF(K$36="","",J47/K47-1) -> 16.479366 | ... M72: =IF(N$36="","",M47/N47-1)
B74: Balance Sheet (Clean)
B75: Balance Sheet
B76: Total Assets | C76: =IF(C$4="","",C79+C80) -> 22948823 | D76: =IF(D$4="","",D79+D80) -> 22491544 | E76: =IF(E$4="","",E79+E80) -> 23463484 | F76: =IF(F$4="","",F79+F80) -> 24779977 | G76: =IF(G$4="","",G79+G80) -> 21433646 | H76: =IF(H$4="","",H79+H80) -> 21472710 | I76: =IF(I$4="","",I79+I80) -> 21251042 | J76: =IF(J$4="","",J79+J80) -> 21694645 | ... M76: =IF(M$4="","",M79+M80)
B77: Incl. ST AR | C77: =IF(C$4="","",C28) -> 537904 | D77: =IF(D$4="","",D28) -> 687833 | E77: =IF(E$4="","",E28) -> 2889765 | F77: =IF(F$4="","",F28) -> 3144251 | G77: =IF(G$4="","",G28) -> 2049144 | H77: =IF(H$4="","",H28) -> 1797319
B78: Incl. ST Inventory | C78: =IF(C$4="","",C29) -> 137638 | D78: =IF(D$4="","",D29) -> 125636 | E78: =IF(E$4="","",E29) -> 42046 | F78: =IF(F$4="","",F29) -> 142658 | G78: =IF(G$4="","",G29) -> 131170 | H78: =IF(H$4="","",H29) -> 123530
B79: Total Liabilities | C79: =IF(C$4="","",C30) -> 4047566 | D79: =IF(D$4="","",D30) -> 4021026 | E79: =IF(E$4="","",E30) -> 4786265 | F79: =IF(F$4="","",F30) -> 5631759 | G79: =IF(G$4="","",G30) -> 4142576 | H79: =IF(H$4="","",H30) -> 4426398 | I79: =IF(I$4="","",I30) -> 4475236 | J79: =IF(J$4="","",J30) -> 4318962 | ... M79: =IF(M$4="","",M30)
B80: Total Equity | C80: =IF(C$4="","",C31) -> 18901257 | D80: =IF(D$4="","",D31) -> 18470518 | E80: =IF(E$4="","",E31) -> 18677219 | F80: =IF(F$4="","",F31) -> 19148218 | G80: =IF(G$4="","",G31) -> 17291070 | H80: =IF(H$4="","",H31) -> 17046312 | I80: =IF(I$4="","",I31) -> 16775806 | J80: =IF(J$4="","",J31) -> 17375683 | ... M80: =IF(M$4="","",M31)

Sheet BS
B1: Most Recent Quarter | C1: 45838 | F1: =IF(MONTH(C1)=MONTH(Normalized_FCF!G1),"FY","Quarter")&" Report" -> Quarter Report | H1: =scaling_factor -> 1000
B2: Lastest Balance Sheet
B3: ST Operating Assets | C3: Book | D3: Valued @ | F3: ST Non-Operating Assets | G3: Book | H3: Valued @
B4: ST AR | C4: =519815+18089 -> 537904 | D4: 0.6 | F4: Cash and cash equivalents | G4: =1505443+7675879 -> 9181322 | H4: 0.9
B5: Operating ST Financial Assets | C5: 0 | D5: 0.6 | F5: Restricted cash | G5: 937107 | H5: 0.7
B6: Inventory | C6: 137638 | D6: 0.5 | F6: Securities with stable income | G6: 0 | H6: 0.6
B7: Properties held for sale | C7: 0 | D7: 0.6 | F7: Other Securities | G7: 0 | H7: 0.6
B8: Properties held for income | C8: 0 | D8: 0.6 | F8: Properties with stable income | G8: 0 | H8: 0.6
B9: Prepayments and Contract Assets | C9: 207695 | D9: 0.1 | F9: Other Properties | G9: 0 | H9: 0.6
B10: ST DTA | C10: 0 | D10: 0.9 | F10: Assets held for sale | G10: 0 | H10: 0.6
B11: Other ST Assets | C11: 0 | D11: 0.05
B12: Operating ST Assets | C12: =SUM(C4:C11) -> 883237 | D12: =C4*D4+C5*D5+C9*D9+C6*D6+C8*D8+C7*D7+C10*D10+C11*D11 -> 412330.9 | F12: Non-Operating ST Assets | G12: =SUM(G4:G10) -> 10118429 | H12: =G4*H4+G5*H5+G6*H6+G7*H7+G8*H8+G9*H9+G10*H10 -> 8919164.7
B14: LT Operating Assets | C14: Book | D14: Valued @ | F14: LT Non-Operating Assets | G14: Book | H14: Valued @
B15: LT AR and Prepayments | C15: 453310 | D15: 0.4 | F15: LT Depositis | G15: 0 | H15: 0.8
B16: Operating LT Financial Assets | C16: 0 | D16: 0.5 | F16: Securities with stable income | G16: 0 | H16: 0.6
B17: Properties held for sale | C17: 0 | D17: 0.6 | F17: Other Securities | G17: =439187 -> 439187 | H17: 0.6
B18: Properties held for income | C18: 0 | D18: 0.6 | F18: JV or associate with stable income | G18: 0 | H18: 0.1
B19: PP&E & Right of Use Assets | C19: =3715248+73168+31796 -> 3820212 | D19: 0.1 | F19: Other JV or associate | G19: 0 | H19: 0.1
B20: Biological assets | C20: 0 | D20: 0.05 | F20: Properties with stable income | G20: 0 | H20: 0.2
B21: Intangible assets | C21: 5970133 | D21: 0.05 | F21: Other Properties | G21: 0 | H21: 0.1
B22: LT DTA | C22: 84764 | D22: 0.9
B23: Other assets & Goodwill | C23: =1179551 -> 1179551 | D23: 0
B24: Operating LT Assets | C24: =SUM(C15:C23) -> 11507970 | D24: =C15*D15+C16*D16+C18*D18+C17*D17+C19*D19+C20*D20+C21*D21+C22*D22+C23*D23 -> 938139.45 | F24: Non-Operating LT Assets | G24: =SUM(G15:G21) -> 439187 | H24: =G15*H15+G16*H16+G17*H17+G18*H18+G19*H19+G20*H20+G21*H21 -> 263512.2
B26: ST Liabilities | C26: Book | F26: BS Summary | G26: Book | H26: Valued @
B27: ST Borrowing | C27: 0 | F27: Total Equity | G27: =G32-G30 -> 18901257 | H27: =H32-G30 -> 6485581.2
B28: ST Lease liabilities | C28: 12125 | F28: Incl. Minority Interest (NCI) | G28: 2421183
B29: ST SH Loan | C29: 0 | F29: Incl. Common Equity | G29: =G27-G28 -> 16480074 | H29: =H27-G28 -> 4064398.2
B30: ST Financial Liabilities | C30: 0 | F30: Total Liabilities | G30: =C33+C42 -> 4047566
B31: ST Interest-bearing Debt | C31: =SUM(C27:C30) -> 12125 | F31: incl. Interest-bearing Debt | G31: =C31+C40 -> 43677
B32: Other ST liabilities | C32: =C33-C31 -> 2578910 | F32: Total Assets | G32: =G35+G40 -> 22948823 | H32: =H35+H40 -> 10533147
B33: Current Liabilities | C33: 2591035
F34: Assets Summary | G34: Book | H34: Valued @
B35: LT Liabilities | C35: Book | F35: Operating Assets | G35: =C12+C24 -> 12391207 | H35: =D12+D24 -> 1350470.3
B36: LT Borrowing | C36: 0 | F36: incl. AR | G36: =C4+C15 -> 991214
B37: LT Lease liabilities | C37: 31552 | F37: incl. inventory | G37: =C6 -> 137638
B38: LT SH Loan | C38: 0 | F38: incl. Properties held for sale | G38: =C7+C17 -> 0
B39: LT Financial Liabilities | C39: 0 | F39: incl. Fixed Assets | G39: =C7+C17+C19+C20 -> 3820212 | H39: =C7*D7+C17*D17+C19*D19+C20*D20 -> 382021.2
B40: LT Interest-bearing Debt | C40: =SUM(C36:C39) -> 31552 | F40: Non-operating Assets | G40: =G12+G24 -> 10557616 | H40: =H12+H24 -> 9182676.9
B41: Other LT liabilities | C41: =C42-C40 -> 1424979 | F41: incl. Assets with stable income | G41: =C70 -> 10118429 | H41: =H40-H42 -> 8919164.7
B42: Noncurrent Liabilities | C42: 1456531 | F42: incl. Other Assets | G42: =C82 -> 439187 | H42: =D82 -> 263512.2
B44: Balance Sheet Analysis
B45: Asset Value Stress Test | C45: Book | D45: Est. Realizable Value | F45: Notes
B46: Equity | C46: =G29 -> 16480074 | D46: =H29 -> 4064398.2
B47: ="Equity per share ("&Market_currency&")" -> Equity per share (HKD) | C47: =C46*H1/Common_Shares*Exchange_Rate -> 3.2370578 | D47: =D46*H1/Common_Shares*Exchange_Rate -> 0.79833937
B49: Leverage % | C49: Normalized | D49: Latest
B50: Debt/EBIT | C50: =G31/Normalized_FCF!C8 -> 0.022976896 | D50: =G31/Normalized_FCF!G8 -> 0.019246709
B51: Common Equity/Total Asset | D51: =G29/G32 -> 0.71812284
B53: Profibility % | C53: Normalized | D53: Latest
B54: Operating Asset Yield | C54: =Normalized_FCF!C8/G35 -> 0.15340794 | D54: =Normalized_FCF!G8/G35 -> 0.18313979
B55: Non-Operating Asset Yield | C55: =Normalized_FCF!C9/G40 -> 0 | D55: =Normalized_FCF!G9/G40 -> 0
B57: Reinvestment % | C57: Normalized | D57: Latest
B58: D&A/Fixed Assets | D58: =Normalized_FCF!G15/BS!$G$39 -> 0
B59: Fixed Assets/Total Assets | D59: =G39/G32 -> 0.16646658
B61: NCI % | C61: Estimate | D61: Latest
B62: Est. of NCI Ownership Percentage | C62: =IF(G28<=0,0,G28/G29) -> 0.14691578 | D62: =G28/G29 -> 0.14691578 | F62: Rough Estimate only
B64: Non-operating Assets Analysis
B65: Non-operating Assets with stable income | C65: Book | D65: Non-Operating | F65: Notes
B66: Cash | C66: =G4+G5+G15 -> 10118429 | D66: =C66-D75 -> 8029573.9 | F66: Non-Operating Cash is the Excess cash not required for operations
B67: Securities with stable income | C67: =G6+G16 -> 0
B68: JV or associate with stable income | C68: =G18 -> 0
B69: Properties with stable income | C69: =G8+G20 -> 0
B70: Non-operating Assets with stable income | C70: =SUM(C66:C69) -> 10118429
B72: Cash Management Analysis | C72: Latest | D72: Normalized
B73: Monthly Operating Expenses | C73: =(Normalized_FCF!G26+Normalized_FCF!G35-Normalized_FCF!G89)/12 -> -359583.06 | D73: =(Normalized_FCF!C26+Normalized_FCF!C35-Normalized_FCF!C89)/12 -> -348142.52 | F73: Variable + Fixed Costs & Dividends
B74: Operating Expenses Multiple (months) | C74: =-$C$66/C73 -> 28.139337 | D74: =-$C$66/D73 -> 29.064043 | F74: Companies typically need cash to cover 1 to 2 months of operating expenses
B75: Operating Cash Requirement | D75: =MAX(-D73*D76,G5) -> 2088855.1 | F75: 1x for stable businesses, 2x for for volatile ones, 6x for cash hoarders
B76: Operating Cash Multiple (months) | D76: =IF(D74<=3,1,IF(D74>18,6,2)) -> 6 | F76: Rough Estimate
B78: Other Non-operating Assets | C78: Book | D78: Valued @
B79: Other Securities | C79: =G7+G17 -> 439187 | D79: =G7*H7+G17*H17 -> 263512.2
B80: Other JV or associate | C80: =G19 -> 0 | D80: =G19*H19 -> 0
B81: Other Properties | C81: =G9+G21 -> 0 | D81: =G9*H9+G21*H21 -> 0
B82: Other Non-operating Assets | C82: =SUM(C79:C81) -> 439187 | D82: =SUM(D79:D81) -> 263512.2
B84: Non-FCF Value of the Equity Value
B85: Non-FCF Value | D85: Per-Share
B86: Interest-bearing Debt | C86: =-DCF!F4*Exchange_Rate -> 43677 | D86: =C86*scaling_factor/Common_Shares -> 0.0085791467 | E86: =Market_currency -> HKD
B87: Non-operating Cash | C87: =DCF!F5*Exchange_Rate -> 8029573.9 | D87: =C87*scaling_factor/Common_Shares -> 1.5771892 | E87: =Market_currency -> HKD
B88: Other Non-operating Assets | C88: =DCF!F6*Exchange_Rate -> 263512.2 | D88: =C88*scaling_factor/Common_Shares -> 0.051759732 | E88: =Market_currency -> HKD
B89: Total Non-FCF Value | C89: =SUM(C86:C88) -> 8336763.1 | D89: =SUM(D86:D88) -> 1.6375281 | E89: =Market_currency -> HKD

Sheet Normalized_FCF
B1: =Thesis!E17 -> HKD | C1: Normalized | G1: =Data!C1 -> 45657 | H1: =EOMONTH(EDATE(G1,-12),0) -> 45291 | I1: =EOMONTH(EDATE(H1,-12),0) -> 44926 | J1: =EOMONTH(EDATE(I1,-12),0) -> 44561 | K1: =EOMONTH(EDATE(J1,-12),0) -> 44196 | L1: =EOMONTH(EDATE(K1,-12),0) -> 43830 | M1: =EOMONTH(EDATE(L1,-12),0) -> 43465 | N1: =EOMONTH(EDATE(M1,-12),0) -> 43100 | O1: =EOMONTH(EDATE(N1,-12),0) -> 42735 | ... Q1: =EOMONTH(EDATE(P1,-12),0) -> 42004
B2: FCFE Analysis | E2: Notes
B3: Normalized FCFE | C3: =scaling_factor -> 1000 | G3: Historical FCFE | H3: =scaling_factor -> 1000
B4: Sales | C4: =G4*0.9 -> 4551300 | G4: =Data!C36 -> 5057000 | H4: =Data!D36 -> 5891068 | I4: =Data!E36 -> 8214719 | J4: =Data!F36 -> 7075818 | K4: =Data!G36 -> 3996951 | L4: =Data!H36 -> 3869308 | M4: =Data!I36 -> 3686176 | N4: =Data!J36 -> 3471922 | ... Q4: =Data!M36
B5: Variable Costs | C5: =C26 -> -2441491.5 | G5: =G26 -> -2578778 | H5: =H26 -> -2639602 | I5: =I26 -> -3273637 | J5: =J26 -> -2950985 | K5: =K26 -> -2444330 | L5: =L26 -> -2130616 | M5: =M26 -> -1994255 | N5: =N26 -> -1803156 | ... Q5: =Q26
B6: Contribution Margin | C6: =C4+C5 -> 2109808.5 | G6: =IF(G4="","",G4+G5) -> 2478222 | H6: =IF(H4="","",H4+H5) -> 3251466 | I6: =IF(I4="","",I4+I5) -> 4941082 | J6: =IF(J4="","",J4+J5) -> 4124833 | K6: =IF(K4="","",K4+K5) -> 1552621 | L6: =IF(L4="","",L4+L5) -> 1738692 | M6: =IF(M4="","",M4+M5) -> 1691921 | N6: =IF(N4="","",N4+N5) -> 1668766 | ... Q6: =IF(Q4="","",Q4+Q5)
B7: Fixed Costs | C7: =C35 -> -208899 | G7: =G35 -> -208899 | H7: =H35 -> -201296 | I7: =I35 -> -207812 | J7: =J35 -> -207903 | K7: =K35 -> -181914 | L7: =L35 -> -182291 | M7: =M35 -> -205351 | N7: =N35 -> -202034 | ... Q7: =Q35
B8: Operating EBIT | C8: =C6+C7 -> 1900909.5 | G8: =IF(G$4="","",G6+G7) -> 2269323 | H8: =IF(H$4="","",H6+H7) -> 3050170 | I8: =IF(I$4="","",I6+I7) -> 4733270 | J8: =IF(J$4="","",J6+J7) -> 3916930 | K8: =IF(K$4="","",K6+K7) -> 1370707 | L8: =IF(L$4="","",L6+L7) -> 1556401 | M8: =IF(M$4="","",M6+M7) -> 1486570 | N8: =IF(N$4="","",N6+N7) -> 1466732 | ... Q8: =IF(Q$4="","",Q6+Q7)
B9: Stable Non-Operating EBIT | C9: =C61 -> 0 | G9: =G59 -> 0 | H9: =H59 -> 0 | I9: =I59 -> 0 | J9: =J59 -> 0 | K9: =K59 -> 0 | L9: =L59 -> 0 | M9: =M59 -> 0 | N9: =N59 -> 0 | ... Q9: =Q59
B10: Net Interest Income | C10: =C48 -> 9912.5106 | G10: =G48 -> 36812.985 | H10: =H48 -> 32924.942 | I10: =I48 -> 20742.982 | J10: =J48 -> 13088.728 | K10: =K48 -> 0 | L10: =L48 -> 0 | M10: =M48 -> 0 | N10: =N48 -> 0 | ... Q10: =Q48
B11: Pre-tax Profit | C11: =SUM(C8:C10) -> 1910822 | G11: =IF(G$4="","",SUM(G8:G10)) -> 2306136 | H11: =IF(H$4="","",SUM(H8:H10)) -> 3083094.9 | I11: =IF(I$4="","",SUM(I8:I10)) -> 4754013 | J11: =IF(J$4="","",SUM(J8:J10)) -> 3930018.7 | K11: =IF(K$4="","",SUM(K8:K10)) -> 1370707 | L11: =IF(L$4="","",SUM(L8:L10)) -> 1556401 | M11: =IF(M$4="","",SUM(M8:M10)) -> 1486570 | N11: =IF(N$4="","",SUM(N8:N10)) -> 1466732 | ... Q11: =IF(Q$4="","",SUM(Q8:Q10))
B12: Income Tax | C12: =-C11*C41 -> -477705.51 | G12: =Data!C46 -> -710922 | H12: =Data!D46 -> -917979 | I12: =Data!E46 -> -1317738 | J12: =Data!F46 -> -1071328 | K12: =Data!G46 -> -425331 | L12: =Data!H46 -> -456674 | M12: =Data!I46 -> -487781 | N12: =Data!J46 -> -465034 | ... Q12: =Data!M46
B13: NCI’s Share of Profits | C13: =-C4*C79 -> -335976.4 | G13: =Data!C48 -> -320909 | H13: =Data!D48 -> -411691 | I13: =Data!E48 -> -592781 | J13: =Data!F48 -> -522336 | K13: =Data!G48 -> -107242 | L13: =Data!H48 -> -35728 | M13: =Data!I48 -> -51440 | N13: =Data!J48 -> -101935 | ... Q13: =Data!M48
B14: After-tax Profit | C14: =SUM(C11:C13) -> 1097140.1 | G14: =IF(G$4="","",SUM(G11:G13)) -> 1274305 | H14: =IF(H$4="","",SUM(H11:H13)) -> 1753424.9 | I14: =IF(I$4="","",SUM(I11:I13)) -> 2843494 | J14: =IF(J$4="","",SUM(J11:J13)) -> 2336354.7 | K14: =IF(K$4="","",SUM(K11:K13)) -> 838134 | L14: =IF(L$4="","",SUM(L11:L13)) -> 1063999 | M14: =IF(M$4="","",SUM(M11:M13)) -> 947349 | N14: =IF(N$4="","",SUM(N11:N13)) -> 899763 | ... Q14: =IF(Q$4="","",SUM(Q11:Q13))
B15: Add Back D&A | C15: =BS!$G$39*BS!D58 -> 0 | G15: =IF(Data!C61="","",-Data!C61) -> 0 | H15: =IF(Data!D61="","",-Data!D61) -> 0 | I15: =IF(Data!E61="","",-Data!E61) -> 0 | J15: =IF(Data!F61="","",-Data!F61) -> 0 | K15: =IF(Data!G61="","",-Data!G61) -> 0 | L15: =IF(Data!H61="","",-Data!H61) -> 0 | M15: =IF(Data!I61="","",-Data!I61) -> 0 | N15: =IF(Data!J61="","",-Data!J61) -> 0 | ... Q15: =IF(Data!M61="","",-Data!M61)
B16: Maintenance Capex | C16: =-C4*C82 -> 0 | G16: =Data!C62 -> 0 | H16: =Data!D62 -> 0 | I16: =Data!E62 -> 0 | J16: =Data!F62 -> 0 | K16: =Data!G62 -> 0 | L16: =Data!H62 -> 0 | M16: =Data!I62 -> 0 | N16: =Data!J62 -> 0 | ... Q16: =Data!M62
B17: WCInv | C17: =-C4*C83 -> 0 | E17: WCInv is by default excluded
B18: Net Borrowing | C18: 0 | E18: Net borrowing is excluded
B19: FCFE | C19: =C14+C17 -> 1097140.1 | G19: =IF(G$4="","",G14+G17) -> 1274305 | H19: =IF(H$4="","",H14+H17) -> 1753424.9 | I19: =IF(I$4="","",I14+I17) -> 2843494 | J19: =IF(J$4="","",J14+J17) -> 2336354.7 | K19: =IF(K$4="","",K14+K17) -> 838134 | L19: =IF(L$4="","",L14+L17) -> 1063999 | M19: =IF(M$4="","",M14+M17) -> 947349 | N19: =IF(N$4="","",N14+N17) -> 899763 | ... Q19: =IF(Q$4="","",Q14+Q17)
B21: Operating Cost Structure | E21: Notes
B22: Variable Costs
B23: COGS | C23: =-C4*C29 -> -2283631.2 | G23: =Data!C37 -> -2468686 | H23: =Data!D37 -> -2425040 | I23: =Data!E37 -> -2925125 | J23: =Data!F37 -> -2681244 | K23: =Data!G37 -> -2127744 | L23: =Data!H37 -> -1880565 | M23: =Data!I37 -> -1785634 | N23: =Data!J37 -> -1596518 | ... Q23: =Data!M37
B24: Selling Expenses | C24: =-C4*C30 -> -157860.29 | G24: =Data!C40 -> -110092 | H24: =Data!D40 -> -214562 | I24: =Data!E40 -> -348512 | J24: =Data!F40 -> -269741 | K24: =Data!G40 -> -316586 | L24: =Data!H40 -> -250051 | M24: =Data!I40 -> -208621 | N24: =Data!J40 -> -206638 | ... Q24: =Data!M40
B25: R&D | C25: =-C4*C31 -> 0 | G25: =Data!C42 -> 0 | H25: =Data!D42 -> 0 | I25: =Data!E42 -> 0 | J25: =Data!F42 -> 0 | K25: =Data!G42 -> 0 | L25: =Data!H42 -> 0 | M25: =Data!I42 -> 0 | N25: =Data!J42 -> 0 | ... Q25: =Data!M42
B26: Variable Costs | C26: =SUM(C23:C25) -> -2441491.5 | G26: =IF(G$4="","",SUM(G23:G25)) -> -2578778 | H26: =IF(H$4="","",SUM(H23:H25)) -> -2639602 | I26: =IF(I$4="","",SUM(I23:I25)) -> -3273637 | J26: =IF(J$4="","",SUM(J23:J25)) -> -2950985 | K26: =IF(K$4="","",SUM(K23:K25)) -> -2444330 | L26: =IF(L$4="","",SUM(L23:L25)) -> -2130616 | M26: =IF(M$4="","",SUM(M23:M25)) -> -1994255 | N26: =IF(N$4="","",SUM(N23:N25)) -> -1803156 | ... Q26: =IF(Q$4="","",SUM(Q23:Q25))
B28: Variable Costs % of Sales
B29: COGS | C29: =AVERAGE(G29:P29) -> 0.50175361 | G29: =IF(G$4="","",ABS(G23/G$4)) -> 0.48817204 | H29: =IF(H$4="","",ABS(H23/H$4)) -> 0.41164692 | I29: =IF(I$4="","",ABS(I23/I$4)) -> 0.35608339 | J29: =IF(J$4="","",ABS(J23/J$4)) -> 0.37893061 | K29: =IF(K$4="","",ABS(K23/K$4)) -> 0.53234178 | L29: =IF(L$4="","",ABS(L23/L$4)) -> 0.48602101 | M29: =IF(M$4="","",ABS(M23/M$4)) -> 0.48441366 | N29: =IF(N$4="","",ABS(N23/N$4)) -> 0.45983694 | ... Q29: =IF(Q$4="","",ABS(Q23/Q$4))
B30: =B24 -> Selling Expenses | C30: =AVERAGE(G30:J30) -> 0.034684659 | G30: =IF(G$4="","",ABS(G24/G$4)) -> 0.021770219 | H30: =IF(H$4="","",ABS(H24/H$4)) -> 0.036421579 | I30: =IF(I$4="","",ABS(I24/I$4)) -> 0.04242531 | J30: =IF(J$4="","",ABS(J24/J$4)) -> 0.038121529 | K30: =IF(K$4="","",ABS(K24/K$4)) -> 0.079206875 | L30: =IF(L$4="","",ABS(L24/L$4)) -> 0.064624217 | M30: =IF(M$4="","",ABS(M24/M$4)) -> 0.056595507 | N30: =IF(N$4="","",ABS(N24/N$4)) -> 0.05951689 | ... Q30: =IF(Q$4="","",ABS(Q24/Q$4))
B31: =B25 -> R&D | C31: 0 | G31: =IF(G$4="","",ABS(G25/G$4)) -> 0 | H31: =IF(H$4="","",ABS(H25/H$4)) -> 0 | I31: =IF(I$4="","",ABS(I25/I$4)) -> 0 | J31: =IF(J$4="","",ABS(J25/J$4)) -> 0 | K31: =IF(K$4="","",ABS(K25/K$4)) -> 0 | L31: =IF(L$4="","",ABS(L25/L$4)) -> 0 | M31: =IF(M$4="","",ABS(M25/M$4)) -> 0 | N31: =IF(N$4="","",ABS(N25/N$4)) -> 0 | ... Q31: =IF(Q$4="","",ABS(Q25/Q$4))
B32: Variable Costs | C32: =ABS(C26/$C$4) -> 0.53643826 | G32: =IF(G$4="","",ABS(G26/G$4)) -> 0.50994226 | H32: =IF(H$4="","",ABS(H26/H$4)) -> 0.4480685 | I32: =IF(I$4="","",ABS(I26/I$4)) -> 0.3985087 | J32: =IF(J$4="","",ABS(J26/J$4)) -> 0.41705213 | K32: =IF(K$4="","",ABS(K26/K$4)) -> 0.61154865 | L32: =IF(L$4="","",ABS(L26/L$4)) -> 0.55064523 | M32: =IF(M$4="","",ABS(M26/M$4)) -> 0.54100917 | N32: =IF(N$4="","",ABS(N26/N$4)) -> 0.51935383 | ... Q32: =IF(Q$4="","",ABS(Q26/Q$4))
B34: Fixed Costs
B35: G&A and other Opex | C35: =G35 -> -208899 | G35: =IF(G4="","",Data!C41) -> -208899 | H35: =IF(H4="","",Data!D41) -> -201296 | I35: =IF(I4="","",Data!E41) -> -207812 | J35: =IF(J4="","",Data!F41) -> -207903 | K35: =IF(K4="","",Data!G41) -> -181914 | L35: =IF(L4="","",Data!H41) -> -182291 | M35: =IF(M4="","",Data!I41) -> -205351 | N35: =IF(N4="","",Data!J41) -> -202034 | ... Q35: =IF(Q4="","",Data!M41)
B37: Fixed Costs % of Sales
B38: G&A and other Opex | C38: =ABS(C35/$C$4) -> 0.045898754 | G38: =IF(G$4="","",ABS(G35/G$4)) -> 0.041308879 | H38: =IF(H$4="","",ABS(H35/H$4)) -> 0.034169696 | I38: =IF(I$4="","",ABS(I35/I$4)) -> 0.025297518 | J38: =IF(J$4="","",ABS(J35/J$4)) -> 0.029382186 | K38: =IF(K$4="","",ABS(K35/K$4)) -> 0.045513192 | L38: =IF(L$4="","",ABS(L35/L$4)) -> 0.047112042 | M38: =IF(M$4="","",ABS(M35/M$4)) -> 0.055708409 | N38: =IF(N$4="","",ABS(N35/N$4)) -> 0.058190823 | ... Q38: =IF(Q$4="","",ABS(Q35/Q$4))
B40: Tax % of Pre-tax Profit
B41: Income Tax Rate | C41: 0.25 | E41: Use the marginal tax rate | G41: =IF(G$4="","",-G12/SUM(G8+G9,G10)) -> 0.3082741 | H41: =IF(H$4="","",-H12/SUM(H8+H9,H10)) -> 0.29774594 | I41: =IF(I$4="","",-I12/SUM(I8+I9,I10)) -> 0.27718435 | J41: =IF(J$4="","",-J12/SUM(J8+J9,J10)) -> 0.27260125 | K41: =IF(K$4="","",-K12/SUM(K8+K9,K10)) -> 0.31030045 | L41: =IF(L$4="","",-L12/SUM(L8+L9,L10)) -> 0.29341667 | M41: =IF(M$4="","",-M12/SUM(M8+M9,M10)) -> 0.32812515 | N41: =IF(N$4="","",-N12/SUM(N8+N9,N10)) -> 0.31705451 | ... Q41: =IF(Q$4="","",-Q12/SUM(Q8+Q9,Q10))
B43: Non-operating Income | E43: Notes
B44: Interest
B45: Interest Expense | C45: =-BS!G31*Normalized_FCF!C52 -> -2620.62 | G45: =Data!C51 -> -1746 | H45: =Data!D51 -> -2921 | I45: =Data!E51 -> -1360 | J45: =Data!F51 -> -1275 | K45: =Data!G51 -> 0 | L45: =Data!H51 -> 0 | M45: =Data!I51 -> 0 | N45: =Data!J51 -> 0 | ... Q45: =Data!M51
B46: Operating Interest Income | C46: =BS!D75*C51 -> 12533.131 | G46: =IFERROR(IF(G$4="","",($C$46/$C$47)*G47),0) -> 38558.985 | H46: =IFERROR(IF(H$4="","",($C$46/$C$47)*H47),0) -> 35845.942 | I46: =IFERROR(IF(I$4="","",($C$46/$C$47)*I47),0) -> 22102.982 | J46: =IFERROR(IF(J$4="","",($C$46/$C$47)*J47),0) -> 14363.728 | K46: =IFERROR(IF(K$4="","",($C$46/$C$47)*K47),0) -> 0 | L46: =IFERROR(IF(L$4="","",($C$46/$C$47)*L47),0) -> 0 | M46: =IFERROR(IF(M$4="","",($C$46/$C$47)*M47),0) -> 0 | N46: =IFERROR(IF(N$4="","",($C$46/$C$47)*N47),0) -> 0 | ... Q46: =IFERROR(IF(Q$4="","",($C$46/$C$47)*Q47),0)
B47: From Interest Income | C47: =BS!$C$66*C51 -> 60710.574 | G47: =Data!C52 -> 186780 | H47: =Data!D52 -> 173638 | I47: =Data!E52 -> 107067 | J47: =Data!F52 -> 69578 | K47: =Data!G52 -> 0 | L47: =Data!H52 -> 0 | M47: =Data!I52 -> 0 | N47: =Data!J52 -> 0 | ... Q47: =Data!M52
B48: Net Interest Income | C48: =C45+C46 -> 9912.5106 | G48: =IF(G$4="","",(G45+G46)) -> 36812.985 | H48: =IF(H$4="","",(H45+H46)) -> 32924.942 | I48: =IF(I$4="","",(I45+I46)) -> 20742.982 | J48: =IF(J$4="","",(J45+J46)) -> 13088.728 | K48: =IF(K$4="","",(K45+K46)) -> 0 | L48: =IF(L$4="","",(L45+L46)) -> 0 | M48: =IF(M$4="","",(M45+M46)) -> 0 | N48: =IF(N$4="","",(N45+N46)) -> 0 | ... Q48: =IF(Q$4="","",(Q45+Q46))
B50: % Interest | G50: Latest Asset Value
B51: Interest Yield/Cash | C51: 0.006 | G51: =IF(Normalized_FCF!G4="","",Normalized_FCF!G47/BS!$C$66) -> 0.018459387
B52: Interest Rate/Debt | C52: 0.06 | G52: =IFERROR(ABS(Normalized_FCF!G45/BS!$G$31),0) -> 0.039975273
B53: Pre-tax Profit/Interest Expense | C53: =-C8/C45 -> 725.36634 | G53: =IF(G4="","",-G8/G45) -> 1299.7268 | H53: =IF(H4="","",-H8/H45) -> 1044.2212 | I53: =IF(I4="","",-I8/I45) -> 3480.3456 | J53: =IF(J4="","",-J8/J45) -> 3072.102 | K53: =IF(K4="","",-K8/K45) -> #DIV/0! | L53: =IF(L4="","",-L8/L45) -> #DIV/0! | M53: =IF(M4="","",-M8/M45) -> #DIV/0! | N53: =IF(N4="","",-N8/N45) -> #DIV/0! | ... Q53: =IF(Q4="","",-Q8/Q45)
B55: Non-operating EBIT | G55: Latest Asset Value
B56: Dividend or Interests from FA | C56: =BS!$C67*C64 -> 0 | G56: =Data!C56 -> 0 | H56: =Data!D56 -> 0 | I56: =Data!E56 -> 0 | J56: =Data!F56 -> 0 | K56: =Data!G56 -> 0 | L56: =Data!H56 -> 0 | M56: =Data!I56 -> 0 | N56: =Data!J56 -> 0 | ... Q56: =Data!M56
B57: Share of JV or associate Results | C57: =BS!$C68*C65 -> 0 | G57: =Data!C55 -> 0 | H57: =Data!D55 -> 0 | I57: =Data!E55 -> 0 | J57: =Data!F55 -> 0 | K57: =Data!G55 -> 0 | L57: =Data!H55 -> 0 | M57: =Data!I55 -> 0 | N57: =Data!J55 -> 0 | ... Q57: =Data!M55
B58: Investment property | C58: =BS!$C69*C66 -> 0 | G58: =Data!C57 -> 0 | H58: =Data!D57 -> 0 | I58: =Data!E57 -> 0 | J58: =Data!F57 -> 0 | K58: =Data!G57 -> 0 | L58: =Data!H57 -> 0 | M58: =Data!I57 -> 0 | N58: =Data!J57 -> 0 | ... Q58: =Data!M57
B59: Stable Non-Operating EBIT | C59: =SUM(C56:C58) -> 0 | G59: =IF(G4="","",SUM(G56:G58)) -> 0 | H59: =IF(H4="","",SUM(H56:H58)) -> 0 | I59: =IF(I4="","",SUM(I56:I58)) -> 0 | J59: =IF(J4="","",SUM(J56:J58)) -> 0 | K59: =IF(K4="","",SUM(K56:K58)) -> 0 | L59: =IF(L4="","",SUM(L56:L58)) -> 0 | M59: =IF(M4="","",SUM(M56:M58)) -> 0 | N59: =IF(N4="","",SUM(N56:N58)) -> 0 | ... Q59: =IF(Q4="","",SUM(Q56:Q58))
B60: Other Non-operating Income | C60: 0 | E60: Assume 0 | G60: =Data!C58 -> 71540 | H60: =Data!D58 -> -1970 | I60: =Data!E58 -> -213084 | J60: =Data!F58 -> 146926 | K60: =Data!G58 -> 241907 | L60: =Data!H58 -> 76414 | M60: =Data!I58 -> 153139 | N60: =Data!J58 -> 180886 | ... Q60: =Data!M58
B61: Total Non-Operating EBIT | C61: =C59+C60 -> 0 | G61: =IF(G4="","",G59+G60) -> 71540 | H61: =IF(H4="","",H59+H60) -> -1970 | I61: =IF(I4="","",I59+I60) -> -213084 | J61: =IF(J4="","",J59+J60) -> 146926 | K61: =IF(K4="","",K59+K60) -> 241907 | L61: =IF(L4="","",L59+L60) -> 76414 | M61: =IF(M4="","",M59+M60) -> 153139 | N61: =IF(N4="","",N59+N60) -> 180886 | ... Q61: =IF(Q4="","",Q59+Q60)
B63: Non-operating Asset Yield % | G63: Latest Asset Value
B64: Dividend or Interests from FA | C64: =G64 -> 0 | G64: =IFERROR(G56/BS!$C$67,0) -> 0
B65: JV or associate | C65: =G65 -> 0 | G65: =IFERROR(G57/BS!$C$68,0) -> 0
B66: Investment property | C66: =G66 -> 0 | G66: =IFERROR(G58/BS!$C$69,0) -> 0
B67: Stable Non-Operating EBIT | C67: =C59/BS!C70 -> 0 | G67: =G59/BS!C70 -> 0
B69: P&L & Dividend Analysis | E69: Notes
B70: P&L % Sales
B71: Variable Costs | C71: =ABS(C5/C$4) -> 0.53643826 | G71: =IF(G$4="","",ABS(G5/G$4)) -> 0.50994226 | H71: =IF(H$4="","",ABS(H5/H$4)) -> 0.4480685 | I71: =IF(I$4="","",ABS(I5/I$4)) -> 0.3985087 | J71: =IF(J$4="","",ABS(J5/J$4)) -> 0.41705213 | K71: =IF(K$4="","",ABS(K5/K$4)) -> 0.61154865 | L71: =IF(L$4="","",ABS(L5/L$4)) -> 0.55064523 | M71: =IF(M$4="","",ABS(M5/M$4)) -> 0.54100917 | N71: =IF(N$4="","",ABS(N5/N$4)) -> 0.51935383 | ... Q71: =IF(Q$4="","",ABS(Q5/Q$4))
B72: Contribution Margin | C72: =ABS(C6/C$4) -> 0.46356174 | G72: =IF(G$4="","",ABS(G6/G$4)) -> 0.49005774 | H72: =IF(H$4="","",ABS(H6/H$4)) -> 0.5519315 | I72: =IF(I$4="","",ABS(I6/I$4)) -> 0.6014913 | J72: =IF(J$4="","",ABS(J6/J$4)) -> 0.58294787 | K72: =IF(K$4="","",ABS(K6/K$4)) -> 0.38845135 | L72: =IF(L$4="","",ABS(L6/L$4)) -> 0.44935477 | M72: =IF(M$4="","",ABS(M6/M$4)) -> 0.45899083 | N72: =IF(N$4="","",ABS(N6/N$4)) -> 0.48064617 | ... Q72: =IF(Q$4="","",ABS(Q6/Q$4))
B73: Fixed Costs | C73: =ABS(C7/C$4) -> 0.045898754 | G73: =IF(G$4="","",ABS(G7/G$4)) -> 0.041308879 | H73: =IF(H$4="","",ABS(H7/H$4)) -> 0.034169696 | I73: =IF(I$4="","",ABS(I7/I$4)) -> 0.025297518 | J73: =IF(J$4="","",ABS(J7/J$4)) -> 0.029382186 | K73: =IF(K$4="","",ABS(K7/K$4)) -> 0.045513192 | L73: =IF(L$4="","",ABS(L7/L$4)) -> 0.047112042 | M73: =IF(M$4="","",ABS(M7/M$4)) -> 0.055708409 | N73: =IF(N$4="","",ABS(N7/N$4)) -> 0.058190823 | ... Q73: =IF(Q$4="","",ABS(Q7/Q$4))
B74: Operating EBIT | C74: =ABS(C8/C$4) -> 0.41766298 | G74: =IF(G$4="","",ABS(G8/G$4)) -> 0.44874886 | H74: =IF(H$4="","",ABS(H8/H$4)) -> 0.5177618 | I74: =IF(I$4="","",ABS(I8/I$4)) -> 0.57619378 | J74: =IF(J$4="","",ABS(J8/J$4)) -> 0.55356568 | K74: =IF(K$4="","",ABS(K8/K$4)) -> 0.34293815 | L74: =IF(L$4="","",ABS(L8/L$4)) -> 0.40224273 | M74: =IF(M$4="","",ABS(M8/M$4)) -> 0.40328243 | N74: =IF(N$4="","",ABS(N8/N$4)) -> 0.42245534 | ... Q74: =IF(Q$4="","",ABS(Q8/Q$4))
B75: Non-Operating EBIT | C75: =ABS(C9/C$4) -> 0 | G75: =IF(G$4="","",G9/G$4) -> 0 | H75: =IF(H$4="","",H9/H$4) -> 0 | I75: =IF(I$4="","",I9/I$4) -> 0 | J75: =IF(J$4="","",J9/J$4) -> 0 | K75: =IF(K$4="","",K9/K$4) -> 0 | L75: =IF(L$4="","",L9/L$4) -> 0 | M75: =IF(M$4="","",M9/M$4) -> 0 | N75: =IF(N$4="","",N9/N$4) -> 0 | ... Q75: =IF(Q$4="","",Q9/Q$4)
B76: Net Interest Income | C76: =ABS(C10/C$4) -> 0.0021779515 | G76: =IF(G$4="","",ABS(G10/G$4)) -> 0.0072796095 | H76: =IF(H$4="","",ABS(H10/H$4)) -> 0.0055889598 | I76: =IF(I$4="","",ABS(I10/I$4)) -> 0.0025250993 | J76: =IF(J$4="","",ABS(J10/J$4)) -> 0.001849783 | K76: =IF(K$4="","",ABS(K10/K$4)) -> 0 | L76: =IF(L$4="","",ABS(L10/L$4)) -> 0 | M76: =IF(M$4="","",ABS(M10/M$4)) -> 0 | N76: =IF(N$4="","",ABS(N10/N$4)) -> 0 | ... Q76: =IF(Q$4="","",ABS(Q10/Q$4))
B77: Pre-tax Profit | C77: =C11/C4 -> 0.41984093 | G77: =IF(G$4="","",G11/G$4) -> 0.45602847 | H77: =IF(H$4="","",H11/H$4) -> 0.52335076 | I77: =IF(I$4="","",I11/I$4) -> 0.57871888 | J77: =IF(J$4="","",J11/J$4) -> 0.55541546 | K77: =IF(K$4="","",K11/K$4) -> 0.34293815 | L77: =IF(L$4="","",L11/L$4) -> 0.40224273 | M77: =IF(M$4="","",M11/M$4) -> 0.40328243 | N77: =IF(N$4="","",N11/N$4) -> 0.42245534 | ... Q77: =IF(Q$4="","",Q11/Q$4)
B78: Income Tax | C78: =ABS(C12/C$4) -> 0.10496023 | G78: =IF(G$4="","",ABS(G12/G$4)) -> 0.14058177 | H78: =IF(H$4="","",ABS(H12/H$4)) -> 0.15582557 | I78: =IF(I$4="","",ABS(I12/I$4)) -> 0.16041182 | J78: =IF(J$4="","",ABS(J12/J$4)) -> 0.15140695 | K78: =IF(K$4="","",ABS(K12/K$4)) -> 0.10641386 | L78: =IF(L$4="","",ABS(L12/L$4)) -> 0.11802472 | M78: =IF(M$4="","",ABS(M12/M$4)) -> 0.13232711 | N78: =IF(N$4="","",ABS(N12/N$4)) -> 0.13394137 | ... Q78: =IF(Q$4="","",ABS(Q12/Q$4))
B79: =B13 -> NCI’s Share of Profits | C79: =MIN(BS!C62,MAX(G79:K79)) -> 0.073819875 | G79: =IF(G$4="","",-G13/G$4) -> 0.063458375 | H79: =IF(H$4="","",-H13/H$4) -> 0.069883933 | I79: =IF(I$4="","",-I13/I$4) -> 0.072160837 | J79: =IF(J$4="","",-J13/J$4) -> 0.073819875 | K79: =IF(K$4="","",-K13/K$4) -> 0.026830952 | L79: =IF(L$4="","",-L13/L$4) -> 0.0092336924 | M79: =IF(M$4="","",-M13/M$4) -> 0.013954841 | N79: =IF(N$4="","",-N13/N$4) -> 0.029359819 | ... Q79: =IF(Q$4="","",-Q13/Q$4)
B80: After-tax Profit | C80: =ABS(C14/C$4) -> 0.24106082 | G80: =IF(G$4="","",ABS(G14/G$4)) -> 0.25198833 | H80: =IF(H$4="","",ABS(H14/H$4)) -> 0.29764127 | I80: =IF(I$4="","",ABS(I14/I$4)) -> 0.34614623 | J80: =IF(J$4="","",ABS(J14/J$4)) -> 0.33018864 | K80: =IF(K$4="","",ABS(K14/K$4)) -> 0.20969334 | L80: =IF(L$4="","",ABS(L14/L$4)) -> 0.27498431 | M80: =IF(M$4="","",ABS(M14/M$4)) -> 0.25700048 | N80: =IF(N$4="","",ABS(N14/N$4)) -> 0.25915415 | ... Q80: =IF(Q$4="","",ABS(Q14/Q$4))
B81: Add Back D&A | C81: =ABS(C15/C$4) -> 0 | G81: =IF(G$4="","",G15/G$4) -> 0 | H81: =IF(H$4="","",H15/H$4) -> 0 | I81: =IF(I$4="","",I15/I$4) -> 0 | J81: =IF(J$4="","",J15/J$4) -> 0 | K81: =IF(K$4="","",K15/K$4) -> 0 | L81: =IF(L$4="","",L15/L$4) -> 0 | M81: =IF(M$4="","",M15/M$4) -> 0 | N81: =IF(N$4="","",N15/N$4) -> 0 | ... Q81: =IF(Q$4="","",Q15/Q$4)
B82: Maintenance Capex | C82: =MAX(AVERAGE(G82:J82),C81) -> 0 | E82: Historical Average or D&A | G82: =IF(G$4="","",-G16/G$4) -> 0 | H82: =IF(H$4="","",-H16/H$4) -> 0 | I82: =IF(I$4="","",-I16/I$4) -> 0 | J82: =IF(J$4="","",-J16/J$4) -> 0 | K82: =IF(K$4="","",-K16/K$4) -> 0 | L82: =IF(L$4="","",-L16/L$4) -> 0 | M82: =IF(M$4="","",-M16/M$4) -> 0 | N82: =IF(N$4="","",-N16/N$4) -> 0 | ... Q82: =IF(Q$4="","",-Q16/Q$4)
B83: WCInv | C83: 0 | E83: =E17 -> WCInv is by default excluded
B84: Net Borrowing | C84: 0 | E84: =E18 -> Net borrowing is excluded
B85: Total FCFE | C85: =ABS(C19/C$4) -> 0.24106082 | G85: =IF(G$4="","",ABS(G19/G$4)) -> 0.25198833 | H85: =IF(H$4="","",ABS(H19/H$4)) -> 0.29764127 | I85: =IF(I$4="","",ABS(I19/I$4)) -> 0.34614623 | J85: =IF(J$4="","",ABS(J19/J$4)) -> 0.33018864 | K85: =IF(K$4="","",ABS(K19/K$4)) -> 0.20969334 | L85: =IF(L$4="","",ABS(L19/L$4)) -> 0.27498431 | M85: =IF(M$4="","",ABS(M19/M$4)) -> 0.25700048 | N85: =IF(N$4="","",ABS(N19/N$4)) -> 0.25915415 | ... Q85: =IF(Q$4="","",ABS(Q19/Q$4))
B87: Dividends
B88: ="Dividend per share ("&Market_currency&")" -> Dividend per share (HKD) | C88: =G88 -> 0.3 | G88: =Data!C65 -> 0.3 | H88: =Data!D65 -> 0.28 | I88: =Data!E65 -> 0.43 | J88: =Data!F65 -> 0 | K88: =Data!G65 -> 0 | L88: =Data!H65 -> 0 | M88: =Data!I65 -> 0 | N88: =Data!J65 -> 0 | ... Q88: =Data!M65
B89: ="Dividend ("&Market_currency&")" -> Dividend (HKD) | C89: =C88*Common_Shares/scaling_factor -> 1527319.7 | G89: =IF(G$4="","",G88*Common_Shares/scaling_factor) -> 1527319.7 | H89: =IF(H$4="","",H88*Common_Shares/scaling_factor) -> 1425498.4 | I89: =IF(I$4="","",I88*Common_Shares/scaling_factor) -> 2189158.3 | J89: =IF(J$4="","",J88*Common_Shares/scaling_factor) -> 0 | K89: =IF(K$4="","",K88*Common_Shares/scaling_factor) -> 0 | L89: =IF(L$4="","",L88*Common_Shares/scaling_factor) -> 0 | M89: =IF(M$4="","",M88*Common_Shares/scaling_factor) -> 0 | N89: =IF(N$4="","",N88*Common_Shares/scaling_factor) -> 0 | ... Q89: =IF(Q$4="","",Q88*Common_Shares/scaling_factor)
B90: Payout Ratio | C90: =C88/(C19*scaling_factor/Common_Shares) -> 1.3920918 | G90: =IF(G$4="","",G88/(G19*scaling_factor/Common_Shares)) -> 1.1985512 | H90: =IF(H$4="","",H88/(H19*scaling_factor/Common_Shares)) -> 0.81297943 | I90: =IF(I$4="","",I88/(I19*scaling_factor/Common_Shares)) -> 0.76988321 | J90: =IF(J$4="","",J88/(J19*scaling_factor/Common_Shares)) -> 0 | K90: =IF(K$4="","",K88/(K19*scaling_factor/Common_Shares)) -> 0 | L90: =IF(L$4="","",L88/(L19*scaling_factor/Common_Shares)) -> 0 | M90: =IF(M$4="","",M88/(M19*scaling_factor/Common_Shares)) -> 0 | N90: =IF(N$4="","",N88/(N19*scaling_factor/Common_Shares)) -> 0 | ... Q90: =IF(Q$4="","",Q88/(Q19*scaling_factor/Common_Shares))
B91: Dividend tax rate | C91: 0.1
B92: Dividend after tax Yield | C92: =(C88*(1-dividend_tax_rate))/Market_Price -> 0.085443038 | G92: =IF(G$4="","",(G88*(1-dividend_tax_rate))/Market_Price) -> 0.085443038 | H92: =IF(H$4="","",(H88*(1-dividend_tax_rate))/Market_Price) -> 0.079746835 | I92: =IF(I$4="","",(I88*(1-dividend_tax_rate))/Market_Price) -> 0.12246835 | J92: =IF(J$4="","",(J88*(1-dividend_tax_rate))/Market_Price) -> 0 | K92: =IF(K$4="","",(K88*(1-dividend_tax_rate))/Market_Price) -> 0 | L92: =IF(L$4="","",(L88*(1-dividend_tax_rate))/Market_Price) -> 0 | M92: =IF(M$4="","",(M88*(1-dividend_tax_rate))/Market_Price) -> 0 | N92: =IF(N$4="","",(N88*(1-dividend_tax_rate))/Market_Price) -> 0 | ... Q92: =IF(Q$4="","",(Q88*(1-dividend_tax_rate))/Market_Price)
B94: YoY %
B95: Sales | C95: =C4/G4-1 -> -0.1 | G95: =IF(H4="","",G4/H4-1) -> -0.1415818 | H95: =IF(I4="","",H4/I4-1) -> -0.28286433 | I95: =IF(J4="","",I4/J4-1) -> 0.1609568 | J95: =IF(K4="","",J4/K4-1) -> 0.77030391 | K95: =IF(L4="","",K4/L4-1) -> 0.032988586 | L95: =IF(M4="","",L4/M4-1) -> 0.049680753 | M95: =IF(N4="","",M4/N4-1) -> 0.061710488 | N95: =IF(O4="","",N4/O4-1) -> 0.91831083 | ... Q95: =IF(R4="","",Q4/R4-1)
B96: Pre-tax Profit | C96: =C11/G11-1 -> -0.17141832 | G96: =IF(H5="","",G11/H11-1) -> -0.25200617 | H96: =IF(I5="","",H11/I11-1) -> -0.35147528 | I96: =IF(J5="","",I11/J11-1) -> 0.20966675 | J96: =IF(K5="","",J11/K11-1) -> 1.8671472 | K96: =IF(L5="","",K11/L11-1) -> -0.11930987 | L96: =IF(M5="","",L11/M11-1) -> 0.046974579 | M96: =IF(N5="","",M11/N11-1) -> 0.013525307 | N96: =IF(O5="","",N11/O11-1) -> 5.2182333 | ... Q96: =IF(R5="","",Q11/R11-1)
B98: Operating Efficiency Analysis | E98: Notes
B99: Balance Sheet | G99: Latest Asset Value
B100: Total Assets | C100: =BS!G32 -> 22948823 | G100: =IF(G$4="","",G104+G103) -> 22948823 | H100: =IF(H$4="","",H104+H103) -> 22491544 | I100: =IF(I$4="","",I104+I103) -> 23463484 | J100: =IF(J$4="","",J104+J103) -> 24779977 | K100: =IF(K$4="","",K104+K103) -> 21433646 | L100: =IF(L$4="","",L104+L103) -> 21472710 | M100: =IF(M$4="","",M104+M103) -> 21251042 | N100: =IF(N$4="","",N104+N103) -> 21694645 | ... Q100: =IF(Q$4="","",Q104+Q103)
B101: Incl. AR | C101: =BS!C4 -> 537904 | G101: =IF(G$4="","",Data!D77) -> 687833 | H101: =IF(H$4="","",Data!E77) -> 2889765 | I101: =IF(I$4="","",Data!F77) -> 3144251 | J101: =IF(J$4="","",Data!G77) -> 2049144 | K101: =IF(K$4="","",Data!H77) -> 1797319 | L101: =IF(L$4="","",Data!I77) -> 0 | M101: =IF(M$4="","",Data!J77) -> 0 | N101: =IF(N$4="","",Data!K77) -> 0 | ... Q101: =IF(Q$4="","",Data!N77)
B102: Incl. Inventory | C102: =BS!C6+BS!C7 -> 137638 | G102: =IF(G$4="","",Data!D78) -> 125636 | H102: =IF(H$4="","",Data!E78) -> 42046 | I102: =IF(I$4="","",Data!F78) -> 142658 | J102: =IF(J$4="","",Data!G78) -> 131170 | K102: =IF(K$4="","",Data!H78) -> 123530 | L102: =IF(L$4="","",Data!I78) -> 0 | M102: =IF(M$4="","",Data!J78) -> 0 | N102: =IF(N$4="","",Data!K78) -> 0 | ... Q102: =IF(Q$4="","",Data!N78)
B103: Total Liabilities | C103: =BS!G30 -> 4047566 | G103: =Data!C79 -> 4047566 | H103: =Data!D79 -> 4021026 | I103: =Data!E79 -> 4786265 | J103: =Data!F79 -> 5631759 | K103: =Data!G79 -> 4142576 | L103: =Data!H79 -> 4426398 | M103: =Data!I79 -> 4475236 | N103: =Data!J79 -> 4318962 | ... Q103: =Data!M79
B104: Total Equity | C104: =BS!G27 -> 18901257 | G104: =Data!C80 -> 18901257 | H104: =Data!D80 -> 18470518 | I104: =Data!E80 -> 18677219 | J104: =Data!F80 -> 19148218 | K104: =Data!G80 -> 17291070 | L104: =Data!H80 -> 17046312 | M104: =Data!I80 -> 16775806 | N104: =Data!J80 -> 17375683 | ... Q104: =Data!M80
B106: Operating Asset % of Sales | G106: Latest Asset Value
B107: AR | C107: =C101/C$4 -> 0.11818689 | G107: =IF(G$4="","",G101/G$4) -> 0.13601602 | H107: =IF(H$4="","",H101/H$4) -> 0.4905333 | I107: =IF(I$4="","",I101/I$4) -> 0.38275819 | J107: =IF(J$4="","",J101/J$4) -> 0.28959818 | K107: =IF(K$4="","",K101/K$4) -> 0.44967251 | L107: =IF(L$4="","",L101/L$4) -> 0 | M107: =IF(M$4="","",M101/M$4) -> 0 | N107: =IF(N$4="","",N101/N$4) -> 0 | ... Q107: =IF(Q$4="","",Q101/Q$4)
B108: Inventory | C108: =C102/C$4 -> 0.030241469 | G108: =IF(G$4="","",G102/G$4) -> 0.024843979 | H108: =IF(H$4="","",H102/H$4) -> 0.0071372457 | I108: =IF(I$4="","",I102/I$4) -> 0.017366145 | J108: =IF(J$4="","",J102/J$4) -> 0.018537786 | K108: =IF(K$4="","",K102/K$4) -> 0.030906058 | L108: =IF(L$4="","",L102/L$4) -> 0 | M108: =IF(M$4="","",M102/M$4) -> 0 | N108: =IF(N$4="","",N102/N$4) -> 0 | ... Q108: =IF(Q$4="","",Q102/Q$4)
B109: Properties held for sale | C109: =BS!$G$38/C$4 -> 0 | G109: =BS!$G$38/G$4 -> 0
B111: Cash Flow Statement
B112: CFO/Net Income | G112: =IF(G$4="","",Data!C$22/Data!C15) -> 1.3057337 | H112: =IF(H$4="","",Data!D$22/Data!D15) -> 1.974417 | I112: =IF(I$4="","",Data!E$22/Data!E15) -> 1.1630549 | J112: =IF(J$4="","",Data!F$22/Data!F15) -> 1.2604711 | K112: =IF(K$4="","",Data!G$22/Data!G15) -> 0.70481764 | L112: =IF(L$4="","",Data!H$22/Data!H15) -> 1.6343627 | M112: =IF(M$4="","",Data!I$22/Data!I15) -> 1.4261751 | N112: =IF(N$4="","",Data!J$22/Data!J15) -> 1.2985902 | ... Q112: =IF(Q$4="","",Data!M$22/Data!M15)
B113: CFO/FCFE | G113: =IF(G$4="","",Data!C$22/G19) -> 1.8597385 | H113: =IF(H$4="","",Data!D$22/H19) -> 2.5909355 | I113: =IF(I$4="","",Data!E$22/I19) -> 1.3531121 | J113: =IF(J$4="","",Data!F$22/J19) -> 1.6513284 | K113: =IF(K$4="","",Data!G$22/K19) -> 0.99842985 | L113: =IF(L$4="","",Data!H$22/L19) -> 1.8066192 | M113: =IF(M$4="","",Data!I$22/M19) -> 1.7341561 | N113: =IF(N$4="","",Data!J$22/N19) -> 1.7067739 | ... Q113: =IF(Q$4="","",Data!M$22/Q19)
B115: ROE | G115: =IFERROR(IF(#REF!*G117*(1/#REF!)=G119,"","Error"),"") | H115: =IFERROR(IF(#REF!*H117*(1/#REF!)=H119,"","Error"),"") | I115: =IFERROR(IF(#REF!*I117*(1/#REF!)=I119,"","Error"),"") | J115: =IFERROR(IF(#REF!*J117*(1/#REF!)=J119,"","Error"),"") | K115: =IFERROR(IF(#REF!*K117*(1/#REF!)=K119,"","Error"),"") | L115: =IFERROR(IF(#REF!*L117*(1/#REF!)=L119,"","Error"),"") | M115: =IFERROR(IF(#REF!*M117*(1/#REF!)=M119,"","Error"),"") | N115: =IFERROR(IF(#REF!*N117*(1/#REF!)=N119,"","Error"),"") | ... Q115: =IFERROR(IF(#REF!*Q117*(1/#REF!)=Q119,"","Error"),"")
B116: Pre-tax Profit/Sales | C116: =C77 -> 0.41984093 | G116: =IF(G4="","",G77) -> 0.45602847 | H116: =IF(H4="","",H77) -> 0.52335076 | I116: =IF(I4="","",I77) -> 0.57871888 | J116: =IF(J4="","",J77) -> 0.55541546 | K116: =IF(K4="","",K77) -> 0.34293815 | L116: =IF(L4="","",L77) -> 0.40224273 | M116: =IF(M4="","",M77) -> 0.40328243 | N116: =IF(N4="","",N77) -> 0.42245534 | ... Q116: =IF(Q4="","",Q77)
...

Sheet DCF
B2: No-Growth DCF Valuation
B3: No-Growth DCF | C3: =scaling_factor -> 1000 | E3: FV adjustments | H3: Normalized Values
B4: Normalized FCFE | C4: =Normalized_FCF!C19 -> 1097140.1 | D4: =Reporting_currency -> HKD | E4: Interest-bearing Debt | F4: =-BS!G31 -> -43677 | G4: =Reporting_currency -> HKD | H4: Revenues | I4: =Normalized_FCF!C4 -> 4551300
B5: /Equity Cost of Capital | C5: =Equity_Cost -> 0.0725 | E5: Non-operating Cash | F5: =BS!D66 -> 8029573.9 | G5: =Reporting_currency -> HKD | H5: Fixed Costs | I5: =Normalized_FCF!C7 -> -208899
B6: Stable Income Value | C6: =(C4*(1+Terminal_Growth))/(Equity_Cost-Terminal_Growth) -> 15132967 | D6: =Reporting_currency -> HKD | E6: Other Non-op. Assets | F6: =BS!H42 -> 263512.2 | G6: =Reporting_currency -> HKD | H6: Other Income, includes | I6: =I7+I8 -> 9912.5106
B7: + FV adjustments | C7: =F7 -> 8249409.1 | E7: FV adjustments | F7: =SUM(F4:F6) -> 8249409.1 | G7: =Reporting_currency -> HKD | H7: Non-op EBIT | I7: =Normalized_FCF!C9 -> 0
B8: Equity Value | C8: =C6+C7 -> 23382376 | D8: =Reporting_currency -> HKD | E8: FV adj. per share | F8: =FV_adjustments*scaling_factor/Common_Shares*Exchange_Rate -> 1.6203698 | G8: =Market_currency -> HKD | H8: =Normalized_FCF!B10 -> Net Interest Income | I8: =Normalized_FCF!C10 -> 9912.5106
B9: ="*"&Thesis!E15 -> *HKD | C9: =Exchange_Rate -> 1 | D9: =Thesis!E15 -> HKD | H9: =Normalized_FCF!B79 -> NCI’s Share of Profits | I9: =Normalized_FCF!C79 -> 0.073819875
B10: Value | C10: =C8*Exchange_Rate -> 23382376 | D10: =Market_currency -> HKD | H10: Tax rate | I10: =Normalized_FCF!C41 -> 0.25
B11: Value per share | C11: =(C10*scaling_factor)/Common_Shares -> 4.5928254 | D11: =Market_currency -> HKD
B13: Growth DCF Valuation
B14: Stage | C14: I | E14: Stage | F14: =IF(F17=C17,"I","II") -> I | H14: Terminal Stage
B15: High g Period (HGP) | C15: =Scenarios!C45 -> 3 | E15: =IF(F14="II","Change year","Terminal Year") -> Terminal Year | F15: =IF(F14="II",_xlfn.CEILING.MATH(C15/2),C15+1) -> 4 | H15: Terminal g Rate: | I15: =Terminal_Growth -> 0
B16: High g Rate (HGR) | C16: =Scenarios!C46 -> 0.0013 | E16: High Growth Rate_II | F16: =Scenarios!C41 -> 0.0013
B17: Contribution Margin | C17: =Normalized_FCF!C32 -> 0.53643826 | E17: Contribution Margin_II | F17: =Scenarios!C40 -> 0.53643826 | H17: Output
B18: D&A - maint. Capx | C18: =Normalized_FCF!C81-Normalized_FCF!C82 -> 0 | E18: D&A - maint. Capx | F18: =IF(F14="II",C18/2,C18) -> 0 | H18: Value Per Share | I18: =(L52+FV_adjustments)*Exchange_Rate/Common_Shares*scaling_factor -> 4.603592 | J18: =Market_currency -> HKD
A20: Stage | B20: Year | C20: Revenues | D20: Growth Rates | E20: Contribution Margin | F20: Fixed Costs | G20: EBIT | H20: =B18 -> D&A - maint. Capx | I20: FCFE/TV | J20: FCFE g | K20: Disc. Factor | L20: PV of FCFE/TV
A21: =IF($C$15<B21,"",IF(B21>=$F$15,"II","I")) -> I | B21: 1 | C21: =I4*(1+D21) -> 4557216.7 | D21: =IF(A21="",0,IF(A21="I",$C$16,$F$16)) -> 0.0013 | E21: =$C$17 -> 0.53643826 | F21: =I5*(1+D21) -> -209170.57 | G21: =C21*(1-E21)+F21+$I$6 -> 1913293.2 | H21: =IF(A21="",0%,IF(A21="I",$C$18,$F$18)) -> 0 | I21: =(G21*(1-$I$10)+C21*(H21-$I$9)) -> 1098556.7 | J21: =I21/C4-1 -> 0.001291191 | K21: =IF($C$15<B21,0,1/(1+Equity_Cost)^B21) -> 0.93240093 | L21: =I21*K21 -> 1024295.3
A22: =IF($C$15<B22,"",IF(B22>=$F$15,"II","I")) -> I | B22: 2 | C22: =IF(A22="",0,C21*(1+D22)) -> 4563141.1 | D22: =IF(A22="",0,IF(A22="I",$C$16,$F$16)) -> 0.0013 | E22: =IF($C$15<B22,0,IF(B22>=$F$15,$F$17,$C$17)) -> 0.53643826 | F22: =IF(A22="",0,F21*(1+D22)) -> -209442.49 | G22: =IF(A22="", 0,C22*(1-E22)+F22+$I$6) -> 1915767.6 | H22: =IF(A22="",0%,IF(A22="I",$C$18,$F$18)) -> 0 | I22: =IF(A22="", 0,G22*(1-$I$10)+C22*(H22-$I$9)) -> 1099975.2 | J22: =IF(A22="", 0,I22/I21-1) -> 0.0012912024 | K22: =IF($C$15<B22,0,1/(1+Equity_Cost)^B22) -> 0.8693715 | L22: =I22*K22 -> 956287.09
A23: =IF($C$15<B23,"",IF(B23>=$F$15,"II","I")) -> I | B23: 3 | C23: =IF(A23="",0,C22*(1+D23)) -> 4569073.2 | D23: =IF(A23="",0,IF(A23="I",$C$16,$F$16)) -> 0.0013 | E23: =IF($C$15<B23,0,IF(B23>=$F$15,$F$17,$C$17)) -> 0.53643826 | F23: =IF(A23="",0,F22*(1+D23)) -> -209714.77 | G23: =IF(A23="", 0,C23*(1-E23)+F23+$I$6) -> 1918245.2 | H23: =IF(A23="",0%,IF(A23="I",$C$18,$F$18)) -> 0 | I23: =IF(A23="", 0,G23*(1-$I$10)+C23*(H23-$I$9)) -> 1101395.5 | J23: =IF(A23="", 0,I23/I22-1) -> 0.0012912137 | K23: =IF($C$15<B23,0,1/(1+Equity_Cost)^B23) -> 0.8106028 | L23: =I23*K23 -> 892794.28
A24: =IF($C$15<B24,"",IF(B24>=$F$15,"II","I")) | B24: 4 | C24: =IF(A24="",0,C23*(1+D24)) -> 0 | D24: =IF(A24="",0,IF(A24="I",$C$16,$F$16)) -> 0 | E24: =IF($C$15<B24,0,IF(B24>=$F$15,$F$17,$C$17)) -> 0 | F24: =IF(A24="",0,F23*(1+D24)) -> 0 | G24: =IF(A24="", 0,C24*(1-E24)+F24+$I$6) -> 0 | H24: =IF(A24="",0%,IF(A24="I",$C$18,$F$18)) -> 0 | I24: =IF(A24="", 0,G24*(1-$I$10)+C24*(H24-$I$9)) -> 0 | J24: =IF(A24="", 0,I24/I23-1) -> 0 | K24: =IF($C$15<B24,0,1/(1+Equity_Cost)^B24) -> 0 | L24: =I24*K24 -> 0
A25: =IF($C$15<B25,"",IF(B25>=$F$15,"II","I")) | B25: 5 | C25: =IF(A25="",0,C24*(1+D25)) -> 0 | D25: =IF(A25="",0,IF(A25="I",$C$16,$F$16)) -> 0 | E25: =IF($C$15<B25,0,IF(B25>=$F$15,$F$17,$C$17)) -> 0 | F25: =IF(A25="",0,F24*(1+D25)) -> 0 | G25: =IF(A25="", 0,C25*(1-E25)+F25+$I$6) -> 0 | H25: =IF(A25="",0%,IF(A25="I",$C$18,$F$18)) -> 0 | I25: =IF(A25="", 0,G25*(1-$I$10)+C25*(H25-$I$9)) -> 0 | J25: =IF(A25="", 0,I25/I24-1) -> 0 | K25: =IF($C$15<B25,0,1/(1+Equity_Cost)^B25) -> 0 | L25: =I25*K25 -> 0
A26: =IF($C$15<B26,"",IF(B26>=$F$15,"II","I")) | B26: 6 | C26: =IF(A26="",0,C25*(1+D26)) -> 0 | D26: =IF(A26="",0,IF(A26="I",$C$16,$F$16)) -> 0 | E26: =IF($C$15<B26,0,IF(B26>=$F$15,$F$17,$C$17)) -> 0 | F26: =IF(A26="",0,F25*(1+D26)) -> 0 | G26: =IF(A26="", 0,C26*(1-E26)+F26+$I$6) -> 0 | H26: =IF(A26="",0%,IF(A26="I",$C$18,$F$18)) -> 0 | I26: =IF(A26="", 0,G26*(1-$I$10)+C26*(H26-$I$9)) -> 0 | J26: =IF(A26="", 0,I26/I25-1) -> 0 | K26: =IF($C$15<B26,0,1/(1+Equity_Cost)^B26) -> 0 | L26: =I26*K26 -> 0
A27: =IF($C$15<B27,"",IF(B27>=$F$15,"II","I")) | B27: 7 | C27: =IF(A27="",0,C26*(1+D27)) -> 0 | D27: =IF(A27="",0,IF(A27="I",$C$16,$F$16)) -> 0 | E27: =IF($C$15<B27,0,IF(B27>=$F$15,$F$17,$C$17)) -> 0 | F27: =IF(A27="",0,F26*(1+D27)) -> 0 | G27: =IF(A27="", 0,C27*(1-E27)+F27+$I$6) -> 0 | H27: =IF(A27="",0%,IF(A27="I",$C$18,$F$18)) -> 0 | I27: =IF(A27="", 0,G27*(1-$I$10)+C27*(H27-$I$9)) -> 0 | J27: =IF(A27="", 0,I27/I26-1) -> 0 | K27: =IF($C$15<B27,0,1/(1+Equity_Cost)^B27) -> 0 | L27: =I27*K27 -> 0
A28: =IF($C$15<B28,"",IF(B28>=$F$15,"II","I")) | B28: 8 | C28: =IF(A28="",0,C27*(1+D28)) -> 0 | D28: =IF(A28="",0,IF(A28="I",$C$16,$F$16)) -> 0 | E28: =IF($C$15<B28,0,IF(B28>=$F$15,$F$17,$C$17)) -> 0 | F28: =IF(A28="",0,F27*(1+D28)) -> 0 | G28: =IF(A28="", 0,C28*(1-E28)+F28+$I$6) -> 0 | H28: =IF(A28="",0%,IF(A28="I",$C$18,$F$18)) -> 0 | I28: =IF(A28="", 0,G28*(1-$I$10)+C28*(H28-$I$9)) -> 0 | J28: =IF(A28="", 0,I28/I27-1) -> 0 | K28: =IF($C$15<B28,0,1/(1+Equity_Cost)^B28) -> 0 | L28: =I28*K28 -> 0
A29: =IF($C$15<B29,"",IF(B29>=$F$15,"II","I")) | B29: 9 | C29: =IF(A29="",0,C28*(1+D29)) -> 0 | D29: =IF(A29="",0,IF(A29="I",$C$16,$F$16)) -> 0 | E29: =IF($C$15<B29,0,IF(B29>=$F$15,$F$17,$C$17)) -> 0 | F29: =IF(A29="",0,F28*(1+D29)) -> 0 | G29: =IF(A29="", 0,C29*(1-E29)+F29+$I$6) -> 0 | H29: =IF(A29="",0%,IF(A29="I",$C$18,$F$18)) -> 0 | I29: =IF(A29="", 0,G29*(1-$I$10)+C29*(H29-$I$9)) -> 0 | J29: =IF(A29="", 0,I29/I28-1) -> 0 | K29: =IF($C$15<B29,0,1/(1+Equity_Cost)^B29) -> 0 | L29: =I29*K29 -> 0
A30: =IF($C$15<B30,"",IF(B30>=$F$15,"II","I")) | B30: 10 | C30: =IF(A30="",0,C29*(1+D30)) -> 0 | D30: =IF(A30="",0,IF(A30="I",$C$16,$F$16)) -> 0 | E30: =IF($C$15<B30,0,IF(B30>=$F$15,$F$17,$C$17)) -> 0 | F30: =IF(A30="",0,F29*(1+D30)) -> 0 | G30: =IF(A30="", 0,C30*(1-E30)+F30+$I$6) -> 0 | H30: =IF(A30="",0%,IF(A30="I",$C$18,$F$18)) -> 0 | I30: =IF(A30="", 0,G30*(1-$I$10)+C30*(H30-$I$9)) -> 0 | J30: =IF(A30="", 0,I30/I29-1) -> 0 | K30: =IF($C$15<B30,0,1/(1+Equity_Cost)^B30) -> 0 | L30: =I30*K30 -> 0
A31: =IF($C$15<B31,"",IF(B31>=$F$15,"II","I")) | B31: 11 | C31: =IF(A31="",0,C30*(1+D31)) -> 0 | D31: =IF(A31="",0,IF(A31="I",$C$16,$F$16)) -> 0 | E31: =IF($C$15<B31,0,IF(B31>=$F$15,$F$17,$C$17)) -> 0 | F31: =IF(A31="",0,F30*(1+D31)) -> 0 | G31: =IF(A31="", 0,C31*(1-E31)+F31+$I$6) -> 0 | H31: =IF(A31="",0%,IF(A31="I",$C$18,$F$18)) -> 0 | I31: =IF(A31="", 0,G31*(1-$I$10)+C31*(H31-$I$9)) -> 0 | J31: =IF(A31="", 0,I31/I30-1) -> 0 | K31: =IF($C$15<B31,0,1/(1+Equity_Cost)^B31) -> 0 | L31: =I31*K31 -> 0
A32: =IF($C$15<B32,"",IF(B32>=$F$15,"II","I")) | B32: 12 | C32: =IF(A32="",0,C31*(1+D32)) -> 0 | D32: =IF(A32="",0,IF(A32="I",$C$16,$F$16)) -> 0 | E32: =IF($C$15<B32,0,IF(B32>=$F$15,$F$17,$C$17)) -> 0 | F32: =IF(A32="",0,F31*(1+D32)) -> 0 | G32: =IF(A32="", 0,C32*(1-E32)+F32+$I$6) -> 0 | H32: =IF(A32="",0%,IF(A32="I",$C$18,$F$18)) -> 0 | I32: =IF(A32="", 0,G32*(1-$I$10)+C32*(H32-$I$9)) -> 0 | J32: =IF(A32="", 0,I32/I31-1) -> 0 | K32: =IF($C$15<B32,0,1/(1+Equity_Cost)^B32) -> 0 | L32: =I32*K32 -> 0
A33: =IF($C$15<B33,"",IF(B33>=$F$15,"II","I")) | B33: 13 | C33: =IF(A33="",0,C32*(1+D33)) -> 0 | D33: =IF(A33="",0,IF(A33="I",$C$16,$F$16)) -> 0 | E33: =IF($C$15<B33,0,IF(B33>=$F$15,$F$17,$C$17)) -> 0 | F33: =IF(A33="",0,F32*(1+D33)) -> 0 | G33: =IF(A33="", 0,C33*(1-E33)+F33+$I$6) -> 0 | H33: =IF(A33="",0%,IF(A33="I",$C$18,$F$18)) -> 0 | I33: =IF(A33="", 0,G33*(1-$I$10)+C33*(H33-$I$9)) -> 0 | J33: =IF(A33="", 0,I33/I32-1) -> 0 | K33: =IF($C$15<B33,0,1/(1+Equity_Cost)^B33) -> 0 | L33: =I33*K33 -> 0
... A50: =IF($C$15<B50,"",IF(B50>=$F$15,"II","I")) | B50: 30 | C50: =IF(A50="",0,C49*(1+D50)) -> 0 | D50: =IF(A50="",0,IF(A50="I",$C$16,$F$16)) -> 0 | E50: =IF($C$15<B50,0,IF(B50>=$F$15,$F$17,$C$17)) -> 0 | F50: =IF(A50="",0,F49*(1+D50)) -> 0 | G50: =IF(A50="", 0,C50*(1-E50)+F50+$I$6) -> 0 | H50: =IF(A50="",0%,IF(A50="I",$C$18,$F$18)) -> 0 | I50: =IF(A50="", 0,G50*(1-$I$10)+C50*(H50-$I$9)) -> 0 | J50: =IF(A50="", 0,I50/I49-1) -> 0 | K50: =IF($C$15<B50,0,1/(1+Equity_Cost)^B50) -> 0 | L50: =I50*K50 -> 0
A51: T | B51: =C15+1 -> 4 | C51: =VLOOKUP(C15,B21:C50,2,FALSE)*(1+Terminal_Growth) -> 4569073.2 | D51: =Terminal_Growth -> 0 | E51: =F17 -> 0.53643826 | F51: =VLOOKUP(C15,B21:F50,5,FALSE)*(1+Terminal_Growth) -> -209714.77 | G51: =C51*(1-E51)+F51+$I$6 -> 1918245.2 | H51: =F18 -> 0 | I51: =(G51*(1-$I$10)+C51*(H51-$I$9))/Equity_Cost -> 15191662 | J51: =(G51*(1-$I$10)+C51*(H51-$I$9))/VLOOKUP(C15,B21:I50,8,FALSE)-1 -> 0 | K51: =1/(1+Equity_Cost)^C15 -> 0.8106028 | L51: =I51*K51 -> 12314404
J52: PV of total FCFE = | L52: =SUM(L21:L51) -> 15187781
B54: Sensitivity Analysis (Enterprise Value)
A55: =L52 -> 15187781 | B55: =C94 -> 0.04 | C55: =C93 -> -0.15 | D55: =C92 -> 0 | E55: =C91 -> 0.02 | F55: =C90 -> -0.3
A56: 1 | B56: 15734184 | C56: 12878404 | D56: 15132967 | E56: 15433576 | F56: 10623840
A57: 2 | B57: 16317183 | C57: 11091570 | D57: 15132967 | E57: 15719469 | F57: 7680820
A58: 3 | B58: 16882514 | C58: 9675431.5 | D58: 15132967 | E58: 15991368 | F58: 5759967.7
A59: 4 | B59: 17430715 | C59: 8553084 | D59: 15132967 | E59: 16249957 | F59: 4506264.6
A60: 5 | B60: 17962303 | C60: 7663577.7 | D60: 15132967 | E60: 16495887 | F60: 3687996.8
A61: 6 | B61: 18477782 | C61: 6958607.8 | D61: 15132967 | E61: 16729779 | F61: 3153929.3
A62: 7 | B62: 18977641 | C62: 6399890.3 | D62: 15132967 | E62: 16952222 | F62: 2805353.7
A63: 8 | B63: 19462353 | C63: 5957083.9 | D63: 15132967 | E63: 17163776 | F63: 2577845.2
A64: 9 | B64: 19932376 | C64: 5606141.8 | D64: 15132967 | E64: 17364975 | F64: 2429354.8
A65: 10 | B65: 20388157 | C65: 5328005.9 | D65: 15132967 | E65: 17556324 | F65: 2332438
A66: 15 | B66: 22468068 | C66: 4597705.8 | D66: 15132967 | E66: 18381410 | F66: 2171883.6
A67: 20 | B67: 24251371 | C67: 4369351.3 | D67: 15132967 | E67: 19023378 | F67: 2152867.3
... A69: 30 | B69: 27091311 | C69: 4275621.4 | D69: 15132967 | E69: 19911504 | F69: 2150348.2
B71: Sensitivity Analysis (Equity Value per share)
B72: =B55 -> 0.04 | C72: =C55 -> -0.15 | D72: =D55 -> 0 | E72: =E55 -> 0.02 | F72: =F55 -> -0.3
A73: 0 | B73: =C11 -> 4.5928254 | C73: =C11 -> 4.5928254 | D73: =C11 -> 4.5928254 | E73: =C11 -> 4.5928254 | F73: =C11 -> 4.5928254
A74: 1 | B74: =(B56+FV_adjustments)/Common_Shares*scaling_factor*Exchange_Rate -> 4.710918 | C74: =(C56+FV_adjustments)/Common_Shares*scaling_factor*Exchange_Rate -> 4.1499784 | D74: =(D56+FV_adjustments)/Common_Shares*scaling_factor*Exchange_Rate -> 4.5928254 | E74: =(E56+FV_adjustments)/Common_Shares*scaling_factor*Exchange_Rate -> 4.6518717 | F74: =(F56+FV_adjustments)/Common_Shares*scaling_factor*Exchange_Rate -> 3.7071313
A75: 2 | B75: =(B57+FV_adjustments)/Common_Shares*scaling_factor*Exchange_Rate -> 4.825432 | C75: =(C57+FV_adjustments)/Common_Shares*scaling_factor*Exchange_Rate -> 3.799004 | D75: =(D57+FV_adjustments)/Common_Shares*scaling_factor*Exchange_Rate -> 4.5928254 | E75: =(E57+FV_adjustments)/Common_Shares*scaling_factor*Exchange_Rate -> 4.7080276 | F75: =(F57+FV_adjustments)/Common_Shares*scaling_factor*Exchange_Rate -> 3.1290558
A76: 3 | B76: =(B58+FV_adjustments)/Common_Shares*scaling_factor*Exchange_Rate -> 4.9364759 | C76: =(C58+FV_adjustments)/Common_Shares*scaling_factor*Exchange_Rate -> 3.5208425 | D76: =(D58+FV_adjustments)/Common_Shares*scaling_factor*Exchange_Rate -> 4.5928254 | E76: =(E58+FV_adjustments)/Common_Shares*scaling_factor*Exchange_Rate -> 4.7614346 | F76: =(F58+FV_adjustments)/Common_Shares*scaling_factor*Exchange_Rate -> 2.7517572
A77: 4 | B77: =(B59+FV_adjustments)/Common_Shares*scaling_factor*Exchange_Rate -> 5.0441548 | C77: =(C59+FV_adjustments)/Common_Shares*scaling_factor*Exchange_Rate -> 3.3003881 | D77: =(D59+FV_adjustments)/Common_Shares*scaling_factor*Exchange_Rate -> 4.5928254 | E77: =(E59+FV_adjustments)/Common_Shares*scaling_factor*Exchange_Rate -> 4.8122273 | F77: =(F59+FV_adjustments)/Common_Shares*scaling_factor*Exchange_Rate -> 2.5055016
A78: 5 | B78: =(B60+FV_adjustments)/Common_Shares*scaling_factor*Exchange_Rate -> 5.1485707 | C78: =(C60+FV_adjustments)/Common_Shares*scaling_factor*Exchange_Rate -> 3.1256691 | D78: =(D60+FV_adjustments)/Common_Shares*scaling_factor*Exchange_Rate -> 4.5928254 | E78: =(E60+FV_adjustments)/Common_Shares*scaling_factor*Exchange_Rate -> 4.8605336 | F78: =(F60+FV_adjustments)/Common_Shares*scaling_factor*Exchange_Rate -> 2.3447754
A79: 6 | B79: =(B61+FV_adjustments)/Common_Shares*scaling_factor*Exchange_Rate -> 5.2498225 | C79: =(C61+FV_adjustments)/Common_Shares*scaling_factor*Exchange_Rate -> 2.9871971 | D79: =(D61+FV_adjustments)/Common_Shares*scaling_factor*Exchange_Rate -> 4.5928254 | E79: =(E61+FV_adjustments)/Common_Shares*scaling_factor*Exchange_Rate -> 4.9064753 | F79: =(F61+FV_adjustments)/Common_Shares*scaling_factor*Exchange_Rate -> 2.2398725
A80: =A62 -> 7 | B80: =(B62+FV_adjustments)/Common_Shares*scaling_factor*Exchange_Rate -> 5.348006 | C80: =(C62+FV_adjustments)/Common_Shares*scaling_factor*Exchange_Rate -> 2.8774524 | D80: =(D62+FV_adjustments)/Common_Shares*scaling_factor*Exchange_Rate -> 4.5928254 | E80: =(E62+FV_adjustments)/Common_Shares*scaling_factor*Exchange_Rate -> 4.9501681 | F80: =(F62+FV_adjustments)/Common_Shares*scaling_factor*Exchange_Rate -> 2.1714044
A81: 8 | B81: =(B63+FV_adjustments)/Common_Shares*scaling_factor*Exchange_Rate -> 5.4432143 | C81: =(C63+FV_adjustments)/Common_Shares*scaling_factor*Exchange_Rate -> 2.7904752 | D81: =(D63+FV_adjustments)/Common_Shares*scaling_factor*Exchange_Rate -> 4.5928254 | E81: =(E63+FV_adjustments)/Common_Shares*scaling_factor*Exchange_Rate -> 4.9917221 | F81: =(F63+FV_adjustments)/Common_Shares*scaling_factor*Exchange_Rate -> 2.1267166
A82: =A64 -> 9 | B82: =(B64+FV_adjustments)/Common_Shares*scaling_factor*Exchange_Rate -> 5.5355375 | C82: =(C64+FV_adjustments)/Common_Shares*scaling_factor*Exchange_Rate -> 2.7215423 | D82: =(D64+FV_adjustments)/Common_Shares*scaling_factor*Exchange_Rate -> 4.5928254 | E82: =(E64+FV_adjustments)/Common_Shares*scaling_factor*Exchange_Rate -> 5.031242 | F82: =(F64+FV_adjustments)/Common_Shares*scaling_factor*Exchange_Rate -> 2.0975498
A83: =A65 -> 10 | B83: =(B65+FV_adjustments)/Common_Shares*scaling_factor*Exchange_Rate -> 5.625063 | C83: =(C65+FV_adjustments)/Common_Shares*scaling_factor*Exchange_Rate -> 2.6669101 | D83: =(D65+FV_adjustments)/Common_Shares*scaling_factor*Exchange_Rate -> 4.5928254 | E83: =(E65+FV_adjustments)/Common_Shares*scaling_factor*Exchange_Rate -> 5.0688273 | F83: =(F65+FV_adjustments)/Common_Shares*scaling_factor*Exchange_Rate -> 2.0785131
A84: =A66 -> 15 | B84: =(B66+FV_adjustments)/Common_Shares*scaling_factor*Exchange_Rate -> 6.0336045 | C84: =(C66+FV_adjustments)/Common_Shares*scaling_factor*Exchange_Rate -> 2.5234628 | D84: =(D66+FV_adjustments)/Common_Shares*scaling_factor*Exchange_Rate -> 4.5928254 | E84: =(E66+FV_adjustments)/Common_Shares*scaling_factor*Exchange_Rate -> 5.2308927 | F84: =(F66+FV_adjustments)/Common_Shares*scaling_factor*Exchange_Rate -> 2.0469766
A85: =A67 -> 20 | B85: =(B67+FV_adjustments)/Common_Shares*scaling_factor*Exchange_Rate -> 6.3838853 | C85: =(C67+FV_adjustments)/Common_Shares*scaling_factor*Exchange_Rate -> 2.4786088 | D85: =(D67+FV_adjustments)/Common_Shares*scaling_factor*Exchange_Rate -> 4.5928254 | E85: =(E67+FV_adjustments)/Common_Shares*scaling_factor*Exchange_Rate -> 5.3569897 | F85: =(F67+FV_adjustments)/Common_Shares*scaling_factor*Exchange_Rate -> 2.0432414
A86: =A68 -> 25 | B86: =(B68+FV_adjustments)/Common_Shares*scaling_factor*Exchange_Rate -> 6.6842138 | C86: =(C68+FV_adjustments)/Common_Shares*scaling_factor*Exchange_Rate -> 2.4645836 | D86: =(D68+FV_adjustments)/Common_Shares*scaling_factor*Exchange_Rate -> 4.5928254 | E86: =(E68+FV_adjustments)/Common_Shares*scaling_factor*Exchange_Rate -> 5.455101 | F86: =(F68+FV_adjustments)/Common_Shares*scaling_factor*Exchange_Rate -> 2.042799
A87: =A69 -> 30 | B87: =(B69+FV_adjustments)/Common_Shares*scaling_factor*Exchange_Rate -> 6.9417135 | C87: =(C69+FV_adjustments)/Common_Shares*scaling_factor*Exchange_Rate -> 2.4601981 | D87: =(D69+FV_adjustments)/Common_Shares*scaling_factor*Exchange_Rate -> 4.5928254 | E87: =(E69+FV_adjustments)/Common_Shares*scaling_factor*Exchange_Rate -> 5.5314377 | F87: =(F69+FV_adjustments)/Common_Shares*scaling_factor*Exchange_Rate -> 2.0427466
B89: Scenarios | C89: HGR | D89: HGP | E89: Value per share | F89: Adj. Probabilities
B90: =Scenarios!B29 -> Snowball Scenario | C90: =Scenarios!C29 -> -0.3 | D90: =Scenarios!D29 -> 3 | E90: =INDEX(B$73:F$87, MATCH(D90, A$73:A$87, 0), MATCH(C90, B$72:F$72, 0)) -> 2.7517572 | F90: =Scenarios!F29 -> 0.15
B91: =Scenarios!B22 -> Optimistic | C91: =Scenarios!C22 -> 0.02 | D91: =Scenarios!D22 -> 3 | E91: =INDEX(B$73:F$87, MATCH(D91, A$73:A$87, 0), MATCH(C91, B$72:F$72, 0)) -> 4.7614346 | F91: =Scenarios!F22*(1-F$90-F$94) -> 0.16
B92: =Scenarios!B23 -> Base | C92: =Scenarios!C23 -> 0 | D92: =Scenarios!D23 -> 3 | E92: =INDEX(B$73:F$87, MATCH(D92, A$73:A$87, 0), MATCH(C92, B$72:F$72, 0)) -> 4.5928254 | F92: =Scenarios!F23*(1-F$90-F$94) -> 0.44
B93: =Scenarios!B24 -> Pessimistic | C93: =Scenarios!C24 -> -0.15 | D93: =Scenarios!D24 -> 3 | E93: =INDEX(B$73:F$87, MATCH(D93, A$73:A$87, 0), MATCH(C93, B$72:F$72, 0)) -> 3.5208425 | F93: =Scenarios!F24*(1-F$90-F$94) -> 0.2
B94: =Scenarios!B30 -> Devil's advocate | C94: =Scenarios!C30 -> 0.04 | D94: =Scenarios!D30 -> 3 | E94: =INDEX(B$73:F$87, MATCH(D94, A$73:A$87, 0), MATCH(C94, B$72:F$72, 0)) -> 4.9364759 | F94: =Scenarios!F30 -> 0.05

Sheet Scenarios
B2: Current Situation
B3: Selection | D3: Prompt for fundamental Analysis
B4: Past Years Selected | C4: 2 | D4: ="DCF Model Inputs for " & Thesis!C5 & " – " & Thesis!C4 & ": Please develop Base, Pessimistic, and Optimistic scenarios under the following unified framework. " & "Assume a consistent high-growth period across all cases, with each scenario using a single FCFE CAGR during this phase. " & "Apply a two-stage model only if there is a material shift in FCFE margin or growth, and ensure this structure is used consistently across scenarios. " & "Margins should remain constant within each stage and be identical across all scenarios; any variation in outlook should be reflected through adjustments to the growth rate, not the margin. " & "Terminal growth is fixed at 0%, so modify the high-growth duration or rate accordingly to reflect long-term expectations. " & "Specify the FCFE margin (stage-specific if applicable) for all scenarios. " & "For each scenario, specify the FCFE CAGR during the high-growth period. Accompany each with a concise business narrative and respective probability explaining the key drivers behind the scenario." -> DCF Model Inputs for 0639.HK – 首钢资源: Please develop Base, Pessimistic, and Optimistic scenarios under the following unified framework. Assume a consistent high-growth period across all cases, with each scenario using a single FCFE CAGR during this phase. Apply a two-stage model only if there is a material shift in FCFE margin or growth, and ensure this structure is used consistently across scenarios. Margins should remain constant within each stage and be identical across all scenarios; any variation in outlook should be reflected through adjustments to the growth rate, not the margin. Terminal growth is fixed at 0%, so modify the high-growth duration or rate accordingly to reflect long-term expectations. Specify the FCFE margin (stage-specific if applicable) for all scenarios. For each scenario, specify the FCFE CAGR during the high-growth period. Accompany each with a concise business narrative and respective probability explaining the key drivers behind the scenario.
B6: Latest | C6: =DCF!C3&" "&Reporting_currency -> 1000 HKD
B7: EBIT | C7: =Normalized_FCF!G8 -> 2269323
B8: FCFE | C8: =Normalized_FCF!G19 -> 1274305
B9: Normalized | C9: =Normalized_FCF!C19 -> 1097140.1
B11: YoY CAGR
B12: Sales | C12: =(Normalized_FCF!G4/OFFSET(Normalized_FCF!G4, 0, $C$4))^(1/$C$4) - 1 -> -0.21539672
B13: Operating EBIT | C13: =(Normalized_FCF!G8/OFFSET(Normalized_FCF!G8, 0, $C$4))^(1/$C$4) - 1 -> -0.30758333
B14: FCFE | C14: =(Normalized_FCF!G19/OFFSET(Normalized_FCF!G19, 0, $C$4))^(1/$C$4) - 1 -> -0.33056173
B16: Scenarios Analysis
B17: Assumption | E17: Note on Manual Adjustments
B18: High Growth Period (HGP) | C18: 3 | E18: accepts 5-10, 15, 20, 25, or 30
B20: General Scenarios
B21: Scenarios | C21: HGR | D21: HGP | E21: ="Value per share ("&Market_currency&")" -> Value per share (HKD) | F21: Probabilities | G21: Adj. Probabilities
B22: Optimistic | C22: 0.02 | D22: =C18 -> 3 | E22: =DCF!E91 -> 4.7614346 | F22: =1-F23-F24 -> 0.2 | G22: =F22*(1-F$29-F$30) -> 0.16
B23: Base | C23: 0 | D23: =C18 -> 3 | E23: =DCF!E92 -> 4.5928254 | F23: 0.55 | G23: =F23*(1-F$29-F$30) -> 0.44
B24: Pessimistic | C24: -0.15 | D24: =C18 -> 3 | E24: =DCF!E93 -> 3.5208425 | F24: 0.25 | G24: =F24*(1-F$29-F$30) -> 0.2
B25: Under General Scenario | C25: =E23*F23+E24*F24+E22*F22 -> 4.3585515 | D25: =Market_currency -> HKD
B27: Extreme Scenarios
B28: Scenarios | C28: HGR | D28: HGP | E28: ="Value per share ("&Market_currency&")" -> Value per share (HKD) | F28: Probabilities | G28: Adj. Probabilities
B29: Snowball Scenario | C29: -0.3 | D29: =C18 -> 3 | E29: =DCF!E90 -> 2.7517572 | F29: 0.15 | G29: =F29 -> 0.15
B30: Devil's advocate | C30: 0.04 | D30: =C18 -> 3 | E30: =DCF!E94 -> 4.9364759 | F30: 0.05 | G30: =F30 -> 0.05
B32: Conclusion
B33: Annual Dividend per share | C33: =Normalized_FCF!C88*(1-dividend_tax_rate) -> 0.27 | D33: =Market_currency -> HKD | E33: With a holding period of | F33: =Holding_Period -> 3
B34: Market Price | C34: =Market_Price -> 3.16 | D34: =Market_currency -> HKD | E34: Implied Annual Return | F34: =RATE(Holding_Period,$C$33,-C34,$C$36) -> 0.17337144
B35: No-g Model Value per share | C35: =DCF!C11 -> 4.5928254 | D35: =Market_currency -> HKD | E35: Implied Annual Return | F35: =RATE(Holding_Period,$C$33,-C35,$C$36) -> 0.027256442
B36: g Model Value per share | C36: =E22*G22+E23*G23+E24*G24+E30*G30+E29*G29 -> 4.1464286 | D36: =Market_currency -> HKD | E36: is assumed to be the | F36: Expected Value
B38: Stage II Normalized Values
B39: =IF(DCF!F14="II","2","1")&"-stage DCF" -> 1-stage DCF | E39: Note on Manual Adjustments
B40: Contribution Margin_II | C40: =DCF!C17 -> 0.53643826 | E40: Try obtain this number by reverse engineering.
B41: High Growth Rate_II | C41: =DCF!C16 -> 0.0013
B43: Growth Classification
B44: Equity Value Driving Factors | E44: Note on Manual Adjustments
B45: High Growth Period (HGP) | C45: =C18 -> 3 | E45: Use general Scenarios' HGP assumption
B46: High Growth Rate (HGR) | C46: 0.0013 | E46: Use Excel Goal Seek to find the HGR
B47: Equity Value per share | C47: =DCF!I18 -> 4.603592 | D47: =Market_currency -> HKD | E47: Set to Expected Equity Value
B49: Type of Company | E49: Note on the logic
B50: Negative Growth | C50: =IF(C36<C35,"Y","N") -> Y
B51: Low Growth | C51: =IF(C50="Y","N",IF(C46>8%,"N","Y")) -> N | E51: >8% is Categorized as High Growth
B52: High Growth | C52: =IF(C46>8%,"Y","N") -> N
B53: Asset Play | C53: =IF(F53>50%,"Y","N") -> N | E53: The Non-FCF Value is of the Expected Value, at | F53: =BS!D89/C36 -> 0.39492494
B55: Margin of Safety (MOS)
B56: Inputs
B57: Expected Holding Period | C57: =Holding_Period -> 3
B58: After-tax Dividend per share | C58: =C33 -> 0.27 | D58: =Market_currency -> HKD
B60: Results
B61: Buy Price Outputs | C61: PV(Dividends) | D61: PV(Equity Value) | E61: ="Buy below ("&Market_currency&")" -> Buy below (HKD) | F61: Implied Annual Return | G61: MOS below Value
B62: Target Price | C62: =PV(F62, Holding_Period, -C58, 0) -> 0.49405993 | D62: =C36/(1+F62)^Holding_Period -> 1.9107966 | E62: =C62+D62 -> 2.4048565 | F62: =Thesis!E22 -> 0.29465259 | G62: =(1-E62/C36) -> 0.42001738
B63: Entry Price | C63: =PV(F63, Holding_Period, -C58, 0) -> 0.56808107 | D63: =C36/(1+F63)^Holding_Period -> 2.395049 | E63: =C63+D63 -> 2.9631301 | F63: =Thesis!E23 -> 0.20075184 | G63: =(1-E63/C36) -> 0.28537776
B65: Sell Price Outputs | C65: PV(Dividends) | D65: PV(Equity Value) | E65: ="Sell above ("&Market_currency&")" -> Sell above (HKD) | F65: Implied Annual Return | G65: MOS below Value
B66: Exit Price | C66: =PV(F66, Holding_Period, -C58, 0) -> 0.65140284 | D66: =C36/(1+F66)^Holding_Period -> 2.9719958 | E66: =C66+D66 -> 3.6233986 | F66: =Thesis!E24 -> 0.1174 | G66: =(1-E66/C36) -> 0.12613987
B67: Sell Price | C67: =PV(F67, Holding_Period, -C58, 0) -> 0.70534131 | D67: =C36/(1+F67)^Holding_Period -> 3.3611066 | E67: =C67+D67 -> 4.0664479 | F67: =Thesis!E25 -> 0.0725 | G67: =(1-E67/C36) -> 0.019289051

Sheet 投资主题
A2: 执行摘要
E3: 更新日期: | F3: =Thesis!F3 -> 45930
B4: 公司： | C4: =Thesis!C4 -> 首钢资源 | E4: 组合: | F4: =Thesis!F4 -> INT
B5: 股票代码： | C5: =Thesis!C5 -> 0639.HK | E5: 精选: | F5: =Thesis!F5 -> Y
B6: 对比板块: | C6: =Thesis!C6 -> MAT_01
B7: 市价货币： | C7: =Market_currency -> HKD
B8: 市场价格： | C8: =Market_Price -> 3.16
B9: 股份数量： | C9: =Common_Shares -> 5091065770
B10: 市值： | C10: =投资主题!C8*Common_Shares/1000000 -> 16087.768 | D10: 隐含年回报率: | E10: =Scenarios!F34 -> 0.17337144
B12: 指导说明：该模型使用结构化的投资流程来评估公司，确定其内在价值和目标价格。它关注可持续的自由现金流（FCF）能力，调整财务结构，纳入增长情景，并根据得出的内在价值计算预期回报。
B14: 估值概述
B15: 商业模式风险溢价: | C15: =Thesis!C15 -> N | D15: 外汇符号： | E15: =IF(E17=C7,C7,E17&"/"&C7) -> HKD
B16: 管理风险溢价: | C16: =Thesis!C16 -> N | D16: 汇率： | E16: =Exchange_Rate -> 1
B17: 永续增长率 (g) = | C17: =Terminal_Growth -> 0 | D17: 报告货币: | E17: =Reporting_currency -> HKD
B18: ="预期股权价值 ("&C7&") :" -> 预期股权价值 (HKD) : | C18: =C125 -> 4.1464286 | D18: 报告间隔： | E18: =Thesis!E18 -> 6
B19: 增长分类: | C19: =IF(Scenarios!C50="Y",Scenarios!B50,"")&IF(Scenarios!C51="Y",Scenarios!B51,"")&IF(Scenarios!C52="Y",Scenarios!B52,"")&" "&IF(Scenarios!C53="Y",Scenarios!B53,"") -> Negative Growth | D19: 下次更新日期： | E19: =EOMONTH(EDATE(BS!C1,E18+2),0) -> 46081
B21: 投资决策 | C21: =C138&" ("&Market_currency&")" -> (HKD) | D21: 持有期 | E21: =Holding_Period -> 3
B22: 目标价格 | C22: =E140 -> 2.4048565 | D22: @目标回报率 | E22: =Thesis!E22 -> 0.29465259
B23: 入场价格 | C23: =E141 -> 2.9631301 | D23: @入场收益率 | E23: =Thesis!E23 -> 0.20075184
B24: 退出价格 | C24: =E144 -> 3.6233986 | D24: @基准收益率 | E24: =Thesis!E24 -> 0.1174
B25: 卖出价格 | C25: =E145 -> 4.0664479 | D25: @基础Equity Cost | E25: =Thesis!E25 -> 0.0725
A27: 步骤1：确定公司可持续盈利能力（计算标准化FCFE）
B29: 目标：量化业务持续生成的潜在自由现金流（FCFE），去除临时波动或会计选择的影响。
B30: FCFE = (Normalized Operating EBIT + Depreciation & Amortization – Capital Expenditures) + Stable Non-Operating EBIT + Net Interest Income – Taxes – NCI’s Share of Profits – Working Capital Investment
B32: 关键组成部分 | C32: =scaling_factor -> 1000
B33: • Normalized Operating EBIT：核心业务运营的税前息前利润，调整以剔除一次性或非经常性项目，形成可持续盈利基础。
B34: Normalized Operating EBIT = | C34: =Normalized_FCF!C8 -> 1900909.5 | D34: =Reporting_currency -> HKD
B36: • Depreciation & Amortization (D&A): 非现金费用，加入以反映运营产生的现金。 • Capital Expenditures (Capex): 维持或扩展运营资产所需的现金流出。
B37: D&A = | C37: =Normalized_FCF!C15 -> 0 | D37: =Reporting_currency -> HKD
B38: Capex = | C38: =Normalized_FCF!C16 -> 0 | D38: =Reporting_currency -> HKD
B40: • Stable Non-Operating EBIT: 来自非核心资产的持续收益，如固定收益投资、支付股息的股票或租赁物业。
B41: Stable Non-Operating EBIT = | C41: =Normalized_FCF!C9 -> 0 | D41: =Reporting_currency -> HKD
B43: • Net Interest Income: 利息收入减去利息支出
B44: Operating Interest Income = | C44: =Normalized_FCF!C46 -> 12533.131 | D44: =Reporting_currency -> HKD
B45: Interest Expense = | C45: =Normalized_FCF!C45 -> -2620.62 | D45: =Reporting_currency -> HKD
B46: Net Interest Income = | C46: =Normalized_FCF!C10 -> 9912.5106 | D46: =Reporting_currency -> HKD
B48: • NCI’s Share of Profits: NCI代表子公司中母公司未拥有的股权部分。
B49: Est. NCI’s Share of Profits = | C49: =Normalized_FCF!C13 -> -335976.4 | D49: =Reporting_currency -> HKD
B51: • Taxes: Tax = (Normalized Operating EBIT + Stable Non-Operating EBIT + Interest Income – Interest Expense) × Tax Rate
B52: Taxes = | C52: =Normalized_FCF!C12 -> -477705.51 | D52: =Reporting_currency -> HKD
B54: • Working Capital Investment (WCInv): WCInv仅在显著扭曲FCFE时纳入。
B55: WCInv = | C55: =Normalized_FCF!C17 -> 0 | D55: =Reporting_currency -> HKD
B57: 关于净借款的说明：理论上，本金偿还通过净借款核算。然而，该模型旨在避免明确预测债务发行或偿还。相反，本金偿还通过有息债务在股权价值调整中反映。
B58: 洞察：这一步骤通过纳入运营和稳定的非运营来源，同时考虑税金和再投资需求，确保现金流的全面衡量。
B60: 最新FCFE = | C60: =Normalized_FCF!G19 -> 1274305 | D60: =Reporting_currency -> HKD
B61: Normalized FCFE = | C61: =Normalized_FCF!C19 -> 1097140.1 | D61: =Reporting_currency -> HKD
B62: Normalized FCFE/Market Cap = | C62: =Normalized_FCF!C124 -> 0.068197163
B63: After tax Dividend/Market Cap = | C63: =Normalized_FCF!C92 -> 0.085443038 | E63: 派息比率: | F63: =Normalized_FCF!C90 -> 1.3920918
B65: 杜邦分析 | C65: Normalized | D65: 最新
B66: ROE = | C66: =Normalized_FCF!C119 -> 0.10109497 | D66: =Normalized_FCF!G119 -> 0.12200966
B67: =Normalized_FCF!B116 -> Pre-tax Profit/Sales | C67: =Normalized_FCF!C116 -> 0.41984093 | D67: =Normalized_FCF!G116 -> 0.45602847
B68: =Normalized_FCF!B117 -> Sales/Total Assets | C68: =Normalized_FCF!C117 -> 0.1983239 | D68: =Normalized_FCF!G117 -> 0.22035989
B69: =Normalized_FCF!B118 -> Total Assets/Equity | C69: =Normalized_FCF!C118 -> 1.2141427 | D69: =Normalized_FCF!G118 -> 1.2141427
A71: 步骤2：公允价值调整 (Fair Value Adjustment)
B73: 目标：根据资本结构，确定计算股权价值所需的公允价值调整 (FV Adjustment)。
B74: FV adjustmets = Non-Operating Cash + Other Non-Operating Assets – Total Interest-Bearing Debt
B76: 关键组成部分
B77: 关于债务的说明：总有息债务包括本金偿还。理想情况下，应根据偿还时间表贴现。但为简单和保守起见，该模型使用总有息债务的账面价值。
B78: Total Interest-Bearing Debt = | C78: =DCF!F4 -> -43677 | D78: =Reporting_currency -> HKD
B79: Total Interest-Bearing Debt per share = | C79: =C78*scaling_factor*Exchange_Rate/Common_Shares -> -0.0085791467 | D79: =Market_currency -> HKD
B80: Debt to Equity Ratio = | C80: =IF(BS!G31/BS!G27>300%,"nm",BS!G31/BS!G27) -> 0.0023107987
B81: Debt to EBIT Ratio = | C81: =IF(BS!C50>30,"nm",BS!C50) -> 0.022976896
B83: • Non-Operating Cash: 运营不需要的超额现金
B84: Est. Non-Operating Cash = | C84: =DCF!F5 -> 8029573.9 | D84: =Reporting_currency -> HKD
B85: 总现金 = | C85: =BS!C66 -> 10118429 | D85: =Reporting_currency -> HKD
B86: Est. Non-Operating Cash per share = | C86: =C84*scaling_factor*Exchange_Rate/Common_Shares -> 1.5771892 | D86: =Market_currency -> HKD
B88: • Other Non-Operating Assets: 不贡献FCFE的资产（如非收益性投资或物业）
B89: Other Non-Operating Assets = | C89: =DCF!F6 -> 263512.2 | D89: =Reporting_currency -> HKD
B90: Other Non-Operating Assets per share = | C90: =C89*scaling_factor*Exchange_Rate/Common_Shares -> 0.051759732 | D90: =Market_currency -> HKD
B92: 公允价值调整 (FV Adjustment) = | C92: =DCF!F8 -> 1.6203698 | D92: =Market_currency -> HKD
A94: 步骤3：零增长模型与增长模型的价值
B96: 目标：在假设当前的标准化自由现金流股权（FCFE）保持稳定的前提下，计算其内在价值，并分别考虑零增长和增长两种情境。
B97: Enterprise Value = Normalized FCFE / (Cost of Equity - Terminal Growth Rate)
B98: Equity Value = Enterprise Value - FV adjustment
B100: 关键组成部分
B101: Cost of Equity = | C101: =E25+C103 -> 0.0725
B102: Base Cost of Equity | C102: =E25 -> 0.0725
B103: Risk Premium | C103: =IF(C15="Y",1%,0)+IF(C16="Y",1%,0) -> 0
B104: 永续增长率 (g) = | C104: 0
B106: 说明：
B107: Cost of Equity: 反映公司的风险概况，代表投资者为承担拥有此类业务一般风险所需的最低回报，而目标年回报率作为投资者要求的回报率。
B108: 永续增长率: 将g设为0%是一个保守假设，仅基于公司当前表现的盈利能力估值，不依赖潜在乐观的未来增长预测。
B110: a. 零增长模型
B111: 估计(净资产)可变现价值 = | C111: =BS!D47 -> 0.79833937 | D111: =Market_currency -> HKD
B112: 无增长股权价值每股 = | C112: =DCF!C11 -> 4.5928254 | D112: =Market_currency -> HKD
B114: 洞察：无增长股权价值每股代表公司在考虑未来增长潜力前，基于当前可持续运营和净财务状况的内在价值估计，作为基本锚定的估值基线。
B116: b. 增长模型
B117: 情景 | C117: HGR | D117: HGP | E117: 每股EV | F117: 概率
B118: =DCF!B90 -> Snowball Scenario | C118: =DCF!C90 -> -0.3 | D118: =DCF!D90 -> 3 | E118: =ROUND(DCF!E90,2)&" "&Market_currency -> 2.75 HKD | F118: =DCF!F90 -> 0.15
B119: =DCF!B91 -> Optimistic | C119: =DCF!C91 -> 0.02 | D119: =DCF!D91 -> 3 | E119: =ROUND(DCF!E91,2)&" "&Market_currency -> 4.76 HKD | F119: =DCF!F91 -> 0.16
B120: =DCF!B92 -> Base | C120: =DCF!C92 -> 0 | D120: =DCF!D92 -> 3 | E120: =ROUND(DCF!E92,2)&" "&Market_currency -> 4.59 HKD | F120: =DCF!F92 -> 0.44
B121: =DCF!B93 -> Pessimistic | C121: =DCF!C93 -> -0.15 | D121: =DCF!D93 -> 3 | E121: =ROUND(DCF!E93,2)&" "&Market_currency -> 3.52 HKD | F121: =DCF!F93 -> 0.2
B122: =DCF!B94 -> Devil's advocate | C122: =DCF!C94 -> 0.04 | D122: =DCF!D94 -> 3 | E122: =ROUND(DCF!E94,2)&" "&Market_currency -> 4.94 HKD | F122: =DCF!F94 -> 0.05
B124: 目标：通过建模合理的FCFE/股息、高增长期（HGP）和高增长率（HGR）情景，并按概率加权，估计内在价值。
B125: Expected Equity Value = | C125: =Scenarios!C36 -> 4.1464286 | D125: =Market_currency -> HKD
B127: 洞察：分析市场大幅波动作为市场感知结果范围的指标，包括定义“雪球”或“魔鬼代言人”等情景边界的极端情况。情景分析使用基本推理评估这些情景的可能性。
A129: 步骤4：投资决策
B131: 目标：将公司内在价值估计（来自步骤4）转化为满足特定投资要求的具体买入价格。
B132: 计算逻辑：The Target Buy Price is determined by discounting future cash flows—expected annual dividends and the Expected Equity Value—at the Target Annual Return, realized over the holding period.
B134: 关键组成部分
...
