Workbook
Name Common_Shares: Thesis!$C$11
Name Equity_Cost: Valuation_Model!$C$5
Name Exchange_Rate: Thesis!$C$13
Name Market_currency: Thesis!$D$10
Name Market_Price: Thesis!$C$10
Name Reporting_currency: Thesis!$C$12
Name Terminal_Growth: Valuation_Model!$F$4

Sheet Thesis
B1: Investment Thesis for | C1: 首程控股 | D1: 0697.HK
B2: Model last updated: | C2: 45643 | E2: Status: Not Held
A3: Introduction
B4: Comapny Information
B5: Comp_Sector: | C5: C0008
B6: Review Interval: | C6: 8
B7: Review Date: | C7: =EOMONTH(EDATE(BS!C1,Thesis!C6),0) -> 45716
B9: =D1&" Stock Information" -> 0697.HK Stock Information
B10: Market Price: | C10: 1.7 | D10: HKD
B11: Number of Shares: | C11: 7286015440
B12: Reporting Currency: | C12: CNY
B13: Exchange Rate: | C13: 1.06 | D13: =IF(C12=D10,D10,C12&"/"&D10) -> CNY/HKD
B14: Capitalization: | C14: =Thesis!C10*Thesis!C11/1000000 -> 12386.226
A16: Stock Analysis
A18: ="1." -> 1. | B18: Adjusted FCFE Calculation
B19: Formula:
B20: Adjusted FCFE = Net Income + D&A – Maintenance Capex ± WCInv (if material).
B22: Variables | C22: =Data!C3 -> 1000
B23: Operating after-tax Profit = | C23: =Normalized_FCF!C16 -> 203787.93 | D23: =C12 -> CNY
B24: Non-Operating after-tax Profit = | C24: =Normalized_FCF!C11 -> 124963.87
B25: Net Income = | C25: =C23+C24 -> 328751.8
B27: Adjusted FCFE = | C27: =Normalized_FCF!C19 -> 203787.93
B28: Adjusted FCFE per share = | C28: =C27/(Common_Shares/Data!C3) -> 0.027969737
B29: FCFE/Market Price = | C29: =C28/Market_Price -> 0.016452786
B31: Notes:
B32: 1. the model explicitly avoids aggressive growth assumptions and prioritizes downside protection.
B33: 2. Net borrowing is excluded (fixed at 0), and WCInv is only included if it materially distorts FCFE (>5% volatility).
B34: 3. Normalization: 5-year averages will smooth cyclicality for 590.HK.
A36: ="2." -> 2. | B36: Equity Cost of Capital (Buffett Method)
B37: Equity Cost of Capital (r) = | C37: 0.1
B39: Qualitative Adjustments
B40: Nonexistent moats | C40: 0 | D40: HK
B41: Weak balance sheets | C41: 0 | D41: Stable Business
B42: Poor management | C42: 0
B43: Qualitative Adjustments | C43: =SUM(C40:C42) -> 0
A45: ="3." -> 3. | B45: No-Growth DCF Valuation
B46: Key Metrics:
B47: Adjusted Earnings Yield = Adjusted FCFE / Market Cap.
B48: Intrinsic Value (No Growth) = Adjusted FCFE / Equity Cost of Capital.
B50: Decision Rule:
B51: Buy if Adjusted Earnings Yield > 7%
A53: ="4." -> 4. | B53: Growth Scenario Analysis
B54: Formula:
B55: g = (r × P - Adjusted FCFE) / (P + Adjusted FCFE)
B57: Phase Breakdown:
B58: High Growth: 5 years at 5%, then transitions to 3% perpetual growth.
B60: Scenario Analysis:
B61: Base Case
B62: Opertimistic Case
B63: Pessimistic Case
B65: Valuation
B66: the Equity Value will be conservatively realized
B67: over a holding period of | C67: 3
B68: Target Return | C68: 0.2
B69: Margin of Safety: | C69: =Scenarios!F83 -> 0.4555853
B71: Output:
B72: Buy price range incorporating a 15–20% margin of safety (e.g., HKD 10–14/share).
A74: ="5." -> 5. | B74: Equity Value Calculation
B75: Formula:
B76: Equity Value = Intrinsic Value (with user-selected implied g) + Non-operating Assets - Interest-bearing Debt
B78: Key Adjustments:
B79: Non-operating Assets: Include cash, marketable securities, real estate, etc., at market value.
B80: Debt: Subtract total interest-bearing debt (market value if distressed).
A82: Conclusion
B84: Scenarios | C84: HGR | D84: Value per share | E84: Probabilities
B85: Optimistic
B86: Base
B87: No Growth
B88: Pessimistic
B90: Price Target: | C90: =Scenarios!C83 -> 0.19161739 | D90: =Reporting_currency -> CNY
A92: KEY EXCLUSIONS & LIMITATIONS
B93: Conservative Bias:
B94: Excludes net borrowing, potentially undervaluing firms with debt efficiency.
B96: Growth Constraints:
B97: Perpetual growth capped at 3%, penalizing high-growth companies.
B99: Subjective Adjustments:
B100: Non-operating assets and debt require manual review.

Sheet Data
B1: =Thesis!C12 -> CNY | C1: 45291 | D1: =EOMONTH(EDATE(C1,-12),0) -> 44926 | E1: =EOMONTH(EDATE(D1,-12),0) -> 44561 | F1: =EOMONTH(EDATE(E1,-12),0) -> 44196 | G1: =EOMONTH(EDATE(F1,-12),0) -> 43830 | H1: =EOMONTH(EDATE(G1,-12),0) -> 43465 | I1: =EOMONTH(EDATE(H1,-12),0) -> 43100 | J1: =EOMONTH(EDATE(I1,-12),0) -> 42735 | K1: =EOMONTH(EDATE(J1,-12),0) -> 42369 | ... M1: =EOMONTH(EDATE(L1,-12),0) -> 41639
B2: Data (Dirty)
B3: Income Statement | C3: 1000
B4: Sales | C4: 883478 | D4: 1599809 | E4: 1195031 | F4: 705854 | G4: 396091 | H4: 1676296
B5: COGS | C5: 523759 | D5: 535391 | E5: 647828 | F5: 531460 | G5: 193695 | H5: 1515759
B6: OPEX | C6: 299979 | D6: 378568 | E6: 343154 | F6: 250972 | G6: 231174 | H6: 164177
B7: Incl. Selling Expenses
B8: R&D
B9: Share of JV or associate Results | C9: =-31502-31381 -> -62883 | D9: =499-60820 -> -60321
B10: Dividend or Interests from FA | C10: 328373 | D10: 414899
B11: Investment property
B12: Interest Expense | C12: 105689 | D12: 102356 | E12: 74343 | F12: 77168 | G12: 27358 | H12: 5699
B13: Interest Income | C13: 127073 | D13: 62873
B14: Income Tax Paid | C14: 6906 | D14: 269091
B15: Reported Net Income | C15: 459545 | D15: 914347
B16: Non-controling Interests | C16: 55980 | D16: -7663
B18: Cash Flow Statement
B19: D&A | C19: 35974 | D19: 32106 | E19: 181.018 | F19: 186.147
B20: CAPX | C20: 15312 | D20: 11600
B21: WCInv | C21: -169280 | D21: -50846
B22: ="Dividend per share ("&Market_currency&")" -> Dividend per share (HKD) | C22: 0.0548 | D22: 0.0952
B24: Balance Sheet
B25: ST AR
B26: ST Inventory
B27: Total Liabilities | C27: 642877 | D27: 734909 | E27: 677999 | F27: 1352795 | G27: 1205068
B28: Total Equity | C28: 3027292 | D28: 2824568 | E28: 2735259 | F28: 250534 | G28: 13930
B30: Other Data
B31: Contingent Liabilities | D31: 18682 | E31: 61277 | F31: 51229 | G31: 23195
B33: IS & CF Statements (Clean)
B34: Income Statement
B35: Sales | C35: =IF(C$4="","",C4) -> 883478 | D35: =IF(D$4="","",D4) -> 1599809 | E35: =IF(E$4="","",E4) -> 1195031 | F35: =IF(F$4="","",F4) -> 705854 | G35: =IF(G$4="","",G4) -> 396091 | H35: =IF(H$4="","",H4) -> 1676296 | I35: =IF(I$4="","",I4) | J35: =IF(J$4="","",J4) | ... M35: =IF(M$4="","",M4)
B36: COGS | C36: =IF(C$4="","",-C5) -> -523759 | D36: =IF(D$4="","",-D5) -> -535391 | E36: =IF(E$4="","",-E5) -> -647828 | F36: =IF(F$4="","",-F5) -> -531460 | G36: =IF(G$4="","",-G5) -> -193695 | H36: =IF(H$4="","",-H5) -> -1515759 | I36: =IF(I$4="","",-I5) | J36: =IF(J$4="","",-J5) | ... M36: =IF(M$4="","",-M5)
B37: Gross Margin | C37: =IF(C35="","",C35+C36) -> 359719 | D37: =IF(D35="","",D35+D36) -> 1064418 | E37: =IF(E35="","",E35+E36) -> 547203 | F37: =IF(F35="","",F35+F36) -> 174394 | G37: =IF(G35="","",G35+G36) -> 202396 | H37: =IF(H35="","",H35+H36) -> 160537 | I37: =IF(I35="","",I35+I36) | J37: =IF(J35="","",J35+J36) | ... M37: =IF(M35="","",M35+M36)
B38: OPEX | C38: =IF(C$4="","",-C6) -> -299979 | D38: =IF(D$4="","",-D6) -> -378568 | E38: =IF(E$4="","",-E6) -> -343154 | F38: =IF(F$4="","",-F6) -> -250972 | G38: =IF(G$4="","",-G6) -> -231174 | H38: =IF(H$4="","",-H6) -> -164177 | I38: =IF(I$4="","",-I6) | J38: =IF(J$4="","",-J6) | ... M38: =IF(M$4="","",-M6)
B39: Incl. Selling Expenses | C39: =IF(C$4="","",-C7) -> 0 | D39: =IF(D$4="","",-D7) -> 0 | E39: =IF(E$4="","",-E7) -> 0 | F39: =IF(F$4="","",-F7) -> 0 | G39: =IF(G$4="","",-G7) -> 0 | H39: =IF(H$4="","",-H7) -> 0 | I39: =IF(I$4="","",-I7) | J39: =IF(J$4="","",-J7) | ... M39: =IF(M$4="","",-M7)
B40: Incl. Other Opex | C40: =IF(C$4="","",C38-C39) -> -299979 | D40: =IF(D$4="","",D38-D39) -> -378568 | E40: =IF(E$4="","",E38-E39) -> -343154 | F40: =IF(F$4="","",F38-F39) -> -250972 | G40: =IF(G$4="","",G38-G39) -> -231174 | H40: =IF(H$4="","",H38-H39) -> -164177 | I40: =IF(I$4="","",I38-I39) | J40: =IF(J$4="","",J38-J39) | ... M40: =IF(M$4="","",M38-M39)
B41: R&D | C41: =IF(C$4="","",-C8) -> 0 | D41: =IF(D$4="","",-D8) -> 0 | E41: =IF(E$4="","",-E8) -> 0 | F41: =IF(F$4="","",-F8) -> 0 | G41: =IF(G$4="","",-G8) -> 0 | H41: =IF(H$4="","",-H8) -> 0 | I41: =IF(I$4="","",-I8) | J41: =IF(J$4="","",-J8) | ... M41: =IF(M$4="","",-M8)
B42: Operating EBIT | C42: =IF(C$4="","",C37+C38+C41) -> 59740 | D42: =IF(D$4="","",D37+D38+D41) -> 685850 | E42: =IF(E$4="","",E37+E38+E41) -> 204049 | F42: =IF(F$4="","",F37+F38+F41) -> -76578 | G42: =IF(G$4="","",G37+G38+G41) -> -28778 | H42: =IF(H$4="","",H37+H38+H41) -> -3640 | I42: =IF(I$4="","",I37+I38+I41) | J42: =IF(J$4="","",J37+J38+J41) | ... M42: =IF(M$4="","",M37+M38+M41)
B43: Non-operating EBIT | C43: =IF(C$4="","",C46-C45-C44-C42) -> 385327 | D43: =IF(D$4="","",D46-D45-D44-D42) -> 537071 | E43: =IF(E$4="","",E46-E45-E44-E42) -> -129706 | F43: =IF(F$4="","",F46-F45-F44-F42) -> 153746 | G43: =IF(G$4="","",G46-G45-G44-G42) -> 56136 | H43: =IF(H$4="","",H46-H45-H44-H42) -> 9339 | I43: =IF(I$4="","",I46-I45-I44-I42) | J43: =IF(J$4="","",J46-J45-J44-J42) | ... M43: =IF(M$4="","",M46-M45-M44-M42)
B44: Net Interest Income | C44: =IF(C$4="","",C50+C51) -> 21384 | D44: =IF(D$4="","",D50+D51) -> -39483 | E44: =IF(E$4="","",E50+E51) -> -74343 | F44: =IF(F$4="","",F50+F51) -> -77168 | G44: =IF(G$4="","",G50+G51) -> -27358 | H44: =IF(H$4="","",H50+H51) -> -5699 | I44: =IF(I$4="","",I50+I51) | J44: =IF(J$4="","",J50+J51) | ... M44: =IF(M$4="","",M50+M51)
B45: Income Tax Paid | C45: =IF(C$4="","",-C14) -> -6906 | D45: =IF(D$4="","",-D14) -> -269091 | E45: =IF(E$4="","",-E14) -> 0 | F45: =IF(F$4="","",-F14) -> 0 | G45: =IF(G$4="","",-G14) -> 0 | H45: =IF(H$4="","",-H14) -> 0 | I45: =IF(I$4="","",-I14) | J45: =IF(J$4="","",-J14) | ... M45: =IF(M$4="","",-M14)
B46: Reported Net Income | C46: =IF(C$4="","",C15) -> 459545 | D46: =IF(D$4="","",D15) -> 914347 | E46: =IF(E$4="","",E15) -> 0 | F46: =IF(F$4="","",F15) -> 0 | G46: =IF(G$4="","",G15) -> 0 | H46: =IF(H$4="","",H15) -> 0 | I46: =IF(I$4="","",I15) | J46: =IF(J$4="","",J15) | ... M46: =IF(M$4="","",M15)
B47: Non-controling Interests | C47: =IF(C$4="","",MIN(-C16,0)) -> -55980 | D47: =IF(D$4="","",MIN(-D16,0)) -> 0 | E47: =IF(E$4="","",MIN(-E16,0)) -> 0 | F47: =IF(F$4="","",MIN(-F16,0)) -> 0 | G47: =IF(G$4="","",MIN(-G16,0)) -> 0 | H47: =IF(H$4="","",MIN(-H16,0)) -> 0 | I47: =IF(I$4="","",MIN(-I16,0)) | J47: =IF(J$4="","",MIN(-J16,0)) | ... M47: =IF(M$4="","",MIN(-M16,0))
B49: Net Interest Income
B50: Interest Expense | C50: =IF(C$4="","",-C12) -> -105689 | D50: =IF(D$4="","",-D12) -> -102356 | E50: =IF(E$4="","",-E12) -> -74343 | F50: =IF(F$4="","",-F12) -> -77168 | G50: =IF(G$4="","",-G12) -> -27358 | H50: =IF(H$4="","",-H12) -> -5699 | I50: =IF(I$4="","",-I12) | J50: =IF(J$4="","",-J12) | ... M50: =IF(M$4="","",-M12)
B51: Interest Income | C51: =IF(C$4="","",C13) -> 127073 | D51: =IF(D$4="","",D13) -> 62873 | E51: =IF(E$4="","",E13) -> 0 | F51: =IF(F$4="","",F13) -> 0 | G51: =IF(G$4="","",G13) -> 0 | H51: =IF(H$4="","",H13) -> 0 | I51: =IF(I$4="","",I13) | J51: =IF(J$4="","",J13) | ... M51: =IF(M$4="","",M13)
B53: Non-operating EBIT
B54: Share of JV or associate Results | C54: =IF(C$4="","",C9) -> -62883 | D54: =IF(D$4="","",D9) -> -60321 | E54: =IF(E$4="","",E9) -> 0 | F54: =IF(F$4="","",F9) -> 0 | G54: =IF(G$4="","",G9) -> 0 | H54: =IF(H$4="","",H9) -> 0 | I54: =IF(I$4="","",I9) | J54: =IF(J$4="","",J9) | ... M54: =IF(M$4="","",M9)
B55: Dividend or Interests from FA | C55: =IF(C$4="","",C10) -> 328373 | D55: =IF(D$4="","",D10) -> 414899 | E55: =IF(E$4="","",E10) -> 0 | F55: =IF(F$4="","",F10) -> 0 | G55: =IF(G$4="","",G10) -> 0 | H55: =IF(H$4="","",H10) -> 0 | I55: =IF(I$4="","",I10) | J55: =IF(J$4="","",J10) | ... M55: =IF(M$4="","",M10)
B56: Investment property | C56: =IF(C$4="","",C11) -> 0 | D56: =IF(D$4="","",D11) -> 0 | E56: =IF(E$4="","",E11) -> 0 | F56: =IF(F$4="","",F11) -> 0 | G56: =IF(G$4="","",G11) -> 0 | H56: =IF(H$4="","",H11) -> 0 | I56: =IF(I$4="","",I11) | J56: =IF(J$4="","",J11) | ... M56: =IF(M$4="","",M11)
B57: Other Non-operating Income | C57: =IF(C$4="","",C43-C54-C55-C56) -> 119837 | D57: =IF(D$4="","",D43-D54-D55-D56) -> 182493 | E57: =IF(E$4="","",E43-E54-E55-E56) -> -129706 | F57: =IF(F$4="","",F43-F54-F55-F56) -> 153746 | G57: =IF(G$4="","",G43-G54-G55-G56) -> 56136 | H57: =IF(H$4="","",H43-H54-H55-H56) -> 9339 | I57: =IF(I$4="","",I43-I54-I55-I56) | J57: =IF(J$4="","",J43-J54-J55-J56) | ... M57: =IF(M$4="","",M43-M54-M55-M56)
B59: Cash Flow Statement
B60: D&A | C60: =IF(C$4="","",-C19) -> -35974 | D60: =IF(D$4="","",-D19) -> -32106 | E60: =IF(E$4="","",-E19) -> -181.018 | F60: =IF(F$4="","",-F19) -> -186.147 | G60: =IF(G$4="","",-G19) -> 0 | H60: =IF(H$4="","",-H19) -> 0 | I60: =IF(I$4="","",-I19) | J60: =IF(J$4="","",-J19) | ... M60: =IF(M$4="","",-M19)
B61: CAPX | C61: =IF(C$4="","",-C20) -> -15312 | D61: =IF(D$4="","",-D20) -> -11600 | E61: =IF(E$4="","",-E20) -> 0 | F61: =IF(F$4="","",-F20) -> 0 | G61: =IF(G$4="","",-G20) -> 0 | H61: =IF(H$4="","",-H20) -> 0 | I61: =IF(I$4="","",-I20) | J61: =IF(J$4="","",-J20) | ... M61: =IF(M$4="","",-M20)
B62: WCInv | C62: =IF(C$4="","",-C21) -> 169280 | D62: =IF(D$4="","",-D21) -> 50846 | E62: =IF(E$4="","",-E21) -> 0 | F62: =IF(F$4="","",-F21) -> 0 | G62: =IF(G$4="","",-G21) -> 0 | H62: =IF(H$4="","",-H21) -> 0 | I62: =IF(I$4="","",-I21) | J62: =IF(J$4="","",-J21) | ... M62: =IF(M$4="","",-M21)
B63: Dividend per share | C63: =IF(C$4="","",C22) -> 0.0548 | D63: =IF(D$4="","",D22) -> 0.0952 | E63: =IF(E$4="","",E22) -> 0 | F63: =IF(F$4="","",F22) -> 0 | G63: =IF(G$4="","",G22) -> 0 | H63: =IF(H$4="","",H22) -> 0 | I63: =IF(I$4="","",I22) | J63: =IF(J$4="","",J22) | ... M63: =IF(M$4="","",M22)
B65: YoY %
B66: =B35 -> Sales | C66: =IF(D$35="","",C35/D35-1) -> -0.44776033 | D66: =IF(E$35="","",D35/E35-1) -> 0.33871757 | E66: =IF(F$35="","",E35/F35-1) -> 0.69302859 | F66: =IF(G$35="","",F35/G35-1) -> 0.78205008 | G66: =IF(H$35="","",G35/H35-1) -> -0.76371059 | H66: =IF(I$35="","",H35/I35-1) | I66: =IF(J$35="","",I35/J35-1) | J66: =IF(K$35="","",J35/K35-1) | ... M66: =IF(N$35="","",M35/N35-1)
B67: =B42 -> Operating EBIT | C67: =IF(D$35="","",C36/D36-1) -> -0.021726178 | D67: =IF(E$35="","",D36/E36-1) -> -0.17355996 | E67: =IF(F$35="","",E36/F36-1) -> 0.21895909 | F67: =IF(G$35="","",F36/G36-1) -> 1.7437982 | G67: =IF(H$35="","",G36/H36-1) -> -0.87221254 | H67: =IF(I$35="","",H36/I36-1) | I67: =IF(J$35="","",I36/J36-1) | J67: =IF(K$35="","",J36/K36-1) | ... M67: =IF(N$35="","",M36/N36-1)
B68: =B57 -> Other Non-operating Income | C68: =IF(D$35="","",C37/D37-1) -> -0.662051 | D68: =IF(E$35="","",D37/E37-1) -> 0.94519767 | E68: =IF(F$35="","",E37/F37-1) -> 2.1377398 | F68: =IF(G$35="","",F37/G37-1) -> -0.13835254 | G68: =IF(H$35="","",G37/H37-1) -> 0.26074363 | H68: =IF(I$35="","",H37/I37-1) | I68: =IF(J$35="","",I37/J37-1) | J68: =IF(K$35="","",J37/K37-1) | ... M68: =IF(N$35="","",M37/N37-1)
B69: =B46 -> Reported Net Income | C69: =IF(D$35="","",C38/D38-1) -> -0.20759547 | D69: =IF(E$35="","",D38/E38-1) -> 0.10320148 | E69: =IF(F$35="","",E38/F38-1) -> 0.36729994 | F69: =IF(G$35="","",F38/G38-1) -> 0.085641119 | G69: =IF(H$35="","",G38/H38-1) -> 0.40807787 | H69: =IF(I$35="","",H38/I38-1) | I69: =IF(J$35="","",I38/J38-1) | J69: =IF(K$35="","",J38/K38-1) | ... M69: =IF(N$35="","",M38/N38-1)
B70: =B47 -> Non-controling Interests | C70: =IF(D$35="","",C63/D63-1) -> -0.42436975 | D70: =IF(E$35="","",D63/E63-1) -> #DIV/0! | E70: =IF(F$35="","",E63/F63-1) -> #DIV/0! | F70: =IF(G$35="","",F63/G63-1) -> #DIV/0! | G70: =IF(H$35="","",G63/H63-1) -> #DIV/0! | H70: =IF(I$35="","",H63/I63-1) | I70: =IF(J$35="","",I63/J63-1) | J70: =IF(K$35="","",J63/K63-1) | ... M70: =IF(N$35="","",M63/N63-1)
B72: Balance Sheet (Clean)
B73: Balance Sheet
B74: Total Assets | C74: =IF(C$4="","",C77+C78) -> 3670169 | D74: =IF(D$4="","",D77+D78) -> 3559477 | E74: =IF(E$4="","",E77+E78) -> 3413258 | F74: =IF(F$4="","",F77+F78) -> 1603329 | G74: =IF(G$4="","",G77+G78) -> 1218998 | H74: =IF(H$4="","",H77+H78) -> 0 | I74: =IF(I$4="","",I77+I78) | J74: =IF(J$4="","",J77+J78) | ... M74: =IF(M$4="","",M77+M78)
B75: Incl. ST AR | C75: =IF(C$4="","",C25) -> 0 | D75: =IF(D$4="","",D25) -> 0 | E75: =IF(E$4="","",E25) -> 0 | F75: =IF(F$4="","",F25) -> 0 | G75: =IF(G$4="","",G25) -> 0 | H75: =IF(H$4="","",H25) -> 0
B76: Incl. ST Inventory | C76: =IF(C$4="","",C26) -> 0 | D76: =IF(D$4="","",D26) -> 0 | E76: =IF(E$4="","",E26) -> 0 | F76: =IF(F$4="","",F26) -> 0 | G76: =IF(G$4="","",G26) -> 0 | H76: =IF(H$4="","",H26) -> 0
B77: Total Liabilities | C77: =IF(C$4="","",C27) -> 642877 | D77: =IF(D$4="","",D27) -> 734909 | E77: =IF(E$4="","",E27) -> 677999 | F77: =IF(F$4="","",F27) -> 1352795 | G77: =IF(G$4="","",G27) -> 1205068 | H77: =IF(H$4="","",H27) -> 0 | I77: =IF(I$4="","",I27) | J77: =IF(J$4="","",J27) | ... M77: =IF(M$4="","",M27)
B78: Total Equity | C78: =IF(C$4="","",C28) -> 3027292 | D78: =IF(D$4="","",D28) -> 2824568 | E78: =IF(E$4="","",E28) -> 2735259 | F78: =IF(F$4="","",F28) -> 250534 | G78: =IF(G$4="","",G28) -> 13930 | H78: =IF(H$4="","",H28) -> 0 | I78: =IF(I$4="","",I28) | J78: =IF(J$4="","",J28) | ... M78: =IF(M$4="","",M28)

Sheet Normalized_FCF
B1: =Thesis!C12 -> CNY | C1: Normalized | G1: =Data!C1 -> 45291 | H1: =EOMONTH(EDATE(G1,-12),0) -> 44926 | I1: =EOMONTH(EDATE(H1,-12),0) -> 44561 | J1: =EOMONTH(EDATE(I1,-12),0) -> 44196 | K1: =EOMONTH(EDATE(J1,-12),0) -> 43830 | L1: =EOMONTH(EDATE(K1,-12),0) -> 43465 | M1: =EOMONTH(EDATE(L1,-12),0) -> 43100 | N1: =EOMONTH(EDATE(M1,-12),0) -> 42735 | O1: =EOMONTH(EDATE(N1,-12),0) -> 42369 | ... Q1: =EOMONTH(EDATE(P1,-12),0) -> 41639
B2: FCFE Analysis | E2: Notes
B3: Adjusted FCFE | C3: =Data!C3 -> 1000
B4: Sales | C4: =AVERAGE(G4:I4) -> 1226106 | E4: Historical Average | G4: =Data!C35 -> 883478 | H4: =Data!D35 -> 1599809 | I4: =Data!E35 -> 1195031 | J4: =Data!F35 -> 705854 | K4: =Data!G35 -> 396091 | L4: =Data!H35 -> 1676296 | M4: =Data!I35 | N4: =Data!J35 | ... Q4: =Data!M35
B5: Variable Costs | C5: =C49 -> -738887.81 | G5: =G49 -> -523759 | H5: =H49 -> -535391 | I5: =I49 -> -647828 | J5: =J49 -> -531460 | K5: =K49 -> -193695 | L5: =L49 -> -1515759 | M5: =M49 | N5: =N49 | ... Q5: =Q49
B6: Contribution Margin | C6: =C4+C5 -> 487218.19 | G6: =IF(G4="","",G4+G5) -> 359719 | H6: =IF(H4="","",H4+H5) -> 1064418 | I6: =IF(I4="","",I4+I5) -> 547203 | J6: =IF(J4="","",J4+J5) -> 174394 | K6: =IF(K4="","",K4+K5) -> 202396 | L6: =IF(L4="","",L4+L5) -> 160537 | M6: =IF(M4="","",M4+M5) | N6: =IF(N4="","",N4+N5) | ... Q6: =IF(Q4="","",Q4+Q5)
B7: Fixed Costs | C7: =C52 -> -339273.5 | G7: =G52 -> -299979 | H7: =H52 -> -378568 | I7: =I52 -> -343154 | J7: =J52 -> -250972 | K7: =K52 -> -231174 | L7: =L52 -> -164177 | M7: =M52 | N7: =N52 | ... Q7: =Q52
B8: Add Back D&A | C8: =BS!$G$29*BS!C43 -> 35974 | G8: =IF(Data!C60="","",-Data!C60) -> 35974 | H8: =IF(Data!D60="","",-Data!D60) -> 32106 | I8: =IF(Data!E60="","",-Data!E60) -> 181.018 | J8: =IF(Data!F60="","",-Data!F60) -> 186.147 | K8: =IF(Data!G60="","",-Data!G60) -> 0 | L8: =IF(Data!H60="","",-Data!H60) -> 0 | M8: =IF(Data!I60="","",-Data!I60) | N8: =IF(Data!J60="","",-Data!J60) | ... Q8: =IF(Data!M60="","",-Data!M60)
B9: Maintenance Capex | C9: =-C4*C31 -> -35974 | G9: =Data!C61 -> -15312 | H9: =Data!D61 -> -11600 | I9: =Data!E61 -> 0 | J9: =Data!F61 -> 0 | K9: =Data!G61 -> 0 | L9: =Data!H61 -> 0 | M9: =Data!I61 | N9: =Data!J61 | ... Q9: =Data!M61
B10: Operating EBIT | C10: =SUM(C6:C9) -> 147944.69 | G10: =IF(G$4="","",SUM(G6:G9)) -> 80402 | H10: =IF(H$4="","",SUM(H6:H9)) -> 706356 | I10: =IF(I$4="","",SUM(I6:I9)) -> 204230.02 | J10: =IF(J$4="","",SUM(J6:J9)) -> -76391.853 | K10: =IF(K$4="","",SUM(K6:K9)) -> -28778 | L10: =IF(L$4="","",SUM(L6:L9)) -> -3640 | M10: =IF(M$4="","",SUM(M6:M9)) | N10: =IF(N$4="","",SUM(N6:N9)) | ... Q10: =IF(Q$4="","",SUM(Q6:Q9))
B11: Non-Operating EBIT | C11: =C67 -> 124963.87 | E11: Stable Non-Operating CF | G11: =G67 -> 385327 | H11: =H67 -> 537071 | I11: =I67 -> -129706 | J11: =J67 -> 153746 | K11: =K67 -> 56136 | L11: =L67 -> 9339 | M11: =M67 | N11: =N67 | ... Q11: =Q67
B12: Net Interest Income | C12: =C78 -> 14989.54 | G12: =G78 -> 21384 | H12: =H78 -> -39483 | I12: =I78 -> -74343 | J12: =J78 -> -77168 | K12: =K78 -> -27358 | L12: =L78 -> -5699 | M12: =M78 | N12: =N78 | ... Q12: =Q78
B13: Pre-tax Profit | C13: =SUM(C10:C12) -> 287898.1 | G13: =IF(G$4="","",SUM(G10:G12)) -> 487113 | H13: =IF(H$4="","",SUM(H10:H12)) -> 1203944 | I13: =IF(I$4="","",SUM(I10:I12)) -> 181.018 | J13: =IF(J$4="","",SUM(J10:J12)) -> 186.147 | K13: =IF(K$4="","",SUM(K10:K12)) -> 0 | L13: =IF(L$4="","",SUM(L10:L12)) -> 0 | M13: =IF(M$4="","",SUM(M10:M12)) | N13: =IF(N$4="","",SUM(N10:N12)) | ... Q13: =IF(Q$4="","",SUM(Q10:Q12))
B14: Income Tax | C14: =-C13*C36 -> -71974.524 | G14: =Data!C45 -> -6906 | H14: =Data!D45 -> -269091 | I14: =Data!E45 -> 0 | J14: =Data!F45 -> 0 | K14: =Data!G45 -> 0 | L14: =Data!H45 -> 0 | M14: =Data!I45 | N14: =Data!J45 | ... Q14: =Data!M45
B15: Non-controling Interests | C15: =-C4*C33 -> -12135.639 | G15: =Data!C47 -> -55980 | H15: =Data!D47 -> 0 | I15: =Data!E47 -> 0 | J15: =Data!F47 -> 0 | K15: =Data!G47 -> 0 | L15: =Data!H47 -> 0 | M15: =Data!I47 | N15: =Data!J47 | ... Q15: =Data!M47
B16: After-tax Profit | C16: =SUM(C13:C15) -> 203787.93 | G16: =IF(G$4="","",SUM(G13:G15)) -> 424227 | H16: =IF(H$4="","",SUM(H13:H15)) -> 934853 | I16: =IF(I$4="","",SUM(I13:I15)) -> 181.018 | J16: =IF(J$4="","",SUM(J13:J15)) -> 186.147 | K16: =IF(K$4="","",SUM(K13:K15)) -> 0 | L16: =IF(L$4="","",SUM(L13:L15)) -> 0 | M16: =IF(M$4="","",SUM(M13:M15)) | N16: =IF(N$4="","",SUM(N13:N15)) | ... Q16: =IF(Q$4="","",SUM(Q13:Q15))
B17: WCInv | C17: =-C4*C32 -> 0 | E17: WCInv is excluded
B18: Net Borrowing | C18: 0 | E18: Net borrowing is excluded
B19: Total FCFE | C19: =SUM(C16:C18) -> 203787.93 | G19: =IF(G$4="","",SUM(G16:G18)) -> 424227 | H19: =IF(H$4="","",SUM(H16:H18)) -> 934853 | I19: =IF(I$4="","",SUM(I16:I18)) -> 181.018 | J19: =IF(J$4="","",SUM(J16:J18)) -> 186.147 | K19: =IF(K$4="","",SUM(K16:K18)) -> 0 | L19: =IF(L$4="","",SUM(L16:L18)) -> 0 | M19: =IF(M$4="","",SUM(M16:M18)) | N19: =IF(N$4="","",SUM(N16:N18)) | ... Q19: =IF(Q$4="","",SUM(Q16:Q18))
B21: % Sales
B22: Variable Costs | C22: =ABS(C5/C$4) -> 0.60262963 | G22: =IF(G$4="","",ABS(G5/G$4)) -> 0.59283763 | H22: =IF(H$4="","",ABS(H5/H$4)) -> 0.33465932 | I22: =IF(I$4="","",ABS(I5/I$4)) -> 0.54210142 | J22: =IF(J$4="","",ABS(J5/J$4)) -> 0.75293191 | K22: =IF(K$4="","",ABS(K5/K$4)) -> 0.48901641 | L22: =IF(L$4="","",ABS(L5/L$4)) -> 0.90423111 | M22: =IF(M$4="","",ABS(M5/M$4)) | N22: =IF(N$4="","",ABS(N5/N$4)) | ... Q22: =IF(Q$4="","",ABS(Q5/Q$4))
B23: Contribution Margin | C23: =ABS(C6/C$4) -> 0.39737037 | G23: =IF(G$4="","",ABS(G6/G$4)) -> 0.40716237 | H23: =IF(H$4="","",ABS(H6/H$4)) -> 0.66534068 | I23: =IF(I$4="","",ABS(I6/I$4)) -> 0.45789858 | J23: =IF(J$4="","",ABS(J6/J$4)) -> 0.24706809 | K23: =IF(K$4="","",ABS(K6/K$4)) -> 0.51098359 | L23: =IF(L$4="","",ABS(L6/L$4)) -> 0.095768886 | M23: =IF(M$4="","",ABS(M6/M$4)) | N23: =IF(N$4="","",ABS(N6/N$4)) | ... Q23: =IF(Q$4="","",ABS(Q6/Q$4))
B24: Fixed Costs | C24: =ABS(C7/C$4) -> 0.27670813 | G24: =IF(G$4="","",ABS(G7/G$4)) -> 0.33954326 | H24: =IF(H$4="","",ABS(H7/H$4)) -> 0.23663325 | I24: =IF(I$4="","",ABS(I7/I$4)) -> 0.28715071 | J24: =IF(J$4="","",ABS(J7/J$4)) -> 0.35555795 | K24: =IF(K$4="","",ABS(K7/K$4)) -> 0.58363861 | L24: =IF(L$4="","",ABS(L7/L$4)) -> 0.09794034 | M24: =IF(M$4="","",ABS(M7/M$4)) | N24: =IF(N$4="","",ABS(N7/N$4)) | ... Q24: =IF(Q$4="","",ABS(Q7/Q$4))
B25: Operating EBIT | C25: =ABS(C10/C$4) -> 0.12066223 | G25: =IF(G$4="","",ABS(G10/G$4)) -> 0.091006228 | H25: =IF(H$4="","",ABS(H10/H$4)) -> 0.44152521 | I25: =IF(I$4="","",ABS(I10/I$4)) -> 0.17089935 | J25: =IF(J$4="","",ABS(J10/J$4)) -> 0.10822614 | K25: =IF(K$4="","",ABS(K10/K$4)) -> 0.072655021 | L25: =IF(L$4="","",ABS(L10/L$4)) -> 0.0021714542 | M25: =IF(M$4="","",ABS(M10/M$4)) | N25: =IF(N$4="","",ABS(N10/N$4)) | ... Q25: =IF(Q$4="","",ABS(Q10/Q$4))
B26: Net Interest Income | C26: =ABS(C12/C$4) -> 0.012225321 | G26: =IF(G$4="","",ABS(G12/G$4)) -> 0.024204338 | H26: =IF(H$4="","",ABS(H12/H$4)) -> 0.024679821 | I26: =IF(I$4="","",ABS(I12/I$4)) -> 0.062210102 | J26: =IF(J$4="","",ABS(J12/J$4)) -> 0.10932572 | K26: =IF(K$4="","",ABS(K12/K$4)) -> 0.069069986 | L26: =IF(L$4="","",ABS(L12/L$4)) -> 0.0033997576 | M26: =IF(M$4="","",ABS(M12/M$4)) | N26: =IF(N$4="","",ABS(N12/N$4)) | ... Q26: =IF(Q$4="","",ABS(Q12/Q$4))
B27: Income Tax | C27: =ABS(C14/C$4) -> 0.058701714 | G27: =IF(G$4="","",ABS(G14/G$4)) -> 0.007816833 | H27: =IF(H$4="","",ABS(H14/H$4)) -> 0.16820195 | I27: =IF(I$4="","",ABS(I14/I$4)) -> 0 | J27: =IF(J$4="","",ABS(J14/J$4)) -> 0 | K27: =IF(K$4="","",ABS(K14/K$4)) -> 0 | L27: =IF(L$4="","",ABS(L14/L$4)) -> 0 | M27: =IF(M$4="","",ABS(M14/M$4)) | N27: =IF(N$4="","",ABS(N14/N$4)) | ... Q27: =IF(Q$4="","",ABS(Q14/Q$4))
C28: =ABS(C16/C$4) -> 0.16620743 | G28: =IF(G$4="","",ABS(G16/G$4)) -> 0.48017834 | H28: =IF(H$4="","",ABS(H16/H$4)) -> 0.58435288 | I28: =IF(I$4="","",ABS(I16/I$4)) -> 0.00015147557 | J28: =IF(J$4="","",ABS(J16/J$4)) -> 0.00026371884 | K28: =IF(K$4="","",ABS(K16/K$4)) -> 0 | L28: =IF(L$4="","",ABS(L16/L$4)) -> 0 | M28: =IF(M$4="","",ABS(M16/M$4)) | N28: =IF(N$4="","",ABS(N16/N$4)) | ... Q28: =IF(Q$4="","",ABS(Q16/Q$4))
B29: Non-Operating Income | C29: =ABS(C11/C$4) -> 0.1019193 | G29: =IF(G$4="","",G11/G$4) -> 0.43614782 | H29: =IF(H$4="","",H11/H$4) -> 0.33570945 | I29: =IF(I$4="","",I11/I$4) -> -0.10853777 | J29: =IF(J$4="","",J11/J$4) -> 0.21781558 | K29: =IF(K$4="","",K11/K$4) -> 0.14172501 | L29: =IF(L$4="","",L11/L$4) -> 0.0055712118 | M29: =IF(M$4="","",M11/M$4) | N29: =IF(N$4="","",N11/N$4) | ... Q29: =IF(Q$4="","",Q11/Q$4)
B30: Add Back D&A | C30: =ABS(C8/C$4) -> 0.029340041 | G30: =IF(G$4="","",G8/G$4) -> 0.040718614 | H30: =IF(H$4="","",H8/H$4) -> 0.020068646 | I30: =IF(I$4="","",I8/I$4) -> 0.00015147557 | J30: =IF(J$4="","",J8/J$4) -> 0.00026371884 | K30: =IF(K$4="","",K8/K$4) -> 0 | L30: =IF(L$4="","",L8/L$4) -> 0 | M30: =IF(M$4="","",M8/M$4) | N30: =IF(N$4="","",N8/N$4) | ... Q30: =IF(Q$4="","",Q8/Q$4)
B31: Maintenance Capex | C31: =MAX(AVERAGE(G31:J31),C30) -> 0.029340041 | E31: Historical Average or D&A | G31: =IF(G$4="","",-G9/G$4) -> 0.017331501 | H31: =IF(H$4="","",-H9/H$4) -> 0.0072508656 | I31: =IF(I$4="","",-I9/I$4) -> 0 | J31: =IF(J$4="","",-J9/J$4) -> 0 | K31: =IF(K$4="","",-K9/K$4) -> 0 | L31: =IF(L$4="","",-L9/L$4) -> 0 | M31: =IF(M$4="","",-M9/M$4) | N31: =IF(N$4="","",-N9/N$4) | ... Q31: =IF(Q$4="","",-Q9/Q$4)
B32: WCInv | C32: =MIN(AVERAGE(G32:J32)/2,0) -> 0 | E32: WCInv effect is reduced | G32: =IF(G$4="","",-G17/G$4) -> 0 | H32: =IF(H$4="","",-H17/H$4) -> 0 | I32: =IF(I$4="","",-I17/I$4) -> 0 | J32: =IF(J$4="","",-J17/J$4) -> 0 | K32: =IF(K$4="","",-K17/K$4) -> 0 | L32: =IF(L$4="","",-L17/L$4) -> 0 | M32: =IF(M$4="","",-M17/M$4) | N32: =IF(N$4="","",-N17/N$4) | ... Q32: =IF(Q$4="","",-Q17/Q$4)
B33: Non-controling Interests | C33: =IF(BS!G33<=0,0,BS!G33/BS!G34) -> 0.0098977083 | G33: =IF(G$4="","",-G15/G$4) -> 0.063363208 | H33: =IF(H$4="","",-H15/H$4) -> 0 | I33: =IF(I$4="","",-I15/I$4) -> 0 | J33: =IF(J$4="","",-J15/J$4) -> 0 | K33: =IF(K$4="","",-K15/K$4) -> 0 | L33: =IF(L$4="","",-L15/L$4) -> 0 | M33: =IF(M$4="","",-M15/M$4) | N33: =IF(N$4="","",-N15/N$4) | ... Q33: =IF(Q$4="","",-Q15/Q$4)
B34: Total FCFE | C34: =ABS(C19/C$4) -> 0.16620743 | G34: =IF(G$4="","",ABS(G19/G$4)) -> 0.48017834 | H34: =IF(H$4="","",ABS(H19/H$4)) -> 0.58435288 | I34: =IF(I$4="","",ABS(I19/I$4)) -> 0.00015147557 | J34: =IF(J$4="","",ABS(J19/J$4)) -> 0.00026371884 | K34: =IF(K$4="","",ABS(K19/K$4)) -> 0 | L34: =IF(L$4="","",ABS(L19/L$4)) -> 0 | M34: =IF(M$4="","",ABS(M19/M$4)) | N34: =IF(N$4="","",ABS(N19/N$4)) | ... Q34: =IF(Q$4="","",ABS(Q19/Q$4))
B36: Income Tax Rate | C36: 0.25 | E36: Use the highest past tax rate | G36: =IF(G$4="","",-G14/G16) -> 0.01627902 | H36: =IF(H$4="","",-H14/H16) -> 0.28784312 | I36: =IF(I$4="","",-I14/I16) -> 0 | J36: =IF(J$4="","",-J14/J16) -> 0 | K36: =IF(K$4="","",-K14/K16) -> #DIV/0! | L36: =IF(L$4="","",-L14/L16) -> #DIV/0! | M36: =IF(M$4="","",-M14/M16) | N36: =IF(N$4="","",-N14/N16) | ... Q36: =IF(Q$4="","",-Q14/Q16)
B38: YoY Growth Rates
B39: Sales | C39: =C4/G4-1 -> 0.38781724 | G39: =IF(H4="","",G4/H4-1) -> -0.44776033 | H39: =IF(I4="","",H4/I4-1) -> 0.33871757 | I39: =IF(J4="","",I4/J4-1) -> 0.69302859 | J39: =IF(K4="","",J4/K4-1) -> 0.78205008 | K39: =IF(L4="","",K4/L4-1) -> -0.76371059 | L39: =IF(M4="","",L4/M4-1) | M39: =IF(N4="","",M4/N4-1) | N39: =IF(O4="","",N4/O4-1) | ... Q39: =IF(R4="","",Q4/R4-1)
B41: Per Share Indicators
B42: ="FCFE per share ("&Market_currency&")" -> FCFE per share (HKD) | C42: =C19*$C$3/Common_Shares*Exchange_Rate -> 0.029647921 | G42: =IF(G$4="","",G19*$C$3/Common_Shares*Exchange_Rate) -> 0.061718318 | H42: =IF(H$4="","",H19*$C$3/Common_Shares*Exchange_Rate) -> 0.13600632 | I42: =IF(I$4="","",I19*$C$3/Common_Shares*Exchange_Rate) -> 2.6335256e-05 | J42: =IF(J$4="","",J19*$C$3/Common_Shares*Exchange_Rate) -> 2.7081444e-05 | K42: =IF(K$4="","",K19*$C$3/Common_Shares*Exchange_Rate) -> 0 | L42: =IF(L$4="","",L19*$C$3/Common_Shares*Exchange_Rate) -> 0 | M42: =IF(M$4="","",M19*$C$3/Common_Shares*Exchange_Rate) | N42: =IF(N$4="","",N19*$C$3/Common_Shares*Exchange_Rate) | ... Q42: =IF(Q$4="","",Q19*$C$3/Common_Shares*Exchange_Rate)
B43: FCFE/Market Price | C43: =C42/Market_Price -> 0.017439953 | G43: =IF(G$4="","",G42/Market_Price) -> 0.036304893 | H43: =IF(H$4="","",H42/Market_Price) -> 0.08000372 | I43: =IF(I$4="","",I42/Market_Price) -> 1.5491327e-05 | J43: =IF(J$4="","",J42/Market_Price) -> 1.5930261e-05 | K43: =IF(K$4="","",K42/Market_Price) -> 0 | L43: =IF(L$4="","",L42/Market_Price) -> 0 | M43: =IF(M$4="","",M42/Market_Price) | N43: =IF(N$4="","",N42/Market_Price) | ... Q43: =IF(Q$4="","",Q42/Market_Price)
B45: Detailed Analysis | E45: Notes
B46: Operating Costs
B47: COGS | C47: =-C4*C55 -> -738887.81 | G47: =Data!C36 -> -523759 | H47: =Data!D36 -> -535391 | I47: =Data!E36 -> -647828 | J47: =Data!F36 -> -531460 | K47: =Data!G36 -> -193695 | L47: =Data!H36 -> -1515759 | M47: =Data!I36 | N47: =Data!J36 | ... Q47: =Data!M36
B48: Selling Expenses | C48: =-C4*C56 -> 0 | G48: =Data!C39 -> 0 | H48: =Data!D39 -> 0 | I48: =Data!E39 -> 0 | J48: =Data!F39 -> 0 | K48: =Data!G39 -> 0 | L48: =Data!H39 -> 0 | M48: =Data!I39 | N48: =Data!J39 | ... Q48: =Data!M39
B49: Variable Costs | C49: =C47+C48 -> -738887.81 | G49: =IF(G$4="","",G47+G48) -> -523759 | H49: =IF(H$4="","",H47+H48) -> -535391 | I49: =IF(I$4="","",I47+I48) -> -647828 | J49: =IF(J$4="","",J47+J48) -> -531460 | K49: =IF(K$4="","",K47+K48) -> -193695 | L49: =IF(L$4="","",L47+L48) -> -1515759 | M49: =IF(M$4="","",M47+M48) | N49: =IF(N$4="","",N47+N48) | ... Q49: =IF(Q$4="","",Q47+Q48)
B50: Other Opex (Fixed Overhead) | C50: =AVERAGE(G50:H50) -> -339273.5 | E50: Historical Average | G50: =Data!C40 -> -299979 | H50: =Data!D40 -> -378568 | I50: =Data!E40 -> -343154 | J50: =Data!F40 -> -250972 | K50: =Data!G40 -> -231174 | L50: =Data!H40 -> -164177 | M50: =Data!I40 | N50: =Data!J40 | ... Q50: =Data!M40
B51: - R&D | C51: =AVERAGE(G51:J51) -> 0 | E51: Historical Average | G51: =Data!C41 -> 0 | H51: =Data!D41 -> 0 | I51: =Data!E41 -> 0 | J51: =Data!F41 -> 0 | K51: =Data!G41 -> 0 | L51: =Data!H41 -> 0 | M51: =Data!I41 | N51: =Data!J41 | ... Q51: =Data!M41
B52: Fixed Costs | C52: =C50+C51 -> -339273.5 | G52: =IF(G4="","",G50+G51) -> -299979 | H52: =IF(H4="","",H50+H51) -> -378568 | I52: =IF(I4="","",I50+I51) -> -343154 | J52: =IF(J4="","",J50+J51) -> -250972 | K52: =IF(K4="","",K50+K51) -> -231174 | L52: =IF(L4="","",L50+L51) -> -164177 | M52: =IF(M4="","",M50+M51) | N52: =IF(N4="","",N50+N51) | ... Q52: =IF(Q4="","",Q50+Q51)
B54: % Sales of Operating Costs
B55: COGS | C55: =AVERAGE(G55:L55) -> 0.60262963 | E55: Historical Average | G55: =IF(G$4="","",ABS(G47/G$4)) -> 0.59283763 | H55: =IF(H$4="","",ABS(H47/H$4)) -> 0.33465932 | I55: =IF(I$4="","",ABS(I47/I$4)) -> 0.54210142 | J55: =IF(J$4="","",ABS(J47/J$4)) -> 0.75293191 | K55: =IF(K$4="","",ABS(K47/K$4)) -> 0.48901641 | L55: =IF(L$4="","",ABS(L47/L$4)) -> 0.90423111 | M55: =IF(M$4="","",ABS(M47/M$4)) | N55: =IF(N$4="","",ABS(N47/N$4)) | ... Q55: =IF(Q$4="","",ABS(Q47/Q$4))
B56: =B48 -> Selling Expenses | C56: =AVERAGE(G56:H56) -> 0 | E56: Historical Average | G56: =IF(G$4="","",ABS(G48/G$4)) -> 0 | H56: =IF(H$4="","",ABS(H48/H$4)) -> 0 | I56: =IF(I$4="","",ABS(I48/I$4)) -> 0 | J56: =IF(J$4="","",ABS(J48/J$4)) -> 0 | K56: =IF(K$4="","",ABS(K48/K$4)) -> 0 | L56: =IF(L$4="","",ABS(L48/L$4)) -> 0 | M56: =IF(M$4="","",ABS(M48/M$4)) | N56: =IF(N$4="","",ABS(N48/N$4)) | ... Q56: =IF(Q$4="","",ABS(Q48/Q$4))
B57: Variable Costs | C57: =ABS(C49/$C$4) -> 0.60262963 | G57: =IF(G$4="","",ABS(G49/G$4)) -> 0.59283763 | H57: =IF(H$4="","",ABS(H49/H$4)) -> 0.33465932 | I57: =IF(I$4="","",ABS(I49/I$4)) -> 0.54210142 | J57: =IF(J$4="","",ABS(J49/J$4)) -> 0.75293191 | K57: =IF(K$4="","",ABS(K49/K$4)) -> 0.48901641 | L57: =IF(L$4="","",ABS(L49/L$4)) -> 0.90423111 | M57: =IF(M$4="","",ABS(M49/M$4)) | N57: =IF(N$4="","",ABS(N49/N$4)) | ... Q57: =IF(Q$4="","",ABS(Q49/Q$4))
B58: =B50 -> Other Opex (Fixed Overhead) | C58: =ABS(C50/$C$4) -> 0.27670813 | G58: =IF(G$4="","",ABS(G50/G$4)) -> 0.33954326 | H58: =IF(H$4="","",ABS(H50/H$4)) -> 0.23663325 | I58: =IF(I$4="","",ABS(I50/I$4)) -> 0.28715071 | J58: =IF(J$4="","",ABS(J50/J$4)) -> 0.35555795 | K58: =IF(K$4="","",ABS(K50/K$4)) -> 0.58363861 | L58: =IF(L$4="","",ABS(L50/L$4)) -> 0.09794034 | M58: =IF(M$4="","",ABS(M50/M$4)) | N58: =IF(N$4="","",ABS(N50/N$4)) | ... Q58: =IF(Q$4="","",ABS(Q50/Q$4))
B59: =B51 -> - R&D | C59: =ABS(C51/$C$4) -> 0 | G59: =IF(G$4="","",ABS(G51/G$4)) -> 0 | H59: =IF(H$4="","",ABS(H51/H$4)) -> 0 | I59: =IF(I$4="","",ABS(I51/I$4)) -> 0 | J59: =IF(J$4="","",ABS(J51/J$4)) -> 0 | K59: =IF(K$4="","",ABS(K51/K$4)) -> 0 | L59: =IF(L$4="","",ABS(L51/L$4)) -> 0 | M59: =IF(M$4="","",ABS(M51/M$4)) | N59: =IF(N$4="","",ABS(N51/N$4)) | ... Q59: =IF(Q$4="","",ABS(Q51/Q$4))
B60: Fixed Costs | C60: =ABS(C52/$C$4) -> 0.27670813 | G60: =IF(G$4="","",ABS(G52/G$4)) -> 0.33954326 | H60: =IF(H$4="","",ABS(H52/H$4)) -> 0.23663325 | I60: =IF(I$4="","",ABS(I52/I$4)) -> 0.28715071 | J60: =IF(J$4="","",ABS(J52/J$4)) -> 0.35555795 | K60: =IF(K$4="","",ABS(K52/K$4)) -> 0.58363861 | L60: =IF(L$4="","",ABS(L52/L$4)) -> 0.09794034 | M60: =IF(M$4="","",ABS(M52/M$4)) | N60: =IF(N$4="","",ABS(N52/N$4)) | ... Q60: =IF(Q$4="","",ABS(Q52/Q$4))
B62: Non-operating EBIT
B63: Dividend or Interests from FA | C63: =BS!$G28*C70 -> 187846.87 | G63: =Data!C55 -> 328373 | H63: =Data!D55 -> 414899 | I63: =Data!E55 -> 0 | J63: =Data!F55 -> 0 | K63: =Data!G55 -> 0 | L63: =Data!H55 -> 0 | M63: =Data!I55 | N63: =Data!J55 | ... Q63: =Data!M55
B64: Share of JV or associate Results | C64: =BS!$G26*C71 -> -62883 | G64: =Data!C54 -> -62883 | H64: =Data!D54 -> -60321 | I64: =Data!E54 -> 0 | J64: =Data!F54 -> 0 | K64: =Data!G54 -> 0 | L64: =Data!H54 -> 0 | M64: =Data!I54 | N64: =Data!J54 | ... Q64: =Data!M54
B65: Investment property | C65: =BS!$G27*C72 -> 0 | G65: =Data!C56 -> 0 | H65: =Data!D56 -> 0 | I65: =Data!E56 -> 0 | J65: =Data!F56 -> 0 | K65: =Data!G56 -> 0 | L65: =Data!H56 -> 0 | M65: =Data!I56 | N65: =Data!J56 | ... Q65: =Data!M56
B66: Other Non-operating Income | C66: 0 | E66: Unable to predict, so assume 0 | G66: =Data!C57 -> 119837 | H66: =Data!D57 -> 182493 | I66: =Data!E57 -> -129706 | J66: =Data!F57 -> 153746 | K66: =Data!G57 -> 56136 | L66: =Data!H57 -> 9339 | M66: =Data!I57 | N66: =Data!J57 | ... Q66: =Data!M57
B67: Non-Operating EBIT | C67: =SUM(C63:C66) -> 124963.87 | G67: =IF(G4="","",SUM(G63:G66)) -> 385327 | H67: =IF(H4="","",SUM(H63:H66)) -> 537071 | I67: =IF(I4="","",SUM(I63:I66)) -> -129706 | J67: =IF(J4="","",SUM(J63:J66)) -> 153746 | K67: =IF(K4="","",SUM(K63:K66)) -> 56136 | L67: =IF(L4="","",SUM(L63:L66)) -> 9339 | M67: =IF(M4="","",SUM(M63:M66)) | N67: =IF(N4="","",SUM(N63:N66)) | ... Q67: =IF(Q4="","",SUM(Q63:Q66))
B69: Non-operating Asset Yield %
B70: Dividend or Interests from FA | C70: =G70 -> 0.10759456 | G70: =IFERROR(G63/BS!$G$25,0) -> 0.10759456
B71: JV or associate | C71: =G71 -> -0.080495804 | G71: =IFERROR(G64/BS!$G$26,0) -> -0.080495804
B72: Investment property | C72: =G72 -> 0 | G72: =IFERROR(G65/BS!$G$27,0) -> 0
B73: Non-Operating EBIT | C73: =C67/SUM(BS!G25:G27) -> 0.03260088 | G73: =G67/SUM(BS!G25:G27) -> 0.10052505
B75: Interest
B76: Interest Expense | C76: =-BS!G31*Normalized_FCF!C81 -> -105689 | G76: =Data!C50 -> -105689 | H76: =Data!D50 -> -102356 | I76: =Data!E50 -> -74343 | J76: =Data!F50 -> -77168 | K76: =Data!G50 -> -27358 | L76: =Data!H50 -> -5699 | M76: =Data!I50 | N76: =Data!J50 | ... Q76: =Data!M50
B77: Interest Income | C77: =BS!$G$24*C82 -> 120678.54 | G77: =Data!C51 -> 127073 | H77: =Data!D51 -> 62873 | I77: =Data!E51 -> 0 | J77: =Data!F51 -> 0 | K77: =Data!G51 -> 0 | L77: =Data!H51 -> 0 | M77: =Data!I51 | N77: =Data!J51 | ... Q77: =Data!M51
B78: Net Interest Income | C78: =C76+C77 -> 14989.54 | G78: =IF(G4="","",G76+G77) -> 21384 | H78: =IF(H4="","",H76+H77) -> -39483 | I78: =IF(I4="","",I76+I77) -> -74343 | J78: =IF(J4="","",J76+J77) -> -77168 | K78: =IF(K4="","",K76+K77) -> -27358 | L78: =IF(L4="","",L76+L77) -> -5699 | M78: =IF(M4="","",M76+M77) | N78: =IF(N4="","",N76+N77) | ... Q78: =IF(Q4="","",Q76+Q77)
B80: % Interest
B81: Interest Rate/Debt | C81: =Normalized_FCF!G81 -> 0.032608166 | E81: Use Last year's rate | G81: =IFERROR(ABS(Normalized_FCF!G76/BS!$G$31),0) -> 0.032608166
B82: Interest Yield/Cash | C82: 0.03 | E82: Reference the market rate | G82: =IF(Normalized_FCF!G4="","",Normalized_FCF!G77/BS!$G$24) -> 0.031589626
B84: Balance Sheet Analysis | E84: Notes
B85: Balance Sheet
B86: Total Assets | C86: =BS!G23 -> 14352098 | G86: =IF(G$4="","",G90+G89) -> 3670169 | H86: =IF(H$4="","",H90+H89) -> 3559477 | I86: =IF(I$4="","",I90+I89) -> 3413258 | J86: =IF(J$4="","",J90+J89) -> 1603329 | K86: =IF(K$4="","",K90+K89) -> 1218998 | L86: =IF(L$4="","",L90+L89) -> 0 | M86: =IF(M$4="","",M90+M89) | N86: =IF(N$4="","",N90+N89) | ... Q86: =IF(Q$4="","",Q90+Q89)
B87: Incl. ST AR | C87: =BS!C4 -> 649112 | G87: =IF(G$4="","",Data!D75) -> 0 | H87: =IF(H$4="","",Data!E75) -> 0 | I87: =IF(I$4="","",Data!F75) -> 0 | J87: =IF(J$4="","",Data!G75) -> 0 | K87: =IF(K$4="","",Data!H75) -> 0 | L87: =IF(L$4="","",Data!I75) -> 0 | M87: =IF(M$4="","",Data!J75) | N87: =IF(N$4="","",Data!K75) | ... Q87: =IF(Q$4="","",Data!N75)
B88: Incl. ST Inventory | C88: =BS!C7+BS!C8 -> 0 | G88: =IF(G$4="","",Data!D76) -> 0 | H88: =IF(H$4="","",Data!E76) -> 0 | I88: =IF(I$4="","",Data!F76) -> 0 | J88: =IF(J$4="","",Data!G76) -> 0 | K88: =IF(K$4="","",Data!H76) -> 0 | L88: =IF(L$4="","",Data!I76) -> 0 | M88: =IF(M$4="","",Data!J76) | N88: =IF(N$4="","",Data!K76) | ... Q88: =IF(Q$4="","",Data!N76)
B89: Total Liabilities | C89: =BS!G30 -> 4197215 | G89: =Data!C77 -> 642877 | H89: =Data!D77 -> 734909 | I89: =Data!E77 -> 677999 | J89: =Data!F77 -> 1352795 | K89: =Data!G77 -> 1205068 | L89: =Data!H77 -> 0 | M89: =Data!I77 | N89: =Data!J77 | ... Q89: =Data!M77
B90: Total Equity | C90: =BS!G32 -> 10154883 | G90: =Data!C78 -> 3027292 | H90: =Data!D78 -> 2824568 | I90: =Data!E78 -> 2735259 | J90: =Data!F78 -> 250534 | K90: =Data!G78 -> 13930 | L90: =Data!H78 -> 0 | M90: =Data!I78 | N90: =Data!J78 | ... Q90: =Data!M78
B92: % Sales
B93: ST_AR | C93: =C87/C$4 -> 0.52940937 | G93: =IF(G$4="","",G87/G$4) -> 0 | H93: =IF(H$4="","",H87/H$4) -> 0 | I93: =IF(I$4="","",I87/I$4) -> 0 | J93: =IF(J$4="","",J87/J$4) -> 0 | K93: =IF(K$4="","",K87/K$4) -> 0 | L93: =IF(L$4="","",L87/L$4) -> 0 | M93: =IF(M$4="","",M87/M$4) | N93: =IF(N$4="","",N87/N$4) | ... Q93: =IF(Q$4="","",Q87/Q$4)
B94: ST_Inventory | C94: =C88/C$4 -> 0 | G94: =IF(G$4="","",G88/G$4) -> 0 | H94: =IF(H$4="","",H88/H$4) -> 0 | I94: =IF(I$4="","",I88/I$4) -> 0 | J94: =IF(J$4="","",J88/J$4) -> 0 | K94: =IF(K$4="","",K88/K$4) -> 0 | L94: =IF(L$4="","",L88/L$4) -> 0 | M94: =IF(M$4="","",M88/M$4) | N94: =IF(N$4="","",N88/N$4) | ... Q94: =IF(Q$4="","",Q88/Q$4)
B96: Leverage
B97: Pre-tax Profit/Interest Expense | C97: =-C4/C76 -> 11.601075 | G97: =IF(G4="","",-G4/G76) -> 8.3592238 | H97: =IF(H4="","",-H4/H76) -> 15.629851 | I97: =IF(I4="","",-I4/I76) -> 16.07456 | J97: =IF(J4="","",-J4/J76) -> 9.146978 | K97: =IF(K4="","",-K4/K76) -> 14.478069 | L97: =IF(L4="","",-L4/L76) -> 294.13862 | M97: =IF(M4="","",-M4/M76) | N97: =IF(N4="","",-N4/N76) | ... Q97: =IF(Q4="","",-Q4/Q76)
B98: Equity / Total Assets | C98: =C90/C86 -> 0.70755391 | G98: =IF(G90="","",G90/G86) -> 0.82483722 | H98: =IF(H90="","",H90/H86) -> 0.79353456 | I98: =IF(I90="","",I90/I86) -> 0.8013631 | J98: =IF(J90="","",J90/J86) -> 0.15625863 | K98: =IF(K90="","",K90/K86) -> 0.011427418 | L98: =IF(L90="","",L90/L86) -> #DIV/0! | M98: =IF(M90="","",M90/M86) | N98: =IF(N90="","",N90/N86) | ... Q98: =IF(Q90="","",Q90/Q86)
B100: ROE | G100: =IFERROR(IF(#REF!*G102*(1/G98)=G104,"","Error"),"") | H100: =IFERROR(IF(#REF!*H102*(1/H98)=H104,"","Error"),"") | I100: =IFERROR(IF(#REF!*I102*(1/I98)=I104,"","Error"),"") | J100: =IFERROR(IF(#REF!*J102*(1/J98)=J104,"","Error"),"") | K100: =IFERROR(IF(#REF!*K102*(1/K98)=K104,"","Error"),"") | L100: =IFERROR(IF(#REF!*L102*(1/L98)=L104,"","Error"),"") | M100: =IFERROR(IF(#REF!*M102*(1/M98)=M104,"","Error"),"") | N100: =IFERROR(IF(#REF!*N102*(1/N98)=N104,"","Error"),"") | ... Q100: =IFERROR(IF(#REF!*Q102*(1/Q98)=Q104,"","Error"),"")
B101: EBIT/Sales | C101: =C25 -> 0.12066223 | G101: =G25 -> 0.091006228 | H101: =H25 -> 0.44152521 | I101: =I25 -> 0.17089935 | J101: =J25 -> 0.10822614 | K101: =K25 -> 0.072655021 | L101: =L25 -> 0.0021714542 | M101: =M25 | N101: =N25 | ... Q101: =Q25
B102: Sales/Total Assets | C102: =C4/C86 -> 0.085430437 | G102: =IF(G4="","",G4/G86) -> 0.24071862 | H102: =IF(H4="","",H4/H86) -> 0.44945058 | I102: =IF(I4="","",I4/I86) -> 0.35011447 | J102: =IF(J4="","",J4/J86) -> 0.44024277 | K102: =IF(K4="","",K4/K86) -> 0.32493162 | L102: =IF(L4="","",L4/L86) -> #DIV/0! | M102: =IF(M4="","",M4/M86) | N102: =IF(N4="","",N4/N86) | ... Q102: =IF(Q4="","",Q4/Q86)
B103: Total Assets/Equity | C103: =C86/C90 -> 1.4133199 | G103: =IF(G$4="","",G86/G90) -> 1.2123604 | H103: =IF(H$4="","",H86/H90) -> 1.2601846 | I103: =IF(I$4="","",I86/I90) -> 1.2478738 | J103: =IF(J$4="","",J86/J90) -> 6.3996464 | K103: =IF(K$4="","",K86/K90) -> 87.50883 | L103: =IF(L$4="","",L86/L90) -> #DIV/0! | M103: =IF(M$4="","",M86/M90) | N103: =IF(N$4="","",N86/N90) | ... Q103: =IF(Q$4="","",Q86/Q90)
B104: EBIT ROE | C104: =C10/C90 -> 0.014568823 | G104: =IF(G$4="","",G10/G90) -> 0.02655905 | H104: =IF(H$4="","",H10/H90) -> 0.25007576 | I104: =IF(I$4="","",I10/I90) -> 0.074665696 | J104: =IF(J$4="","",J10/J90) -> -0.30491611 | K104: =IF(K$4="","",K10/K90) -> -2.0659009 | L104: =IF(L$4="","",L10/L90) -> #DIV/0! | M104: =IF(M$4="","",M10/M90) | N104: =IF(N$4="","",N10/N90) | ... Q104: =IF(Q$4="","",Q10/Q90)
B106: Dividend Analysis | E106: Notes
B107: Dividend
B108: Dividend per share | C108: =G108 -> 0.0548 | G108: =Data!C63 -> 0.0548 | H108: =Data!D63 -> 0.0952 | I108: =Data!E63 -> 0 | J108: =Data!F63 -> 0 | K108: =Data!G63 -> 0 | L108: =Data!H63 -> 0 | M108: =Data!I63 | N108: =Data!J63 | ... Q108: =Data!M63
B109: Dividend | C109: =C108*Common_Shares/$C$3 -> 399273.65 | G109: =IF(G$4="","",G108*Common_Shares/$C$3) -> 399273.65 | H109: =IF(H$4="","",H108*Common_Shares/$C$3) -> 693628.67 | I109: =IF(I$4="","",I108*Common_Shares/$C$3) -> 0 | J109: =IF(J$4="","",J108*Common_Shares/$C$3) -> 0 | K109: =IF(K$4="","",K108*Common_Shares/$C$3) -> 0 | L109: =IF(L$4="","",L108*Common_Shares/$C$3) -> 0 | M109: =IF(M$4="","",M108*Common_Shares/$C$3) | N109: =IF(N$4="","",N108*Common_Shares/$C$3) | ... Q109: =IF(Q$4="","",Q108*Common_Shares/$C$3)
B110: Dividend/FCFE before WCInv | C110: =C108/(C19*$C$3/Common_Shares) -> 1.9592605 | G110: =IF(G$4="","",G108/(G19*$C$3/Common_Shares)) -> 0.94117924 | H110: =IF(H$4="","",H108/(H19*$C$3/Common_Shares)) -> 0.7419655 | I110: =IF(I$4="","",I108/(I19*$C$3/Common_Shares)) -> 0 | J110: =IF(J$4="","",J108/(J19*$C$3/Common_Shares)) -> 0 | K110: =IF(K$4="","",K108/(K19*$C$3/Common_Shares)) -> #DIV/0! | L110: =IF(L$4="","",L108/(L19*$C$3/Common_Shares)) -> #DIV/0! | M110: =IF(M$4="","",M108/(M19*$C$3/Common_Shares)) | N110: =IF(N$4="","",N108/(N19*$C$3/Common_Shares)) | ... Q110: =IF(Q$4="","",Q108/(Q19*$C$3/Common_Shares))

Sheet BS
B1: Most Recent Quarter | C1: 45473 | F1: =IF(MONTH(C1)=MONTH(Normalized_FCF!G1),"FY","Quarter")&" Report" -> Quarter Report
B2: Lastest Balance Sheet
B3: Operating Assets | C3: =Data!C3 -> 1000 | D3: Valued @ | F3: Non-Operating Assets | H3: Valued @
B4: ST AR | C4: 649112 | D4: 0.6 | F4: Cash and cash equivalents | G4: 4022618 | H4: 0.9
B5: Operating ST Financial Assets | C5: 0 | D5: 0.6 | F5: Restricted cash | G5: 0 | H5: 0.8
B6: Prepayments and Contract Assets | C6: 0 | D6: 0.1 | F6: ST Income Stock/Debt | G6: 0 | H6: 0.7
B7: Inventory | C7: 0 | D7: 0.5 | F7: ST Other Securities | G7: 171402 | H7: 0.6
B8: Operating Properties held for sale | C8: 0 | D8: 0.6 | F8: Properties held for sale | G8: 0 | H8: 0.6
B9: ST DTA | C9: 0 | D9: 0.9 | F9: Properties under development | G9: 0 | H9: 0.6
B10: Other ST Assets | C10: 0 | D10: 0.05 | F10: Non-Operating ST Assets | G10: =SUM(G4:G9) -> 4194020 | H10: =G4*H4+G5*H5+G6*H6+G7*H7+G8*H8+G9*H9 -> 3723197.4
B11: Operating ST Assets | C11: =SUM(C4:C10) -> 649112 | D11: =C4*D4+C5*D5+C6*D6+C7*D7+C8*D8+C9*D9+C10*D10 -> 389467.2 | F11: LT Depositis | G11: 0 | H11: 0.8
B12: LT AR | C12: 103165 | D12: 0.4 | F12: LT Income Stock/Debt | G12: =2479179+572769 -> 3051948 | H12: 0.7
B13: Operating LT Financial Assets | C13: 0 | D13: 0.5 | F13: LT Other Securities | G13: =4626423-G12 -> 1574475 | H13: 0.6
B14: Operating Investment Properties | C14: 875642 | D14: 0.6 | F14: Investments in JV or associate | G14: 781196 | H14: 0.1
B15: PP&E & Right of Use Assets | C15: 2545809 | D15: 0.1 | F15: Investment property | G15: 0 | H15: 0.2
B16: Biological assets | C16: 0 | D16: 0.05 | F16: Properties under development | G16: 0 | H16: 0.1
B17: Intangible assets | C17: 0 | D17: 0.05 | F17: Non-Operating LT Assets | G17: =SUM(G11:G16) -> 5407619 | H17: =G11*H11+G12*H12+G13*H13+G14*H14+G15*H15+G16*H16 -> 3159168.2
B18: LT DTA | C18: 23095 | D18: 0.9
B19: Other assets & Goodwill | C19: 553636 | D19: 0 | F19: Operating Assets | G19: =C11+C20 -> 4750459 | H19: =D11+D20 -> 1231484.8
B20: Operating LT Assets | C20: =SUM(C12:C19) -> 4101347 | D20: =C12*D12+C13*D13+C14*D14+C15*D15+C16*D16+C17*D17+C18*D18+C19*D19 -> 842017.6 | F20: Non-operating Assets | G20: =G10+G17 -> 9601639 | H20: =H10+H17 -> 6882365.6
B22: Liabilities | G22: Book | H22: Estimate
B23: ST Borrowing | C23: 30697 | F23: Total Assets | G23: =G19+G20 -> 14352098 | H23: =H19+H20 -> 8113850.4
B24: ST Lease liabilities | C24: 143877 | F24: incl. Cash | G24: =G4+G5+G11 -> 4022618
B25: ST SH Loan | C25: 0 | F25: incl. Income Stock/Debt | G25: =G6+G12 -> 3051948
B26: ST Financial Liabilities | C26: 222396 | F26: incl. JV or associate | G26: =G14 -> 781196
B27: ST Debt | C27: =SUM(C23:C26) -> 396970 | F27: incl. Investment property | G27: =G15 -> 0
B28: Other ST liabilities | C28: =C29-C27 -> 844275 | F28: incl. Other Securities | G28: =G7+G13 -> 1745877 | H28: =G7*H7+G13*H13 -> 1047526.2
B29: Current Liabilities | C29: 1241245 | F29: incl. Fixed Assets | G29: =SUM(C14:C17)+SUM(G15:G16) -> 3421451
B30: LT Borrowing | C30: 1075543 | F30: Total Liabilities | G30: =C29+C36 -> 4197215
B31: LT Lease liabilities | C31: 1679438 | F31: incl. Interest-bearing Debt | G31: =C27+C34 -> 3241182
B32: LT SH Loan | C32: 0 | F32: Total Equity | G32: =G23-G30 -> 10154883 | H32: =H23-G30 -> 3916635.4
B33: LT Financial Liabilities | C33: 89231 | F33: Incl. Non-common Interest | G33: 99525
B34: LT Debt | C34: =SUM(C30:C33) -> 2844212 | F34: Incl. Common Equity | G34: =G32-G33 -> 10055358 | H34: =H32-G33 -> 3817110.4
B35: Other LT liabilities | C35: =C36-C34 -> 111758
B36: Noncurrent Liabilities | C36: 2955970
B38: Balance Sheet Analysis
B39: Asset Value | C39: Book | D39: Estimate
B40: ="Equity per share ("&Market_currency&")" -> Equity per share (HKD) | C40: =G34*C3/Common_Shares*Exchange_Rate -> 1.4628955 | D40: =H34*C3/Common_Shares*Exchange_Rate -> 0.55532919
B42: Leverage % | C42: Normalized | D42: Latest | F42: Notes
B43: D&A/Fixed Assets | C43: =D43 -> 0.010514253 | D43: =Normalized_FCF!G8/BS!$G$29 -> 0.010514253 | F43: Same as Last year's D&A
B44: Fixed Assets/Total Assets | D44: =G29/G23 -> 0.23839379
B45: Debt/EBIT | D45: =BS!G31/Normalized_FCF!C10 -> 21.908066
B47: Profibility % | C47: Normalized | D47: Latest
B48: Operating Asset Yield | C48: =Normalized_FCF!C10/G19 -> 0.031143241 | D48: =Normalized_FCF!G10/G19 -> 0.016925101
B49: Non-Operating Asset Yield | C49: =Normalized_FCF!C11/G20 -> 0.013014847 | D49: =Normalized_FCF!G11/G20 -> 0.040131378

Sheet Valuation_Model
B2: No-Growth DCF Valuation Analysis | H2: Notes
B3: No-Growth DCF | C3: =Normalized_FCF!C3 -> 1000 | E3: Special Assumption
B4: Adjusted FCFE | C4: =Normalized_FCF!C19 -> 203787.93 | D4: =Reporting_currency -> CNY | E4: Terminal Growth Rate: | F4: 0
B5: /Equity Cost of Capital | C5: =Thesis!C37 -> 0.1 | E5: - Expects no significant growth at terminal years
B6: = Enterprise Value | C6: =(C4*(1+Terminal_Growth))/(Equity_Cost-Terminal_Growth) -> 2037879.3 | E6: - Avoids overvaluation.
B7: - Interest Bearing Debt | C7: =BS!G31 -> 3241182
B8: + Other Securities | C8: =BS!H28 -> 1047526.2
B9: = Equity Value | C9: =C6-C7+C8 -> -155776.47 | D9: =Reporting_currency -> CNY
B10: * Exchange rate | C10: =Exchange_Rate -> 1.06
B11: Equity Value per share | C11: =(C9*C3)/Common_Shares*C10 -> -0.022663013 | D11: =Market_currency -> HKD
B13: Implied Growth Sensitivity Test
B14: FCFE Projection
B15: High Growth Period (HGP) | C15: =Scenarios!C25 -> 0.17
B16: High Growth Rate (HGR) | C16: =Scenarios!C24 -> 15
B17: Value Per Share | C17: =(F51-C7)/Common_Shares*C3 -> 0.34543073 | D17: =IF(ROUND(C17,1)=ROUND(Scenarios!C29,1),"equals Market Price","a Current Projection") -> a Current Projection
B19: Year | C19: FCFE | D19: Growth Rates | E19: Discount Factor | F19: PV of FCFE
B20: 1 | C20: =C4*(1+D20) -> 238431.88 | D20: =IF($C$16<B20,0,Valuation_Model!$C$15) -> 0.17 | E20: =IF($C$16<B20,0,1/(1+Equity_Cost)^B20) -> 0.90909091 | F20: =C20*E20 -> 216756.26
B21: 2 | C21: =IF(ROW()-ROW($C$20)<$C$16, $C$20*(1+D21)^(ROW()-ROW($C$20)), 0) -> 278965.3 | D21: =IF($C$16<B21,0,Valuation_Model!$C$15) -> 0.17 | E21: =IF($C$16<B21,0,1/(1+Equity_Cost)^B21) -> 0.82644628 | F21: =C21*E21 -> 230549.84
B22: 3 | C22: =IF(ROW()-ROW($C$20)<$C$16, $C$20*(1+D22)^(ROW()-ROW($C$20)), 0) -> 326389.4 | D22: =IF($C$16<B22,0,Valuation_Model!$C$15) -> 0.17 | E22: =IF($C$16<B22,0,1/(1+Equity_Cost)^B22) -> 0.7513148 | F22: =C22*E22 -> 245221.19
B23: 4 | C23: =IF(ROW()-ROW($C$20)<$C$16, $C$20*(1+D23)^(ROW()-ROW($C$20)), 0) -> 381875.6 | D23: =IF($C$16<B23,0,Valuation_Model!$C$15) -> 0.17 | E23: =IF($C$16<B23,0,1/(1+Equity_Cost)^B23) -> 0.68301346 | F23: =C23*E23 -> 260826.17
B24: 5 | C24: =IF(ROW()-ROW($C$20)<$C$16, $C$20*(1+D24)^(ROW()-ROW($C$20)), 0) -> 446794.45 | D24: =IF($C$16<B24,0,Valuation_Model!$C$15) -> 0.17 | E24: =IF($C$16<B24,0,1/(1+Equity_Cost)^B24) -> 0.62092132 | F24: =C24*E24 -> 277424.2
B25: 6 | C25: =IF(ROW()-ROW($C$20)<$C$16, $C$20*(1+D25)^(ROW()-ROW($C$20)), 0) -> 522749.51 | D25: =IF($C$16<B25,0,Valuation_Model!$C$15) -> 0.17 | E25: =IF($C$16<B25,0,1/(1+Equity_Cost)^B25) -> 0.56447393 | F25: =C25*E25 -> 295078.47
B26: 7 | C26: =IF(ROW()-ROW($C$20)<$C$16, $C$20*(1+D26)^(ROW()-ROW($C$20)), 0) -> 611616.93 | D26: =IF($C$16<B26,0,Valuation_Model!$C$15) -> 0.17 | E26: =IF($C$16<B26,0,1/(1+Equity_Cost)^B26) -> 0.51315812 | F26: =C26*E26 -> 313856.19
B27: 8 | C27: =IF(ROW()-ROW($C$20)<$C$16, $C$20*(1+D27)^(ROW()-ROW($C$20)), 0) -> 715591.8 | D27: =IF($C$16<B27,0,Valuation_Model!$C$15) -> 0.17 | E27: =IF($C$16<B27,0,1/(1+Equity_Cost)^B27) -> 0.46650738 | F27: =C27*E27 -> 333828.86
B28: 9 | C28: =IF(ROW()-ROW($C$20)<$C$16, $C$20*(1+D28)^(ROW()-ROW($C$20)), 0) -> 837242.41 | D28: =IF($C$16<B28,0,Valuation_Model!$C$15) -> 0.17 | E28: =IF($C$16<B28,0,1/(1+Equity_Cost)^B28) -> 0.42409762 | F28: =C28*E28 -> 355072.51
B29: 10 | C29: =IF(ROW()-ROW($C$20)<$C$16, $C$20*(1+D29)^(ROW()-ROW($C$20)), 0) -> 979573.62 | D29: =IF($C$16<B29,0,Valuation_Model!$C$15) -> 0.17 | E29: =IF($C$16<B29,0,1/(1+Equity_Cost)^B29) -> 0.38554329 | F29: =C29*E29 -> 377668.04
B30: 11 | C30: =IF(ROW()-ROW($C$20)<$C$16, $C$20*(1+D30)^(ROW()-ROW($C$20)), 0) -> 1146101.1 | D30: =IF($C$16<B30,0,Valuation_Model!$C$15) -> 0.17 | E30: =IF($C$16<B30,0,1/(1+Equity_Cost)^B30) -> 0.3504939 | F30: =C30*E30 -> 401701.46
B31: 12 | C31: =IF(ROW()-ROW($C$20)<$C$16, $C$20*(1+D31)^(ROW()-ROW($C$20)), 0) -> 1340938.3 | D31: =IF($C$16<B31,0,Valuation_Model!$C$15) -> 0.17 | E31: =IF($C$16<B31,0,1/(1+Equity_Cost)^B31) -> 0.31863082 | F31: =C31*E31 -> 427264.28
B32: 13 | C32: =IF(ROW()-ROW($C$20)<$C$16, $C$20*(1+D32)^(ROW()-ROW($C$20)), 0) -> 1568897.8 | D32: =IF($C$16<B32,0,Valuation_Model!$C$15) -> 0.17 | E32: =IF($C$16<B32,0,1/(1+Equity_Cost)^B32) -> 0.28966438 | F32: =C32*E32 -> 454453.82
... B49: 30 | C49: =IF(ROW()-ROW($C$20)<$C$16, $C$20*(1+D49)^(ROW()-ROW($C$20)), 0) -> 0 | D49: =IF($C$16<B49,0,Valuation_Model!$C$15) -> 0 | E49: =IF($C$16<B49,0,1/(1+Equity_Cost)^B49) -> 0 | F49: =C49*E49 -> 0
B50: Terminal Year | C50: =C$20*(1+Terminal_Growth)^$C$16/Equity_Cost -> 2384318.8 | D50: =Terminal_Growth -> 0 | E50: =1/(1+Equity_Cost)^C16 -> 0.23939205 | F50: =C50*E50 -> 570786.97
E51: Total PV | F51: =SUM(F20:F50) -> 5757995.6
B53: Sensitivity Analysis (Enterprise Value)
A54: =F51 -> 5757995.6 | B54: =C77 -> -0.05 | C54: =C76 -> 0.05 | D54: =C75 -> 0.15 | E54: =C74 -> 0.15 | F54: =C73 -> 0.2
A55: 5 | B55: 1872646.2 | C55: 2216763.3 | D55: 2621766.4 | E55: 2621766.4 | F55: 2851332.9
A56: 10 | B56: 1739129.1 | C56: 2416926.4 | D56: 3527103.1 | E56: 3527103.1 | F56: 4335121.3
A57: 15 | B57: 1610971.9 | C57: 2661951.4 | D57: 5004177.6 | E57: 5004177.6 | F57: 7159584.9
A58: 20 | B58: 1509654 | C58: 2909775.1 | D58: 7063977.8 | E58: 7063977.8 | F58: 11853815
A59: 25 | B59: 1436297.3 | C59: 3139479.6 | D59: 9770004.8 | E59: 9770004.8 | F59: 19311723
A60: 30 | B60: 1385729.5 | C60: 3342197.5 | D60: 13232474 | E60: 13232474 | F60: 30961912
B62: Sensitivity Analysis (Equity Value per share)
B63: =B54 -> -0.05 | C63: =C54 -> 0.05 | D63: =D54 -> 0.15 | E63: =E54 -> 0.15 | F63: =F54 -> 0.2
A64: 0 | B64: =C11 -> -0.022663013 | C64: =C11 -> -0.022663013 | D64: =C11 -> -0.022663013 | E64: =C11 -> -0.022663013 | F64: =C11 -> -0.022663013
A65: =A55 -> 5 | B65: =(B55-$C$7+$C$8)/Common_Shares*$C$3*Exchange_Rate -> -0.046701813 | C65: =(C55-$C$7+$C$8)/Common_Shares*$C$3*Exchange_Rate -> 0.0033617754 | D65: =(D55-$C$7+$C$8)/Common_Shares*$C$3*Exchange_Rate -> 0.062283327 | E65: =(E55-$C$7+$C$8)/Common_Shares*$C$3*Exchange_Rate -> 0.062283327 | F65: =(F55-$C$7+$C$8)/Common_Shares*$C$3*Exchange_Rate -> 0.095681621
A66: =A56 -> 10 | B66: =(B56-$C$7+$C$8)/Common_Shares*$C$3*Exchange_Rate -> -0.066126444 | C66: =(C56-$C$7+$C$8)/Common_Shares*$C$3*Exchange_Rate -> 0.032482336 | D66: =(D56-$C$7+$C$8)/Common_Shares*$C$3*Exchange_Rate -> 0.1939955 | E66: =(E56-$C$7+$C$8)/Common_Shares*$C$3*Exchange_Rate -> 0.1939955 | F66: =(F56-$C$7+$C$8)/Common_Shares*$C$3*Exchange_Rate -> 0.31154936
A67: =A57 -> 15 | B67: =(B57-$C$7+$C$8)/Common_Shares*$C$3*Exchange_Rate -> -0.084771287 | C67: =(C57-$C$7+$C$8)/Common_Shares*$C$3*Exchange_Rate -> 0.068129596 | D67: =(D57-$C$7+$C$8)/Common_Shares*$C$3*Exchange_Rate -> 0.40888647 | E67: =(E57-$C$7+$C$8)/Common_Shares*$C$3*Exchange_Rate -> 0.40888647 | F67: =(F57-$C$7+$C$8)/Common_Shares*$C$3*Exchange_Rate -> 0.72246413
A68: =A58 -> 20 | B68: =(B58-$C$7+$C$8)/Common_Shares*$C$3*Exchange_Rate -> -0.099511441 | C68: =(C58-$C$7+$C$8)/Common_Shares*$C$3*Exchange_Rate -> 0.10418403 | D68: =(D58-$C$7+$C$8)/Common_Shares*$C$3*Exchange_Rate -> 0.70855481 | E68: =(E58-$C$7+$C$8)/Common_Shares*$C$3*Exchange_Rate -> 0.70855481 | F68: =(F58-$C$7+$C$8)/Common_Shares*$C$3*Exchange_Rate -> 1.4054003
A69: =A59 -> 25 | B69: =(B59-$C$7+$C$8)/Common_Shares*$C$3*Exchange_Rate -> -0.11018369 | C69: =(C59-$C$7+$C$8)/Common_Shares*$C$3*Exchange_Rate -> 0.1376024 | D69: =(D59-$C$7+$C$8)/Common_Shares*$C$3*Exchange_Rate -> 1.1022389 | E69: =(E59-$C$7+$C$8)/Common_Shares*$C$3*Exchange_Rate -> 1.1022389 | F69: =(F59-$C$7+$C$8)/Common_Shares*$C$3*Exchange_Rate -> 2.490408
A70: =A60 -> 30 | B70: =(B60-$C$7+$C$8)/Common_Shares*$C$3*Exchange_Rate -> -0.11754049 | C70: =(C60-$C$7+$C$8)/Common_Shares*$C$3*Exchange_Rate -> 0.16709466 | D70: =(D60-$C$7+$C$8)/Common_Shares*$C$3*Exchange_Rate -> 1.6059734 | E70: =(E60-$C$7+$C$8)/Common_Shares*$C$3*Exchange_Rate -> 1.6059734 | F70: =(F60-$C$7+$C$8)/Common_Shares*$C$3*Exchange_Rate -> 4.1853263
B72: Scenarios | C72: HGR | D72: HGP | E72: Value per share | F72: Capitialization
B73: =Scenarios!B67 -> Revaluation | C73: =Scenarios!C69 -> 0.2 | D73: =Scenarios!C68 -> 10 | E73: =INDEX(B$64:F$70, MATCH(D73, A$64:A$70, 0), MATCH(C73, B$63:F$63, 0)) -> 0.31154936 | F73: =E73*Common_Shares/1000000 -> 2269.9534
B74: =Scenarios!B49 -> Optimistic | C74: =Scenarios!C51 -> 0.15 | D74: =Scenarios!C50 -> 10 | E74: =INDEX(B$64:F$70, MATCH(D74, A$64:A$70, 0), MATCH(C74, B$63:F$63, 0)) -> 0.1939955 | F74: =E74*Common_Shares/1000000 -> 1413.4542 | H74: MATCH(1%, C65:E65, 0) finds the column number for HGR = 1%.
B75: =Scenarios!B37 -> Base | C75: =Scenarios!C39 -> 0.15 | D75: =Scenarios!C38 -> 10 | E75: =INDEX(B$64:F$70, MATCH(D75, A$64:A$70, 0), MATCH(C75, B$63:F$63, 0)) -> 0.1939955 | F75: =E75*Common_Shares/1000000 -> 1413.4542 | H75: MATCH(5, B66:B69, 0) finds the row number for HGP = 5.
B76: =Scenarios!B43 -> Pessimistic | C76: =Scenarios!C45 -> 0.05 | D76: =Scenarios!C44 -> 10 | E76: =INDEX(B$64:F$70, MATCH(D76, A$64:A$70, 0), MATCH(C76, B$63:F$63, 0)) -> 0.032482336 | F76: =E76*Common_Shares/1000000 -> 236.6668 | H76: INDEX(C66:E69, ...) retrieves the value from the specified range.
B77: =Scenarios!B61 -> Devil's advocate | C77: =Scenarios!C63 -> -0.05 | D77: =Scenarios!C62 -> 10 | E77: =INDEX(B$64:F$70, MATCH(D77, A$64:A$70, 0), MATCH(C77, B$63:F$63, 0)) -> -0.066126444 | F77: =E77*Common_Shares/1000000 -> -481.79829

Sheet Scenarios
B2: Current Situation
B3: Selection
B4: Past Years Selected | C4: 4 | E4: Tie the business story into the three levers of value: FCFE, growth and risk.
B6: FCFE | C6: =Valuation_Model!C3 -> 1000 | E6: Prompt for Scenario Analysis
B7: Lastest | C7: =Normalized_FCF!G19 -> 424227 | E7: Given 六福珠宝’s (0590.HK) normalized FCFE of HKD 1,270,672,000, please analyze its valuation assumptions under three scenarios (Base, Pessimistic, Optimistic) using a two-stage model, a growth stage and a terminal stage. Define the growth period, growth rates and probabilities for each scenario. Explain the rationale behind the probabilities. Summarize the business drivers and scenario narratives to align with the model’s inputs. For context only, the terminal value assumes 0% growth to prevent overvaluation. The finalized scenarios will be incorporated directly into the valuation framework.”
B8: Normalized | C8: =Normalized_FCF!C19 -> 203787.93
B10: Growth Rate
B11: Sales Growth Rates | C11: =AVERAGE(Normalized_FCF!G39:INDEX(Normalized_FCF!G39:Q39, $C$4)) -> 0.34150898
B12: Op. FCFE Before WCInv
B13: Non-Operating Income
B15: Margin
B16: Contribution Margin
B17: Op. FCFE Before WCInv
B19: Objective Scenarios
B20: No Growth Scenario | E20: Business Story
B21: Value per share | C21: =Valuation_Model!E76 -> 0.032482336 | D21: =Reporting_currency -> CNY | E21: Unbiased Scenario where the company FCFE has no growth and no risk.
B23: Market Scenario
B24: High Growth Period (HGP) | C24: 15
B25: High Growth Rate (HGR) | C25: 0.17
B26: Value per share | C26: =Valuation_Model!C17 -> 0.34543073
B28: Reference Price Points
B29: Market Price | C29: =Market_Price -> 1.7
B30: 52 week High | C30: 13
B31: 52 week Low
B33: General Scenarios
B34: Assumption
B35: High Growth Period (HGP) | C35: 10 | E35: For both Base and Pessimistic case, I would use 10 yrs to do forecast
B37: Base | E37: Business Story
B38: High Growth Period (HGP) | C38: =C35 -> 10
B39: High Growth Rate (HGR) | C39: 0.15
B40: Value per share | C40: =Valuation_Model!E75 -> 0.1939955 | D40: =Market_currency -> HKD
B41: Probabilities | C41: 0.5
B43: Pessimistic | E43: Business Story
B44: High Growth Period (HGP) | C44: =C35 -> 10
B45: High Growth Rate (HGR) | C45: 0.05
B46: Value per share | C46: =Valuation_Model!E76 -> 0.032482336 | D46: =Market_currency -> HKD
B47: Probabilities | C47: 0.25
B49: Optimistic | E49: Business Story
B50: High Growth Period (HGP) | C50: 10
B51: High Growth Rate (HGR) | C51: 0.15
B52: Value per share | C52: =Valuation_Model!E74 -> 0.1939955 | D52: =Market_currency -> HKD
B53: Probabilities | C53: =1-C41-C47 -> 0.25
B55: Expected Value = | C55: =C40*C41+C46*C47+C52*C53 -> 0.15361721 | D55: =Market_currency -> HKD
B57: Extreme Scenarios
B58: Assumption
B59: High Growth Period (HGP) | C59: 10
B61: Devil's advocate | E61: Business Story
B62: High Growth Period (HGP) | C62: =C59 -> 10 | E62: There is always a chance the some devil's advocate is right and I'm wrong, so the probabilities should reflect this depending on how illogical this implied drivers are.
B63: High Growth Rate (HGR) | C63: -0.05
B64: Value per share | C64: =Valuation_Model!E77 -> -0.066126444 | D64: =Market_currency -> HKD
B65: Probabilities | C65: 0.1
B67: Revaluation | E67: Business Story
B68: High Growth Period (HGP) | C68: =C59 -> 10
B69: High Growth Rate (HGR) | C69: 0.2
B70: Value per share | C70: =Valuation_Model!E73 -> 0.31154936 | D70: =Market_currency -> HKD
B71: Probabilities | C71: 0
B73: Expected Value = | C73: =C64*C65+C70*C71+C55*(1-C65-C71) -> 0.13164284 | D73: =Market_currency -> HKD
B75: Margin of Safety (MOS)
B76: Inputs | E76: Special Assumption
B77: Target Return | C77: =Thesis!C68 -> 0.2 | E77: the Equity Value will be conservatively realized | F77: =Thesis!C67 -> 3
B78: Annual Dividend per share | C78: =Normalized_FCF!C108 -> 0.0548 | D78: =Market_currency -> HKD | E78: over a holding period of
B80: Output
B81: PV(Dividends) | C81: =PV(C77, F77, -C78, 0) -> 0.11543519
B82: PV(Equity Value) | C82: =C73/(1+C77)^F77 -> 0.0761822
B83: Buy Below | C83: =C81+C82 -> 0.19161739 | D83: =Market_currency -> HKD | E83: at a MOS of | F83: =(C83/C73-1) -> 0.4555853 | I83: Buy at < PV(dividends, 3yrs, r) + PV(Equity value, 3yrs, r)
B87: CAGR Calculator | C87: Initial Value (PV) | D87: Final Value (FV) | E87: # of Years
B88: Inputs = | C88: =Normalized_FCF!L10 -> -3640 | D88: =Normalized_FCF!G10 -> 80402 | E88: 6
B89: CAGR = | C89: =(D88/C88)^(1/E88)-1 -> #NUM!
