Workbook
Name Common_Shares: Thesis!$C$7
Name Equity_Cost: Valuation_Model!$C$5
Name Exchange_Rate: Thesis!$C$17
Name Market_currency: Thesis!$D$6
Name Market_Price: Thesis!$C$6
Name Reporting_currency: Thesis!$C$16
Name Terminal_Growth: Valuation_Model!$F$4

Sheet Thesis
B1: Model last updated: | C1: 45754 | E1: Selected: | F1: N
A2: Executive Summary
B4: =D5&" Stock Information" -> 0806.HK Stock Information
B5: Company Name | C5: 惠理集團 | D5: 0806.HK
B6: Market Price: | C6: 1.35 | D6: HKD
B7: Number of Shares: | C7: 1826709831
B8: Report Interval: | C8: 6
B9: Update Required After: | C9: =EOMONTH(EDATE(BS!C1,C8+2),0) -> 45900
B10: ="Capitalization ("&Market_currency&"):" -> Capitalization (HKD): | C10: =Thesis!C6*Thesis!C7/1000000 -> 2466.0583
B12: Guidance Note: This model determines a target buy price consistent with defined investment criteria. It follows a logical progression: establishing current sustainable earnings, adjusting for financial structure, incorporating growth scenarios, and finally applying the investor’s required return.
B14: Valuation Overview
B15: Growth Classification: | C15: =IF(Scenarios!C69="Y",Scenarios!B69,"")&IF(Scenarios!C70="Y",Scenarios!B70,"")&IF(Scenarios!C71="Y",Scenarios!B71,"")&" "&IF(Scenarios!C72="Y",Scenarios!B72,"") -> Low Growth Asset Play
B16: Reporting Currency: | C16: HKD
B17: Exchange Rate: | C17: 1 | D17: =IF(C16=D6,D6,C16&"/"&D6) -> HKD
B18: Comp_Sector: | C18: FIN_02
B19: Target Annual Return: | C19: 0.25
B20: ="Target Buy Price ("&Market_currency&"):" -> Target Buy Price (HKD): | C20: =C129 -> 0.28748109 | D20: assuming a holding period of | E20: 3
B21: Implied Market Annual Return: | C21: =Scenarios!C87 -> -0.26037178
A23: Step 1: Establishing the Company’s Sustainable Earning Power (Calculating Normalized FCFE)
B25: Goal: To quantify the underlying FCFE the business consistently generates for its equity owners, stripping away temporary fluctuations or accounting choices.The FCFE/Market Cap yield gives a direct measure of this cash generation relative to the current market price.
B26: FCFE = (Normalized Operating EBIT + Depreciation & Amortization – Capital Expenditures) + Stable Non-Operating EBIT + Net Interest Income – Taxes – NCI’s Share of Profits – Working Capital Investment
B28: Key Components | C28: =Data!C3 -> 1000
B29: • Normalized Operating EBIT: Earnings before interest and taxes from core business operations, adjusted to remove one-time or irregular items for a sustainable earnings base.
B30: Normalized Operating EBIT = | C30: =Normalized_FCF!C8 -> -62266 | D30: =Reporting_currency -> HKD
B32: • Depreciation & Amortization (D&A): Non-cash expenses added back to reflect cash generated from operations. • Capital Expenditures (Capex): Cash outflows required to maintain or expand operational assets
B33: D&A = | C33: =Normalized_FCF!C9 -> 0 | D33: =Reporting_currency -> HKD
B34: Capex = | C34: =Normalized_FCF!C10 -> 0 | D34: =Reporting_currency -> HKD
B36: • Stable Non-Operating EBIT: Consistent earnings from non-core assets, such as fixed-income investments, dividend-paying stocks, or rental properties.
B37: Stable Non-Operating EBIT = | C37: =Normalized_FCF!C11 -> 70547.28 | D37: =Reporting_currency -> HKD
B39: • Net Interest Income: Interest income minus interest expense
B40: Operating Interest Income = | C40: =Normalized_FCF!C48 -> 5314.0836 | D40: =Reporting_currency -> HKD
B41: Interest Expense = | C41: =Normalized_FCF!C47 -> -8149 | D41: =Reporting_currency -> HKD
B42: Net Interest Income = | C42: =Normalized_FCF!C12 -> -2834.9164 | D42: =Reporting_currency -> HKD
B44: • NCI’s Share of Profits: NCI represents the portion of a subsidiary’s equity not owned by the parent company.
B45: Est. NCI’s Share of Profits = | C45: =Normalized_FCF!C15 -> 0 | D45: =Reporting_currency -> HKD
B47: • Taxes: Tax = (Normalized Operating EBIT + Stable Non-Operating EBIT + Interest Income – Interest Expense) × Tax Rate
B48: Taxes = | C48: =Normalized_FCF!C14 -> -1361.5909 | D48: =Reporting_currency -> HKD
B50: • Working Capital Investment (WCInv): WCInv is only included if it materially distorts FCFE.
B51: WCInv = | C51: =Normalized_FCF!C17 -> 0 | D51: =Reporting_currency -> HKD
B53: Note on Net Borrowing: In theory, principal repayments are accounted for through Net Borrowing. However, this model aims to avoid explicitly forecasting debt issuance or repayments. Instead, principal repayments are reflected in the Equity Value adjustment through interest-bearing debt.
B54: Insight: This step ensures a comprehensive measure of cash flow by incorporating both operating and stable non-operating sources while accounting for taxes and reinvestment needs.
B56: Latest FCFE = | C56: =Normalized_FCF!G19 -> -263415.91 | D56: =Reporting_currency -> HKD
B57: Normalized FCFE = | C57: =Normalized_FCF!C19 -> 4084.7727 | D57: =Reporting_currency -> HKD
B58: Normalized FCFE/Market Cap = | C58: =Normalized_FCF!C125 -> 0.0016563975
B59: Dividend/Market Cap = | C59: =Normalized_FCF!C93 -> 0.0074074074
A61: Step 2: The No-Growth Baseline (Calculating Stable Income Value)
B63: Goal: To determine the intrinsic value of the company’s equity if the Normalized FCFE (calculated in Step 1) were to remain constant perpetually, with zero future growth. This establishes a baseline value derived solely from the current sustainable earnings power.
B64: Stable Income Value = Normalized FCFE / (Cost of Equity – Terminal Growth Rate)
B66: Key Components
B67: Base Cost of Equity | C67: 0.08
B68: Business Model Risk Premium | C68: =IF(D68="Y",1%,0) -> 0 | D68: N
B69: Management Risk Premium | C69: =IF(D69="Y",1%,0) -> 0 | D69: N
B70: Cost of Equity = | C70: =SUM(C67:C69) -> 0.08
B72: Note:
B73: Cost of Equity: Cost of Equity reflects the company’s risk profile and represents the minimum return the investor requires for taking on the general risk of owning this type of business, while the target annual return serves as the investor’s hurdle rate.
B74: Terminal Growth Rate: Setting g=0% is a conservative assumption, valuing the company based only on its current demonstrated earning power without relying on potentially optimistic future growth projections.
B76: Terminal Growth Rate (g) = | C76: 0
B77: No Growth SIV Per Share = | C77: =Valuation_Model!C6*C28*Exchange_Rate/Common_Shares -> 0.027951707 | D77: =Market_currency -> HKD
A79: Step 3: Adjusting for Financial Structure (Calculating No Growth Equity Value)
B81: Goal: To refine the Stable Income Value (SIV) by incorporating the company’s balance sheet structure.
B82: Equity Value = Stable Income Value – Total Interest-Bearing Debt + Non-Operating Cash + Other Non-Operating Assets
B84: Key Components
B85: Note on debt: The total interest-bearing debt captures the principal repayments. Ideally, this amount should be discounted based on the repayment schedule. However, for simplicity and conservatism, this model uses the book value of the total interest-bearing debt.
B86: Total Interest-Bearing Debt = | C86: =Valuation_Model!C7 -> 97365 | D86: =Reporting_currency -> HKD
B87: Total Interest-Bearing Debt per share = | C87: =C86*C28*Exchange_Rate/Common_Shares -> 0.053300748 | D87: =Market_currency -> HKD
B89: • Non-Operating Cash: Excess cash not required for operations
B90: Total Cash = | C90: =BS!C66 -> 1077437 | D90: =Reporting_currency -> HKD
B91: Est. Non-Operating Cash = | C91: =Valuation_Model!C8 -> 913534.95 | D91: =Reporting_currency -> HKD
B92: Est. Non-Operating Cash per share = | C92: =C91*C28*Exchange_Rate/Common_Shares -> 0.50009856 | D92: =Market_currency -> HKD
B94: • Other Non-Operating Assets: Assets not contributing to FCFE (e.g., non-income-generating investments or properties)
B95: Other Non-Operating Assets = | C95: =Valuation_Model!C9 -> 84349.6 | D95: =Reporting_currency -> HKD
B96: Other Non-Operating Assets per share = | C96: =C95*C28*Exchange_Rate/Common_Shares -> 0.046175697 | D96: =Market_currency -> HKD
B98: Insight: The No Growth Equity Value per share represents an estimate of the company’s intrinsic worth based on its current sustainable operations and net financial position, before factoring in any future growth potential. It serves as a fundamentally anchored valuation baseline.
B100: No Growth Equity Value per share = | C100: =Valuation_Model!C12 -> 0.52092521 | D100: =Market_currency -> HKD
A102: Step 4: Incorporating Future Potential & Risk (Scenario Analysis)
B104: Goal: To estimate the company’s intrinsic value by considering plausible future scenarios beyond the static no-growth assumption. Based on fundamental research, each scenario defines high growth periods (HGP), high growth rates (HGR), and its probability.
B106: Scenarios | C106: HGR | D106: HGP | E106: EV per share | F106: Probabilities
B107: =Valuation_Model!B74 -> Snowball Scenario | C107: =Valuation_Model!C74 -> 0.1 | D107: =Valuation_Model!D74 -> 15 | E107: =ROUND(Valuation_Model!E74,2)&" "&Market_currency -> 0.54 HKD | F107: =Valuation_Model!F74 -> 0.05
B108: =Valuation_Model!B75 -> Optimistic | C108: =Valuation_Model!C75 -> 0.06 | D108: =Valuation_Model!D75 -> 10 | E108: =ROUND(Valuation_Model!E75,2)&" "&Market_currency -> 0.53 HKD | F108: =Valuation_Model!F75 -> 0.18
B109: =Valuation_Model!B76 -> Base | C109: =Valuation_Model!C76 -> 0 | D109: =Valuation_Model!D76 -> 10 | E109: =ROUND(Valuation_Model!E76,2)&" "&Market_currency -> 0.52 HKD | F109: =Valuation_Model!F76 -> 0.54
B110: =Valuation_Model!B77 -> Pessimistic | C110: =Valuation_Model!C77 -> 0.02 | D110: =Valuation_Model!D77 -> 10 | E110: =ROUND(Valuation_Model!E77,2)&" "&Market_currency -> 0.52 HKD | F110: =Valuation_Model!F77 -> 0.18
B111: =Valuation_Model!B78 -> Devil's advocate | C111: =Valuation_Model!C78 -> 0 | D111: =Valuation_Model!D78 -> 15 | E111: =ROUND(Valuation_Model!E78,2)&" "&Market_currency -> 0.52 HKD | F111: =Valuation_Model!F78 -> 0.05
B113: Expected Equity Value = | C113: =Scenarios!C60 -> 0.5233615 | D113: =Market_currency -> HKD
B115: Insight: Significant market volatility is analyzed as an indicator of the range of market-perceived outcomes, including extremes that define boundaries for scenarios like "Snowball" or "Devil’s Advocate." Scenario Analysis then filters these using fundamental reasoning to evaluate their likelihood.
A117: Step 5: Determining the Investment Decision (Calculating Target Buy Price)
B119: Goal: To translate our estimate of the company’s intrinsic value (from Step 4) into a concrete buy price that meets the specific investment requirements.
B120: Calculation Logic: The Target Buy Price is determined by discounting future cash flows—expected annual dividends and the Expected Equity Value—at the Target Annual Return, realized over the holding period.
B121: Key Components
B122: Expected Holding period = | C122: =E20 -> 3
B123: Target Annual Return = | C123: =C19 -> 0.25
B124: Annual Dividend per share = | C124: =Scenarios!C77 -> 0.01 | D124: =Market_currency -> HKD
B126: Result
B127: ="PV("&C122&" yrs of Dividends)" -> PV(3 yrs of Dividends) | C127: =Scenarios!C81 -> 0.01952
B128: ="+ PV(Equity Value realized at year "&C122&")" -> + PV(Equity Value realized at year 3) | C128: =Scenarios!C82 -> 0.26796109
B129: Buy Below: | C129: =Scenarios!C83 -> 0.28748109 | D129: =Reporting_currency -> HKD
B130: @ a Margin of Safety of | C130: =Scenarios!F83 -> 0.45070264
A132: Step 6: Risk Analysis
B134: Goal: To identify and assess the key risk factors inherent in this valuation model, focusing on those with the greatest potential impact on the final result.
B136: Key Risk Factors
B137: 1. Accuracy of Normalized FCFE, which is affacted by uncertainties include:
...

Sheet Data
B1: =Thesis!C16 -> HKD | C1: 45657 | D1: =EOMONTH(EDATE(C1,-12),0) -> 45291 | E1: =EOMONTH(EDATE(D1,-12),0) -> 44926 | F1: =EOMONTH(EDATE(E1,-12),0) -> 44561 | G1: =EOMONTH(EDATE(F1,-12),0) -> 44196 | H1: =EOMONTH(EDATE(G1,-12),0) -> 43830 | I1: =EOMONTH(EDATE(H1,-12),0) -> 43465 | J1: =EOMONTH(EDATE(I1,-12),0) -> 43100 | K1: =EOMONTH(EDATE(J1,-12),0) -> 42735 | ... M1: =EOMONTH(EDATE(L1,-12),0) -> 42004
B2: Data (Dirty)
B3: Income Statement | C3: 1000
B4: Sales | C4: 247271 | D4: 281951 | E4: 331953 | F4: 755414 | G4: 2050629
B5: COGS | C5: 219537 | D5: 232905
B6: OPEX | C6: =227454+5669+14513+113831 -> 361467 | D6: =250848+7069+19250+113116 -> 390283 | E6: 330088 | F6: 389543 | G6: 672911
B7: Incl. Selling Expenses
B8: R&D
B9: Share of JV or associate Results
B10: Dividend or Interests from FA | C10: =52198+11417 -> 63615 | D10: =48974+5641 -> 54615
B11: Investment property | C11: 12454 | D11: 12191
B12: Interest Expense | C12: 8149 | D12: 7447 | E12: 5293 | F12: 3968 | G12: 0
B13: Interest Income | C13: 34933 | D13: 42648
B14: Income Tax Paid | C14: 2918 | D14: 4507 | E14: 3959 | F14: 50081 | G14: 221776
B15: Reported Net Income | C15: 30811 | D15: 23088 | E15: -544315 | F15: 457813 | G15: 1379475
B16: Non-controling Interests | C16: -424 | D16: 0 | E16: 0 | F16: 0 | G16: 0
B18: Cash Flow Statement
B19: D&A
B20: CAPX | C20: -1.006 | D20: -1.006 | E20: -0.986 | F20: -5.18 | G20: -8.445
B21: WCInv | C21: 34.15 | D21: 34.15 | E21: -39.788 | F21: 0.91 | G21: 980.628
B22: CFO | C22: -2094 | D22: 56325 | E22: -76641 | F22: 1075649 | G22: 212852
B23: CFI | C23: 459814 | D23: -67601 | E23: 398831 | F23: -706056 | G23: -13297
B24: CFF | C24: -937078 | D24: -89539 | E24: -232800 | F24: -678918 | G24: -439768
B25: ="Dividend per share ("&Market_currency&")" -> Dividend per share (HKD) | C25: 0.01 | D25: 0 | E25: 0.034 | F25: 0.08 | G25: 0.26
B27: Balance Sheet | C27: Latest Asset Value
B28: ST AR | C28: =BS!C4 -> 83455 | D28: 56325 | E28: 67131 | F28: 190060 | G28: 1495304
B29: ST Inventory | C29: =BS!C6 -> 0 | D29: 0 | E29: 0 | F29: 0 | G29: 0
B30: Total Liabilities | C30: =BS!C33+BS!C42 -> 215440 | D30: 1135384 | E30: 253658 | F30: 405587 | G30: 880771
B31: Total Equity | C31: =BS!G27 -> 3559773 | D31: 3542698 | E31: 4494199 | F31: 5264755 | G31: 5418042
B32: Non-common Interest | C32: =BS!G28 -> 7710 | D32: 0 | E32: 0 | F32: 0 | G32: 0
B34: IS & CF Statements (Clean)
B35: Income Statement
B36: Sales | C36: =IF(C$4="","",C4) -> 247271 | D36: =IF(D$4="","",D4) -> 281951 | E36: =IF(E$4="","",E4) -> 331953 | F36: =IF(F$4="","",F4) -> 755414 | G36: =IF(G$4="","",G4) -> 2050629 | H36: =IF(H$4="","",H4) | I36: =IF(I$4="","",I4) | J36: =IF(J$4="","",J4) | ... M36: =IF(M$4="","",M4)
B37: COGS | C37: =IF(C$4="","",-C5) -> -219537 | D37: =IF(D$4="","",-D5) -> -232905 | E37: =IF(E$4="","",-E5) -> 0 | F37: =IF(F$4="","",-F5) -> 0 | G37: =IF(G$4="","",-G5) -> 0 | H37: =IF(H$4="","",-H5) | I37: =IF(I$4="","",-I5) | J37: =IF(J$4="","",-J5) | ... M37: =IF(M$4="","",-M5)
B38: Gross Margin | C38: =IF(C36="","",C36+C37) -> 27734 | D38: =IF(D36="","",D36+D37) -> 49046 | E38: =IF(E36="","",E36+E37) -> 331953 | F38: =IF(F36="","",F36+F37) -> 755414 | G38: =IF(G36="","",G36+G37) -> 2050629 | H38: =IF(H36="","",H36+H37) | I38: =IF(I36="","",I36+I37) | J38: =IF(J36="","",J36+J37) | ... M38: =IF(M36="","",M36+M37)
B39: OPEX | C39: =IF(C$4="","",-C6) -> -361467 | D39: =IF(D$4="","",-D6) -> -390283 | E39: =IF(E$4="","",-E6) -> -330088 | F39: =IF(F$4="","",-F6) -> -389543 | G39: =IF(G$4="","",-G6) -> -672911 | H39: =IF(H$4="","",-H6) | I39: =IF(I$4="","",-I6) | J39: =IF(J$4="","",-J6) | ... M39: =IF(M$4="","",-M6)
B40: Incl. Selling Expenses | C40: =IF(C$4="","",-C7) -> 0 | D40: =IF(D$4="","",-D7) -> 0 | E40: =IF(E$4="","",-E7) -> 0 | F40: =IF(F$4="","",-F7) -> 0 | G40: =IF(G$4="","",-G7) -> 0 | H40: =IF(H$4="","",-H7) | I40: =IF(I$4="","",-I7) | J40: =IF(J$4="","",-J7) | ... M40: =IF(M$4="","",-M7)
B41: Incl. Other Opex | C41: =IF(C$4="","",C39-C40) -> -361467 | D41: =IF(D$4="","",D39-D40) -> -390283 | E41: =IF(E$4="","",E39-E40) -> -330088 | F41: =IF(F$4="","",F39-F40) -> -389543 | G41: =IF(G$4="","",G39-G40) -> -672911 | H41: =IF(H$4="","",H39-H40) | I41: =IF(I$4="","",I39-I40) | J41: =IF(J$4="","",J39-J40) | ... M41: =IF(M$4="","",M39-M40)
B42: R&D | C42: =IF(C$4="","",-C8) -> 0 | D42: =IF(D$4="","",-D8) -> 0 | E42: =IF(E$4="","",-E8) -> 0 | F42: =IF(F$4="","",-F8) -> 0 | G42: =IF(G$4="","",-G8) -> 0 | H42: =IF(H$4="","",-H8) | I42: =IF(I$4="","",-I8) | J42: =IF(J$4="","",-J8) | ... M42: =IF(M$4="","",-M8)
B43: Operating EBIT | C43: =IF(C$4="","",C38+C39+C42) -> -333733 | D43: =IF(D$4="","",D38+D39+D42) -> -341237 | E43: =IF(E$4="","",E38+E39+E42) -> 1865 | F43: =IF(F$4="","",F38+F39+F42) -> 365871 | G43: =IF(G$4="","",G38+G39+G42) -> 1377718 | H43: =IF(H$4="","",H38+H39+H42) | I43: =IF(I$4="","",I38+I39+I42) | J43: =IF(J$4="","",J38+J39+J42) | ... M43: =IF(M$4="","",M38+M39+M42)
B44: Non-operating EBIT | C44: =IF(C$4="","",C47-C46-C45-C43) -> 340678 | D44: =IF(D$4="","",D47-D46-D45-D43) -> 333631 | E44: =IF(E$4="","",E47-E46-E45-E43) -> -536928 | F44: =IF(F$4="","",F47-F46-F45-F43) -> 145991 | G44: =IF(G$4="","",G47-G46-G45-G43) -> 223533 | H44: =IF(H$4="","",H47-H46-H45-H43) | I44: =IF(I$4="","",I47-I46-I45-I43) | J44: =IF(J$4="","",J47-J46-J45-J43) | ... M44: =IF(M$4="","",M47-M46-M45-M43)
B45: Net Interest Income | C45: =IF(C$4="","",C51+C52) -> 26784 | D45: =IF(D$4="","",D51+D52) -> 35201 | E45: =IF(E$4="","",E51+E52) -> -5293 | F45: =IF(F$4="","",F51+F52) -> -3968 | G45: =IF(G$4="","",G51+G52) -> 0 | H45: =IF(H$4="","",H51+H52) | I45: =IF(I$4="","",I51+I52) | J45: =IF(J$4="","",J51+J52) | ... M45: =IF(M$4="","",M51+M52)
B46: Income Tax Paid | C46: =IF(C$4="","",-C14) -> -2918 | D46: =IF(D$4="","",-D14) -> -4507 | E46: =IF(E$4="","",-E14) -> -3959 | F46: =IF(F$4="","",-F14) -> -50081 | G46: =IF(G$4="","",-G14) -> -221776 | H46: =IF(H$4="","",-H14) | I46: =IF(I$4="","",-I14) | J46: =IF(J$4="","",-J14) | ... M46: =IF(M$4="","",-M14)
B47: Reported Net Income | C47: =IF(C$4="","",C15) -> 30811 | D47: =IF(D$4="","",D15) -> 23088 | E47: =IF(E$4="","",E15) -> -544315 | F47: =IF(F$4="","",F15) -> 457813 | G47: =IF(G$4="","",G15) -> 1379475 | H47: =IF(H$4="","",H15) | I47: =IF(I$4="","",I15) | J47: =IF(J$4="","",J15) | ... M47: =IF(M$4="","",M15)
B48: Non-controling Interests | C48: =IF(C$4="","",MIN(-C16,0)) -> 0 | D48: =IF(D$4="","",MIN(-D16,0)) -> 0 | E48: =IF(E$4="","",MIN(-E16,0)) -> 0 | F48: =IF(F$4="","",MIN(-F16,0)) -> 0 | G48: =IF(G$4="","",MIN(-G16,0)) -> 0 | H48: =IF(H$4="","",MIN(-H16,0)) | I48: =IF(I$4="","",MIN(-I16,0)) | J48: =IF(J$4="","",MIN(-J16,0)) | ... M48: =IF(M$4="","",MIN(-M16,0))
B50: Net Interest Income
B51: Interest Expense | C51: =IF(C$4="","",-C12) -> -8149 | D51: =IF(D$4="","",-D12) -> -7447 | E51: =IF(E$4="","",-E12) -> -5293 | F51: =IF(F$4="","",-F12) -> -3968 | G51: =IF(G$4="","",-G12) -> 0 | H51: =IF(H$4="","",-H12) | I51: =IF(I$4="","",-I12) | J51: =IF(J$4="","",-J12) | ... M51: =IF(M$4="","",-M12)
B52: Interest Income | C52: =IF(C$4="","",C13) -> 34933 | D52: =IF(D$4="","",D13) -> 42648 | E52: =IF(E$4="","",E13) -> 0 | F52: =IF(F$4="","",F13) -> 0 | G52: =IF(G$4="","",G13) -> 0 | H52: =IF(H$4="","",H13) | I52: =IF(I$4="","",I13) | J52: =IF(J$4="","",J13) | ... M52: =IF(M$4="","",M13)
B54: Non-operating EBIT
B55: Share of JV or associate Results | C55: =IF(C$4="","",C9) -> 0 | D55: =IF(D$4="","",D9) -> 0 | E55: =IF(E$4="","",E9) -> 0 | F55: =IF(F$4="","",F9) -> 0 | G55: =IF(G$4="","",G9) -> 0 | H55: =IF(H$4="","",H9) | I55: =IF(I$4="","",I9) | J55: =IF(J$4="","",J9) | ... M55: =IF(M$4="","",M9)
B56: Dividend or Interests from FA | C56: =IF(C$4="","",C10) -> 63615 | D56: =IF(D$4="","",D10) -> 54615 | E56: =IF(E$4="","",E10) -> 0 | F56: =IF(F$4="","",F10) -> 0 | G56: =IF(G$4="","",G10) -> 0 | H56: =IF(H$4="","",H10) | I56: =IF(I$4="","",I10) | J56: =IF(J$4="","",J10) | ... M56: =IF(M$4="","",M10)
B57: Investment property | C57: =IF(C$4="","",C11) -> 12454 | D57: =IF(D$4="","",D11) -> 12191 | E57: =IF(E$4="","",E11) -> 0 | F57: =IF(F$4="","",F11) -> 0 | G57: =IF(G$4="","",G11) -> 0 | H57: =IF(H$4="","",H11) | I57: =IF(I$4="","",I11) | J57: =IF(J$4="","",J11) | ... M57: =IF(M$4="","",M11)
B58: Other Non-operating Income | C58: =IF(C$4="","",C44-C55-C56-C57) -> 264609 | D58: =IF(D$4="","",D44-D55-D56-D57) -> 266825 | E58: =IF(E$4="","",E44-E55-E56-E57) -> -536928 | F58: =IF(F$4="","",F44-F55-F56-F57) -> 145991 | G58: =IF(G$4="","",G44-G55-G56-G57) -> 223533 | H58: =IF(H$4="","",H44-H55-H56-H57) | I58: =IF(I$4="","",I44-I55-I56-I57) | J58: =IF(J$4="","",J44-J55-J56-J57) | ... M58: =IF(M$4="","",M44-M55-M56-M57)
B60: Cash Flow Statement
B61: D&A | C61: =IF(C$4="","",-C19) -> 0 | D61: =IF(D$4="","",-D19) -> 0 | E61: =IF(E$4="","",-E19) -> 0 | F61: =IF(F$4="","",-F19) -> 0 | G61: =IF(G$4="","",-G19) -> 0 | H61: =IF(H$4="","",-H19) | I61: =IF(I$4="","",-I19) | J61: =IF(J$4="","",-J19) | ... M61: =IF(M$4="","",-M19)
B62: CAPX | C62: =IF(C$4="","",-C20) -> 1.006 | D62: =IF(D$4="","",-D20) -> 1.006 | E62: =IF(E$4="","",-E20) -> 0.986 | F62: =IF(F$4="","",-F20) -> 5.18 | G62: =IF(G$4="","",-G20) -> 8.445 | H62: =IF(H$4="","",-H20) | I62: =IF(I$4="","",-I20) | J62: =IF(J$4="","",-J20) | ... M62: =IF(M$4="","",-M20)
B63: WCInv | C63: =IF(C$4="","",-C21) -> -34.15 | D63: =IF(D$4="","",-D21) -> -34.15 | E63: =IF(E$4="","",-E21) -> 39.788 | F63: =IF(F$4="","",-F21) -> -0.91 | G63: =IF(G$4="","",-G21) -> -980.628 | H63: =IF(H$4="","",-H21) | I63: =IF(I$4="","",-I21) | J63: =IF(J$4="","",-J21) | ... M63: =IF(M$4="","",-M21)
B64: Net Change in Cash | C64: =IF(C$4="","",C22+C23+C24) -> -479358 | D64: =IF(D$4="","",D22+D23+D24) -> -100815 | E64: =IF(E$4="","",E22+E23+E24) -> 89390 | F64: =IF(F$4="","",F22+F23+F24) -> -309325 | G64: =IF(G$4="","",G22+G23+G24) -> -240213 | H64: =IF(H$4="","",H22+H23+H24) | I64: =IF(I$4="","",I22+I23+I24) | J64: =IF(J$4="","",J22+J23+J24) | ... M64: =IF(M$4="","",M22+M23+M24)
B65: Dividend per share | C65: =IF(C$4="","",C25) -> 0.01 | D65: =IF(D$4="","",D25) -> 0 | E65: =IF(E$4="","",E25) -> 0.034 | F65: =IF(F$4="","",F25) -> 0.08 | G65: =IF(G$4="","",G25) -> 0.26 | H65: =IF(H$4="","",H25) | I65: =IF(I$4="","",I25) | J65: =IF(J$4="","",J25) | ... M65: =IF(M$4="","",M25)
B67: YoY %
B68: =B36 -> Sales | C68: =IF(D$36="","",C36/D36-1) -> -0.1230001 | D68: =IF(E$36="","",D36/E36-1) -> -0.15062976 | E68: =IF(F$36="","",E36/F36-1) -> -0.56056811 | F68: =IF(G$36="","",F36/G36-1) -> -0.6316184 | G68: =IF(H$36="","",G36/H36-1) | H68: =IF(I$36="","",H36/I36-1) | I68: =IF(J$36="","",I36/J36-1) | J68: =IF(K$36="","",J36/K36-1) | ... M68: =IF(N$36="","",M36/N36-1)
B69: Gross Margin | C69: =IF(D$36="","",C38/D38-1) -> -0.43453085 | D69: =IF(E$36="","",D38/E38-1) -> -0.85225017 | E69: =IF(F$36="","",E38/F38-1) -> -0.56056811 | F69: =IF(G$36="","",F38/G38-1) -> -0.6316184 | G69: =IF(H$36="","",G38/H38-1) | H69: =IF(I$36="","",H38/I38-1) | I69: =IF(J$36="","",I38/J38-1) | J69: =IF(K$36="","",J38/K38-1) | ... M69: =IF(N$36="","",M38/N38-1)
B70: =B43 -> Operating EBIT | C70: =IF(D$36="","",C43/D43-1) -> -0.021990581 | D70: =IF(E$36="","",D43/E43-1) -> -183.9689 | E70: =IF(F$36="","",E43/F43-1) -> -0.99490257 | F70: =IF(G$36="","",F43/G43-1) -> -0.73443695 | G70: =IF(H$36="","",G43/H43-1) | H70: =IF(I$36="","",H43/I43-1) | I70: =IF(J$36="","",I43/J43-1) | J70: =IF(K$36="","",J43/K43-1) | ... M70: =IF(N$36="","",M43/N43-1)
B71: Non-operating EBIT | C71: =IF(D$36="","",C44/D44-1) -> 0.021122138 | D71: =IF(E$36="","",D44/E44-1) -> -1.6213701 | E71: =IF(F$36="","",E44/F44-1) -> -4.6778158 | F71: =IF(G$36="","",F44/G44-1) -> -0.34689285 | G71: =IF(H$36="","",G44/H44-1) | H71: =IF(I$36="","",H44/I44-1) | I71: =IF(J$36="","",I44/J44-1) | J71: =IF(K$36="","",J44/K44-1) | ... M71: =IF(N$36="","",M44/N44-1)
B72: =B47 -> Reported Net Income | C72: =IF(D$36="","",C47/D47-1) -> 0.33450277 | D72: =IF(E$36="","",D47/E47-1) -> -1.0424166 | E72: =IF(F$36="","",E47/F47-1) -> -2.1889461 | F72: =IF(G$36="","",F47/G47-1) -> -0.66812519 | G72: =IF(H$36="","",G47/H47-1) | H72: =IF(I$36="","",H47/I47-1) | I72: =IF(J$36="","",I47/J47-1) | J72: =IF(K$36="","",J47/K47-1) | ... M72: =IF(N$36="","",M47/N47-1)
B74: Balance Sheet (Clean)
B75: Balance Sheet
B76: Total Assets | C76: =IF(C$4="","",C79+C80) -> 3775213 | D76: =IF(D$4="","",D79+D80) -> 4678082 | E76: =IF(E$4="","",E79+E80) -> 4747857 | F76: =IF(F$4="","",F79+F80) -> 5670342 | G76: =IF(G$4="","",G79+G80) -> 6298813 | H76: =IF(H$4="","",H79+H80) | I76: =IF(I$4="","",I79+I80) | J76: =IF(J$4="","",J79+J80) | ... M76: =IF(M$4="","",M79+M80)
B77: Incl. ST AR | C77: =IF(C$4="","",C28) -> 83455 | D77: =IF(D$4="","",D28) -> 56325 | E77: =IF(E$4="","",E28) -> 67131 | F77: =IF(F$4="","",F28) -> 190060 | G77: =IF(G$4="","",G28) -> 1495304 | H77: =IF(H$4="","",H28)
B78: Incl. ST Inventory | C78: =IF(C$4="","",C29) -> 0 | D78: =IF(D$4="","",D29) -> 0 | E78: =IF(E$4="","",E29) -> 0 | F78: =IF(F$4="","",F29) -> 0 | G78: =IF(G$4="","",G29) -> 0 | H78: =IF(H$4="","",H29)
B79: Total Liabilities | C79: =IF(C$4="","",C30) -> 215440 | D79: =IF(D$4="","",D30) -> 1135384 | E79: =IF(E$4="","",E30) -> 253658 | F79: =IF(F$4="","",F30) -> 405587 | G79: =IF(G$4="","",G30) -> 880771 | H79: =IF(H$4="","",H30) | I79: =IF(I$4="","",I30) | J79: =IF(J$4="","",J30) | ... M79: =IF(M$4="","",M30)
B80: Total Equity | C80: =IF(C$4="","",C31) -> 3559773 | D80: =IF(D$4="","",D31) -> 3542698 | E80: =IF(E$4="","",E31) -> 4494199 | F80: =IF(F$4="","",F31) -> 5264755 | G80: =IF(G$4="","",G31) -> 5418042 | H80: =IF(H$4="","",H31) | I80: =IF(I$4="","",I31) | J80: =IF(J$4="","",J31) | ... M80: =IF(M$4="","",M31)

Sheet BS
B1: Most Recent Quarter | C1: 45657 | F1: =IF(MONTH(C1)=MONTH(Normalized_FCF!G1),"FY","Quarter")&" Report" -> FY Report | H1: =Data!C3 -> 1000
B2: Lastest Balance Sheet
B3: ST Operating Assets | C3: Book | D3: Valued @ | F3: ST Non-Operating Assets | G3: Book | H3: Valued @
B4: ST AR | C4: =37674+19634+26147 -> 83455 | D4: 0.6 | F4: Cash and cash equivalents | G4: 1077437 | H4: 0.9
B5: Operating ST Financial Assets | C5: 0 | D5: 0.6 | F5: Restricted cash | G5: 0 | H5: 0.7
B6: Inventory | C6: 0 | D6: 0.5 | F6: Securities with stable income | G6: 0 | H6: 0.6
B7: Properties held for sale | C7: 0 | D7: 0.6 | F7: Other Securities | G7: 60407 | H7: 0.6
B8: Properties held for income | C8: 0 | D8: 0.6 | F8: Properties with stable income | G8: 0 | H8: 0.6
B9: Prepayments and Contract Assets | C9: 15614 | D9: 0.1 | F9: Other Properties | G9: 0 | H9: 0.6
B10: ST DTA | C10: 0 | D10: 0.9
B11: Other ST Assets | C11: 0 | D11: 0.05
B12: Operating ST Assets | C12: =SUM(C4:C11) -> 99069 | D12: =C4*D4+C5*D5+C9*D9+C6*D6+C8*D8+C7*D7+C10*D10+C11*D11 -> 51634.4 | F12: Non-Operating ST Assets | G12: =SUM(G4:G9) -> 1137844 | H12: =G4*H4+G5*H5+G6*H6+G7*H7+G8*H8+G9*H9 -> 1005937.5
B14: LT Operating Assets | C14: Book | D14: Valued @ | F14: LT Non-Operating Assets | G14: Book | H14: Valued @
B15: LT AR | C15: 0 | D15: 0.4 | F15: LT Depositis | G15: 0 | H15: 0.8
B16: Operating LT Financial Assets | C16: 0 | D16: 0.5 | F16: Securities with stable income | G16: 1688685 | H16: 0.6
B17: Properties held for sale | C17: 0 | D17: 0.6 | F17: Other Securities | G17: 0 | H17: 0.6
B18: Properties held for income | C18: 0 | D18: 0.6 | F18: JV or associate with stable income | G18: 0 | H18: 0.1
B19: PP&E & Right of Use Assets | C19: =145400+31250 -> 176650 | D19: 0.1 | F19: Other JV or associate | G19: =479666+1388 -> 481054 | H19: 0.1
B20: Biological assets | C20: 0 | D20: 0.05 | F20: Properties with stable income | G20: 173307 | H20: 0.2
B21: Intangible assets | C21: 9357 | D21: 0.05 | F21: Other Properties | G21: 0 | H21: 0.1
B22: LT DTA | C22: 2304 | D22: 0.9
B23: Other assets & Goodwill | C23: 6943 | D23: 0
B24: Operating LT Assets | C24: =SUM(C15:C23) -> 195254 | D24: =C15*D15+C16*D16+C18*D18+C17*D17+C19*D19+C20*D20+C21*D21+C22*D22+C23*D23 -> 20206.45 | F24: Non-Operating LT Assets | G24: =SUM(G15:G21) -> 2343046 | H24: =G15*H15+G16*H16+G17*H17+G18*H18+G19*H19+G20*H20+G21*H21 -> 1095977.8
B26: ST Liabilities | C26: Book | F26: BS Summary | G26: Book | H26: Valued @
B27: ST Borrowing | C27: 65941 | F27: Total Equity | G27: =G32-G30 -> 3559773 | H27: =H32-G30 -> 1958316.1
B28: ST Lease liabilities | C28: 12865 | F28: Incl. Minority Interest (NCI) | G28: 7710
B29: ST SH Loan | C29: 0 | F29: Incl. Common Equity | G29: =G27-G28 -> 3552063 | H29: =H27-G28 -> 1950606.1
B30: ST Financial Liabilities | C30: 0 | F30: Total Liabilities | G30: =C33+C42 -> 215440
B31: ST Interest-bearing Debt | C31: =SUM(C27:C30) -> 78806 | F31: incl. Interest-bearing Debt | G31: =C31+C40 -> 97365
B32: Other ST liabilities | C32: =C33-C31 -> 116223 | F32: Total Assets | G32: =G35+G40 -> 3775213 | H32: =H35+H40 -> 2173756.1
B33: Current Liabilities | C33: 195029
F34: Assets Summary | G34: Book | H34: Valued @
B35: LT Liabilities | C35: Book | F35: Operating Assets | G35: =C12+C24 -> 294323 | H35: =D12+D24 -> 71840.85
B36: LT Borrowing | C36: 0 | F36: incl. AR | G36: =C4+C15 -> 83455
B37: LT Lease liabilities | C37: 18559 | F37: incl. inventory | G37: =C6 -> 0
B38: LT SH Loan | C38: 0 | F38: incl. Properties held for sale | G38: =C7+C17 -> 0
B39: LT Financial Liabilities | C39: 0 | F39: incl. Fixed Assets | G39: =C7+C17+C19+C20 -> 176650 | H39: =C7*D7+C17*D17+C19*D19+C20*D20 -> 17665
B40: LT Interest-bearing Debt | C40: =SUM(C36:C39) -> 18559 | F40: Non-operating Assets | G40: =G12+G24 -> 3480890 | H40: =H12+H24 -> 2101915.3
B41: Other LT liabilities | C41: =C42-C40 -> 1852 | F41: incl. Assets with stable income | G41: =C70 -> 2939429 | H41: =H40-H42 -> 2017565.7
B42: Noncurrent Liabilities | C42: 20411 | F42: incl. Other Assets | G42: =C82 -> 541461 | H42: =D82 -> 84349.6
B44: Balance Sheet Analysis
B45: Asset Value Stress Test | C45: Book | D45: Stress Test | F45: Notes
B46: Equity | C46: =G29 -> 3552063 | D46: =H29 -> 1950606.1
B47: ="Equity per share ("&Market_currency&")" -> Equity per share (HKD) | C47: =C46*H1/Common_Shares*Exchange_Rate -> 1.9445141 | D47: =D46*H1/Common_Shares*Exchange_Rate -> 1.0678248
B49: Leverage % | C49: Normalized | D49: Latest
B50: Debt/EBIT | C50: =G31/Normalized_FCF!C8 -> -1.5636945 | D50: =G31/Normalized_FCF!G8 -> -0.2917452
B51: Common Equity/Total Asset | D51: =G29/G32 -> 0.94089075
B53: Profibility % | C53: Normalized | D53: Latest
B54: Operating Asset Yield | C54: =Normalized_FCF!C8/G35 -> -0.21155669 | D54: =Normalized_FCF!G8/G35 -> -1.1339005
B55: Non-Operating Asset Yield | C55: =Normalized_FCF!C11/G40 -> 0.020267024 | D55: =Normalized_FCF!G11/G40 -> 0.021853319
B57: Reinvestment % | C57: Normalized | D57: Latest
B58: D&A/Fixed Assets | D58: =Normalized_FCF!G9/BS!$G$39 -> 0
B59: Fixed Assets/Total Assets | D59: =G39/G32 -> 0.046792062
B61: NCI % | C61: Estimate | D61: Latest
B62: Est. of NCI Ownership Percentage | C62: =IF(G28<=0,0,G28/G29) -> 0.0021705696 | D62: =G28/G29 -> 0.0021705696 | F62: Rough Estimate only
B64: Non-operating Assets Analysis
B65: Non-operating Assets with stable income | C65: Book | D65: Non-Operating | F65: Notes
B66: Cash | C66: =G4+G5+G15 -> 1077437 | D66: =C66-D75 -> 913534.95 | F66: Non-Operating Cash is the Excess cash not required for operations
B67: Securities with stable income | C67: =G6+G16 -> 1688685
B68: JV or associate with stable income | C68: =G18 -> 0
B69: Properties with stable income | C69: =G8+G20 -> 173307
B70: Non-operating Assets with stable income | C70: =SUM(C66:C69) -> 2939429
B72: Cash Management Analysis | C72: Latest | D72: Normalized
B73: Monthly Operating Expenses | C73: =(Normalized_FCF!G25+Normalized_FCF!G35-Normalized_FCF!G91)/12 -> -49939.258 | D73: =(Normalized_FCF!C25+Normalized_FCF!C35-Normalized_FCF!C91)/12 -> -27317.008 | F73: Variable + Fixed Costs & Dividends
B74: Operating Expenses Multiple (months) | C74: =-$C$66/C73 -> 21.57495 | D74: =-$C$66/D73 -> 39.441984 | F74: Companies typically need cash to cover 1 to 2 months of operating expenses
B75: Operating Cash Requirement | D75: =MAX(-D73*D76,G5) -> 163902.05 | F75: 1x for stable businesses, 2x for for volatile ones, 6x for cash hoarders
B76: Operating Cash Multiple (months) | D76: =IF(D74<=3,1,IF(D74>18,6,2)) -> 6 | F76: Rough Estimate
B78: Other Non-operating Assets | C78: Book | D78: Valued @
B79: Other Securities | C79: =G7+G17 -> 60407 | D79: =G7*H7+G17*H17 -> 36244.2
B80: Other JV or associate | C80: =G19 -> 481054 | D80: =G19*H19 -> 48105.4
B81: Other Properties | C81: =G9+G21 -> 0 | D81: =G9*H9+G21*H21 -> 0
B82: Other Non-operating Assets | C82: =SUM(C79:C81) -> 541461 | D82: =SUM(D79:D81) -> 84349.6
B84: Non-FCF Value of the Equity Value
B85: Non-FCF Value | D85: Per-Share
B86: Interest-bearing Debt | C86: =-Valuation_Model!C7*Exchange_Rate -> -97365 | D86: =C86*$H$1/Common_Shares -> -0.053300748 | E86: =Market_currency -> HKD
B87: Non-operating Cash | C87: =Valuation_Model!C8*Exchange_Rate -> 913534.95 | D87: =C87*$H$1/Common_Shares -> 0.50009856 | E87: =Market_currency -> HKD
B88: Other Non-operating Assets | C88: =Valuation_Model!C9*Exchange_Rate -> 84349.6 | D88: =C88*$H$1/Common_Shares -> 0.046175697 | E88: =Market_currency -> HKD
B89: Total Non-FCF Value | C89: =SUM(C86:C88) -> 900519.55 | D89: =SUM(D86:D88) -> 0.49297351 | E89: =Market_currency -> HKD

Sheet Normalized_FCF
B1: =Thesis!C16 -> HKD | C1: Normalized | G1: =Data!C1 -> 45657 | H1: =EOMONTH(EDATE(G1,-12),0) -> 45291 | I1: =EOMONTH(EDATE(H1,-12),0) -> 44926 | J1: =EOMONTH(EDATE(I1,-12),0) -> 44561 | K1: =EOMONTH(EDATE(J1,-12),0) -> 44196 | L1: =EOMONTH(EDATE(K1,-12),0) -> 43830 | M1: =EOMONTH(EDATE(L1,-12),0) -> 43465 | N1: =EOMONTH(EDATE(M1,-12),0) -> 43100 | O1: =EOMONTH(EDATE(N1,-12),0) -> 42735 | ... Q1: =EOMONTH(EDATE(P1,-12),0) -> 42004
B2: FCFE Analysis | E2: Notes
B3: FCFE | C3: =Data!C3 -> 1000
B4: Sales | C4: =G4 -> 247271 | G4: =Data!C36 -> 247271 | H4: =Data!D36 -> 281951 | I4: =Data!E36 -> 331953 | J4: =Data!F36 -> 755414 | K4: =Data!G36 -> 2050629 | L4: =Data!H36 | M4: =Data!I36 | N4: =Data!J36 | ... Q4: =Data!M36
B5: Variable Costs | C5: =C25 -> -219537 | G5: =G25 -> -219537 | H5: =H25 -> -232905 | I5: =I25 -> 0 | J5: =J25 -> 0 | K5: =K25 -> 0 | L5: =L25 | M5: =M25 | N5: =N25 | ... Q5: =Q25
B6: Contribution Margin | C6: =C4+C5 -> 27734 | G6: =IF(G4="","",G4+G5) -> 27734 | H6: =IF(H4="","",H4+H5) -> 49046 | I6: =IF(I4="","",I4+I5) -> 331953 | J6: =IF(J4="","",J4+J5) -> 755414 | K6: =IF(K4="","",K4+K5) -> 2050629 | L6: =IF(L4="","",L4+L5) | M6: =IF(M4="","",M4+M5) | N6: =IF(N4="","",N4+N5) | ... Q6: =IF(Q4="","",Q4+Q5)
B7: Fixed Costs | C7: =C35 -> -90000 | G7: =G35 -> -361467 | H7: =H35 -> -390283 | I7: =I35 -> -330088 | J7: =J35 -> -389543 | K7: =K35 -> -672911 | L7: =L35 | M7: =M35 | N7: =N35 | ... Q7: =Q35
B8: Operating EBIT | C8: =C6+C7 -> -62266 | G8: =IF(G$4="","",G6+G7) -> -333733 | H8: =IF(H$4="","",H6+H7) -> -341237 | I8: =IF(I$4="","",I6+I7) -> 1865 | J8: =IF(J$4="","",J6+J7) -> 365871 | K8: =IF(K$4="","",K6+K7) -> 1377718 | L8: =IF(L$4="","",L6+L7) | M8: =IF(M$4="","",M6+M7) | N8: =IF(N$4="","",N6+N7) | ... Q8: =IF(Q$4="","",Q6+Q7)
B9: Add Back D&A | C9: =BS!$G$39*BS!D58 -> 0 | G9: =IF(Data!C61="","",-Data!C61) -> 0 | H9: =IF(Data!D61="","",-Data!D61) -> 0 | I9: =IF(Data!E61="","",-Data!E61) -> 0 | J9: =IF(Data!F61="","",-Data!F61) -> 0 | K9: =IF(Data!G61="","",-Data!G61) -> 0 | L9: =IF(Data!H61="","",-Data!H61) | M9: =IF(Data!I61="","",-Data!I61) | N9: =IF(Data!J61="","",-Data!J61) | ... Q9: =IF(Data!M61="","",-Data!M61)
B10: Maintenance Capex | C10: =-C4*C78 -> 0 | G10: =Data!C62 -> 1.006 | H10: =Data!D62 -> 1.006 | I10: =Data!E62 -> 0.986 | J10: =Data!F62 -> 5.18 | K10: =Data!G62 -> 8.445 | L10: =Data!H62 | M10: =Data!I62 | N10: =Data!J62 | ... Q10: =Data!M62
B11: Stable Non-Operating EBIT | C11: =C63 -> 70547.28 | G11: =G61 -> 76069 | H11: =H61 -> 66806 | I11: =I61 -> 0 | J11: =J61 -> 0 | K11: =K61 -> 0 | L11: =L61 | M11: =M61 | N11: =N61 | ... Q11: =Q61
B12: Net Interest Income | C12: =C50 -> -2834.9164 | G12: =G50 -> -2834.9164 | H12: =H50 -> -959.2939 | I12: =I50 -> -5293 | J12: =J50 -> -3968 | K12: =K50 -> 0 | L12: =L50 | M12: =M50 | N12: =N50 | ... Q12: =Q50
B13: Pre-tax Profit | C13: =SUM(C8:C12) -> 5446.3636 | G13: =IF(G$4="","",SUM(G8:G12)) -> -260497.91 | H13: =IF(H$4="","",SUM(H8:H12)) -> -275389.29 | I13: =IF(I$4="","",SUM(I8:I12)) -> -3427.014 | J13: =IF(J$4="","",SUM(J8:J12)) -> 361908.18 | K13: =IF(K$4="","",SUM(K8:K12)) -> 1377726.4 | L13: =IF(L$4="","",SUM(L8:L12)) | M13: =IF(M$4="","",SUM(M8:M12)) | N13: =IF(N$4="","",SUM(N8:N12)) | ... Q13: =IF(Q$4="","",SUM(Q8:Q12))
B14: Income Tax | C14: =-SUM(C8+C11,C12)*C43 -> -1361.5909 | G14: =Data!C46 -> -2918 | H14: =Data!D46 -> -4507 | I14: =Data!E46 -> -3959 | J14: =Data!F46 -> -50081 | K14: =Data!G46 -> -221776 | L14: =Data!H46 | M14: =Data!I46 | N14: =Data!J46 | ... Q14: =Data!M46
B15: NCI’s Share of Profits | C15: =-C4*C83 -> 0 | G15: =Data!C48 -> 0 | H15: =Data!D48 -> 0 | I15: =Data!E48 -> 0 | J15: =Data!F48 -> 0 | K15: =Data!G48 -> 0 | L15: =Data!H48 | M15: =Data!I48 | N15: =Data!J48 | ... Q15: =Data!M48
B16: After-tax Profit | C16: =SUM(C13:C15) -> 4084.7727 | G16: =IF(G$4="","",SUM(G13:G15)) -> -263415.91 | H16: =IF(H$4="","",SUM(H13:H15)) -> -279896.29 | I16: =IF(I$4="","",SUM(I13:I15)) -> -7386.014 | J16: =IF(J$4="","",SUM(J13:J15)) -> 311827.18 | K16: =IF(K$4="","",SUM(K13:K15)) -> 1155950.4 | L16: =IF(L$4="","",SUM(L13:L15)) | M16: =IF(M$4="","",SUM(M13:M15)) | N16: =IF(N$4="","",SUM(N13:N15)) | ... Q16: =IF(Q$4="","",SUM(Q13:Q15))
B17: WCInv | C17: =-C4*C85 -> 0 | E17: WCInv is by default excluded
B18: Net Borrowing | C18: 0 | E18: Net borrowing is excluded
B19: FCFE | C19: =C16+C17 -> 4084.7727 | G19: =IF(G$4="","",G16+G17) -> -263415.91 | H19: =IF(H$4="","",H16+H17) -> -279896.29 | I19: =IF(I$4="","",I16+I17) -> -7386.014 | J19: =IF(J$4="","",J16+J17) -> 311827.18 | K19: =IF(K$4="","",K16+K17) -> 1155950.4 | L19: =IF(L$4="","",L16+L17) | M19: =IF(M$4="","",M16+M17) | N19: =IF(N$4="","",N16+N17) | ... Q19: =IF(Q$4="","",Q16+Q17)
B21: Operating Cost Structure | E21: Notes
B22: Variable Costs
B23: COGS | C23: =-C4*C28 -> -219537 | G23: =Data!C37 -> -219537 | H23: =Data!D37 -> -232905 | I23: =Data!E37 -> 0 | J23: =Data!F37 -> 0 | K23: =Data!G37 -> 0 | L23: =Data!H37 | M23: =Data!I37 | N23: =Data!J37 | ... Q23: =Data!M37
B24: Selling Expenses | C24: =-C4*C29 -> 0 | G24: =Data!C40 -> 0 | H24: =Data!D40 -> 0 | I24: =Data!E40 -> 0 | J24: =Data!F40 -> 0 | K24: =Data!G40 -> 0 | L24: =Data!H40 | M24: =Data!I40 | N24: =Data!J40 | ... Q24: =Data!M40
B25: Variable Costs | C25: =C23+C24 -> -219537 | G25: =IF(G$4="","",G23+G24) -> -219537 | H25: =IF(H$4="","",H23+H24) -> -232905 | I25: =IF(I$4="","",I23+I24) -> 0 | J25: =IF(J$4="","",J23+J24) -> 0 | K25: =IF(K$4="","",K23+K24) -> 0 | L25: =IF(L$4="","",L23+L24) | M25: =IF(M$4="","",M23+M24) | N25: =IF(N$4="","",N23+N24) | ... Q25: =IF(Q$4="","",Q23+Q24)
B27: Variable Costs % of Sales
B28: COGS | C28: =G28 -> 0.88783966 | E28: Historical Average | G28: =IF(G$4="","",ABS(G23/G$4)) -> 0.88783966 | H28: =IF(H$4="","",ABS(H23/H$4)) -> 0.82604779 | I28: =IF(I$4="","",ABS(I23/I$4)) -> 0 | J28: =IF(J$4="","",ABS(J23/J$4)) -> 0 | K28: =IF(K$4="","",ABS(K23/K$4)) -> 0 | L28: =IF(L$4="","",ABS(L23/L$4)) | M28: =IF(M$4="","",ABS(M23/M$4)) | N28: =IF(N$4="","",ABS(N23/N$4)) | ... Q28: =IF(Q$4="","",ABS(Q23/Q$4))
B29: =B24 -> Selling Expenses | C29: =AVERAGE(G29:J29) -> 0 | E29: Historical Average | G29: =IF(G$4="","",ABS(G24/G$4)) -> 0 | H29: =IF(H$4="","",ABS(H24/H$4)) -> 0 | I29: =IF(I$4="","",ABS(I24/I$4)) -> 0 | J29: =IF(J$4="","",ABS(J24/J$4)) -> 0 | K29: =IF(K$4="","",ABS(K24/K$4)) -> 0 | L29: =IF(L$4="","",ABS(L24/L$4)) | M29: =IF(M$4="","",ABS(M24/M$4)) | N29: =IF(N$4="","",ABS(N24/N$4)) | ... Q29: =IF(Q$4="","",ABS(Q24/Q$4))
B30: Variable Costs | C30: =ABS(C25/$C$4) -> 0.88783966 | G30: =IF(G$4="","",ABS(G25/G$4)) -> 0.88783966 | H30: =IF(H$4="","",ABS(H25/H$4)) -> 0.82604779 | I30: =IF(I$4="","",ABS(I25/I$4)) -> 0 | J30: =IF(J$4="","",ABS(J25/J$4)) -> 0 | K30: =IF(K$4="","",ABS(K25/K$4)) -> 0 | L30: =IF(L$4="","",ABS(L25/L$4)) | M30: =IF(M$4="","",ABS(M25/M$4)) | N30: =IF(N$4="","",ABS(N25/N$4)) | ... Q30: =IF(Q$4="","",ABS(Q25/Q$4))
B32: Fixed Costs
B33: G&A and other Opex | C33: -90000 | E33: Historical Average | G33: =Data!C41 -> -361467 | H33: =Data!D41 -> -390283 | I33: =Data!E41 -> -330088 | J33: =Data!F41 -> -389543 | K33: =Data!G41 -> -672911 | L33: =Data!H41 | M33: =Data!I41 | N33: =Data!J41 | ... Q33: =Data!M41
B34: R&D | C34: =AVERAGE(G34:J34) -> 0 | E34: Historical Average | G34: =Data!C42 -> 0 | H34: =Data!D42 -> 0 | I34: =Data!E42 -> 0 | J34: =Data!F42 -> 0 | K34: =Data!G42 -> 0 | L34: =Data!H42 | M34: =Data!I42 | N34: =Data!J42 | ... Q34: =Data!M42
B35: Fixed Costs | C35: =C33+C34 -> -90000 | G35: =IF(G4="","",G33+G34) -> -361467 | H35: =IF(H4="","",H33+H34) -> -390283 | I35: =IF(I4="","",I33+I34) -> -330088 | J35: =IF(J4="","",J33+J34) -> -389543 | K35: =IF(K4="","",K33+K34) -> -672911 | L35: =IF(L4="","",L33+L34) | M35: =IF(M4="","",M33+M34) | N35: =IF(N4="","",N33+N34) | ... Q35: =IF(Q4="","",Q33+Q34)
B37: Fixed Costs % of Sales
B38: =B33 -> G&A and other Opex | C38: =ABS(C33/$C$4) -> 0.36397313 | G38: =IF(G$4="","",ABS(G33/G$4)) -> 1.4618253 | H38: =IF(H$4="","",ABS(H33/H$4)) -> 1.3842228 | I38: =IF(I$4="","",ABS(I33/I$4)) -> 0.99438173 | J38: =IF(J$4="","",ABS(J33/J$4)) -> 0.51566823 | K38: =IF(K$4="","",ABS(K33/K$4)) -> 0.32814858 | L38: =IF(L$4="","",ABS(L33/L$4)) | M38: =IF(M$4="","",ABS(M33/M$4)) | N38: =IF(N$4="","",ABS(N33/N$4)) | ... Q38: =IF(Q$4="","",ABS(Q33/Q$4))
B39: =B34 -> R&D | C39: =ABS(C34/$C$4) -> 0 | G39: =IF(G$4="","",ABS(G34/G$4)) -> 0 | H39: =IF(H$4="","",ABS(H34/H$4)) -> 0 | I39: =IF(I$4="","",ABS(I34/I$4)) -> 0 | J39: =IF(J$4="","",ABS(J34/J$4)) -> 0 | K39: =IF(K$4="","",ABS(K34/K$4)) -> 0 | L39: =IF(L$4="","",ABS(L34/L$4)) | M39: =IF(M$4="","",ABS(M34/M$4)) | N39: =IF(N$4="","",ABS(N34/N$4)) | ... Q39: =IF(Q$4="","",ABS(Q34/Q$4))
B40: Fixed Costs | C40: =ABS(C35/$C$4) -> 0.36397313 | G40: =IF(G$4="","",ABS(G35/G$4)) -> 1.4618253 | H40: =IF(H$4="","",ABS(H35/H$4)) -> 1.3842228 | I40: =IF(I$4="","",ABS(I35/I$4)) -> 0.99438173 | J40: =IF(J$4="","",ABS(J35/J$4)) -> 0.51566823 | K40: =IF(K$4="","",ABS(K35/K$4)) -> 0.32814858 | L40: =IF(L$4="","",ABS(L35/L$4)) | M40: =IF(M$4="","",ABS(M35/M$4)) | N40: =IF(N$4="","",ABS(N35/N$4)) | ... Q40: =IF(Q$4="","",ABS(Q35/Q$4))
B42: Tax % of Pre-tax Profit
B43: Income Tax Rate | C43: 0.25 | E43: Use the highest past tax rate | G43: =IF(G$4="","",-G14/SUM(G8+G11,G12)) -> -0.011201582 | H43: =IF(H$4="","",-H14/SUM(H8+H11,H12)) -> -0.016365864 | I43: =IF(I$4="","",-I14/SUM(I8+I11,I12)) -> -1.1549008 | J43: =IF(J$4="","",-J14/SUM(J8+J11,J12)) -> 0.13838238 | K43: =IF(K$4="","",-K14/SUM(K8+K11,K12)) -> 0.16097344 | L43: =IF(L$4="","",-L14/SUM(L8+L11,L12)) | M43: =IF(M$4="","",-M14/SUM(M8+M11,M12)) | N43: =IF(N$4="","",-N14/SUM(N8+N11,N12)) | ... Q43: =IF(Q$4="","",-Q14/SUM(Q8+Q11,Q12))
B45: Non-operating Income | E45: Notes
B46: Interest
B47: Interest Expense | C47: =-BS!G31*Normalized_FCF!C54 -> -8149 | G47: =Data!C51 -> -8149 | H47: =Data!D51 -> -7447 | I47: =Data!E51 -> -5293 | J47: =Data!F51 -> -3968 | K47: =Data!G51 -> 0 | L47: =Data!H51 | M47: =Data!I51 | N47: =Data!J51 | ... Q47: =Data!M51
B48: Operating Interest Income | C48: =BS!D75*C53 -> 5314.0836 | G48: =IFERROR(IF(G$4="","",($C$48/$C$49)*G49),0) -> 5314.0836 | H48: =IFERROR(IF(H$4="","",($C$48/$C$49)*H49),0) -> 6487.7061 | I48: =IFERROR(IF(I$4="","",($C$48/$C$49)*I49),0) -> 0 | J48: =IFERROR(IF(J$4="","",($C$48/$C$49)*J49),0) -> 0 | K48: =IFERROR(IF(K$4="","",($C$48/$C$49)*K49),0) -> 0 | L48: =IFERROR(IF(L$4="","",($C$48/$C$49)*L49),0) | M48: =IFERROR(IF(M$4="","",($C$48/$C$49)*M49),0) | N48: =IFERROR(IF(N$4="","",($C$48/$C$49)*N49),0) | ... Q48: =IFERROR(IF(Q$4="","",($C$48/$C$49)*Q49),0)
B49: From Interest Income | C49: =BS!$C$66*C53 -> 34933 | G49: =Data!C52 -> 34933 | H49: =Data!D52 -> 42648 | I49: =Data!E52 -> 0 | J49: =Data!F52 -> 0 | K49: =Data!G52 -> 0 | L49: =Data!H52 | M49: =Data!I52 | N49: =Data!J52 | ... Q49: =Data!M52
B50: Net Interest Income | C50: =C47+C48 -> -2834.9164 | G50: =IF(G$4="","",(G47+G48)) -> -2834.9164 | H50: =IF(H$4="","",(H47+H48)) -> -959.2939 | I50: =IF(I$4="","",(I47+I48)) -> -5293 | J50: =IF(J$4="","",(J47+J48)) -> -3968 | K50: =IF(K$4="","",(K47+K48)) -> 0 | L50: =IF(L$4="","",(L47+L48)) | M50: =IF(M$4="","",(M47+M48)) | N50: =IF(N$4="","",(N47+N48)) | ... Q50: =IF(Q$4="","",(Q47+Q48))
B52: % Interest | G52: Latest Asset Value
B53: Interest Yield/Cash | C53: =G53 -> 0.032422313 | E53: Reference the market rate | G53: =IF(Normalized_FCF!G4="","",Normalized_FCF!G49/BS!$C$66) -> 0.032422313
B54: Interest Rate/Debt | C54: =G54 -> 0.083695373 | E54: Use Last year's rate | G54: =IFERROR(ABS(Normalized_FCF!G47/BS!$G$31),0) -> 0.083695373
B55: Pre-tax Profit/Interest Expense | C55: =-C8/C47 -> -7.6409375 | G55: =IF(G4="","",-G8/G47) -> -40.953859 | H55: =IF(H4="","",-H8/H47) -> -45.822076 | I55: =IF(I4="","",-I8/I47) -> 0.35235216 | J55: =IF(J4="","",-J8/J47) -> 92.205393 | K55: =IF(K4="","",-K8/K47) -> #DIV/0! | L55: =IF(L4="","",-L8/L47) | M55: =IF(M4="","",-M8/M47) | N55: =IF(N4="","",-N8/N47) | ... Q55: =IF(Q4="","",-Q8/Q47)
B57: Non-operating EBIT | G57: Latest Asset Value
B58: Dividend or Interests from FA | C58: =BS!$C67*C66 -> 63615 | G58: =Data!C56 -> 63615 | H58: =Data!D56 -> 54615 | I58: =Data!E56 -> 0 | J58: =Data!F56 -> 0 | K58: =Data!G56 -> 0 | L58: =Data!H56 | M58: =Data!I56 | N58: =Data!J56 | ... Q58: =Data!M56
B59: Share of JV or associate Results | C59: =BS!$C68*C67 -> 0 | G59: =Data!C55 -> 0 | H59: =Data!D55 -> 0 | I59: =Data!E55 -> 0 | J59: =Data!F55 -> 0 | K59: =Data!G55 -> 0 | L59: =Data!H55 | M59: =Data!I55 | N59: =Data!J55 | ... Q59: =Data!M55
B60: Investment property | C60: =BS!$C69*C68 -> 6932.28 | G60: =Data!C57 -> 12454 | H60: =Data!D57 -> 12191 | I60: =Data!E57 -> 0 | J60: =Data!F57 -> 0 | K60: =Data!G57 -> 0 | L60: =Data!H57 | M60: =Data!I57 | N60: =Data!J57 | ... Q60: =Data!M57
B61: Stable Non-Operating EBIT | C61: =SUM(C58:C60) -> 70547.28 | G61: =IF(G4="","",SUM(G58:G60)) -> 76069 | H61: =IF(H4="","",SUM(H58:H60)) -> 66806 | I61: =IF(I4="","",SUM(I58:I60)) -> 0 | J61: =IF(J4="","",SUM(J58:J60)) -> 0 | K61: =IF(K4="","",SUM(K58:K60)) -> 0 | L61: =IF(L4="","",SUM(L58:L60)) | M61: =IF(M4="","",SUM(M58:M60)) | N61: =IF(N4="","",SUM(N58:N60)) | ... Q61: =IF(Q4="","",SUM(Q58:Q60))
B62: Other Non-operating Income | C62: 0 | E62: Assume 0 | G62: =Data!C58 -> 264609 | H62: =Data!D58 -> 266825 | I62: =Data!E58 -> -536928 | J62: =Data!F58 -> 145991 | K62: =Data!G58 -> 223533 | L62: =Data!H58 | M62: =Data!I58 | N62: =Data!J58 | ... Q62: =Data!M58
B63: Total Non-Operating EBIT | C63: =C61+C62 -> 70547.28 | G63: =IF(G4="","",G61+G62) -> 340678 | H63: =IF(H4="","",H61+H62) -> 333631 | I63: =IF(I4="","",I61+I62) -> -536928 | J63: =IF(J4="","",J61+J62) -> 145991 | K63: =IF(K4="","",K61+K62) -> 223533 | L63: =IF(L4="","",L61+L62) | M63: =IF(M4="","",M61+M62) | N63: =IF(N4="","",N61+N62) | ... Q63: =IF(Q4="","",Q61+Q62)
B65: Non-operating Asset Yield % | G65: Latest Asset Value
B66: Dividend or Interests from FA | C66: =G66 -> 0.037671324 | G66: =IFERROR(G58/BS!$C$67,0) -> 0.037671324
B67: JV or associate | C67: =G67 -> 0 | G67: =IFERROR(G59/BS!$C$68,0) -> 0
B68: Investment property | C68: 0.04 | G68: =IFERROR(G60/BS!$C$69,0) -> 0.071860917
B69: Stable Non-Operating EBIT | C69: =C61/BS!C70 -> 0.024000335 | G69: =G61/BS!C70 -> 0.025878836
B71: P&L & Dividend Analysis | E71: Notes
B72: P&L % Sales
B73: Variable Costs | C73: =ABS(C5/C$4) -> 0.88783966 | G73: =IF(G$4="","",ABS(G5/G$4)) -> 0.88783966 | H73: =IF(H$4="","",ABS(H5/H$4)) -> 0.82604779 | I73: =IF(I$4="","",ABS(I5/I$4)) -> 0 | J73: =IF(J$4="","",ABS(J5/J$4)) -> 0 | K73: =IF(K$4="","",ABS(K5/K$4)) -> 0 | L73: =IF(L$4="","",ABS(L5/L$4)) | M73: =IF(M$4="","",ABS(M5/M$4)) | N73: =IF(N$4="","",ABS(N5/N$4)) | ... Q73: =IF(Q$4="","",ABS(Q5/Q$4))
B74: Contribution Margin | C74: =ABS(C6/C$4) -> 0.11216034 | G74: =IF(G$4="","",ABS(G6/G$4)) -> 0.11216034 | H74: =IF(H$4="","",ABS(H6/H$4)) -> 0.17395221 | I74: =IF(I$4="","",ABS(I6/I$4)) -> 1 | J74: =IF(J$4="","",ABS(J6/J$4)) -> 1 | K74: =IF(K$4="","",ABS(K6/K$4)) -> 1 | L74: =IF(L$4="","",ABS(L6/L$4)) | M74: =IF(M$4="","",ABS(M6/M$4)) | N74: =IF(N$4="","",ABS(N6/N$4)) | ... Q74: =IF(Q$4="","",ABS(Q6/Q$4))
B75: Fixed Costs | C75: =ABS(C7/C$4) -> 0.36397313 | G75: =IF(G$4="","",ABS(G7/G$4)) -> 1.4618253 | H75: =IF(H$4="","",ABS(H7/H$4)) -> 1.3842228 | I75: =IF(I$4="","",ABS(I7/I$4)) -> 0.99438173 | J75: =IF(J$4="","",ABS(J7/J$4)) -> 0.51566823 | K75: =IF(K$4="","",ABS(K7/K$4)) -> 0.32814858 | L75: =IF(L$4="","",ABS(L7/L$4)) | M75: =IF(M$4="","",ABS(M7/M$4)) | N75: =IF(N$4="","",ABS(N7/N$4)) | ... Q75: =IF(Q$4="","",ABS(Q7/Q$4))
B76: Operating EBIT | C76: =ABS(C8/C$4) -> 0.25181279 | G76: =IF(G$4="","",ABS(G8/G$4)) -> 1.3496649 | H76: =IF(H$4="","",ABS(H8/H$4)) -> 1.2102706 | I76: =IF(I$4="","",ABS(I8/I$4)) -> 0.0056182652 | J76: =IF(J$4="","",ABS(J8/J$4)) -> 0.48433177 | K76: =IF(K$4="","",ABS(K8/K$4)) -> 0.67185142 | L76: =IF(L$4="","",ABS(L8/L$4)) | M76: =IF(M$4="","",ABS(M8/M$4)) | N76: =IF(N$4="","",ABS(N8/N$4)) | ... Q76: =IF(Q$4="","",ABS(Q8/Q$4))
B77: Add Back D&A | C77: =ABS(C9/C$4) -> 0 | G77: =IF(G$4="","",G9/G$4) -> 0 | H77: =IF(H$4="","",H9/H$4) -> 0 | I77: =IF(I$4="","",I9/I$4) -> 0 | J77: =IF(J$4="","",J9/J$4) -> 0 | K77: =IF(K$4="","",K9/K$4) -> 0 | L77: =IF(L$4="","",L9/L$4) | M77: =IF(M$4="","",M9/M$4) | N77: =IF(N$4="","",N9/N$4) | ... Q77: =IF(Q$4="","",Q9/Q$4)
B78: Maintenance Capex | C78: =MAX(AVERAGE(G78:J78),C77) -> 0 | E78: Historical Average or D&A | G78: =IF(G$4="","",-G10/G$4) -> -4.0684108e-06 | H78: =IF(H$4="","",-H10/H$4) -> -3.5679959e-06 | I78: =IF(I$4="","",-I10/I$4) -> -2.9703e-06 | J78: =IF(J$4="","",-J10/J$4) -> -6.8571671e-06 | K78: =IF(K$4="","",-K10/K$4) -> -4.1182486e-06 | L78: =IF(L$4="","",-L10/L$4) | M78: =IF(M$4="","",-M10/M$4) | N78: =IF(N$4="","",-N10/N$4) | ... Q78: =IF(Q$4="","",-Q10/Q$4)
B79: Non-Operating EBIT | C79: =ABS(C11/C$4) -> 0.28530349 | G79: =IF(G$4="","",G11/G$4) -> 0.30763413 | H79: =IF(H$4="","",H11/H$4) -> 0.23694188 | I79: =IF(I$4="","",I11/I$4) -> 0 | J79: =IF(J$4="","",J11/J$4) -> 0 | K79: =IF(K$4="","",K11/K$4) -> 0 | L79: =IF(L$4="","",L11/L$4) | M79: =IF(M$4="","",M11/M$4) | N79: =IF(N$4="","",N11/N$4) | ... Q79: =IF(Q$4="","",Q11/Q$4)
B80: Net Interest Income | C80: =ABS(C12/C$4) -> 0.011464816 | G80: =IF(G$4="","",ABS(G12/G$4)) -> 0.011464816 | H80: =IF(H$4="","",ABS(H12/H$4)) -> 0.0034023426 | I80: =IF(I$4="","",ABS(I12/I$4)) -> 0.015945028 | J80: =IF(J$4="","",ABS(J12/J$4)) -> 0.0052527488 | K80: =IF(K$4="","",ABS(K12/K$4)) -> 0 | L80: =IF(L$4="","",ABS(L12/L$4)) | M80: =IF(M$4="","",ABS(M12/M$4)) | N80: =IF(N$4="","",ABS(N12/N$4)) | ... Q80: =IF(Q$4="","",ABS(Q12/Q$4))
B81: Pre-tax Profit | C81: =C13/C4 -> 0.022025889 | G81: =IF(G$4="","",G13/G$4) -> -1.0534916 | H81: =IF(H$4="","",H13/H$4) -> -0.97672747 | I81: =IF(I$4="","",I13/I$4) -> -0.010323793 | J81: =IF(J$4="","",J13/J$4) -> 0.47908588 | K81: =IF(K$4="","",K13/K$4) -> 0.67185554 | L81: =IF(L$4="","",L13/L$4) | M81: =IF(M$4="","",M13/M$4) | N81: =IF(N$4="","",N13/N$4) | ... Q81: =IF(Q$4="","",Q13/Q$4)
B82: Income Tax | C82: =ABS(C14/C$4) -> 0.0055064722 | G82: =IF(G$4="","",ABS(G14/G$4)) -> 0.011800818 | H82: =IF(H$4="","",ABS(H14/H$4)) -> 0.015985047 | I82: =IF(I$4="","",ABS(I14/I$4)) -> 0.011926387 | J82: =IF(J$4="","",ABS(J14/J$4)) -> 0.066296097 | K82: =IF(K$4="","",ABS(K14/K$4)) -> 0.10815023 | L82: =IF(L$4="","",ABS(L14/L$4)) | M82: =IF(M$4="","",ABS(M14/M$4)) | N82: =IF(N$4="","",ABS(N14/N$4)) | ... Q82: =IF(Q$4="","",ABS(Q14/Q$4))
B83: =B15 -> NCI’s Share of Profits | C83: =MIN(BS!C62,MAX(G83:K83)) -> 0 | G83: =IF(G$4="","",-G15/G$4) -> 0 | H83: =IF(H$4="","",-H15/H$4) -> 0 | I83: =IF(I$4="","",-I15/I$4) -> 0 | J83: =IF(J$4="","",-J15/J$4) -> 0 | K83: =IF(K$4="","",-K15/K$4) -> 0 | L83: =IF(L$4="","",-L15/L$4) | M83: =IF(M$4="","",-M15/M$4) | N83: =IF(N$4="","",-N15/N$4) | ... Q83: =IF(Q$4="","",-Q15/Q$4)
B84: After-tax Profit | C84: =ABS(C16/C$4) -> 0.016519417 | G84: =IF(G$4="","",ABS(G16/G$4)) -> 1.0652924 | H84: =IF(H$4="","",ABS(H16/H$4)) -> 0.99271252 | I84: =IF(I$4="","",ABS(I16/I$4)) -> 0.02225018 | J84: =IF(J$4="","",ABS(J16/J$4)) -> 0.41278978 | K84: =IF(K$4="","",ABS(K16/K$4)) -> 0.5637053 | L84: =IF(L$4="","",ABS(L16/L$4)) | M84: =IF(M$4="","",ABS(M16/M$4)) | N84: =IF(N$4="","",ABS(N16/N$4)) | ... Q84: =IF(Q$4="","",ABS(Q16/Q$4))
B85: WCInv | C85: 0 | E85: =E17 -> WCInv is by default excluded
B86: Net Borrowing | C86: 0 | E86: =E18 -> Net borrowing is excluded
B87: Total FCFE | C87: =ABS(C19/C$4) -> 0.016519417 | G87: =IF(G$4="","",ABS(G19/G$4)) -> 1.0652924 | H87: =IF(H$4="","",ABS(H19/H$4)) -> 0.99271252 | I87: =IF(I$4="","",ABS(I19/I$4)) -> 0.02225018 | J87: =IF(J$4="","",ABS(J19/J$4)) -> 0.41278978 | K87: =IF(K$4="","",ABS(K19/K$4)) -> 0.5637053 | L87: =IF(L$4="","",ABS(L19/L$4)) | M87: =IF(M$4="","",ABS(M19/M$4)) | N87: =IF(N$4="","",ABS(N19/N$4)) | ... Q87: =IF(Q$4="","",ABS(Q19/Q$4))
B89: Dividends
B90: ="Dividend per share ("&Market_currency&")" -> Dividend per share (HKD) | C90: =G90 -> 0.01 | G90: =Data!C65 -> 0.01 | H90: =Data!D65 -> 0 | I90: =Data!E65 -> 0.034 | J90: =Data!F65 -> 0.08 | K90: =Data!G65 -> 0.26 | L90: =Data!H65 | M90: =Data!I65 | N90: =Data!J65 | ... Q90: =Data!M65
B91: ="Dividend ("&Market_currency&")" -> Dividend (HKD) | C91: =C90*Common_Shares/$C$3 -> 18267.098 | G91: =IF(G$4="","",G90*Common_Shares/$C$3) -> 18267.098 | H91: =IF(H$4="","",H90*Common_Shares/$C$3) -> 0 | I91: =IF(I$4="","",I90*Common_Shares/$C$3) -> 62108.134 | J91: =IF(J$4="","",J90*Common_Shares/$C$3) -> 146136.79 | K91: =IF(K$4="","",K90*Common_Shares/$C$3) -> 474944.56 | L91: =IF(L$4="","",L90*Common_Shares/$C$3) | M91: =IF(M$4="","",M90*Common_Shares/$C$3) | N91: =IF(N$4="","",N90*Common_Shares/$C$3) | ... Q91: =IF(Q$4="","",Q90*Common_Shares/$C$3)
B92: Payout Ratio | C92: =C90/(C19*$C$3/Common_Shares) -> 4.4719987 | G92: =IF(G$4="","",G90/(G19*$C$3/Common_Shares)) -> -0.069346982 | H92: =IF(H$4="","",H90/(H19*$C$3/Common_Shares)) -> 0 | I92: =IF(I$4="","",I90/(I19*$C$3/Common_Shares)) -> -8.4088839 | J92: =IF(J$4="","",J90/(J19*$C$3/Common_Shares)) -> 0.46864672 | K92: =IF(K$4="","",K90/(K19*$C$3/Common_Shares)) -> 0.41086931 | L92: =IF(L$4="","",L90/(L19*$C$3/Common_Shares)) | M92: =IF(M$4="","",M90/(M19*$C$3/Common_Shares)) | N92: =IF(N$4="","",N90/(N19*$C$3/Common_Shares)) | ... Q92: =IF(Q$4="","",Q90/(Q19*$C$3/Common_Shares))
B93: Dividend Yield | C93: =C90/Market_Price -> 0.0074074074 | G93: =IF(G$4="","",G90/Market_Price) -> 0.0074074074 | H93: =IF(H$4="","",H90/Market_Price) -> 0 | I93: =IF(I$4="","",I90/Market_Price) -> 0.025185185 | J93: =IF(J$4="","",J90/Market_Price) -> 0.059259259 | K93: =IF(K$4="","",K90/Market_Price) -> 0.19259259 | L93: =IF(L$4="","",L90/Market_Price) | M93: =IF(M$4="","",M90/Market_Price) | N93: =IF(N$4="","",N90/Market_Price) | ... Q93: =IF(Q$4="","",Q90/Market_Price)
B95: YoY %
B96: Sales | C96: =C4/G4-1 -> 0 | G96: =IF(H4="","",G4/H4-1) -> -0.1230001 | H96: =IF(I4="","",H4/I4-1) -> -0.15062976 | I96: =IF(J4="","",I4/J4-1) -> -0.56056811 | J96: =IF(K4="","",J4/K4-1) -> -0.6316184 | K96: =IF(L4="","",K4/L4-1) | L96: =IF(M4="","",L4/M4-1) | M96: =IF(N4="","",M4/N4-1) | N96: =IF(O4="","",N4/O4-1) | ... Q96: =IF(R4="","",Q4/R4-1)
B97: Pre-tax Profit | C97: =C13/G13-1 -> -1.0209075 | G97: =IF(H5="","",G13/H13-1) -> -0.054073917 | H97: =IF(I5="","",H13/I13-1) -> 79.358378 | I97: =IF(J5="","",I13/J13-1) -> -1.0094693 | J97: =IF(K5="","",J13/K13-1) -> -0.73731492 | K97: =IF(L5="","",K13/L13-1) | L97: =IF(M5="","",L13/M13-1) | M97: =IF(N5="","",M13/N13-1) | N97: =IF(O5="","",N13/O13-1) | ... Q97: =IF(R5="","",Q13/R13-1)
B99: Operating Efficiency Analysis | E99: Notes
B100: Balance Sheet | G100: Latest Asset Value
B101: Total Assets | C101: =BS!G32 -> 3775213 | G101: =IF(G$4="","",G105+G104) -> 3775213 | H101: =IF(H$4="","",H105+H104) -> 4678082 | I101: =IF(I$4="","",I105+I104) -> 4747857 | J101: =IF(J$4="","",J105+J104) -> 5670342 | K101: =IF(K$4="","",K105+K104) -> 6298813 | L101: =IF(L$4="","",L105+L104) | M101: =IF(M$4="","",M105+M104) | N101: =IF(N$4="","",N105+N104) | ... Q101: =IF(Q$4="","",Q105+Q104)
B102: Incl. AR | C102: =BS!C4 -> 83455 | G102: =IF(G$4="","",Data!D77) -> 56325 | H102: =IF(H$4="","",Data!E77) -> 67131 | I102: =IF(I$4="","",Data!F77) -> 190060 | J102: =IF(J$4="","",Data!G77) -> 1495304 | K102: =IF(K$4="","",Data!H77) | L102: =IF(L$4="","",Data!I77) | M102: =IF(M$4="","",Data!J77) | N102: =IF(N$4="","",Data!K77) | ... Q102: =IF(Q$4="","",Data!N77)
B103: Incl. Inventory | C103: =BS!C6+BS!C7 -> 0 | G103: =IF(G$4="","",Data!D78) -> 0 | H103: =IF(H$4="","",Data!E78) -> 0 | I103: =IF(I$4="","",Data!F78) -> 0 | J103: =IF(J$4="","",Data!G78) -> 0 | K103: =IF(K$4="","",Data!H78) | L103: =IF(L$4="","",Data!I78) | M103: =IF(M$4="","",Data!J78) | N103: =IF(N$4="","",Data!K78) | ... Q103: =IF(Q$4="","",Data!N78)
B104: Total Liabilities | C104: =BS!G30 -> 215440 | G104: =Data!C79 -> 215440 | H104: =Data!D79 -> 1135384 | I104: =Data!E79 -> 253658 | J104: =Data!F79 -> 405587 | K104: =Data!G79 -> 880771 | L104: =Data!H79 | M104: =Data!I79 | N104: =Data!J79 | ... Q104: =Data!M79
B105: Total Equity | C105: =BS!G27 -> 3559773 | G105: =Data!C80 -> 3559773 | H105: =Data!D80 -> 3542698 | I105: =Data!E80 -> 4494199 | J105: =Data!F80 -> 5264755 | K105: =Data!G80 -> 5418042 | L105: =Data!H80 | M105: =Data!I80 | N105: =Data!J80 | ... Q105: =Data!M80
B107: Operating Asset % of Sales | G107: Latest Asset Value
B108: AR | C108: =C102/C$4 -> 0.3375042 | G108: =IF(G$4="","",G102/G$4) -> 0.22778652 | H108: =IF(H$4="","",H102/H$4) -> 0.23809456 | I108: =IF(I$4="","",I102/I$4) -> 0.57255093 | J108: =IF(J$4="","",J102/J$4) -> 1.9794497 | K108: =IF(K$4="","",K102/K$4) -> #VALUE! | L108: =IF(L$4="","",L102/L$4) | M108: =IF(M$4="","",M102/M$4) | N108: =IF(N$4="","",N102/N$4) | ... Q108: =IF(Q$4="","",Q102/Q$4)
B109: Inventory | C109: =C103/C$4 -> 0 | G109: =IF(G$4="","",G103/G$4) -> 0 | H109: =IF(H$4="","",H103/H$4) -> 0 | I109: =IF(I$4="","",I103/I$4) -> 0 | J109: =IF(J$4="","",J103/J$4) -> 0 | K109: =IF(K$4="","",K103/K$4) -> #VALUE! | L109: =IF(L$4="","",L103/L$4) | M109: =IF(M$4="","",M103/M$4) | N109: =IF(N$4="","",N103/N$4) | ... Q109: =IF(Q$4="","",Q103/Q$4)
B110: Properties held for sale | C110: =BS!$G$38/C$4 -> 0 | G110: =BS!$G$38/G$4 -> 0
B112: Cash Flow Statement
B113: CFO/Net Income | G113: =IF(G$4="","",Data!C$22/Data!C15) -> -0.067962741 | H113: =IF(H$4="","",Data!D$22/Data!D15) -> 2.439579 | I113: =IF(I$4="","",Data!E$22/Data!E15) -> 0.14080266 | J113: =IF(J$4="","",Data!F$22/Data!F15) -> 2.3495379 | K113: =IF(K$4="","",Data!G$22/Data!G15) -> 0.15429928 | L113: =IF(L$4="","",Data!H$22/Data!H15) | M113: =IF(M$4="","",Data!I$22/Data!I15) | N113: =IF(N$4="","",Data!J$22/Data!J15) | ... Q113: =IF(Q$4="","",Data!M$22/Data!M15)
B114: CFO/FCFE | G114: =IF(G$4="","",Data!C$22/G19) -> 0.0079494059 | H114: =IF(H$4="","",Data!D$22/H19) -> -0.20123525 | I114: =IF(I$4="","",Data!E$22/I19) -> 10.376503 | J114: =IF(J$4="","",Data!F$22/J19) -> 3.4495037 | K114: =IF(K$4="","",Data!G$22/K19) -> 0.18413592 | L114: =IF(L$4="","",Data!H$22/L19) | M114: =IF(M$4="","",Data!I$22/M19) | N114: =IF(N$4="","",Data!J$22/N19) | ... Q114: =IF(Q$4="","",Data!M$22/Q19)
B116: ROE | G116: =IFERROR(IF(#REF!*G118*(1/#REF!)=G120,"","Error"),"") | H116: =IFERROR(IF(#REF!*H118*(1/#REF!)=H120,"","Error"),"") | I116: =IFERROR(IF(#REF!*I118*(1/#REF!)=I120,"","Error"),"") | J116: =IFERROR(IF(#REF!*J118*(1/#REF!)=J120,"","Error"),"") | K116: =IFERROR(IF(#REF!*K118*(1/#REF!)=K120,"","Error"),"") | L116: =IFERROR(IF(#REF!*L118*(1/#REF!)=L120,"","Error"),"") | M116: =IFERROR(IF(#REF!*M118*(1/#REF!)=M120,"","Error"),"") | N116: =IFERROR(IF(#REF!*N118*(1/#REF!)=N120,"","Error"),"") | ... Q116: =IFERROR(IF(#REF!*Q118*(1/#REF!)=Q120,"","Error"),"")
...

Sheet Valuation_Model
B2: No-Growth DCF Valuation | H2: Notes
B3: No-Growth DCF | C3: =Normalized_FCF!C3 -> 1000 | E3: Special Assumption
B4: Adjusted FCFE | C4: =Normalized_FCF!C19 -> 4084.7727 | D4: =Reporting_currency -> HKD | E4: Terminal Growth Rate (g): | F4: =Thesis!C76 -> 0
B5: /Equity Cost of Capital | C5: =Thesis!C70 -> 0.08
B6: Stable Income Value | C6: =(C4*(1+Terminal_Growth))/(Equity_Cost-Terminal_Growth) -> 51059.659 | D6: =Reporting_currency -> HKD | E6: Conservative Valuation: Setting g=0 can be a conservative assumption to avoid overestimating the stock’s value, especially if future growth is uncertain or unreliable.
B7: - Interest-bearing Debt | C7: =BS!G31 -> 97365 | D7: =Reporting_currency -> HKD
B8: + Non-operating Cash | C8: =BS!D66 -> 913534.95 | D8: =Reporting_currency -> HKD
B9: + Other Non-operating Assets | C9: =BS!H42 -> 84349.6 | D9: =Reporting_currency -> HKD
B10: Equity Value | C10: =C6-C7+C8+C9 -> 951579.21 | D10: =Reporting_currency -> HKD
B11: * Exchange rate | C11: =Exchange_Rate -> 1 | D11: =Thesis!D17 -> HKD
B12: Equity Value per share | C12: =(C10*C3)/Common_Shares*C11 -> 0.52092521 | D12: =Market_currency -> HKD
B14: Implied Growth Scenario Analysis
B15: FCFE Projection
B16: High Growth Period (HGP) | C16: =Scenarios!C65 -> 0.046574871
B17: High Growth Rate (HGR) | C17: =Scenarios!C64 -> 10
B18: Value Per Share | C18: =(F52-C7+C8+C9)*Exchange_Rate/Common_Shares*C3 -> 0.52541102 | D18: =Market_currency -> HKD
B20: Year | C20: FCFE | D20: Growth Rates | E20: Discount Factor | F20: PV of FCFE
B21: 1 | C21: =C4*(1+D21) -> 4275.0205 | D21: =IF($C$17<B21,0,Valuation_Model!$C$16) -> 0.046574871 | E21: =IF($C$17<B21,0,1/(1+Equity_Cost)^B21) -> 0.92592593 | F21: =C21*E21 -> 3958.3523
B22: 2 | C22: =IF(ROW()-ROW($C$21)<$C$17, $C$21*(1+D22)^(ROW()-ROW($C$21)), 0) -> 4474.129 | D22: =IF($C$17<B22,0,Valuation_Model!$C$16) -> 0.046574871 | E22: =IF($C$17<B22,0,1/(1+Equity_Cost)^B22) -> 0.85733882 | F22: =C22*E22 -> 3835.8445
B23: 3 | C23: =IF(ROW()-ROW($C$21)<$C$17, $C$21*(1+D23)^(ROW()-ROW($C$21)), 0) -> 4682.511 | D23: =IF($C$17<B23,0,Valuation_Model!$C$16) -> 0.046574871 | E23: =IF($C$17<B23,0,1/(1+Equity_Cost)^B23) -> 0.79383224 | F23: =C23*E23 -> 3717.1282
B24: 4 | C24: =IF(ROW()-ROW($C$21)<$C$17, $C$21*(1+D24)^(ROW()-ROW($C$21)), 0) -> 4900.5983 | D24: =IF($C$17<B24,0,Valuation_Model!$C$16) -> 0.046574871 | E24: =IF($C$17<B24,0,1/(1+Equity_Cost)^B24) -> 0.73502985 | F24: =C24*E24 -> 3602.086
B25: 5 | C25: =IF(ROW()-ROW($C$21)<$C$17, $C$21*(1+D25)^(ROW()-ROW($C$21)), 0) -> 5128.843 | D25: =IF($C$17<B25,0,Valuation_Model!$C$16) -> 0.046574871 | E25: =IF($C$17<B25,0,1/(1+Equity_Cost)^B25) -> 0.6805832 | F25: =C25*E25 -> 3490.6044
B26: 6 | C26: =IF(ROW()-ROW($C$21)<$C$17, $C$21*(1+D26)^(ROW()-ROW($C$21)), 0) -> 5367.7182 | D26: =IF($C$17<B26,0,Valuation_Model!$C$16) -> 0.046574871 | E26: =IF($C$17<B26,0,1/(1+Equity_Cost)^B26) -> 0.63016963 | F26: =C26*E26 -> 3382.573
B27: 7 | C27: =IF(ROW()-ROW($C$21)<$C$17, $C$21*(1+D27)^(ROW()-ROW($C$21)), 0) -> 5617.719 | D27: =IF($C$17<B27,0,Valuation_Model!$C$16) -> 0.046574871 | E27: =IF($C$17<B27,0,1/(1+Equity_Cost)^B27) -> 0.5834904 | F27: =C27*E27 -> 3277.8851
B28: 8 | C28: =IF(ROW()-ROW($C$21)<$C$17, $C$21*(1+D28)^(ROW()-ROW($C$21)), 0) -> 5879.3636 | D28: =IF($C$17<B28,0,Valuation_Model!$C$16) -> 0.046574871 | E28: =IF($C$17<B28,0,1/(1+Equity_Cost)^B28) -> 0.54026888 | F28: =C28*E28 -> 3176.4372
B29: 9 | C29: =IF(ROW()-ROW($C$21)<$C$17, $C$21*(1+D29)^(ROW()-ROW($C$21)), 0) -> 6153.1942 | D29: =IF($C$17<B29,0,Valuation_Model!$C$16) -> 0.046574871 | E29: =IF($C$17<B29,0,1/(1+Equity_Cost)^B29) -> 0.50024897 | F29: =C29*E29 -> 3078.129
B30: 10 | C30: =IF(ROW()-ROW($C$21)<$C$17, $C$21*(1+D30)^(ROW()-ROW($C$21)), 0) -> 6439.7784 | D30: =IF($C$17<B30,0,Valuation_Model!$C$16) -> 0.046574871 | E30: =IF($C$17<B30,0,1/(1+Equity_Cost)^B30) -> 0.46319349 | F30: =C30*E30 -> 2982.8634
B31: 11 | C31: =IF(ROW()-ROW($C$21)<$C$17, $C$21*(1+D31)^(ROW()-ROW($C$21)), 0) -> 0 | D31: =IF($C$17<B31,0,Valuation_Model!$C$16) -> 0 | E31: =IF($C$17<B31,0,1/(1+Equity_Cost)^B31) -> 0 | F31: =C31*E31 -> 0
B32: 12 | C32: =IF(ROW()-ROW($C$21)<$C$17, $C$21*(1+D32)^(ROW()-ROW($C$21)), 0) -> 0 | D32: =IF($C$17<B32,0,Valuation_Model!$C$16) -> 0 | E32: =IF($C$17<B32,0,1/(1+Equity_Cost)^B32) -> 0 | F32: =C32*E32 -> 0
B33: 13 | C33: =IF(ROW()-ROW($C$21)<$C$17, $C$21*(1+D33)^(ROW()-ROW($C$21)), 0) -> 0 | D33: =IF($C$17<B33,0,Valuation_Model!$C$16) -> 0 | E33: =IF($C$17<B33,0,1/(1+Equity_Cost)^B33) -> 0 | F33: =C33*E33 -> 0
... B50: 30 | C50: =IF(ROW()-ROW($C$21)<$C$17, $C$21*(1+D50)^(ROW()-ROW($C$21)), 0) -> 0 | D50: =IF($C$17<B50,0,Valuation_Model!$C$16) -> 0 | E50: =IF($C$17<B50,0,1/(1+Equity_Cost)^B50) -> 0 | F50: =C50*E50 -> 0
B51: Terminal Year | C51: =C$21*(1+Terminal_Growth)^$C$17/Equity_Cost -> 53437.756 | D51: =Terminal_Growth -> 0 | E51: =1/(1+Equity_Cost)^C17 -> 0.46319349 | F51: =C51*E51 -> 24752.02
E52: Total PV | F52: =SUM(F21:F51) -> 59253.924
B54: Sensitivity Analysis (Enterprise Value)
A55: =F52 -> 59253.924 | B55: =C78 -> 0 | C55: =C77 -> 0.02 | D55: =C76 -> 0 | E55: =C75 -> 0.06 | F55: =C74 -> 0.1
A56: 5 | B56: 51059.659 | C56: 52707.111 | D56: 51059.659 | E56: 56152.201 | F56: 59812.311
A57: 10 | B57: 51059.659 | C57: 54356.079 | D57: 51059.659 | E57: 61979.633 | F57: 71263.616
A58: 15 | B58: 51059.659 | C58: 56397.136 | D58: 51059.659 | E58: 69995.492 | F58: 88888.45
A59: 20 | B59: 51059.659 | C59: 58476.645 | D59: 51059.659 | E59: 79139.407 | F59: 111659.53
A60: 25 | B60: 51059.659 | C60: 60410.703 | D60: 51059.659 | E60: 88721.952 | F60: 138968.48
A61: 30 | B61: 51059.659 | C61: 62116.812 | D61: 51059.659 | E61: 98303.28 | F61: 170500.72
B63: Sensitivity Analysis (Equity Value per share)
B64: =B55 -> 0 | C64: =C55 -> 0.02 | D64: =D55 -> 0 | E64: =E55 -> 0.06 | F64: =F55 -> 0.1
A65: 0 | B65: =C12 -> 0.52092521 | C65: =C12 -> 0.52092521 | D65: =C12 -> 0.52092521 | E65: =C12 -> 0.52092521 | F65: =C12 -> 0.52092521
A66: =A56 -> 5 | B66: =(B56-$C$7+$C$8+$C$9)/Common_Shares*$C$3*Exchange_Rate -> 0.52092521 | C66: =(C56-$C$7+$C$8+$C$9)/Common_Shares*$C$3*Exchange_Rate -> 0.52182708 | D66: =(D56-$C$7+$C$8+$C$9)/Common_Shares*$C$3*Exchange_Rate -> 0.52092521 | E66: =(E56-$C$7+$C$8+$C$9)/Common_Shares*$C$3*Exchange_Rate -> 0.52371304 | F66: =(F56-$C$7+$C$8+$C$9)/Common_Shares*$C$3*Exchange_Rate -> 0.5257167
A67: =A57 -> 10 | B67: =(B57-$C$7+$C$8+$C$9)/Common_Shares*$C$3*Exchange_Rate -> 0.52092521 | C67: =(C57-$C$7+$C$8+$C$9)/Common_Shares*$C$3*Exchange_Rate -> 0.52272978 | D67: =(D57-$C$7+$C$8+$C$9)/Common_Shares*$C$3*Exchange_Rate -> 0.52092521 | E67: =(E57-$C$7+$C$8+$C$9)/Common_Shares*$C$3*Exchange_Rate -> 0.52690316 | F67: =(F57-$C$7+$C$8+$C$9)/Common_Shares*$C$3*Exchange_Rate -> 0.53198551
A68: =A58 -> 15 | B68: =(B58-$C$7+$C$8+$C$9)/Common_Shares*$C$3*Exchange_Rate -> 0.52092521 | C68: =(C58-$C$7+$C$8+$C$9)/Common_Shares*$C$3*Exchange_Rate -> 0.52384712 | D68: =(D58-$C$7+$C$8+$C$9)/Common_Shares*$C$3*Exchange_Rate -> 0.52092521 | E68: =(E58-$C$7+$C$8+$C$9)/Common_Shares*$C$3*Exchange_Rate -> 0.5312913 | F68: =(F58-$C$7+$C$8+$C$9)/Common_Shares*$C$3*Exchange_Rate -> 0.54163392
A69: =A59 -> 20 | B69: =(B59-$C$7+$C$8+$C$9)/Common_Shares*$C$3*Exchange_Rate -> 0.52092521 | C69: =(C59-$C$7+$C$8+$C$9)/Common_Shares*$C$3*Exchange_Rate -> 0.52498551 | D69: =(D59-$C$7+$C$8+$C$9)/Common_Shares*$C$3*Exchange_Rate -> 0.52092521 | E69: =(E59-$C$7+$C$8+$C$9)/Common_Shares*$C$3*Exchange_Rate -> 0.53629698 | F69: =(F59-$C$7+$C$8+$C$9)/Common_Shares*$C$3*Exchange_Rate -> 0.55409954
A70: =A60 -> 25 | B70: =(B60-$C$7+$C$8+$C$9)/Common_Shares*$C$3*Exchange_Rate -> 0.52092521 | C70: =(C60-$C$7+$C$8+$C$9)/Common_Shares*$C$3*Exchange_Rate -> 0.52604428 | D70: =(D60-$C$7+$C$8+$C$9)/Common_Shares*$C$3*Exchange_Rate -> 0.52092521 | E70: =(E60-$C$7+$C$8+$C$9)/Common_Shares*$C$3*Exchange_Rate -> 0.54154277 | F70: =(F60-$C$7+$C$8+$C$9)/Common_Shares*$C$3*Exchange_Rate -> 0.56904934
A71: =A61 -> 30 | B71: =(B61-$C$7+$C$8+$C$9)/Common_Shares*$C$3*Exchange_Rate -> 0.52092521 | C71: =(C61-$C$7+$C$8+$C$9)/Common_Shares*$C$3*Exchange_Rate -> 0.52697826 | D71: =(D61-$C$7+$C$8+$C$9)/Common_Shares*$C$3*Exchange_Rate -> 0.52092521 | E71: =(E61-$C$7+$C$8+$C$9)/Common_Shares*$C$3*Exchange_Rate -> 0.5467879 | F71: =(F61-$C$7+$C$8+$C$9)/Common_Shares*$C$3*Exchange_Rate -> 0.58631111
B73: Scenarios | C73: HGR | D73: HGP | E73: Value per share | F73: Probabilities
B74: =Scenarios!B54 -> Snowball Scenario | C74: =Scenarios!C56 -> 0.1 | D74: =Scenarios!C55 -> 15 | E74: =INDEX(B$65:F$71, MATCH(D74, A$65:A$71, 0), MATCH(C74, B$64:F$64, 0)) -> 0.54163392 | F74: =Scenarios!C58 -> 0.05
B75: =Scenarios!B36 -> Optimistic | C75: =Scenarios!C38 -> 0.06 | D75: =Scenarios!C37 -> 10 | E75: =INDEX(B$65:F$71, MATCH(D75, A$65:A$71, 0), MATCH(C75, B$64:F$64, 0)) -> 0.52690316 | F75: =Scenarios!C40*(1-F$74-F$78) -> 0.18
B76: =Scenarios!B24 -> Base | C76: =Scenarios!C26 -> 0 | D76: =Scenarios!C25 -> 10 | E76: =INDEX(B$65:F$71, MATCH(D76, A$65:A$71, 0), MATCH(C76, B$64:F$64, 0)) -> 0.52092521 | F76: =Scenarios!C28*(1-F$74-F$78) -> 0.54
B77: =Scenarios!B30 -> Pessimistic | C77: =Scenarios!C32 -> 0.02 | D77: =Scenarios!C31 -> 10 | E77: =INDEX(B$65:F$71, MATCH(D77, A$65:A$71, 0), MATCH(C77, B$64:F$64, 0)) -> 0.52272978 | F77: =Scenarios!C34*(1-F$74-F$78) -> 0.18
B78: =Scenarios!B48 -> Devil's advocate | C78: =Scenarios!C50 -> 0 | D78: =Scenarios!C49 -> 15 | E78: =INDEX(B$65:F$71, MATCH(D78, A$65:A$71, 0), MATCH(C78, B$64:F$64, 0)) -> 0.52092521 | F78: =Scenarios!C52 -> 0.05
B80: Note of the formulas: | C80: MATCH(1%, C65:E65, 0) finds the column number for HGR = 1%.
C81: MATCH(5, B66:B69, 0) finds the row number for HGP = 5.
C82: INDEX(C66:E69, ...) retrieves the value from the specified range.

Sheet Scenarios
B2: Current Situation | H2: Warning: Do Not Remove this logic
B3: Selection | H3: 0 | I3: =-Market_Price -> -1.35
B4: Past Years Selected | C4: 3 | E4: Tie the business story into the three levers of value: FCFE, growth and risk. | H4: 1 | I4: =IF(ROW()-3 < $C$76, $C$77, IF(ROW()-3 = $C$76, $C$77 + $C$60, "")) -> 0.01
H5: 2 | I5: =IF(ROW()-3 < $C$76, $C$77, IF(ROW()-3 = $C$76, $C$77 + $C$60, "")) -> 0.01
B6: Latest | C6: =Valuation_Model!C3 -> 1000 | E6: Prompt for fundamental Analysis | H6: 3 | I6: =IF(ROW()-3 < $C$76, $C$77, IF(ROW()-3 = $C$76, $C$77 + $C$60, "")) -> 0.5333615
B7: EBIT | C7: =Normalized_FCF!G8 -> -333733 | D7: =Reporting_currency -> HKD | E7: ="Please develop three logical "&C18&"-year scenarios (Base Case, Pessimistic Case, Optimistic Case) and two extreme "&C46&"-year scenarios (Success Scenario, Devil’s Advocate Scenario) for "&Thesis!C5&"("&Thesis!D5&"). Each scenario should include the Compound Growth Rate, the Probability Assessment, and the Business Narrative." -> Please develop three logical 10-year scenarios (Base Case, Pessimistic Case, Optimistic Case) and two extreme 15-year scenarios (Success Scenario, Devil’s Advocate Scenario) for 惠理集團(0806.HK). Each scenario should include the Compound Growth Rate, the Probability Assessment, and the Business Narrative. | H7: 4 | I7: =IF(ROW()-3 < $C$76, $C$77, IF(ROW()-3 = $C$76, $C$77 + $C$60, ""))
B8: FCFE | C8: =Normalized_FCF!G19 -> -263415.91 | D8: =Reporting_currency -> HKD | H8: 5 | I8: =IF(ROW()-3 < $C$76, $C$77, IF(ROW()-3 = $C$76, $C$77 + $C$60, ""))
B9: Normalized | C9: =Normalized_FCF!C19 -> 4084.7727 | D9: =Reporting_currency -> HKD | H9: 6 | I9: =IF(ROW()-3 < $C$76, $C$77, IF(ROW()-3 = $C$76, $C$77 + $C$60, ""))
H10: 7 | I10: =IF(ROW()-3 < $C$76, $C$77, IF(ROW()-3 = $C$76, $C$77 + $C$60, ""))
B11: CAGR | H11: 8 | I11: =IF(ROW()-3 < $C$76, $C$77, IF(ROW()-3 = $C$76, $C$77 + $C$60, ""))
B12: Sales | C12: =(Normalized_FCF!G4/OFFSET(Normalized_FCF!G4, 0, $C$4))^(1/$C$4) - 1 -> -0.31082521 | H12: 9 | I12: =IF(ROW()-3 < $C$76, $C$77, IF(ROW()-3 = $C$76, $C$77 + $C$60, ""))
B13: Operating EBIT | C13: =(Normalized_FCF!G8/OFFSET(Normalized_FCF!G8, 0, $C$4))^(1/$C$4) - 1 -> -1.9698183 | H13: 10 | I13: =IF(ROW()-3 < $C$76, $C$77, IF(ROW()-3 = $C$76, $C$77 + $C$60, ""))
B14: FCFE | C14: =(Normalized_FCF!G19/OFFSET(Normalized_FCF!G19, 0, $C$4))^(1/$C$4) - 1 -> -1.9453138
B16: General Scenarios
B17: Assumption | E17: Guidance Note
B18: High Growth Period (HGP) | C18: 10 | E18: Fundamental analysis and market signal analysis should be combined, with fundamental analysis given priority and market signal analysis serving as a supplement. Market signal analysis predicts a company's future trend, while fundamental analysis interprets the trend and identifies relevant fundamental factors and possibilities.
B20: Reference
B21: Market Price | C21: =Market_Price -> 1.35 | D21: =Market_currency -> HKD
B22: No Growth Value per share | C22: =Valuation_Model!C12 -> 0.52092521 | D22: =Market_currency -> HKD
B24: Base | E24: Business Story
B25: High Growth Period (HGP) | C25: =C18 -> 10
B26: High Growth Rate (HGR) | C26: 0
B27: Value per share | C27: =Valuation_Model!E76 -> 0.52092521 | D27: =Market_currency -> HKD
B28: Probabilities | C28: 0.6
B30: Pessimistic | E30: Business Story
B31: High Growth Period (HGP) | C31: =C18 -> 10
B32: High Growth Rate (HGR) | C32: 0.02
B33: Value per share | C33: =Valuation_Model!E77 -> 0.52272978 | D33: =Market_currency -> HKD
B34: Probabilities | C34: 0.2
B36: Optimistic | E36: Business Story
B37: High Growth Period (HGP) | C37: =C18 -> 10
B38: High Growth Rate (HGR) | C38: 0.06
B39: Value per share | C39: =Valuation_Model!E75 -> 0.52690316 | D39: =Market_currency -> HKD
B40: Probabilities | C40: =1-C28-C34 -> 0.2
B42: Expected Value = | C42: =C27*C28+C33*C34+C39*C40 -> 0.52248172 | D42: =Market_currency -> HKD
B44: Extreme Scenarios
B45: Assumption
B46: High Growth Period (HGP) | C46: 15
B48: Devil's advocate | E48: Business Story
B49: High Growth Period (HGP) | C49: =C46 -> 15
B50: High Growth Rate (HGR) | C50: 0
B51: Value per share | C51: =Valuation_Model!E78 -> 0.52092521 | D51: =Market_currency -> HKD
B52: Probabilities | C52: 0.05
B54: Snowball Scenario | E54: Business Story
B55: High Growth Period (HGP) | C55: =C46 -> 15
B56: High Growth Rate (HGR) | C56: 0.1
B57: Value per share | C57: =Valuation_Model!E74 -> 0.54163392 | D57: =Market_currency -> HKD
B58: Probabilities | C58: 0.05
B60: Expected Value = | C60: =C51*C52+C57*C58+C42*(1-C52-C58) -> 0.5233615 | D60: =Market_currency -> HKD | E60: is assumed to be materialized in | F60: =Thesis!E20 -> 3
B62: Growth Classification
B63: Equity Value Driving Factors | E63: Note on Manual Adjustments
B64: High Growth Period (HGP) | C64: =C18 -> 10 | E64: Use general Scenarios' HGP assumption
B65: High Growth Rate (HGR) | C65: 0.046574871 | E65: Use Excel Goal Seek to find the HGR
B66: Equity Value per share | C66: =Valuation_Model!C18 -> 0.52541102 | D66: =Market_currency -> HKD | E66: Set to Expected Equity Value
B68: Type of Company | E68: Note on the logic
B69: Negative Growth | C69: =IF(C60<C22,"Y","N") -> N
B70: Low Growth | C70: =IF(C69="Y","N",IF(C65>8%,"N","Y")) -> Y | E70: >8% is Categorized as High Growth
B71: High Growth | C71: =IF(C65>8%,"Y","N") -> N
B72: Asset Play | C72: =IF(F72>50%,"Y","N") -> Y | E72: The Non-FCF Value is of the Expected Value, at | F72: =BS!D89/C60 -> 0.94193689
B74: Margin of Safety (MOS)
B75: Inputs
B76: Expected Holding Period | C76: =F60 -> 3
B77: Annual Dividend per share | C77: =Normalized_FCF!C90 -> 0.01 | D77: =Market_currency -> HKD
B79: Target Price Output
B80: @Target Annual Return | C80: =Thesis!C123 -> 0.25
B81: PV(Dividends) | C81: =PV(C80, C76, -C77, 0) -> 0.01952
B82: PV(Equity Value) | C82: =C60/(1+C80)^C76 -> 0.26796109
B83: Buy Below | C83: =C81+C82 -> 0.28748109 | D83: =Market_currency -> HKD | E83: at a MOS of | F83: =(1-C83/C60) -> 0.45070264
B85: Current Return Output
B86: @Market Price | C86: =Market_Price -> 1.35 | D86: =Market_currency -> HKD
B87: Annual Return | C87: =IRR(OFFSET($I$3, 0, 0, $C$76 + 1, 1)) -> -0.26037178
E89: Inputs Legend
E90: Font Color | F90: Fact or Verified Data
E91: Font Color | F91: Subjective Driving Factors
E92: Font Color | F92: Subjective Non-Driving Factors
