Workbook
Name Common_Shares: Thesis!$C$6
Name dividend_tax_rate: Normalized_FCF!$C$93
Name Equity_Cost: Thesis!$C$86
Name Exchange_Rate: Thesis!$C$16
Name Market_currency: Thesis!$C$13
Name Market_Price: Thesis!$C$12
Name Reporting_currency: Thesis!$C$25
Name scaling_factor: Data!$C$3
Name Terminal_Growth: Thesis!$C$92
Name valuation_method: Thesis!$E$21

Sheet Thesis
B1: Model last updated: | C1: 45780 | D1: CN | E1: Selected: | F1: Y
A2: Executive Summary
B4: Company Information
B5: Company Name | C5: 重庆啤酒
B6: Number of Shares: | C6: 483971198
B7: Report Interval: | C7: 6
B8: Update Required After: | C8: =EOMONTH(EDATE(BS!C1,C7+2),0) -> 45900
B10: Listing Information
B11: Symbol: | C11: 600132.SS
B12: Market Price: | C12: 55.15
B13: Market Currency | C13: CNY
B14: Capitalization: | C14: =Thesis!C12*Common_Shares/1000000 -> 26691.012 | D14: =IF(D11="","",Thesis!D12*Common_Shares/1000000)
B15: Forex Symbol: | C15: =IF(C25=C13,C13,C25&"/"&C13) -> CNY | D15: =IF(D11="","",IF(C25=D13,D13,C25&"/"&D13))
B16: Exchange Rate: | C16: 1
B18: Guidance Note: This model determines a target buy price consistent with defined investment criteria. It follows a logical progression: establishing current sustainable earnings, adjusting for financial structure, incorporating growth scenarios, and finally applying the investor’s required return.
B20: Valuation Overview
B21: Growth Classification: | C21: =IF(Scenarios!C69="Y",Scenarios!B69,"")&IF(Scenarios!C70="Y",Scenarios!B70,"")&IF(Scenarios!C71="Y",Scenarios!B71,"")&" "&IF(Scenarios!C72="Y",Scenarios!B72,"") -> Low Growth | D21: Valuation Method | E21: DCF
B22: Comp_Sector: | C22: CNS_03 | D22: =IF(valuation_method="DDM","DDM Terminal Value","")
B23: Business Model Risk Premium: | C23: N
B24: Management Risk Premium: | C24: N
B25: Reporting Currency: | C25: CNY | D25: =IF(D11="","",Market_currency&"/"&D13&":") | E25: =IF(D11="","",1/Exchange_Rate*D16)
B26: ="Expected Equity Value ("&C13&") :" -> Expected Equity Value (CNY) : | C26: =C132 -> 82.720031 | D26: Market Implied Annual Return: | E26: =Scenarios!C87 -> 0.17920704
B28: Valuation Outputs | C28: =C145&" ("&Market_currency&")" -> 600132.SS (CNY) | D28: =IF(D11="","",D145&" ("&D13&")") | E28: Holding Period | F28: 3
B29: Target Price | C29: =C149 -> 38.33886 | D29: =D149 | E29: Target return | F29: 0.337
B30: Entry Price | C30: =C157 -> 54.104774 | D30: =D157 | E30: Entry yield | F30: 0.187
B31: Sell Price | C31: =C165 -> 75.227039 | D31: =D165 | E31: Base equity cost | F31: 0.06
B32: Exit Price | C32: =C173 -> 69.902329 | D32: =D173 | E32: Benchmark yield | F32: 0.087
A34: Step 1: Establishing the Company’s Sustainable Earning Power (Calculating Normalized FCFE)
B36: Goal: To quantify the underlying FCFE the business consistently generates for its equity owners, stripping away temporary fluctuations or accounting choices.The FCFE/Market Cap yield gives a direct measure of this cash generation relative to the current market price.
B37: FCFE = (Normalized Operating EBIT + Depreciation & Amortization – Capital Expenditures) + Stable Non-Operating EBIT + Net Interest Income – Taxes – NCI’s Share of Profits – Working Capital Investment
B39: Key Components | C39: =scaling_factor -> 1
B40: • Normalized Operating EBIT: Earnings before interest and taxes from core business operations, adjusted to remove one-time or irregular items for a sustainable earnings base.
B41: Normalized Operating EBIT = | C41: =Normalized_FCF!C8 -> 2.9577151e+09 | D41: =Reporting_currency -> CNY
B43: • Depreciation & Amortization (D&A): Non-cash expenses added back to reflect cash generated from operations. • Capital Expenditures (Capex): Cash outflows required to maintain or expand operational assets
B44: D&A = | C44: =Normalized_FCF!C9 -> 575917865 | D44: =Reporting_currency -> CNY
B45: Capex = | C45: =Normalized_FCF!C10 -> -575917865 | D45: =Reporting_currency -> CNY
B47: • Stable Non-Operating EBIT: Consistent earnings from non-core assets, such as fixed-income investments, dividend-paying stocks, or rental properties.
B48: Stable Non-Operating EBIT = | C48: =Normalized_FCF!C11 -> 0 | D48: =Reporting_currency -> CNY
B50: • Net Interest Income: Interest income minus interest expense
B51: Operating Interest Income = | C51: =Normalized_FCF!C48 -> 39079015 | D51: =Reporting_currency -> CNY
B52: Interest Expense = | C52: =Normalized_FCF!C47 -> -7672861 | D52: =Reporting_currency -> CNY
B53: Net Interest Income = | C53: =Normalized_FCF!C12 -> 31406154 | D53: =Reporting_currency -> CNY
B55: • NCI’s Share of Profits: NCI represents the portion of a subsidiary’s equity not owned by the parent company.
B56: Est. NCI’s Share of Profits = | C56: =Normalized_FCF!C15 -> -1.418797e+08 | D56: =Reporting_currency -> CNY
B58: • Taxes: Tax = (Normalized Operating EBIT + Stable Non-Operating EBIT + Interest Income – Interest Expense) × Tax Rate
B59: Taxes = | C59: =Normalized_FCF!C14 -> -7.4728032e+08 | D59: =Reporting_currency -> CNY
B61: • Working Capital Investment (WCInv): WCInv is only included if it materially distorts FCFE.
B62: WCInv = | C62: =Normalized_FCF!C17 -> 0 | D62: =Reporting_currency -> CNY
B64: Note on Net Borrowing: In theory, principal repayments are accounted for through Net Borrowing. However, this model aims to avoid explicitly forecasting debt issuance or repayments. Instead, principal repayments are reflected in the Equity Value adjustment through interest-bearing debt.
B65: Insight: This step ensures a comprehensive measure of cash flow by incorporating both operating and stable non-operating sources while accounting for taxes and reinvestment needs.
B67: Latest FCFE = | C67: =Normalized_FCF!G19 -> 2.3232788e+09 | D67: =Reporting_currency -> CNY
B68: Normalized FCFE = | C68: =Normalized_FCF!C19 -> 2.0999612e+09 | D68: =Reporting_currency -> CNY
B69: Normalized FCFE/Market Cap = | C69: =Normalized_FCF!C126 -> 0.07867672
B70: After tax Dividend/Market Cap = | C70: =Normalized_FCF!C94 -> 0.039165911 | E70: Payout Ratio: | F70: =Normalized_FCF!C92 -> 0.55312015
B72: DuPont Analysis | C72: Normalized | D72: Latest
B73: ROE = | C73: =Normalized_FCF!C121 -> 1.2182305 | D73: =Normalized_FCF!G121 -> 1.2799741
B74: =Normalized_FCF!B118 -> Pre-tax Profit/Sales | C74: =Normalized_FCF!C118 -> 0.21117896 | D74: =Normalized_FCF!G118 -> 0.21445579
B75: =Normalized_FCF!B119 -> Sales/Total Assets | C75: =Normalized_FCF!C119 -> 1.2904821 | D75: =Normalized_FCF!G119 -> 1.33517
B76: =Normalized_FCF!B120 -> Total Assets/Equity | C76: =Normalized_FCF!C120 -> 4.4701989 | D76: =Normalized_FCF!G120 -> 4.4701989
A78: Step 2: The No-Growth Baseline (Calculating Stable Income Value)
B80: Goal: To determine the intrinsic value of the company’s equity if the Normalized FCFE (calculated in Step 1) were to remain constant perpetually, with zero future growth. This establishes a baseline value derived solely from the current sustainable earnings power.
B81: Stable Income Value = Normalized FCFE / (Cost of Equity – Terminal Growth Rate)
B83: Key Components
B84: Base Cost of Equity | C84: =F31 -> 0.06
B85: Risk Premium | C85: =IF(C23="Y",1%,0)+IF(C24="Y",1%,0) -> 0
B86: Cost of Equity = | C86: =F31+C85 -> 0.06
B88: Note:
B89: Cost of Equity: Cost of Equity reflects the company’s risk profile and represents the minimum return the investor requires for taking on the general risk of owning this type of business, while the target annual return serves as the investor’s hurdle rate.
B90: Terminal Growth Rate: Setting g=0% is a conservative assumption, valuing the company based only on its current demonstrated earning power without relying on potentially optimistic future growth projections.
B92: Terminal Growth Rate (g) = | C92: 0
B93: No Growth SIV Per Share = | C93: =DCF!C6*scaling_factor*Exchange_Rate/Common_Shares -> 72.317018 | D93: =Market_currency -> CNY
A95: Step 3: Adjusting for Financial Structure (Calculating No Growth Equity Value)
B97: Goal: To refine the Stable Income Value (SIV) by incorporating the company’s balance sheet structure.
B98: Equity Value = Stable Income Value – Total Interest-Bearing Debt + Non-Operating Cash + Other Non-Operating Assets
B100: Key Components
B101: Note on debt: The total interest-bearing debt captures the principal repayments. Ideally, this amount should be discounted based on the repayment schedule. However, for simplicity and conservatism, this model uses the book value of the total interest-bearing debt.
B102: Total Interest-Bearing Debt = | C102: =DCF!C7 -> 1.235217e+08 | D102: =Reporting_currency -> CNY
B103: Total Interest-Bearing Debt per share = | C103: =C102*scaling_factor*Exchange_Rate/Common_Shares -> 0.25522532 | D103: =Market_currency -> CNY
B104: Debt to Equity Ratio = | C104: =IF(BS!G31/BS!G27>300%,"nm",BS!G31/BS!G27) -> 0.050341857
B105: Debt to EBIT Ratio = | C105: =IF(BS!C50>30,"nm",BS!C50) -> 0.041762543
B107: • Non-Operating Cash: Excess cash not required for operations
B108: Total Cash = | C108: =BS!C66 -> 1.0816591e+09 | D108: =Reporting_currency -> CNY
B109: Est. Non-Operating Cash = | C109: =DCF!C8 -> 51803896 | D109: =Reporting_currency -> CNY
B110: Est. Non-Operating Cash per share = | C110: =C109*scaling_factor*Exchange_Rate/Common_Shares -> 0.10703921 | D110: =Market_currency -> CNY
B112: • Other Non-Operating Assets: Assets not contributing to FCFE (e.g., non-income-generating investments or properties)
B113: Other Non-Operating Assets = | C113: =DCF!C9 -> 29558001 | D113: =Reporting_currency -> CNY
B114: Other Non-Operating Assets per share = | C114: =C113*scaling_factor*Exchange_Rate/Common_Shares -> 0.061073884 | D114: =Market_currency -> CNY
B116: Insight: The No Growth Equity Value per share represents an estimate of the company’s intrinsic worth based on its current sustainable operations and net financial position, before factoring in any future growth potential. It serves as a fundamentally anchored valuation baseline.
B118: No Growth Equity Value per share = | C118: =IF(valuation_method="DCF",DCF!C12,DDM!C7) -> 72.229906 | D118: =Market_currency -> CNY
B119: Est. Realizable Value | C119: =BS!D47 -> -13.312996 | D119: =Market_currency -> CNY
A121: Step 4: Incorporating Future Potential & Risk (Scenario Analysis)
B123: Goal: To estimate the company’s intrinsic value by considering plausible future scenarios beyond the static no-growth assumption. Based on fundamental research, each scenario defines high growth periods (HGP), high growth rates (HGR), and its probability.
B125: Scenarios | C125: HGR | D125: HGP | E125: EV per share | F125: Probabilities
B126: =DCF!B74 -> Snowball Scenario | C126: =DCF!C74 -> 0.1 | D126: =DCF!D74 -> 15 | E126: =ROUND(IF(valuation_method="DCF",DCF!E74,DDM!E69),2)&" "&Market_currency -> 121.77 CNY | F126: =DCF!F74 -> 0.05
B127: =DCF!B75 -> Optimistic | C127: =DCF!C75 -> 0.06 | D127: =DCF!D75 -> 10 | E127: =ROUND(IF(valuation_method="DCF",DCF!E75,DDM!E70),2)&" "&Market_currency -> 86.11 CNY | F127: =DCF!F75 -> 0.18
B128: =DCF!B76 -> Base | C128: =DCF!C76 -> 0.04 | D128: =DCF!D76 -> 10 | E128: =ROUND(IF(valuation_method="DCF",DCF!E76,DDM!E71),2)&" "&Market_currency -> 81.04 CNY | F128: =DCF!F76 -> 0.54
B129: =DCF!B77 -> Pessimistic | C129: =DCF!C77 -> 0.02 | D129: =DCF!D77 -> 10 | E129: =ROUND(IF(valuation_method="DCF",DCF!E77,DDM!E72),2)&" "&Market_currency -> 76.43 CNY | F129: =DCF!F77 -> 0.18
B130: =DCF!B78 -> Devil's advocate | C130: =DCF!C78 -> 0 | D130: =DCF!D78 -> 15 | E130: =ROUND(IF(valuation_method="DCF",DCF!E78,DDM!E73),2)&" "&Market_currency -> 72.23 CNY | F130: =DCF!F78 -> 0.05
B132: Expected Equity Value = | C132: =Scenarios!C60 -> 82.720031 | D132: =Market_currency -> CNY
B134: Insight: Significant market volatility is analyzed as an indicator of the range of market-perceived outcomes, including extremes that define boundaries for scenarios like "Snowball" or "Devil’s Advocate." Scenario Analysis then filters these using fundamental reasoning to evaluate their likelihood.
...

Sheet Data
B1: =Thesis!C25 -> CNY | C1: 45657 | D1: =EOMONTH(EDATE(C1,-12),0) -> 45291 | E1: =EOMONTH(EDATE(D1,-12),0) -> 44926 | F1: =EOMONTH(EDATE(E1,-12),0) -> 44561 | G1: =EOMONTH(EDATE(F1,-12),0) -> 44196 | H1: =EOMONTH(EDATE(G1,-12),0) -> 43830 | I1: =EOMONTH(EDATE(H1,-12),0) -> 43465 | J1: =EOMONTH(EDATE(I1,-12),0) -> 43100 | K1: =EOMONTH(EDATE(J1,-12),0) -> 42735 | ... M1: =EOMONTH(EDATE(L1,-12),0) -> 42004
B2: Data (Dirty)
B3: Income Statement | C3: 1
B4: Sales | C4: 14644597842 | D4: 14814836410 | E4: 14039040539 | F4: 13119310688 | G4: 10941631163 | H4: 3581923735 | I4: 3467335930 | J4: 3175519522 | K4: 3195921516 | L4: 3323745278
B5: COGS | C5: 8483123346 | D5: 8491525016 | E5: 7873287284 | F5: 7328418046 | G5: 6166079008 | H5: 2359127300 | I5: 2362728713 | J5: 2190920673 | K5: 2209433704 | L5: 2369740058
B6: OPEX | C6: =516942154+C7 -> 3029595871 | D6: =494670738+D7 -> 3027292571 | E6: =534570349+E7 -> 2860787576 | F6: =516877145+F7 -> 2729771806 | G6: =684104925+G7 -> 2988418106 | H6: =161996928+H7 -> 654203552 | I6: =153940810+I7 -> 609225228 | J6: =155718230+J7 -> 620936767 | K6: =183628555+K7 -> 629182097 | L6: =232657686+L7 -> 722526234
B7: Incl. Selling Expenses | C7: 2512653717 | D7: 2532621833 | E7: 2326217227 | F7: 2212894661 | G7: 2304313181 | H7: 492206624 | I7: 455284418 | J7: 465218537 | K7: 445553542 | L7: 489868548
B8: R&D | C8: 22666046 | D8: 26232056 | E8: 110747936 | F8: 163151285 | G8: 84212617 | H8: 0 | I8: 0
B9: Share of JV or associate Results
B10: Dividend or Interests from FA
B11: Investment property
B12: Interest Expense | C12: 7672861 | D12: 5921669 | E12: 3696844 | F12: 14186775 | G12: 35823675 | H12: 10770646 | I12: 12333775
B13: Interest Income | C13: 41044772 | D13: 71308016 | E13: 65718589 | F13: 36050786 | G13: 44443082 | H13: 8582394 | I13: 6609967
B14: Income Tax Paid | C14: 670547120 | D14: 664121997 | E14: 711879179 | F14: 541923819 | G14: 378467716 | H14: 98780687 | I14: 61018006 | J14: 18873927 | K14: 16833271 | L14: 42979625
B15: Reported Net Income | C15: 2249380492 | D15: 2711568555 | E15: 2586899641 | F15: 2399156196 | G15: 1752317096 | H15: 728536930 | I15: 421259471 | J15: 326122335 | K15: 139941169 | L15: -153552021
B16: Non-controling Interests | C16: 146792828
B18: Cash Flow Statement
B19: D&A | C19: 575917865 | D19: 514817738 | E19: 504410326 | F19: 451827434 | G19: 413794059 | H19: 174070610 | I19: 173632673
B20: CAPX
B21: WCInv
B22: CFO | C22: 2542046725 | D22: 3096948817 | E22: 3752648259 | F22: 3564787113 | G22: 3689730876 | H22: 705779861 | I22: 744379875 | J22: 820031927 | K22: 569431362 | L22: 448312451
B23: CFI | C23: -633430356 | D23: -1050978857 | E23: -388086486 | F23: -1151748524 | G23: -2804885087 | H23: -22429423 | I23: -17918687 | J23: 6460189 | K23: -71411814 | L23: -100881139
B24: CFF | C24: -3527746522 | D24: -2742702995 | E24: -2133485949 | F24: -2013680615 | G24: -587625771 | H24: -398002277 | I24: -448634809 | J24: -405497889 | K24: -449187720 | L24: -252880739
B25: ="Dividend per share ("&Market_currency&")" -> Dividend per share (CNY) | C25: =(9+15)/10 -> 2.4
B27: Balance Sheet | C27: Latest Asset Value
B28: ST AR | C28: =BS!C4 -> 91009310 | D28: 64628136 | E28: 65511539 | F28: 109244674 | G28: 114510542 | H28: 58261577 | I28: 67050347 | J28: 26764864 | K28: 51244805 | L28: 61946543
B29: ST Inventory | C29: =BS!C6 -> 2.1858356e+09 | D29: 2100354952 | E29: 2166477563 | F29: 1886751987 | G29: 1420570476 | H29: 364381375 | I29: 336913911 | J29: 631313453 | K29: 825981328 | L29: 1074501976
B30: Total Liabilities | C30: =BS!C33+BS!C42 -> 8.5146816e+09 | D30: 8734763046 | E30: 8874519390 | F30: 8404513904 | G30: 8026536570 | H30: 2003002194 | I30: 2135750535 | J30: 2340923121 | K30: 2123382866 | L30: 2502070463
B31: Total Equity | C31: =BS!G27 -> 2.4536581e+09 | D31: 3652148548 | E31: 3623022779 | F31: 3128295240 | G31: 1568836504 | H31: 1511351330 | I31: 1161882585 | J31: 1165260073 | K31: 1242276954 | L31: 1219123567
B32: Non-common Interest | C32: =BS!G28 -> 1.2684378e+09 | D32: 1511947928 | E32: 1566866997 | F32: 1373750136 | G32: 983547315 | H32: 92634421 | I32: 16868025 | J32: 1596604 | K32: 12325253 | L32: 77762305
B34: IS & CF Statements (Clean)
B35: Income Statement
B36: Sales | C36: =IF(C$4="","",C4) -> 14644597842 | D36: =IF(D$4="","",D4) -> 14814836410 | E36: =IF(E$4="","",E4) -> 14039040539 | F36: =IF(F$4="","",F4) -> 13119310688 | G36: =IF(G$4="","",G4) -> 10941631163 | H36: =IF(H$4="","",H4) -> 3581923735 | I36: =IF(I$4="","",I4) -> 3467335930 | J36: =IF(J$4="","",J4) -> 3175519522 | ... M36: =IF(M$4="","",M4)
B37: COGS | C37: =IF(C$4="","",-C5) -> -8483123346 | D37: =IF(D$4="","",-D5) -> -8491525016 | E37: =IF(E$4="","",-E5) -> -7873287284 | F37: =IF(F$4="","",-F5) -> -7328418046 | G37: =IF(G$4="","",-G5) -> -6166079008 | H37: =IF(H$4="","",-H5) -> -2359127300 | I37: =IF(I$4="","",-I5) -> -2362728713 | J37: =IF(J$4="","",-J5) -> -2190920673 | ... M37: =IF(M$4="","",-M5)
B38: Gross Margin | C38: =IF(C36="","",C36+C37) -> 6161474496 | D38: =IF(D36="","",D36+D37) -> 6323311394 | E38: =IF(E36="","",E36+E37) -> 6165753255 | F38: =IF(F36="","",F36+F37) -> 5790892642 | G38: =IF(G36="","",G36+G37) -> 4775552155 | H38: =IF(H36="","",H36+H37) -> 1222796435 | I38: =IF(I36="","",I36+I37) -> 1104607217 | J38: =IF(J36="","",J36+J37) -> 984598849 | ... M38: =IF(M36="","",M36+M37)
B39: OPEX | C39: =IF(C$4="","",-C6) -> -3029595871 | D39: =IF(D$4="","",-D6) -> -3027292571 | E39: =IF(E$4="","",-E6) -> -2860787576 | F39: =IF(F$4="","",-F6) -> -2729771806 | G39: =IF(G$4="","",-G6) -> -2988418106 | H39: =IF(H$4="","",-H6) -> -654203552 | I39: =IF(I$4="","",-I6) -> -609225228 | J39: =IF(J$4="","",-J6) -> -620936767 | ... M39: =IF(M$4="","",-M6)
B40: Incl. Selling Expenses | C40: =IF(C$4="","",-C7) -> -2512653717 | D40: =IF(D$4="","",-D7) -> -2532621833 | E40: =IF(E$4="","",-E7) -> -2326217227 | F40: =IF(F$4="","",-F7) -> -2212894661 | G40: =IF(G$4="","",-G7) -> -2304313181 | H40: =IF(H$4="","",-H7) -> -492206624 | I40: =IF(I$4="","",-I7) -> -455284418 | J40: =IF(J$4="","",-J7) -> -465218537 | ... M40: =IF(M$4="","",-M7)
B41: Incl. Other Opex | C41: =IF(C$4="","",C39-C40) -> -516942154 | D41: =IF(D$4="","",D39-D40) -> -494670738 | E41: =IF(E$4="","",E39-E40) -> -534570349 | F41: =IF(F$4="","",F39-F40) -> -516877145 | G41: =IF(G$4="","",G39-G40) -> -684104925 | H41: =IF(H$4="","",H39-H40) -> -161996928 | I41: =IF(I$4="","",I39-I40) -> -153940810 | J41: =IF(J$4="","",J39-J40) -> -155718230 | ... M41: =IF(M$4="","",M39-M40)
B42: R&D | C42: =IF(C$4="","",-C8) -> -22666046 | D42: =IF(D$4="","",-D8) -> -26232056 | E42: =IF(E$4="","",-E8) -> -110747936 | F42: =IF(F$4="","",-F8) -> -163151285 | G42: =IF(G$4="","",-G8) -> -84212617 | H42: =IF(H$4="","",-H8) -> 0 | I42: =IF(I$4="","",-I8) -> 0 | J42: =IF(J$4="","",-J8) -> 0 | ... M42: =IF(M$4="","",-M8)
B43: Operating EBIT | C43: =IF(C$4="","",C38+C39+C42) -> 3109212579 | D43: =IF(D$4="","",D38+D39+D42) -> 3269786767 | E43: =IF(E$4="","",E38+E39+E42) -> 3194217743 | F43: =IF(F$4="","",F38+F39+F42) -> 2897969551 | G43: =IF(G$4="","",G38+G39+G42) -> 1702921432 | H43: =IF(H$4="","",H38+H39+H42) -> 568592883 | I43: =IF(I$4="","",I38+I39+I42) -> 495381989 | J43: =IF(J$4="","",J38+J39+J42) -> 363662082 | ... M43: =IF(M$4="","",M38+M39+M42)
B44: Non-operating EBIT | C44: =IF(C$4="","",C47-C46-C45-C43) -> -222656878 | D44: =IF(D$4="","",D47-D46-D45-D43) -> 40517438 | E44: =IF(E$4="","",E47-E46-E45-E43) -> 42539332 | F44: =IF(F$4="","",F47-F46-F45-F43) -> 21246453 | G44: =IF(G$4="","",G47-G46-G45-G43) -> 419243973 | H44: =IF(H$4="","",H47-H46-H45-H43) -> 260912986 | I44: =IF(I$4="","",I47-I46-I45-I43) -> -7380704 | J44: =IF(J$4="","",J47-J46-J45-J43) -> -18665820 | ... M44: =IF(M$4="","",M47-M46-M45-M43)
B45: Net Interest Income | C45: =IF(C$4="","",C51+C52) -> 33371911 | D45: =IF(D$4="","",D51+D52) -> 65386347 | E45: =IF(E$4="","",E51+E52) -> 62021745 | F45: =IF(F$4="","",F51+F52) -> 21864011 | G45: =IF(G$4="","",G51+G52) -> 8619407 | H45: =IF(H$4="","",H51+H52) -> -2188252 | I45: =IF(I$4="","",I51+I52) -> -5723808 | J45: =IF(J$4="","",J51+J52) -> 0 | ... M45: =IF(M$4="","",M51+M52)
B46: Income Tax Paid | C46: =IF(C$4="","",-C14) -> -670547120 | D46: =IF(D$4="","",-D14) -> -664121997 | E46: =IF(E$4="","",-E14) -> -711879179 | F46: =IF(F$4="","",-F14) -> -541923819 | G46: =IF(G$4="","",-G14) -> -378467716 | H46: =IF(H$4="","",-H14) -> -98780687 | I46: =IF(I$4="","",-I14) -> -61018006 | J46: =IF(J$4="","",-J14) -> -18873927 | ... M46: =IF(M$4="","",-M14)
B47: Reported Net Income | C47: =IF(C$4="","",C15) -> 2249380492 | D47: =IF(D$4="","",D15) -> 2711568555 | E47: =IF(E$4="","",E15) -> 2586899641 | F47: =IF(F$4="","",F15) -> 2399156196 | G47: =IF(G$4="","",G15) -> 1752317096 | H47: =IF(H$4="","",H15) -> 728536930 | I47: =IF(I$4="","",I15) -> 421259471 | J47: =IF(J$4="","",J15) -> 326122335 | ... M47: =IF(M$4="","",M15)
B48: Non-controling Interests | C48: =IF(C$4="","",MIN(-C16,0)) -> -146792828 | D48: =IF(D$4="","",MIN(-D16,0)) -> 0 | E48: =IF(E$4="","",MIN(-E16,0)) -> 0 | F48: =IF(F$4="","",MIN(-F16,0)) -> 0 | G48: =IF(G$4="","",MIN(-G16,0)) -> 0 | H48: =IF(H$4="","",MIN(-H16,0)) -> 0 | I48: =IF(I$4="","",MIN(-I16,0)) -> 0 | J48: =IF(J$4="","",MIN(-J16,0)) -> 0 | ... M48: =IF(M$4="","",MIN(-M16,0))
B50: Net Interest Income
B51: Interest Expense | C51: =IF(C$4="","",-C12) -> -7672861 | D51: =IF(D$4="","",-D12) -> -5921669 | E51: =IF(E$4="","",-E12) -> -3696844 | F51: =IF(F$4="","",-F12) -> -14186775 | G51: =IF(G$4="","",-G12) -> -35823675 | H51: =IF(H$4="","",-H12) -> -10770646 | I51: =IF(I$4="","",-I12) -> -12333775 | J51: =IF(J$4="","",-J12) -> 0 | ... M51: =IF(M$4="","",-M12)
B52: Interest Income | C52: =IF(C$4="","",C13) -> 41044772 | D52: =IF(D$4="","",D13) -> 71308016 | E52: =IF(E$4="","",E13) -> 65718589 | F52: =IF(F$4="","",F13) -> 36050786 | G52: =IF(G$4="","",G13) -> 44443082 | H52: =IF(H$4="","",H13) -> 8582394 | I52: =IF(I$4="","",I13) -> 6609967 | J52: =IF(J$4="","",J13) -> 0 | ... M52: =IF(M$4="","",M13)
B54: Non-operating EBIT
B55: Share of JV or associate Results | C55: =IF(C$4="","",C9) -> 0 | D55: =IF(D$4="","",D9) -> 0 | E55: =IF(E$4="","",E9) -> 0 | F55: =IF(F$4="","",F9) -> 0 | G55: =IF(G$4="","",G9) -> 0 | H55: =IF(H$4="","",H9) -> 0 | I55: =IF(I$4="","",I9) -> 0 | J55: =IF(J$4="","",J9) -> 0 | ... M55: =IF(M$4="","",M9)
B56: Dividend or Interests from FA | C56: =IF(C$4="","",C10) -> 0 | D56: =IF(D$4="","",D10) -> 0 | E56: =IF(E$4="","",E10) -> 0 | F56: =IF(F$4="","",F10) -> 0 | G56: =IF(G$4="","",G10) -> 0 | H56: =IF(H$4="","",H10) -> 0 | I56: =IF(I$4="","",I10) -> 0 | J56: =IF(J$4="","",J10) -> 0 | ... M56: =IF(M$4="","",M10)
B57: Investment property | C57: =IF(C$4="","",C11) -> 0 | D57: =IF(D$4="","",D11) -> 0 | E57: =IF(E$4="","",E11) -> 0 | F57: =IF(F$4="","",F11) -> 0 | G57: =IF(G$4="","",G11) -> 0 | H57: =IF(H$4="","",H11) -> 0 | I57: =IF(I$4="","",I11) -> 0 | J57: =IF(J$4="","",J11) -> 0 | ... M57: =IF(M$4="","",M11)
B58: Other Non-operating Income | C58: =IF(C$4="","",C44-C55-C56-C57) -> -222656878 | D58: =IF(D$4="","",D44-D55-D56-D57) -> 40517438 | E58: =IF(E$4="","",E44-E55-E56-E57) -> 42539332 | F58: =IF(F$4="","",F44-F55-F56-F57) -> 21246453 | G58: =IF(G$4="","",G44-G55-G56-G57) -> 419243973 | H58: =IF(H$4="","",H44-H55-H56-H57) -> 260912986 | I58: =IF(I$4="","",I44-I55-I56-I57) -> -7380704 | J58: =IF(J$4="","",J44-J55-J56-J57) -> -18665820 | ... M58: =IF(M$4="","",M44-M55-M56-M57)
B60: Cash Flow Statement
B61: D&A | C61: =IF(C$4="","",-C19) -> -575917865 | D61: =IF(D$4="","",-D19) -> -514817738 | E61: =IF(E$4="","",-E19) -> -504410326 | F61: =IF(F$4="","",-F19) -> -451827434 | G61: =IF(G$4="","",-G19) -> -413794059 | H61: =IF(H$4="","",-H19) -> -174070610 | I61: =IF(I$4="","",-I19) -> -173632673 | J61: =IF(J$4="","",-J19) -> 0 | ... M61: =IF(M$4="","",-M19)
B62: CAPX | C62: =IF(C$4="","",IF(C20=0,C61,-C20)) -> -575917865 | D62: =IF(D$4="","",IF(D20=0,D61,-D20)) -> -514817738 | E62: =IF(E$4="","",IF(E20=0,E61,-E20)) -> -504410326 | F62: =IF(F$4="","",IF(F20=0,F61,-F20)) -> -451827434 | G62: =IF(G$4="","",IF(G20=0,G61,-G20)) -> -413794059 | H62: =IF(H$4="","",IF(H20=0,H61,-H20)) -> -174070610 | I62: =IF(I$4="","",IF(I20=0,I61,-I20)) -> -173632673 | J62: =IF(J$4="","",IF(J20=0,J61,-J20)) -> 0 | ... M62: =IF(M$4="","",IF(M20=0,M61,-M20))
B63: WCInv | C63: =IF(C$4="","",-C21) -> 0 | D63: =IF(D$4="","",-D21) -> 0 | E63: =IF(E$4="","",-E21) -> 0 | F63: =IF(F$4="","",-F21) -> 0 | G63: =IF(G$4="","",-G21) -> 0 | H63: =IF(H$4="","",-H21) -> 0 | I63: =IF(I$4="","",-I21) -> 0 | J63: =IF(J$4="","",-J21) -> 0 | ... M63: =IF(M$4="","",-M21)
B64: Net Change in Cash | C64: =IF(C$4="","",C22+C23+C24) -> -1619130153 | D64: =IF(D$4="","",D22+D23+D24) -> -696733035 | E64: =IF(E$4="","",E22+E23+E24) -> 1231075824 | F64: =IF(F$4="","",F22+F23+F24) -> 399357974 | G64: =IF(G$4="","",G22+G23+G24) -> 297220018 | H64: =IF(H$4="","",H22+H23+H24) -> 285348161 | I64: =IF(I$4="","",I22+I23+I24) -> 277826379 | J64: =IF(J$4="","",J22+J23+J24) -> 420994227 | ... M64: =IF(M$4="","",M22+M23+M24)
B65: Dividend per share | C65: =IF(C$4="","",C25) -> 2.4 | D65: =IF(D$4="","",D25) -> 0 | E65: =IF(E$4="","",E25) -> 0 | F65: =IF(F$4="","",F25) -> 0 | G65: =IF(G$4="","",G25) -> 0 | H65: =IF(H$4="","",H25) -> 0 | I65: =IF(I$4="","",I25) -> 0 | J65: =IF(J$4="","",J25) -> 0 | ... M65: =IF(M$4="","",M25)
B67: YoY %
B68: =B36 -> Sales | C68: =IF(D$36="","",C36/D36-1) -> -0.011491087 | D68: =IF(E$36="","",D36/E36-1) -> 0.055259893 | E68: =IF(F$36="","",E36/F36-1) -> 0.070105044 | F68: =IF(G$36="","",F36/G36-1) -> 0.19902695 | G68: =IF(H$36="","",G36/H36-1) -> 2.0546801 | H68: =IF(I$36="","",H36/I36-1) -> 0.033047794 | I68: =IF(J$36="","",I36/J36-1) -> 0.091895643 | J68: =IF(K$36="","",J36/K36-1) -> -0.0063837594 | ... M68: =IF(N$36="","",M36/N36-1)
B69: Gross Margin | C69: =IF(D$36="","",C38/D38-1) -> -0.025593694 | D69: =IF(E$36="","",D38/E38-1) -> 0.025553754 | E69: =IF(F$36="","",E38/F38-1) -> 0.064732786 | F69: =IF(G$36="","",F38/G38-1) -> 0.21261217 | G69: =IF(H$36="","",G38/H38-1) -> 2.9054351 | H69: =IF(I$36="","",H38/I38-1) -> 0.1069966 | I69: =IF(J$36="","",I38/J38-1) -> 0.12188555 | J69: =IF(K$36="","",J38/K38-1) -> -0.0019148366 | ... M69: =IF(N$36="","",M38/N38-1)
B70: =B43 -> Operating EBIT | C70: =IF(D$36="","",C43/D43-1) -> -0.049108459 | D70: =IF(E$36="","",D43/E43-1) -> 0.023658069 | E70: =IF(F$36="","",E43/F43-1) -> 0.10222612 | F70: =IF(G$36="","",F43/G43-1) -> 0.70176351 | G70: =IF(H$36="","",G43/H43-1) -> 1.9949749 | H70: =IF(I$36="","",H43/I43-1) -> 0.14778675 | I70: =IF(J$36="","",I43/J43-1) -> 0.36220413 | J70: =IF(K$36="","",J43/K43-1) -> 0.017789715 | ... M70: =IF(N$36="","",M43/N43-1)
B71: Non-operating EBIT | C71: =IF(D$36="","",C44/D44-1) -> -6.4953346 | D71: =IF(E$36="","",D44/E44-1) -> -0.047529989 | E71: =IF(F$36="","",E44/F44-1) -> 1.0021851 | F71: =IF(G$36="","",F44/G44-1) -> -0.94932198 | G71: =IF(H$36="","",G44/H44-1) -> 0.60683444 | H71: =IF(I$36="","",H44/I44-1) -> -36.350691 | I71: =IF(J$36="","",I44/J44-1) -> -0.60458721 | J71: =IF(K$36="","",J44/K44-1) -> -0.90691816 | ... M71: =IF(N$36="","",M44/N44-1)
B72: =B47 -> Reported Net Income | C72: =IF(D$36="","",C47/D47-1) -> -0.17045044 | D72: =IF(E$36="","",D47/E47-1) -> 0.048192405 | E72: =IF(F$36="","",E47/F47-1) -> 0.078253948 | F72: =IF(G$36="","",F47/G47-1) -> 0.36913359 | G72: =IF(H$36="","",G47/H47-1) -> 1.405255 | H72: =IF(I$36="","",H47/I47-1) -> 0.72942564 | I72: =IF(J$36="","",I47/J47-1) -> 0.29172223 | J72: =IF(K$36="","",J47/K47-1) -> 1.3304245 | ... M72: =IF(N$36="","",M47/N47-1)
B74: Balance Sheet (Clean)
B75: Balance Sheet
B76: Total Assets | C76: =IF(C$4="","",C79+C80) -> 1.096834e+10 | D76: =IF(D$4="","",D79+D80) -> 12386911594 | E76: =IF(E$4="","",E79+E80) -> 12497542169 | F76: =IF(F$4="","",F79+F80) -> 11532809144 | G76: =IF(G$4="","",G79+G80) -> 9595373074 | H76: =IF(H$4="","",H79+H80) -> 3514353524 | I76: =IF(I$4="","",I79+I80) -> 3297633120 | J76: =IF(J$4="","",J79+J80) -> 3506183194 | ... M76: =IF(M$4="","",M79+M80)
B77: Incl. ST AR | C77: =IF(C$4="","",C28) -> 91009310 | D77: =IF(D$4="","",D28) -> 64628136 | E77: =IF(E$4="","",E28) -> 65511539 | F77: =IF(F$4="","",F28) -> 109244674 | G77: =IF(G$4="","",G28) -> 114510542 | H77: =IF(H$4="","",H28) -> 58261577
B78: Incl. ST Inventory | C78: =IF(C$4="","",C29) -> 2.1858356e+09 | D78: =IF(D$4="","",D29) -> 2100354952 | E78: =IF(E$4="","",E29) -> 2166477563 | F78: =IF(F$4="","",F29) -> 1886751987 | G78: =IF(G$4="","",G29) -> 1420570476 | H78: =IF(H$4="","",H29) -> 364381375
B79: Total Liabilities | C79: =IF(C$4="","",C30) -> 8.5146816e+09 | D79: =IF(D$4="","",D30) -> 8734763046 | E79: =IF(E$4="","",E30) -> 8874519390 | F79: =IF(F$4="","",F30) -> 8404513904 | G79: =IF(G$4="","",G30) -> 8026536570 | H79: =IF(H$4="","",H30) -> 2003002194 | I79: =IF(I$4="","",I30) -> 2135750535 | J79: =IF(J$4="","",J30) -> 2340923121 | ... M79: =IF(M$4="","",M30)
B80: Total Equity | C80: =IF(C$4="","",C31) -> 2.4536581e+09 | D80: =IF(D$4="","",D31) -> 3652148548 | E80: =IF(E$4="","",E31) -> 3623022779 | F80: =IF(F$4="","",F31) -> 3128295240 | G80: =IF(G$4="","",G31) -> 1568836504 | H80: =IF(H$4="","",H31) -> 1511351330 | I80: =IF(I$4="","",I31) -> 1161882585 | J80: =IF(J$4="","",J31) -> 1165260073 | ... M80: =IF(M$4="","",M31)

Sheet BS
B1: Most Recent Quarter | C1: 45657 | F1: =IF(MONTH(C1)=MONTH(Normalized_FCF!G1),"FY","Quarter")&" Report" -> FY Report | H1: =scaling_factor -> 1
B2: Lastest Balance Sheet
B3: ST Operating Assets | C3: Book | D3: Valued @ | F3: ST Non-Operating Assets | G3: Book | H3: Valued @
B4: ST AR | C4: =63423634.85+27585675 -> 91009310 | D4: 0.6 | F4: Cash and cash equivalents | G4: 1.0816591e+09 | H4: 0.9
B5: Operating ST Financial Assets | C5: 0 | D5: 0.6 | F5: Restricted cash | G5: 0 | H5: 0.7
B6: Inventory | C6: 2.1858356e+09 | D6: 0.5 | F6: Securities with stable income | G6: 0 | H6: 0.6
B7: Properties held for sale | C7: 0 | D7: 0.6 | F7: Other Securities | G7: 22482126 | H7: 0.6
B8: Properties held for income | C8: 0 | D8: 0.6 | F8: Properties with stable income | G8: 0 | H8: 0.6
B9: Prepayments and Contract Assets | C9: 28013000 | D9: 0.1 | F9: Other Properties | G9: 0 | H9: 0.6
B10: ST DTA | C10: 0 | D10: 0.9
B11: Other ST Assets | C11: 2.7003836e+08 | D11: 0.05
B12: Operating ST Assets | C12: =SUM(C4:C11) -> 2.5748963e+09 | D12: =C4*D4+C5*D5+C9*D9+C6*D6+C8*D8+C7*D7+C10*D10+C11*D11 -> 1.1638266e+09 | F12: Non-Operating ST Assets | G12: =SUM(G4:G9) -> 1.1041412e+09 | H12: =G4*H4+G5*H5+G6*H6+G7*H7+G8*H8+G9*H9 -> 9.8698244e+08
B14: LT Operating Assets | C14: Book | D14: Valued @ | F14: LT Non-Operating Assets | G14: Book | H14: Valued @
B15: LT AR and Prepayments | C15: 0 | D15: 0.4 | F15: LT Depositis | G15: 0 | H15: 0.8
B16: Operating LT Financial Assets | C16: 0 | D16: 0.5 | F16: Securities with stable income | G16: 0 | H16: 0.6
B17: Properties held for sale | C17: 0 | D17: 0.6 | F17: Other Securities | G17: 0 | H17: 0.6
B18: Properties held for income | C18: 0 | D18: 0.6 | F18: JV or associate with stable income | G18: 0 | H18: 0.1
B19: PP&E & Right of Use Assets | C19: =4755026247.47+159772560.73+160044048.75 -> 5.0748429e+09 | D19: 0.1 | F19: Other JV or associate | G19: =142861296.29+17825955.91 -> 1.6068725e+08 | H19: 0.1
B20: Biological assets | C20: 0 | D20: 0.05 | F20: Properties with stable income | G20: 0 | H20: 0.2
B21: Intangible assets | C21: 6.506348e+08 | D21: 0.05 | F21: Other Properties | G21: 0 | H21: 0.1
B22: LT DTA | C22: 7.0346537e+08 | D22: 0.9
B23: Other assets & Goodwill | C23: =699192456.06+479496.08 -> 6.9967195e+08 | D23: 0
B24: Operating LT Assets | C24: =SUM(C15:C23) -> 7.128615e+09 | D24: =C15*D15+C16*D16+C18*D18+C17*D17+C19*D19+C20*D20+C21*D21+C22*D22+C23*D23 -> 1.1731349e+09 | F24: Non-Operating LT Assets | G24: =SUM(G15:G21) -> 1.6068725e+08 | H24: =G15*H15+G16*H16+G17*H17+G18*H18+G19*H19+G20*H20+G21*H21 -> 16068725
B26: ST Liabilities | C26: Book | F26: BS Summary | G26: Book | H26: Valued @
B27: ST Borrowing | C27: 0 | F27: Total Equity | G27: =G32-G30 -> 2.4536581e+09 | H27: =H32-G30 -> -5.174669e+09
B28: ST Lease liabilities | C28: 0 | F28: Incl. Minority Interest (NCI) | G28: 1.2684378e+09
B29: ST SH Loan | C29: 0 | F29: Incl. Common Equity | G29: =G27-G28 -> 1.1852203e+09 | H29: =H27-G28 -> -6.4431068e+09
B30: ST Financial Liabilities | C30: 897606.82 | F30: Total Liabilities | G30: =C33+C42 -> 8.5146816e+09
B31: ST Interest-bearing Debt | C31: =SUM(C27:C30) -> 897606.82 | F31: incl. Interest-bearing Debt | G31: =C31+C40 -> 1.235217e+08
B32: Other ST liabilities | C32: =C33-C31 -> 7.7384123e+09 | F32: Total Assets | G32: =G35+G40 -> 1.096834e+10 | H32: =H35+H40 -> 3.3400126e+09
B33: Current Liabilities | C33: 7.7393099e+09
F34: Assets Summary | G34: Book | H34: Valued @
B35: LT Liabilities | C35: Book | F35: Operating Assets | G35: =C12+C24 -> 9.7035113e+09 | H35: =D12+D24 -> 2.3369615e+09
B36: LT Borrowing | C36: 0 | F36: incl. AR | G36: =C4+C15 -> 91009310
B37: LT Lease liabilities | C37: 1.226241e+08 | F37: incl. inventory | G37: =C6 -> 2.1858356e+09
B38: LT SH Loan | C38: 0 | F38: incl. Properties held for sale | G38: =C7+C17 -> 0
B39: LT Financial Liabilities | C39: 0 | F39: incl. Fixed Assets | G39: =C7+C17+C19+C20 -> 5.0748429e+09 | H39: =C7*D7+C17*D17+C19*D19+C20*D20 -> 5.0748429e+08
B40: LT Interest-bearing Debt | C40: =SUM(C36:C39) -> 1.226241e+08 | F40: Non-operating Assets | G40: =G12+G24 -> 1.2648285e+09 | H40: =H12+H24 -> 1.0030512e+09
B41: Other LT liabilities | C41: =C42-C40 -> 6.5274758e+08 | F41: incl. Assets with stable income | G41: =C70 -> 1.0816591e+09 | H41: =H40-H42 -> 9.7349317e+08
B42: Noncurrent Liabilities | C42: 7.7537168e+08 | F42: incl. Other Assets | G42: =C82 -> 1.8316938e+08 | H42: =D82 -> 29558001
B44: Balance Sheet Analysis
B45: Asset Value Stress Test | C45: Book | D45: Est. Realizable Value | F45: Notes
B46: Equity | C46: =G29 -> 1.1852203e+09 | D46: =H29 -> -6.4431068e+09
B47: ="Equity per share ("&Market_currency&")" -> Equity per share (CNY) | C47: =C46*H1/Common_Shares*Exchange_Rate -> 2.4489479 | D47: =D46*H1/Common_Shares*Exchange_Rate -> -13.312996
B49: Leverage % | C49: Normalized | D49: Latest
B50: Debt/EBIT | C50: =G31/Normalized_FCF!C8 -> 0.041762543 | D50: =G31/Normalized_FCF!G8 -> 0.039727648
B51: Common Equity/Total Asset | D51: =G29/G32 -> 0.10805831
B53: Profibility % | C53: Normalized | D53: Latest
B54: Operating Asset Yield | C54: =Normalized_FCF!C8/G35 -> 0.30480875 | D54: =Normalized_FCF!G8/G35 -> 0.32042139
B55: Non-Operating Asset Yield | C55: =Normalized_FCF!C11/G40 -> 0 | D55: =Normalized_FCF!G11/G40 -> 0
B57: Reinvestment % | C57: Normalized | D57: Latest
B58: D&A/Fixed Assets | D58: =Normalized_FCF!G9/BS!$G$39 -> 0.11348487
B59: Fixed Assets/Total Assets | D59: =G39/G32 -> 0.46268104
B61: NCI % | C61: Estimate | D61: Latest
B62: Est. of NCI Ownership Percentage | C62: =IF(G28<=0,0,G28/G29) -> 1.0702128 | D62: =G28/G29 -> 1.0702128 | F62: Rough Estimate only
B64: Non-operating Assets Analysis
B65: Non-operating Assets with stable income | C65: Book | D65: Non-Operating | F65: Notes
B66: Cash | C66: =G4+G5+G15 -> 1.0816591e+09 | D66: =C66-D75 -> 51803896 | F66: Non-Operating Cash is the Excess cash not required for operations
B67: Securities with stable income | C67: =G6+G16 -> 0
B68: JV or associate with stable income | C68: =G18 -> 0
B69: Properties with stable income | C69: =G8+G20 -> 0
B70: Non-operating Assets with stable income | C70: =SUM(C66:C69) -> 1.0816591e+09
B72: Cash Management Analysis | C72: Latest | D72: Normalized
B73: Monthly Operating Expenses | C73: =(Normalized_FCF!G25+Normalized_FCF!G35-Normalized_FCF!G91)/12 -> -1.0580763e+09 | D73: =(Normalized_FCF!C25+Normalized_FCF!C35-Normalized_FCF!C91)/12 -> -1.0298552e+09 | F73: Variable + Fixed Costs & Dividends
B74: Operating Expenses Multiple (months) | C74: =-$C$66/C73 -> 1.0222883 | D74: =-$C$66/D73 -> 1.0503021 | F74: Companies typically need cash to cover 1 to 2 months of operating expenses
B75: Operating Cash Requirement | D75: =MAX(-D73*D76,G5) -> 1.0298552e+09 | F75: 1x for stable businesses, 2x for for volatile ones, 6x for cash hoarders
B76: Operating Cash Multiple (months) | D76: =IF(D74<=3,1,IF(D74>18,6,2)) -> 1 | F76: Rough Estimate
B78: Other Non-operating Assets | C78: Book | D78: Valued @
B79: Other Securities | C79: =G7+G17 -> 22482126 | D79: =G7*H7+G17*H17 -> 13489275
B80: Other JV or associate | C80: =G19 -> 1.6068725e+08 | D80: =G19*H19 -> 16068725
B81: Other Properties | C81: =G9+G21 -> 0 | D81: =G9*H9+G21*H21 -> 0
B82: Other Non-operating Assets | C82: =SUM(C79:C81) -> 1.8316938e+08 | D82: =SUM(D79:D81) -> 29558001
B84: Non-FCF Value of the Equity Value
B85: Non-FCF Value | D85: Per-Share
B86: Interest-bearing Debt | C86: =-DCF!C7*Exchange_Rate -> -1.235217e+08 | D86: =C86*scaling_factor/Common_Shares -> -0.25522532 | E86: =Market_currency -> CNY
B87: Non-operating Cash | C87: =DCF!C8*Exchange_Rate -> 51803896 | D87: =C87*scaling_factor/Common_Shares -> 0.10703921 | E87: =Market_currency -> CNY
B88: Other Non-operating Assets | C88: =DCF!C9*Exchange_Rate -> 29558001 | D88: =C88*scaling_factor/Common_Shares -> 0.061073884 | E88: =Market_currency -> CNY
B89: Total Non-FCF Value | C89: =SUM(C86:C88) -> -42159808 | D89: =SUM(D86:D88) -> -0.087112225 | E89: =Market_currency -> CNY

Sheet Normalized_FCF
B1: =Thesis!C25 -> CNY | C1: Normalized | G1: =Data!C1 -> 45657 | H1: =EOMONTH(EDATE(G1,-12),0) -> 45291 | I1: =EOMONTH(EDATE(H1,-12),0) -> 44926 | J1: =EOMONTH(EDATE(I1,-12),0) -> 44561 | K1: =EOMONTH(EDATE(J1,-12),0) -> 44196 | L1: =EOMONTH(EDATE(K1,-12),0) -> 43830 | M1: =EOMONTH(EDATE(L1,-12),0) -> 43465 | N1: =EOMONTH(EDATE(M1,-12),0) -> 43100 | O1: =EOMONTH(EDATE(N1,-12),0) -> 42735 | ... Q1: =EOMONTH(EDATE(P1,-12),0) -> 42004
B2: FCFE Analysis | E2: Notes
B3: FCFE | C3: =scaling_factor -> 1
B4: Sales | C4: =AVERAGE(G4:J4) -> 1.4154446e+10 | G4: =Data!C36 -> 14644597842 | H4: =Data!D36 -> 14814836410 | I4: =Data!E36 -> 14039040539 | J4: =Data!F36 -> 13119310688 | K4: =Data!G36 -> 10941631163 | L4: =Data!H36 -> 3581923735 | M4: =Data!I36 -> 3467335930 | N4: =Data!J36 -> 3175519522 | ... Q4: =Data!M36
B5: Variable Costs | C5: =C25 -> -1.0627751e+10 | G5: =G25 -> -10995777063 | H5: =H25 -> -11024146849 | I5: =I25 -> -10199504511 | J5: =J25 -> -9541312707 | K5: =K25 -> -8470392189 | L5: =L25 -> -2851333924 | M5: =M25 -> -2818013131 | N5: =N25 -> -2656139210 | ... Q5: =Q25
B6: Contribution Margin | C6: =C4+C5 -> 3.5266955e+09 | G6: =IF(G4="","",G4+G5) -> 3648820779 | H6: =IF(H4="","",H4+H5) -> 3790689561 | I6: =IF(I4="","",I4+I5) -> 3839536028 | J6: =IF(J4="","",J4+J5) -> 3577997981 | K6: =IF(K4="","",K4+K5) -> 2471238974 | L6: =IF(L4="","",L4+L5) -> 730589811 | M6: =IF(M4="","",M4+M5) -> 649322799 | N6: =IF(N4="","",N4+N5) -> 519380312 | ... Q6: =IF(Q4="","",Q4+Q5)
B7: Fixed Costs | C7: =C35 -> -5.6898044e+08 | G7: =G35 -> -539608200 | H7: =H35 -> -520902794 | I7: =I35 -> -645318285 | J7: =J35 -> -680028430 | K7: =K35 -> -768317542 | L7: =L35 -> -161996928 | M7: =M35 -> -153940810 | N7: =N35 -> -155718230 | ... Q7: =Q35
B8: Operating EBIT | C8: =C6+C7 -> 2.9577151e+09 | G8: =IF(G$4="","",G6+G7) -> 3109212579 | H8: =IF(H$4="","",H6+H7) -> 3269786767 | I8: =IF(I$4="","",I6+I7) -> 3194217743 | J8: =IF(J$4="","",J6+J7) -> 2897969551 | K8: =IF(K$4="","",K6+K7) -> 1702921432 | L8: =IF(L$4="","",L6+L7) -> 568592883 | M8: =IF(M$4="","",M6+M7) -> 495381989 | N8: =IF(N$4="","",N6+N7) -> 363662082 | ... Q8: =IF(Q$4="","",Q6+Q7)
B9: Add Back D&A | C9: =BS!$G$39*BS!D58 -> 575917865 | G9: =IF(Data!C61="","",-Data!C61) -> 575917865 | H9: =IF(Data!D61="","",-Data!D61) -> 514817738 | I9: =IF(Data!E61="","",-Data!E61) -> 504410326 | J9: =IF(Data!F61="","",-Data!F61) -> 451827434 | K9: =IF(Data!G61="","",-Data!G61) -> 413794059 | L9: =IF(Data!H61="","",-Data!H61) -> 174070610 | M9: =IF(Data!I61="","",-Data!I61) -> 173632673 | N9: =IF(Data!J61="","",-Data!J61) -> 0 | ... Q9: =IF(Data!M61="","",-Data!M61)
B10: Maintenance Capex | C10: =-C4*C78 -> -575917865 | G10: =Data!C62 -> -575917865 | H10: =Data!D62 -> -514817738 | I10: =Data!E62 -> -504410326 | J10: =Data!F62 -> -451827434 | K10: =Data!G62 -> -413794059 | L10: =Data!H62 -> -174070610 | M10: =Data!I62 -> -173632673 | N10: =Data!J62 -> 0 | ... Q10: =Data!M62
B11: Stable Non-Operating EBIT | C11: =C63 -> 0 | G11: =G61 -> 0 | H11: =H61 -> 0 | I11: =I61 -> 0 | J11: =J61 -> 0 | K11: =K61 -> 0 | L11: =L61 -> 0 | M11: =M61 -> 0 | N11: =N61 -> 0 | ... Q11: =Q61
B12: Net Interest Income | C12: =C50 -> 31406154 | G12: =G50 -> 31406154 | H12: =H50 -> 61971192 | I12: =I50 -> 58874285 | J12: =J50 -> 20137431 | K12: =K50 -> 6490894.6 | L12: =L50 -> -2599288.6 | M12: =M50 -> -6040379.1 | N12: =N50 -> 0 | ... Q12: =Q50
B13: Pre-tax Profit | C13: =SUM(C8:C12) -> 2.9891213e+09 | G13: =IF(G$4="","",SUM(G8:G12)) -> 3.1406187e+09 | H13: =IF(H$4="","",SUM(H8:H12)) -> 3.331758e+09 | I13: =IF(I$4="","",SUM(I8:I12)) -> 3.253092e+09 | J13: =IF(J$4="","",SUM(J8:J12)) -> 2.918107e+09 | K13: =IF(K$4="","",SUM(K8:K12)) -> 1.7094123e+09 | L13: =IF(L$4="","",SUM(L8:L12)) -> 5.6599359e+08 | M13: =IF(M$4="","",SUM(M8:M12)) -> 4.8934161e+08 | N13: =IF(N$4="","",SUM(N8:N12)) -> 363662082 | ... Q13: =IF(Q$4="","",SUM(Q8:Q12))
B14: Income Tax | C14: =-SUM(C8+C11,C12)*C43 -> -7.4728032e+08 | G14: =Data!C46 -> -670547120 | H14: =Data!D46 -> -664121997 | I14: =Data!E46 -> -711879179 | J14: =Data!F46 -> -541923819 | K14: =Data!G46 -> -378467716 | L14: =Data!H46 -> -98780687 | M14: =Data!I46 -> -61018006 | N14: =Data!J46 -> -18873927 | ... Q14: =Data!M46
B15: NCI’s Share of Profits | C15: =-C4*C83 -> -1.418797e+08 | G15: =Data!C48 -> -146792828 | H15: =Data!D48 -> 0 | I15: =Data!E48 -> 0 | J15: =Data!F48 -> 0 | K15: =Data!G48 -> 0 | L15: =Data!H48 -> 0 | M15: =Data!I48 -> 0 | N15: =Data!J48 -> 0 | ... Q15: =Data!M48
B16: After-tax Profit | C16: =SUM(C13:C15) -> 2.0999612e+09 | G16: =IF(G$4="","",SUM(G13:G15)) -> 2.3232788e+09 | H16: =IF(H$4="","",SUM(H13:H15)) -> 2.667636e+09 | I16: =IF(I$4="","",SUM(I13:I15)) -> 2.5412128e+09 | J16: =IF(J$4="","",SUM(J13:J15)) -> 2.3761832e+09 | K16: =IF(K$4="","",SUM(K13:K15)) -> 1.3309446e+09 | L16: =IF(L$4="","",SUM(L13:L15)) -> 4.6721291e+08 | M16: =IF(M$4="","",SUM(M13:M15)) -> 4.283236e+08 | N16: =IF(N$4="","",SUM(N13:N15)) -> 344788155 | ... Q16: =IF(Q$4="","",SUM(Q13:Q15))
B17: WCInv | C17: =-C4*C85 -> 0 | E17: WCInv is by default excluded
B18: Net Borrowing | C18: 0 | E18: Net borrowing is excluded
B19: FCFE | C19: =C16+C17 -> 2.0999612e+09 | G19: =IF(G$4="","",G16+G17) -> 2.3232788e+09 | H19: =IF(H$4="","",H16+H17) -> 2.667636e+09 | I19: =IF(I$4="","",I16+I17) -> 2.5412128e+09 | J19: =IF(J$4="","",J16+J17) -> 2.3761832e+09 | K19: =IF(K$4="","",K16+K17) -> 1.3309446e+09 | L19: =IF(L$4="","",L16+L17) -> 4.6721291e+08 | M19: =IF(M$4="","",M16+M17) -> 4.283236e+08 | N19: =IF(N$4="","",N16+N17) -> 344788155 | ... Q19: =IF(Q$4="","",Q16+Q17)
B21: Operating Cost Structure | E21: Notes
B22: Variable Costs
B23: COGS | C23: =-C4*C28 -> -8.1991951e+09 | G23: =Data!C37 -> -8483123346 | H23: =Data!D37 -> -8491525016 | I23: =Data!E37 -> -7873287284 | J23: =Data!F37 -> -7328418046 | K23: =Data!G37 -> -6166079008 | L23: =Data!H37 -> -2359127300 | M23: =Data!I37 -> -2362728713 | N23: =Data!J37 -> -2190920673 | ... Q23: =Data!M37
B24: Selling Expenses | C24: =-C4*C29 -> -2.4285557e+09 | G24: =Data!C40 -> -2512653717 | H24: =Data!D40 -> -2532621833 | I24: =Data!E40 -> -2326217227 | J24: =Data!F40 -> -2212894661 | K24: =Data!G40 -> -2304313181 | L24: =Data!H40 -> -492206624 | M24: =Data!I40 -> -455284418 | N24: =Data!J40 -> -465218537 | ... Q24: =Data!M40
B25: Variable Costs | C25: =C23+C24 -> -1.0627751e+10 | G25: =IF(G$4="","",G23+G24) -> -10995777063 | H25: =IF(H$4="","",H23+H24) -> -11024146849 | I25: =IF(I$4="","",I23+I24) -> -10199504511 | J25: =IF(J$4="","",J23+J24) -> -9541312707 | K25: =IF(K$4="","",K23+K24) -> -8470392189 | L25: =IF(L$4="","",L23+L24) -> -2851333924 | M25: =IF(M$4="","",M23+M24) -> -2818013131 | N25: =IF(N$4="","",N23+N24) -> -2656139210 | ... Q25: =IF(Q$4="","",Q23+Q24)
B27: Variable Costs % of Sales
B28: COGS | C28: =G28 -> 0.57926639 | E28: Historical Average | G28: =IF(G$4="","",ABS(G23/G$4)) -> 0.57926639 | H28: =IF(H$4="","",ABS(H23/H$4)) -> 0.5731771 | I28: =IF(I$4="","",ABS(I23/I$4)) -> 0.56081377 | J28: =IF(J$4="","",ABS(J23/J$4)) -> 0.5585978 | K28: =IF(K$4="","",ABS(K23/K$4)) -> 0.56354294 | L28: =IF(L$4="","",ABS(L23/L$4)) -> 0.65862019 | M28: =IF(M$4="","",ABS(M23/M$4)) -> 0.68142481 | N28: =IF(N$4="","",ABS(N23/N$4)) -> 0.68994086 | ... Q28: =IF(Q$4="","",ABS(Q23/Q$4))
B29: =B24 -> Selling Expenses | C29: =G29 -> 0.17157547 | E29: Historical Average | G29: =IF(G$4="","",ABS(G24/G$4)) -> 0.17157547 | H29: =IF(H$4="","",ABS(H24/H$4)) -> 0.17095172 | I29: =IF(I$4="","",ABS(I24/I$4)) -> 0.16569631 | J29: =IF(J$4="","",ABS(J24/J$4)) -> 0.16867461 | K29: =IF(K$4="","",ABS(K24/K$4)) -> 0.21060052 | L29: =IF(L$4="","",ABS(L24/L$4)) -> 0.13741404 | M29: =IF(M$4="","",ABS(M24/M$4)) -> 0.13130669 | N29: =IF(N$4="","",ABS(N24/N$4)) -> 0.14650155 | ... Q29: =IF(Q$4="","",ABS(Q24/Q$4))
B30: Variable Costs | C30: =ABS(C25/$C$4) -> 0.75084186 | G30: =IF(G$4="","",ABS(G25/G$4)) -> 0.75084186 | H30: =IF(H$4="","",ABS(H25/H$4)) -> 0.74412883 | I30: =IF(I$4="","",ABS(I25/I$4)) -> 0.72651008 | J30: =IF(J$4="","",ABS(J25/J$4)) -> 0.72727241 | K30: =IF(K$4="","",ABS(K25/K$4)) -> 0.77414346 | L30: =IF(L$4="","",ABS(L25/L$4)) -> 0.79603424 | M30: =IF(M$4="","",ABS(M25/M$4)) -> 0.8127315 | N30: =IF(N$4="","",ABS(N25/N$4)) -> 0.83644241 | ... Q30: =IF(Q$4="","",ABS(Q25/Q$4))
B32: Fixed Costs
B33: G&A and other Opex | C33: =AVERAGE(G33:J33) -> -5.157651e+08 | E33: Historical Average | G33: =Data!C41 -> -516942154 | H33: =Data!D41 -> -494670738 | I33: =Data!E41 -> -534570349 | J33: =Data!F41 -> -516877145 | K33: =Data!G41 -> -684104925 | L33: =Data!H41 -> -161996928 | M33: =Data!I41 -> -153940810 | N33: =Data!J41 -> -155718230 | ... Q33: =Data!M41
B34: R&D | C34: =AVERAGE(G34:I34) -> -53215346 | E34: Historical Average | G34: =Data!C42 -> -22666046 | H34: =Data!D42 -> -26232056 | I34: =Data!E42 -> -110747936 | J34: =Data!F42 -> -163151285 | K34: =Data!G42 -> -84212617 | L34: =Data!H42 -> 0 | M34: =Data!I42 -> 0 | N34: =Data!J42 -> 0 | ... Q34: =Data!M42
B35: Fixed Costs | C35: =C33+C34 -> -5.6898044e+08 | G35: =IF(G4="","",G33+G34) -> -539608200 | H35: =IF(H4="","",H33+H34) -> -520902794 | I35: =IF(I4="","",I33+I34) -> -645318285 | J35: =IF(J4="","",J33+J34) -> -680028430 | K35: =IF(K4="","",K33+K34) -> -768317542 | L35: =IF(L4="","",L33+L34) -> -161996928 | M35: =IF(M4="","",M33+M34) -> -153940810 | N35: =IF(N4="","",N33+N34) -> -155718230 | ... Q35: =IF(Q4="","",Q33+Q34)
B37: Fixed Costs % of Sales
B38: =B33 -> G&A and other Opex | C38: =ABS(C33/$C$4) -> 0.03643838 | G38: =IF(G$4="","",ABS(G33/G$4)) -> 0.03529917 | H38: =IF(H$4="","",ABS(H33/H$4)) -> 0.033390226 | I38: =IF(I$4="","",ABS(I33/I$4)) -> 0.038077413 | J38: =IF(J$4="","",ABS(J33/J$4)) -> 0.039398194 | K38: =IF(K$4="","",ABS(K33/K$4)) -> 0.062523121 | L38: =IF(L$4="","",ABS(L33/L$4)) -> 0.045226236 | M38: =IF(M$4="","",ABS(M33/M$4)) -> 0.044397432 | N38: =IF(N$4="","",ABS(N33/N$4)) -> 0.049037088 | ... Q38: =IF(Q$4="","",ABS(Q33/Q$4))
B39: =B34 -> R&D | C39: =ABS(C34/$C$4) -> 0.0037596204 | G39: =IF(G$4="","",ABS(G34/G$4)) -> 0.0015477411 | H39: =IF(H$4="","",ABS(H34/H$4)) -> 0.0017706612 | I39: =IF(I$4="","",ABS(I34/I$4)) -> 0.0078885687 | J39: =IF(J$4="","",ABS(J34/J$4)) -> 0.012435965 | K39: =IF(K$4="","",ABS(K34/K$4)) -> 0.0076965322 | L39: =IF(L$4="","",ABS(L34/L$4)) -> 0 | M39: =IF(M$4="","",ABS(M34/M$4)) -> 0 | N39: =IF(N$4="","",ABS(N34/N$4)) -> 0 | ... Q39: =IF(Q$4="","",ABS(Q34/Q$4))
B40: Fixed Costs | C40: =ABS(C35/$C$4) -> 0.040198001 | G40: =IF(G$4="","",ABS(G35/G$4)) -> 0.036846911 | H40: =IF(H$4="","",ABS(H35/H$4)) -> 0.035160887 | I40: =IF(I$4="","",ABS(I35/I$4)) -> 0.045965982 | J40: =IF(J$4="","",ABS(J35/J$4)) -> 0.051834159 | K40: =IF(K$4="","",ABS(K35/K$4)) -> 0.070219653 | L40: =IF(L$4="","",ABS(L35/L$4)) -> 0.045226236 | M40: =IF(M$4="","",ABS(M35/M$4)) -> 0.044397432 | N40: =IF(N$4="","",ABS(N35/N$4)) -> 0.049037088 | ... Q40: =IF(Q$4="","",ABS(Q35/Q$4))
B42: Tax % of Pre-tax Profit
B43: Income Tax Rate | C43: 0.25 | E43: Use the highest past tax rate | G43: =IF(G$4="","",-G14/SUM(G8+G11,G12)) -> 0.21350797 | H43: =IF(H$4="","",-H14/SUM(H8+H11,H12)) -> 0.19933081 | I43: =IF(I$4="","",-I14/SUM(I8+I11,I12)) -> 0.21883155 | J43: =IF(J$4="","",-J14/SUM(J8+J11,J12)) -> 0.18571074 | K43: =IF(K$4="","",-K14/SUM(K8+K11,K12)) -> 0.22140224 | L43: =IF(L$4="","",-L14/SUM(L8+L11,L12)) -> 0.17452616 | M43: =IF(M$4="","",-M14/SUM(M8+M11,M12)) -> 0.12469409 | N43: =IF(N$4="","",-N14/SUM(N8+N11,N12)) -> 0.051899629 | ... Q43: =IF(Q$4="","",-Q14/SUM(Q8+Q11,Q12))
B45: Non-operating Income | E45: Notes
B46: Interest
B47: Interest Expense | C47: =-BS!G31*Normalized_FCF!C54 -> -7672861 | G47: =Data!C51 -> -7672861 | H47: =Data!D51 -> -5921669 | I47: =Data!E51 -> -3696844 | J47: =Data!F51 -> -14186775 | K47: =Data!G51 -> -35823675 | L47: =Data!H51 -> -10770646 | M47: =Data!I51 -> -12333775 | N47: =Data!J51 -> 0 | ... Q47: =Data!M51
B48: Operating Interest Income | C48: =BS!D75*C53 -> 39079015 | G48: =IFERROR(IF(G$4="","",($C$48/$C$49)*G49),0) -> 39079015 | H48: =IFERROR(IF(H$4="","",($C$48/$C$49)*H49),0) -> 67892861 | I48: =IFERROR(IF(I$4="","",($C$48/$C$49)*I49),0) -> 62571129 | J48: =IFERROR(IF(J$4="","",($C$48/$C$49)*J49),0) -> 34324206 | K48: =IFERROR(IF(K$4="","",($C$48/$C$49)*K49),0) -> 42314570 | L48: =IFERROR(IF(L$4="","",($C$48/$C$49)*L49),0) -> 8171357.4 | M48: =IFERROR(IF(M$4="","",($C$48/$C$49)*M49),0) -> 6293395.9 | N48: =IFERROR(IF(N$4="","",($C$48/$C$49)*N49),0) -> 0 | ... Q48: =IFERROR(IF(Q$4="","",($C$48/$C$49)*Q49),0)
B49: From Interest Income | C49: =BS!$C$66*C53 -> 41044772 | G49: =Data!C52 -> 41044772 | H49: =Data!D52 -> 71308016 | I49: =Data!E52 -> 65718589 | J49: =Data!F52 -> 36050786 | K49: =Data!G52 -> 44443082 | L49: =Data!H52 -> 8582394 | M49: =Data!I52 -> 6609967 | N49: =Data!J52 -> 0 | ... Q49: =Data!M52
B50: Net Interest Income | C50: =C47+C48 -> 31406154 | G50: =IF(G$4="","",(G47+G48)) -> 31406154 | H50: =IF(H$4="","",(H47+H48)) -> 61971192 | I50: =IF(I$4="","",(I47+I48)) -> 58874285 | J50: =IF(J$4="","",(J47+J48)) -> 20137431 | K50: =IF(K$4="","",(K47+K48)) -> 6490894.6 | L50: =IF(L$4="","",(L47+L48)) -> -2599288.6 | M50: =IF(M$4="","",(M47+M48)) -> -6040379.1 | N50: =IF(N$4="","",(N47+N48)) -> 0 | ... Q50: =IF(Q$4="","",(Q47+Q48))
B52: % Interest | G52: Latest Asset Value
B53: Interest Yield/Cash | C53: =G53 -> 0.037946126 | E53: Reference the market rate | G53: =IF(Normalized_FCF!G4="","",Normalized_FCF!G49/BS!$C$66) -> 0.037946126
B54: Interest Rate/Debt | C54: =G54 -> 0.062117512 | E54: Use Last year's rate | G54: =IFERROR(ABS(Normalized_FCF!G47/BS!$G$31),0) -> 0.062117512
B55: Pre-tax Profit/Interest Expense | C55: =-C8/C47 -> 385.47748 | G55: =IF(G4="","",-G8/G47) -> 405.22207 | H55: =IF(H4="","",-H8/H47) -> 552.17317 | I55: =IF(I4="","",-I8/I47) -> 864.03909 | J55: =IF(J4="","",-J8/J47) -> 204.27261 | K55: =IF(K4="","",-K8/K47) -> 47.536201 | L55: =IF(L4="","",-L8/L47) -> 52.790973 | M55: =IF(M4="","",-M8/M47) -> 40.164669 | N55: =IF(N4="","",-N8/N47) -> #DIV/0! | ... Q55: =IF(Q4="","",-Q8/Q47)
B57: Non-operating EBIT | G57: Latest Asset Value
B58: Dividend or Interests from FA | C58: =BS!$C67*C66 -> 0 | G58: =Data!C56 -> 0 | H58: =Data!D56 -> 0 | I58: =Data!E56 -> 0 | J58: =Data!F56 -> 0 | K58: =Data!G56 -> 0 | L58: =Data!H56 -> 0 | M58: =Data!I56 -> 0 | N58: =Data!J56 -> 0 | ... Q58: =Data!M56
B59: Share of JV or associate Results | C59: =BS!$C68*C67 -> 0 | G59: =Data!C55 -> 0 | H59: =Data!D55 -> 0 | I59: =Data!E55 -> 0 | J59: =Data!F55 -> 0 | K59: =Data!G55 -> 0 | L59: =Data!H55 -> 0 | M59: =Data!I55 -> 0 | N59: =Data!J55 -> 0 | ... Q59: =Data!M55
B60: Investment property | C60: =BS!$C69*C68 -> 0 | G60: =Data!C57 -> 0 | H60: =Data!D57 -> 0 | I60: =Data!E57 -> 0 | J60: =Data!F57 -> 0 | K60: =Data!G57 -> 0 | L60: =Data!H57 -> 0 | M60: =Data!I57 -> 0 | N60: =Data!J57 -> 0 | ... Q60: =Data!M57
B61: Stable Non-Operating EBIT | C61: =SUM(C58:C60) -> 0 | G61: =IF(G4="","",SUM(G58:G60)) -> 0 | H61: =IF(H4="","",SUM(H58:H60)) -> 0 | I61: =IF(I4="","",SUM(I58:I60)) -> 0 | J61: =IF(J4="","",SUM(J58:J60)) -> 0 | K61: =IF(K4="","",SUM(K58:K60)) -> 0 | L61: =IF(L4="","",SUM(L58:L60)) -> 0 | M61: =IF(M4="","",SUM(M58:M60)) -> 0 | N61: =IF(N4="","",SUM(N58:N60)) -> 0 | ... Q61: =IF(Q4="","",SUM(Q58:Q60))
B62: Other Non-operating Income | C62: 0 | E62: Assume 0 | G62: =Data!C58 -> -222656878 | H62: =Data!D58 -> 40517438 | I62: =Data!E58 -> 42539332 | J62: =Data!F58 -> 21246453 | K62: =Data!G58 -> 419243973 | L62: =Data!H58 -> 260912986 | M62: =Data!I58 -> -7380704 | N62: =Data!J58 -> -18665820 | ... Q62: =Data!M58
B63: Total Non-Operating EBIT | C63: =C61+C62 -> 0 | G63: =IF(G4="","",G61+G62) -> -222656878 | H63: =IF(H4="","",H61+H62) -> 40517438 | I63: =IF(I4="","",I61+I62) -> 42539332 | J63: =IF(J4="","",J61+J62) -> 21246453 | K63: =IF(K4="","",K61+K62) -> 419243973 | L63: =IF(L4="","",L61+L62) -> 260912986 | M63: =IF(M4="","",M61+M62) -> -7380704 | N63: =IF(N4="","",N61+N62) -> -18665820 | ... Q63: =IF(Q4="","",Q61+Q62)
B65: Non-operating Asset Yield % | G65: Latest Asset Value
B66: Dividend or Interests from FA | C66: =G66 -> 0 | G66: =IFERROR(G58/BS!$C$67,0) -> 0
B67: JV or associate | C67: =G67 -> 0 | G67: =IFERROR(G59/BS!$C$68,0) -> 0
B68: Investment property | C68: =G68 -> 0 | G68: =IFERROR(G60/BS!$C$69,0) -> 0
B69: Stable Non-Operating EBIT | C69: =C61/BS!C70 -> 0 | G69: =G61/BS!C70 -> 0
B71: P&L & Dividend Analysis | E71: Notes
B72: P&L % Sales
B73: Variable Costs | C73: =ABS(C5/C$4) -> 0.75084186 | G73: =IF(G$4="","",ABS(G5/G$4)) -> 0.75084186 | H73: =IF(H$4="","",ABS(H5/H$4)) -> 0.74412883 | I73: =IF(I$4="","",ABS(I5/I$4)) -> 0.72651008 | J73: =IF(J$4="","",ABS(J5/J$4)) -> 0.72727241 | K73: =IF(K$4="","",ABS(K5/K$4)) -> 0.77414346 | L73: =IF(L$4="","",ABS(L5/L$4)) -> 0.79603424 | M73: =IF(M$4="","",ABS(M5/M$4)) -> 0.8127315 | N73: =IF(N$4="","",ABS(N5/N$4)) -> 0.83644241 | ... Q73: =IF(Q$4="","",ABS(Q5/Q$4))
B74: Contribution Margin | C74: =ABS(C6/C$4) -> 0.24915814 | G74: =IF(G$4="","",ABS(G6/G$4)) -> 0.24915814 | H74: =IF(H$4="","",ABS(H6/H$4)) -> 0.25587117 | I74: =IF(I$4="","",ABS(I6/I$4)) -> 0.27348992 | J74: =IF(J$4="","",ABS(J6/J$4)) -> 0.27272759 | K74: =IF(K$4="","",ABS(K6/K$4)) -> 0.22585654 | L74: =IF(L$4="","",ABS(L6/L$4)) -> 0.20396576 | M74: =IF(M$4="","",ABS(M6/M$4)) -> 0.1872685 | N74: =IF(N$4="","",ABS(N6/N$4)) -> 0.16355759 | ... Q74: =IF(Q$4="","",ABS(Q6/Q$4))
B75: Fixed Costs | C75: =ABS(C7/C$4) -> 0.040198001 | G75: =IF(G$4="","",ABS(G7/G$4)) -> 0.036846911 | H75: =IF(H$4="","",ABS(H7/H$4)) -> 0.035160887 | I75: =IF(I$4="","",ABS(I7/I$4)) -> 0.045965982 | J75: =IF(J$4="","",ABS(J7/J$4)) -> 0.051834159 | K75: =IF(K$4="","",ABS(K7/K$4)) -> 0.070219653 | L75: =IF(L$4="","",ABS(L7/L$4)) -> 0.045226236 | M75: =IF(M$4="","",ABS(M7/M$4)) -> 0.044397432 | N75: =IF(N$4="","",ABS(N7/N$4)) -> 0.049037088 | ... Q75: =IF(Q$4="","",ABS(Q7/Q$4))
B76: Operating EBIT | C76: =ABS(C8/C$4) -> 0.20896014 | G76: =IF(G$4="","",ABS(G8/G$4)) -> 0.21231123 | H76: =IF(H$4="","",ABS(H8/H$4)) -> 0.22071029 | I76: =IF(I$4="","",ABS(I8/I$4)) -> 0.22752393 | J76: =IF(J$4="","",ABS(J8/J$4)) -> 0.22089343 | K76: =IF(K$4="","",ABS(K8/K$4)) -> 0.15563689 | L76: =IF(L$4="","",ABS(L8/L$4)) -> 0.15873953 | M76: =IF(M$4="","",ABS(M8/M$4)) -> 0.14287107 | N76: =IF(N$4="","",ABS(N8/N$4)) -> 0.1145205 | ... Q76: =IF(Q$4="","",ABS(Q8/Q$4))
B77: Add Back D&A | C77: =ABS(C9/C$4) -> 0.040688124 | G77: =IF(G$4="","",G9/G$4) -> 0.039326301 | H77: =IF(H$4="","",H9/H$4) -> 0.034750147 | I77: =IF(I$4="","",I9/I$4) -> 0.035929117 | J77: =IF(J$4="","",J9/J$4) -> 0.034439876 | K77: =IF(K$4="","",K9/K$4) -> 0.037818315 | L77: =IF(L$4="","",L9/L$4) -> 0.048596962 | M77: =IF(M$4="","",M9/M$4) -> 0.05007668 | N77: =IF(N$4="","",N9/N$4) -> 0 | ... Q77: =IF(Q$4="","",Q9/Q$4)
B78: Maintenance Capex | C78: =MAX(AVERAGE(G78:J78),C77) -> 0.040688124 | E78: Historical Average or D&A | G78: =IF(G$4="","",-G10/G$4) -> 0.039326301 | H78: =IF(H$4="","",-H10/H$4) -> 0.034750147 | I78: =IF(I$4="","",-I10/I$4) -> 0.035929117 | J78: =IF(J$4="","",-J10/J$4) -> 0.034439876 | K78: =IF(K$4="","",-K10/K$4) -> 0.037818315 | L78: =IF(L$4="","",-L10/L$4) -> 0.048596962 | M78: =IF(M$4="","",-M10/M$4) -> 0.05007668 | N78: =IF(N$4="","",-N10/N$4) -> 0 | ... Q78: =IF(Q$4="","",-Q10/Q$4)
B79: Non-Operating EBIT | C79: =ABS(C11/C$4) -> 0 | G79: =IF(G$4="","",G11/G$4) -> 0 | H79: =IF(H$4="","",H11/H$4) -> 0 | I79: =IF(I$4="","",I11/I$4) -> 0 | J79: =IF(J$4="","",J11/J$4) -> 0 | K79: =IF(K$4="","",K11/K$4) -> 0 | L79: =IF(L$4="","",L11/L$4) -> 0 | M79: =IF(M$4="","",M11/M$4) -> 0 | N79: =IF(N$4="","",N11/N$4) -> 0 | ... Q79: =IF(Q$4="","",Q11/Q$4)
B80: Net Interest Income | C80: =ABS(C12/C$4) -> 0.0022188189 | G80: =IF(G$4="","",ABS(G12/G$4)) -> 0.0021445556 | H80: =IF(H$4="","",ABS(H12/H$4)) -> 0.0041830494 | I80: =IF(I$4="","",ABS(I12/I$4)) -> 0.0041936117 | J80: =IF(J$4="","",ABS(J12/J$4)) -> 0.0015349458 | K80: =IF(K$4="","",ABS(K12/K$4)) -> 0.00059322915 | L80: =IF(L$4="","",ABS(L12/L$4)) -> 0.00072566832 | M80: =IF(M$4="","",ABS(M12/M$4)) -> 0.0017420807 | N80: =IF(N$4="","",ABS(N12/N$4)) -> 0 | ... Q80: =IF(Q$4="","",ABS(Q12/Q$4))
B81: Pre-tax Profit | C81: =C13/C4 -> 0.21117896 | G81: =IF(G$4="","",G13/G$4) -> 0.21445579 | H81: =IF(H$4="","",H13/H$4) -> 0.22489333 | I81: =IF(I$4="","",I13/I$4) -> 0.23171755 | J81: =IF(J$4="","",J13/J$4) -> 0.22242838 | K81: =IF(K$4="","",K13/K$4) -> 0.15623012 | L81: =IF(L$4="","",L13/L$4) -> 0.15801386 | M81: =IF(M$4="","",M13/M$4) -> 0.14112899 | N81: =IF(N$4="","",N13/N$4) -> 0.1145205 | ... Q81: =IF(Q$4="","",Q13/Q$4)
B82: Income Tax | C82: =ABS(C14/C$4) -> 0.05279474 | G82: =IF(G$4="","",ABS(G14/G$4)) -> 0.045788019 | H82: =IF(H$4="","",ABS(H14/H$4)) -> 0.044828169 | I82: =IF(I$4="","",ABS(I14/I$4)) -> 0.05070711 | J82: =IF(J$4="","",ABS(J14/J$4)) -> 0.041307339 | K82: =IF(K$4="","",ABS(K14/K$4)) -> 0.034589698 | L82: =IF(L$4="","",ABS(L14/L$4)) -> 0.027577552 | M82: =IF(M$4="","",ABS(M14/M$4)) -> 0.01759795 | N82: =IF(N$4="","",ABS(N14/N$4)) -> 0.0059435714 | ... Q82: =IF(Q$4="","",ABS(Q14/Q$4))
B83: =B15 -> NCI’s Share of Profits | C83: =MIN(BS!C62,MAX(G83:K83)) -> 0.010023684 | G83: =IF(G$4="","",-G15/G$4) -> 0.010023684 | H83: =IF(H$4="","",-H15/H$4) -> 0 | I83: =IF(I$4="","",-I15/I$4) -> 0 | J83: =IF(J$4="","",-J15/J$4) -> 0 | K83: =IF(K$4="","",-K15/K$4) -> 0 | L83: =IF(L$4="","",-L15/L$4) -> 0 | M83: =IF(M$4="","",-M15/M$4) -> 0 | N83: =IF(N$4="","",-N15/N$4) -> 0 | ... Q83: =IF(Q$4="","",-Q15/Q$4)
B84: After-tax Profit | C84: =ABS(C16/C$4) -> 0.14836054 | G84: =IF(G$4="","",ABS(G16/G$4)) -> 0.15864408 | H84: =IF(H$4="","",ABS(H16/H$4)) -> 0.18006516 | I84: =IF(I$4="","",ABS(I16/I$4)) -> 0.18101044 | J84: =IF(J$4="","",ABS(J16/J$4)) -> 0.18112104 | K84: =IF(K$4="","",ABS(K16/K$4)) -> 0.12164042 | L84: =IF(L$4="","",ABS(L16/L$4)) -> 0.13043631 | M84: =IF(M$4="","",ABS(M16/M$4)) -> 0.12353104 | N84: =IF(N$4="","",ABS(N16/N$4)) -> 0.10857693 | ... Q84: =IF(Q$4="","",ABS(Q16/Q$4))
B85: WCInv | C85: 0 | E85: =E17 -> WCInv is by default excluded
B86: Net Borrowing | C86: 0 | E86: =E18 -> Net borrowing is excluded
B87: Total FCFE | C87: =ABS(C19/C$4) -> 0.14836054 | G87: =IF(G$4="","",ABS(G19/G$4)) -> 0.15864408 | H87: =IF(H$4="","",ABS(H19/H$4)) -> 0.18006516 | I87: =IF(I$4="","",ABS(I19/I$4)) -> 0.18101044 | J87: =IF(J$4="","",ABS(J19/J$4)) -> 0.18112104 | K87: =IF(K$4="","",ABS(K19/K$4)) -> 0.12164042 | L87: =IF(L$4="","",ABS(L19/L$4)) -> 0.13043631 | M87: =IF(M$4="","",ABS(M19/M$4)) -> 0.12353104 | N87: =IF(N$4="","",ABS(N19/N$4)) -> 0.10857693 | ... Q87: =IF(Q$4="","",ABS(Q19/Q$4))
B89: Dividends
B90: ="Dividend per share ("&Market_currency&")" -> Dividend per share (CNY) | C90: =G90 -> 2.4 | G90: =Data!C65 -> 2.4 | H90: =Data!D65 -> 0 | I90: =Data!E65 -> 0 | J90: =Data!F65 -> 0 | K90: =Data!G65 -> 0 | L90: =Data!H65 -> 0 | M90: =Data!I65 -> 0 | N90: =Data!J65 -> 0 | ... Q90: =Data!M65
B91: ="Dividend ("&Market_currency&")" -> Dividend (CNY) | C91: =C90*Common_Shares/scaling_factor -> 1.1615309e+09 | G91: =IF(G$4="","",G90*Common_Shares/scaling_factor) -> 1.1615309e+09 | H91: =IF(H$4="","",H90*Common_Shares/scaling_factor) -> 0 | I91: =IF(I$4="","",I90*Common_Shares/scaling_factor) -> 0 | J91: =IF(J$4="","",J90*Common_Shares/scaling_factor) -> 0 | K91: =IF(K$4="","",K90*Common_Shares/scaling_factor) -> 0 | L91: =IF(L$4="","",L90*Common_Shares/scaling_factor) -> 0 | M91: =IF(M$4="","",M90*Common_Shares/scaling_factor) -> 0 | N91: =IF(N$4="","",N90*Common_Shares/scaling_factor) -> 0 | ... Q91: =IF(Q$4="","",Q90*Common_Shares/scaling_factor)
B92: Payout Ratio | C92: =C90/(C19*scaling_factor/Common_Shares) -> 0.55312015 | G92: =IF(G$4="","",G90/(G19*scaling_factor/Common_Shares)) -> 0.49995329 | H92: =IF(H$4="","",H90/(H19*scaling_factor/Common_Shares)) -> 0 | I92: =IF(I$4="","",I90/(I19*scaling_factor/Common_Shares)) -> 0 | J92: =IF(J$4="","",J90/(J19*scaling_factor/Common_Shares)) -> 0 | K92: =IF(K$4="","",K90/(K19*scaling_factor/Common_Shares)) -> 0 | L92: =IF(L$4="","",L90/(L19*scaling_factor/Common_Shares)) -> 0 | M92: =IF(M$4="","",M90/(M19*scaling_factor/Common_Shares)) -> 0 | N92: =IF(N$4="","",N90/(N19*scaling_factor/Common_Shares)) -> 0 | ... Q92: =IF(Q$4="","",Q90/(Q19*scaling_factor/Common_Shares))
B93: Dividend tax rate | C93: 0.1
B94: Dividend after tax Yield | C94: =(C90*(1-dividend_tax_rate))/Market_Price -> 0.039165911 | G94: =IF(G$4="","",(G90*(1-dividend_tax_rate))/Market_Price) -> 0.039165911 | H94: =IF(H$4="","",(H90*(1-dividend_tax_rate))/Market_Price) -> 0 | I94: =IF(I$4="","",(I90*(1-dividend_tax_rate))/Market_Price) -> 0 | J94: =IF(J$4="","",(J90*(1-dividend_tax_rate))/Market_Price) -> 0 | K94: =IF(K$4="","",(K90*(1-dividend_tax_rate))/Market_Price) -> 0 | L94: =IF(L$4="","",(L90*(1-dividend_tax_rate))/Market_Price) -> 0 | M94: =IF(M$4="","",(M90*(1-dividend_tax_rate))/Market_Price) -> 0 | N94: =IF(N$4="","",(N90*(1-dividend_tax_rate))/Market_Price) -> 0 | ... Q94: =IF(Q$4="","",(Q90*(1-dividend_tax_rate))/Market_Price)
B96: YoY %
B97: Sales | C97: =C4/G4-1 -> -0.03346978 | G97: =IF(H4="","",G4/H4-1) -> -0.011491087 | H97: =IF(I4="","",H4/I4-1) -> 0.055259893 | I97: =IF(J4="","",I4/J4-1) -> 0.070105044 | J97: =IF(K4="","",J4/K4-1) -> 0.19902695 | K97: =IF(L4="","",K4/L4-1) -> 2.0546801 | L97: =IF(M4="","",L4/M4-1) -> 0.033047794 | M97: =IF(N4="","",M4/N4-1) -> 0.091895643 | N97: =IF(O4="","",N4/O4-1) -> -0.0063837594 | ... Q97: =IF(R4="","",Q4/R4-1)
B98: Pre-tax Profit | C98: =C13/G13-1 -> -0.048238097 | G98: =IF(H5="","",G13/H13-1) -> -0.057368881 | H98: =IF(I5="","",H13/I13-1) -> 0.024181896 | I98: =IF(J5="","",I13/J13-1) -> 0.11479533 | J98: =IF(K5="","",J13/K13-1) -> 0.70708198 | K98: =IF(L5="","",K13/L13-1) -> 2.0201973 | L98: =IF(M5="","",L13/M13-1) -> 0.1566431 | M98: =IF(N5="","",M13/N13-1) -> 0.34559426 | N98: =IF(O5="","",N13/O13-1) -> 0.017789715 | ... Q98: =IF(R5="","",Q13/R13-1)
B100: Operating Efficiency Analysis | E100: Notes
B101: Balance Sheet | G101: Latest Asset Value
B102: Total Assets | C102: =BS!G32 -> 1.096834e+10 | G102: =IF(G$4="","",G106+G105) -> 1.096834e+10 | H102: =IF(H$4="","",H106+H105) -> 12386911594 | I102: =IF(I$4="","",I106+I105) -> 12497542169 | J102: =IF(J$4="","",J106+J105) -> 11532809144 | K102: =IF(K$4="","",K106+K105) -> 9595373074 | L102: =IF(L$4="","",L106+L105) -> 3514353524 | M102: =IF(M$4="","",M106+M105) -> 3297633120 | N102: =IF(N$4="","",N106+N105) -> 3506183194 | ... Q102: =IF(Q$4="","",Q106+Q105)
B103: Incl. AR | C103: =BS!C4 -> 91009310 | G103: =IF(G$4="","",Data!D77) -> 64628136 | H103: =IF(H$4="","",Data!E77) -> 65511539 | I103: =IF(I$4="","",Data!F77) -> 109244674 | J103: =IF(J$4="","",Data!G77) -> 114510542 | K103: =IF(K$4="","",Data!H77) -> 58261577 | L103: =IF(L$4="","",Data!I77) -> 0 | M103: =IF(M$4="","",Data!J77) -> 0 | N103: =IF(N$4="","",Data!K77) -> 0 | ... Q103: =IF(Q$4="","",Data!N77)
B104: Incl. Inventory | C104: =BS!C6+BS!C7 -> 2.1858356e+09 | G104: =IF(G$4="","",Data!D78) -> 2100354952 | H104: =IF(H$4="","",Data!E78) -> 2166477563 | I104: =IF(I$4="","",Data!F78) -> 1886751987 | J104: =IF(J$4="","",Data!G78) -> 1420570476 | K104: =IF(K$4="","",Data!H78) -> 364381375 | L104: =IF(L$4="","",Data!I78) -> 0 | M104: =IF(M$4="","",Data!J78) -> 0 | N104: =IF(N$4="","",Data!K78) -> 0 | ... Q104: =IF(Q$4="","",Data!N78)
B105: Total Liabilities | C105: =BS!G30 -> 8.5146816e+09 | G105: =Data!C79 -> 8.5146816e+09 | H105: =Data!D79 -> 8734763046 | I105: =Data!E79 -> 8874519390 | J105: =Data!F79 -> 8404513904 | K105: =Data!G79 -> 8026536570 | L105: =Data!H79 -> 2003002194 | M105: =Data!I79 -> 2135750535 | N105: =Data!J79 -> 2340923121 | ... Q105: =Data!M79
B106: Total Equity | C106: =BS!G27 -> 2.4536581e+09 | G106: =Data!C80 -> 2.4536581e+09 | H106: =Data!D80 -> 3652148548 | I106: =Data!E80 -> 3623022779 | J106: =Data!F80 -> 3128295240 | K106: =Data!G80 -> 1568836504 | L106: =Data!H80 -> 1511351330 | M106: =Data!I80 -> 1161882585 | N106: =Data!J80 -> 1165260073 | ... Q106: =Data!M80
B108: Operating Asset % of Sales | G108: Latest Asset Value
B109: AR | C109: =C103/C$4 -> 0.0064297329 | G109: =IF(G$4="","",G103/G$4) -> 0.0044131042 | H109: =IF(H$4="","",H103/H$4) -> 0.0044220224 | I109: =IF(I$4="","",I103/I$4) -> 0.0077814915 | J109: =IF(J$4="","",J103/J$4) -> 0.0087283962 | K109: =IF(K$4="","",K103/K$4) -> 0.0053247616 | L109: =IF(L$4="","",L103/L$4) -> 0 | M109: =IF(M$4="","",M103/M$4) -> 0 | N109: =IF(N$4="","",N103/N$4) -> 0 | ... Q109: =IF(Q$4="","",Q103/Q$4)
B110: Inventory | C110: =C104/C$4 -> 0.15442749 | G110: =IF(G$4="","",G104/G$4) -> 0.14342183 | H110: =IF(H$4="","",H104/H$4) -> 0.14623702 | I110: =IF(I$4="","",I104/I$4) -> 0.13439323 | J110: =IF(J$4="","",J104/J$4) -> 0.10828088 | K110: =IF(K$4="","",K104/K$4) -> 0.03330229 | L110: =IF(L$4="","",L104/L$4) -> 0 | M110: =IF(M$4="","",M104/M$4) -> 0 | N110: =IF(N$4="","",N104/N$4) -> 0 | ... Q110: =IF(Q$4="","",Q104/Q$4)
B111: Properties held for sale | C111: =BS!$G$38/C$4 -> 0 | G111: =BS!$G$38/G$4 -> 0
B113: Cash Flow Statement
B114: CFO/Net Income | G114: =IF(G$4="","",Data!C$22/Data!C15) -> 1.1301097 | H114: =IF(H$4="","",Data!D$22/Data!D15) -> 1.1421245 | I114: =IF(I$4="","",Data!E$22/Data!E15) -> 1.4506354 | J114: =IF(J$4="","",Data!F$22/Data!F15) -> 1.4858504 | K114: =IF(K$4="","",Data!G$22/Data!G15) -> 2.1056297 | L114: =IF(L$4="","",Data!H$22/Data!H15) -> 0.96876333 | M114: =IF(M$4="","",Data!I$22/Data!I15) -> 1.7670342 | N114: =IF(N$4="","",Data!J$22/Data!J15) -> 2.5144918 | ... Q114: =IF(Q$4="","",Data!M$22/Data!M15)
B115: CFO/FCFE | G115: =IF(G$4="","",Data!C$22/G19) -> 1.0941634 | H115: =IF(H$4="","",Data!D$22/H19) -> 1.1609338 | I115: =IF(I$4="","",Data!E$22/I19) -> 1.4767154 | J115: =IF(J$4="","",Data!F$22/J19) -> 1.5002156 | K115: =IF(K$4="","",Data!G$22/K19) -> 2.7722648 | L115: =IF(L$4="","",Data!H$22/L19) -> 1.5106172 | M115: =IF(M$4="","",Data!I$22/M19) -> 1.7378913 | N115: =IF(N$4="","",Data!J$22/N19) -> 2.3783646 | ... Q115: =IF(Q$4="","",Data!M$22/Q19)
...

Sheet DCF
B2: No-Growth DCF Valuation | H2: Notes
B3: No-Growth DCF | C3: =scaling_factor -> 1 | E3: Special Assumption
B4: Adjusted FCFE | C4: =Normalized_FCF!C19 -> 2.0999612e+09 | D4: =Reporting_currency -> CNY | E4: Terminal Growth Rate (g): | F4: =Terminal_Growth -> 0
B5: /Equity Cost of Capital | C5: =Equity_Cost -> 0.06
B6: Stable Income Value | C6: =(C4*(1+Terminal_Growth))/(Equity_Cost-Terminal_Growth) -> 3.4999354e+10 | D6: =Reporting_currency -> CNY | E6: Conservative Valuation: Setting g=0 can be a conservative assumption to avoid overestimating the stock’s value, especially if future growth is uncertain or unreliable.
B7: - Interest-bearing Debt | C7: =BS!G31 -> 1.235217e+08 | D7: =Reporting_currency -> CNY
B8: + Non-operating Cash | C8: =BS!D66 -> 51803896 | D8: =Reporting_currency -> CNY
B9: + Other Non-operating Assets | C9: =BS!H42 -> 29558001 | D9: =Reporting_currency -> CNY
B10: Equity Value | C10: =C6-C7+C8+C9 -> 3.4957194e+10 | D10: =Reporting_currency -> CNY
B11: * Exchange rate | C11: =Exchange_Rate -> 1 | D11: =Thesis!C15 -> CNY
B12: Equity Value per share | C12: =(C10*scaling_factor)/Common_Shares*Exchange_Rate -> 72.229906 | D12: =Market_currency -> CNY
B14: Implied Growth Scenario Analysis
B15: FCFE Projection
B16: High Growth Period (HGP) | C16: =Scenarios!C65 -> 0.046574871
B17: High Growth Rate (HGR) | C17: =Scenarios!C64 -> 10
B18: Value Per Share | C18: =(F52-C7+C8+C9)*Exchange_Rate/Common_Shares*scaling_factor -> 82.654784 | D18: =Market_currency -> CNY
B20: Year | C20: FCFE | D20: Growth Rates | E20: Discount Factor | F20: PV of FCFE
B21: 1 | C21: =C4*(1+D21) -> 2.1977667e+09 | D21: =IF($C$17<B21,0,DCF!$C$16) -> 0.046574871 | E21: =IF($C$17<B21,0,1/(1+Equity_Cost)^B21) -> 0.94339623 | F21: =C21*E21 -> 2.0733648e+09
B22: 2 | C22: =IF(ROW()-ROW($C$21)<$C$17, $C$21*(1+D22)^(ROW()-ROW($C$21)), 0) -> 2.3001274e+09 | D22: =IF($C$17<B22,0,DCF!$C$16) -> 0.046574871 | E22: =IF($C$17<B22,0,1/(1+Equity_Cost)^B22) -> 0.88999644 | F22: =C22*E22 -> 2.0471052e+09
B23: 3 | C23: =IF(ROW()-ROW($C$21)<$C$17, $C$21*(1+D23)^(ROW()-ROW($C$21)), 0) -> 2.4072555e+09 | D23: =IF($C$17<B23,0,DCF!$C$16) -> 0.046574871 | E23: =IF($C$17<B23,0,1/(1+Equity_Cost)^B23) -> 0.83961928 | F23: =C23*E23 -> 2.0211781e+09
B24: 4 | C24: =IF(ROW()-ROW($C$21)<$C$17, $C$21*(1+D24)^(ROW()-ROW($C$21)), 0) -> 2.5193731e+09 | D24: =IF($C$17<B24,0,DCF!$C$16) -> 0.046574871 | E24: =IF($C$17<B24,0,1/(1+Equity_Cost)^B24) -> 0.79209366 | F24: =C24*E24 -> 1.9955795e+09
B25: 5 | C25: =IF(ROW()-ROW($C$21)<$C$17, $C$21*(1+D25)^(ROW()-ROW($C$21)), 0) -> 2.6367126e+09 | D25: =IF($C$17<B25,0,DCF!$C$16) -> 0.046574871 | E25: =IF($C$17<B25,0,1/(1+Equity_Cost)^B25) -> 0.74725817 | F25: =C25*E25 -> 1.970305e+09
B26: 6 | C26: =IF(ROW()-ROW($C$21)<$C$17, $C$21*(1+D26)^(ROW()-ROW($C$21)), 0) -> 2.7595171e+09 | D26: =IF($C$17<B26,0,DCF!$C$16) -> 0.046574871 | E26: =IF($C$17<B26,0,1/(1+Equity_Cost)^B26) -> 0.70496054 | F26: =C26*E26 -> 1.9453507e+09
B27: 7 | C27: =IF(ROW()-ROW($C$21)<$C$17, $C$21*(1+D27)^(ROW()-ROW($C$21)), 0) -> 2.8880413e+09 | D27: =IF($C$17<B27,0,DCF!$C$16) -> 0.046574871 | E27: =IF($C$17<B27,0,1/(1+Equity_Cost)^B27) -> 0.66505711 | F27: =C27*E27 -> 1.9207124e+09
B28: 8 | C28: =IF(ROW()-ROW($C$21)<$C$17, $C$21*(1+D28)^(ROW()-ROW($C$21)), 0) -> 3.0225514e+09 | D28: =IF($C$17<B28,0,DCF!$C$16) -> 0.046574871 | E28: =IF($C$17<B28,0,1/(1+Equity_Cost)^B28) -> 0.62741237 | F28: =C28*E28 -> 1.8963862e+09
B29: 9 | C29: =IF(ROW()-ROW($C$21)<$C$17, $C$21*(1+D29)^(ROW()-ROW($C$21)), 0) -> 3.1633264e+09 | D29: =IF($C$17<B29,0,DCF!$C$16) -> 0.046574871 | E29: =IF($C$17<B29,0,1/(1+Equity_Cost)^B29) -> 0.59189846 | F29: =C29*E29 -> 1.872368e+09
B30: 10 | C30: =IF(ROW()-ROW($C$21)<$C$17, $C$21*(1+D30)^(ROW()-ROW($C$21)), 0) -> 3.3106579e+09 | D30: =IF($C$17<B30,0,DCF!$C$16) -> 0.046574871 | E30: =IF($C$17<B30,0,1/(1+Equity_Cost)^B30) -> 0.55839478 | F30: =C30*E30 -> 1.8486541e+09
B31: 11 | C31: =IF(ROW()-ROW($C$21)<$C$17, $C$21*(1+D31)^(ROW()-ROW($C$21)), 0) -> 0 | D31: =IF($C$17<B31,0,DCF!$C$16) -> 0 | E31: =IF($C$17<B31,0,1/(1+Equity_Cost)^B31) -> 0 | F31: =C31*E31 -> 0
B32: 12 | C32: =IF(ROW()-ROW($C$21)<$C$17, $C$21*(1+D32)^(ROW()-ROW($C$21)), 0) -> 0 | D32: =IF($C$17<B32,0,DCF!$C$16) -> 0 | E32: =IF($C$17<B32,0,1/(1+Equity_Cost)^B32) -> 0 | F32: =C32*E32 -> 0
B33: 13 | C33: =IF(ROW()-ROW($C$21)<$C$17, $C$21*(1+D33)^(ROW()-ROW($C$21)), 0) -> 0 | D33: =IF($C$17<B33,0,DCF!$C$16) -> 0 | E33: =IF($C$17<B33,0,1/(1+Equity_Cost)^B33) -> 0 | F33: =C33*E33 -> 0
... B50: 30 | C50: =IF(ROW()-ROW($C$21)<$C$17, $C$21*(1+D50)^(ROW()-ROW($C$21)), 0) -> 0 | D50: =IF($C$17<B50,0,DCF!$C$16) -> 0 | E50: =IF($C$17<B50,0,1/(1+Equity_Cost)^B50) -> 0 | F50: =C50*E50 -> 0
B51: Terminal Year | C51: =C$21*(1+Terminal_Growth)^$C$17/Equity_Cost -> 3.6629444e+10 | D51: =Terminal_Growth -> 0 | E51: =1/(1+Equity_Cost)^C17 -> 0.55839478 | F51: =C51*E51 -> 2.045369e+10
E52: Total PV | F52: =SUM(F21:F51) -> 4.0044694e+10
B54: Sensitivity Analysis (Enterprise Value)
A55: =F52 -> 4.0044694e+10 | B55: =C78 -> 0 | C55: =C77 -> 0.02 | D55: =C76 -> 0.04 | E55: =C75 -> 0.06 | F55: =C74 -> 0.1
A56: 5 | B56: 3.4999354e+10 | C56: 3.6045913e+10 | D56: 3.7119915e+10 | E56: 3.8222573e+10 | F56: 4.0518897e+10
A57: 10 | B57: 3.4999354e+10 | C57: 3.703359e+10 | D57: 3.9264419e+10 | E57: 4.1715676e+10 | F57: 4.7388511e+10
A58: 15 | B58: 3.4999354e+10 | C58: 3.837284e+10 | D58: 4.2327055e+10 | E58: 4.6979667e+10 | F58: 5.8973005e+10
A59: 20 | B59: 3.4999354e+10 | C59: 3.9869617e+10 | D59: 4.5943125e+10 | E59: 5.3566967e+10 | F59: 7.5393318e+10
A60: 25 | B60: 3.4999354e+10 | C60: 4.139732e+10 | D60: 4.9852155e+10 | E60: 6.1143121e+10 | F60: 9.7006894e+10
A61: 30 | B61: 3.4999354e+10 | C61: 4.2876534e+10 | D61: 5.3870461e+10 | E61: 6.9458204e+10 | F61: 1.2440224e+11
B63: Sensitivity Analysis (Equity Value per share)
B64: =B55 -> 0 | C64: =C55 -> 0.02 | D64: =D55 -> 0.04 | E64: =E55 -> 0.06 | F64: =F55 -> 0.1
A65: 0 | B65: =C12 -> 72.229906 | C65: =C12 -> 72.229906 | D65: =C12 -> 72.229906 | E65: =C12 -> 72.229906 | F65: =C12 -> 72.229906
A66: =A56 -> 5 | B66: =(B56-$C$7+$C$8+$C$9)/Common_Shares*$C$3*Exchange_Rate -> 72.229906 | C66: =(C56-$C$7+$C$8+$C$9)/Common_Shares*$C$3*Exchange_Rate -> 74.392346 | D66: =(D56-$C$7+$C$8+$C$9)/Common_Shares*$C$3*Exchange_Rate -> 76.611491 | E66: =(E56-$C$7+$C$8+$C$9)/Common_Shares*$C$3*Exchange_Rate -> 78.889845 | F66: =(F56-$C$7+$C$8+$C$9)/Common_Shares*$C$3*Exchange_Rate -> 83.6346
A67: =A57 -> 10 | B67: =(B57-$C$7+$C$8+$C$9)/Common_Shares*$C$3*Exchange_Rate -> 72.229906 | C67: =(C57-$C$7+$C$8+$C$9)/Common_Shares*$C$3*Exchange_Rate -> 76.433123 | D67: =(D57-$C$7+$C$8+$C$9)/Common_Shares*$C$3*Exchange_Rate -> 81.042549 | E67: =(E57-$C$7+$C$8+$C$9)/Common_Shares*$C$3*Exchange_Rate -> 86.107431 | F67: =(F57-$C$7+$C$8+$C$9)/Common_Shares*$C$3*Exchange_Rate -> 97.828862
A68: =A58 -> 15 | B68: =(B58-$C$7+$C$8+$C$9)/Common_Shares*$C$3*Exchange_Rate -> 72.229906 | C68: =(C58-$C$7+$C$8+$C$9)/Common_Shares*$C$3*Exchange_Rate -> 79.200334 | D68: =(D58-$C$7+$C$8+$C$9)/Common_Shares*$C$3*Exchange_Rate -> 87.370686 | E68: =(E58-$C$7+$C$8+$C$9)/Common_Shares*$C$3*Exchange_Rate -> 96.984091 | F68: =(F58-$C$7+$C$8+$C$9)/Common_Shares*$C$3*Exchange_Rate -> 121.76519
A69: =A59 -> 20 | B69: =(B59-$C$7+$C$8+$C$9)/Common_Shares*$C$3*Exchange_Rate -> 72.229906 | C69: =(C59-$C$7+$C$8+$C$9)/Common_Shares*$C$3*Exchange_Rate -> 82.293031 | D69: =(D59-$C$7+$C$8+$C$9)/Common_Shares*$C$3*Exchange_Rate -> 94.842349 | E69: =(E59-$C$7+$C$8+$C$9)/Common_Shares*$C$3*Exchange_Rate -> 110.59503 | F69: =(F59-$C$7+$C$8+$C$9)/Common_Shares*$C$3*Exchange_Rate -> 155.69348
A70: =A60 -> 25 | B70: =(B60-$C$7+$C$8+$C$9)/Common_Shares*$C$3*Exchange_Rate -> 72.229906 | C70: =(C60-$C$7+$C$8+$C$9)/Common_Shares*$C$3*Exchange_Rate -> 85.449631 | D70: =(D60-$C$7+$C$8+$C$9)/Common_Shares*$C$3*Exchange_Rate -> 102.91934 | E70: =(E60-$C$7+$C$8+$C$9)/Common_Shares*$C$3*Exchange_Rate -> 126.24917 | F70: =(F60-$C$7+$C$8+$C$9)/Common_Shares*$C$3*Exchange_Rate -> 200.35228
A71: =A61 -> 30 | B71: =(B61-$C$7+$C$8+$C$9)/Common_Shares*$C$3*Exchange_Rate -> 72.229906 | C71: =(C61-$C$7+$C$8+$C$9)/Common_Shares*$C$3*Exchange_Rate -> 88.50604 | D71: =(D61-$C$7+$C$8+$C$9)/Common_Shares*$C$3*Exchange_Rate -> 111.22212 | E71: =(E61-$C$7+$C$8+$C$9)/Common_Shares*$C$3*Exchange_Rate -> 143.43011 | F71: =(F61-$C$7+$C$8+$C$9)/Common_Shares*$C$3*Exchange_Rate -> 256.95761
B73: Scenarios | C73: HGR | D73: HGP | E73: Value per share | F73: Probabilities
B74: =Scenarios!B54 -> Snowball Scenario | C74: =Scenarios!C56 -> 0.1 | D74: =Scenarios!C55 -> 15 | E74: =INDEX(B$65:F$71, MATCH(D74, A$65:A$71, 0), MATCH(C74, B$64:F$64, 0)) -> 121.76519 | F74: =Scenarios!C58 -> 0.05
B75: =Scenarios!B36 -> Optimistic | C75: =Scenarios!C38 -> 0.06 | D75: =Scenarios!C37 -> 10 | E75: =INDEX(B$65:F$71, MATCH(D75, A$65:A$71, 0), MATCH(C75, B$64:F$64, 0)) -> 86.107431 | F75: =Scenarios!C40*(1-F$74-F$78) -> 0.18
B76: =Scenarios!B24 -> Base | C76: =Scenarios!C26 -> 0.04 | D76: =Scenarios!C25 -> 10 | E76: =INDEX(B$65:F$71, MATCH(D76, A$65:A$71, 0), MATCH(C76, B$64:F$64, 0)) -> 81.042549 | F76: =Scenarios!C28*(1-F$74-F$78) -> 0.54
B77: =Scenarios!B30 -> Pessimistic | C77: =Scenarios!C32 -> 0.02 | D77: =Scenarios!C31 -> 10 | E77: =INDEX(B$65:F$71, MATCH(D77, A$65:A$71, 0), MATCH(C77, B$64:F$64, 0)) -> 76.433123 | F77: =Scenarios!C34*(1-F$74-F$78) -> 0.18
B78: =Scenarios!B48 -> Devil's advocate | C78: =Scenarios!C50 -> 0 | D78: =Scenarios!C49 -> 15 | E78: =INDEX(B$65:F$71, MATCH(D78, A$65:A$71, 0), MATCH(C78, B$64:F$64, 0)) -> 72.229906 | F78: =Scenarios!C52 -> 0.05
B80: Note of the formulas: | C80: MATCH(1%, C65:E65, 0) finds the column number for HGR = 1%.
C81: MATCH(5, B66:B69, 0) finds the row number for HGP = 5.
C82: INDEX(C66:E69, ...) retrieves the value from the specified range.

Sheet DDM
B2: No-Growth DDM Valuation | H2: Notes
B3: No-Growth DDM | C3: =scaling_factor -> 1 | E3: Special Assumption
B4: Dividend | C4: =Normalized_FCF!C91*(1-dividend_tax_rate) -> 1.0453778e+09 | D4: =Market_currency -> CNY | E4: Terminal Growth Rate (g): | F4: =Thesis!E22 -> 0
B5: /Equity Cost of Capital | C5: =Equity_Cost -> 0.06
B6: Dividend Value | C6: =(C4*(1+Terminal_Growth))/(Equity_Cost-Terminal_Growth) -> 17422963128 | D6: =Reporting_currency -> CNY
B7: Dividend Value per share | C7: =(C6*scaling_factor)/Common_Shares*Exchange_Rate -> 36 | D7: =Market_currency -> CNY
B9: Implied Growth Scenario Analysis
B10: FCFE Projection
B11: High Growth Period (HGP) | C11: =Scenarios!C65 -> 0.046574871
B12: High Growth Rate (HGR) | C12: =Scenarios!C64 -> 10
B13: Value Per Share | C13: =F47/Common_Shares*scaling_factor -> 41.189589 | D13: =Market_currency -> CNY
B15: Year | C15: Dividends | D15: Growth Rates | E15: Discount Factor | F15: PV of Dividends
B16: 1 | C16: =C4*(1+D16) -> 1.0940661e+09 | D16: =IF($C$12<B16,0,DDM!$C$11) -> 0.046574871 | E16: =IF($C$12<B16,0,1/(1+Equity_Cost)^B16) -> 0.94339623 | F16: =C16*E16 -> 1.0321379e+09
B17: 2 | C17: =IF(ROW()-ROW($C$16)<$C$12, $C$16*(1+D17)^(ROW()-ROW($C$16)), 0) -> 1.1450221e+09 | D17: =IF($C$12<B17,0,DDM!$C$11) -> 0.046574871 | E17: =IF($C$12<B17,0,1/(1+Equity_Cost)^B17) -> 0.88999644 | F17: =C17*E17 -> 1.0190656e+09
B18: 3 | C18: =IF(ROW()-ROW($C$16)<$C$12, $C$16*(1+D18)^(ROW()-ROW($C$16)), 0) -> 1.1983514e+09 | D18: =IF($C$12<B18,0,DDM!$C$11) -> 0.046574871 | E18: =IF($C$12<B18,0,1/(1+Equity_Cost)^B18) -> 0.83961928 | F18: =C18*E18 -> 1.0061589e+09
B19: 4 | C19: =IF(ROW()-ROW($C$16)<$C$12, $C$16*(1+D19)^(ROW()-ROW($C$16)), 0) -> 1.2541644e+09 | D19: =IF($C$12<B19,0,DDM!$C$11) -> 0.046574871 | E19: =IF($C$12<B19,0,1/(1+Equity_Cost)^B19) -> 0.79209366 | F19: =C19*E19 -> 9.934157e+08
B20: 5 | C20: =IF(ROW()-ROW($C$16)<$C$12, $C$16*(1+D20)^(ROW()-ROW($C$16)), 0) -> 1.312577e+09 | D20: =IF($C$12<B20,0,DDM!$C$11) -> 0.046574871 | E20: =IF($C$12<B20,0,1/(1+Equity_Cost)^B20) -> 0.74725817 | F20: =C20*E20 -> 9.8083387e+08
B21: 6 | C21: =IF(ROW()-ROW($C$16)<$C$12, $C$16*(1+D21)^(ROW()-ROW($C$16)), 0) -> 1.3737101e+09 | D21: =IF($C$12<B21,0,DDM!$C$11) -> 0.046574871 | E21: =IF($C$12<B21,0,1/(1+Equity_Cost)^B21) -> 0.70496054 | F21: =C21*E21 -> 9.684114e+08
B22: 7 | C22: =IF(ROW()-ROW($C$16)<$C$12, $C$16*(1+D22)^(ROW()-ROW($C$16)), 0) -> 1.4376904e+09 | D22: =IF($C$12<B22,0,DDM!$C$11) -> 0.046574871 | E22: =IF($C$12<B22,0,1/(1+Equity_Cost)^B22) -> 0.66505711 | F22: =C22*E22 -> 9.5614626e+08
B23: 8 | C23: =IF(ROW()-ROW($C$16)<$C$12, $C$16*(1+D23)^(ROW()-ROW($C$16)), 0) -> 1.5046507e+09 | D23: =IF($C$12<B23,0,DDM!$C$11) -> 0.046574871 | E23: =IF($C$12<B23,0,1/(1+Equity_Cost)^B23) -> 0.62741237 | F23: =C23*E23 -> 9.4403646e+08
B24: 9 | C24: =IF(ROW()-ROW($C$16)<$C$12, $C$16*(1+D24)^(ROW()-ROW($C$16)), 0) -> 1.5747296e+09 | D24: =IF($C$12<B24,0,DDM!$C$11) -> 0.046574871 | E24: =IF($C$12<B24,0,1/(1+Equity_Cost)^B24) -> 0.59189846 | F24: =C24*E24 -> 9.3208003e+08
B25: 10 | C25: =IF(ROW()-ROW($C$16)<$C$12, $C$16*(1+D25)^(ROW()-ROW($C$16)), 0) -> 1.6480724e+09 | D25: =IF($C$12<B25,0,DDM!$C$11) -> 0.046574871 | E25: =IF($C$12<B25,0,1/(1+Equity_Cost)^B25) -> 0.55839478 | F25: =C25*E25 -> 9.2027504e+08
B26: 11 | C26: =IF(ROW()-ROW($C$16)<$C$12, $C$16*(1+D26)^(ROW()-ROW($C$16)), 0) -> 0 | D26: =IF($C$12<B26,0,DDM!$C$11) -> 0 | E26: =IF($C$12<B26,0,1/(1+Equity_Cost)^B26) -> 0 | F26: =C26*E26 -> 0
B27: 12 | C27: =IF(ROW()-ROW($C$16)<$C$12, $C$16*(1+D27)^(ROW()-ROW($C$16)), 0) -> 0 | D27: =IF($C$12<B27,0,DDM!$C$11) -> 0 | E27: =IF($C$12<B27,0,1/(1+Equity_Cost)^B27) -> 0 | F27: =C27*E27 -> 0
B28: 13 | C28: =IF(ROW()-ROW($C$16)<$C$12, $C$16*(1+D28)^(ROW()-ROW($C$16)), 0) -> 0 | D28: =IF($C$12<B28,0,DDM!$C$11) -> 0 | E28: =IF($C$12<B28,0,1/(1+Equity_Cost)^B28) -> 0 | F28: =C28*E28 -> 0
... B45: 30 | C45: =IF(ROW()-ROW($C$16)<$C$12, $C$16*(1+D45)^(ROW()-ROW($C$16)), 0) -> 0 | D45: =IF($C$12<B45,0,DDM!$C$11) -> 0 | E45: =IF($C$12<B45,0,1/(1+Equity_Cost)^B45) -> 0 | F45: =C45*E45 -> 0
B46: Terminal Year | C46: =C$16*(1+F4)^$C$12/Equity_Cost -> 1.8234435e+10 | D46: =Terminal_Growth -> 0 | E46: =1/(1+Equity_Cost)^C12 -> 0.55839478 | F46: =C46*E46 -> 1.0182013e+10
E47: Total PV | F47: =SUM(F16:F46) -> 1.9934575e+10
B49: Sensitivity Analysis (Enterprise Value)
A50: =F47 -> 1.9934575e+10 | B50: =C73 -> 0 | C50: =C72 -> 0.02 | D50: =C71 -> 0.04 | E50: =C70 -> 0.06 | F50: =C69 -> 0.1
A51: 5 | B51: 1.7422963e+10 | C51: 1.7943949e+10 | D51: 1.8478595e+10 | E51: 1.9027508e+10 | F51: 2.0170637e+10
A52: 10 | B52: 1.7422963e+10 | C52: 1.8435622e+10 | D52: 1.9546147e+10 | E52: 2.0766403e+10 | F52: 2.3590386e+10
A53: 15 | B53: 1.7422963e+10 | C53: 1.9102312e+10 | D53: 2.1070753e+10 | E53: 2.338686e+10 | F53: 2.9357241e+10
A54: 20 | B54: 1.7422963e+10 | C54: 1.9847419e+10 | D54: 2.2870861e+10 | E54: 2.6666072e+10 | F54: 3.7531407e+10
A55: 25 | B55: 1.7422963e+10 | C55: 2.0607923e+10 | D55: 2.4816808e+10 | E55: 3.0437543e+10 | F55: 4.8290821e+10
A56: 30 | B56: 1.7422963e+10 | C56: 2.1344287e+10 | D56: 2.6817154e+10 | E56: 3.4576859e+10 | F56: 6.1928448e+10
B58: Sensitivity Analysis (Equity Value per share)
B59: =B50 -> 0 | C59: =C50 -> 0.02 | D59: =D50 -> 0.04 | E59: =E50 -> 0.06 | F59: =F50 -> 0.1
A60: 0 | B60: =C7 -> 36 | C60: =C7 -> 36 | D60: =C7 -> 36 | E60: =C7 -> 36 | F60: =C7 -> 36
A61: =A51 -> 5 | B61: =B51/Common_Shares*$C$3*Exchange_Rate -> 36 | C61: =C51/Common_Shares*$C$3*Exchange_Rate -> 37.07648 | D61: =D51/Common_Shares*$C$3*Exchange_Rate -> 38.181188 | E61: =E51/Common_Shares*$C$3*Exchange_Rate -> 39.315372 | F61: =F51/Common_Shares*$C$3*Exchange_Rate -> 41.677349
A62: =A52 -> 10 | B62: =B52/Common_Shares*$C$3*Exchange_Rate -> 36 | C62: =C52/Common_Shares*$C$3*Exchange_Rate -> 38.092395 | D62: =D52/Common_Shares*$C$3*Exchange_Rate -> 40.387005 | E62: =E52/Common_Shares*$C$3*Exchange_Rate -> 42.908345 | F62: =F52/Common_Shares*$C$3*Exchange_Rate -> 48.743368
A63: =A53 -> 15 | B63: =B53/Common_Shares*$C$3*Exchange_Rate -> 36 | C63: =C53/Common_Shares*$C$3*Exchange_Rate -> 39.469935 | D63: =D53/Common_Shares*$C$3*Exchange_Rate -> 43.537203 | E63: =E53/Common_Shares*$C$3*Exchange_Rate -> 48.322835 | F63: =F53/Common_Shares*$C$3*Exchange_Rate -> 60.659067
A64: =A54 -> 20 | B64: =B54/Common_Shares*$C$3*Exchange_Rate -> 36 | C64: =C54/Common_Shares*$C$3*Exchange_Rate -> 41.009505 | D64: =D54/Common_Shares*$C$3*Exchange_Rate -> 47.256658 | E64: =E54/Common_Shares*$C$3*Exchange_Rate -> 55.098468 | F64: =F54/Common_Shares*$C$3*Exchange_Rate -> 77.548844
A65: =A55 -> 25 | B65: =B55/Common_Shares*$C$3*Exchange_Rate -> 36 | C65: =C55/Common_Shares*$C$3*Exchange_Rate -> 42.580887 | D65: =D55/Common_Shares*$C$3*Exchange_Rate -> 51.277449 | E65: =E55/Common_Shares*$C$3*Exchange_Rate -> 62.891228 | F65: =F55/Common_Shares*$C$3*Exchange_Rate -> 99.780362
A66: =A56 -> 30 | B66: =B56/Common_Shares*$C$3*Exchange_Rate -> 36 | C66: =C56/Common_Shares*$C$3*Exchange_Rate -> 44.102392 | D66: =D56/Common_Shares*$C$3*Exchange_Rate -> 55.41064 | E66: =E56/Common_Shares*$C$3*Exchange_Rate -> 71.444043 | F66: =F56/Common_Shares*$C$3*Exchange_Rate -> 127.95895
B68: Scenarios | C68: HGR | D68: HGP | E68: Value per share | F68: Probabilities
B69: =Scenarios!B54 -> Snowball Scenario | C69: =Scenarios!C56 -> 0.1 | D69: =Scenarios!C55 -> 15 | E69: =INDEX(B$60:F$66, MATCH(D69, A$60:A$66, 0), MATCH(C69, B$59:F$59, 0)) -> 60.659067 | F69: =Scenarios!C58 -> 0.05
B70: =Scenarios!B36 -> Optimistic | C70: =Scenarios!C38 -> 0.06 | D70: =Scenarios!C37 -> 10 | E70: =INDEX(B$60:F$66, MATCH(D70, A$60:A$66, 0), MATCH(C70, B$59:F$59, 0)) -> 42.908345 | F70: =Scenarios!C40*(1-F$69-F$73) -> 0.18
B71: =Scenarios!B24 -> Base | C71: =Scenarios!C26 -> 0.04 | D71: =Scenarios!C25 -> 10 | E71: =INDEX(B$60:F$66, MATCH(D71, A$60:A$66, 0), MATCH(C71, B$59:F$59, 0)) -> 40.387005 | F71: =Scenarios!C28*(1-F$69-F$73) -> 0.54
B72: =Scenarios!B30 -> Pessimistic | C72: =Scenarios!C32 -> 0.02 | D72: =Scenarios!C31 -> 10 | E72: =INDEX(B$60:F$66, MATCH(D72, A$60:A$66, 0), MATCH(C72, B$59:F$59, 0)) -> 38.092395 | F72: =Scenarios!C34*(1-F$69-F$73) -> 0.18
B73: =Scenarios!B48 -> Devil's advocate | C73: =Scenarios!C50 -> 0 | D73: =Scenarios!C49 -> 15 | E73: =INDEX(B$60:F$66, MATCH(D73, A$60:A$66, 0), MATCH(C73, B$59:F$59, 0)) -> 36 | F73: =Scenarios!C52 -> 0.05
B75: Note of the formulas: | C75: MATCH(1%, C65:E65, 0) finds the column number for HGR = 1%.
C76: MATCH(5, B66:B69, 0) finds the row number for HGP = 5.
C77: INDEX(C66:E69, ...) retrieves the value from the specified range.

Sheet Scenarios
B2: Current Situation | H2: Warning: Do Not Remove this logic
B3: Selection | H3: 0 | I3: =-Market_Price -> -55.15
B4: Past Years Selected | C4: 3 | E4: Tie the business story into the three levers of value: FCFE, growth and risk. | H4: 1 | I4: =IF(ROW()-3 < $C$76, $C$77, IF(ROW()-3 = $C$76, $C$77 + $C$60, "")) -> 2.16
H5: 2 | I5: =IF(ROW()-3 < $C$76, $C$77, IF(ROW()-3 = $C$76, $C$77 + $C$60, "")) -> 2.16
B6: Latest | C6: =DCF!C3 -> 1 | E6: Prompt for fundamental Analysis | H6: 3 | I6: =IF(ROW()-3 < $C$76, $C$77, IF(ROW()-3 = $C$76, $C$77 + $C$60, "")) -> 84.880031
B7: EBIT | C7: =Normalized_FCF!G8 -> 3109212579 | D7: =Reporting_currency -> CNY | E7: ="Please develop three logical "&C18&"-year scenarios (Base Case, Pessimistic Case, Optimistic Case) and two extreme "&C46&"-year scenarios (Success Scenario, Devil’s Advocate Scenario) for "&Thesis!C5&"("&Thesis!C11&"). Each scenario should include the Compound Growth Rate, the Probability Assessment, and the Business Narrative." -> Please develop three logical 10-year scenarios (Base Case, Pessimistic Case, Optimistic Case) and two extreme 15-year scenarios (Success Scenario, Devil’s Advocate Scenario) for 重庆啤酒(600132.SS). Each scenario should include the Compound Growth Rate, the Probability Assessment, and the Business Narrative. | H7: 4 | I7: =IF(ROW()-3 < $C$76, $C$77, IF(ROW()-3 = $C$76, $C$77 + $C$60, ""))
B8: FCFE | C8: =Normalized_FCF!G19 -> 2.3232788e+09 | D8: =Reporting_currency -> CNY | H8: 5 | I8: =IF(ROW()-3 < $C$76, $C$77, IF(ROW()-3 = $C$76, $C$77 + $C$60, ""))
B9: Normalized | C9: =Normalized_FCF!C19 -> 2.0999612e+09 | D9: =Reporting_currency -> CNY | H9: 6 | I9: =IF(ROW()-3 < $C$76, $C$77, IF(ROW()-3 = $C$76, $C$77 + $C$60, ""))
H10: 7 | I10: =IF(ROW()-3 < $C$76, $C$77, IF(ROW()-3 = $C$76, $C$77 + $C$60, ""))
B11: YoY CAGR | H11: 8 | I11: =IF(ROW()-3 < $C$76, $C$77, IF(ROW()-3 = $C$76, $C$77 + $C$60, ""))
B12: Sales | C12: =(Normalized_FCF!G4/OFFSET(Normalized_FCF!G4, 0, $C$4))^(1/$C$4) - 1 -> 0.037342435 | H12: 9 | I12: =IF(ROW()-3 < $C$76, $C$77, IF(ROW()-3 = $C$76, $C$77 + $C$60, ""))
B13: Operating EBIT | C13: =(Normalized_FCF!G8/OFFSET(Normalized_FCF!G8, 0, $C$4))^(1/$C$4) - 1 -> 0.023730241 | H13: 10 | I13: =IF(ROW()-3 < $C$76, $C$77, IF(ROW()-3 = $C$76, $C$77 + $C$60, ""))
B14: FCFE | C14: =(Normalized_FCF!G19/OFFSET(Normalized_FCF!G19, 0, $C$4))^(1/$C$4) - 1 -> -0.0074772486
B16: General Scenarios
B17: Assumption | E17: Guidance Note
B18: High Growth Period (HGP) | C18: 10 | E18: Fundamental analysis and market signal analysis should be combined, with fundamental analysis given priority and market signal analysis serving as a supplement. Market signal analysis predicts a company's future trend, while fundamental analysis interprets the trend and identifies relevant fundamental factors and possibilities.
B20: Reference
B21: Market Price | C21: =Market_Price -> 55.15 | D21: =Market_currency -> CNY
B22: No Growth Value per share | C22: =IF(valuation_method="DCF",DCF!C12,DDM!C7) -> 72.229906 | D22: =Market_currency -> CNY
B24: Base | E24: Business Story
B25: High Growth Period (HGP) | C25: =C18 -> 10
B26: High Growth Rate (HGR) | C26: 0.04
B27: Value per share | C27: =IF(valuation_method="DCF",DCF!E76,DDM!E71) -> 81.042549 | D27: =Market_currency -> CNY
B28: Probabilities | C28: 0.6
B30: Pessimistic | E30: Business Story
B31: High Growth Period (HGP) | C31: =C18 -> 10
B32: High Growth Rate (HGR) | C32: 0.02
B33: Value per share | C33: =IF(valuation_method="DCF",DCF!E77,DDM!E72) -> 76.433123 | D33: =Market_currency -> CNY
B34: Probabilities | C34: 0.2
B36: Optimistic | E36: Business Story
B37: High Growth Period (HGP) | C37: =C18 -> 10
B38: High Growth Rate (HGR) | C38: 0.06
B39: Value per share | C39: =IF(valuation_method="DCF",DCF!E75,DDM!E70) -> 86.107431 | D39: =Market_currency -> CNY
B40: Probabilities | C40: =1-C28-C34 -> 0.2
B42: Expected Value = | C42: =C27*C28+C33*C34+C39*C40 -> 81.13364 | D42: =Market_currency -> CNY
B44: Extreme Scenarios
B45: Assumption
B46: High Growth Period (HGP) | C46: 15
B48: Devil's advocate | E48: Business Story
B49: High Growth Period (HGP) | C49: =C46 -> 15
B50: High Growth Rate (HGR) | C50: 0
B51: Value per share | C51: =IF(valuation_method="DCF",DCF!E78,DDM!E73) -> 72.229906 | D51: =Market_currency -> CNY
B52: Probabilities | C52: 0.05
B54: Snowball Scenario | E54: Business Story
B55: High Growth Period (HGP) | C55: =C46 -> 15
B56: High Growth Rate (HGR) | C56: 0.1
B57: Value per share | C57: =IF(valuation_method="DCF",DCF!E74,DDM!E69) -> 121.76519 | D57: =Market_currency -> CNY
B58: Probabilities | C58: 0.05
B60: Expected Value = | C60: =C51*C52+C57*C58+C42*(1-C52-C58) -> 82.720031 | D60: =Market_currency -> CNY | E60: is assumed to be materialized in | F60: =Thesis!F28 -> 3
B62: Growth Classification
B63: Equity Value Driving Factors | E63: Note on Manual Adjustments
B64: High Growth Period (HGP) | C64: =C18 -> 10 | E64: Use general Scenarios' HGP assumption
B65: High Growth Rate (HGR) | C65: 0.046574871 | E65: Use Excel Goal Seek to find the HGR
B66: Equity Value per share | C66: =IF(valuation_method="DCF",DCF!C18,DDM!C13) -> 82.654784 | D66: =Market_currency -> CNY | E66: Set to Expected Equity Value
B68: Type of Company | E68: Note on the logic
B69: Negative Growth | C69: =IF(C60<C22,"Y","N") -> N
B70: Low Growth | C70: =IF(C69="Y","N",IF(C65>8%,"N","Y")) -> Y | E70: >8% is Categorized as High Growth
B71: High Growth | C71: =IF(C65>8%,"Y","N") -> N
B72: Asset Play | C72: =IF(F72>50%,"Y","N") -> N | E72: The Non-FCF Value is of the Expected Value, at | F72: =BS!D89/C60 -> -0.0010530971
B74: Margin of Safety (MOS)
B75: Inputs
B76: Expected Holding Period | C76: =F60 -> 3
B77: After-tax Dividend per share | C77: =Normalized_FCF!C90*(1-dividend_tax_rate) -> 2.16 | D77: =Market_currency -> CNY
B79: Target Price Output
B80: @Target Annual Return | C80: =Thesis!F29 -> 0.337
B81: PV(Dividends) | C81: =PV(C80, C76, -C77, 0) -> 3.7276755
B82: PV(Equity Value) | C82: =C60/(1+C80)^C76 -> 34.611185
B83: Buy Below | C83: =C81+C82 -> 38.33886 | D83: =Market_currency -> CNY | E83: at a MOS of | F83: =(1-C83/C60) -> 0.53652265
B85: Current Return Output
B86: @Market Price | C86: =Market_Price -> 55.15 | D86: =Market_currency -> CNY
B87: Annual Return | C87: =IRR(OFFSET($I$3, 0, 0, $C$76 + 1, 1)) -> 0.17920704
B89: Entry Price Output
B90: @ Entry Yield | C90: =Thesis!F30 -> 0.187
B91: PV(Dividends) | C91: =PV(C90, C76, -C77, 0) -> 4.6442708
B92: PV(Equity Value) | C92: =C60/(1+C90)^C76 -> 49.460503
B93: Buy Below | C93: =C91+C92 -> 54.104774 | D93: =Market_currency -> CNY | E93: at a MOS of | F93: =(1-C93/C60) -> 0.34592899
B95: Sell Price Output
B96: @Selling Yield | C96: =Thesis!F31 -> 0.06
B97: PV(Dividends) | C97: =PV(C96, C76, -C77, 0) -> 5.7737058
B98: PV(Equity Value) | C98: =C60/(1+C96)^C76 -> 69.453333
B99: Sell Above | C99: =C97+C98 -> 75.227039 | D99: HKD | E99: at a MOS of | F99: =(1-C99/C60) -> 0.090582559
B101: Exit Price Output
B102: @Benchmark Yield | C102: =Thesis!F32 -> 0.087
B103: PV(Dividends) | C103: =PV(C102, C76, -C77, 0) -> 5.4969625
B104: PV(Equity Value) | C104: =C60/(1+C102)^C76 -> 64.405366
B105: Sell Above | C105: =C103+C104 -> 69.902329 | D105: HKD | E105: at a MOS of | F105: =(1-C105/C66) -> 0.15428574
E107: Inputs Legend
E108: Font Color | F108: Fact or Verified Data
E109: Font Color | F109: Subjective Driving Factors
E110: Font Color | F110: Subjective Non-Driving Factors
