Workbook
Name Common_Shares: Thesis!$C$6
Name Equity_Cost: Thesis!$C$86
Name Exchange_Rate: Thesis!$C$16
Name Market_currency: Thesis!$C$13
Name Market_Price: Thesis!$C$12
Name Reporting_currency: Thesis!$C$25
Name scaling_factor: Data!$C$3
Name Terminal_Growth: Thesis!$C$92
Name valuation_method: Thesis!$E$21

Sheet Thesis
B1: Model last updated: | C1: 45797 | D1: CN | E1: Selected: | F1: Y
A2: Executive Summary
B4: Company Information
B5: Company Name | C5: 浙江鼎力
B6: Number of Shares: | C6: 506347879
B7: Report Interval: | C7: 6
B8: Update Required After: | C8: =EOMONTH(EDATE(BS!C1,C7+2),0) -> 45900
B10: Listing Information
B11: Symbol: | C11: 603338.SS
B12: Market Price: | C12: 45.93
B13: Market Currency | C13: CNY
B14: Capitalization: | C14: =Thesis!C12*Common_Shares/1000000 -> 23256.558 | D14: =IF(D11="","",Thesis!D12*Common_Shares/1000000)
B15: Forex Symbol: | C15: =IF(C25=C13,C13,C25&"/"&C13) -> CNY | D15: =IF(D11="","",IF(C25=D13,D13,C25&"/"&D13))
B16: Exchange Rate: | C16: 1
B18: Guidance Note: This model determines a target buy price consistent with defined investment criteria. It follows a logical progression: establishing current sustainable earnings, adjusting for financial structure, incorporating growth scenarios, and finally applying the investor’s required return.
B20: Valuation Overview
B21: Growth Classification: | C21: =IF(Scenarios!C69="Y",Scenarios!B69,"")&IF(Scenarios!C70="Y",Scenarios!B70,"")&IF(Scenarios!C71="Y",Scenarios!B71,"")&" "&IF(Scenarios!C72="Y",Scenarios!B72,"") -> Low Growth | D21: Valuation Method | E21: DCF
B22: Comp_Sector: | C22: IND_01 | D22: =IF(valuation_method="DDM","DDM Terminal Value","")
B23: Business Model Risk Premium: | C23: N
B24: Management Risk Premium: | C24: N
B25: Reporting Currency: | C25: CNY | D25: =IF(D11="","",Market_currency&"/"&D13&":") | E25: =IF(D11="","",1/Exchange_Rate*D16)
B26: ="Expected Equity Value ("&C13&") :" -> Expected Equity Value (CNY) : | C26: =C132 -> 64.714648 | D26: Market Implied Annual Return: | E26: =Scenarios!C87 -> 0.14060796
B28: Valuation Outputs | C28: =C145&" ("&Market_currency&")" -> 603338.SS (CNY) | D28: =IF(D11="","",D145&" ("&D13&")") | E28: Holding Period | F28: 3
B29: Target Price | C29: =C149 -> 28.803264 | D29: =D149 | E29: Target return | F29: 0.337
B30: Entry Price | C30: =C157 -> 40.844732 | D30: =D157 | E30: Entry yield | F30: 0.187
B31: Sell Price | C31: =C165 -> 57.008678 | D31: =D165 | E31: Base equity cost | F31: 0.06
B32: Exit Price | C32: =C173 -> 52.931363 | D32: =D173 | E32: Benchmark yield | F32: 0.087
A34: Step 1: Establishing the Company’s Sustainable Earning Power (Calculating Normalized FCFE)
B36: Goal: To quantify the underlying FCFE the business consistently generates for its equity owners, stripping away temporary fluctuations or accounting choices.The FCFE/Market Cap yield gives a direct measure of this cash generation relative to the current market price.
B37: FCFE = (Normalized Operating EBIT + Depreciation & Amortization – Capital Expenditures) + Stable Non-Operating EBIT + Net Interest Income – Taxes – NCI’s Share of Profits – Working Capital Investment
B39: Key Components | C39: =scaling_factor -> 1
B40: • Normalized Operating EBIT: Earnings before interest and taxes from core business operations, adjusted to remove one-time or irregular items for a sustainable earnings base.
B41: Normalized Operating EBIT = | C41: =Normalized_FCF!C8 -> 1.4620555e+09 | D41: =Reporting_currency -> CNY
B43: • Depreciation & Amortization (D&A): Non-cash expenses added back to reflect cash generated from operations. • Capital Expenditures (Capex): Cash outflows required to maintain or expand operational assets
B44: D&A = | C44: =Normalized_FCF!C9 -> 213032611 | D44: =Reporting_currency -> CNY
B45: Capex = | C45: =Normalized_FCF!C10 -> -2.1303261e+08 | D45: =Reporting_currency -> CNY
B47: • Stable Non-Operating EBIT: Consistent earnings from non-core assets, such as fixed-income investments, dividend-paying stocks, or rental properties.
B48: Stable Non-Operating EBIT = | C48: =Normalized_FCF!C11 -> 0 | D48: =Reporting_currency -> CNY
B50: • Net Interest Income: Interest income minus interest expense
B51: Operating Interest Income = | C51: =Normalized_FCF!C48 -> 9271615.3 | D51: =Reporting_currency -> CNY
B52: Interest Expense = | C52: =Normalized_FCF!C47 -> -10773913 | D52: =Reporting_currency -> CNY
B53: Net Interest Income = | C53: =Normalized_FCF!C12 -> -1502297.7 | D53: =Reporting_currency -> CNY
B55: • NCI’s Share of Profits: NCI represents the portion of a subsidiary’s equity not owned by the parent company.
B56: Est. NCI’s Share of Profits = | C56: =Normalized_FCF!C15 -> -194943.1 | D56: =Reporting_currency -> CNY
B58: • Taxes: Tax = (Normalized Operating EBIT + Stable Non-Operating EBIT + Interest Income – Interest Expense) × Tax Rate
B59: Taxes = | C59: =Normalized_FCF!C14 -> -3.6513831e+08 | D59: =Reporting_currency -> CNY
B61: • Working Capital Investment (WCInv): WCInv is only included if it materially distorts FCFE.
B62: WCInv = | C62: =Normalized_FCF!C17 -> 0 | D62: =Reporting_currency -> CNY
B64: Note on Net Borrowing: In theory, principal repayments are accounted for through Net Borrowing. However, this model aims to avoid explicitly forecasting debt issuance or repayments. Instead, principal repayments are reflected in the Equity Value adjustment through interest-bearing debt.
B65: Insight: This step ensures a comprehensive measure of cash flow by incorporating both operating and stable non-operating sources while accounting for taxes and reinvestment needs.
B67: Latest FCFE = | C67: =Normalized_FCF!G19 -> 1.5880407e+09 | D67: =Reporting_currency -> CNY
B68: Normalized FCFE = | C68: =Normalized_FCF!C19 -> 1.09522e+09 | D68: =Reporting_currency -> CNY
B69: Normalized FCFE/Market Cap = | C69: =Normalized_FCF!C125 -> 0.047092953
B70: Dividend/Market Cap = | C70: =Normalized_FCF!C93 -> 0.021772262 | E70: Payout Ratio: | F70: =Normalized_FCF!C92 -> 0.46232527
B72: DuPont Analysis | C72: Normalized | D72: Latest
B73: ROE = | C73: =Normalized_FCF!C120 -> 0.14549955 | D73: =Normalized_FCF!G120 -> 0.18902581
B74: =Normalized_FCF!B117 -> Pre-tax Profit/Sales | C74: =Normalized_FCF!C117 -> 0.2240567 | D74: =Normalized_FCF!G117 -> 0.24330033
B75: =Normalized_FCF!B118 -> Sales/Total Assets | C75: =Normalized_FCF!C118 -> 0.4245631 | D75: =Normalized_FCF!G118 -> 0.50794528
B76: =Normalized_FCF!B119 -> Total Assets/Equity | C76: =Normalized_FCF!C119 -> 1.5295422 | D76: =Normalized_FCF!G119 -> 1.5295422
A78: Step 2: The No-Growth Baseline (Calculating Stable Income Value)
B80: Goal: To determine the intrinsic value of the company’s equity if the Normalized FCFE (calculated in Step 1) were to remain constant perpetually, with zero future growth. This establishes a baseline value derived solely from the current sustainable earnings power.
B81: Stable Income Value = Normalized FCFE / (Cost of Equity – Terminal Growth Rate)
B83: Key Components
B84: Base Cost of Equity | C84: =F31 -> 0.06
B85: Risk Premium | C85: =IF(C23="Y",1%,0)+IF(C24="Y",1%,0) -> 0
B86: Cost of Equity = | C86: =F31+C85 -> 0.06
B88: Note:
B89: Cost of Equity: Cost of Equity reflects the company’s risk profile and represents the minimum return the investor requires for taking on the general risk of owning this type of business, while the target annual return serves as the investor’s hurdle rate.
B90: Terminal Growth Rate: Setting g=0% is a conservative assumption, valuing the company based only on its current demonstrated earning power without relying on potentially optimistic future growth projections.
B92: Terminal Growth Rate (g) = | C92: 0
B93: No Growth SIV Per Share = | C93: =DCF!C6*scaling_factor*Exchange_Rate/Common_Shares -> 36.049655 | D93: =Market_currency -> CNY
A95: Step 3: Adjusting for Financial Structure (Calculating No Growth Equity Value)
B97: Goal: To refine the Stable Income Value (SIV) by incorporating the company’s balance sheet structure.
B98: Equity Value = Stable Income Value – Total Interest-Bearing Debt + Non-Operating Cash + Other Non-Operating Assets
B100: Key Components
B101: Note on debt: The total interest-bearing debt captures the principal repayments. Ideally, this amount should be discounted based on the repayment schedule. However, for simplicity and conservatism, this model uses the book value of the total interest-bearing debt.
B102: Total Interest-Bearing Debt = | C102: =DCF!C7 -> 5.3348119e+08 | D102: =Reporting_currency -> CNY
B103: Total Interest-Bearing Debt per share = | C103: =C102*scaling_factor*Exchange_Rate/Common_Shares -> 1.0535863 | D103: =Market_currency -> CNY
B104: Debt to Equity Ratio = | C104: =IF(BS!G31/BS!G27>300%,"nm",BS!G31/BS!G27) -> 0.053145119
B105: Debt to EBIT Ratio = | C105: =IF(BS!C50>30,"nm",BS!C50) -> 0.36488436
B107: • Non-Operating Cash: Excess cash not required for operations
B108: Total Cash = | C108: =BS!C66 -> 5.0780174e+09 | D108: =Reporting_currency -> CNY
B109: Est. Non-Operating Cash = | C109: =DCF!C8 -> 4.1508558e+09 | D109: =Reporting_currency -> CNY
B110: Est. Non-Operating Cash per share = | C110: =C109*scaling_factor*Exchange_Rate/Common_Shares -> 8.1976364 | D110: =Market_currency -> CNY
B112: • Other Non-Operating Assets: Assets not contributing to FCFE (e.g., non-income-generating investments or properties)
B113: Other Non-Operating Assets = | C113: =DCF!C9 -> 1.2524075e+08 | D113: =Reporting_currency -> CNY
B114: Other Non-Operating Assets per share = | C114: =C113*scaling_factor*Exchange_Rate/Common_Shares -> 0.24734132 | D114: =Market_currency -> CNY
B116: Insight: The No Growth Equity Value per share represents an estimate of the company’s intrinsic worth based on its current sustainable operations and net financial position, before factoring in any future growth potential. It serves as a fundamentally anchored valuation baseline.
B118: No Growth Equity Value per share = | C118: =IF(valuation_method="DCF",DCF!C12,DDM!C7) -> 43.441047 | D118: =Market_currency -> CNY
B119: Est. Realizable Value | C119: =BS!D47 -> 5.6082458 | D119: =Market_currency -> CNY
A121: Step 4: Incorporating Future Potential & Risk (Scenario Analysis)
B123: Goal: To estimate the company’s intrinsic value by considering plausible future scenarios beyond the static no-growth assumption. Based on fundamental research, each scenario defines high growth periods (HGP), high growth rates (HGR), and its probability.
B125: Scenarios | C125: HGR | D125: HGP | E125: EV per share | F125: Probabilities
B126: =DCF!B74 -> Snowball Scenario | C126: =DCF!C74 -> 0.08 | D126: =DCF!D74 -> 30 | E126: =ROUND(IF(valuation_method="DCF",DCF!E74,DDM!E69),2)&" "&Market_currency -> 102.01 CNY | F126: =DCF!F74 -> 0.05
B127: =DCF!B75 -> Optimistic | C127: =DCF!C75 -> 0.06 | D127: =DCF!D75 -> 30 | E127: =ROUND(IF(valuation_method="DCF",DCF!E75,DDM!E70),2)&" "&Market_currency -> 78.93 CNY | F127: =DCF!F75 -> 0.18
B128: =DCF!B76 -> Base | C128: =DCF!C76 -> 0.04 | D128: =DCF!D76 -> 30 | E128: =ROUND(IF(valuation_method="DCF",DCF!E76,DDM!E71),2)&" "&Market_currency -> 62.88 CNY | F128: =DCF!F76 -> 0.54
B129: =DCF!B77 -> Pessimistic | C129: =DCF!C77 -> 0.02 | D129: =DCF!D77 -> 30 | E129: =ROUND(IF(valuation_method="DCF",DCF!E77,DDM!E72),2)&" "&Market_currency -> 51.55 CNY | F129: =DCF!F77 -> 0.18
B130: =DCF!B78 -> Devil's advocate | C130: =DCF!C78 -> 0 | D130: =DCF!D78 -> 30 | E130: =ROUND(IF(valuation_method="DCF",DCF!E78,DDM!E73),2)&" "&Market_currency -> 43.44 CNY | F130: =DCF!F78 -> 0.05
B132: Expected Equity Value = | C132: =Scenarios!C60 -> 64.714648 | D132: =Market_currency -> CNY
B134: Insight: Significant market volatility is analyzed as an indicator of the range of market-perceived outcomes, including extremes that define boundaries for scenarios like "Snowball" or "Devil’s Advocate." Scenario Analysis then filters these using fundamental reasoning to evaluate their likelihood.
...

Sheet Data
B1: =Thesis!C25 -> CNY | C1: 45657 | D1: =EOMONTH(EDATE(C1,-12),0) -> 45291 | E1: =EOMONTH(EDATE(D1,-12),0) -> 44926 | F1: =EOMONTH(EDATE(E1,-12),0) -> 44561 | G1: =EOMONTH(EDATE(F1,-12),0) -> 44196 | H1: =EOMONTH(EDATE(G1,-12),0) -> 43830 | I1: =EOMONTH(EDATE(H1,-12),0) -> 43465 | J1: =EOMONTH(EDATE(I1,-12),0) -> 43100 | K1: =EOMONTH(EDATE(J1,-12),0) -> 42735 | ... M1: =EOMONTH(EDATE(L1,-12),0) -> 42004
B2: Data (Dirty)
B3: Income Statement | C3: 1
B4: Sales | C4: 7798913979 | D4: 6311963850 | E4: 5445152633 | F4: 4939315985 | G4: 2956758302 | H4: 2389355321 | I4: 1707538304 | J4: 1139183826 | K4: 694657422 | L4: 479151199
B5: COGS | C5: 5114327878 | D5: 3915820963 | E5: 3767200164 | F5: 3505125804 | G5: 1936776307 | H5: 1447475772 | I5: 1008193651 | J5: 672472586 | K5: 406608482 | L5: 285219753
B6: OPEX | C6: 478714939 | D6: 373685879 | E6: 280986971 | F6: 199250773 | G6: 157114047 | H6: 162036874 | I6: 148533985 | J6: 122587394 | K6: 111709735 | L6: 77990782
B7: Incl. Selling Expenses | C7: 253881041 | D7: 232460848 | E7: 157533022 | F7: 110815428 | G7: 99736422 | H7: 104708887 | I7: 91880229 | J7: 50830792 | K7: 39460173 | L7: 32507628
B8: R&D | C8: 255918596 | D8: 220006702 | E8: 202331051 | F8: 154945424 | G8: 104720121 | H8: 79166101 | I8: 61487163
B9: Share of JV or associate Results | C9: -70283969 | D9: 76220632 | E9: 20133006 | F9: 1499444 | G9: 11085542 | H9: 38861023 | I9: -12704453 | J9: 0 | K9: 0 | L9: 0
B10: Dividend or Interests from FA
B11: Investment property
B12: Interest Expense | C12: 10773913 | D12: 19213222 | E12: 16787986 | F12: 5280756 | G12: 1093564 | H12: 2759318 | I12: 1307356
B13: Interest Income | C13: 156551394 | D13: 159297476 | E13: 52423241 | F13: 16165039 | G13: 12495464 | H13: 24748172 | I13: 14095046
B14: Income Tax Paid | C14: 309204387 | D14: 307004817 | E14: 202660810 | F14: 136628407 | G14: 109313998 | H14: 110812786 | I14: 84670792 | J14: 49833797 | K14: 31011793 | L14: 21880350
B15: Reported Net Income | C15: 1629038383 | D15: 1867145469 | E15: 1257239986 | F15: 884463388 | G15: 664140193 | H15: 694081237 | I15: 480468472 | J15: 283145541 | K15: 174985183 | L15: 125750467
B16: Non-controling Interests | C16: 233229 | D16: 0 | E16: 0 | F16: 0 | G16: 0 | H16: 0 | I16: 0 | J16: 0 | K16: 202868 | L16: 16241
B18: Cash Flow Statement
B19: D&A | C19: 213032611 | D19: 135475921 | E19: 104602959 | F19: 78877993 | G19: 40782935 | H19: 28330776 | I19: 25091208
B20: CAPX
B21: WCInv
B22: CFO | C22: 1916547999 | D22: 2227397039 | E22: 936702406 | F22: 373661725 | G22: 891764853 | H22: 696158346 | I22: 415714136 | J22: 348706422 | K22: 142342727 | L22: 112359422
B23: CFI | C23: -178527168 | D23: -862617775 | E23: -1221538814 | F23: -69051239 | G23: -707286524 | H23: -666330101 | I23: 156611794 | J23: -1034615747 | K23: -185922892 | L23: -345198556
B24: CFF | C24: -996799146 | D24: -520447150 | E24: 44534961 | F24: 2069283867 | G24: -192224576 | H24: 147431845 | I24: 83396087 | J24: 893792882 | K24: -14815942 | L24: 409943115
B25: ="Dividend per share ("&Market_currency&")" -> Dividend per share (CNY) | C25: =10/10 -> 1 | D25: =10/10 -> 1 | E25: =5/10 -> 0.5
B27: Balance Sheet | C27: Latest Asset Value
B28: ST AR | C28: =BS!C4 -> 2.4703637e+09 | D28: 2391271680 | E28: 2078427810 | F28: 1620191874 | G28: 635971724 | H28: 797615199 | I28: 525650211 | J28: 299236277 | K28: 180459802 | L28: 105834918
B29: ST Inventory | C29: =BS!C6 -> 2.3421363e+09 | D29: 1921374942 | E29: 1795225840 | F29: 1387177645 | G29: 941597028 | H29: 460791109 | I29: 359087239 | J29: 243055593 | K29: 179108332 | L29: 137707371
B30: Total Liabilities | C30: =BS!C33+BS!C42 -> 5.3156493e+09 | D30: 5242067251 | E30: 4736625835 | F30: 3596300871 | G30: 2124874675 | H30: 1651958950 | I30: 1032202540 | J30: 576053698 | K30: 285486746 | L30: 172274845
B31: Total Equity | C31: =BS!G27 -> 1.0038197e+10 | D31: 8965233891 | E31: 7065182676 | F31: 5978168759 | G31: 3744157600 | H31: 3207493644 | I31: 2601382187 | J31: 2202505763 | K31: 1085805361 | L31: 922655590
B32: Non-common Interest | C32: =BS!G28 -> 2901653.6 | D32: 0 | E32: 0 | F32: 0 | G32: 0 | H32: 0 | I32: 0 | J32: 0 | K32: 0 | L32: 6016241
B34: IS & CF Statements (Clean)
B35: Income Statement
B36: Sales | C36: =IF(C$4="","",C4) -> 7798913979 | D36: =IF(D$4="","",D4) -> 6311963850 | E36: =IF(E$4="","",E4) -> 5445152633 | F36: =IF(F$4="","",F4) -> 4939315985 | G36: =IF(G$4="","",G4) -> 2956758302 | H36: =IF(H$4="","",H4) -> 2389355321 | I36: =IF(I$4="","",I4) -> 1707538304 | J36: =IF(J$4="","",J4) -> 1139183826 | ... M36: =IF(M$4="","",M4)
B37: COGS | C37: =IF(C$4="","",-C5) -> -5114327878 | D37: =IF(D$4="","",-D5) -> -3915820963 | E37: =IF(E$4="","",-E5) -> -3767200164 | F37: =IF(F$4="","",-F5) -> -3505125804 | G37: =IF(G$4="","",-G5) -> -1936776307 | H37: =IF(H$4="","",-H5) -> -1447475772 | I37: =IF(I$4="","",-I5) -> -1008193651 | J37: =IF(J$4="","",-J5) -> -672472586 | ... M37: =IF(M$4="","",-M5)
B38: Gross Margin | C38: =IF(C36="","",C36+C37) -> 2684586101 | D38: =IF(D36="","",D36+D37) -> 2396142887 | E38: =IF(E36="","",E36+E37) -> 1677952469 | F38: =IF(F36="","",F36+F37) -> 1434190181 | G38: =IF(G36="","",G36+G37) -> 1019981995 | H38: =IF(H36="","",H36+H37) -> 941879549 | I38: =IF(I36="","",I36+I37) -> 699344653 | J38: =IF(J36="","",J36+J37) -> 466711240 | ... M38: =IF(M36="","",M36+M37)
B39: OPEX | C39: =IF(C$4="","",-C6) -> -478714939 | D39: =IF(D$4="","",-D6) -> -373685879 | E39: =IF(E$4="","",-E6) -> -280986971 | F39: =IF(F$4="","",-F6) -> -199250773 | G39: =IF(G$4="","",-G6) -> -157114047 | H39: =IF(H$4="","",-H6) -> -162036874 | I39: =IF(I$4="","",-I6) -> -148533985 | J39: =IF(J$4="","",-J6) -> -122587394 | ... M39: =IF(M$4="","",-M6)
B40: Incl. Selling Expenses | C40: =IF(C$4="","",-C7) -> -253881041 | D40: =IF(D$4="","",-D7) -> -232460848 | E40: =IF(E$4="","",-E7) -> -157533022 | F40: =IF(F$4="","",-F7) -> -110815428 | G40: =IF(G$4="","",-G7) -> -99736422 | H40: =IF(H$4="","",-H7) -> -104708887 | I40: =IF(I$4="","",-I7) -> -91880229 | J40: =IF(J$4="","",-J7) -> -50830792 | ... M40: =IF(M$4="","",-M7)
B41: Incl. Other Opex | C41: =IF(C$4="","",C39-C40) -> -224833898 | D41: =IF(D$4="","",D39-D40) -> -141225031 | E41: =IF(E$4="","",E39-E40) -> -123453949 | F41: =IF(F$4="","",F39-F40) -> -88435345 | G41: =IF(G$4="","",G39-G40) -> -57377625 | H41: =IF(H$4="","",H39-H40) -> -57327987 | I41: =IF(I$4="","",I39-I40) -> -56653756 | J41: =IF(J$4="","",J39-J40) -> -71756602 | ... M41: =IF(M$4="","",M39-M40)
B42: R&D | C42: =IF(C$4="","",-C8) -> -255918596 | D42: =IF(D$4="","",-D8) -> -220006702 | E42: =IF(E$4="","",-E8) -> -202331051 | F42: =IF(F$4="","",-F8) -> -154945424 | G42: =IF(G$4="","",-G8) -> -104720121 | H42: =IF(H$4="","",-H8) -> -79166101 | I42: =IF(I$4="","",-I8) -> -61487163 | J42: =IF(J$4="","",-J8) -> 0 | ... M42: =IF(M$4="","",-M8)
B43: Operating EBIT | C43: =IF(C$4="","",C38+C39+C42) -> 1949952566 | D43: =IF(D$4="","",D38+D39+D42) -> 1802450306 | E43: =IF(E$4="","",E38+E39+E42) -> 1194634447 | F43: =IF(F$4="","",F38+F39+F42) -> 1079993984 | G43: =IF(G$4="","",G38+G39+G42) -> 758147827 | H43: =IF(H$4="","",H38+H39+H42) -> 700676574 | I43: =IF(I$4="","",I38+I39+I42) -> 489323505 | J43: =IF(J$4="","",J38+J39+J42) -> 344123846 | ... M43: =IF(M$4="","",M38+M39+M42)
B44: Non-operating EBIT | C44: =IF(C$4="","",C47-C46-C45-C43) -> -157487277 | D44: =IF(D$4="","",D47-D46-D45-D43) -> 231615726 | E44: =IF(E$4="","",E47-E46-E45-E43) -> 229631094 | F44: =IF(F$4="","",F47-F46-F45-F43) -> -69786472 | G44: =IF(G$4="","",G47-G46-G45-G43) -> 3904464 | H44: =IF(H$4="","",H47-H46-H45-H43) -> 82228595 | I44: =IF(I$4="","",I47-I46-I45-I43) -> 63028069 | J44: =IF(J$4="","",J47-J46-J45-J43) -> -11144508 | ... M44: =IF(M$4="","",M47-M46-M45-M43)
B45: Net Interest Income | C45: =IF(C$4="","",C51+C52) -> 145777481 | D45: =IF(D$4="","",D51+D52) -> 140084254 | E45: =IF(E$4="","",E51+E52) -> 35635255 | F45: =IF(F$4="","",F51+F52) -> 10884283 | G45: =IF(G$4="","",G51+G52) -> 11401900 | H45: =IF(H$4="","",H51+H52) -> 21988854 | I45: =IF(I$4="","",I51+I52) -> 12787690 | J45: =IF(J$4="","",J51+J52) -> 0 | ... M45: =IF(M$4="","",M51+M52)
B46: Income Tax Paid | C46: =IF(C$4="","",-C14) -> -309204387 | D46: =IF(D$4="","",-D14) -> -307004817 | E46: =IF(E$4="","",-E14) -> -202660810 | F46: =IF(F$4="","",-F14) -> -136628407 | G46: =IF(G$4="","",-G14) -> -109313998 | H46: =IF(H$4="","",-H14) -> -110812786 | I46: =IF(I$4="","",-I14) -> -84670792 | J46: =IF(J$4="","",-J14) -> -49833797 | ... M46: =IF(M$4="","",-M14)
B47: Reported Net Income | C47: =IF(C$4="","",C15) -> 1629038383 | D47: =IF(D$4="","",D15) -> 1867145469 | E47: =IF(E$4="","",E15) -> 1257239986 | F47: =IF(F$4="","",F15) -> 884463388 | G47: =IF(G$4="","",G15) -> 664140193 | H47: =IF(H$4="","",H15) -> 694081237 | I47: =IF(I$4="","",I15) -> 480468472 | J47: =IF(J$4="","",J15) -> 283145541 | ... M47: =IF(M$4="","",M15)
B48: Non-controling Interests | C48: =IF(C$4="","",MIN(-C16,0)) -> -233229 | D48: =IF(D$4="","",MIN(-D16,0)) -> 0 | E48: =IF(E$4="","",MIN(-E16,0)) -> 0 | F48: =IF(F$4="","",MIN(-F16,0)) -> 0 | G48: =IF(G$4="","",MIN(-G16,0)) -> 0 | H48: =IF(H$4="","",MIN(-H16,0)) -> 0 | I48: =IF(I$4="","",MIN(-I16,0)) -> 0 | J48: =IF(J$4="","",MIN(-J16,0)) -> 0 | ... M48: =IF(M$4="","",MIN(-M16,0))
B50: Net Interest Income
B51: Interest Expense | C51: =IF(C$4="","",-C12) -> -10773913 | D51: =IF(D$4="","",-D12) -> -19213222 | E51: =IF(E$4="","",-E12) -> -16787986 | F51: =IF(F$4="","",-F12) -> -5280756 | G51: =IF(G$4="","",-G12) -> -1093564 | H51: =IF(H$4="","",-H12) -> -2759318 | I51: =IF(I$4="","",-I12) -> -1307356 | J51: =IF(J$4="","",-J12) -> 0 | ... M51: =IF(M$4="","",-M12)
B52: Interest Income | C52: =IF(C$4="","",C13) -> 156551394 | D52: =IF(D$4="","",D13) -> 159297476 | E52: =IF(E$4="","",E13) -> 52423241 | F52: =IF(F$4="","",F13) -> 16165039 | G52: =IF(G$4="","",G13) -> 12495464 | H52: =IF(H$4="","",H13) -> 24748172 | I52: =IF(I$4="","",I13) -> 14095046 | J52: =IF(J$4="","",J13) -> 0 | ... M52: =IF(M$4="","",M13)
B54: Non-operating EBIT
B55: Share of JV or associate Results | C55: =IF(C$4="","",C9) -> -70283969 | D55: =IF(D$4="","",D9) -> 76220632 | E55: =IF(E$4="","",E9) -> 20133006 | F55: =IF(F$4="","",F9) -> 1499444 | G55: =IF(G$4="","",G9) -> 11085542 | H55: =IF(H$4="","",H9) -> 38861023 | I55: =IF(I$4="","",I9) -> -12704453 | J55: =IF(J$4="","",J9) -> 0 | ... M55: =IF(M$4="","",M9)
B56: Dividend or Interests from FA | C56: =IF(C$4="","",C10) -> 0 | D56: =IF(D$4="","",D10) -> 0 | E56: =IF(E$4="","",E10) -> 0 | F56: =IF(F$4="","",F10) -> 0 | G56: =IF(G$4="","",G10) -> 0 | H56: =IF(H$4="","",H10) -> 0 | I56: =IF(I$4="","",I10) -> 0 | J56: =IF(J$4="","",J10) -> 0 | ... M56: =IF(M$4="","",M10)
B57: Investment property | C57: =IF(C$4="","",C11) -> 0 | D57: =IF(D$4="","",D11) -> 0 | E57: =IF(E$4="","",E11) -> 0 | F57: =IF(F$4="","",F11) -> 0 | G57: =IF(G$4="","",G11) -> 0 | H57: =IF(H$4="","",H11) -> 0 | I57: =IF(I$4="","",I11) -> 0 | J57: =IF(J$4="","",J11) -> 0 | ... M57: =IF(M$4="","",M11)
B58: Other Non-operating Income | C58: =IF(C$4="","",C44-C55-C56-C57) -> -87203308 | D58: =IF(D$4="","",D44-D55-D56-D57) -> 155395094 | E58: =IF(E$4="","",E44-E55-E56-E57) -> 209498088 | F58: =IF(F$4="","",F44-F55-F56-F57) -> -71285916 | G58: =IF(G$4="","",G44-G55-G56-G57) -> -7181078 | H58: =IF(H$4="","",H44-H55-H56-H57) -> 43367572 | I58: =IF(I$4="","",I44-I55-I56-I57) -> 75732522 | J58: =IF(J$4="","",J44-J55-J56-J57) -> -11144508 | ... M58: =IF(M$4="","",M44-M55-M56-M57)
B60: Cash Flow Statement
B61: D&A | C61: =IF(C$4="","",-C19) -> -213032611 | D61: =IF(D$4="","",-D19) -> -135475921 | E61: =IF(E$4="","",-E19) -> -104602959 | F61: =IF(F$4="","",-F19) -> -78877993 | G61: =IF(G$4="","",-G19) -> -40782935 | H61: =IF(H$4="","",-H19) -> -28330776 | I61: =IF(I$4="","",-I19) -> -25091208 | J61: =IF(J$4="","",-J19) -> 0 | ... M61: =IF(M$4="","",-M19)
B62: CAPX | C62: =IF(C$4="","",IF(C20=0,C61,-C20)) -> -213032611 | D62: =IF(D$4="","",IF(D20=0,D61,-D20)) -> -135475921 | E62: =IF(E$4="","",IF(E20=0,E61,-E20)) -> -104602959 | F62: =IF(F$4="","",IF(F20=0,F61,-F20)) -> -78877993 | G62: =IF(G$4="","",IF(G20=0,G61,-G20)) -> -40782935 | H62: =IF(H$4="","",IF(H20=0,H61,-H20)) -> -28330776 | I62: =IF(I$4="","",IF(I20=0,I61,-I20)) -> -25091208 | J62: =IF(J$4="","",IF(J20=0,J61,-J20)) -> 0 | ... M62: =IF(M$4="","",IF(M20=0,M61,-M20))
B63: WCInv | C63: =IF(C$4="","",-C21) -> 0 | D63: =IF(D$4="","",-D21) -> 0 | E63: =IF(E$4="","",-E21) -> 0 | F63: =IF(F$4="","",-F21) -> 0 | G63: =IF(G$4="","",-G21) -> 0 | H63: =IF(H$4="","",-H21) -> 0 | I63: =IF(I$4="","",-I21) -> 0 | J63: =IF(J$4="","",-J21) -> 0 | ... M63: =IF(M$4="","",-M21)
B64: Net Change in Cash | C64: =IF(C$4="","",C22+C23+C24) -> 741221685 | D64: =IF(D$4="","",D22+D23+D24) -> 844332114 | E64: =IF(E$4="","",E22+E23+E24) -> -240301447 | F64: =IF(F$4="","",F22+F23+F24) -> 2373894353 | G64: =IF(G$4="","",G22+G23+G24) -> -7746247 | H64: =IF(H$4="","",H22+H23+H24) -> 177260090 | I64: =IF(I$4="","",I22+I23+I24) -> 655722017 | J64: =IF(J$4="","",J22+J23+J24) -> 207883557 | ... M64: =IF(M$4="","",M22+M23+M24)
B65: Dividend per share | C65: =IF(C$4="","",C25) -> 1 | D65: =IF(D$4="","",D25) -> 1 | E65: =IF(E$4="","",E25) -> 0.5 | F65: =IF(F$4="","",F25) -> 0 | G65: =IF(G$4="","",G25) -> 0 | H65: =IF(H$4="","",H25) -> 0 | I65: =IF(I$4="","",I25) -> 0 | J65: =IF(J$4="","",J25) -> 0 | ... M65: =IF(M$4="","",M25)
B67: YoY %
B68: =B36 -> Sales | C68: =IF(D$36="","",C36/D36-1) -> 0.23557646 | D68: =IF(E$36="","",D36/E36-1) -> 0.15918952 | E68: =IF(F$36="","",E36/F36-1) -> 0.10241026 | F68: =IF(G$36="","",F36/G36-1) -> 0.67051733 | G68: =IF(H$36="","",G36/H36-1) -> 0.23747116 | H68: =IF(I$36="","",H36/I36-1) -> 0.39929823 | I68: =IF(J$36="","",I36/J36-1) -> 0.49891375 | J68: =IF(K$36="","",J36/K36-1) -> 0.63992177 | ... M68: =IF(N$36="","",M36/N36-1)
B69: Gross Margin | C69: =IF(D$36="","",C38/D38-1) -> 0.12037814 | D69: =IF(E$36="","",D38/E38-1) -> 0.42801595 | E69: =IF(F$36="","",E38/F38-1) -> 0.16996511 | F69: =IF(G$36="","",F38/G38-1) -> 0.40609363 | G69: =IF(H$36="","",G38/H38-1) -> 0.082921904 | H69: =IF(I$36="","",H38/I38-1) -> 0.3468031 | I69: =IF(J$36="","",I38/J38-1) -> 0.49845256 | J69: =IF(K$36="","",J38/K38-1) -> 0.62024981 | ... M69: =IF(N$36="","",M38/N38-1)
B70: =B43 -> Operating EBIT | C70: =IF(D$36="","",C43/D43-1) -> 0.081834301 | D70: =IF(E$36="","",D43/E43-1) -> 0.50878816 | E70: =IF(F$36="","",E43/F43-1) -> 0.10614917 | F70: =IF(G$36="","",F43/G43-1) -> 0.42451636 | G70: =IF(H$36="","",G43/H43-1) -> 0.082022512 | H70: =IF(I$36="","",H43/I43-1) -> 0.43192912 | I70: =IF(J$36="","",I43/J43-1) -> 0.42194013 | J70: =IF(K$36="","",J43/K43-1) -> 0.95148802 | ... M70: =IF(N$36="","",M43/N43-1)
B71: Non-operating EBIT | C71: =IF(D$36="","",C44/D44-1) -> -1.6799507 | D71: =IF(E$36="","",D44/E44-1) -> 0.0086426971 | E71: =IF(F$36="","",E44/F44-1) -> -4.2904815 | F71: =IF(G$36="","",F44/G44-1) -> -18.873509 | G71: =IF(H$36="","",G44/H44-1) -> -0.95251696 | H71: =IF(I$36="","",H44/I44-1) -> 0.30463453 | I71: =IF(J$36="","",I44/J44-1) -> -6.6555273 | J71: =IF(K$36="","",J44/K44-1) -> -1.3757702 | ... M71: =IF(N$36="","",M44/N44-1)
B72: =B47 -> Reported Net Income | C72: =IF(D$36="","",C47/D47-1) -> -0.12752466 | D72: =IF(E$36="","",D47/E47-1) -> 0.48511461 | E72: =IF(F$36="","",E47/F47-1) -> 0.42147205 | F72: =IF(G$36="","",F47/G47-1) -> 0.331742 | G72: =IF(H$36="","",G47/H47-1) -> -0.043137665 | H72: =IF(I$36="","",H47/I47-1) -> 0.44459268 | I72: =IF(J$36="","",I47/J47-1) -> 0.69689577 | J72: =IF(K$36="","",J47/K47-1) -> 0.61811152 | ... M72: =IF(N$36="","",M47/N47-1)
B74: Balance Sheet (Clean)
B75: Balance Sheet
B76: Total Assets | C76: =IF(C$4="","",C79+C80) -> 1.5353847e+10 | D76: =IF(D$4="","",D79+D80) -> 14207301142 | E76: =IF(E$4="","",E79+E80) -> 11801808511 | F76: =IF(F$4="","",F79+F80) -> 9574469630 | G76: =IF(G$4="","",G79+G80) -> 5869032275 | H76: =IF(H$4="","",H79+H80) -> 4859452594 | I76: =IF(I$4="","",I79+I80) -> 3633584727 | J76: =IF(J$4="","",J79+J80) -> 2778559461 | ... M76: =IF(M$4="","",M79+M80)
B77: Incl. ST AR | C77: =IF(C$4="","",C28) -> 2.4703637e+09 | D77: =IF(D$4="","",D28) -> 2391271680 | E77: =IF(E$4="","",E28) -> 2078427810 | F77: =IF(F$4="","",F28) -> 1620191874 | G77: =IF(G$4="","",G28) -> 635971724 | H77: =IF(H$4="","",H28) -> 797615199
B78: Incl. ST Inventory | C78: =IF(C$4="","",C29) -> 2.3421363e+09 | D78: =IF(D$4="","",D29) -> 1921374942 | E78: =IF(E$4="","",E29) -> 1795225840 | F78: =IF(F$4="","",F29) -> 1387177645 | G78: =IF(G$4="","",G29) -> 941597028 | H78: =IF(H$4="","",H29) -> 460791109
B79: Total Liabilities | C79: =IF(C$4="","",C30) -> 5.3156493e+09 | D79: =IF(D$4="","",D30) -> 5242067251 | E79: =IF(E$4="","",E30) -> 4736625835 | F79: =IF(F$4="","",F30) -> 3596300871 | G79: =IF(G$4="","",G30) -> 2124874675 | H79: =IF(H$4="","",H30) -> 1651958950 | I79: =IF(I$4="","",I30) -> 1032202540 | J79: =IF(J$4="","",J30) -> 576053698 | ... M79: =IF(M$4="","",M30)
B80: Total Equity | C80: =IF(C$4="","",C31) -> 1.0038197e+10 | D80: =IF(D$4="","",D31) -> 8965233891 | E80: =IF(E$4="","",E31) -> 7065182676 | F80: =IF(F$4="","",F31) -> 5978168759 | G80: =IF(G$4="","",G31) -> 3744157600 | H80: =IF(H$4="","",H31) -> 3207493644 | I80: =IF(I$4="","",I31) -> 2601382187 | J80: =IF(J$4="","",J31) -> 2202505763 | ... M80: =IF(M$4="","",M31)

Sheet BS
B1: Most Recent Quarter | C1: 45657 | F1: =IF(MONTH(C1)=MONTH(Normalized_FCF!G1),"FY","Quarter")&" Report" -> FY Report | H1: =scaling_factor -> 1
B2: Lastest Balance Sheet
B3: ST Operating Assets | C3: Book | D3: Valued @ | F3: ST Non-Operating Assets | G3: Book | H3: Valued @
B4: ST AR | C4: =20196142.69+2309129845.46+18315265.15+122722445.83 -> 2.4703637e+09 | D4: 0.6 | F4: Cash and cash equivalents | G4: 5.0780174e+09 | H4: 0.9
B5: Operating ST Financial Assets | C5: 14974287 | D5: 0.6 | F5: Restricted cash | G5: 0 | H5: 0.7
B6: Inventory | C6: 2.3421363e+09 | D6: 0.5 | F6: Securities with stable income | G6: 0 | H6: 0.6
B7: Properties held for sale | C7: 0 | D7: 0.6 | F7: Other Securities | G7: 2.0873459e+08 | H7: 0.6
B8: Properties held for income | C8: 0 | D8: 0.6 | F8: Properties with stable income | G8: 0 | H8: 0.6
B9: Prepayments and Contract Assets | C9: 26411605 | D9: 0.1 | F9: Other Properties | G9: 0 | H9: 0.6
B10: ST DTA | C10: 0 | D10: 0.9
B11: Other ST Assets | C11: =1154749077.73+69993040.32 -> 1.2247421e+09 | D11: 0.05
B12: Operating ST Assets | C12: =SUM(C4:C11) -> 6.078628e+09 | D12: =C4*D4+C5*D5+C9*D9+C6*D6+C8*D8+C7*D7+C10*D10+C11*D11 -> 2.7261492e+09 | F12: Non-Operating ST Assets | G12: =SUM(G4:G9) -> 5.2867519e+09 | H12: =G4*H4+G5*H5+G6*H6+G7*H7+G8*H8+G9*H9 -> 4.6954564e+09
B14: LT Operating Assets | C14: Book | D14: Valued @ | F14: LT Non-Operating Assets | G14: Book | H14: Valued @
B15: LT AR | C15: 1.0171513e+09 | D15: 0.4 | F15: LT Depositis | G15: 0 | H15: 0.8
B16: Operating LT Financial Assets | C16: 0 | D16: 0.5 | F16: Securities with stable income | G16: 40867997 | H16: 0.6
B17: Properties held for sale | C17: 0 | D17: 0.6 | F17: Other Securities | G17: 0 | H17: 0.6
B18: Properties held for income | C18: 0 | D18: 0.6 | F18: JV or associate with stable income | G18: 0 | H18: 0.1
B19: PP&E & Right of Use Assets | C19: =1799948914+58349007.87+51120522.33 -> 1.9094184e+09 | D19: 0.1 | F19: Other JV or associate | G19: 0 | H19: 0.1
B20: Biological assets | C20: 0 | D20: 0.05 | F20: Properties with stable income | G20: 0 | H20: 0.2
B21: Intangible assets | C21: 7.8359044e+08 | D21: 0.05 | F21: Other Properties | G21: 0 | H21: 0.1
B22: LT DTA | C22: 83517871 | D22: 0.9
B23: Other assets & Goodwill | C23: =140139590.91+2936428.79+10844760 -> 1.5392078e+08 | D23: 0
B24: Operating LT Assets | C24: =SUM(C15:C23) -> 3.9475988e+09 | D24: =C15*D15+C16*D16+C18*D18+C17*D17+C19*D19+C20*D20+C21*D21+C22*D22+C23*D23 -> 7.1214796e+08 | F24: Non-Operating LT Assets | G24: =SUM(G15:G21) -> 40867997 | H24: =G15*H15+G16*H16+G17*H17+G18*H18+G19*H19+G20*H20+G21*H21 -> 24520798
B26: ST Liabilities | C26: Book | F26: BS Summary | G26: Book | H26: Valued @
B27: ST Borrowing | C27: 1.1007069e+08 | F27: Total Equity | G27: =G32-G30 -> 1.0038197e+10 | H27: =H32-G30 -> 2.842625e+09
B28: ST Lease liabilities | C28: 0 | F28: Incl. Minority Interest (NCI) | G28: 2901653.6
B29: ST SH Loan | C29: 0 | F29: Incl. Common Equity | G29: =G27-G28 -> 1.0035296e+10 | H29: =H27-G28 -> 2.8397234e+09
B30: ST Financial Liabilities | C30: 999897.45 | F30: Total Liabilities | G30: =C33+C42 -> 5.3156493e+09
B31: ST Interest-bearing Debt | C31: =SUM(C27:C30) -> 1.1107059e+08 | F31: incl. Interest-bearing Debt | G31: =C31+C40 -> 5.3348119e+08
B32: Other ST liabilities | C32: =C33-C31 -> 4.4116357e+09 | F32: Total Assets | G32: =G35+G40 -> 1.5353847e+10 | H32: =H35+H40 -> 8.1582744e+09
B33: Current Liabilities | C33: 4.5227063e+09
F34: Assets Summary | G34: Book | H34: Valued @
B35: LT Liabilities | C35: Book | F35: Operating Assets | G35: =C12+C24 -> 1.0026227e+10 | H35: =D12+D24 -> 3.4382972e+09
B36: LT Borrowing | C36: 3.7805537e+08 | F36: incl. AR | G36: =C4+C15 -> 3.487515e+09
B37: LT Lease liabilities | C37: 44355236 | F37: incl. inventory | G37: =C6 -> 2.3421363e+09
B38: LT SH Loan | C38: 0 | F38: incl. Properties held for sale | G38: =C7+C17 -> 0
B39: LT Financial Liabilities | C39: 0 | F39: incl. Fixed Assets | G39: =C7+C17+C19+C20 -> 1.9094184e+09 | H39: =C7*D7+C17*D17+C19*D19+C20*D20 -> 1.9094184e+08
B40: LT Interest-bearing Debt | C40: =SUM(C36:C39) -> 4.224106e+08 | F40: Non-operating Assets | G40: =G12+G24 -> 5.3276199e+09 | H40: =H12+H24 -> 4.7199772e+09
B41: Other LT liabilities | C41: =C42-C40 -> 3.7053242e+08 | F41: incl. Assets with stable income | G41: =C70 -> 5.1188854e+09 | H41: =H40-H42 -> 4.5947364e+09
B42: Noncurrent Liabilities | C42: 7.9294302e+08 | F42: incl. Other Assets | G42: =C82 -> 2.0873459e+08 | H42: =D82 -> 1.2524075e+08
B44: Balance Sheet Analysis
B45: Asset Value Stress Test | C45: Book | D45: Est. Realizable Value | F45: Notes
B46: Equity | C46: =G29 -> 1.0035296e+10 | D46: =H29 -> 2.8397234e+09
B47: ="Equity per share ("&Market_currency&")" -> Equity per share (CNY) | C47: =C46*H1/Common_Shares*Exchange_Rate -> 19.818975 | D47: =D46*H1/Common_Shares*Exchange_Rate -> 5.6082458
B49: Leverage % | C49: Normalized | D49: Latest
B50: Debt/EBIT | C50: =G31/Normalized_FCF!C8 -> 0.36488436 | D50: =G31/Normalized_FCF!G8 -> 0.27358675
B51: Common Equity/Total Asset | D51: =G29/G32 -> 0.6536014
B53: Profibility % | C53: Normalized | D53: Latest
B54: Operating Asset Yield | C54: =Normalized_FCF!C8/G35 -> 0.14582311 | D54: =Normalized_FCF!G8/G35 -> 0.19448518
B55: Non-Operating Asset Yield | C55: =Normalized_FCF!C11/G40 -> 0 | D55: =Normalized_FCF!G11/G40 -> -0.013192377
B57: Reinvestment % | C57: Normalized | D57: Latest
B58: D&A/Fixed Assets | D58: =Normalized_FCF!G9/BS!$G$39 -> 0.11156937
B59: Fixed Assets/Total Assets | D59: =G39/G32 -> 0.12436092
B61: NCI % | C61: Estimate | D61: Latest
B62: Est. of NCI Ownership Percentage | C62: =IF(G28<=0,0,G28/G29) -> 0.0002891448 | D62: =G28/G29 -> 0.0002891448 | F62: Rough Estimate only
B64: Non-operating Assets Analysis
B65: Non-operating Assets with stable income | C65: Book | D65: Non-Operating | F65: Notes
B66: Cash | C66: =G4+G5+G15 -> 5.0780174e+09 | D66: =C66-D75 -> 4.1508558e+09 | F66: Non-Operating Cash is the Excess cash not required for operations
B67: Securities with stable income | C67: =G6+G16 -> 40867997
B68: JV or associate with stable income | C68: =G18 -> 0
B69: Properties with stable income | C69: =G8+G20 -> 0
B70: Non-operating Assets with stable income | C70: =SUM(C66:C69) -> 5.1188854e+09
B72: Cash Management Analysis | C72: Latest | D72: Normalized
B73: Monthly Operating Expenses | C73: =(Normalized_FCF!G25+Normalized_FCF!G35-Normalized_FCF!G91)/12 -> -5.2960911e+08 | D73: =(Normalized_FCF!C25+Normalized_FCF!C35-Normalized_FCF!C91)/12 -> -4.6358076e+08 | F73: Variable + Fixed Costs & Dividends
B74: Operating Expenses Multiple (months) | C74: =-$C$66/C73 -> 9.5882365 | D74: =-$C$66/D73 -> 10.9539 | F74: Companies typically need cash to cover 1 to 2 months of operating expenses
B75: Operating Cash Requirement | D75: =MAX(-D73*D76,G5) -> 9.2716153e+08 | F75: 1x for stable businesses, 2x for for volatile ones, 6x for cash hoarders
B76: Operating Cash Multiple (months) | D76: =IF(valuation_method="DCF",IF(D74<=3,1,IF(D74>18,6,2)),-C66/D73) -> 2 | F76: Rough Estimate
B78: Other Non-operating Assets | C78: Book | D78: Valued @
B79: Other Securities | C79: =G7+G17 -> 2.0873459e+08 | D79: =G7*H7+G17*H17 -> 1.2524075e+08
B80: Other JV or associate | C80: =G19 -> 0 | D80: =G19*H19 -> 0
B81: Other Properties | C81: =G9+G21 -> 0 | D81: =G9*H9+G21*H21 -> 0
B82: Other Non-operating Assets | C82: =SUM(C79:C81) -> 2.0873459e+08 | D82: =SUM(D79:D81) -> 1.2524075e+08
B84: Non-FCF Value of the Equity Value
B85: Non-FCF Value | D85: Per-Share
B86: Interest-bearing Debt | C86: =-DCF!C7*Exchange_Rate -> -5.3348119e+08 | D86: =C86*scaling_factor/Common_Shares -> -1.0535863 | E86: =Market_currency -> CNY
B87: Non-operating Cash | C87: =DCF!C8*Exchange_Rate -> 4.1508558e+09 | D87: =C87*scaling_factor/Common_Shares -> 8.1976364 | E87: =Market_currency -> CNY
B88: Other Non-operating Assets | C88: =DCF!C9*Exchange_Rate -> 1.2524075e+08 | D88: =C88*scaling_factor/Common_Shares -> 0.24734132 | E88: =Market_currency -> CNY
B89: Total Non-FCF Value | C89: =SUM(C86:C88) -> 3.7426154e+09 | D89: =SUM(D86:D88) -> 7.3913915 | E89: =Market_currency -> CNY

Sheet Normalized_FCF
B1: =Thesis!C25 -> CNY | C1: Normalized | G1: =Data!C1 -> 45657 | H1: =EOMONTH(EDATE(G1,-12),0) -> 45291 | I1: =EOMONTH(EDATE(H1,-12),0) -> 44926 | J1: =EOMONTH(EDATE(I1,-12),0) -> 44561 | K1: =EOMONTH(EDATE(J1,-12),0) -> 44196 | L1: =EOMONTH(EDATE(K1,-12),0) -> 43830 | M1: =EOMONTH(EDATE(L1,-12),0) -> 43465 | N1: =EOMONTH(EDATE(M1,-12),0) -> 43100 | O1: =EOMONTH(EDATE(N1,-12),0) -> 42735 | ... Q1: =EOMONTH(EDATE(P1,-12),0) -> 42004
B2: FCFE Analysis | E2: Notes
B3: FCFE | C3: =scaling_factor -> 1
B4: Sales | C4: =AVERAGE(G4:I4) -> 6.5186768e+09 | G4: =Data!C36 -> 7798913979 | H4: =Data!D36 -> 6311963850 | I4: =Data!E36 -> 5445152633 | J4: =Data!F36 -> 4939315985 | K4: =Data!G36 -> 2956758302 | L4: =Data!H36 -> 2389355321 | M4: =Data!I36 -> 1707538304 | N4: =Data!J36 -> 1139183826 | ... Q4: =Data!M36
B5: Variable Costs | C5: =C25 -> -4.5758688e+09 | G5: =G25 -> -5368208919 | H5: =H25 -> -4148281811 | I5: =I25 -> -3924733186 | J5: =J25 -> -3615941232 | K5: =K25 -> -2036512729 | L5: =L25 -> -1552184659 | M5: =M25 -> -1100073880 | N5: =N25 -> -723303378 | ... Q5: =Q25
B6: Contribution Margin | C6: =C4+C5 -> 1.942808e+09 | G6: =IF(G4="","",G4+G5) -> 2430705060 | H6: =IF(H4="","",H4+H5) -> 2163682039 | I6: =IF(I4="","",I4+I5) -> 1520419447 | J6: =IF(J4="","",J4+J5) -> 1323374753 | K6: =IF(K4="","",K4+K5) -> 920245573 | L6: =IF(L4="","",L4+L5) -> 837170662 | M6: =IF(M4="","",M4+M5) -> 607464424 | N6: =IF(N4="","",N4+N5) -> 415880448 | ... Q6: =IF(Q4="","",Q4+Q5)
B7: Fixed Costs | C7: =C35 -> -480752494 | G7: =G35 -> -480752494 | H7: =H35 -> -361231733 | I7: =I35 -> -325785000 | J7: =J35 -> -243380769 | K7: =K35 -> -162097746 | L7: =L35 -> -136494088 | M7: =M35 -> -118140919 | N7: =N35 -> -71756602 | ... Q7: =Q35
B8: Operating EBIT | C8: =C6+C7 -> 1.4620555e+09 | G8: =IF(G$4="","",G6+G7) -> 1949952566 | H8: =IF(H$4="","",H6+H7) -> 1802450306 | I8: =IF(I$4="","",I6+I7) -> 1194634447 | J8: =IF(J$4="","",J6+J7) -> 1079993984 | K8: =IF(K$4="","",K6+K7) -> 758147827 | L8: =IF(L$4="","",L6+L7) -> 700676574 | M8: =IF(M$4="","",M6+M7) -> 489323505 | N8: =IF(N$4="","",N6+N7) -> 344123846 | ... Q8: =IF(Q$4="","",Q6+Q7)
B9: Add Back D&A | C9: =BS!$G$39*BS!D58 -> 213032611 | G9: =IF(Data!C61="","",-Data!C61) -> 213032611 | H9: =IF(Data!D61="","",-Data!D61) -> 135475921 | I9: =IF(Data!E61="","",-Data!E61) -> 104602959 | J9: =IF(Data!F61="","",-Data!F61) -> 78877993 | K9: =IF(Data!G61="","",-Data!G61) -> 40782935 | L9: =IF(Data!H61="","",-Data!H61) -> 28330776 | M9: =IF(Data!I61="","",-Data!I61) -> 25091208 | N9: =IF(Data!J61="","",-Data!J61) -> 0 | ... Q9: =IF(Data!M61="","",-Data!M61)
B10: Maintenance Capex | C10: =-C4*C78 -> -2.1303261e+08 | G10: =Data!C62 -> -213032611 | H10: =Data!D62 -> -135475921 | I10: =Data!E62 -> -104602959 | J10: =Data!F62 -> -78877993 | K10: =Data!G62 -> -40782935 | L10: =Data!H62 -> -28330776 | M10: =Data!I62 -> -25091208 | N10: =Data!J62 -> 0 | ... Q10: =Data!M62
B11: Stable Non-Operating EBIT | C11: =C63 -> 0 | G11: =G61 -> -70283969 | H11: =H61 -> 76220632 | I11: =I61 -> 20133006 | J11: =J61 -> 1499444 | K11: =K61 -> 11085542 | L11: =L61 -> 38861023 | M11: =M61 -> -12704453 | N11: =N61 -> 0 | ... Q11: =Q61
B12: Net Interest Income | C12: =C50 -> -1502297.7 | G12: =G50 -> 17809768 | H12: =H50 -> 9871848.2 | I12: =I50 -> -7216373.9 | J12: =J50 -> -2329288.7 | K12: =K50 -> 1187899.9 | L12: =L50 -> 1759286.7 | M12: =M50 -> 1266165 | N12: =N50 -> 0 | ... Q12: =Q50
B13: Pre-tax Profit | C13: =SUM(C8:C12) -> 1.4605532e+09 | G13: =IF(G$4="","",SUM(G8:G12)) -> 1.8974784e+09 | H13: =IF(H$4="","",SUM(H8:H12)) -> 1.8885428e+09 | I13: =IF(I$4="","",SUM(I8:I12)) -> 1.2075511e+09 | J13: =IF(J$4="","",SUM(J8:J12)) -> 1.0791641e+09 | K13: =IF(K$4="","",SUM(K8:K12)) -> 7.7042127e+08 | L13: =IF(L$4="","",SUM(L8:L12)) -> 7.4129688e+08 | M13: =IF(M$4="","",SUM(M8:M12)) -> 4.7788522e+08 | N13: =IF(N$4="","",SUM(N8:N12)) -> 344123846 | ... Q13: =IF(Q$4="","",SUM(Q8:Q12))
B14: Income Tax | C14: =-SUM(C8+C11,C12)*C43 -> -3.6513831e+08 | G14: =Data!C46 -> -309204387 | H14: =Data!D46 -> -307004817 | I14: =Data!E46 -> -202660810 | J14: =Data!F46 -> -136628407 | K14: =Data!G46 -> -109313998 | L14: =Data!H46 -> -110812786 | M14: =Data!I46 -> -84670792 | N14: =Data!J46 -> -49833797 | ... Q14: =Data!M46
B15: NCI’s Share of Profits | C15: =-C4*C83 -> -194943.1 | G15: =Data!C48 -> -233229 | H15: =Data!D48 -> 0 | I15: =Data!E48 -> 0 | J15: =Data!F48 -> 0 | K15: =Data!G48 -> 0 | L15: =Data!H48 -> 0 | M15: =Data!I48 -> 0 | N15: =Data!J48 -> 0 | ... Q15: =Data!M48
B16: After-tax Profit | C16: =SUM(C13:C15) -> 1.09522e+09 | G16: =IF(G$4="","",SUM(G13:G15)) -> 1.5880407e+09 | H16: =IF(H$4="","",SUM(H13:H15)) -> 1.581538e+09 | I16: =IF(I$4="","",SUM(I13:I15)) -> 1.0048903e+09 | J16: =IF(J$4="","",SUM(J13:J15)) -> 9.4253573e+08 | K16: =IF(K$4="","",SUM(K13:K15)) -> 6.6110727e+08 | L16: =IF(L$4="","",SUM(L13:L15)) -> 6.304841e+08 | M16: =IF(M$4="","",SUM(M13:M15)) -> 3.9321443e+08 | N16: =IF(N$4="","",SUM(N13:N15)) -> 294290049 | ... Q16: =IF(Q$4="","",SUM(Q13:Q15))
B17: WCInv | C17: =-C4*C85 -> 0 | E17: WCInv is by default excluded
B18: Net Borrowing | C18: 0 | E18: Net borrowing is excluded
B19: FCFE | C19: =C16+C17 -> 1.09522e+09 | G19: =IF(G$4="","",G16+G17) -> 1.5880407e+09 | H19: =IF(H$4="","",H16+H17) -> 1.581538e+09 | I19: =IF(I$4="","",I16+I17) -> 1.0048903e+09 | J19: =IF(J$4="","",J16+J17) -> 9.4253573e+08 | K19: =IF(K$4="","",K16+K17) -> 6.6110727e+08 | L19: =IF(L$4="","",L16+L17) -> 6.304841e+08 | M19: =IF(M$4="","",M16+M17) -> 3.9321443e+08 | N19: =IF(N$4="","",N16+N17) -> 294290049 | ... Q19: =IF(Q$4="","",Q16+Q17)
B21: Operating Cost Structure | E21: Notes
B22: Variable Costs
B23: COGS | C23: =-C4*C28 -> -4.3636638e+09 | G23: =Data!C37 -> -5114327878 | H23: =Data!D37 -> -3915820963 | I23: =Data!E37 -> -3767200164 | J23: =Data!F37 -> -3505125804 | K23: =Data!G37 -> -1936776307 | L23: =Data!H37 -> -1447475772 | M23: =Data!I37 -> -1008193651 | N23: =Data!J37 -> -672472586 | ... Q23: =Data!M37
B24: Selling Expenses | C24: =-C4*C29 -> -2.1220499e+08 | G24: =Data!C40 -> -253881041 | H24: =Data!D40 -> -232460848 | I24: =Data!E40 -> -157533022 | J24: =Data!F40 -> -110815428 | K24: =Data!G40 -> -99736422 | L24: =Data!H40 -> -104708887 | M24: =Data!I40 -> -91880229 | N24: =Data!J40 -> -50830792 | ... Q24: =Data!M40
B25: Variable Costs | C25: =C23+C24 -> -4.5758688e+09 | G25: =IF(G$4="","",G23+G24) -> -5368208919 | H25: =IF(H$4="","",H23+H24) -> -4148281811 | I25: =IF(I$4="","",I23+I24) -> -3924733186 | J25: =IF(J$4="","",J23+J24) -> -3615941232 | K25: =IF(K$4="","",K23+K24) -> -2036512729 | L25: =IF(L$4="","",L23+L24) -> -1552184659 | M25: =IF(M$4="","",M23+M24) -> -1100073880 | N25: =IF(N$4="","",N23+N24) -> -723303378 | ... Q25: =IF(Q$4="","",Q23+Q24)
B27: Variable Costs % of Sales
B28: COGS | C28: =AVERAGE(G28:J28) -> 0.66940944 | E28: Historical Average | G28: =IF(G$4="","",ABS(G23/G$4)) -> 0.65577437 | H28: =IF(H$4="","",ABS(H23/H$4)) -> 0.62038077 | I28: =IF(I$4="","",ABS(I23/I$4)) -> 0.69184473 | J28: =IF(J$4="","",ABS(J23/J$4)) -> 0.7096379 | K28: =IF(K$4="","",ABS(K23/K$4)) -> 0.65503369 | L28: =IF(L$4="","",ABS(L23/L$4)) -> 0.60580181 | M28: =IF(M$4="","",ABS(M23/M$4)) -> 0.59043692 | N28: =IF(N$4="","",ABS(N23/N$4)) -> 0.59031086 | ... Q28: =IF(Q$4="","",ABS(Q23/Q$4))
B29: =B24 -> Selling Expenses | C29: =G29 -> 0.032553384 | E29: Historical Average | G29: =IF(G$4="","",ABS(G24/G$4)) -> 0.032553384 | H29: =IF(H$4="","",ABS(H24/H$4)) -> 0.036828609 | I29: =IF(I$4="","",ABS(I24/I$4)) -> 0.028930873 | J29: =IF(J$4="","",ABS(J24/J$4)) -> 0.022435379 | K29: =IF(K$4="","",ABS(K24/K$4)) -> 0.033731679 | L29: =IF(L$4="","",ABS(L24/L$4)) -> 0.043823071 | M29: =IF(M$4="","",ABS(M24/M$4)) -> 0.05380859 | N29: =IF(N$4="","",ABS(N24/N$4)) -> 0.04462036 | ... Q29: =IF(Q$4="","",ABS(Q24/Q$4))
B30: Variable Costs | C30: =ABS(C25/$C$4) -> 0.70196282 | G30: =IF(G$4="","",ABS(G25/G$4)) -> 0.68832775 | H30: =IF(H$4="","",ABS(H25/H$4)) -> 0.65720937 | I30: =IF(I$4="","",ABS(I25/I$4)) -> 0.72077561 | J30: =IF(J$4="","",ABS(J25/J$4)) -> 0.73207328 | K30: =IF(K$4="","",ABS(K25/K$4)) -> 0.68876537 | L30: =IF(L$4="","",ABS(L25/L$4)) -> 0.64962488 | M30: =IF(M$4="","",ABS(M25/M$4)) -> 0.64424551 | N30: =IF(N$4="","",ABS(N25/N$4)) -> 0.63493122 | ... Q30: =IF(Q$4="","",ABS(Q25/Q$4))
B32: Fixed Costs
B33: G&A and other Opex | C33: =G33 -> -224833898 | E33: Historical Average | G33: =Data!C41 -> -224833898 | H33: =Data!D41 -> -141225031 | I33: =Data!E41 -> -123453949 | J33: =Data!F41 -> -88435345 | K33: =Data!G41 -> -57377625 | L33: =Data!H41 -> -57327987 | M33: =Data!I41 -> -56653756 | N33: =Data!J41 -> -71756602 | ... Q33: =Data!M41
B34: R&D | C34: =G34 -> -255918596 | E34: Historical Average | G34: =Data!C42 -> -255918596 | H34: =Data!D42 -> -220006702 | I34: =Data!E42 -> -202331051 | J34: =Data!F42 -> -154945424 | K34: =Data!G42 -> -104720121 | L34: =Data!H42 -> -79166101 | M34: =Data!I42 -> -61487163 | N34: =Data!J42 -> 0 | ... Q34: =Data!M42
B35: Fixed Costs | C35: =C33+C34 -> -480752494 | G35: =IF(G4="","",G33+G34) -> -480752494 | H35: =IF(H4="","",H33+H34) -> -361231733 | I35: =IF(I4="","",I33+I34) -> -325785000 | J35: =IF(J4="","",J33+J34) -> -243380769 | K35: =IF(K4="","",K33+K34) -> -162097746 | L35: =IF(L4="","",L33+L34) -> -136494088 | M35: =IF(M4="","",M33+M34) -> -118140919 | N35: =IF(N4="","",N33+N34) -> -71756602 | ... Q35: =IF(Q4="","",Q33+Q34)
B37: Fixed Costs % of Sales
B38: =B33 -> G&A and other Opex | C38: =ABS(C33/$C$4) -> 0.034490726 | G38: =IF(G$4="","",ABS(G33/G$4)) -> 0.028828873 | H38: =IF(H$4="","",ABS(H33/H$4)) -> 0.022374182 | I38: =IF(I$4="","",ABS(I33/I$4)) -> 0.022672266 | J38: =IF(J$4="","",ABS(J33/J$4)) -> 0.017904371 | K38: =IF(K$4="","",ABS(K33/K$4)) -> 0.019405585 | L38: =IF(L$4="","",ABS(L33/L$4)) -> 0.023993077 | M38: =IF(M$4="","",ABS(M33/M$4)) -> 0.033178615 | N38: =IF(N$4="","",ABS(N33/N$4)) -> 0.062989485 | ... Q38: =IF(Q$4="","",ABS(Q33/Q$4))
B39: =B34 -> R&D | C39: =ABS(C34/$C$4) -> 0.039259286 | G39: =IF(G$4="","",ABS(G34/G$4)) -> 0.032814645 | H39: =IF(H$4="","",ABS(H34/H$4)) -> 0.034855507 | I39: =IF(I$4="","",ABS(I34/I$4)) -> 0.037158013 | J39: =IF(J$4="","",ABS(J34/J$4)) -> 0.031369814 | K39: =IF(K$4="","",ABS(K34/K$4)) -> 0.035417207 | L39: =IF(L$4="","",ABS(L34/L$4)) -> 0.033132829 | M39: =IF(M$4="","",ABS(M34/M$4)) -> 0.036009244 | N39: =IF(N$4="","",ABS(N34/N$4)) -> 0 | ... Q39: =IF(Q$4="","",ABS(Q34/Q$4))
B40: Fixed Costs | C40: =ABS(C35/$C$4) -> 0.073750012 | G40: =IF(G$4="","",ABS(G35/G$4)) -> 0.061643518 | H40: =IF(H$4="","",ABS(H35/H$4)) -> 0.05722969 | I40: =IF(I$4="","",ABS(I35/I$4)) -> 0.059830279 | J40: =IF(J$4="","",ABS(J35/J$4)) -> 0.049274185 | K40: =IF(K$4="","",ABS(K35/K$4)) -> 0.054822792 | L40: =IF(L$4="","",ABS(L35/L$4)) -> 0.057125906 | M40: =IF(M$4="","",ABS(M35/M$4)) -> 0.069187859 | N40: =IF(N$4="","",ABS(N35/N$4)) -> 0.062989485 | ... Q40: =IF(Q$4="","",ABS(Q35/Q$4))
B42: Tax % of Pre-tax Profit
B43: Income Tax Rate | C43: 0.25 | E43: Use the highest past tax rate | G43: =IF(G$4="","",-G14/SUM(G8+G11,G12)) -> 0.16295542 | H43: =IF(H$4="","",-H14/SUM(H8+H11,H12)) -> 0.16256175 | I43: =IF(I$4="","",-I14/SUM(I8+I11,I12)) -> 0.16782794 | J43: =IF(J$4="","",-J14/SUM(J8+J11,J12)) -> 0.12660577 | K43: =IF(K$4="","",-K14/SUM(K8+K11,K12)) -> 0.1418886 | L43: =IF(L$4="","",-L14/SUM(L8+L11,L12)) -> 0.14948503 | M43: =IF(M$4="","",-M14/SUM(M8+M11,M12)) -> 0.17717809 | N43: =IF(N$4="","",-N14/SUM(N8+N11,N12)) -> 0.14481355 | ... Q43: =IF(Q$4="","",-Q14/SUM(Q8+Q11,Q12))
B45: Non-operating Income | E45: Notes
B46: Interest
B47: Interest Expense | C47: =-BS!G31*Normalized_FCF!C54 -> -10773913 | G47: =Data!C51 -> -10773913 | H47: =Data!D51 -> -19213222 | I47: =Data!E51 -> -16787986 | J47: =Data!F51 -> -5280756 | K47: =Data!G51 -> -1093564 | L47: =Data!H51 -> -2759318 | M47: =Data!I51 -> -1307356 | N47: =Data!J51 -> 0 | ... Q47: =Data!M51
B48: Operating Interest Income | C48: =BS!D75*C53 -> 9271615.3 | G48: =IFERROR(IF(G$4="","",($C$48/$C$49)*G49),0) -> 28583681 | H48: =IFERROR(IF(H$4="","",($C$48/$C$49)*H49),0) -> 29085070 | I48: =IFERROR(IF(I$4="","",($C$48/$C$49)*I49),0) -> 9571612.1 | J48: =IFERROR(IF(J$4="","",($C$48/$C$49)*J49),0) -> 2951467.3 | K48: =IFERROR(IF(K$4="","",($C$48/$C$49)*K49),0) -> 2281463.9 | L48: =IFERROR(IF(L$4="","",($C$48/$C$49)*L49),0) -> 4518604.7 | M48: =IFERROR(IF(M$4="","",($C$48/$C$49)*M49),0) -> 2573521 | N48: =IFERROR(IF(N$4="","",($C$48/$C$49)*N49),0) -> 0 | ... Q48: =IFERROR(IF(Q$4="","",($C$48/$C$49)*Q49),0)
B49: From Interest Income | C49: =BS!$C$66*C53 -> 50780174 | G49: =Data!C52 -> 156551394 | H49: =Data!D52 -> 159297476 | I49: =Data!E52 -> 52423241 | J49: =Data!F52 -> 16165039 | K49: =Data!G52 -> 12495464 | L49: =Data!H52 -> 24748172 | M49: =Data!I52 -> 14095046 | N49: =Data!J52 -> 0 | ... Q49: =Data!M52
B50: Net Interest Income | C50: =C47+C48 -> -1502297.7 | G50: =IF(G$4="","",(G47+G48)) -> 17809768 | H50: =IF(H$4="","",(H47+H48)) -> 9871848.2 | I50: =IF(I$4="","",(I47+I48)) -> -7216373.9 | J50: =IF(J$4="","",(J47+J48)) -> -2329288.7 | K50: =IF(K$4="","",(K47+K48)) -> 1187899.9 | L50: =IF(L$4="","",(L47+L48)) -> 1759286.7 | M50: =IF(M$4="","",(M47+M48)) -> 1266165 | N50: =IF(N$4="","",(N47+N48)) -> 0 | ... Q50: =IF(Q$4="","",(Q47+Q48))
B52: % Interest | G52: Latest Asset Value
B53: Interest Yield/Cash | C53: 0.01 | E53: Reference the market rate | G53: =IF(Normalized_FCF!G4="","",Normalized_FCF!G49/BS!$C$66) -> 0.030829236
B54: Interest Rate/Debt | C54: =G54 -> 0.020195488 | E54: Use Last year's rate | G54: =IFERROR(ABS(Normalized_FCF!G47/BS!$G$31),0) -> 0.020195488
B55: Pre-tax Profit/Interest Expense | C55: =-C8/C47 -> 135.7033 | G55: =IF(G4="","",-G8/G47) -> 180.98833 | H55: =IF(H4="","",-H8/H47) -> 93.813016 | I55: =IF(I4="","",-I8/I47) -> 71.160081 | J55: =IF(J4="","",-J8/J47) -> 204.51503 | K55: =IF(K4="","",-K8/K47) -> 693.28163 | L55: =IF(L4="","",-L8/L47) -> 253.93107 | M55: =IF(M4="","",-M8/M47) -> 374.28482 | N55: =IF(N4="","",-N8/N47) -> #DIV/0! | ... Q55: =IF(Q4="","",-Q8/Q47)
B57: Non-operating EBIT | G57: Latest Asset Value
B58: Dividend or Interests from FA | C58: =BS!$C67*C66 -> 0 | G58: =Data!C56 -> 0 | H58: =Data!D56 -> 0 | I58: =Data!E56 -> 0 | J58: =Data!F56 -> 0 | K58: =Data!G56 -> 0 | L58: =Data!H56 -> 0 | M58: =Data!I56 -> 0 | N58: =Data!J56 -> 0 | ... Q58: =Data!M56
B59: Share of JV or associate Results | C59: =BS!$C68*C67 -> 0 | G59: =Data!C55 -> -70283969 | H59: =Data!D55 -> 76220632 | I59: =Data!E55 -> 20133006 | J59: =Data!F55 -> 1499444 | K59: =Data!G55 -> 11085542 | L59: =Data!H55 -> 38861023 | M59: =Data!I55 -> -12704453 | N59: =Data!J55 -> 0 | ... Q59: =Data!M55
B60: Investment property | C60: =BS!$C69*C68 -> 0 | G60: =Data!C57 -> 0 | H60: =Data!D57 -> 0 | I60: =Data!E57 -> 0 | J60: =Data!F57 -> 0 | K60: =Data!G57 -> 0 | L60: =Data!H57 -> 0 | M60: =Data!I57 -> 0 | N60: =Data!J57 -> 0 | ... Q60: =Data!M57
B61: Stable Non-Operating EBIT | C61: =SUM(C58:C60) -> 0 | G61: =IF(G4="","",SUM(G58:G60)) -> -70283969 | H61: =IF(H4="","",SUM(H58:H60)) -> 76220632 | I61: =IF(I4="","",SUM(I58:I60)) -> 20133006 | J61: =IF(J4="","",SUM(J58:J60)) -> 1499444 | K61: =IF(K4="","",SUM(K58:K60)) -> 11085542 | L61: =IF(L4="","",SUM(L58:L60)) -> 38861023 | M61: =IF(M4="","",SUM(M58:M60)) -> -12704453 | N61: =IF(N4="","",SUM(N58:N60)) -> 0 | ... Q61: =IF(Q4="","",SUM(Q58:Q60))
B62: Other Non-operating Income | C62: 0 | E62: Assume 0 | G62: =Data!C58 -> -87203308 | H62: =Data!D58 -> 155395094 | I62: =Data!E58 -> 209498088 | J62: =Data!F58 -> -71285916 | K62: =Data!G58 -> -7181078 | L62: =Data!H58 -> 43367572 | M62: =Data!I58 -> 75732522 | N62: =Data!J58 -> -11144508 | ... Q62: =Data!M58
B63: Total Non-Operating EBIT | C63: =C61+C62 -> 0 | G63: =IF(G4="","",G61+G62) -> -157487277 | H63: =IF(H4="","",H61+H62) -> 231615726 | I63: =IF(I4="","",I61+I62) -> 229631094 | J63: =IF(J4="","",J61+J62) -> -69786472 | K63: =IF(K4="","",K61+K62) -> 3904464 | L63: =IF(L4="","",L61+L62) -> 82228595 | M63: =IF(M4="","",M61+M62) -> 63028069 | N63: =IF(N4="","",N61+N62) -> -11144508 | ... Q63: =IF(Q4="","",Q61+Q62)
B65: Non-operating Asset Yield % | G65: Latest Asset Value
B66: Dividend or Interests from FA | C66: =G66 -> 0 | G66: =IFERROR(G58/BS!$C$67,0) -> 0
B67: JV or associate | C67: =G67 -> 0 | G67: =IFERROR(G59/BS!$C$68,0) -> 0
B68: Investment property | C68: =G68 -> 0 | G68: =IFERROR(G60/BS!$C$69,0) -> 0
B69: Stable Non-Operating EBIT | C69: =C61/BS!C70 -> 0 | G69: =G61/BS!C70 -> -0.013730327
B71: P&L & Dividend Analysis | E71: Notes
B72: P&L % Sales
B73: Variable Costs | C73: =ABS(C5/C$4) -> 0.70196282 | G73: =IF(G$4="","",ABS(G5/G$4)) -> 0.68832775 | H73: =IF(H$4="","",ABS(H5/H$4)) -> 0.65720937 | I73: =IF(I$4="","",ABS(I5/I$4)) -> 0.72077561 | J73: =IF(J$4="","",ABS(J5/J$4)) -> 0.73207328 | K73: =IF(K$4="","",ABS(K5/K$4)) -> 0.68876537 | L73: =IF(L$4="","",ABS(L5/L$4)) -> 0.64962488 | M73: =IF(M$4="","",ABS(M5/M$4)) -> 0.64424551 | N73: =IF(N$4="","",ABS(N5/N$4)) -> 0.63493122 | ... Q73: =IF(Q$4="","",ABS(Q5/Q$4))
B74: Contribution Margin | C74: =ABS(C6/C$4) -> 0.29803718 | G74: =IF(G$4="","",ABS(G6/G$4)) -> 0.31167225 | H74: =IF(H$4="","",ABS(H6/H$4)) -> 0.34279063 | I74: =IF(I$4="","",ABS(I6/I$4)) -> 0.27922439 | J74: =IF(J$4="","",ABS(J6/J$4)) -> 0.26792672 | K74: =IF(K$4="","",ABS(K6/K$4)) -> 0.31123463 | L74: =IF(L$4="","",ABS(L6/L$4)) -> 0.35037512 | M74: =IF(M$4="","",ABS(M6/M$4)) -> 0.35575449 | N74: =IF(N$4="","",ABS(N6/N$4)) -> 0.36506878 | ... Q74: =IF(Q$4="","",ABS(Q6/Q$4))
B75: Fixed Costs | C75: =ABS(C7/C$4) -> 0.073750012 | G75: =IF(G$4="","",ABS(G7/G$4)) -> 0.061643518 | H75: =IF(H$4="","",ABS(H7/H$4)) -> 0.05722969 | I75: =IF(I$4="","",ABS(I7/I$4)) -> 0.059830279 | J75: =IF(J$4="","",ABS(J7/J$4)) -> 0.049274185 | K75: =IF(K$4="","",ABS(K7/K$4)) -> 0.054822792 | L75: =IF(L$4="","",ABS(L7/L$4)) -> 0.057125906 | M75: =IF(M$4="","",ABS(M7/M$4)) -> 0.069187859 | N75: =IF(N$4="","",ABS(N7/N$4)) -> 0.062989485 | ... Q75: =IF(Q$4="","",ABS(Q7/Q$4))
B76: Operating EBIT | C76: =ABS(C8/C$4) -> 0.22428716 | G76: =IF(G$4="","",ABS(G8/G$4)) -> 0.25002873 | H76: =IF(H$4="","",ABS(H8/H$4)) -> 0.28556094 | I76: =IF(I$4="","",ABS(I8/I$4)) -> 0.21939412 | J76: =IF(J$4="","",ABS(J8/J$4)) -> 0.21865254 | K76: =IF(K$4="","",ABS(K8/K$4)) -> 0.25641184 | L76: =IF(L$4="","",ABS(L8/L$4)) -> 0.29324922 | M76: =IF(M$4="","",ABS(M8/M$4)) -> 0.28656663 | N76: =IF(N$4="","",ABS(N8/N$4)) -> 0.30207929 | ... Q76: =IF(Q$4="","",ABS(Q8/Q$4))
B77: Add Back D&A | C77: =ABS(C9/C$4) -> 0.032680346 | G77: =IF(G$4="","",G9/G$4) -> 0.027315676 | H77: =IF(H$4="","",H9/H$4) -> 0.021463355 | I77: =IF(I$4="","",I9/I$4) -> 0.01921029 | J77: =IF(J$4="","",J9/J$4) -> 0.015969416 | K77: =IF(K$4="","",K9/K$4) -> 0.013793124 | L77: =IF(L$4="","",L9/L$4) -> 0.01185708 | M77: =IF(M$4="","",M9/M$4) -> 0.014694375 | N77: =IF(N$4="","",N9/N$4) -> 0 | ... Q77: =IF(Q$4="","",Q9/Q$4)
B78: Maintenance Capex | C78: =MAX(AVERAGE(G78:J78),C77) -> 0.032680346 | E78: Historical Average or D&A | G78: =IF(G$4="","",-G10/G$4) -> 0.027315676 | H78: =IF(H$4="","",-H10/H$4) -> 0.021463355 | I78: =IF(I$4="","",-I10/I$4) -> 0.01921029 | J78: =IF(J$4="","",-J10/J$4) -> 0.015969416 | K78: =IF(K$4="","",-K10/K$4) -> 0.013793124 | L78: =IF(L$4="","",-L10/L$4) -> 0.01185708 | M78: =IF(M$4="","",-M10/M$4) -> 0.014694375 | N78: =IF(N$4="","",-N10/N$4) -> 0 | ... Q78: =IF(Q$4="","",-Q10/Q$4)
B79: Non-Operating EBIT | C79: =ABS(C11/C$4) -> 0 | G79: =IF(G$4="","",G11/G$4) -> -0.00901202 | H79: =IF(H$4="","",H11/H$4) -> 0.012075581 | I79: =IF(I$4="","",I11/I$4) -> 0.0036974181 | J79: =IF(J$4="","",J11/J$4) -> 0.00030357321 | K79: =IF(K$4="","",K11/K$4) -> 0.0037492216 | L79: =IF(L$4="","",L11/L$4) -> 0.016264229 | M79: =IF(M$4="","",M11/M$4) -> -0.0074402155 | N79: =IF(N$4="","",N11/N$4) -> 0 | ... Q79: =IF(Q$4="","",Q11/Q$4)
B80: Net Interest Income | C80: =ABS(C12/C$4) -> 0.00023046053 | G80: =IF(G$4="","",ABS(G12/G$4)) -> 0.0022836216 | H80: =IF(H$4="","",ABS(H12/H$4)) -> 0.00156399 | I80: =IF(I$4="","",ABS(I12/I$4)) -> 0.001325284 | J80: =IF(J$4="","",ABS(J12/J$4)) -> 0.00047158123 | K80: =IF(K$4="","",ABS(K12/K$4)) -> 0.00040175754 | L80: =IF(L$4="","",ABS(L12/L$4)) -> 0.00073630182 | M80: =IF(M$4="","",ABS(M12/M$4)) -> 0.00074151485 | N80: =IF(N$4="","",ABS(N12/N$4)) -> 0 | ... Q80: =IF(Q$4="","",ABS(Q12/Q$4))
B81: Pre-tax Profit | C81: =C13/C4 -> 0.2240567 | G81: =IF(G$4="","",G13/G$4) -> 0.24330033 | H81: =IF(H$4="","",H13/H$4) -> 0.29920051 | I81: =IF(I$4="","",I13/I$4) -> 0.22176625 | J81: =IF(J$4="","",J13/J$4) -> 0.21848453 | K81: =IF(K$4="","",K13/K$4) -> 0.26056282 | L81: =IF(L$4="","",L13/L$4) -> 0.31024975 | M81: =IF(M$4="","",M13/M$4) -> 0.27986793 | N81: =IF(N$4="","",N13/N$4) -> 0.30207929 | ... Q81: =IF(Q$4="","",Q13/Q$4)
B82: Income Tax | C82: =ABS(C14/C$4) -> 0.056014176 | G82: =IF(G$4="","",ABS(G14/G$4)) -> 0.039647108 | H82: =IF(H$4="","",ABS(H14/H$4)) -> 0.048638558 | I82: =IF(I$4="","",ABS(I14/I$4)) -> 0.037218573 | J82: =IF(J$4="","",ABS(J14/J$4)) -> 0.027661402 | K82: =IF(K$4="","",ABS(K14/K$4)) -> 0.036970894 | L82: =IF(L$4="","",ABS(L14/L$4)) -> 0.046377692 | M82: =IF(M$4="","",ABS(M14/M$4)) -> 0.049586467 | N82: =IF(N$4="","",ABS(N14/N$4)) -> 0.043745176 | ... Q82: =IF(Q$4="","",ABS(Q14/Q$4))
B83: =B15 -> NCI’s Share of Profits | C83: =MIN(BS!C62,MAX(G83:K83)) -> 2.9905318e-05 | G83: =IF(G$4="","",-G15/G$4) -> 2.9905318e-05 | H83: =IF(H$4="","",-H15/H$4) -> 0 | I83: =IF(I$4="","",-I15/I$4) -> 0 | J83: =IF(J$4="","",-J15/J$4) -> 0 | K83: =IF(K$4="","",-K15/K$4) -> 0 | L83: =IF(L$4="","",-L15/L$4) -> 0 | M83: =IF(M$4="","",-M15/M$4) -> 0 | N83: =IF(N$4="","",-N15/N$4) -> 0 | ... Q83: =IF(Q$4="","",-Q15/Q$4)
B84: After-tax Profit | C84: =ABS(C16/C$4) -> 0.16801262 | G84: =IF(G$4="","",ABS(G16/G$4)) -> 0.20362332 | H84: =IF(H$4="","",ABS(H16/H$4)) -> 0.25056195 | I84: =IF(I$4="","",ABS(I16/I$4)) -> 0.18454768 | J84: =IF(J$4="","",ABS(J16/J$4)) -> 0.19082313 | K84: =IF(K$4="","",ABS(K16/K$4)) -> 0.22359192 | L84: =IF(L$4="","",ABS(L16/L$4)) -> 0.26387205 | M84: =IF(M$4="","",ABS(M16/M$4)) -> 0.23028147 | N84: =IF(N$4="","",ABS(N16/N$4)) -> 0.25833412 | ... Q84: =IF(Q$4="","",ABS(Q16/Q$4))
B85: WCInv | C85: 0 | E85: =E17 -> WCInv is by default excluded
B86: Net Borrowing | C86: 0 | E86: =E18 -> Net borrowing is excluded
B87: Total FCFE | C87: =ABS(C19/C$4) -> 0.16801262 | G87: =IF(G$4="","",ABS(G19/G$4)) -> 0.20362332 | H87: =IF(H$4="","",ABS(H19/H$4)) -> 0.25056195 | I87: =IF(I$4="","",ABS(I19/I$4)) -> 0.18454768 | J87: =IF(J$4="","",ABS(J19/J$4)) -> 0.19082313 | K87: =IF(K$4="","",ABS(K19/K$4)) -> 0.22359192 | L87: =IF(L$4="","",ABS(L19/L$4)) -> 0.26387205 | M87: =IF(M$4="","",ABS(M19/M$4)) -> 0.23028147 | N87: =IF(N$4="","",ABS(N19/N$4)) -> 0.25833412 | ... Q87: =IF(Q$4="","",ABS(Q19/Q$4))
B89: Dividends
B90: ="Dividend per share ("&Market_currency&")" -> Dividend per share (CNY) | C90: =G90 -> 1 | G90: =Data!C65 -> 1 | H90: =Data!D65 -> 1 | I90: =Data!E65 -> 0.5 | J90: =Data!F65 -> 0 | K90: =Data!G65 -> 0 | L90: =Data!H65 -> 0 | M90: =Data!I65 -> 0 | N90: =Data!J65 -> 0 | ... Q90: =Data!M65
B91: ="Dividend ("&Market_currency&")" -> Dividend (CNY) | C91: =C90*Common_Shares/scaling_factor -> 506347879 | G91: =IF(G$4="","",G90*Common_Shares/scaling_factor) -> 506347879 | H91: =IF(H$4="","",H90*Common_Shares/scaling_factor) -> 506347879 | I91: =IF(I$4="","",I90*Common_Shares/scaling_factor) -> 2.5317394e+08 | J91: =IF(J$4="","",J90*Common_Shares/scaling_factor) -> 0 | K91: =IF(K$4="","",K90*Common_Shares/scaling_factor) -> 0 | L91: =IF(L$4="","",L90*Common_Shares/scaling_factor) -> 0 | M91: =IF(M$4="","",M90*Common_Shares/scaling_factor) -> 0 | N91: =IF(N$4="","",N90*Common_Shares/scaling_factor) -> 0 | ... Q91: =IF(Q$4="","",Q90*Common_Shares/scaling_factor)
B92: Payout Ratio | C92: =C90/(C19*scaling_factor/Common_Shares) -> 0.46232527 | G92: =IF(G$4="","",G90/(G19*scaling_factor/Common_Shares)) -> 0.31885068 | H92: =IF(H$4="","",H90/(H19*scaling_factor/Common_Shares)) -> 0.3201617 | I92: =IF(I$4="","",I90/(I19*scaling_factor/Common_Shares)) -> 0.25194188 | J92: =IF(J$4="","",J90/(J19*scaling_factor/Common_Shares)) -> 0 | K92: =IF(K$4="","",K90/(K19*scaling_factor/Common_Shares)) -> 0 | L92: =IF(L$4="","",L90/(L19*scaling_factor/Common_Shares)) -> 0 | M92: =IF(M$4="","",M90/(M19*scaling_factor/Common_Shares)) -> 0 | N92: =IF(N$4="","",N90/(N19*scaling_factor/Common_Shares)) -> 0 | ... Q92: =IF(Q$4="","",Q90/(Q19*scaling_factor/Common_Shares))
B93: Dividend Yield | C93: =C90/Market_Price -> 0.021772262 | G93: =IF(G$4="","",G90/Market_Price) -> 0.021772262 | H93: =IF(H$4="","",H90/Market_Price) -> 0.021772262 | I93: =IF(I$4="","",I90/Market_Price) -> 0.010886131 | J93: =IF(J$4="","",J90/Market_Price) -> 0 | K93: =IF(K$4="","",K90/Market_Price) -> 0 | L93: =IF(L$4="","",L90/Market_Price) -> 0 | M93: =IF(M$4="","",M90/Market_Price) -> 0 | N93: =IF(N$4="","",N90/Market_Price) -> 0 | ... Q93: =IF(Q$4="","",Q90/Market_Price)
B95: YoY %
B96: Sales | C96: =C4/G4-1 -> -0.16415583 | G96: =IF(H4="","",G4/H4-1) -> 0.23557646 | H96: =IF(I4="","",H4/I4-1) -> 0.15918952 | I96: =IF(J4="","",I4/J4-1) -> 0.10241026 | J96: =IF(K4="","",J4/K4-1) -> 0.67051733 | K96: =IF(L4="","",K4/L4-1) -> 0.23747116 | L96: =IF(M4="","",L4/M4-1) -> 0.39929823 | M96: =IF(N4="","",M4/N4-1) -> 0.49891375 | N96: =IF(O4="","",N4/O4-1) -> 0.63992177 | ... Q96: =IF(R4="","",Q4/R4-1)
B97: Pre-tax Profit | C97: =C13/G13-1 -> -0.2302662 | G97: =IF(H5="","",G13/H13-1) -> 0.0047314676 | H97: =IF(I5="","",H13/I13-1) -> 0.56394443 | I97: =IF(J5="","",I13/J13-1) -> 0.11896887 | J97: =IF(K5="","",J13/K13-1) -> 0.40074552 | K97: =IF(L5="","",K13/L13-1) -> 0.039288423 | L97: =IF(M5="","",L13/M13-1) -> 0.55120279 | M97: =IF(N5="","",M13/N13-1) -> 0.38870126 | N97: =IF(O5="","",N13/O13-1) -> 0.95148802 | ... Q97: =IF(R5="","",Q13/R13-1)
B99: Operating Efficiency Analysis | E99: Notes
B100: Balance Sheet | G100: Latest Asset Value
B101: Total Assets | C101: =BS!G32 -> 1.5353847e+10 | G101: =IF(G$4="","",G105+G104) -> 1.5353847e+10 | H101: =IF(H$4="","",H105+H104) -> 14207301142 | I101: =IF(I$4="","",I105+I104) -> 11801808511 | J101: =IF(J$4="","",J105+J104) -> 9574469630 | K101: =IF(K$4="","",K105+K104) -> 5869032275 | L101: =IF(L$4="","",L105+L104) -> 4859452594 | M101: =IF(M$4="","",M105+M104) -> 3633584727 | N101: =IF(N$4="","",N105+N104) -> 2778559461 | ... Q101: =IF(Q$4="","",Q105+Q104)
B102: Incl. AR | C102: =BS!C4 -> 2.4703637e+09 | G102: =IF(G$4="","",Data!D77) -> 2391271680 | H102: =IF(H$4="","",Data!E77) -> 2078427810 | I102: =IF(I$4="","",Data!F77) -> 1620191874 | J102: =IF(J$4="","",Data!G77) -> 635971724 | K102: =IF(K$4="","",Data!H77) -> 797615199 | L102: =IF(L$4="","",Data!I77) -> 0 | M102: =IF(M$4="","",Data!J77) -> 0 | N102: =IF(N$4="","",Data!K77) -> 0 | ... Q102: =IF(Q$4="","",Data!N77)
B103: Incl. Inventory | C103: =BS!C6+BS!C7 -> 2.3421363e+09 | G103: =IF(G$4="","",Data!D78) -> 1921374942 | H103: =IF(H$4="","",Data!E78) -> 1795225840 | I103: =IF(I$4="","",Data!F78) -> 1387177645 | J103: =IF(J$4="","",Data!G78) -> 941597028 | K103: =IF(K$4="","",Data!H78) -> 460791109 | L103: =IF(L$4="","",Data!I78) -> 0 | M103: =IF(M$4="","",Data!J78) -> 0 | N103: =IF(N$4="","",Data!K78) -> 0 | ... Q103: =IF(Q$4="","",Data!N78)
B104: Total Liabilities | C104: =BS!G30 -> 5.3156493e+09 | G104: =Data!C79 -> 5.3156493e+09 | H104: =Data!D79 -> 5242067251 | I104: =Data!E79 -> 4736625835 | J104: =Data!F79 -> 3596300871 | K104: =Data!G79 -> 2124874675 | L104: =Data!H79 -> 1651958950 | M104: =Data!I79 -> 1032202540 | N104: =Data!J79 -> 576053698 | ... Q104: =Data!M79
B105: Total Equity | C105: =BS!G27 -> 1.0038197e+10 | G105: =Data!C80 -> 1.0038197e+10 | H105: =Data!D80 -> 8965233891 | I105: =Data!E80 -> 7065182676 | J105: =Data!F80 -> 5978168759 | K105: =Data!G80 -> 3744157600 | L105: =Data!H80 -> 3207493644 | M105: =Data!I80 -> 2601382187 | N105: =Data!J80 -> 2202505763 | ... Q105: =Data!M80
B107: Operating Asset % of Sales | G107: Latest Asset Value
B108: AR | C108: =C102/C$4 -> 0.37896705 | G108: =IF(G$4="","",G102/G$4) -> 0.30661598 | H108: =IF(H$4="","",H102/H$4) -> 0.32928386 | I108: =IF(I$4="","",I102/I$4) -> 0.29754756 | J108: =IF(J$4="","",J102/J$4) -> 0.12875704 | K108: =IF(K$4="","",K102/K$4) -> 0.26976003 | L108: =IF(L$4="","",L102/L$4) -> 0 | M108: =IF(M$4="","",M102/M$4) -> 0 | N108: =IF(N$4="","",N102/N$4) -> 0 | ... Q108: =IF(Q$4="","",Q102/Q$4)
B109: Inventory | C109: =C103/C$4 -> 0.35929628 | G109: =IF(G$4="","",G103/G$4) -> 0.24636442 | H109: =IF(H$4="","",H103/H$4) -> 0.28441637 | I109: =IF(I$4="","",I103/I$4) -> 0.25475459 | J109: =IF(J$4="","",J103/J$4) -> 0.19063308 | K109: =IF(K$4="","",K103/K$4) -> 0.15584335 | L109: =IF(L$4="","",L103/L$4) -> 0 | M109: =IF(M$4="","",M103/M$4) -> 0 | N109: =IF(N$4="","",N103/N$4) -> 0 | ... Q109: =IF(Q$4="","",Q103/Q$4)
B110: Properties held for sale | C110: =BS!$G$38/C$4 -> 0 | G110: =BS!$G$38/G$4 -> 0
B112: Cash Flow Statement
B113: CFO/Net Income | G113: =IF(G$4="","",Data!C$22/Data!C15) -> 1.1764904 | H113: =IF(H$4="","",Data!D$22/Data!D15) -> 1.1929424 | I113: =IF(I$4="","",Data!E$22/Data!E15) -> 0.74504662 | J113: =IF(J$4="","",Data!F$22/Data!F15) -> 0.4224728 | K113: =IF(K$4="","",Data!G$22/Data!G15) -> 1.3427359 | L113: =IF(L$4="","",Data!H$22/Data!H15) -> 1.0029926 | M113: =IF(M$4="","",Data!I$22/Data!I15) -> 0.86522667 | N113: =IF(N$4="","",Data!J$22/Data!J15) -> 1.2315448 | ... Q113: =IF(Q$4="","",Data!M$22/Data!M15)
B114: CFO/FCFE | G114: =IF(G$4="","",Data!C$22/G19) -> 1.2068632 | H114: =IF(H$4="","",Data!D$22/H19) -> 1.4083741 | I114: =IF(I$4="","",Data!E$22/I19) -> 0.93214397 | J114: =IF(J$4="","",Data!F$22/J19) -> 0.39644303 | K114: =IF(K$4="","",Data!G$22/K19) -> 1.3488958 | L114: =IF(L$4="","",Data!H$22/L19) -> 1.1041648 | M114: =IF(M$4="","",Data!I$22/M19) -> 1.05722 | N114: =IF(N$4="","",Data!J$22/N19) -> 1.1849073 | ... Q114: =IF(Q$4="","",Data!M$22/Q19)
B116: ROE | G116: =IFERROR(IF(#REF!*G118*(1/#REF!)=G120,"","Error"),"") | H116: =IFERROR(IF(#REF!*H118*(1/#REF!)=H120,"","Error"),"") | I116: =IFERROR(IF(#REF!*I118*(1/#REF!)=I120,"","Error"),"") | J116: =IFERROR(IF(#REF!*J118*(1/#REF!)=J120,"","Error"),"") | K116: =IFERROR(IF(#REF!*K118*(1/#REF!)=K120,"","Error"),"") | L116: =IFERROR(IF(#REF!*L118*(1/#REF!)=L120,"","Error"),"") | M116: =IFERROR(IF(#REF!*M118*(1/#REF!)=M120,"","Error"),"") | N116: =IFERROR(IF(#REF!*N118*(1/#REF!)=N120,"","Error"),"") | ... Q116: =IFERROR(IF(#REF!*Q118*(1/#REF!)=Q120,"","Error"),"")
...

Sheet DCF
B2: No-Growth DCF Valuation | H2: Notes
B3: No-Growth DCF | C3: =scaling_factor -> 1 | E3: Special Assumption
B4: Adjusted FCFE | C4: =Normalized_FCF!C19 -> 1.09522e+09 | D4: =Reporting_currency -> CNY | E4: Terminal Growth Rate (g): | F4: =Terminal_Growth -> 0
B5: /Equity Cost of Capital | C5: =Equity_Cost -> 0.06
B6: Stable Income Value | C6: =(C4*(1+Terminal_Growth))/(Equity_Cost-Terminal_Growth) -> 1.8253666e+10 | D6: =Reporting_currency -> CNY | E6: Conservative Valuation: Setting g=0 can be a conservative assumption to avoid overestimating the stock’s value, especially if future growth is uncertain or unreliable.
B7: - Interest-bearing Debt | C7: =BS!G31 -> 5.3348119e+08 | D7: =Reporting_currency -> CNY
B8: + Non-operating Cash | C8: =BS!D66 -> 4.1508558e+09 | D8: =Reporting_currency -> CNY
B9: + Other Non-operating Assets | C9: =BS!H42 -> 1.2524075e+08 | D9: =Reporting_currency -> CNY
B10: Equity Value | C10: =C6-C7+C8+C9 -> 2.1996282e+10 | D10: =Reporting_currency -> CNY
B11: * Exchange rate | C11: =Exchange_Rate -> 1 | D11: =Thesis!C15 -> CNY
B12: Equity Value per share | C12: =(C10*scaling_factor)/Common_Shares*Exchange_Rate -> 43.441047 | D12: =Market_currency -> CNY
B14: Implied Growth Scenario Analysis
B15: FCFE Projection
B16: High Growth Period (HGP) | C16: =Scenarios!C65 -> 0.042510317
B17: High Growth Rate (HGR) | C17: =Scenarios!C64 -> 30
B18: Value Per Share | C18: =(F52-C7+C8+C9)*Exchange_Rate/Common_Shares*scaling_factor -> 64.595614 | D18: =Market_currency -> CNY
B20: Year | C20: FCFE | D20: Growth Rates | E20: Discount Factor | F20: PV of FCFE
B21: 1 | C21: =C4*(1+D21) -> 1.1417781e+09 | D21: =IF($C$17<B21,0,DCF!$C$16) -> 0.042510317 | E21: =IF($C$17<B21,0,1/(1+Equity_Cost)^B21) -> 0.94339623 | F21: =C21*E21 -> 1.0771492e+09
B22: 2 | C22: =IF(ROW()-ROW($C$21)<$C$17, $C$21*(1+D22)^(ROW()-ROW($C$21)), 0) -> 1.1903155e+09 | D22: =IF($C$17<B22,0,DCF!$C$16) -> 0.042510317 | E22: =IF($C$17<B22,0,1/(1+Equity_Cost)^B22) -> 0.88999644 | F22: =C22*E22 -> 1.0593765e+09
B23: 3 | C23: =IF(ROW()-ROW($C$21)<$C$17, $C$21*(1+D23)^(ROW()-ROW($C$21)), 0) -> 1.2409162e+09 | D23: =IF($C$17<B23,0,DCF!$C$16) -> 0.042510317 | E23: =IF($C$17<B23,0,1/(1+Equity_Cost)^B23) -> 0.83961928 | F23: =C23*E23 -> 1.0418971e+09
B24: 4 | C24: =IF(ROW()-ROW($C$21)<$C$17, $C$21*(1+D24)^(ROW()-ROW($C$21)), 0) -> 1.2936679e+09 | D24: =IF($C$17<B24,0,DCF!$C$16) -> 0.042510317 | E24: =IF($C$17<B24,0,1/(1+Equity_Cost)^B24) -> 0.79209366 | F24: =C24*E24 -> 1.0247062e+09
B25: 5 | C25: =IF(ROW()-ROW($C$21)<$C$17, $C$21*(1+D25)^(ROW()-ROW($C$21)), 0) -> 1.3486621e+09 | D25: =IF($C$17<B25,0,DCF!$C$16) -> 0.042510317 | E25: =IF($C$17<B25,0,1/(1+Equity_Cost)^B25) -> 0.74725817 | F25: =C25*E25 -> 1.0077988e+09
B26: 6 | C26: =IF(ROW()-ROW($C$21)<$C$17, $C$21*(1+D26)^(ROW()-ROW($C$21)), 0) -> 1.4059942e+09 | D26: =IF($C$17<B26,0,DCF!$C$16) -> 0.042510317 | E26: =IF($C$17<B26,0,1/(1+Equity_Cost)^B26) -> 0.70496054 | F26: =C26*E26 -> 9.9117043e+08
B27: 7 | C27: =IF(ROW()-ROW($C$21)<$C$17, $C$21*(1+D27)^(ROW()-ROW($C$21)), 0) -> 1.4657635e+09 | D27: =IF($C$17<B27,0,DCF!$C$16) -> 0.042510317 | E27: =IF($C$17<B27,0,1/(1+Equity_Cost)^B27) -> 0.66505711 | F27: =C27*E27 -> 9.7481641e+08
B28: 8 | C28: =IF(ROW()-ROW($C$21)<$C$17, $C$21*(1+D28)^(ROW()-ROW($C$21)), 0) -> 1.5280735e+09 | D28: =IF($C$17<B28,0,DCF!$C$16) -> 0.042510317 | E28: =IF($C$17<B28,0,1/(1+Equity_Cost)^B28) -> 0.62741237 | F28: =C28*E28 -> 9.5873223e+08
B29: 9 | C29: =IF(ROW()-ROW($C$21)<$C$17, $C$21*(1+D29)^(ROW()-ROW($C$21)), 0) -> 1.5930324e+09 | D29: =IF($C$17<B29,0,DCF!$C$16) -> 0.042510317 | E29: =IF($C$17<B29,0,1/(1+Equity_Cost)^B29) -> 0.59189846 | F29: =C29*E29 -> 9.4291344e+08
B30: 10 | C30: =IF(ROW()-ROW($C$21)<$C$17, $C$21*(1+D30)^(ROW()-ROW($C$21)), 0) -> 1.6607527e+09 | D30: =IF($C$17<B30,0,DCF!$C$16) -> 0.042510317 | E30: =IF($C$17<B30,0,1/(1+Equity_Cost)^B30) -> 0.55839478 | F30: =C30*E30 -> 9.2735565e+08
B31: 11 | C31: =IF(ROW()-ROW($C$21)<$C$17, $C$21*(1+D31)^(ROW()-ROW($C$21)), 0) -> 1.7313519e+09 | D31: =IF($C$17<B31,0,DCF!$C$16) -> 0.042510317 | E31: =IF($C$17<B31,0,1/(1+Equity_Cost)^B31) -> 0.52678753 | F31: =C31*E31 -> 9.1205456e+08
B32: 12 | C32: =IF(ROW()-ROW($C$21)<$C$17, $C$21*(1+D32)^(ROW()-ROW($C$21)), 0) -> 1.8049522e+09 | D32: =IF($C$17<B32,0,DCF!$C$16) -> 0.042510317 | E32: =IF($C$17<B32,0,1/(1+Equity_Cost)^B32) -> 0.49696936 | F32: =C32*E32 -> 8.9700593e+08
B33: 13 | C33: =IF(ROW()-ROW($C$21)<$C$17, $C$21*(1+D33)^(ROW()-ROW($C$21)), 0) -> 1.8816813e+09 | D33: =IF($C$17<B33,0,DCF!$C$16) -> 0.042510317 | E33: =IF($C$17<B33,0,1/(1+Equity_Cost)^B33) -> 0.46883902 | F33: =C33*E33 -> 8.822056e+08
... B50: 30 | C50: =IF(ROW()-ROW($C$21)<$C$17, $C$21*(1+D50)^(ROW()-ROW($C$21)), 0) -> 3.8186706e+09 | D50: =IF($C$17<B50,0,DCF!$C$16) -> 0.042510317 | E50: =IF($C$17<B50,0,1/(1+Equity_Cost)^B50) -> 0.17411013 | F50: =C50*E50 -> 6.6486925e+08
B51: Terminal Year | C51: =C$21*(1+Terminal_Growth)^$C$17/Equity_Cost -> 1.9029636e+10 | D51: =Terminal_Growth -> 0 | E51: =1/(1+Equity_Cost)^C17 -> 0.17411013 | F51: =C51*E51 -> 3.3132523e+09
E52: Total PV | F52: =SUM(F21:F51) -> 2.8965237e+10
B54: Sensitivity Analysis (Enterprise Value)
A55: =F52 -> 2.8965237e+10 | B55: =C78 -> 0 | C55: =C77 -> 0.02 | D55: =C76 -> 0.04 | E55: =C75 -> 0.06 | F55: =C74 -> 0.08
A56: 5 | B56: 1.8253666e+10 | C56: 1.8799492e+10 | D56: 1.935963e+10 | E56: 1.9934713e+10 | F56: 2.0525395e+10
A57: 10 | B57: 1.8253666e+10 | C57: 1.9314608e+10 | D57: 2.0478081e+10 | E57: 2.1756517e+10 | F57: 2.3163747e+10
A58: 15 | B58: 1.8253666e+10 | C58: 2.0013084e+10 | D58: 2.2075377e+10 | E58: 2.4501914e+10 | F58: 2.7366349e+10
A59: 20 | B59: 1.8253666e+10 | C59: 2.0793718e+10 | D59: 2.3961313e+10 | E59: 2.7937474e+10 | F59: 3.2956421e+10
A60: 25 | B60: 1.8253666e+10 | C60: 2.1590481e+10 | D60: 2.600004e+10 | E60: 3.1888764e+10 | F60: 3.9823276e+10
A61: 30 | B61: 1.8253666e+10 | C61: 2.2361954e+10 | D61: 2.8095759e+10 | E61: 3.6225437e+10 | F61: 4.7907715e+10
B63: Sensitivity Analysis (Equity Value per share)
B64: =B55 -> 0 | C64: =C55 -> 0.02 | D64: =D55 -> 0.04 | E64: =E55 -> 0.06 | F64: =F55 -> 0.08
A65: 0 | B65: =C12 -> 43.441047 | C65: =C12 -> 43.441047 | D65: =C12 -> 43.441047 | E65: =C12 -> 43.441047 | F65: =C12 -> 43.441047
A66: =A56 -> 5 | B66: =(B56-$C$7+$C$8+$C$9)/Common_Shares*$C$3*Exchange_Rate -> 43.441047 | C66: =(C56-$C$7+$C$8+$C$9)/Common_Shares*$C$3*Exchange_Rate -> 44.519012 | D66: =(D56-$C$7+$C$8+$C$9)/Common_Shares*$C$3*Exchange_Rate -> 45.625244 | E66: =(E56-$C$7+$C$8+$C$9)/Common_Shares*$C$3*Exchange_Rate -> 46.760991 | F66: =(F56-$C$7+$C$8+$C$9)/Common_Shares*$C$3*Exchange_Rate -> 47.927543
A67: =A57 -> 10 | B67: =(B57-$C$7+$C$8+$C$9)/Common_Shares*$C$3*Exchange_Rate -> 43.441047 | C67: =(C57-$C$7+$C$8+$C$9)/Common_Shares*$C$3*Exchange_Rate -> 45.536328 | D67: =(D57-$C$7+$C$8+$C$9)/Common_Shares*$C$3*Exchange_Rate -> 47.834103 | E67: =(E57-$C$7+$C$8+$C$9)/Common_Shares*$C$3*Exchange_Rate -> 50.35892 | F67: =(F57-$C$7+$C$8+$C$9)/Common_Shares*$C$3*Exchange_Rate -> 53.138096
A68: =A58 -> 15 | B68: =(B58-$C$7+$C$8+$C$9)/Common_Shares*$C$3*Exchange_Rate -> 43.441047 | C68: =(C58-$C$7+$C$8+$C$9)/Common_Shares*$C$3*Exchange_Rate -> 46.915768 | D68: =(D58-$C$7+$C$8+$C$9)/Common_Shares*$C$3*Exchange_Rate -> 50.988646 | E68: =(E58-$C$7+$C$8+$C$9)/Common_Shares*$C$3*Exchange_Rate -> 55.780878 | F68: =(F58-$C$7+$C$8+$C$9)/Common_Shares*$C$3*Exchange_Rate -> 61.437927
A69: =A59 -> 20 | B69: =(B59-$C$7+$C$8+$C$9)/Common_Shares*$C$3*Exchange_Rate -> 43.441047 | C69: =(C59-$C$7+$C$8+$C$9)/Common_Shares*$C$3*Exchange_Rate -> 48.457462 | D69: =(D59-$C$7+$C$8+$C$9)/Common_Shares*$C$3*Exchange_Rate -> 54.713231 | E69: =(E59-$C$7+$C$8+$C$9)/Common_Shares*$C$3*Exchange_Rate -> 62.565858 | F69: =(F59-$C$7+$C$8+$C$9)/Common_Shares*$C$3*Exchange_Rate -> 72.47791
A70: =A60 -> 25 | B70: =(B60-$C$7+$C$8+$C$9)/Common_Shares*$C$3*Exchange_Rate -> 43.441047 | C70: =(C60-$C$7+$C$8+$C$9)/Common_Shares*$C$3*Exchange_Rate -> 50.03101 | D70: =(D60-$C$7+$C$8+$C$9)/Common_Shares*$C$3*Exchange_Rate -> 58.739568 | E70: =(E60-$C$7+$C$8+$C$9)/Common_Shares*$C$3*Exchange_Rate -> 70.369366 | F70: =(F60-$C$7+$C$8+$C$9)/Common_Shares*$C$3*Exchange_Rate -> 86.039447
A71: =A61 -> 30 | B71: =(B61-$C$7+$C$8+$C$9)/Common_Shares*$C$3*Exchange_Rate -> 43.441047 | C71: =(C61-$C$7+$C$8+$C$9)/Common_Shares*$C$3*Exchange_Rate -> 51.554614 | D71: =(D61-$C$7+$C$8+$C$9)/Common_Shares*$C$3*Exchange_Rate -> 62.87846 | E71: =(E61-$C$7+$C$8+$C$9)/Common_Shares*$C$3*Exchange_Rate -> 78.933978 | F71: =(F61-$C$7+$C$8+$C$9)/Common_Shares*$C$3*Exchange_Rate -> 102.00562
B73: Scenarios | C73: HGR | D73: HGP | E73: Value per share | F73: Probabilities
B74: =Scenarios!B54 -> Snowball Scenario | C74: =Scenarios!C56 -> 0.08 | D74: =Scenarios!C55 -> 30 | E74: =INDEX(B$65:F$71, MATCH(D74, A$65:A$71, 0), MATCH(C74, B$64:F$64, 0)) -> 102.00562 | F74: =Scenarios!C58 -> 0.05
B75: =Scenarios!B36 -> Optimistic | C75: =Scenarios!C38 -> 0.06 | D75: =Scenarios!C37 -> 30 | E75: =INDEX(B$65:F$71, MATCH(D75, A$65:A$71, 0), MATCH(C75, B$64:F$64, 0)) -> 78.933978 | F75: =Scenarios!C40*(1-F$74-F$78) -> 0.18
B76: =Scenarios!B24 -> Base | C76: =Scenarios!C26 -> 0.04 | D76: =Scenarios!C25 -> 30 | E76: =INDEX(B$65:F$71, MATCH(D76, A$65:A$71, 0), MATCH(C76, B$64:F$64, 0)) -> 62.87846 | F76: =Scenarios!C28*(1-F$74-F$78) -> 0.54
B77: =Scenarios!B30 -> Pessimistic | C77: =Scenarios!C32 -> 0.02 | D77: =Scenarios!C31 -> 30 | E77: =INDEX(B$65:F$71, MATCH(D77, A$65:A$71, 0), MATCH(C77, B$64:F$64, 0)) -> 51.554614 | F77: =Scenarios!C34*(1-F$74-F$78) -> 0.18
B78: =Scenarios!B48 -> Devil's advocate | C78: =Scenarios!C50 -> 0 | D78: =Scenarios!C49 -> 30 | E78: =INDEX(B$65:F$71, MATCH(D78, A$65:A$71, 0), MATCH(C78, B$64:F$64, 0)) -> 43.441047 | F78: =Scenarios!C52 -> 0.05
B80: Note of the formulas: | C80: MATCH(1%, C65:E65, 0) finds the column number for HGR = 1%.
C81: MATCH(5, B66:B69, 0) finds the row number for HGP = 5.
C82: INDEX(C66:E69, ...) retrieves the value from the specified range.

Sheet DDM
B2: No-Growth DDM Valuation | H2: Notes
B3: No-Growth DDM | C3: =scaling_factor -> 1 | E3: Special Assumption
B4: Dividend | C4: =Normalized_FCF!C91 -> 506347879 | D4: =Market_currency -> CNY | E4: Terminal Growth Rate (g): | F4: =Thesis!E22 -> 0
B5: /Equity Cost of Capital | C5: =Equity_Cost -> 0.06
B6: Dividend Value | C6: =(C4*(1+Terminal_Growth))/(Equity_Cost-Terminal_Growth) -> 8.4391313e+09 | D6: =Reporting_currency -> CNY
B7: Dividend Value per share | C7: =(C6*scaling_factor)/Common_Shares*Exchange_Rate -> 16.666667 | D7: =Market_currency -> CNY
B9: Implied Growth Scenario Analysis
B10: FCFE Projection
B11: High Growth Period (HGP) | C11: =Scenarios!C65 -> 0.042510317
B12: High Growth Rate (HGR) | C12: =Scenarios!C64 -> 30
B13: Value Per Share | C13: =F47/Common_Shares*scaling_factor -> 26.446958 | D13: =Market_currency -> CNY
B15: Year | C15: Dividends | D15: Growth Rates | E15: Discount Factor | F15: PV of Dividends
B16: 1 | C16: =C4*(1+D16) -> 5.2787289e+08 | D16: =IF($C$12<B16,0,DDM!$C$11) -> 0.042510317 | E16: =IF($C$12<B16,0,1/(1+Equity_Cost)^B16) -> 0.94339623 | F16: =C16*E16 -> 4.9799329e+08
B17: 2 | C17: =IF(ROW()-ROW($C$16)<$C$12, $C$16*(1+D17)^(ROW()-ROW($C$16)), 0) -> 5.5031293e+08 | D17: =IF($C$12<B17,0,DDM!$C$11) -> 0.042510317 | E17: =IF($C$12<B17,0,1/(1+Equity_Cost)^B17) -> 0.88999644 | F17: =C17*E17 -> 4.8977655e+08
B18: 3 | C18: =IF(ROW()-ROW($C$16)<$C$12, $C$16*(1+D18)^(ROW()-ROW($C$16)), 0) -> 5.7370691e+08 | D18: =IF($C$12<B18,0,DDM!$C$11) -> 0.042510317 | E18: =IF($C$12<B18,0,1/(1+Equity_Cost)^B18) -> 0.83961928 | F18: =C18*E18 -> 4.8169538e+08
B19: 4 | C19: =IF(ROW()-ROW($C$16)<$C$12, $C$16*(1+D19)^(ROW()-ROW($C$16)), 0) -> 5.9809537e+08 | D19: =IF($C$12<B19,0,DDM!$C$11) -> 0.042510317 | E19: =IF($C$12<B19,0,1/(1+Equity_Cost)^B19) -> 0.79209366 | F19: =C19*E19 -> 4.7374755e+08
B20: 5 | C20: =IF(ROW()-ROW($C$16)<$C$12, $C$16*(1+D20)^(ROW()-ROW($C$16)), 0) -> 6.2352059e+08 | D20: =IF($C$12<B20,0,DDM!$C$11) -> 0.042510317 | E20: =IF($C$12<B20,0,1/(1+Equity_Cost)^B20) -> 0.74725817 | F20: =C20*E20 -> 4.6593086e+08
B21: 6 | C21: =IF(ROW()-ROW($C$16)<$C$12, $C$16*(1+D21)^(ROW()-ROW($C$16)), 0) -> 6.5002665e+08 | D21: =IF($C$12<B21,0,DDM!$C$11) -> 0.042510317 | E21: =IF($C$12<B21,0,1/(1+Equity_Cost)^B21) -> 0.70496054 | F21: =C21*E21 -> 4.5824314e+08
B22: 7 | C22: =IF(ROW()-ROW($C$16)<$C$12, $C$16*(1+D22)^(ROW()-ROW($C$16)), 0) -> 6.7765949e+08 | D22: =IF($C$12<B22,0,DDM!$C$11) -> 0.042510317 | E22: =IF($C$12<B22,0,1/(1+Equity_Cost)^B22) -> 0.66505711 | F22: =C22*E22 -> 4.5068226e+08
B23: 8 | C23: =IF(ROW()-ROW($C$16)<$C$12, $C$16*(1+D23)^(ROW()-ROW($C$16)), 0) -> 7.0646701e+08 | D23: =IF($C$12<B23,0,DDM!$C$11) -> 0.042510317 | E23: =IF($C$12<B23,0,1/(1+Equity_Cost)^B23) -> 0.62741237 | F23: =C23*E23 -> 4.4324614e+08
B24: 9 | C24: =IF(ROW()-ROW($C$16)<$C$12, $C$16*(1+D24)^(ROW()-ROW($C$16)), 0) -> 7.3649915e+08 | D24: =IF($C$12<B24,0,DDM!$C$11) -> 0.042510317 | E24: =IF($C$12<B24,0,1/(1+Equity_Cost)^B24) -> 0.59189846 | F24: =C24*E24 -> 4.3593271e+08
B25: 10 | C25: =IF(ROW()-ROW($C$16)<$C$12, $C$16*(1+D25)^(ROW()-ROW($C$16)), 0) -> 7.6780796e+08 | D25: =IF($C$12<B25,0,DDM!$C$11) -> 0.042510317 | E25: =IF($C$12<B25,0,1/(1+Equity_Cost)^B25) -> 0.55839478 | F25: =C25*E25 -> 4.2873995e+08
B26: 11 | C26: =IF(ROW()-ROW($C$16)<$C$12, $C$16*(1+D26)^(ROW()-ROW($C$16)), 0) -> 8.0044772e+08 | D26: =IF($C$12<B26,0,DDM!$C$11) -> 0.042510317 | E26: =IF($C$12<B26,0,1/(1+Equity_Cost)^B26) -> 0.52678753 | F26: =C26*E26 -> 4.2166587e+08
B27: 12 | C27: =IF(ROW()-ROW($C$16)<$C$12, $C$16*(1+D27)^(ROW()-ROW($C$16)), 0) -> 8.34475e+08 | D27: =IF($C$12<B27,0,DDM!$C$11) -> 0.042510317 | E27: =IF($C$12<B27,0,1/(1+Equity_Cost)^B27) -> 0.49696936 | F27: =C27*E27 -> 4.1470851e+08
B28: 13 | C28: =IF(ROW()-ROW($C$16)<$C$12, $C$16*(1+D28)^(ROW()-ROW($C$16)), 0) -> 8.699488e+08 | D28: =IF($C$12<B28,0,DDM!$C$11) -> 0.042510317 | E28: =IF($C$12<B28,0,1/(1+Equity_Cost)^B28) -> 0.46883902 | F28: =C28*E28 -> 4.0786594e+08
... B45: 30 | C45: =IF(ROW()-ROW($C$16)<$C$12, $C$16*(1+D45)^(ROW()-ROW($C$16)), 0) -> 1.7654679e+09 | D45: =IF($C$12<B45,0,DDM!$C$11) -> 0.042510317 | E45: =IF($C$12<B45,0,1/(1+Equity_Cost)^B45) -> 0.17411013 | F45: =C45*E45 -> 3.0738586e+08
B46: Terminal Year | C46: =C$16*(1+F4)^$C$12/Equity_Cost -> 8.7978815e+09 | D46: =Terminal_Growth -> 0 | E46: =1/(1+Equity_Cost)^C12 -> 0.17411013 | F46: =C46*E46 -> 1.5318003e+09
E47: Total PV | F47: =SUM(F16:F46) -> 1.3391361e+10
B49: Sensitivity Analysis (Enterprise Value)
A50: =F47 -> 1.3391361e+10 | B50: =C73 -> 0 | C50: =C72 -> 0.02 | D50: =C71 -> 0.04 | E50: =C70 -> 0.06 | F50: =C69 -> 0.08
A51: 5 | B51: 8.4391313e+09 | C51: 8.6914802e+09 | D51: 8.9504462e+09 | E51: 9.2163218e+09 | F51: 9.4894086e+09
A52: 10 | B52: 8.4391313e+09 | C52: 8.9296313e+09 | D52: 9.4675344e+09 | E52: 1.0058588e+10 | F52: 1.0709186e+10
A53: 15 | B53: 8.4391313e+09 | C53: 9.2525547e+09 | D53: 1.0206005e+10 | E53: 1.1327854e+10 | F53: 1.2652155e+10
A54: 20 | B54: 8.4391313e+09 | C54: 9.6134611e+09 | D54: 1.1077921e+10 | E54: 1.29162e+10 | F54: 1.5236586e+10
A55: 25 | B55: 8.4391313e+09 | C55: 9.9818249e+09 | D55: 1.2020476e+10 | E55: 1.4742981e+10 | F55: 1.8411307e+10
A56: 30 | B56: 8.4391313e+09 | C56: 1.0338497e+10 | D56: 1.298938e+10 | E56: 1.6747935e+10 | F56: 2.2148947e+10
B58: Sensitivity Analysis (Equity Value per share)
B59: =B50 -> 0 | C59: =C50 -> 0.02 | D59: =D50 -> 0.04 | E59: =E50 -> 0.06 | F59: =F50 -> 0.08
A60: 0 | B60: =C7 -> 16.666667 | C60: =C7 -> 16.666667 | D60: =C7 -> 16.666667 | E60: =C7 -> 16.666667 | F60: =C7 -> 16.666667
A61: =A51 -> 5 | B61: =B51/Common_Shares*$C$3*Exchange_Rate -> 16.666667 | C61: =C51/Common_Shares*$C$3*Exchange_Rate -> 17.165037 | D61: =D51/Common_Shares*$C$3*Exchange_Rate -> 17.676476 | E61: =E51/Common_Shares*$C$3*Exchange_Rate -> 18.201561 | F61: =F51/Common_Shares*$C$3*Exchange_Rate -> 18.740887
A62: =A52 -> 10 | B62: =B52/Common_Shares*$C$3*Exchange_Rate -> 16.666667 | C62: =C52/Common_Shares*$C$3*Exchange_Rate -> 17.635368 | D62: =D52/Common_Shares*$C$3*Exchange_Rate -> 18.697688 | E62: =E52/Common_Shares*$C$3*Exchange_Rate -> 19.864974 | F62: =F52/Common_Shares*$C$3*Exchange_Rate -> 21.149858
A63: =A53 -> 15 | B63: =B53/Common_Shares*$C$3*Exchange_Rate -> 16.666667 | C63: =C53/Common_Shares*$C$3*Exchange_Rate -> 18.273118 | D63: =D53/Common_Shares*$C$3*Exchange_Rate -> 20.156113 | E63: =E53/Common_Shares*$C$3*Exchange_Rate -> 22.371683 | F63: =F53/Common_Shares*$C$3*Exchange_Rate -> 24.987079
A64: =A54 -> 20 | B64: =B54/Common_Shares*$C$3*Exchange_Rate -> 16.666667 | C64: =C54/Common_Shares*$C$3*Exchange_Rate -> 18.985882 | D64: =D54/Common_Shares*$C$3*Exchange_Rate -> 21.878083 | E64: =E54/Common_Shares*$C$3*Exchange_Rate -> 25.50855 | F64: =F54/Common_Shares*$C$3*Exchange_Rate -> 30.091142
A65: =A55 -> 25 | B65: =B55/Common_Shares*$C$3*Exchange_Rate -> 16.666667 | C65: =C55/Common_Shares*$C$3*Exchange_Rate -> 19.713373 | D65: =D55/Common_Shares*$C$3*Exchange_Rate -> 23.73956 | E65: =E55/Common_Shares*$C$3*Exchange_Rate -> 29.116309 | F65: =F55/Common_Shares*$C$3*Exchange_Rate -> 36.360984
A66: =A56 -> 30 | B66: =B56/Common_Shares*$C$3*Exchange_Rate -> 16.666667 | C66: =C56/Common_Shares*$C$3*Exchange_Rate -> 20.417774 | D66: =D56/Common_Shares*$C$3*Exchange_Rate -> 25.653074 | E66: =E56/Common_Shares*$C$3*Exchange_Rate -> 33.075946 | F66: =F56/Common_Shares*$C$3*Exchange_Rate -> 43.74255
B68: Scenarios | C68: HGR | D68: HGP | E68: Value per share | F68: Probabilities
B69: =Scenarios!B54 -> Snowball Scenario | C69: =Scenarios!C56 -> 0.08 | D69: =Scenarios!C55 -> 30 | E69: =INDEX(B$60:F$66, MATCH(D69, A$60:A$66, 0), MATCH(C69, B$59:F$59, 0)) -> 43.74255 | F69: =Scenarios!C58 -> 0.05
B70: =Scenarios!B36 -> Optimistic | C70: =Scenarios!C38 -> 0.06 | D70: =Scenarios!C37 -> 30 | E70: =INDEX(B$60:F$66, MATCH(D70, A$60:A$66, 0), MATCH(C70, B$59:F$59, 0)) -> 33.075946 | F70: =Scenarios!C40*(1-F$69-F$73) -> 0.18
B71: =Scenarios!B24 -> Base | C71: =Scenarios!C26 -> 0.04 | D71: =Scenarios!C25 -> 30 | E71: =INDEX(B$60:F$66, MATCH(D71, A$60:A$66, 0), MATCH(C71, B$59:F$59, 0)) -> 25.653074 | F71: =Scenarios!C28*(1-F$69-F$73) -> 0.54
B72: =Scenarios!B30 -> Pessimistic | C72: =Scenarios!C32 -> 0.02 | D72: =Scenarios!C31 -> 30 | E72: =INDEX(B$60:F$66, MATCH(D72, A$60:A$66, 0), MATCH(C72, B$59:F$59, 0)) -> 20.417774 | F72: =Scenarios!C34*(1-F$69-F$73) -> 0.18
B73: =Scenarios!B48 -> Devil's advocate | C73: =Scenarios!C50 -> 0 | D73: =Scenarios!C49 -> 30 | E73: =INDEX(B$60:F$66, MATCH(D73, A$60:A$66, 0), MATCH(C73, B$59:F$59, 0)) -> 16.666667 | F73: =Scenarios!C52 -> 0.05
B75: Note of the formulas: | C75: MATCH(1%, C65:E65, 0) finds the column number for HGR = 1%.
C76: MATCH(5, B66:B69, 0) finds the row number for HGP = 5.
C77: INDEX(C66:E69, ...) retrieves the value from the specified range.

Sheet Scenarios
B2: Current Situation | H2: Warning: Do Not Remove this logic
B3: Selection | H3: 0 | I3: =-Market_Price -> -45.93
B4: Past Years Selected | C4: 3 | E4: Tie the business story into the three levers of value: FCFE, growth and risk. | H4: 1 | I4: =IF(ROW()-3 < $C$76, $C$77, IF(ROW()-3 = $C$76, $C$77 + $C$60, "")) -> 1
H5: 2 | I5: =IF(ROW()-3 < $C$76, $C$77, IF(ROW()-3 = $C$76, $C$77 + $C$60, "")) -> 1
B6: Latest | C6: =DCF!C3 -> 1 | E6: Prompt for fundamental Analysis | H6: 3 | I6: =IF(ROW()-3 < $C$76, $C$77, IF(ROW()-3 = $C$76, $C$77 + $C$60, "")) -> 65.714648
B7: EBIT | C7: =Normalized_FCF!G8 -> 1949952566 | D7: =Reporting_currency -> CNY | E7: ="Please develop three logical "&C18&"-year scenarios (Base Case, Pessimistic Case, Optimistic Case) and two extreme "&C46&"-year scenarios (Success Scenario, Devil’s Advocate Scenario) for "&Thesis!C5&"("&Thesis!C11&"). Each scenario should include the Compound Growth Rate, the Probability Assessment, and the Business Narrative." -> Please develop three logical 30-year scenarios (Base Case, Pessimistic Case, Optimistic Case) and two extreme 30-year scenarios (Success Scenario, Devil’s Advocate Scenario) for 浙江鼎力(603338.SS). Each scenario should include the Compound Growth Rate, the Probability Assessment, and the Business Narrative. | H7: 4 | I7: =IF(ROW()-3 < $C$76, $C$77, IF(ROW()-3 = $C$76, $C$77 + $C$60, ""))
B8: FCFE | C8: =Normalized_FCF!G19 -> 1.5880407e+09 | D8: =Reporting_currency -> CNY | H8: 5 | I8: =IF(ROW()-3 < $C$76, $C$77, IF(ROW()-3 = $C$76, $C$77 + $C$60, ""))
B9: Normalized | C9: =Normalized_FCF!C19 -> 1.09522e+09 | D9: =Reporting_currency -> CNY | H9: 6 | I9: =IF(ROW()-3 < $C$76, $C$77, IF(ROW()-3 = $C$76, $C$77 + $C$60, ""))
H10: 7 | I10: =IF(ROW()-3 < $C$76, $C$77, IF(ROW()-3 = $C$76, $C$77 + $C$60, ""))
B11: YoY CAGR | H11: 8 | I11: =IF(ROW()-3 < $C$76, $C$77, IF(ROW()-3 = $C$76, $C$77 + $C$60, ""))
B12: Sales | C12: =(Normalized_FCF!G4/OFFSET(Normalized_FCF!G4, 0, $C$4))^(1/$C$4) - 1 -> 0.16445428 | H12: 9 | I12: =IF(ROW()-3 < $C$76, $C$77, IF(ROW()-3 = $C$76, $C$77 + $C$60, ""))
B13: Operating EBIT | C13: =(Normalized_FCF!G8/OFFSET(Normalized_FCF!G8, 0, $C$4))^(1/$C$4) - 1 -> 0.21768298 | H13: 10 | I13: =IF(ROW()-3 < $C$76, $C$77, IF(ROW()-3 = $C$76, $C$77 + $C$60, ""))
B14: FCFE | C14: =(Normalized_FCF!G19/OFFSET(Normalized_FCF!G19, 0, $C$4))^(1/$C$4) - 1 -> 0.18992961
B16: General Scenarios
B17: Assumption | E17: Guidance Note
B18: High Growth Period (HGP) | C18: 30 | E18: Fundamental analysis and market signal analysis should be combined, with fundamental analysis given priority and market signal analysis serving as a supplement. Market signal analysis predicts a company's future trend, while fundamental analysis interprets the trend and identifies relevant fundamental factors and possibilities.
B20: Reference
B21: Market Price | C21: =Market_Price -> 45.93 | D21: =Market_currency -> CNY
B22: No Growth Value per share | C22: =IF(valuation_method="DCF",DCF!C12,DDM!C7) -> 43.441047 | D22: =Market_currency -> CNY
B24: Base | E24: Business Story
B25: High Growth Period (HGP) | C25: =C18 -> 30
B26: High Growth Rate (HGR) | C26: 0.04
B27: Value per share | C27: =IF(valuation_method="DCF",DCF!E76,DDM!E71) -> 62.87846 | D27: =Market_currency -> CNY
B28: Probabilities | C28: 0.6
B30: Pessimistic | E30: Business Story
B31: High Growth Period (HGP) | C31: =C18 -> 30
B32: High Growth Rate (HGR) | C32: 0.02
B33: Value per share | C33: =IF(valuation_method="DCF",DCF!E77,DDM!E72) -> 51.554614 | D33: =Market_currency -> CNY
B34: Probabilities | C34: 0.2
B36: Optimistic | E36: Business Story
B37: High Growth Period (HGP) | C37: =C18 -> 30
B38: High Growth Rate (HGR) | C38: 0.06
B39: Value per share | C39: =IF(valuation_method="DCF",DCF!E75,DDM!E70) -> 78.933978 | D39: =Market_currency -> CNY
B40: Probabilities | C40: =1-C28-C34 -> 0.2
B42: Expected Value = | C42: =C27*C28+C33*C34+C39*C40 -> 63.824794 | D42: =Market_currency -> CNY
B44: Extreme Scenarios
B45: Assumption
B46: High Growth Period (HGP) | C46: 30
B48: Devil's advocate | E48: Business Story
B49: High Growth Period (HGP) | C49: =C46 -> 30
B50: High Growth Rate (HGR) | C50: 0
B51: Value per share | C51: =IF(valuation_method="DCF",DCF!E78,DDM!E73) -> 43.441047 | D51: =Market_currency -> CNY
B52: Probabilities | C52: 0.05
B54: Snowball Scenario | E54: Business Story
B55: High Growth Period (HGP) | C55: =C46 -> 30
B56: High Growth Rate (HGR) | C56: 0.08
B57: Value per share | C57: =IF(valuation_method="DCF",DCF!E74,DDM!E69) -> 102.00562 | D57: =Market_currency -> CNY
B58: Probabilities | C58: 0.05
B60: Expected Value = | C60: =C51*C52+C57*C58+C42*(1-C52-C58) -> 64.714648 | D60: =Market_currency -> CNY | E60: is assumed to be materialized in | F60: =Thesis!F28 -> 3
B62: Growth Classification
B63: Equity Value Driving Factors | E63: Note on Manual Adjustments
B64: High Growth Period (HGP) | C64: =C18 -> 30 | E64: Use general Scenarios' HGP assumption
B65: High Growth Rate (HGR) | C65: 0.042510317 | E65: Use Excel Goal Seek to find the HGR
B66: Equity Value per share | C66: =IF(valuation_method="DCF",DCF!C18,DDM!C13) -> 64.595614 | D66: =Market_currency -> CNY | E66: Set to Expected Equity Value
B68: Type of Company | E68: Note on the logic
B69: Negative Growth | C69: =IF(C60<C22,"Y","N") -> N
B70: Low Growth | C70: =IF(C69="Y","N",IF(C65>8%,"N","Y")) -> Y | E70: >8% is Categorized as High Growth
B71: High Growth | C71: =IF(C65>8%,"Y","N") -> N
B72: Asset Play | C72: =IF(F72>50%,"Y","N") -> N | E72: The Non-FCF Value is of the Expected Value, at | F72: =BS!D89/C60 -> 0.11421512
B74: Margin of Safety (MOS)
B75: Inputs
B76: Expected Holding Period | C76: =F60 -> 3
B77: Annual Dividend per share | C77: =Normalized_FCF!C90 -> 1 | D77: =Market_currency -> CNY
B79: Target Price Output
B80: @Target Annual Return | C80: =Thesis!F29 -> 0.337
B81: PV(Dividends) | C81: =PV(C80, C76, -C77, 0) -> 1.7257757
B82: PV(Equity Value) | C82: =C60/(1+C80)^C76 -> 27.077488
B83: Buy Below | C83: =C81+C82 -> 28.803264 | D83: =Market_currency -> CNY | E83: at a MOS of | F83: =(1-C83/C60) -> 0.55491895
B85: Current Return Output
B86: @Market Price | C86: =Market_Price -> 45.93 | D86: =Market_currency -> CNY
B87: Annual Return | C87: =IRR(OFFSET($I$3, 0, 0, $C$76 + 1, 1)) -> 0.14060796
B89: Entry Price Output
B90: @ Entry Yield | C90: =Thesis!F30 -> 0.187
B91: PV(Dividends) | C91: =PV(C90, C76, -C77, 0) -> 2.1501254
B92: PV(Equity Value) | C92: =C60/(1+C90)^C76 -> 38.694607
B93: Buy Below | C93: =C91+C92 -> 40.844732 | D93: =Market_currency -> CNY | E93: at a MOS of | F93: =(1-C93/C60) -> 0.36884873
B95: Sell Price Output
B96: @Selling Yield | C96: =Thesis!F31 -> 0.06
B97: PV(Dividends) | C97: =PV(C96, C76, -C77, 0) -> 2.6730119
B98: PV(Equity Value) | C98: =C60/(1+C96)^C76 -> 54.335666
B99: Sell Above | C99: =C97+C98 -> 57.008678 | D99: HKD | E99: at a MOS of | F99: =(1-C99/C60) -> 0.11907613
B101: Exit Price Output
B102: @Benchmark Yield | C102: =Thesis!F32 -> 0.087
B103: PV(Dividends) | C103: =PV(C102, C76, -C77, 0) -> 2.5448901
B104: PV(Equity Value) | C104: =C60/(1+C102)^C76 -> 50.386473
B105: Sell Above | C105: =C103+C104 -> 52.931363 | D105: HKD | E105: at a MOS of | F105: =(1-C105/C66) -> 0.18057342
E107: Inputs Legend
E108: Font Color | F108: Fact or Verified Data
E109: Font Color | F109: Subjective Driving Factors
E110: Font Color | F110: Subjective Non-Driving Factors
