Workbook
Name Common_Shares: Thesis!$C$6
Name dividend_tax_rate: Normalized_FCF!$C$91
Name Equity_Cost: Thesis!$C$86
Name Exchange_Rate: Thesis!$C$16
Name Market_currency: Thesis!$C$13
Name Market_Price: Thesis!$C$12
Name Reporting_currency: Thesis!$C$25
Name scaling_factor: Data!$C$3
Name Terminal_Growth: Thesis!$C$92
Name valuation_method: Thesis!$E$23

Sheet Thesis
B1: Model last updated: | C1: 45917 | D1: INT | E1: Selected: | F1: N
A2: Executive Summary
B4: Company Information
B5: Company Name: | C5: 海底捞
B6: Number of Shares: | C6: 5574000000
B7: Report Interval: | C7: 6
B8: Update Required After: | C8: =EOMONTH(EDATE(BS!C1,C7+2),0) -> 46265
B10: Listing Information
B11: Symbol: | C11: 6862.HK
B12: Market Price: | C12: 13.11
B13: Market Currency: | C13: HKD
B14: Market Capitalization: | C14: =Thesis!C12*Common_Shares/1000000 -> 73075.14 | D14: =IF(D11="","",Thesis!D12*Common_Shares/1000000)
B15: Forex Symbol: | C15: =IF(C25=C13,C13,C25&"/"&C13) -> CNY/HKD | D15: =IF(D11="","",IF(C25=D13,D13,C25&"/"&D13))
B16: Exchange Rate: | C16: 1.0923594
B18: Guidance Note: This model evaluates the company using a structured investment process to determine its intrinsic value and target prices. It focuses on sustainable FCF capacity, adjusts for financial structure, incorporates growth scenarios, and calculates expected returns based on the derived intrinsic value.
B20: Valuation Conclusion
B21: Growth Classification: | C21: =IF(Scenarios!C74="Y",Scenarios!B74,"")&IF(Scenarios!C75="Y",Scenarios!B75,"")&IF(Scenarios!C76="Y",Scenarios!B76,"")&" "&IF(Scenarios!C77="Y",Scenarios!B77,"") -> Low Growth
B22: Comp_Sector: | C22: CNS_01
B23: Business Model Risk Premium: | C23: N | D23: Valuation Method | E23: DCF
B24: Management Risk Premium: | C24: N | D24: Base equity cost | E24: 0.075
B25: Reporting Currency: | C25: CNY | D25: Holding Period | E25: 3
B26: ="Expected Equity Value ("&C13&") :" -> Expected Equity Value (HKD) : | C26: =C132 -> 12.001067 | D26: Market Implied Annual Return: | E26: =Scenarios!C92 -> -0.029030191
B28: Price Targets | C28: =C145&" ("&Market_currency&")" -> 6862.HK (HKD)
B29: Target Price | C29: =C149 -> 4.8777391 | D29: Target return | E29: 0.35
B30: Entry Price | C30: =C157 -> 6.1445465 | D30: Entry yield | E30: 0.25
B31: Sell Price | C31: =C165 -> 9.660386 | D31: Benchmark yield | E31: 0.1174
B32: Exit Price | C32: =C173 -> 8.6018897
A34: Step 1: Establishing the Company’s Sustainable Earning Power (Calculating Normalized FCFE)
B36: Goal: To quantify the underlying FCFE the business consistently generates, stripping away temporary fluctuations or accounting choices.
B37: FCFE = (Normalized Operating EBIT + Depreciation & Amortization – Capital Expenditures) + Stable Non-Operating EBIT + Net Interest Income – Taxes – NCI’s Share of Profits – Working Capital Investment
B39: Key Components | C39: =scaling_factor -> 1000
B40: • Normalized Operating EBIT: Earnings before interest and taxes from core business operations, adjusted to remove one-time or irregular items for a sustainable earnings base.
B41: Normalized Operating EBIT = | C41: =Normalized_FCF!C8 -> 4831254 | D41: =Reporting_currency -> CNY
B43: • Depreciation & Amortization (D&A): Non-cash expenses added back to reflect cash generated from operations. • Capital Expenditures (Capex): Cash outflows required to maintain or expand operational assets
B44: D&A = | C44: =Normalized_FCF!C9 -> 0 | D44: =Reporting_currency -> CNY
B45: Capex = | C45: =Normalized_FCF!C10 -> 0 | D45: =Reporting_currency -> CNY
B47: • Stable Non-Operating EBIT: Consistent earnings from non-core assets, such as fixed-income investments, dividend-paying stocks, or rental properties.
B48: Stable Non-Operating EBIT = | C48: =Normalized_FCF!C11 -> 51775 | D48: =Reporting_currency -> CNY
B50: • Net Interest Income: Interest income minus interest expense
B51: Operating Interest Income = | C51: =Normalized_FCF!C46 -> 62121.272 | D51: =Reporting_currency -> CNY
B52: Interest Expense = | C52: =Normalized_FCF!C45 -> -154206.15 | D52: =Reporting_currency -> CNY
B53: Net Interest Income = | C53: =Normalized_FCF!C12 -> -92084.878 | D53: =Reporting_currency -> CNY
B55: • NCI’s Share of Profits: NCI represents the portion of a subsidiary’s equity not owned by the parent company.
B56: Est. NCI’s Share of Profits = | C56: =Normalized_FCF!C15 -> 0 | D56: =Reporting_currency -> CNY
B58: • Taxes: Tax = (Normalized Operating EBIT + Stable Non-Operating EBIT + Interest Income – Interest Expense) × Tax Rate
B59: Taxes = | C59: =Normalized_FCF!C14 -> -1197736 | D59: =Reporting_currency -> CNY
B61: • Working Capital Investment (WCInv): WCInv is only included if it materially distorts FCFE.
B62: WCInv = | C62: =Normalized_FCF!C17 -> 0 | D62: =Reporting_currency -> CNY
B64: Note on Net Borrowing: In theory, principal repayments are accounted for through Net Borrowing. However, this model aims to avoid explicitly forecasting debt issuance or repayments. Instead, principal repayments are reflected in the Equity Value adjustment through interest-bearing debt.
B65: Insight: This step ensures a comprehensive measure of cash flow by incorporating both operating and stable non-operating sources while accounting for taxes and reinvestment needs.
B67: Latest FCFE = | C67: =Normalized_FCF!G19 -> 3856188.7 | D67: =Reporting_currency -> CNY
B68: Normalized FCFE = | C68: =Normalized_FCF!C19 -> 3593208.1 | D68: =Reporting_currency -> CNY
B69: Normalized FCFE/Market Cap = | C69: =Normalized_FCF!C124 -> 0.053712858
B70: After tax Dividend/Market Cap = | C70: =Normalized_FCF!C92 -> 0 | E70: Payout Ratio: | F70: =Normalized_FCF!C90 -> 0
B72: DuPont Analysis | C72: Normalized | D72: Latest
B73: ROE = | C73: =Normalized_FCF!C119 -> 0.45989402 | D73: =Normalized_FCF!G119 -> 0.55558185
B74: =Normalized_FCF!B116 -> Pre-tax Profit/Sales | C74: =Normalized_FCF!C116 -> 0.11378829 | D74: =Normalized_FCF!G116 -> 0.13537163
B75: =Normalized_FCF!B117 -> Sales/Total Assets | C75: =Normalized_FCF!C117 -> 1.8481868 | D75: =Normalized_FCF!G117 -> 1.8767484
B76: =Normalized_FCF!B118 -> Total Assets/Equity | C76: =Normalized_FCF!C118 -> 2.1868266 | D76: =Normalized_FCF!G118 -> 2.1868266
A78: Step 2: Calculating the No-Growth Baseline (Calculating Stable Income Value)
B80: Goal: Determine the intrinsic value assuming the current Normalized FCFE remains constant with no growth, providing a conservative baseline.
B81: Stable Income Value = Normalized FCFE / (Cost of Equity – Terminal Growth Rate)
B83: Key Components
B84: Base Cost of Equity | C84: =E24 -> 0.075
B85: Risk Premium | C85: =IF(C23="Y",1%,0)+IF(C24="Y",1%,0) -> 0
B86: Cost of Equity = | C86: =E24+C85 -> 0.075
B88: Note:
B89: Cost of Equity: Cost of Equity reflects the company’s risk profile and represents the minimum return the investor requires for taking on the general risk of owning this type of business, while the target annual return serves as the investor’s hurdle rate.
B90: Terminal Growth Rate: Setting g=0% is a conservative assumption, valuing the company based only on its current demonstrated earning power without relying on potentially optimistic future growth projections.
B92: Terminal Growth Rate (g) = | C92: 0
B93: No Growth SIV Per Share = | C93: =DCF!C6*scaling_factor*Exchange_Rate/Common_Shares -> 9.3890076 | D93: =Market_currency -> HKD
A95: Step 3: Adjusting for Financial Structure (Calculating No Growth Equity Value)
B97: Goal: To refine the Stable Income Value (SIV) by incorporating the company’s balance sheet structure.
B98: Equity Value = Stable Income Value – Total Interest-Bearing Debt + Non-Operating Cash + Other Non-Operating Assets
B100: Key Components
B101: Note on debt: The total interest-bearing debt captures the principal repayments. Ideally, this amount should be discounted based on the repayment schedule. However, for simplicity and conservatism, this model uses the book value of the total interest-bearing debt.
B102: Total Interest-Bearing Debt = | C102: =DCF!C7 -> 6168246 | D102: =Reporting_currency -> CNY
B103: Total Interest-Bearing Debt per share = | C103: =C102*scaling_factor*Exchange_Rate/Common_Shares -> 1.2088162 | D103: =Market_currency -> HKD
B104: Debt to Equity Ratio = | C104: =IF(BS!G31/BS!G27>300%,"nm",BS!G31/BS!G27) -> 0.59210448
B105: Debt to EBIT Ratio = | C105: =IF(BS!C50>30,"nm",BS!C50) -> 1.2767381
B107: • Non-Operating Cash: Excess cash not required for operations
B108: Total Cash = | C108: =BS!C66 -> 7848668 | D108: =Reporting_currency -> CNY
B109: Est. Non-Operating Cash = | C109: =DCF!C8 -> 4742604.4 | D109: =Reporting_currency -> CNY
B110: Est. Non-Operating Cash per share = | C110: =C109*scaling_factor*Exchange_Rate/Common_Shares -> 0.92942743 | D110: =Market_currency -> HKD
B112: • Other Non-Operating Assets: Assets not contributing to FCFE (e.g., non-income-generating investments or properties)
B113: Other Non-Operating Assets = | C113: =DCF!C9 -> 2656436.4 | D113: =Reporting_currency -> CNY
B114: Other Non-Operating Assets per share = | C114: =C113*scaling_factor*Exchange_Rate/Common_Shares -> 0.52059262 | D114: =Market_currency -> HKD
B116: Insight: The No Growth Equity Value per share represents an estimate of the company’s intrinsic worth based on its current sustainable operations and net financial position, before factoring in any future growth potential. It serves as a fundamentally anchored valuation baseline.
B118: No Growth Equity Value per share = | C118: =IF(valuation_method="DCF",DCF!C12,#REF!) -> 9.6302115 | D118: =Market_currency -> HKD
B119: Est. (Net Asset) Realizable Value | C119: =BS!D47 -> 0.052355704 | D119: =Market_currency -> HKD
A121: Step 4: Incorporating Future Potential (Scenario Analysis)
B123: Goal: Estimate intrinsic value by modeling plausible FCFE/Dividend, high growth periods (HGP), and high growth rates (HGR) scenarios, weighted by probability.
B125: Scenarios | C125: HGR | D125: HGP | E125: EV per share | F125: Probabilities
B126: =DCF!B74 -> Snowball Scenario | C126: =DCF!C74 -> 0.12 | D126: =DCF!D74 -> 5 | E126: =ROUND(IF(valuation_method="DCF",DCF!E74,#REF!),2)&" "&Market_currency -> 15.81 HKD | F126: =DCF!F74 -> 0.05
B127: =DCF!B75 -> Optimistic | C127: =DCF!C75 -> 0.08 | D127: =DCF!D75 -> 5 | E127: =ROUND(IF(valuation_method="DCF",DCF!E75,#REF!),2)&" "&Market_currency -> 13.45 HKD | F127: =DCF!F75 -> 0.18
B128: =DCF!B76 -> Base | C128: =DCF!C76 -> 0.05 | D128: =DCF!D76 -> 5 | E128: =ROUND(IF(valuation_method="DCF",DCF!E76,#REF!),2)&" "&Market_currency -> 11.89 HKD | F128: =DCF!F76 -> 0.54
B129: =DCF!B77 -> Pessimistic | C129: =DCF!C77 -> 0.02 | D129: =DCF!D77 -> 5 | E129: =ROUND(IF(valuation_method="DCF",DCF!E77,#REF!),2)&" "&Market_currency -> 10.48 HKD | F129: =DCF!F77 -> 0.18
B130: =DCF!B78 -> Devil's advocate | C130: =DCF!C78 -> 0 | D130: =DCF!D78 -> 5 | E130: =ROUND(IF(valuation_method="DCF",DCF!E78,#REF!),2)&" "&Market_currency -> 9.63 HKD | F130: =DCF!F78 -> 0.05
B132: Expected Equity Value = | C132: =Scenarios!C60 -> 12.001067 | D132: =Market_currency -> HKD
B134: Insight: Significant market volatility is analyzed as an indicator of the range of market-perceived outcomes, including extremes that define boundaries for scenarios like "Snowball" or "Devil’s Advocate." Scenario Analysis then filters these using fundamental reasoning to evaluate their likelihood.
...

Sheet Data
B1: =Thesis!C25 -> CNY | C1: 45657 | D1: =EOMONTH(EDATE(C1,-12),0) -> 45291 | E1: =EOMONTH(EDATE(D1,-12),0) -> 44926 | F1: =EOMONTH(EDATE(E1,-12),0) -> 44561 | G1: =EOMONTH(EDATE(F1,-12),0) -> 44196 | H1: =EOMONTH(EDATE(G1,-12),0) -> 43830 | I1: =EOMONTH(EDATE(H1,-12),0) -> 43465 | J1: =EOMONTH(EDATE(I1,-12),0) -> 43100 | K1: =EOMONTH(EDATE(J1,-12),0) -> 42735 | ... M1: =EOMONTH(EDATE(L1,-12),0) -> 42004
B2: Data (Dirty)
B3: Income Statement | C3: 1000
B4: Sales | C4: 42754687 | D4: 41453348
B5: COGS | C5: 16211077 | D5: 16946214
B6: OPEX | C6: =14113263+425543+1465696+2558496+257408+1864070 -> 20684476 | D6: =13039844+361903+1374307+2945399+204302+1611015 -> 19536770
B7: Incl. Selling Expenses
B8: R&D
B9: Share of JV or associate Results | C9: =56897-5122 -> 51775 | D9: =53372-7509 -> 45863
B10: Dividend or Interests from FA
B11: Investment property
B12: Interest Expense | C12: 274678 | D12: 351430
B13: Interest Income | C13: 382926 | D13: 326889
B14: Income Tax Paid | C14: 1923777 | D14: 1337673
B15: Reported Net Income | C15: 4708084 | D15: 4499080
B16: Non-controling Interests | C16: 7806 | D16: 3681
B18: Cash Flow Statement
B19: D&A
B20: CAPX
B21: WCInv
B22: CFO | C22: 7634465 | D22: 9000350 | E22: 6152295 | F22: 3806125 | G22: 2921451 | H22: 4580484 | I22: 2388393 | J22: 1399716 | K22: 1414061 | L22: 641989
B23: CFI | C23: -91488 | D23: -5310684 | E23: -756888 | F23: -4952514 | G23: -4691020 | H23: -5026276 | I23: -3867075 | J23: -1564855 | K23: -1280876 | L23: -915920
B24: CFF | C24: -7630060 | D24: -3501732 | E24: -4987546 | F24: 4310825 | G24: 2339705 | H24: -1489718 | I24: 5339398 | J24: 104943 | K24: 157735 | L24: 158591
B25: ="Dividend per share ("&Market_currency&")" -> Dividend per share (HKD) | C25: 0
B27: Balance Sheet | C27: Latest Asset Value
B28: ST AR | C28: =BS!C4 -> 1791826 | D28: 411995 | E28: 306856 | F28: 367668 | G28: 275233 | H28: 203571 | I28: 150093 | J28: 172951 | K28: 63644 | L28: 29587
B29: ST Inventory | C29: =BS!C6 -> 1060641 | D29: 1074627 | E29: 1141813 | F29: 1456237 | G29: 1154215 | H29: 1199666 | I29: 457124 | J29: 95118 | K29: 49707 | L29: 41065
B30: Total Liabilities | C30: =BS!C33+BS!C42 -> 12363761 | D30: 13160058 | E30: 13983063 | F30: 20092862 | G30: 17289886 | H30: 9987899 | I30: 3315085 | J30: 2644844 | K30: 1677783 | L30: 1249700
B31: Total Equity | C31: =BS!G27 -> 10417496 | D31: 11516940 | E31: 7456092 | F31: 7928625 | G31: 10237258 | H31: 10626033 | I31: 8629558 | J31: 1090981 | K31: 1071740 | L31: 1156918
B32: Non-common Interest | C32: =BS!G28 -> -16298 | D32: -9690 | E32: 12905 | F32: 14065 | G32: 3307 | H32: 3032 | I32: 4586 | J32: 1896 | K32: 269723 | L32: 437690
B34: IS & CF Statements (Clean)
B35: Income Statement
B36: Sales | C36: =IF(C$4="","",C4) -> 42754687 | D36: =IF(D$4="","",D4) -> 41453348 | E36: =IF(E$4="","",E4) | F36: =IF(F$4="","",F4) | G36: =IF(G$4="","",G4) | H36: =IF(H$4="","",H4) | I36: =IF(I$4="","",I4) | J36: =IF(J$4="","",J4) | ... M36: =IF(M$4="","",M4)
B37: COGS | C37: =IF(C$4="","",-C5) -> -16211077 | D37: =IF(D$4="","",-D5) -> -16946214 | E37: =IF(E$4="","",-E5) | F37: =IF(F$4="","",-F5) | G37: =IF(G$4="","",-G5) | H37: =IF(H$4="","",-H5) | I37: =IF(I$4="","",-I5) | J37: =IF(J$4="","",-J5) | ... M37: =IF(M$4="","",-M5)
B38: Gross Margin | C38: =IF(C36="","",C36+C37) -> 26543610 | D38: =IF(D36="","",D36+D37) -> 24507134 | E38: =IF(E36="","",E36+E37) | F38: =IF(F36="","",F36+F37) | G38: =IF(G36="","",G36+G37) | H38: =IF(H36="","",H36+H37) | I38: =IF(I36="","",I36+I37) | J38: =IF(J36="","",J36+J37) | ... M38: =IF(M36="","",M36+M37)
B39: OPEX | C39: =IF(C$4="","",-C6) -> -20684476 | D39: =IF(D$4="","",-D6) -> -19536770 | E39: =IF(E$4="","",-E6) | F39: =IF(F$4="","",-F6) | G39: =IF(G$4="","",-G6) | H39: =IF(H$4="","",-H6) | I39: =IF(I$4="","",-I6) | J39: =IF(J$4="","",-J6) | ... M39: =IF(M$4="","",-M6)
B40: Incl. Selling Expenses | C40: =IF(C$4="","",-C7) -> 0 | D40: =IF(D$4="","",-D7) -> 0 | E40: =IF(E$4="","",-E7) | F40: =IF(F$4="","",-F7) | G40: =IF(G$4="","",-G7) | H40: =IF(H$4="","",-H7) | I40: =IF(I$4="","",-I7) | J40: =IF(J$4="","",-J7) | ... M40: =IF(M$4="","",-M7)
B41: Incl. Other Opex | C41: =IF(C$4="","",C39-C40) -> -20684476 | D41: =IF(D$4="","",D39-D40) -> -19536770 | E41: =IF(E$4="","",E39-E40) | F41: =IF(F$4="","",F39-F40) | G41: =IF(G$4="","",G39-G40) | H41: =IF(H$4="","",H39-H40) | I41: =IF(I$4="","",I39-I40) | J41: =IF(J$4="","",J39-J40) | ... M41: =IF(M$4="","",M39-M40)
B42: R&D | C42: =IF(C$4="","",-C8) -> 0 | D42: =IF(D$4="","",-D8) -> 0 | E42: =IF(E$4="","",-E8) | F42: =IF(F$4="","",-F8) | G42: =IF(G$4="","",-G8) | H42: =IF(H$4="","",-H8) | I42: =IF(I$4="","",-I8) | J42: =IF(J$4="","",-J8) | ... M42: =IF(M$4="","",-M8)
B43: Operating EBIT | C43: =IF(C$4="","",C38+C39+C42) -> 5859134 | D43: =IF(D$4="","",D38+D39+D42) -> 4970364 | E43: =IF(E$4="","",E38+E39+E42) | F43: =IF(F$4="","",F38+F39+F42) | G43: =IF(G$4="","",G38+G39+G42) | H43: =IF(H$4="","",H38+H39+H42) | I43: =IF(I$4="","",I38+I39+I42) | J43: =IF(J$4="","",J38+J39+J42) | ... M43: =IF(M$4="","",M38+M39+M42)
B44: Non-operating EBIT | C44: =IF(C$4="","",C47-C46-C45-C43) -> 664479 | D44: =IF(D$4="","",D47-D46-D45-D43) -> 890930 | E44: =IF(E$4="","",E47-E46-E45-E43) | F44: =IF(F$4="","",F47-F46-F45-F43) | G44: =IF(G$4="","",G47-G46-G45-G43) | H44: =IF(H$4="","",H47-H46-H45-H43) | I44: =IF(I$4="","",I47-I46-I45-I43) | J44: =IF(J$4="","",J47-J46-J45-J43) | ... M44: =IF(M$4="","",M47-M46-M45-M43)
B45: Net Interest Income | C45: =IF(C$4="","",C51+C52) -> 108248 | D45: =IF(D$4="","",D51+D52) -> -24541 | E45: =IF(E$4="","",E51+E52) | F45: =IF(F$4="","",F51+F52) | G45: =IF(G$4="","",G51+G52) | H45: =IF(H$4="","",H51+H52) | I45: =IF(I$4="","",I51+I52) | J45: =IF(J$4="","",J51+J52) | ... M45: =IF(M$4="","",M51+M52)
B46: Income Tax Paid | C46: =IF(C$4="","",-C14) -> -1923777 | D46: =IF(D$4="","",-D14) -> -1337673 | E46: =IF(E$4="","",-E14) | F46: =IF(F$4="","",-F14) | G46: =IF(G$4="","",-G14) | H46: =IF(H$4="","",-H14) | I46: =IF(I$4="","",-I14) | J46: =IF(J$4="","",-J14) | ... M46: =IF(M$4="","",-M14)
B47: Reported Net Income | C47: =IF(C$4="","",C15) -> 4708084 | D47: =IF(D$4="","",D15) -> 4499080 | E47: =IF(E$4="","",E15) | F47: =IF(F$4="","",F15) | G47: =IF(G$4="","",G15) | H47: =IF(H$4="","",H15) | I47: =IF(I$4="","",I15) | J47: =IF(J$4="","",J15) | ... M47: =IF(M$4="","",M15)
B48: Non-controling Interests | C48: =IF(C$4="","",MIN(-C16,0)) -> -7806 | D48: =IF(D$4="","",MIN(-D16,0)) -> -3681 | E48: =IF(E$4="","",MIN(-E16,0)) | F48: =IF(F$4="","",MIN(-F16,0)) | G48: =IF(G$4="","",MIN(-G16,0)) | H48: =IF(H$4="","",MIN(-H16,0)) | I48: =IF(I$4="","",MIN(-I16,0)) | J48: =IF(J$4="","",MIN(-J16,0)) | ... M48: =IF(M$4="","",MIN(-M16,0))
B50: Net Interest Income
B51: Interest Expense | C51: =IF(C$4="","",-C12) -> -274678 | D51: =IF(D$4="","",-D12) -> -351430 | E51: =IF(E$4="","",-E12) | F51: =IF(F$4="","",-F12) | G51: =IF(G$4="","",-G12) | H51: =IF(H$4="","",-H12) | I51: =IF(I$4="","",-I12) | J51: =IF(J$4="","",-J12) | ... M51: =IF(M$4="","",-M12)
B52: Interest Income | C52: =IF(C$4="","",C13) -> 382926 | D52: =IF(D$4="","",D13) -> 326889 | E52: =IF(E$4="","",E13) | F52: =IF(F$4="","",F13) | G52: =IF(G$4="","",G13) | H52: =IF(H$4="","",H13) | I52: =IF(I$4="","",I13) | J52: =IF(J$4="","",J13) | ... M52: =IF(M$4="","",M13)
B54: Non-operating EBIT
B55: Share of JV or associate Results | C55: =IF(C$4="","",C9) -> 51775 | D55: =IF(D$4="","",D9) -> 45863 | E55: =IF(E$4="","",E9) | F55: =IF(F$4="","",F9) | G55: =IF(G$4="","",G9) | H55: =IF(H$4="","",H9) | I55: =IF(I$4="","",I9) | J55: =IF(J$4="","",J9) | ... M55: =IF(M$4="","",M9)
B56: Dividend or Interests from FA | C56: =IF(C$4="","",C10) -> 0 | D56: =IF(D$4="","",D10) -> 0 | E56: =IF(E$4="","",E10) | F56: =IF(F$4="","",F10) | G56: =IF(G$4="","",G10) | H56: =IF(H$4="","",H10) | I56: =IF(I$4="","",I10) | J56: =IF(J$4="","",J10) | ... M56: =IF(M$4="","",M10)
B57: Investment property | C57: =IF(C$4="","",C11) -> 0 | D57: =IF(D$4="","",D11) -> 0 | E57: =IF(E$4="","",E11) | F57: =IF(F$4="","",F11) | G57: =IF(G$4="","",G11) | H57: =IF(H$4="","",H11) | I57: =IF(I$4="","",I11) | J57: =IF(J$4="","",J11) | ... M57: =IF(M$4="","",M11)
B58: Other Non-operating Income | C58: =IF(C$4="","",C44-C55-C56-C57) -> 612704 | D58: =IF(D$4="","",D44-D55-D56-D57) -> 845067 | E58: =IF(E$4="","",E44-E55-E56-E57) | F58: =IF(F$4="","",F44-F55-F56-F57) | G58: =IF(G$4="","",G44-G55-G56-G57) | H58: =IF(H$4="","",H44-H55-H56-H57) | I58: =IF(I$4="","",I44-I55-I56-I57) | J58: =IF(J$4="","",J44-J55-J56-J57) | ... M58: =IF(M$4="","",M44-M55-M56-M57)
B60: Cash Flow Statement
B61: D&A | C61: =IF(C$4="","",-C19) -> 0 | D61: =IF(D$4="","",-D19) -> 0 | E61: =IF(E$4="","",-E19) | F61: =IF(F$4="","",-F19) | G61: =IF(G$4="","",-G19) | H61: =IF(H$4="","",-H19) | I61: =IF(I$4="","",-I19) | J61: =IF(J$4="","",-J19) | ... M61: =IF(M$4="","",-M19)
B62: CAPX | C62: =IF(C$4="","",IF(C20=0,C61,-C20)) -> 0 | D62: =IF(D$4="","",IF(D20=0,D61,-D20)) -> 0 | E62: =IF(E$4="","",IF(E20=0,E61,-E20)) | F62: =IF(F$4="","",IF(F20=0,F61,-F20)) | G62: =IF(G$4="","",IF(G20=0,G61,-G20)) | H62: =IF(H$4="","",IF(H20=0,H61,-H20)) | I62: =IF(I$4="","",IF(I20=0,I61,-I20)) | J62: =IF(J$4="","",IF(J20=0,J61,-J20)) | ... M62: =IF(M$4="","",IF(M20=0,M61,-M20))
B63: WCInv | C63: =IF(C$4="","",-C21) -> 0 | D63: =IF(D$4="","",-D21) -> 0 | E63: =IF(E$4="","",-E21) | F63: =IF(F$4="","",-F21) | G63: =IF(G$4="","",-G21) | H63: =IF(H$4="","",-H21) | I63: =IF(I$4="","",-I21) | J63: =IF(J$4="","",-J21) | ... M63: =IF(M$4="","",-M21)
B64: Net Change in Cash | C64: =IF(C$4="","",C22+C23+C24) -> -87083 | D64: =IF(D$4="","",D22+D23+D24) -> 187934 | E64: =IF(E$4="","",E22+E23+E24) | F64: =IF(F$4="","",F22+F23+F24) | G64: =IF(G$4="","",G22+G23+G24) | H64: =IF(H$4="","",H22+H23+H24) | I64: =IF(I$4="","",I22+I23+I24) | J64: =IF(J$4="","",J22+J23+J24) | ... M64: =IF(M$4="","",M22+M23+M24)
B65: Dividend per share | C65: =IF(C$4="","",C25) -> 0 | D65: =IF(D$4="","",D25) -> 0 | E65: =IF(E$4="","",E25) | F65: =IF(F$4="","",F25) | G65: =IF(G$4="","",G25) | H65: =IF(H$4="","",H25) | I65: =IF(I$4="","",I25) | J65: =IF(J$4="","",J25) | ... M65: =IF(M$4="","",M25)
B67: YoY %
B68: =B36 -> Sales | C68: =IF(D$36="","",C36/D36-1) -> 0.031392856 | D68: =IF(E$36="","",D36/E36-1) | E68: =IF(F$36="","",E36/F36-1) | F68: =IF(G$36="","",F36/G36-1) | G68: =IF(H$36="","",G36/H36-1) | H68: =IF(I$36="","",H36/I36-1) | I68: =IF(J$36="","",I36/J36-1) | J68: =IF(K$36="","",J36/K36-1) | ... M68: =IF(N$36="","",M36/N36-1)
B69: Gross Margin | C69: =IF(D$36="","",C38/D38-1) -> 0.083097273 | D69: =IF(E$36="","",D38/E38-1) | E69: =IF(F$36="","",E38/F38-1) | F69: =IF(G$36="","",F38/G38-1) | G69: =IF(H$36="","",G38/H38-1) | H69: =IF(I$36="","",H38/I38-1) | I69: =IF(J$36="","",I38/J38-1) | J69: =IF(K$36="","",J38/K38-1) | ... M69: =IF(N$36="","",M38/N38-1)
B70: =B43 -> Operating EBIT | C70: =IF(D$36="","",C43/D43-1) -> 0.17881387 | D70: =IF(E$36="","",D43/E43-1) | E70: =IF(F$36="","",E43/F43-1) | F70: =IF(G$36="","",F43/G43-1) | G70: =IF(H$36="","",G43/H43-1) | H70: =IF(I$36="","",H43/I43-1) | I70: =IF(J$36="","",I43/J43-1) | J70: =IF(K$36="","",J43/K43-1) | ... M70: =IF(N$36="","",M43/N43-1)
B71: Non-operating EBIT | C71: =IF(D$36="","",C44/D44-1) -> -0.25417373 | D71: =IF(E$36="","",D44/E44-1) | E71: =IF(F$36="","",E44/F44-1) | F71: =IF(G$36="","",F44/G44-1) | G71: =IF(H$36="","",G44/H44-1) | H71: =IF(I$36="","",H44/I44-1) | I71: =IF(J$36="","",I44/J44-1) | J71: =IF(K$36="","",J44/K44-1) | ... M71: =IF(N$36="","",M44/N44-1)
B72: =B47 -> Reported Net Income | C72: =IF(D$36="","",C47/D47-1) -> 0.046454831 | D72: =IF(E$36="","",D47/E47-1) | E72: =IF(F$36="","",E47/F47-1) | F72: =IF(G$36="","",F47/G47-1) | G72: =IF(H$36="","",G47/H47-1) | H72: =IF(I$36="","",H47/I47-1) | I72: =IF(J$36="","",I47/J47-1) | J72: =IF(K$36="","",J47/K47-1) | ... M72: =IF(N$36="","",M47/N47-1)
B74: Balance Sheet (Clean)
B75: Balance Sheet
B76: Total Assets | C76: =IF(C$4="","",C79+C80) -> 22781257 | D76: =IF(D$4="","",D79+D80) -> 24676998 | E76: =IF(E$4="","",E79+E80) | F76: =IF(F$4="","",F79+F80) | G76: =IF(G$4="","",G79+G80) | H76: =IF(H$4="","",H79+H80) | I76: =IF(I$4="","",I79+I80) | J76: =IF(J$4="","",J79+J80) | ... M76: =IF(M$4="","",M79+M80)
B77: Incl. ST AR | C77: =IF(C$4="","",C28) -> 1791826 | D77: =IF(D$4="","",D28) -> 411995 | E77: =IF(E$4="","",E28) | F77: =IF(F$4="","",F28) | G77: =IF(G$4="","",G28) | H77: =IF(H$4="","",H28)
B78: Incl. ST Inventory | C78: =IF(C$4="","",C29) -> 1060641 | D78: =IF(D$4="","",D29) -> 1074627 | E78: =IF(E$4="","",E29) | F78: =IF(F$4="","",F29) | G78: =IF(G$4="","",G29) | H78: =IF(H$4="","",H29)
B79: Total Liabilities | C79: =IF(C$4="","",C30) -> 12363761 | D79: =IF(D$4="","",D30) -> 13160058 | E79: =IF(E$4="","",E30) | F79: =IF(F$4="","",F30) | G79: =IF(G$4="","",G30) | H79: =IF(H$4="","",H30) | I79: =IF(I$4="","",I30) | J79: =IF(J$4="","",J30) | ... M79: =IF(M$4="","",M30)
B80: Total Equity | C80: =IF(C$4="","",C31) -> 10417496 | D80: =IF(D$4="","",D31) -> 11516940 | E80: =IF(E$4="","",E31) | F80: =IF(F$4="","",F31) | G80: =IF(G$4="","",G31) | H80: =IF(H$4="","",H31) | I80: =IF(I$4="","",I31) | J80: =IF(J$4="","",J31) | ... M80: =IF(M$4="","",M31)

Sheet BS
B1: Most Recent Quarter | C1: 46022 | F1: =IF(MONTH(C1)=MONTH(Normalized_FCF!G1),"FY","Quarter")&" Report" -> FY Report | H1: =scaling_factor -> 1000
B2: Lastest Balance Sheet
B3: ST Operating Assets | C3: Book | D3: Valued @ | F3: ST Non-Operating Assets | G3: Book | H3: Valued @
B4: ST AR | C4: =1517431+274395 -> 1791826 | D4: 0.6 | F4: Cash and cash equivalents | G4: 7474820 | H4: 0.9
B5: Operating ST Financial Assets | C5: 0 | D5: 0.6 | F5: Restricted cash | G5: 371676 | H5: 0.7
B6: Inventory | C6: 1060641 | D6: 0.5 | F6: Securities with stable income | G6: 0 | H6: 0.6
B7: Properties held for sale | C7: 0 | D7: 0.6 | F7: Other Securities | G7: =964975+1139998 -> 2104973 | H7: 0.6
B8: Properties held for income | C8: 0 | D8: 0.6 | F8: Properties with stable income | G8: 0 | H8: 0.6
B9: Prepayments and Contract Assets | C9: 70244 | D9: 0.1 | F9: Other Properties | G9: 0 | H9: 0.6
B10: ST DTA | C10: 0 | D10: 0.9 | F10: Assets held for sale | G10: 149978 | H10: 0.6
B11: Other ST Assets | C11: 0 | D11: 0.05
B12: Operating ST Assets | C12: =SUM(C4:C11) -> 2922711 | D12: =C4*D4+C5*D5+C9*D9+C6*D6+C8*D8+C7*D7+C10*D10+C11*D11 -> 1612440.5 | F12: Non-Operating ST Assets | G12: =SUM(G4:G10) -> 10101447 | H12: =G4*H4+G5*H5+G6*H6+G7*H7+G8*H8+G9*H9+G10*H10 -> 8340481.8
B14: LT Operating Assets | C14: Book | D14: Valued @ | F14: LT Non-Operating Assets | G14: Book | H14: Valued @
B15: LT AR and Prepayments | C15: 174430 | D15: 0.4 | F15: LT Depositis | G15: 2172 | H15: 0.8
B16: Operating LT Financial Assets | C16: 0 | D16: 0.5 | F16: Securities with stable income | G16: 0 | H16: 0.6
B17: Properties held for sale | C17: 0 | D17: 0.6 | F17: Other Securities | G17: =1981265+17227+323929 -> 2322421 | H17: 0.6
B18: Properties held for income | C18: 0 | D18: 0.6 | F18: JV or associate with stable income | G18: 179959 | H18: 0.1
B19: PP&E & Right of Use Assets | C19: =3319749+3018798 -> 6338547 | D19: 0.1 | F19: Other JV or associate | G19: 0 | H19: 0.1
B20: Biological assets | C20: 0 | D20: 0.05 | F20: Properties with stable income | G20: 0 | H20: 0.2
B21: Intangible assets | C21: 52198 | D21: 0.05 | F21: Other Properties | G21: 0 | H21: 0.1
B22: LT DTA | C22: 602527 | D22: 0.9
B23: Other assets & Goodwill | C23: 84845 | D23: 0
B24: Operating LT Assets | C24: =SUM(C15:C23) -> 7252547 | D24: =C15*D15+C16*D16+C18*D18+C17*D17+C19*D19+C20*D20+C21*D21+C22*D22+C23*D23 -> 1248510.9 | F24: Non-Operating LT Assets | G24: =SUM(G15:G21) -> 2504552 | H24: =G15*H15+G16*H16+G17*H17+G18*H18+G19*H19+G20*H20+G21*H21 -> 1413186.1
B26: ST Liabilities | C26: Book | F26: BS Summary | G26: Book | H26: Valued @
B27: ST Borrowing | C27: 97549 | F27: Total Equity | G27: =G32-G30 -> 10417496 | H27: =H32-G30 -> 250858.3
B28: ST Lease liabilities | C28: 888821 | F28: Incl. Minority Interest (NCI) | G28: -16298
B29: ST SH Loan | C29: 0 | F29: Incl. Common Equity | G29: =G27-G28 -> 10433794 | H29: =H27-G28 -> 267156.3
B30: ST Financial Liabilities | C30: 45308 | F30: Total Liabilities | G30: =C33+C42 -> 12363761
B31: ST Interest-bearing Debt | C31: =SUM(C27:C30) -> 1031678 | F31: incl. Interest-bearing Debt | G31: =C31+C40 -> 6168246
B32: Other ST liabilities | C32: =C33-C31 -> 6072143 | F32: Total Assets | G32: =G35+G40 -> 22781257 | H32: =H35+H40 -> 12614619
B33: Current Liabilities | C33: 7103821
F34: Assets Summary | G34: Book | H34: Valued @
B35: LT Liabilities | C35: Book | F35: Operating Assets | G35: =C12+C24 -> 10175258 | H35: =D12+D24 -> 2860951.4
B36: LT Borrowing | C36: 0 | F36: incl. AR | G36: =C4+C15 -> 1966256
B37: LT Lease liabilities | C37: 3108701 | F37: incl. inventory | G37: =C6 -> 1060641
B38: LT SH Loan | C38: 0 | F38: incl. Properties held for sale | G38: =C7+C17 -> 0
B39: LT Financial Liabilities | C39: 2027867 | F39: incl. Fixed Assets | G39: =C7+C17+C19+C20 -> 6338547 | H39: =C7*D7+C17*D17+C19*D19+C20*D20 -> 633854.7
B40: LT Interest-bearing Debt | C40: =SUM(C36:C39) -> 5136568 | F40: Non-operating Assets | G40: =G12+G24 -> 12605999 | H40: =H12+H24 -> 9753667.9
B41: Other LT liabilities | C41: =C42-C40 -> 123372 | F41: incl. Assets with stable income | G41: =C70 -> 8028627 | H41: =H40-H42 -> 7097231.5
B42: Noncurrent Liabilities | C42: 5259940 | F42: incl. Other Assets | G42: =C82 -> 4427394 | H42: =D82 -> 2656436.4
B44: Balance Sheet Analysis
B45: Asset Value Stress Test | C45: Book | D45: Est. Realizable Value | F45: Notes
B46: Equity | C46: =G29 -> 10433794 | D46: =H29 -> 267156.3
B47: ="Equity per share ("&Market_currency&")" -> Equity per share (HKD) | C47: =C46*H1/Common_Shares*Exchange_Rate -> 2.044753 | D47: =D46*H1/Common_Shares*Exchange_Rate -> 0.052355704
B49: Leverage % | C49: Normalized | D49: Latest
B50: Debt/EBIT | C50: =G31/Normalized_FCF!C8 -> 1.2767381 | D50: =G31/Normalized_FCF!G8 -> 1.0527573
B51: Common Equity/Total Asset | D51: =G29/G32 -> 0.45799905
B53: Profibility % | C53: Normalized | D53: Latest
B54: Operating Asset Yield | C54: =Normalized_FCF!C8/G35 -> 0.47480408 | D54: =Normalized_FCF!G8/G35 -> 0.57582166
B55: Non-Operating Asset Yield | C55: =Normalized_FCF!C11/G40 -> 0.0041071715 | D55: =Normalized_FCF!G11/G40 -> 0.0041071715
B57: Reinvestment % | C57: Normalized | D57: Latest
B58: D&A/Fixed Assets | D58: =Normalized_FCF!G9/BS!$G$39 -> 0
B59: Fixed Assets/Total Assets | D59: =G39/G32 -> 0.27823517
B61: NCI % | C61: Estimate | D61: Latest
B62: Est. of NCI Ownership Percentage | C62: =IF(G28<=0,0,G28/G29) -> 0 | D62: =G28/G29 -> -0.0015620397 | F62: Rough Estimate only
B64: Non-operating Assets Analysis
B65: Non-operating Assets with stable income | C65: Book | D65: Non-Operating | F65: Notes
B66: Cash | C66: =G4+G5+G15 -> 7848668 | D66: =C66-D75 -> 4742604.4 | F66: Non-Operating Cash is the Excess cash not required for operations
B67: Securities with stable income | C67: =G6+G16 -> 0
B68: JV or associate with stable income | C68: =G18 -> 179959
B69: Properties with stable income | C69: =G8+G20 -> 0
B70: Non-operating Assets with stable income | C70: =SUM(C66:C69) -> 8028627
B72: Cash Management Analysis | C72: Latest | D72: Normalized
B73: Monthly Operating Expenses | C73: =(Normalized_FCF!G26+Normalized_FCF!G35-Normalized_FCF!G89)/12 -> -3074629.4 | D73: =(Normalized_FCF!C26+Normalized_FCF!C35-Normalized_FCF!C89)/12 -> -3106063.6 | F73: Variable + Fixed Costs & Dividends
B74: Operating Expenses Multiple (months) | C74: =-$C$66/C73 -> 2.55272 | D74: =-$C$66/D73 -> 2.5268858 | F74: Companies typically need cash to cover 1 to 2 months of operating expenses
B75: Operating Cash Requirement | D75: =MAX(-D73*D76,G5) -> 3106063.6 | F75: 1x for stable businesses, 2x for for volatile ones, 6x for cash hoarders
B76: Operating Cash Multiple (months) | D76: =IF(valuation_method="DCF",IF(D74<=3,1,IF(D74>18,6,2)),-C66/D73) -> 1 | F76: Rough Estimate
B78: Other Non-operating Assets | C78: Book | D78: Valued @
B79: Other Securities | C79: =G7+G17 -> 4427394 | D79: =G7*H7+G17*H17 -> 2656436.4
B80: Other JV or associate | C80: =G19 -> 0 | D80: =G19*H19 -> 0
B81: Other Properties | C81: =G9+G21 -> 0 | D81: =G9*H9+G21*H21 -> 0
B82: Other Non-operating Assets | C82: =SUM(C79:C81) -> 4427394 | D82: =SUM(D79:D81) -> 2656436.4
B84: Non-FCF Value of the Equity Value
B85: Non-FCF Value | D85: Per-Share
B86: Interest-bearing Debt | C86: =-DCF!C7*Exchange_Rate -> -6737941.5 | D86: =C86*scaling_factor/Common_Shares -> -1.2088162 | E86: =Market_currency -> HKD
B87: Non-operating Cash | C87: =DCF!C8*Exchange_Rate -> 5180628.5 | D87: =C87*scaling_factor/Common_Shares -> 0.92942743 | E87: =Market_currency -> HKD
B88: Other Non-operating Assets | C88: =DCF!C9*Exchange_Rate -> 2901783.3 | D88: =C88*scaling_factor/Common_Shares -> 0.52059262 | E88: =Market_currency -> HKD
B89: Total Non-FCF Value | C89: =SUM(C86:C88) -> 1344470.2 | D89: =SUM(D86:D88) -> 0.24120385 | E89: =Market_currency -> HKD

Sheet Normalized_FCF
B1: =Thesis!C25 -> CNY | C1: Normalized | G1: =Data!C1 -> 45657 | H1: =EOMONTH(EDATE(G1,-12),0) -> 45291 | I1: =EOMONTH(EDATE(H1,-12),0) -> 44926 | J1: =EOMONTH(EDATE(I1,-12),0) -> 44561 | K1: =EOMONTH(EDATE(J1,-12),0) -> 44196 | L1: =EOMONTH(EDATE(K1,-12),0) -> 43830 | M1: =EOMONTH(EDATE(L1,-12),0) -> 43465 | N1: =EOMONTH(EDATE(M1,-12),0) -> 43100 | O1: =EOMONTH(EDATE(N1,-12),0) -> 42735 | ... Q1: =EOMONTH(EDATE(P1,-12),0) -> 42004
B2: FCFE Analysis | E2: Notes
B3: FCFE | C3: =scaling_factor -> 1000
B4: Sales | C4: =AVERAGE(G4:H4) -> 42104018 | G4: =Data!C36 -> 42754687 | H4: =Data!D36 -> 41453348 | I4: =Data!E36 | J4: =Data!F36 | K4: =Data!G36 | L4: =Data!H36 | M4: =Data!I36 | N4: =Data!J36 | ... Q4: =Data!M36
B5: Variable Costs | C5: =C26 -> -16588287 | G5: =G26 -> -16211077 | H5: =H26 -> -16946214 | I5: =I26 | J5: =J26 | K5: =K26 | L5: =L26 | M5: =M26 | N5: =N26 | ... Q5: =Q26
B6: Contribution Margin | C6: =C4+C5 -> 25515730 | G6: =IF(G4="","",G4+G5) -> 26543610 | H6: =IF(H4="","",H4+H5) -> 24507134 | I6: =IF(I4="","",I4+I5) | J6: =IF(J4="","",J4+J5) | K6: =IF(K4="","",K4+K5) | L6: =IF(L4="","",L4+L5) | M6: =IF(M4="","",M4+M5) | N6: =IF(N4="","",N4+N5) | ... Q6: =IF(Q4="","",Q4+Q5)
B7: Fixed Costs | C7: =C35 -> -20684476 | G7: =G35 -> -20684476 | H7: =H35 -> -19536770 | I7: =I35 | J7: =J35 | K7: =K35 | L7: =L35 | M7: =M35 | N7: =N35 | ... Q7: =Q35
B8: Operating EBIT | C8: =C6+C7 -> 4831254 | G8: =IF(G$4="","",G6+G7) -> 5859134 | H8: =IF(H$4="","",H6+H7) -> 4970364 | I8: =IF(I$4="","",I6+I7) | J8: =IF(J$4="","",J6+J7) | K8: =IF(K$4="","",K6+K7) | L8: =IF(L$4="","",L6+L7) | M8: =IF(M$4="","",M6+M7) | N8: =IF(N$4="","",N6+N7) | ... Q8: =IF(Q$4="","",Q6+Q7)
B9: Add Back D&A | C9: =BS!$G$39*BS!D58 -> 0 | G9: =IF(Data!C61="","",-Data!C61) -> 0 | H9: =IF(Data!D61="","",-Data!D61) -> 0 | I9: =IF(Data!E61="","",-Data!E61) | J9: =IF(Data!F61="","",-Data!F61) | K9: =IF(Data!G61="","",-Data!G61) | L9: =IF(Data!H61="","",-Data!H61) | M9: =IF(Data!I61="","",-Data!I61) | N9: =IF(Data!J61="","",-Data!J61) | ... Q9: =IF(Data!M61="","",-Data!M61)
B10: Maintenance Capex | C10: =-C4*C76 -> 0 | G10: =Data!C62 -> 0 | H10: =Data!D62 -> 0 | I10: =Data!E62 | J10: =Data!F62 | K10: =Data!G62 | L10: =Data!H62 | M10: =Data!I62 | N10: =Data!J62 | ... Q10: =Data!M62
B11: Stable Non-Operating EBIT | C11: =C61 -> 51775 | G11: =G59 -> 51775 | H11: =H59 -> 45863 | I11: =I59 | J11: =J59 | K11: =K59 | L11: =L59 | M11: =M59 | N11: =N59 | ... Q11: =Q59
B12: Net Interest Income | C12: =C48 -> -92084.878 | G12: =G48 -> -123137.32 | H12: =H48 -> -222065.62 | I12: =I48 | J12: =J48 | K12: =K48 | L12: =L48 | M12: =M48 | N12: =N48 | ... Q12: =Q48
B13: Pre-tax Profit | C13: =SUM(C8:C12) -> 4790944.1 | G13: =IF(G$4="","",SUM(G8:G12)) -> 5787771.7 | H13: =IF(H$4="","",SUM(H8:H12)) -> 4794161.4 | I13: =IF(I$4="","",SUM(I8:I12)) | J13: =IF(J$4="","",SUM(J8:J12)) | K13: =IF(K$4="","",SUM(K8:K12)) | L13: =IF(L$4="","",SUM(L8:L12)) | M13: =IF(M$4="","",SUM(M8:M12)) | N13: =IF(N$4="","",SUM(N8:N12)) | ... Q13: =IF(Q$4="","",SUM(Q8:Q12))
B14: Income Tax | C14: =-SUM(C8+C11,C12)*C41 -> -1197736 | G14: =Data!C46 -> -1923777 | H14: =Data!D46 -> -1337673 | I14: =Data!E46 | J14: =Data!F46 | K14: =Data!G46 | L14: =Data!H46 | M14: =Data!I46 | N14: =Data!J46 | ... Q14: =Data!M46
B15: NCI’s Share of Profits | C15: =-C4*C81 -> 0 | G15: =Data!C48 -> -7806 | H15: =Data!D48 -> -3681 | I15: =Data!E48 | J15: =Data!F48 | K15: =Data!G48 | L15: =Data!H48 | M15: =Data!I48 | N15: =Data!J48 | ... Q15: =Data!M48
B16: After-tax Profit | C16: =SUM(C13:C15) -> 3593208.1 | G16: =IF(G$4="","",SUM(G13:G15)) -> 3856188.7 | H16: =IF(H$4="","",SUM(H13:H15)) -> 3452807.4 | I16: =IF(I$4="","",SUM(I13:I15)) | J16: =IF(J$4="","",SUM(J13:J15)) | K16: =IF(K$4="","",SUM(K13:K15)) | L16: =IF(L$4="","",SUM(L13:L15)) | M16: =IF(M$4="","",SUM(M13:M15)) | N16: =IF(N$4="","",SUM(N13:N15)) | ... Q16: =IF(Q$4="","",SUM(Q13:Q15))
B17: WCInv | C17: =-C4*C83 -> 0 | E17: WCInv is by default excluded
B18: Net Borrowing | C18: 0 | E18: Net borrowing is excluded
B19: FCFE | C19: =C16+C17 -> 3593208.1 | G19: =IF(G$4="","",G16+G17) -> 3856188.7 | H19: =IF(H$4="","",H16+H17) -> 3452807.4 | I19: =IF(I$4="","",I16+I17) | J19: =IF(J$4="","",J16+J17) | K19: =IF(K$4="","",K16+K17) | L19: =IF(L$4="","",L16+L17) | M19: =IF(M$4="","",M16+M17) | N19: =IF(N$4="","",N16+N17) | ... Q19: =IF(Q$4="","",Q16+Q17)
B21: Operating Cost Structure | E21: Notes
B22: Variable Costs
B23: COGS | C23: =-C4*C29 -> -16588287 | G23: =Data!C37 -> -16211077 | H23: =Data!D37 -> -16946214 | I23: =Data!E37 | J23: =Data!F37 | K23: =Data!G37 | L23: =Data!H37 | M23: =Data!I37 | N23: =Data!J37 | ... Q23: =Data!M37
B24: Selling Expenses | C24: =-C4*C30 -> 0 | G24: =Data!C40 -> 0 | H24: =Data!D40 -> 0 | I24: =Data!E40 | J24: =Data!F40 | K24: =Data!G40 | L24: =Data!H40 | M24: =Data!I40 | N24: =Data!J40 | ... Q24: =Data!M40
B25: R&D | C25: =-C4*C31 -> 0 | G25: =Data!C42 -> 0 | H25: =Data!D42 -> 0 | I25: =Data!E42 | J25: =Data!F42 | K25: =Data!G42 | L25: =Data!H42 | M25: =Data!I42 | N25: =Data!J42 | ... Q25: =Data!M42
B26: Variable Costs | C26: =SUM(C23:C25) -> -16588287 | G26: =IF(G$4="","",SUM(G23:G25)) -> -16211077 | H26: =IF(H$4="","",SUM(H23:H25)) -> -16946214 | I26: =IF(I$4="","",SUM(I23:I25)) | J26: =IF(J$4="","",SUM(J23:J25)) | K26: =IF(K$4="","",SUM(K23:K25)) | L26: =IF(L$4="","",SUM(L23:L25)) | M26: =IF(M$4="","",SUM(M23:M25)) | N26: =IF(N$4="","",SUM(N23:N25)) | ... Q26: =IF(Q$4="","",SUM(Q23:Q25))
B28: Variable Costs % of Sales
B29: COGS | C29: =AVERAGE(G29:H29) -> 0.39398348 | G29: =IF(G$4="","",ABS(G23/G$4)) -> 0.37916491 | H29: =IF(H$4="","",ABS(H23/H$4)) -> 0.40880206 | I29: =IF(I$4="","",ABS(I23/I$4)) | J29: =IF(J$4="","",ABS(J23/J$4)) | K29: =IF(K$4="","",ABS(K23/K$4)) | L29: =IF(L$4="","",ABS(L23/L$4)) | M29: =IF(M$4="","",ABS(M23/M$4)) | N29: =IF(N$4="","",ABS(N23/N$4)) | ... Q29: =IF(Q$4="","",ABS(Q23/Q$4))
B30: =B24 -> Selling Expenses | C30: 0 | G30: =IF(G$4="","",ABS(G24/G$4)) -> 0 | H30: =IF(H$4="","",ABS(H24/H$4)) -> 0 | I30: =IF(I$4="","",ABS(I24/I$4)) | J30: =IF(J$4="","",ABS(J24/J$4)) | K30: =IF(K$4="","",ABS(K24/K$4)) | L30: =IF(L$4="","",ABS(L24/L$4)) | M30: =IF(M$4="","",ABS(M24/M$4)) | N30: =IF(N$4="","",ABS(N24/N$4)) | ... Q30: =IF(Q$4="","",ABS(Q24/Q$4))
B31: =B25 -> R&D | C31: 0 | G31: =IF(G$4="","",ABS(G25/G$4)) -> 0 | H31: =IF(H$4="","",ABS(H25/H$4)) -> 0 | I31: =IF(I$4="","",ABS(I25/I$4)) | J31: =IF(J$4="","",ABS(J25/J$4)) | K31: =IF(K$4="","",ABS(K25/K$4)) | L31: =IF(L$4="","",ABS(L25/L$4)) | M31: =IF(M$4="","",ABS(M25/M$4)) | N31: =IF(N$4="","",ABS(N25/N$4)) | ... Q31: =IF(Q$4="","",ABS(Q25/Q$4))
B32: Variable Costs | C32: =ABS(C26/$C$4) -> 0.39398348 | G32: =IF(G$4="","",ABS(G26/G$4)) -> 0.37916491 | H32: =IF(H$4="","",ABS(H26/H$4)) -> 0.40880206 | I32: =IF(I$4="","",ABS(I26/I$4)) | J32: =IF(J$4="","",ABS(J26/J$4)) | K32: =IF(K$4="","",ABS(K26/K$4)) | L32: =IF(L$4="","",ABS(L26/L$4)) | M32: =IF(M$4="","",ABS(M26/M$4)) | N32: =IF(N$4="","",ABS(N26/N$4)) | ... Q32: =IF(Q$4="","",ABS(Q26/Q$4))
B34: Fixed Costs
B35: G&A and other Opex | C35: =G35 -> -20684476 | G35: =IF(G4="","",Data!C41) -> -20684476 | H35: =IF(H4="","",Data!D41) -> -19536770 | I35: =IF(I4="","",Data!E41) | J35: =IF(J4="","",Data!F41) | K35: =IF(K4="","",Data!G41) | L35: =IF(L4="","",Data!H41) | M35: =IF(M4="","",Data!I41) | N35: =IF(N4="","",Data!J41) | ... Q35: =IF(Q4="","",Data!M41)
B37: Fixed Costs % of Sales
B38: G&A and other Opex | C38: =ABS(C35/$C$4) -> 0.49127084 | G38: =IF(G$4="","",ABS(G35/G$4)) -> 0.48379435 | H38: =IF(H$4="","",ABS(H35/H$4)) -> 0.47129535 | I38: =IF(I$4="","",ABS(I35/I$4)) | J38: =IF(J$4="","",ABS(J35/J$4)) | K38: =IF(K$4="","",ABS(K35/K$4)) | L38: =IF(L$4="","",ABS(L35/L$4)) | M38: =IF(M$4="","",ABS(M35/M$4)) | N38: =IF(N$4="","",ABS(N35/N$4)) | ... Q38: =IF(Q$4="","",ABS(Q35/Q$4))
B40: Tax % of Pre-tax Profit
B41: Income Tax Rate | C41: 0.25 | E41: Use the marginal tax rate | G41: =IF(G$4="","",-G14/SUM(G8+G11,G12)) -> 0.33238647 | H41: =IF(H$4="","",-H14/SUM(H8+H11,H12)) -> 0.27902127 | I41: =IF(I$4="","",-I14/SUM(I8+I11,I12)) | J41: =IF(J$4="","",-J14/SUM(J8+J11,J12)) | K41: =IF(K$4="","",-K14/SUM(K8+K11,K12)) | L41: =IF(L$4="","",-L14/SUM(L8+L11,L12)) | M41: =IF(M$4="","",-M14/SUM(M8+M11,M12)) | N41: =IF(N$4="","",-N14/SUM(N8+N11,N12)) | ... Q41: =IF(Q$4="","",-Q14/SUM(Q8+Q11,Q12))
B43: Non-operating Income | E43: Notes
B44: Interest
B45: Interest Expense | C45: =-BS!G31*Normalized_FCF!C52 -> -154206.15 | G45: =Data!C51 -> -274678 | H45: =Data!D51 -> -351430 | I45: =Data!E51 | J45: =Data!F51 | K45: =Data!G51 | L45: =Data!H51 | M45: =Data!I51 | N45: =Data!J51 | ... Q45: =Data!M51
B46: Operating Interest Income | C46: =BS!D75*C51 -> 62121.272 | G46: =IFERROR(IF(G$4="","",($C$46/$C$47)*G47),0) -> 151540.68 | H46: =IFERROR(IF(H$4="","",($C$46/$C$47)*H47),0) -> 129364.38 | I46: =IFERROR(IF(I$4="","",($C$46/$C$47)*I47),0) | J46: =IFERROR(IF(J$4="","",($C$46/$C$47)*J47),0) | K46: =IFERROR(IF(K$4="","",($C$46/$C$47)*K47),0) | L46: =IFERROR(IF(L$4="","",($C$46/$C$47)*L47),0) | M46: =IFERROR(IF(M$4="","",($C$46/$C$47)*M47),0) | N46: =IFERROR(IF(N$4="","",($C$46/$C$47)*N47),0) | ... Q46: =IFERROR(IF(Q$4="","",($C$46/$C$47)*Q47),0)
B47: From Interest Income | C47: =BS!$C$66*C51 -> 156973.36 | G47: =Data!C52 -> 382926 | H47: =Data!D52 -> 326889 | I47: =Data!E52 | J47: =Data!F52 | K47: =Data!G52 | L47: =Data!H52 | M47: =Data!I52 | N47: =Data!J52 | ... Q47: =Data!M52
B48: Net Interest Income | C48: =C45+C46 -> -92084.878 | G48: =IF(G$4="","",(G45+G46)) -> -123137.32 | H48: =IF(H$4="","",(H45+H46)) -> -222065.62 | I48: =IF(I$4="","",(I45+I46)) | J48: =IF(J$4="","",(J45+J46)) | K48: =IF(K$4="","",(K45+K46)) | L48: =IF(L$4="","",(L45+L46)) | M48: =IF(M$4="","",(M45+M46)) | N48: =IF(N$4="","",(N45+N46)) | ... Q48: =IF(Q$4="","",(Q45+Q46))
B50: % Interest | G50: Latest Asset Value
B51: Interest Yield/Cash | C51: 0.02 | G51: =IF(Normalized_FCF!G4="","",Normalized_FCF!G47/BS!$C$66) -> 0.048788661
B52: Interest Rate/Debt | C52: 0.025 | G52: =IFERROR(ABS(Normalized_FCF!G45/BS!$G$31),0) -> 0.044530974
B53: Pre-tax Profit/Interest Expense | C53: =-C8/C45 -> 31.32984 | G53: =IF(G4="","",-G8/G45) -> 21.330918 | H53: =IF(H4="","",-H8/H45) -> 14.143255 | I53: =IF(I4="","",-I8/I45) | J53: =IF(J4="","",-J8/J45) | K53: =IF(K4="","",-K8/K45) | L53: =IF(L4="","",-L8/L45) | M53: =IF(M4="","",-M8/M45) | N53: =IF(N4="","",-N8/N45) | ... Q53: =IF(Q4="","",-Q8/Q45)
B55: Non-operating EBIT | G55: Latest Asset Value
B56: Dividend or Interests from FA | C56: =BS!$C67*C64 -> 0 | G56: =Data!C56 -> 0 | H56: =Data!D56 -> 0 | I56: =Data!E56 | J56: =Data!F56 | K56: =Data!G56 | L56: =Data!H56 | M56: =Data!I56 | N56: =Data!J56 | ... Q56: =Data!M56
B57: Share of JV or associate Results | C57: =BS!$C68*C65 -> 51775 | G57: =Data!C55 -> 51775 | H57: =Data!D55 -> 45863 | I57: =Data!E55 | J57: =Data!F55 | K57: =Data!G55 | L57: =Data!H55 | M57: =Data!I55 | N57: =Data!J55 | ... Q57: =Data!M55
B58: Investment property | C58: =BS!$C69*C66 -> 0 | G58: =Data!C57 -> 0 | H58: =Data!D57 -> 0 | I58: =Data!E57 | J58: =Data!F57 | K58: =Data!G57 | L58: =Data!H57 | M58: =Data!I57 | N58: =Data!J57 | ... Q58: =Data!M57
B59: Stable Non-Operating EBIT | C59: =SUM(C56:C58) -> 51775 | G59: =IF(G4="","",SUM(G56:G58)) -> 51775 | H59: =IF(H4="","",SUM(H56:H58)) -> 45863 | I59: =IF(I4="","",SUM(I56:I58)) | J59: =IF(J4="","",SUM(J56:J58)) | K59: =IF(K4="","",SUM(K56:K58)) | L59: =IF(L4="","",SUM(L56:L58)) | M59: =IF(M4="","",SUM(M56:M58)) | N59: =IF(N4="","",SUM(N56:N58)) | ... Q59: =IF(Q4="","",SUM(Q56:Q58))
B60: Other Non-operating Income | C60: 0 | E60: Assume 0 | G60: =Data!C58 -> 612704 | H60: =Data!D58 -> 845067 | I60: =Data!E58 | J60: =Data!F58 | K60: =Data!G58 | L60: =Data!H58 | M60: =Data!I58 | N60: =Data!J58 | ... Q60: =Data!M58
B61: Total Non-Operating EBIT | C61: =C59+C60 -> 51775 | G61: =IF(G4="","",G59+G60) -> 664479 | H61: =IF(H4="","",H59+H60) -> 890930 | I61: =IF(I4="","",I59+I60) | J61: =IF(J4="","",J59+J60) | K61: =IF(K4="","",K59+K60) | L61: =IF(L4="","",L59+L60) | M61: =IF(M4="","",M59+M60) | N61: =IF(N4="","",N59+N60) | ... Q61: =IF(Q4="","",Q59+Q60)
B63: Non-operating Asset Yield % | G63: Latest Asset Value
B64: Dividend or Interests from FA | C64: =G64 -> 0 | G64: =IFERROR(G56/BS!$C$67,0) -> 0
B65: JV or associate | C65: =G65 -> 0.28770442 | G65: =IFERROR(G57/BS!$C$68,0) -> 0.28770442
B66: Investment property | C66: =G66 -> 0 | G66: =IFERROR(G58/BS!$C$69,0) -> 0
B67: Stable Non-Operating EBIT | C67: =C59/BS!C70 -> 0.0064487988 | G67: =G59/BS!C70 -> 0.0064487988
B69: P&L & Dividend Analysis | E69: Notes
B70: P&L % Sales
B71: Variable Costs | C71: =ABS(C5/C$4) -> 0.39398348 | G71: =IF(G$4="","",ABS(G5/G$4)) -> 0.37916491 | H71: =IF(H$4="","",ABS(H5/H$4)) -> 0.40880206 | I71: =IF(I$4="","",ABS(I5/I$4)) | J71: =IF(J$4="","",ABS(J5/J$4)) | K71: =IF(K$4="","",ABS(K5/K$4)) | L71: =IF(L$4="","",ABS(L5/L$4)) | M71: =IF(M$4="","",ABS(M5/M$4)) | N71: =IF(N$4="","",ABS(N5/N$4)) | ... Q71: =IF(Q$4="","",ABS(Q5/Q$4))
B72: Contribution Margin | C72: =ABS(C6/C$4) -> 0.60601652 | G72: =IF(G$4="","",ABS(G6/G$4)) -> 0.62083509 | H72: =IF(H$4="","",ABS(H6/H$4)) -> 0.59119794 | I72: =IF(I$4="","",ABS(I6/I$4)) | J72: =IF(J$4="","",ABS(J6/J$4)) | K72: =IF(K$4="","",ABS(K6/K$4)) | L72: =IF(L$4="","",ABS(L6/L$4)) | M72: =IF(M$4="","",ABS(M6/M$4)) | N72: =IF(N$4="","",ABS(N6/N$4)) | ... Q72: =IF(Q$4="","",ABS(Q6/Q$4))
B73: Fixed Costs | C73: =ABS(C7/C$4) -> 0.49127084 | G73: =IF(G$4="","",ABS(G7/G$4)) -> 0.48379435 | H73: =IF(H$4="","",ABS(H7/H$4)) -> 0.47129535 | I73: =IF(I$4="","",ABS(I7/I$4)) | J73: =IF(J$4="","",ABS(J7/J$4)) | K73: =IF(K$4="","",ABS(K7/K$4)) | L73: =IF(L$4="","",ABS(L7/L$4)) | M73: =IF(M$4="","",ABS(M7/M$4)) | N73: =IF(N$4="","",ABS(N7/N$4)) | ... Q73: =IF(Q$4="","",ABS(Q7/Q$4))
B74: Operating EBIT | C74: =ABS(C8/C$4) -> 0.11474568 | G74: =IF(G$4="","",ABS(G8/G$4)) -> 0.13704074 | H74: =IF(H$4="","",ABS(H8/H$4)) -> 0.1199026 | I74: =IF(I$4="","",ABS(I8/I$4)) | J74: =IF(J$4="","",ABS(J8/J$4)) | K74: =IF(K$4="","",ABS(K8/K$4)) | L74: =IF(L$4="","",ABS(L8/L$4)) | M74: =IF(M$4="","",ABS(M8/M$4)) | N74: =IF(N$4="","",ABS(N8/N$4)) | ... Q74: =IF(Q$4="","",ABS(Q8/Q$4))
B75: Add Back D&A | C75: =ABS(C9/C$4) -> 0 | G75: =IF(G$4="","",G9/G$4) -> 0 | H75: =IF(H$4="","",H9/H$4) -> 0 | I75: =IF(I$4="","",I9/I$4) | J75: =IF(J$4="","",J9/J$4) | K75: =IF(K$4="","",K9/K$4) | L75: =IF(L$4="","",L9/L$4) | M75: =IF(M$4="","",M9/M$4) | N75: =IF(N$4="","",N9/N$4) | ... Q75: =IF(Q$4="","",Q9/Q$4)
B76: Maintenance Capex | C76: =MAX(AVERAGE(G76:J76),C75) -> 0 | E76: Historical Average or D&A | G76: =IF(G$4="","",-G10/G$4) -> 0 | H76: =IF(H$4="","",-H10/H$4) -> 0 | I76: =IF(I$4="","",-I10/I$4) | J76: =IF(J$4="","",-J10/J$4) | K76: =IF(K$4="","",-K10/K$4) | L76: =IF(L$4="","",-L10/L$4) | M76: =IF(M$4="","",-M10/M$4) | N76: =IF(N$4="","",-N10/N$4) | ... Q76: =IF(Q$4="","",-Q10/Q$4)
B77: Non-Operating EBIT | C77: =ABS(C11/C$4) -> 0.0012296926 | G77: =IF(G$4="","",G11/G$4) -> 0.0012109783 | H77: =IF(H$4="","",H11/H$4) -> 0.0011063763 | I77: =IF(I$4="","",I11/I$4) | J77: =IF(J$4="","",J11/J$4) | K77: =IF(K$4="","",K11/K$4) | L77: =IF(L$4="","",L11/L$4) | M77: =IF(M$4="","",M11/M$4) | N77: =IF(N$4="","",N11/N$4) | ... Q77: =IF(Q$4="","",Q11/Q$4)
B78: Net Interest Income | C78: =ABS(C12/C$4) -> 0.0021870805 | G78: =IF(G$4="","",ABS(G12/G$4)) -> 0.0028800893 | H78: =IF(H$4="","",ABS(H12/H$4)) -> 0.005357001 | I78: =IF(I$4="","",ABS(I12/I$4)) | J78: =IF(J$4="","",ABS(J12/J$4)) | K78: =IF(K$4="","",ABS(K12/K$4)) | L78: =IF(L$4="","",ABS(L12/L$4)) | M78: =IF(M$4="","",ABS(M12/M$4)) | N78: =IF(N$4="","",ABS(N12/N$4)) | ... Q78: =IF(Q$4="","",ABS(Q12/Q$4))
B79: Pre-tax Profit | C79: =C13/C4 -> 0.11378829 | G79: =IF(G$4="","",G13/G$4) -> 0.13537163 | H79: =IF(H$4="","",H13/H$4) -> 0.11565197 | I79: =IF(I$4="","",I13/I$4) | J79: =IF(J$4="","",J13/J$4) | K79: =IF(K$4="","",K13/K$4) | L79: =IF(L$4="","",L13/L$4) | M79: =IF(M$4="","",M13/M$4) | N79: =IF(N$4="","",N13/N$4) | ... Q79: =IF(Q$4="","",Q13/Q$4)
B80: Income Tax | C80: =ABS(C14/C$4) -> 0.028447072 | G80: =IF(G$4="","",ABS(G14/G$4)) -> 0.044995698 | H80: =IF(H$4="","",ABS(H14/H$4)) -> 0.03226936 | I80: =IF(I$4="","",ABS(I14/I$4)) | J80: =IF(J$4="","",ABS(J14/J$4)) | K80: =IF(K$4="","",ABS(K14/K$4)) | L80: =IF(L$4="","",ABS(L14/L$4)) | M80: =IF(M$4="","",ABS(M14/M$4)) | N80: =IF(N$4="","",ABS(N14/N$4)) | ... Q80: =IF(Q$4="","",ABS(Q14/Q$4))
B81: =B15 -> NCI’s Share of Profits | C81: =MIN(BS!C62,MAX(G81:K81)) -> 0 | G81: =IF(G$4="","",-G15/G$4) -> 0.00018257647 | H81: =IF(H$4="","",-H15/H$4) -> 8.8798618e-05 | I81: =IF(I$4="","",-I15/I$4) | J81: =IF(J$4="","",-J15/J$4) | K81: =IF(K$4="","",-K15/K$4) | L81: =IF(L$4="","",-L15/L$4) | M81: =IF(M$4="","",-M15/M$4) | N81: =IF(N$4="","",-N15/N$4) | ... Q81: =IF(Q$4="","",-Q15/Q$4)
B82: After-tax Profit | C82: =ABS(C16/C$4) -> 0.085341217 | G82: =IF(G$4="","",ABS(G16/G$4)) -> 0.090193356 | H82: =IF(H$4="","",ABS(H16/H$4)) -> 0.083293812 | I82: =IF(I$4="","",ABS(I16/I$4)) | J82: =IF(J$4="","",ABS(J16/J$4)) | K82: =IF(K$4="","",ABS(K16/K$4)) | L82: =IF(L$4="","",ABS(L16/L$4)) | M82: =IF(M$4="","",ABS(M16/M$4)) | N82: =IF(N$4="","",ABS(N16/N$4)) | ... Q82: =IF(Q$4="","",ABS(Q16/Q$4))
B83: WCInv | C83: 0 | E83: =E17 -> WCInv is by default excluded
B84: Net Borrowing | C84: 0 | E84: =E18 -> Net borrowing is excluded
B85: Total FCFE | C85: =ABS(C19/C$4) -> 0.085341217 | G85: =IF(G$4="","",ABS(G19/G$4)) -> 0.090193356 | H85: =IF(H$4="","",ABS(H19/H$4)) -> 0.083293812 | I85: =IF(I$4="","",ABS(I19/I$4)) | J85: =IF(J$4="","",ABS(J19/J$4)) | K85: =IF(K$4="","",ABS(K19/K$4)) | L85: =IF(L$4="","",ABS(L19/L$4)) | M85: =IF(M$4="","",ABS(M19/M$4)) | N85: =IF(N$4="","",ABS(N19/N$4)) | ... Q85: =IF(Q$4="","",ABS(Q19/Q$4))
B87: Dividends
B88: ="Dividend per share ("&Market_currency&")" -> Dividend per share (HKD) | C88: =G88 -> 0 | G88: =Data!C65 -> 0 | H88: =Data!D65 -> 0 | I88: =Data!E65 | J88: =Data!F65 | K88: =Data!G65 | L88: =Data!H65 | M88: =Data!I65 | N88: =Data!J65 | ... Q88: =Data!M65
B89: ="Dividend ("&Market_currency&")" -> Dividend (HKD) | C89: =C88*Common_Shares/scaling_factor -> 0 | G89: =IF(G$4="","",G88*Common_Shares/scaling_factor) -> 0 | H89: =IF(H$4="","",H88*Common_Shares/scaling_factor) -> 0 | I89: =IF(I$4="","",I88*Common_Shares/scaling_factor) | J89: =IF(J$4="","",J88*Common_Shares/scaling_factor) | K89: =IF(K$4="","",K88*Common_Shares/scaling_factor) | L89: =IF(L$4="","",L88*Common_Shares/scaling_factor) | M89: =IF(M$4="","",M88*Common_Shares/scaling_factor) | N89: =IF(N$4="","",N88*Common_Shares/scaling_factor) | ... Q89: =IF(Q$4="","",Q88*Common_Shares/scaling_factor)
B90: Payout Ratio | C90: =C88/(C19*scaling_factor/Common_Shares) -> 0 | G90: =IF(G$4="","",G88/(G19*scaling_factor/Common_Shares)) -> 0 | H90: =IF(H$4="","",H88/(H19*scaling_factor/Common_Shares)) -> 0 | I90: =IF(I$4="","",I88/(I19*scaling_factor/Common_Shares)) | J90: =IF(J$4="","",J88/(J19*scaling_factor/Common_Shares)) | K90: =IF(K$4="","",K88/(K19*scaling_factor/Common_Shares)) | L90: =IF(L$4="","",L88/(L19*scaling_factor/Common_Shares)) | M90: =IF(M$4="","",M88/(M19*scaling_factor/Common_Shares)) | N90: =IF(N$4="","",N88/(N19*scaling_factor/Common_Shares)) | ... Q90: =IF(Q$4="","",Q88/(Q19*scaling_factor/Common_Shares))
B91: Dividend tax rate | C91: 0
B92: Dividend after tax Yield | C92: =(C88*(1-dividend_tax_rate))/Market_Price -> 0 | G92: =IF(G$4="","",(G88*(1-dividend_tax_rate))/Market_Price) -> 0 | H92: =IF(H$4="","",(H88*(1-dividend_tax_rate))/Market_Price) -> 0 | I92: =IF(I$4="","",(I88*(1-dividend_tax_rate))/Market_Price) | J92: =IF(J$4="","",(J88*(1-dividend_tax_rate))/Market_Price) | K92: =IF(K$4="","",(K88*(1-dividend_tax_rate))/Market_Price) | L92: =IF(L$4="","",(L88*(1-dividend_tax_rate))/Market_Price) | M92: =IF(M$4="","",(M88*(1-dividend_tax_rate))/Market_Price) | N92: =IF(N$4="","",(N88*(1-dividend_tax_rate))/Market_Price) | ... Q92: =IF(Q$4="","",(Q88*(1-dividend_tax_rate))/Market_Price)
B94: YoY %
B95: Sales | C95: =C4/G4-1 -> -0.015218671 | G95: =IF(H4="","",G4/H4-1) -> 0.031392856 | H95: =IF(I4="","",H4/I4-1) | I95: =IF(J4="","",I4/J4-1) | J95: =IF(K4="","",J4/K4-1) | K95: =IF(L4="","",K4/L4-1) | L95: =IF(M4="","",L4/M4-1) | M95: =IF(N4="","",M4/N4-1) | N95: =IF(O4="","",N4/O4-1) | ... Q95: =IF(R4="","",Q4/R4-1)
B96: Pre-tax Profit | C96: =C13/G13-1 -> -0.17222994 | G96: =IF(H5="","",G13/H13-1) -> 0.20725425 | H96: =IF(I5="","",H13/I13-1) | I96: =IF(J5="","",I13/J13-1) | J96: =IF(K5="","",J13/K13-1) | K96: =IF(L5="","",K13/L13-1) | L96: =IF(M5="","",L13/M13-1) | M96: =IF(N5="","",M13/N13-1) | N96: =IF(O5="","",N13/O13-1) | ... Q96: =IF(R5="","",Q13/R13-1)
B98: Operating Efficiency Analysis | E98: Notes
B99: Balance Sheet | G99: Latest Asset Value
B100: Total Assets | C100: =BS!G32 -> 22781257 | G100: =IF(G$4="","",G104+G103) -> 22781257 | H100: =IF(H$4="","",H104+H103) -> 24676998 | I100: =IF(I$4="","",I104+I103) | J100: =IF(J$4="","",J104+J103) | K100: =IF(K$4="","",K104+K103) | L100: =IF(L$4="","",L104+L103) | M100: =IF(M$4="","",M104+M103) | N100: =IF(N$4="","",N104+N103) | ... Q100: =IF(Q$4="","",Q104+Q103)
B101: Incl. AR | C101: =BS!C4 -> 1791826 | G101: =IF(G$4="","",Data!D77) -> 411995 | H101: =IF(H$4="","",Data!E77) | I101: =IF(I$4="","",Data!F77) | J101: =IF(J$4="","",Data!G77) | K101: =IF(K$4="","",Data!H77) | L101: =IF(L$4="","",Data!I77) | M101: =IF(M$4="","",Data!J77) | N101: =IF(N$4="","",Data!K77) | ... Q101: =IF(Q$4="","",Data!N77)
B102: Incl. Inventory | C102: =BS!C6+BS!C7 -> 1060641 | G102: =IF(G$4="","",Data!D78) -> 1074627 | H102: =IF(H$4="","",Data!E78) | I102: =IF(I$4="","",Data!F78) | J102: =IF(J$4="","",Data!G78) | K102: =IF(K$4="","",Data!H78) | L102: =IF(L$4="","",Data!I78) | M102: =IF(M$4="","",Data!J78) | N102: =IF(N$4="","",Data!K78) | ... Q102: =IF(Q$4="","",Data!N78)
B103: Total Liabilities | C103: =BS!G30 -> 12363761 | G103: =Data!C79 -> 12363761 | H103: =Data!D79 -> 13160058 | I103: =Data!E79 | J103: =Data!F79 | K103: =Data!G79 | L103: =Data!H79 | M103: =Data!I79 | N103: =Data!J79 | ... Q103: =Data!M79
B104: Total Equity | C104: =BS!G27 -> 10417496 | G104: =Data!C80 -> 10417496 | H104: =Data!D80 -> 11516940 | I104: =Data!E80 | J104: =Data!F80 | K104: =Data!G80 | L104: =Data!H80 | M104: =Data!I80 | N104: =Data!J80 | ... Q104: =Data!M80
B106: Operating Asset % of Sales | G106: Latest Asset Value
B107: AR | C107: =C101/C$4 -> 0.042557127 | G107: =IF(G$4="","",G101/G$4) -> 0.0096362534 | H107: =IF(H$4="","",H101/H$4) -> #VALUE! | I107: =IF(I$4="","",I101/I$4) | J107: =IF(J$4="","",J101/J$4) | K107: =IF(K$4="","",K101/K$4) | L107: =IF(L$4="","",L101/L$4) | M107: =IF(M$4="","",M101/M$4) | N107: =IF(N$4="","",N101/N$4) | ... Q107: =IF(Q$4="","",Q101/Q$4)
B108: Inventory | C108: =C102/C$4 -> 0.025190969 | G108: =IF(G$4="","",G102/G$4) -> 0.025134718 | H108: =IF(H$4="","",H102/H$4) -> #VALUE! | I108: =IF(I$4="","",I102/I$4) | J108: =IF(J$4="","",J102/J$4) | K108: =IF(K$4="","",K102/K$4) | L108: =IF(L$4="","",L102/L$4) | M108: =IF(M$4="","",M102/M$4) | N108: =IF(N$4="","",N102/N$4) | ... Q108: =IF(Q$4="","",Q102/Q$4)
B109: Properties held for sale | C109: =BS!$G$38/C$4 -> 0 | G109: =BS!$G$38/G$4 -> 0
B111: Cash Flow Statement
B112: CFO/Net Income | G112: =IF(G$4="","",Data!C$22/Data!C15) -> 1.6215652 | H112: =IF(H$4="","",Data!D$22/Data!D15) -> 2.0004868 | I112: =IF(I$4="","",Data!E$22/Data!E15) | J112: =IF(J$4="","",Data!F$22/Data!F15) | K112: =IF(K$4="","",Data!G$22/Data!G15) | L112: =IF(L$4="","",Data!H$22/Data!H15) | M112: =IF(M$4="","",Data!I$22/Data!I15) | N112: =IF(N$4="","",Data!J$22/Data!J15) | ... Q112: =IF(Q$4="","",Data!M$22/Data!M15)
B113: CFO/FCFE | G113: =IF(G$4="","",Data!C$22/G19) -> 1.9797955 | H113: =IF(H$4="","",Data!D$22/H19) -> 2.606676 | I113: =IF(I$4="","",Data!E$22/I19) | J113: =IF(J$4="","",Data!F$22/J19) | K113: =IF(K$4="","",Data!G$22/K19) | L113: =IF(L$4="","",Data!H$22/L19) | M113: =IF(M$4="","",Data!I$22/M19) | N113: =IF(N$4="","",Data!J$22/N19) | ... Q113: =IF(Q$4="","",Data!M$22/Q19)
B115: ROE | G115: =IFERROR(IF(#REF!*G117*(1/#REF!)=G119,"","Error"),"") | H115: =IFERROR(IF(#REF!*H117*(1/#REF!)=H119,"","Error"),"") | I115: =IFERROR(IF(#REF!*I117*(1/#REF!)=I119,"","Error"),"") | J115: =IFERROR(IF(#REF!*J117*(1/#REF!)=J119,"","Error"),"") | K115: =IFERROR(IF(#REF!*K117*(1/#REF!)=K119,"","Error"),"") | L115: =IFERROR(IF(#REF!*L117*(1/#REF!)=L119,"","Error"),"") | M115: =IFERROR(IF(#REF!*M117*(1/#REF!)=M119,"","Error"),"") | N115: =IFERROR(IF(#REF!*N117*(1/#REF!)=N119,"","Error"),"") | ... Q115: =IFERROR(IF(#REF!*Q117*(1/#REF!)=Q119,"","Error"),"")
B116: Pre-tax Profit/Sales | C116: =IF(valuation_method="DDM",C13/(C4+C12),C79) -> 0.11378829 | G116: =IF(G4="","",IF(valuation_method="DDM",G13/(G4+G12),G79)) -> 0.13537163 | H116: =IF(H4="","",IF(valuation_method="DDM",H13/(H4+H12),H79)) -> 0.11565197 | I116: =IF(I4="","",IF(valuation_method="DDM",I13/(I4+I12),I79)) | J116: =IF(J4="","",IF(valuation_method="DDM",J13/(J4+J12),J79)) | K116: =IF(K4="","",IF(valuation_method="DDM",K13/(K4+K12),K79)) | L116: =IF(L4="","",IF(valuation_method="DDM",L13/(L4+L12),L79)) | M116: =IF(M4="","",IF(valuation_method="DDM",M13/(M4+M12),M79)) | N116: =IF(N4="","",IF(valuation_method="DDM",N13/(N4+N12),N79)) | ... Q116: =IF(Q4="","",IF(valuation_method="DDM",Q13/(Q4+Q12),Q79))
...

Sheet DCF
B2: No-Growth DCF Valuation
B3: No-Growth DCF | C3: =scaling_factor -> 1000 | E3: Normalized Values
B4: Normalized FCFE | C4: =Normalized_FCF!C19 -> 3593208.1 | D4: =Reporting_currency -> CNY | E4: Stage | F4: I | H4: Stage | I4: =IF(I6=F6,"I","II") -> I
B5: /Equity Cost of Capital | C5: =Equity_Cost -> 0.075 | E5: Revenues | F5: =Normalized_FCF!C4 -> 42104018 | H5: Change year | I5: =IF(I4="II",_xlfn.CEILING.MATH(C17/2),C17+1) -> 6
B6: Stable Income Value | C6: =(C4*(1+Terminal_Growth))/(Equity_Cost-Terminal_Growth) -> 47909441 | D6: =Reporting_currency -> CNY | E6: Contribution Margin | F6: =Normalized_FCF!C32 -> 0.39398348 | H6: Contribution Margin_II | I6: =Scenarios!C64 -> 0.39398348
B7: - Interest-bearing Debt | C7: =BS!G31 -> 6168246 | D7: =Reporting_currency -> CNY | E7: Fixed Costs | F7: =Normalized_FCF!C7 -> -20684476 | H7: High Growth Rate_II | I7: =IF(I4="II",C16/2,C16) -> 0.052329465
B8: + Non-operating Cash | C8: =BS!D66 -> 4742604.4 | D8: =Reporting_currency -> CNY | E8: D&A - Maintenance Capx | F8: =Normalized_FCF!C75-Normalized_FCF!C76 -> 0
B9: + Other Non-operating Assets | C9: =BS!H42 -> 2656436.4 | D9: =Reporting_currency -> CNY | E9: Other Income | F9: =Normalized_FCF!C11+Normalized_FCF!C12 -> -40309.878 | H9: Special Assumption
B10: Equity Value | C10: =C6-C7+C8+C9 -> 49140236 | D10: =Reporting_currency -> CNY | E10: Tax rate | F10: =Normalized_FCF!C41 -> 0.25 | H10: Terminal Growth Rate (g): | I10: =Terminal_Growth -> 0
B11: * Exchange rate | C11: =Exchange_Rate -> 1.0923594 | D11: =Thesis!C15 -> CNY/HKD
B12: Equity Value per share | C12: =(C10*scaling_factor)/Common_Shares*Exchange_Rate -> 9.6302115 | D12: =Market_currency -> HKD | E12: Note on g=0: It's to avoid overestimating the stock’s value, especially if future growth is uncertain or unreliable.
B14: Implied Growth Scenario Analysis
B15: FCFE Projection
B16: High Growth Rate (HGR) | C16: =Scenarios!C70 -> 0.052329465
B17: High Growth Period (HGP) | C17: =Scenarios!C69 -> 5
B18: Value Per Share | C18: =(I52-C7+C8+C9)*Exchange_Rate/Common_Shares*scaling_factor -> 12.005184 | D18: =Market_currency -> HKD
A20: Stage | B20: Year | C20: Revenues | D20: Contribution Margin | E20: Fixed Costs | F20: FCFE | G20: Growth Rates | H20: Discount Factor | I20: PV of FCFE
A21: =IF($C$17<B21,"",IF(B21>=$I$5,"II","I")) -> I | B21: 1 | C21: =F5*(1+G21) -> 44307298 | D21: =$F$6 -> 0.39398348 | E21: =F7*(1+G21) -> -21766884 | F21: =(C21*(1-(D21+$F$8))+E21+$F$9)*(1-$F$10) -> 3782820.8 | G21: =IF(A21="",0,IF(A21="I",$C$16,$I$7)) -> 0.052329465 | H21: =IF($C$17<B21,0,1/(1+Equity_Cost)^B21) -> 0.93023256 | I21: =F21*H21 -> 3518903.1
A22: =IF($C$17<B22,"",IF(B22>=$I$5,"II","I")) -> I | B22: 2 | C22: =IF(A22="",0,C21*(1+G22)) -> 46625875 | D22: =IF($C$17<B22,0,IF(B22>=$I$5,$I$6,$F$6)) -> 0.39398348 | E22: =IF(A22="",0,E21*(1+G22)) -> -22905933 | F22: =IF(A22="", 0,(C22*(1-(D22+$F$8))+E22+$F$9)*(1-$F$10)) -> 3982355.8 | G22: =IF(A22="",0,IF(A22="I",$C$16,$I$7)) -> 0.052329465 | H22: =IF($C$17<B22,0,1/(1+Equity_Cost)^B22) -> 0.86533261 | I22: =F22*H22 -> 3446062.4
A23: =IF($C$17<B23,"",IF(B23>=$I$5,"II","I")) -> I | B23: 3 | C23: =IF(A23="",0,C22*(1+G23)) -> 49065783 | D23: =IF($C$17<B23,0,IF(B23>=$I$5,$I$6,$F$6)) -> 0.39398348 | E23: =IF(A23="",0,E22*(1+G23)) -> -24104588 | F23: =IF(A23="", 0,(C23*(1-(D23+$F$8))+E23+$F$9)*(1-$F$10)) -> 4192332.4 | G23: =IF(A23="",0,IF(A23="I",$C$16,$I$7)) -> 0.052329465 | H23: =IF($C$17<B23,0,1/(1+Equity_Cost)^B23) -> 0.80496057 | I23: =F23*H23 -> 3374662.3
A24: =IF($C$17<B24,"",IF(B24>=$I$5,"II","I")) -> I | B24: 4 | C24: =IF(A24="",0,C23*(1+G24)) -> 51633369 | D24: =IF($C$17<B24,0,IF(B24>=$I$5,$I$6,$F$6)) -> 0.39398348 | E24: =IF(A24="",0,E23*(1+G24)) -> -25365968 | F24: =IF(A24="", 0,(C24*(1-(D24+$F$8))+E24+$F$9)*(1-$F$10)) -> 4413297 | G24: =IF(A24="",0,IF(A24="I",$C$16,$I$7)) -> 0.052329465 | H24: =IF($C$17<B24,0,1/(1+Equity_Cost)^B24) -> 0.74880053 | I24: =F24*H24 -> 3304679.1
A25: =IF($C$17<B25,"",IF(B25>=$I$5,"II","I")) -> I | B25: 5 | C25: =IF(A25="",0,C24*(1+G25)) -> 54335315 | D25: =IF($C$17<B25,0,IF(B25>=$I$5,$I$6,$F$6)) -> 0.39398348 | E25: =IF(A25="",0,E24*(1+G25)) -> -26693356 | F25: =IF(A25="", 0,(C25*(1-(D25+$F$8))+E25+$F$9)*(1-$F$10)) -> 4645824.5 | G25: =IF(A25="",0,IF(A25="I",$C$16,$I$7)) -> 0.052329465 | H25: =IF($C$17<B25,0,1/(1+Equity_Cost)^B25) -> 0.69655863 | I25: =F25*H25 -> 3236089.2
A26: =IF($C$17<B26,"",IF(B26>=$I$5,"II","I")) | B26: 6 | C26: =IF(A26="",0,C25*(1+G26)) -> 0 | D26: =IF($C$17<B26,0,IF(B26>=$I$5,$I$6,$F$6)) -> 0 | E26: =IF(A26="",0,E25*(1+G26)) -> 0 | F26: =IF(A26="", 0,(C26*(1-(D26+$F$8))+E26+$F$9)*(1-$F$10)) -> 0 | G26: =IF(A26="",0,IF(A26="I",$C$16,$I$7)) -> 0 | H26: =IF($C$17<B26,0,1/(1+Equity_Cost)^B26) -> 0 | I26: =F26*H26 -> 0
A27: =IF($C$17<B27,"",IF(B27>=$I$5,"II","I")) | B27: 7 | C27: =IF(A27="",0,C26*(1+G27)) -> 0 | D27: =IF($C$17<B27,0,IF(B27>=$I$5,$I$6,$F$6)) -> 0 | E27: =IF(A27="",0,E26*(1+G27)) -> 0 | F27: =IF(A27="", 0,(C27*(1-(D27+$F$8))+E27+$F$9)*(1-$F$10)) -> 0 | G27: =IF(A27="",0,IF(A27="I",$C$16,$I$7)) -> 0 | H27: =IF($C$17<B27,0,1/(1+Equity_Cost)^B27) -> 0 | I27: =F27*H27 -> 0
A28: =IF($C$17<B28,"",IF(B28>=$I$5,"II","I")) | B28: 8 | C28: =IF(A28="",0,C27*(1+G28)) -> 0 | D28: =IF($C$17<B28,0,IF(B28>=$I$5,$I$6,$F$6)) -> 0 | E28: =IF(A28="",0,E27*(1+G28)) -> 0 | F28: =IF(A28="", 0,(C28*(1-(D28+$F$8))+E28+$F$9)*(1-$F$10)) -> 0 | G28: =IF(A28="",0,IF(A28="I",$C$16,$I$7)) -> 0 | H28: =IF($C$17<B28,0,1/(1+Equity_Cost)^B28) -> 0 | I28: =F28*H28 -> 0
A29: =IF($C$17<B29,"",IF(B29>=$I$5,"II","I")) | B29: 9 | C29: =IF(A29="",0,C28*(1+G29)) -> 0 | D29: =IF($C$17<B29,0,IF(B29>=$I$5,$I$6,$F$6)) -> 0 | E29: =IF(A29="",0,E28*(1+G29)) -> 0 | F29: =IF(A29="", 0,(C29*(1-(D29+$F$8))+E29+$F$9)*(1-$F$10)) -> 0 | G29: =IF(A29="",0,IF(A29="I",$C$16,$I$7)) -> 0 | H29: =IF($C$17<B29,0,1/(1+Equity_Cost)^B29) -> 0 | I29: =F29*H29 -> 0
A30: =IF($C$17<B30,"",IF(B30>=$I$5,"II","I")) | B30: 10 | C30: =IF(A30="",0,C29*(1+G30)) -> 0 | D30: =IF($C$17<B30,0,IF(B30>=$I$5,$I$6,$F$6)) -> 0 | E30: =IF(A30="",0,E29*(1+G30)) -> 0 | F30: =IF(A30="", 0,(C30*(1-(D30+$F$8))+E30+$F$9)*(1-$F$10)) -> 0 | G30: =IF(A30="",0,IF(A30="I",$C$16,$I$7)) -> 0 | H30: =IF($C$17<B30,0,1/(1+Equity_Cost)^B30) -> 0 | I30: =F30*H30 -> 0
A31: =IF($C$17<B31,"",IF(B31>=$I$5,"II","I")) | B31: 11 | C31: =IF(A31="",0,C30*(1+G31)) -> 0 | D31: =IF($C$17<B31,0,IF(B31>=$I$5,$I$6,$F$6)) -> 0 | E31: =IF(A31="",0,E30*(1+G31)) -> 0 | F31: =IF(A31="", 0,(C31*(1-(D31+$F$8))+E31+$F$9)*(1-$F$10)) -> 0 | G31: =IF(A31="",0,IF(A31="I",$C$16,$I$7)) -> 0 | H31: =IF($C$17<B31,0,1/(1+Equity_Cost)^B31) -> 0 | I31: =F31*H31 -> 0
A32: =IF($C$17<B32,"",IF(B32>=$I$5,"II","I")) | B32: 12 | C32: =IF(A32="",0,C31*(1+G32)) -> 0 | D32: =IF($C$17<B32,0,IF(B32>=$I$5,$I$6,$F$6)) -> 0 | E32: =IF(A32="",0,E31*(1+G32)) -> 0 | F32: =IF(A32="", 0,(C32*(1-(D32+$F$8))+E32+$F$9)*(1-$F$10)) -> 0 | G32: =IF(A32="",0,IF(A32="I",$C$16,$I$7)) -> 0 | H32: =IF($C$17<B32,0,1/(1+Equity_Cost)^B32) -> 0 | I32: =F32*H32 -> 0
A33: =IF($C$17<B33,"",IF(B33>=$I$5,"II","I")) | B33: 13 | C33: =IF(A33="",0,C32*(1+G33)) -> 0 | D33: =IF($C$17<B33,0,IF(B33>=$I$5,$I$6,$F$6)) -> 0 | E33: =IF(A33="",0,E32*(1+G33)) -> 0 | F33: =IF(A33="", 0,(C33*(1-(D33+$F$8))+E33+$F$9)*(1-$F$10)) -> 0 | G33: =IF(A33="",0,IF(A33="I",$C$16,$I$7)) -> 0 | H33: =IF($C$17<B33,0,1/(1+Equity_Cost)^B33) -> 0 | I33: =F33*H33 -> 0
... A50: =IF($C$17<B50,"",IF(B50>=$I$5,"II","I")) | B50: 30 | C50: =IF(A50="",0,C49*(1+G50)) -> 0 | D50: =IF($C$17<B50,0,IF(B50>=$I$5,$I$6,$F$6)) -> 0 | E50: =IF(A50="",0,E49*(1+G50)) -> 0 | F50: =IF(A50="", 0,(C50*(1-(D50+$F$8))+E50+$F$9)*(1-$F$10)) -> 0 | G50: =IF(A50="",0,IF(A50="I",$C$16,$I$7)) -> 0 | H50: =IF($C$17<B50,0,1/(1+Equity_Cost)^B50) -> 0 | I50: =F50*H50 -> 0
B51: Terminal Year | C51: =VLOOKUP(C17,B21:C50,2,FALSE)*(1+Terminal_Growth) -> 54335315 | D51: =I6 -> 0.39398348 | E51: =VLOOKUP(C17,B21:E50,4,FALSE)*(1+Terminal_Growth) -> -26693356 | F51: =(C51*(1-(D51+$F$8))+E51+$F$9)*(1-$F$10)/Equity_Cost -> 61944327 | G51: =Terminal_Growth -> 0 | H51: =1/(1+Equity_Cost)^C17 -> 0.69655863 | I51: =F51*H51 -> 43147856
H52: Total PV | I52: =SUM(I21:I51) -> 60028252
B54: Sensitivity Analysis (Enterprise Value)
A55: =I52 -> 60028252 | B55: =C78 -> 0 | C55: =C77 -> 0.02 | D55: =C76 -> 0.05 | E55: =C75 -> 0.08 | F55: =C74 -> 0.12
A56: 5 | B56: 47909441 | C56: 52270987 | D56: 59438716 | E56: 67415063 | F56: 79427561
A57: 10 | B57: 47909441 | C57: 55625264 | D57: 69688298 | E57: 87378543 | F57: 1.181184e+08
A58: 15 | B58: 47909441 | C58: 58204895 | D58: 78800227 | E58: 1.0781063e+08 | F58: 1.6561427e+08
A59: 20 | B59: 47909441 | C59: 60188777 | D59: 86900777 | E59: 1.2872232e+08 | F59: 2.2391899e+08
A60: 25 | B60: 47909441 | C60: 61714496 | D60: 94102206 | E60: 1.5012488e+08 | F60: 2.9549236e+08
A61: 30 | B61: 47909441 | C61: 62887861 | D61: 1.0050431e+08 | E61: 1.7202982e+08 | F61: 3.8335399e+08
B63: Sensitivity Analysis (Equity Value per share)
B64: =B55 -> 0 | C64: =C55 -> 0.02 | D64: =D55 -> 0.05 | E64: =E55 -> 0.08 | F64: =F55 -> 0.12
A65: 0 | B65: =C12 -> 9.6302115 | C65: =C12 -> 9.6302115 | D65: =C12 -> 9.6302115 | E65: =C12 -> 9.6302115 | F65: =C12 -> 9.6302115
A66: =A56 -> 5 | B66: =(B56-$C$7+$C$8+$C$9)/Common_Shares*$C$3*Exchange_Rate -> 9.6302115 | C66: =(C56-$C$7+$C$8+$C$9)/Common_Shares*$C$3*Exchange_Rate -> 10.484961 | D66: =(D56-$C$7+$C$8+$C$9)/Common_Shares*$C$3*Exchange_Rate -> 11.88965 | E66: =(E56-$C$7+$C$8+$C$9)/Common_Shares*$C$3*Exchange_Rate -> 13.452807 | F66: =(F56-$C$7+$C$8+$C$9)/Common_Shares*$C$3*Exchange_Rate -> 15.806945
A67: =A57 -> 10 | B67: =(B57-$C$7+$C$8+$C$9)/Common_Shares*$C$3*Exchange_Rate -> 9.6302115 | C67: =(C57-$C$7+$C$8+$C$9)/Common_Shares*$C$3*Exchange_Rate -> 11.142313 | D67: =(D57-$C$7+$C$8+$C$9)/Common_Shares*$C$3*Exchange_Rate -> 13.898302 | E67: =(E57-$C$7+$C$8+$C$9)/Common_Shares*$C$3*Exchange_Rate -> 17.365132 | F67: =(F57-$C$7+$C$8+$C$9)/Common_Shares*$C$3*Exchange_Rate -> 23.389345
A68: =A58 -> 15 | B68: =(B58-$C$7+$C$8+$C$9)/Common_Shares*$C$3*Exchange_Rate -> 9.6302115 | C68: =(C58-$C$7+$C$8+$C$9)/Common_Shares*$C$3*Exchange_Rate -> 11.647853 | D68: =(D58-$C$7+$C$8+$C$9)/Common_Shares*$C$3*Exchange_Rate -> 15.684004 | E68: =(E58-$C$7+$C$8+$C$9)/Common_Shares*$C$3*Exchange_Rate -> 21.36929 | F68: =(F58-$C$7+$C$8+$C$9)/Common_Shares*$C$3*Exchange_Rate -> 32.697305
A69: =A59 -> 20 | B69: =(B59-$C$7+$C$8+$C$9)/Common_Shares*$C$3*Exchange_Rate -> 9.6302115 | C69: =(C59-$C$7+$C$8+$C$9)/Common_Shares*$C$3*Exchange_Rate -> 12.036643 | D69: =(D59-$C$7+$C$8+$C$9)/Common_Shares*$C$3*Exchange_Rate -> 17.271502 | E69: =(E59-$C$7+$C$8+$C$9)/Common_Shares*$C$3*Exchange_Rate -> 25.467439 | F69: =(F59-$C$7+$C$8+$C$9)/Common_Shares*$C$3*Exchange_Rate -> 44.123516
A70: =A60 -> 25 | B70: =(B60-$C$7+$C$8+$C$9)/Common_Shares*$C$3*Exchange_Rate -> 9.6302115 | C70: =(C60-$C$7+$C$8+$C$9)/Common_Shares*$C$3*Exchange_Rate -> 12.335644 | D70: =(D60-$C$7+$C$8+$C$9)/Common_Shares*$C$3*Exchange_Rate -> 18.682795 | E70: =(E60-$C$7+$C$8+$C$9)/Common_Shares*$C$3*Exchange_Rate -> 29.661785 | F70: =(F60-$C$7+$C$8+$C$9)/Common_Shares*$C$3*Exchange_Rate -> 58.15004
A71: =A61 -> 30 | B71: =(B61-$C$7+$C$8+$C$9)/Common_Shares*$C$3*Exchange_Rate -> 9.6302115 | C71: =(C61-$C$7+$C$8+$C$9)/Common_Shares*$C$3*Exchange_Rate -> 12.565593 | D71: =(D61-$C$7+$C$8+$C$9)/Common_Shares*$C$3*Exchange_Rate -> 19.937442 | E71: =(E61-$C$7+$C$8+$C$9)/Common_Shares*$C$3*Exchange_Rate -> 33.954585 | F71: =(F61-$C$7+$C$8+$C$9)/Common_Shares*$C$3*Exchange_Rate -> 75.368641
B73: Scenarios | C73: HGR | D73: HGP | E73: Value per share | F73: Probabilities
B74: =Scenarios!B54 -> Snowball Scenario | C74: =Scenarios!C56 -> 0.12 | D74: =Scenarios!C55 -> 5 | E74: =INDEX(B$65:F$71, MATCH(D74, A$65:A$71, 0), MATCH(C74, B$64:F$64, 0)) -> 15.806945 | F74: =Scenarios!C58 -> 0.05
B75: =Scenarios!B36 -> Optimistic | C75: =Scenarios!C38 -> 0.08 | D75: =Scenarios!C37 -> 5 | E75: =INDEX(B$65:F$71, MATCH(D75, A$65:A$71, 0), MATCH(C75, B$64:F$64, 0)) -> 13.452807 | F75: =Scenarios!C40*(1-F$74-F$78) -> 0.18
B76: =Scenarios!B24 -> Base | C76: =Scenarios!C26 -> 0.05 | D76: =Scenarios!C25 -> 5 | E76: =INDEX(B$65:F$71, MATCH(D76, A$65:A$71, 0), MATCH(C76, B$64:F$64, 0)) -> 11.88965 | F76: =Scenarios!C28*(1-F$74-F$78) -> 0.54
B77: =Scenarios!B30 -> Pessimistic | C77: =Scenarios!C32 -> 0.02 | D77: =Scenarios!C31 -> 5 | E77: =INDEX(B$65:F$71, MATCH(D77, A$65:A$71, 0), MATCH(C77, B$64:F$64, 0)) -> 10.484961 | F77: =Scenarios!C34*(1-F$74-F$78) -> 0.18
B78: =Scenarios!B48 -> Devil's advocate | C78: =Scenarios!C50 -> 0 | D78: =Scenarios!C49 -> 5 | E78: =INDEX(B$65:F$71, MATCH(D78, A$65:A$71, 0), MATCH(C78, B$64:F$64, 0)) -> 9.6302115 | F78: =Scenarios!C52 -> 0.05
B80: Note of the formulas: | C80: MATCH(1%, C65:E65, 0) finds the column number for HGR = 1%.
C81: MATCH(5, B66:B69, 0) finds the row number for HGP = 5.
C82: INDEX(C66:E69, ...) retrieves the value from the specified range.

Sheet Scenarios
B2: Current Situation | H2: Warning: Do Not Remove this logic*
B3: Selection | H3: 0 | I3: =-Market_Price -> -13.11
B4: Past Years Selected | C4: 3 | E4: Tie the business story into the three levers of value: FCFE, growth and risk. | H4: 1 | I4: =IF(ROW()-3 < $C$81, $C$82, IF(ROW()-3 = $C$81, $C$82 + $C$60, "")) -> 0
H5: 2 | I5: =IF(ROW()-3 < $C$81, $C$82, IF(ROW()-3 = $C$81, $C$82 + $C$60, "")) -> 0
B6: Latest | C6: =DCF!C3 -> 1000 | E6: Prompt for fundamental Analysis | H6: 3 | I6: =IF(ROW()-3 < $C$81, $C$82, IF(ROW()-3 = $C$81, $C$82 + $C$60, "")) -> 12.001067
B7: EBIT | C7: =Normalized_FCF!G8 -> 5859134 | D7: =Reporting_currency -> CNY | E7: ="Please develop three logical "&C18&"-year scenarios (Base Case, Pessimistic Case, Optimistic Case) and two extreme "&C46&"-year scenarios (Success Scenario, Devil’s Advocate Scenario) for "&Thesis!C5&"("&Thesis!C11&"). Each scenario should include the Compound Growth Rate, the Probability Assessment, and the Business Narrative." -> Please develop three logical 5-year scenarios (Base Case, Pessimistic Case, Optimistic Case) and two extreme 5-year scenarios (Success Scenario, Devil’s Advocate Scenario) for 海底捞(6862.HK). Each scenario should include the Compound Growth Rate, the Probability Assessment, and the Business Narrative. | H7: 4 | I7: =IF(ROW()-3 < $C$81, $C$82, IF(ROW()-3 = $C$81, $C$82 + $C$60, ""))
B8: FCFE | C8: =Normalized_FCF!G19 -> 3856188.7 | D8: =Reporting_currency -> CNY | H8: 5 | I8: =IF(ROW()-3 < $C$81, $C$82, IF(ROW()-3 = $C$81, $C$82 + $C$60, ""))
B9: Normalized | C9: =Normalized_FCF!C19 -> 3593208.1 | D9: =Reporting_currency -> CNY | H9: 6 | I9: =IF(ROW()-3 < $C$81, $C$82, IF(ROW()-3 = $C$81, $C$82 + $C$60, ""))
H10: 7 | I10: =IF(ROW()-3 < $C$81, $C$82, IF(ROW()-3 = $C$81, $C$82 + $C$60, ""))
B11: YoY CAGR | H11: 8 | I11: =IF(ROW()-3 < $C$81, $C$82, IF(ROW()-3 = $C$81, $C$82 + $C$60, ""))
B12: Sales | C12: =(Normalized_FCF!G4/OFFSET(Normalized_FCF!G4, 0, $C$4))^(1/$C$4) - 1 -> #VALUE! | H12: 9 | I12: =IF(ROW()-3 < $C$81, $C$82, IF(ROW()-3 = $C$81, $C$82 + $C$60, ""))
B13: Operating EBIT | C13: =(Normalized_FCF!G8/OFFSET(Normalized_FCF!G8, 0, $C$4))^(1/$C$4) - 1 -> #VALUE! | H13: 10 | I13: =IF(ROW()-3 < $C$81, $C$82, IF(ROW()-3 = $C$81, $C$82 + $C$60, ""))
B14: FCFE | C14: =(Normalized_FCF!G19/OFFSET(Normalized_FCF!G19, 0, $C$4))^(1/$C$4) - 1 -> #VALUE! | H14: *It calculates Annual Return
B16: General Scenarios
B17: Assumption | E17: Guidance Note
B18: High Growth Period (HGP) | C18: 5 | E18: Fundamental analysis and market signal analysis should be combined, with fundamental analysis given priority and market signal analysis serving as a supplement. Market signal analysis predicts a company's future trend, while fundamental analysis interprets the trend and identifies relevant fundamental factors and possibilities.
B20: Reference
B21: Market Price | C21: =Market_Price -> 13.11 | D21: =Market_currency -> HKD
B22: No Growth Value per share | C22: =IF(valuation_method="DCF",DCF!C12,#REF!) -> 9.6302115 | D22: =Market_currency -> HKD
B24: Base | E24: Business Story
B25: High Growth Period (HGP) | C25: =C18 -> 5
B26: High Growth Rate (HGR) | C26: 0.05
B27: Value per share | C27: =IF(valuation_method="DCF",DCF!E76,#REF!) -> 11.88965 | D27: =Market_currency -> HKD
B28: Probabilities | C28: 0.6
B30: Pessimistic | E30: Business Story
B31: High Growth Period (HGP) | C31: =C18 -> 5
B32: High Growth Rate (HGR) | C32: 0.02
B33: Value per share | C33: =IF(valuation_method="DCF",DCF!E77,#REF!) -> 10.484961 | D33: =Market_currency -> HKD
B34: Probabilities | C34: 0.2
B36: Optimistic | E36: Business Story
B37: High Growth Period (HGP) | C37: =C18 -> 5
B38: High Growth Rate (HGR) | C38: 0.08
B39: Value per share | C39: =IF(valuation_method="DCF",DCF!E75,#REF!) -> 13.452807 | D39: =Market_currency -> HKD
B40: Probabilities | C40: =1-C28-C34 -> 0.2
B42: Expected Value = | C42: =C27*C28+C33*C34+C39*C40 -> 11.921344 | D42: =Market_currency -> HKD
B44: Extreme Scenarios
B45: Assumption
B46: High Growth Period (HGP) | C46: =C18 -> 5
B48: Devil's advocate | E48: Business Story
B49: High Growth Period (HGP) | C49: =C46 -> 5
B50: High Growth Rate (HGR) | C50: 0
B51: Value per share | C51: =IF(valuation_method="DCF",DCF!E78,#REF!) -> 9.6302115 | D51: =Market_currency -> HKD
B52: Probabilities | C52: 0.05
B54: Snowball Scenario | E54: Business Story
B55: High Growth Period (HGP) | C55: =C46 -> 5
B56: High Growth Rate (HGR) | C56: 0.12
B57: Value per share | C57: =IF(valuation_method="DCF",DCF!E74,#REF!) -> 15.806945 | D57: =Market_currency -> HKD
B58: Probabilities | C58: 0.05
B60: Expected Value = | C60: =C51*C52+C57*C58+C42*(1-C52-C58) -> 12.001067 | D60: =Market_currency -> HKD | E60: is assumed to be materialized in | F60: =Thesis!E25 -> 3
B62: Extreme Scenarios
E63: Note on Manual Adjustments
B64: Contribution Margin_II | C64: =DCF!F6 -> 0.39398348 | E64: Try obtain this number by reverse engineering.
B65: DCF Type | C65: =IF(DCF!I4="II","2","1")&"-stage DCF" -> 1-stage DCF
B67: Growth Classification
B68: Equity Value Driving Factors | E68: Note on Manual Adjustments
B69: High Growth Period (HGP) | C69: =C18 -> 5 | E69: Use general Scenarios' HGP assumption
B70: High Growth Rate (HGR) | C70: 0.052329465 | E70: Use Excel Goal Seek to find the HGR
B71: Equity Value per share | C71: =IF(valuation_method="DCF",DCF!C18,#REF!) -> 12.005184 | D71: =Market_currency -> HKD | E71: Set to Expected Equity Value
B73: Type of Company | E73: Note on the logic
B74: Negative Growth | C74: =IF(C60<C22,"Y","N") -> N
B75: Low Growth | C75: =IF(C74="Y","N",IF(C70>8%,"N","Y")) -> Y | E75: >8% is Categorized as High Growth
B76: High Growth | C76: =IF(C70>8%,"Y","N") -> N
B77: Asset Play | C77: =IF(F77>50%,"Y","N") -> N | E77: The Non-FCF Value is of the Expected Value, at | F77: =BS!D89/C60 -> 0.020098533
B79: Margin of Safety (MOS)
B80: Inputs
B81: Expected Holding Period | C81: =F60 -> 3
B82: After-tax Dividend per share | C82: =Normalized_FCF!C88*(1-dividend_tax_rate) -> 0 | D82: =Market_currency -> HKD
B84: Target Price Output
B85: @Target Annual Return | C85: =Thesis!E29 -> 0.35
B86: PV(Dividends) | C86: =PV(C85, C81, -C82, 0) -> 0
B87: PV(Equity Value) | C87: =C60/(1+C85)^C81 -> 4.8777391
B88: Buy Below | C88: =C86+C87 -> 4.8777391 | D88: =Market_currency -> HKD | E88: at a MOS of | F88: =(1-C88/C60) -> 0.59355789
B90: Current Return Output
B91: @Market Price | C91: =Market_Price -> 13.11 | D91: =Market_currency -> HKD
B92: Annual Return | C92: =IRR(OFFSET($I$3, 0, 0, $C$81 + 1, 1)) -> -0.029030191
B94: Entry Price Output
B95: @ Entry Yield | C95: =Thesis!E30 -> 0.25
B96: PV(Dividends) | C96: =PV(C95, C81, -C82, 0) -> 0
B97: PV(Equity Value) | C97: =C60/(1+C95)^C81 -> 6.1445465
B98: Buy Below | C98: =C96+C97 -> 6.1445465 | D98: =Market_currency -> HKD | E98: at a MOS of | F98: =(1-C98/C60) -> 0.488
B100: Sell Price Output
B101: @Selling Yield | C101: =Thesis!E24 -> 0.075
B102: PV(Dividends) | C102: =PV(C101, C81, -C82, 0) -> 0
B103: PV(Equity Value) | C103: =C60/(1+C101)^C81 -> 9.660386
B104: Sell Above | C104: =C102+C103 -> 9.660386 | D104: HKD | E104: at a MOS of | F104: =(1-C104/C60) -> 0.19503943
B106: Exit Price Output
B107: @Benchmark Yield | C107: =Thesis!E31 -> 0.1174
B108: PV(Dividends) | C108: =PV(C107, C81, -C82, 0) -> 0
B109: PV(Equity Value) | C109: =C60/(1+C107)^C81 -> 8.6018897
B110: Sell Above | C110: =C108+C109 -> 8.6018897 | D110: HKD | E110: at a MOS of | F110: =(1-C110/C71) -> 0.28348539
E112: Inputs Legend
E113: Font Color | F113: Fact or Verified Data
E114: Font Color | F114: Subjective Driving Factors
E115: Font Color | F115: Subjective Non-Driving Factors

Sheet Breakdown
B2: Divisional Analysis (Optional)

Sheet 投资主题
B1: 模型最后更新日期: | C1: =Thesis!C1 -> 45917 | D1: =Thesis!D1 -> INT | E1: Selected: | F1: =Thesis!F1 -> N
A2: 执行摘要
B4: 公司信息
B5: 公司名称： | C5: =Thesis!C5 -> 海底捞
B6: 股份数量： | C6: =Common_Shares -> 5574000000
B7: 报告间隔： | C7: =Thesis!C7 -> 6
B8: 下次更新日期： | C8: =EOMONTH(EDATE(BS!C1,C7+2),0) -> 46265
B10: 上市信息
B11: 股票代码： | C11: =Thesis!C11 -> 6862.HK
B12: 市场价格： | C12: =Market_Price -> 13.11
B13: 市价货币： | C13: =Market_currency -> HKD
B14: 市值： | C14: =投资主题!C12*Common_Shares/1000000 -> 73075.14 | D14: =IF(D11="","",投资主题!D12*Common_Shares/1000000)
B15: 外汇符号： | C15: =IF(C25=C13,C13,C25&"/"&C13) -> CNY/HKD | D15: =IF(D11="","",IF(C25=D13,D13,C25&"/"&D13))
B16: 汇率： | C16: =Exchange_Rate -> 1.0923594
B18: 指导说明：该模型使用结构化的投资流程来评估公司，确定其内在价值和目标价格。它关注可持续的自由现金流（FCF）能力，调整财务结构，纳入增长情景，并根据得出的内在价值计算预期回报。
B20: 估值概述
B21: 增长分类: | C21: =IF(Scenarios!C74="Y",Scenarios!B74,"")&IF(Scenarios!C75="Y",Scenarios!B75,"")&IF(Scenarios!C76="Y",Scenarios!B76,"")&" "&IF(Scenarios!C77="Y",Scenarios!B77,"") -> Low Growth | D21: 估值方法 | E21: =valuation_method -> DCF
B22: 对比板块: | C22: =Thesis!C22 -> CNS_01 | D22: =IF(valuation_method="DDM","终值贴现率","") | E22: =Thesis!E22 -> 0
B23: 商业模式风险溢价: | C23: =Thesis!C23 -> N
B24: 管理风险溢价: | C24: =Thesis!C24 -> N
B25: 报告货币: | C25: =Reporting_currency -> CNY | D25: =IF(D11="","",Market_currency&"/"&D13&":") | E25: =IF(D11="","",1/Exchange_Rate*D16)
B26: ="预期股权价值 ("&C13&") :" -> 预期股权价值 (HKD) : | C26: =C132 -> 12.001067 | D26: 市场隐含年回报率: | E26: =Scenarios!C92 -> -0.029030191
B28: 估值输出 | C28: =C145&" ("&Market_currency&")" -> 6862.HK (HKD) | D28: =IF(D11="","",D145&" ("&D13&")") | E28: 持有期 | F28: =Thesis!E25 -> 3
B29: 目标价格 | C29: =C149 -> 4.8777391 | D29: =D149 | E29: 目标回报率 | F29: =Thesis!E29 -> 0.35
B30: 入场价格 | C30: =C157 -> 6.1445465 | D30: =D157 | E30: 入场收益率 | F30: =Thesis!E30 -> 0.25
B31: 卖出价格 | C31: =C165 -> 9.660386 | D31: =D165 | E31: 基础Equity Cost | F31: =Thesis!E24 -> 0.075
B32: 退出价格 | C32: =C173 -> 8.6018897 | D32: =D173 | E32: 基准收益率 | F32: =Thesis!E31 -> 0.1174
A34: 步骤1：确定公司可持续盈利能力（计算标准化FCFE）
B36: 目标：量化业务持续生成的潜在自由现金流（FCFE），去除临时波动或会计选择的影响。
B37: FCFE = (Normalized Operating EBIT + Depreciation & Amortization – Capital Expenditures) + Stable Non-Operating EBIT + Net Interest Income – Taxes – NCI’s Share of Profits – Working Capital Investment
B39: 关键组成部分 | C39: =scaling_factor -> 1000
B40: • Normalized Operating EBIT：核心业务运营的税前息前利润，调整以剔除一次性或非经常性项目，形成可持续盈利基础。
B41: Normalized Operating EBIT = | C41: =Normalized_FCF!C8 -> 4831254 | D41: =Reporting_currency -> CNY
B43: • Depreciation & Amortization (D&A): 非现金费用，加入以反映运营产生的现金。 • Capital Expenditures (Capex): 维持或扩展运营资产所需的现金流出。
B44: D&A = | C44: =Normalized_FCF!C9 -> 0 | D44: =Reporting_currency -> CNY
B45: Capex = | C45: =Normalized_FCF!C10 -> 0 | D45: =Reporting_currency -> CNY
B47: • Stable Non-Operating EBIT: 来自非核心资产的持续收益，如固定收益投资、支付股息的股票或租赁物业。
B48: Stable Non-Operating EBIT = | C48: =Normalized_FCF!C11 -> 51775 | D48: =Reporting_currency -> CNY
B50: • Net Interest Income: 利息收入减去利息支出
B51: Operating Interest Income = | C51: =Normalized_FCF!C46 -> 62121.272 | D51: =Reporting_currency -> CNY
B52: Interest Expense = | C52: =Normalized_FCF!C45 -> -154206.15 | D52: =Reporting_currency -> CNY
B53: Net Interest Income = | C53: =Normalized_FCF!C12 -> -92084.878 | D53: =Reporting_currency -> CNY
B55: • NCI’s Share of Profits: NCI代表子公司中母公司未拥有的股权部分。
B56: Est. NCI’s Share of Profits = | C56: =Normalized_FCF!C15 -> 0 | D56: =Reporting_currency -> CNY
B58: • Taxes: Tax = (Normalized Operating EBIT + Stable Non-Operating EBIT + Interest Income – Interest Expense) × Tax Rate
B59: Taxes = | C59: =Normalized_FCF!C14 -> -1197736 | D59: =Reporting_currency -> CNY
B61: • Working Capital Investment (WCInv): WCInv仅在显著扭曲FCFE时纳入。
B62: WCInv = | C62: =Normalized_FCF!C17 -> 0 | D62: =Reporting_currency -> CNY
B64: 关于净借款的说明：理论上，本金偿还通过净借款核算。然而，该模型旨在避免明确预测债务发行或偿还。相反，本金偿还通过有息债务在股权价值调整中反映。
B65: 洞察：这一步骤通过纳入运营和稳定的非运营来源，同时考虑税金和再投资需求，确保现金流的全面衡量。
B67: 最新FCFE = | C67: =Normalized_FCF!G19 -> 3856188.7 | D67: =Reporting_currency -> CNY
B68: Normalized FCFE = | C68: =Normalized_FCF!C19 -> 3593208.1 | D68: =Reporting_currency -> CNY
B69: Normalized FCFE/Market Cap = | C69: =Normalized_FCF!C124 -> 0.053712858
B70: After tax Dividend/Market Cap = | C70: =Normalized_FCF!C92 -> 0 | E70: 派息比率: | F70: =Normalized_FCF!C90 -> 0
B72: 杜邦分析 | C72: Normalized | D72: 最新
B73: ROE = | C73: =Normalized_FCF!C119 -> 0.45989402 | D73: =Normalized_FCF!G119 -> 0.55558185
B74: =Normalized_FCF!B116 -> Pre-tax Profit/Sales | C74: =Normalized_FCF!C116 -> 0.11378829 | D74: =Normalized_FCF!G116 -> 0.13537163
B75: =Normalized_FCF!B117 -> Sales/Total Assets | C75: =Normalized_FCF!C117 -> 1.8481868 | D75: =Normalized_FCF!G117 -> 1.8767484
B76: =Normalized_FCF!B118 -> Total Assets/Equity | C76: =Normalized_FCF!C118 -> 2.1868266 | D76: =Normalized_FCF!G118 -> 2.1868266
A78: 步骤2：计算无增长基线（计算稳定收入价值）
B80: 目标：确定内在价值，假设当前的标准化FCFE保持不变且无增长，提供保守的基线。
B81: Stable Income Value = Normalized FCFE / (Cost of Equity – Terminal Growth Rate)
B83: 关键组成部分
B84: Base Cost of Equity | C84: =F31 -> 0.075
B85: Risk Premium | C85: =IF(C23="Y",1%,0)+IF(C24="Y",1%,0) -> 0
B86: Cost of Equity = | C86: =F31+C85 -> 0.075
B88: 说明：
B89: Cost of Equity: 反映公司的风险概况，代表投资者为承担拥有此类业务一般风险所需的最低回报，而目标年回报率作为投资者要求的回报率。
B90: Terminal Growth Rate: 将g设为0%是一个保守假设，仅基于公司当前表现的盈利能力估值，不依赖潜在乐观的未来增长预测。
B92: Terminal Growth Rate (g) = | C92: 0
B93: No Growth SIV Per Share = | C93: =DCF!C6*scaling_factor*Exchange_Rate/Common_Shares -> 9.3890076 | D93: =Market_currency -> HKD
A95: 步骤3：调整财务结构（计算无增长股权价值）
B97: 目标：通过纳入公司的资产负债表结构，细化稳定收入价值（SIV）。
B98: Equity Value = Stable Income Value – Total Interest-Bearing Debt + Non-Operating Cash + Other Non-Operating Assets
B100: 关键组成部分
B101: 关于债务的说明：总有息债务包括本金偿还。理想情况下，应根据偿还时间表贴现。但为简单和保守起见，该模型使用总有息债务的账面价值。
B102: Total Interest-Bearing Debt = | C102: =DCF!C7 -> 6168246 | D102: =Reporting_currency -> CNY
B103: Total Interest-Bearing Debt per share = | C103: =C102*scaling_factor*Exchange_Rate/Common_Shares -> 1.2088162 | D103: =Market_currency -> HKD
B104: Debt to Equity Ratio = | C104: =IF(BS!G31/BS!G27>300%,"nm",BS!G31/BS!G27) -> 0.59210448
B105: Debt to EBIT Ratio = | C105: =IF(BS!C50>30,"nm",BS!C50) -> 1.2767381
B107: • Non-Operating Cash: 运营不需要的超额现金
B108: Total Cash = | C108: =BS!C66 -> 7848668 | D108: =Reporting_currency -> CNY
B109: Est. Non-Operating Cash = | C109: =DCF!C8 -> 4742604.4 | D109: =Reporting_currency -> CNY
B110: Est. Non-Operating Cash per share = | C110: =C109*scaling_factor*Exchange_Rate/Common_Shares -> 0.92942743 | D110: =Market_currency -> HKD
B112: • Other Non-Operating Assets: 不贡献FCFE的资产（如非收益性投资或物业）
B113: Other Non-Operating Assets = | C113: =DCF!C9 -> 2656436.4 | D113: =Reporting_currency -> CNY
B114: Other Non-Operating Assets per share = | C114: =C113*scaling_factor*Exchange_Rate/Common_Shares -> 0.52059262 | D114: =Market_currency -> HKD
B116: 洞察：无增长股权价值每股代表公司在考虑未来增长潜力前，基于当前可持续运营和净财务状况的内在价值估计，作为基本锚定的估值基线。
B118: 无增长股权价值每股 = | C118: =IF(valuation_method="DCF",DCF!C12,#REF!) -> 9.6302115 | D118: =Market_currency -> HKD
B119: 估计(净资产)可变现价值 | C119: =BS!D47 -> 0.052355704 | D119: =Market_currency -> HKD
A121: 步骤4：纳入未来潜力（情景分析）
B123: 目标：通过建模合理的FCFE/股息、高增长期（HGP）和高增长率（HGR）情景，并按概率加权，估计内在价值。
B125: 情景 | C125: HGR | D125: HGP | E125: 每股EV | F125: 概率
B126: =DCF!B74 -> Snowball Scenario | C126: =DCF!C74 -> 0.12 | D126: =DCF!D74 -> 5 | E126: =ROUND(IF(valuation_method="DCF",DCF!E74,#REF!),2)&" "&Market_currency -> 15.81 HKD | F126: =DCF!F74 -> 0.05
B127: =DCF!B75 -> Optimistic | C127: =DCF!C75 -> 0.08 | D127: =DCF!D75 -> 5 | E127: =ROUND(IF(valuation_method="DCF",DCF!E75,#REF!),2)&" "&Market_currency -> 13.45 HKD | F127: =DCF!F75 -> 0.18
B128: =DCF!B76 -> Base | C128: =DCF!C76 -> 0.05 | D128: =DCF!D76 -> 5 | E128: =ROUND(IF(valuation_method="DCF",DCF!E76,#REF!),2)&" "&Market_currency -> 11.89 HKD | F128: =DCF!F76 -> 0.54
B129: =DCF!B77 -> Pessimistic | C129: =DCF!C77 -> 0.02 | D129: =DCF!D77 -> 5 | E129: =ROUND(IF(valuation_method="DCF",DCF!E77,#REF!),2)&" "&Market_currency -> 10.48 HKD | F129: =DCF!F77 -> 0.18
B130: =DCF!B78 -> Devil's advocate | C130: =DCF!C78 -> 0 | D130: =DCF!D78 -> 5 | E130: =ROUND(IF(valuation_method="DCF",DCF!E78,#REF!),2)&" "&Market_currency -> 9.63 HKD | F130: =DCF!F78 -> 0.05
B132: Expected Equity Value = | C132: =Scenarios!C60 -> 12.001067 | D132: =Market_currency -> HKD
B134: 洞察：分析市场大幅波动作为市场感知结果范围的指标，包括定义“雪球”或“魔鬼代言人”等情景边界的极端情况。情景分析使用基本推理评估这些情景的可能性。
...
