Workbook
Name Common_Shares: Thesis!$C$6
Name dividend_tax_rate: Normalized_FCF!$C$93
Name Equity_Cost: Thesis!$C$86
Name Exchange_Rate: Thesis!$C$16
Name Market_currency: Thesis!$C$13
Name Market_Price: Thesis!$C$12
Name Reporting_currency: Thesis!$C$25
Name scaling_factor: Data!$C$3
Name Terminal_Growth: Thesis!$C$92
Name valuation_method: Thesis!$E$21

Sheet Thesis
B1: Model last updated: | C1: 45874 | D1: INT | E1: Selected: | F1: N
A2: Executive Summary
B4: Company Information
B5: Company Name: | C5: lululemon athletica inc.
B6: Number of Shares: | C6: =114729430+5115961 -> 119845391
B7: Report Interval: | C7: 6
B8: Update Required After: | C8: =EOMONTH(EDATE(BS!C1,C7+2),0) -> 46053
B10: Listing Information
B11: Symbol: | C11: LULU
B12: Market Price: | C12: 196.45
B13: Market Currency: | C13: USD
B14: Market Capitalization: | C14: =Thesis!C12*Common_Shares/1000000 -> 23543.627 | D14: =IF(D11="","",Thesis!D12*Common_Shares/1000000)
B15: Forex Symbol: | C15: =IF(C25=C13,C13,C25&"/"&C13) -> USD | D15: =IF(D11="","",IF(C25=D13,D13,C25&"/"&D13))
B16: Exchange Rate: | C16: 1
B18: Guidance Note: This model evaluates the company using a structured investment process to determine its intrinsic value and target prices. It focuses on sustainable FCF capacity, adjusts for financial structure, incorporates growth scenarios, and calculates expected returns based on the derived intrinsic value.
B20: Valuation Overview
B21: Growth Classification: | C21: =IF(Scenarios!C69="Y",Scenarios!B69,"")&IF(Scenarios!C70="Y",Scenarios!B70,"")&IF(Scenarios!C71="Y",Scenarios!B71,"")&" "&IF(Scenarios!C72="Y",Scenarios!B72,"") -> Low Growth | D21: Valuation Method | E21: DCF
B22: Comp_Sector: | C22: CNS_02 | D22: =IF(valuation_method="DDM","Terminal Value Discount Rate","")
B23: Business Model Risk Premium: | C23: N
B24: Management Risk Premium: | C24: N
B25: Reporting Currency: | C25: USD | D25: =IF(D11="","",Market_currency&"/"&D13&":") | E25: =IF(D11="","",1/Exchange_Rate*D16)
B26: ="Expected Equity Value ("&C13&") :" -> Expected Equity Value (USD) : | C26: =C132 -> 177.33733 | D26: Market Implied Annual Return: | E26: =Scenarios!C87 -> -0.033542605
B28: Valuation Outputs | C28: =C145&" ("&Market_currency&")" -> LULU (USD) | D28: =IF(D11="","",D145&" ("&D13&")") | E28: Holding Period | F28: 3
B29: Target Price | C29: =C149 -> 72.077359 | D29: =D149 | E29: Target return | F29: 0.35
B30: Entry Price | C30: =C157 -> 90.796715 | D30: =D157 | E30: Entry yield | F30: 0.25
B31: Sell Price | C31: =C165 -> 142.74956 | D31: =D165 | E31: Base equity cost | F31: 0.075
B32: Exit Price | C32: =C173 -> 127.10838 | D32: =D173 | E32: Benchmark yield | F32: 0.1174
A34: Step 1: Establishing the Company’s Sustainable Earning Power (Calculating Normalized FCFE)
B36: Goal: To quantify the underlying FCFE the business consistently generates, stripping away temporary fluctuations or accounting choices.
B37: FCFE = (Normalized Operating EBIT + Depreciation & Amortization – Capital Expenditures) + Stable Non-Operating EBIT + Net Interest Income – Taxes – NCI’s Share of Profits – Working Capital Investment
B39: Key Components | C39: =scaling_factor -> 1000
B40: • Normalized Operating EBIT: Earnings before interest and taxes from core business operations, adjusted to remove one-time or irregular items for a sustainable earnings base.
B41: Normalized Operating EBIT = | C41: =Normalized_FCF!C8 -> 2062510.7 | D41: =Reporting_currency -> USD
B43: • Depreciation & Amortization (D&A): Non-cash expenses added back to reflect cash generated from operations. • Capital Expenditures (Capex): Cash outflows required to maintain or expand operational assets
B44: D&A = | C44: =Normalized_FCF!C9 -> 0 | D44: =Reporting_currency -> USD
B45: Capex = | C45: =Normalized_FCF!C10 -> 0 | D45: =Reporting_currency -> USD
B47: • Stable Non-Operating EBIT: Consistent earnings from non-core assets, such as fixed-income investments, dividend-paying stocks, or rental properties.
B48: Stable Non-Operating EBIT = | C48: =Normalized_FCF!C11 -> 0 | D48: =Reporting_currency -> USD
B50: • Net Interest Income: Interest income minus interest expense
B51: Operating Interest Income = | C51: =Normalized_FCF!C48 -> 0 | D51: =Reporting_currency -> USD
B52: Interest Expense = | C52: =Normalized_FCF!C47 -> 0 | D52: =Reporting_currency -> USD
B53: Net Interest Income = | C53: =Normalized_FCF!C12 -> 0 | D53: =Reporting_currency -> USD
B55: • NCI’s Share of Profits: NCI represents the portion of a subsidiary’s equity not owned by the parent company.
B56: Est. NCI’s Share of Profits = | C56: =Normalized_FCF!C15 -> 0 | D56: =Reporting_currency -> USD
B58: • Taxes: Tax = (Normalized Operating EBIT + Stable Non-Operating EBIT + Interest Income – Interest Expense) × Tax Rate
B59: Taxes = | C59: =Normalized_FCF!C14 -> -531509.02 | D59: =Reporting_currency -> USD
B61: • Working Capital Investment (WCInv): WCInv is only included if it materially distorts FCFE.
B62: WCInv = | C62: =Normalized_FCF!C17 -> 0 | D62: =Reporting_currency -> USD
B64: Note on Net Borrowing: In theory, principal repayments are accounted for through Net Borrowing. However, this model aims to avoid explicitly forecasting debt issuance or repayments. Instead, principal repayments are reflected in the Equity Value adjustment through interest-bearing debt.
B65: Insight: This step ensures a comprehensive measure of cash flow by incorporating both operating and stable non-operating sources while accounting for taxes and reinvestment needs.
B67: Latest FCFE = | C67: =Normalized_FCF!G19 -> 1746971 | D67: =Reporting_currency -> USD
B68: Normalized FCFE = | C68: =Normalized_FCF!C19 -> 1531001.7 | D68: =Reporting_currency -> USD
B69: Normalized FCFE/Market Cap = | C69: =Normalized_FCF!C126 -> 0.065028287
B70: After tax Dividend/Market Cap = | C70: =Normalized_FCF!C94 -> 0 | E70: Payout Ratio: | F70: =Normalized_FCF!C92 -> 0
B72: DuPont Analysis | C72: Normalized | D72: Latest
B73: ROE = | C73: =Normalized_FCF!C121 -> 0.48081993 | D73: =Normalized_FCF!G121 -> 0.5847747
B74: =Normalized_FCF!B118 -> Pre-tax Profit/Sales | C74: =Normalized_FCF!C118 -> 0.20413416 | D74: =Normalized_FCF!G118 -> 0.23690991
B75: =Normalized_FCF!B119 -> Sales/Total Assets | C75: =Normalized_FCF!C119 -> 1.3597528 | D75: =Normalized_FCF!G119 -> 1.4249465
B76: =Normalized_FCF!B120 -> Total Assets/Equity | C76: =Normalized_FCF!C120 -> 1.7322349 | D76: =Normalized_FCF!G120 -> 1.7322349
A78: Step 2: Calculating the No-Growth Baseline (Calculating Stable Income Value)
B80: Goal: Determine the intrinsic value assuming the current Normalized FCFE remains constant with no growth, providing a conservative baseline.
B81: Stable Income Value = Normalized FCFE / (Cost of Equity – Terminal Growth Rate)
B83: Key Components
B84: Base Cost of Equity | C84: =F31 -> 0.075
B85: Risk Premium | C85: =IF(C23="Y",1%,0)+IF(C24="Y",1%,0) -> 0
B86: Cost of Equity = | C86: =F31+C85 -> 0.075
B88: Note:
B89: Cost of Equity: Cost of Equity reflects the company’s risk profile and represents the minimum return the investor requires for taking on the general risk of owning this type of business, while the target annual return serves as the investor’s hurdle rate.
B90: Terminal Growth Rate: Setting g=0% is a conservative assumption, valuing the company based only on its current demonstrated earning power without relying on potentially optimistic future growth projections.
B92: Terminal Growth Rate (g) = | C92: 0
B93: No Growth SIV Per Share = | C93: =DCF!C6*scaling_factor*Exchange_Rate/Common_Shares -> 170.33076 | D93: =Market_currency -> USD
A95: Step 3: Adjusting for Financial Structure (Calculating No Growth Equity Value)
B97: Goal: To refine the Stable Income Value (SIV) by incorporating the company’s balance sheet structure.
B98: Equity Value = Stable Income Value – Total Interest-Bearing Debt + Non-Operating Cash + Other Non-Operating Assets
B100: Key Components
B101: Note on debt: The total interest-bearing debt captures the principal repayments. Ideally, this amount should be discounted based on the repayment schedule. However, for simplicity and conservatism, this model uses the book value of the total interest-bearing debt.
B102: Total Interest-Bearing Debt = | C102: =DCF!C7 -> 1706782 | D102: =Reporting_currency -> USD
B103: Total Interest-Bearing Debt per share = | C103: =C102*scaling_factor*Exchange_Rate/Common_Shares -> 14.241532 | D103: =Market_currency -> USD
B104: Debt to Equity Ratio = | C104: =IF(BS!G31/BS!G27>300%,"nm",BS!G31/BS!G27) -> 0.39789116
B105: Debt to EBIT Ratio = | C105: =IF(BS!C50>30,"nm",BS!C50) -> 0.82752635
B107: • Non-Operating Cash: Excess cash not required for operations
B108: Total Cash = | C108: =BS!C66 -> 1325272 | D108: =Reporting_currency -> USD
B109: Est. Non-Operating Cash = | C109: =DCF!C8 -> 655172.73 | D109: =Reporting_currency -> USD
B110: Est. Non-Operating Cash per share = | C110: =C109*scaling_factor*Exchange_Rate/Common_Shares -> 5.4668162 | D110: =Market_currency -> USD
B112: • Other Non-Operating Assets: Assets not contributing to FCFE (e.g., non-income-generating investments or properties)
B113: Other Non-Operating Assets = | C113: =DCF!C9 -> 0 | D113: =Reporting_currency -> USD
B114: Other Non-Operating Assets per share = | C114: =C113*scaling_factor*Exchange_Rate/Common_Shares -> 0 | D114: =Market_currency -> USD
B116: Insight: The No Growth Equity Value per share represents an estimate of the company’s intrinsic worth based on its current sustainable operations and net financial position, before factoring in any future growth potential. It serves as a fundamentally anchored valuation baseline.
B118: No Growth Equity Value per share = | C118: =IF(valuation_method="DCF",DCF!C12,DDM!C7) -> 161.55604 | D118: =Market_currency -> USD
B119: Est. (Net Asset) Realizable Value | C119: =BS!D47 -> -4.6442003 | D119: =Market_currency -> USD
A121: Step 4: Incorporating Future Potential (Scenario Analysis)
B123: Goal: Estimate intrinsic value by modeling plausible FCFE/Dividend, high growth periods (HGP), and high growth rates (HGR) scenarios, weighted by probability.
B125: Scenarios | C125: HGR | D125: HGP | E125: EV per share | F125: Probabilities
B126: =DCF!B74 -> Snowball Scenario | C126: =DCF!C74 -> 0.1 | D126: =DCF!D74 -> 10 | E126: =ROUND(IF(valuation_method="DCF",DCF!E74,DDM!E69),2)&" "&Market_currency -> 227.42 USD | F126: =DCF!F74 -> 0.05
B127: =DCF!B75 -> Optimistic | C127: =DCF!C75 -> 0.08 | D127: =DCF!D75 -> 5 | E127: =ROUND(IF(valuation_method="DCF",DCF!E75,DDM!E70),2)&" "&Market_currency -> 184.13 USD | F127: =DCF!F75 -> 0.18
B128: =DCF!B76 -> Base | C128: =DCF!C76 -> 0.05 | D128: =DCF!D76 -> 5 | E128: =ROUND(IF(valuation_method="DCF",DCF!E76,DDM!E71),2)&" "&Market_currency -> 175.36 USD | F128: =DCF!F76 -> 0.54
B129: =DCF!B77 -> Pessimistic | C129: =DCF!C77 -> 0.02 | D129: =DCF!D77 -> 5 | E129: =ROUND(IF(valuation_method="DCF",DCF!E77,DDM!E72),2)&" "&Market_currency -> 166.96 USD | F129: =DCF!F77 -> 0.18
B130: =DCF!B78 -> Devil's advocate | C130: =DCF!C78 -> 0 | D130: =DCF!D78 -> 10 | E130: =ROUND(IF(valuation_method="DCF",DCF!E78,DDM!E73),2)&" "&Market_currency -> 161.56 USD | F130: =DCF!F78 -> 0.05
B132: Expected Equity Value = | C132: =Scenarios!C60 -> 177.33733 | D132: =Market_currency -> USD
B134: Insight: Significant market volatility is analyzed as an indicator of the range of market-perceived outcomes, including extremes that define boundaries for scenarios like "Snowball" or "Devil’s Advocate." Scenario Analysis then filters these using fundamental reasoning to evaluate their likelihood.
...

Sheet Data
B1: =Thesis!C25 -> USD | C1: 45688 | D1: =EOMONTH(EDATE(C1,-12),0) -> 45322 | E1: =EOMONTH(EDATE(D1,-12),0) -> 44957 | F1: =EOMONTH(EDATE(E1,-12),0) -> 44592 | G1: =EOMONTH(EDATE(F1,-12),0) -> 44227 | H1: =EOMONTH(EDATE(G1,-12),0) -> 43861 | I1: =EOMONTH(EDATE(H1,-12),0) -> 43496 | J1: =EOMONTH(EDATE(I1,-12),0) -> 43131 | K1: =EOMONTH(EDATE(J1,-12),0) -> 42766 | ... M1: =EOMONTH(EDATE(L1,-12),0) -> 42035
B2: Data (Dirty)
B3: Income Statement | C3: 1000
B4: Sales | C4: 10588126 | D4: 9619278 | E4: 8110518 | F4: 6256617 | G4: 4401879 | H4: 3979296 | I4: 3288319 | J4: 2649181 | K4: 2344392 | L4: 2060523
B5: COGS | C5: 4317315 | D5: 4009873 | E5: 3618178 | F5: 2648052 | G5: 1937888 | H5: 1755910 | I5: 1472032 | J5: 1250391 | K5: 1144775 | L5: 1063357
B6: OPEX | C6: 3762379 | D6: 3397218 | E6: 2757447 | F6: 2225034 | G6: 1609003 | H6: 1334276 | I6: 1110451 | J6: 904264 | K6: 778465 | L6: 628090
B7: Incl. Selling Expenses
B8: R&D
B9: Share of JV or associate Results
B10: Dividend or Interests from FA
B11: Investment property
B12: Interest Expense
B13: Interest Income
B14: Income Tax Paid | C14: 761461 | D14: 625545 | E14: 477771 | F14: 358547 | G14: 230437 | H14: 251797 | I14: 231449 | J14: 201336 | K14: 119348 | L14: 102448
B15: Reported Net Income | C15: 1814616 | D15: 1550190 | E15: 854800 | F15: 975322 | G15: 588913 | H15: 645596 | I15: 483801 | J15: 258662 | K15: 303381 | L15: 266047
B16: Non-controling Interests
B18: Cash Flow Statement
B19: D&A
B20: CAPX
B21: WCInv
B22: CFO | C22: 2272713 | D22: 2296164 | E22: 966463 | F22: 1389108 | G22: 803336 | H22: 669316 | I22: 742779 | J22: 489337 | K22: 385119 | L22: 298740
B23: CFI | C23: -798174 | D23: -654132 | E23: -569937 | F23: -427891 | G23: -695532 | H23: -278408 | I23: -242794 | J23: -173392 | K23: -149511 | L23: -143487
B24: CFF | C24: -1652508 | D24: -548828 | E24: -467487 | F24: -844987 | G24: -80788 | H24: -177173 | I24: -590214 | J24: -97862 | K24: -25338 | L24: -273693
B25: ="Dividend per share ("&Market_currency&")" -> Dividend per share (USD)
B27: Balance Sheet | C27: Latest Asset Value
B28: ST AR | C28: =BS!C4 -> 0 | D28: 124769 | E28: 132906 | F28: 77001 | G28: 62399 | H28: 40219 | I28: 35786 | J28: 19173 | K28: 9200 | L28: 13108
B29: ST Inventory | C29: =BS!C6 -> 1652091 | D29: 1323602 | E29: 1447367 | F29: 966481 | G29: 647230 | H29: 518513 | I29: 404842 | J29: 329562 | K29: 298432 | L29: 284009
B30: Total Liabilities | C30: =BS!C33+BS!C42 -> 3140973 | D30: 2859860 | E30: 2458239 | F30: 2202432 | G30: 1626649 | H30: 1329136 | I30: 638736 | J30: 401523 | K30: 297568 | L30: 286595
B31: Total Equity | C31: =BS!G27 -> 4289570 | D31: 4232081 | E31: 3148799 | F31: 2740046 | G31: 2558566 | H31: 1952218 | I31: 1445975 | J31: 1596960 | K31: 1359973 | L31: 1027482
B32: Non-common Interest | C32: =BS!G28 -> 0
B34: IS & CF Statements (Clean)
B35: Income Statement
B36: Sales | C36: =IF(C$4="","",C4) -> 10588126 | D36: =IF(D$4="","",D4) -> 9619278 | E36: =IF(E$4="","",E4) -> 8110518 | F36: =IF(F$4="","",F4) -> 6256617 | G36: =IF(G$4="","",G4) -> 4401879 | H36: =IF(H$4="","",H4) -> 3979296 | I36: =IF(I$4="","",I4) -> 3288319 | J36: =IF(J$4="","",J4) -> 2649181 | ... M36: =IF(M$4="","",M4)
B37: COGS | C37: =IF(C$4="","",-C5) -> -4317315 | D37: =IF(D$4="","",-D5) -> -4009873 | E37: =IF(E$4="","",-E5) -> -3618178 | F37: =IF(F$4="","",-F5) -> -2648052 | G37: =IF(G$4="","",-G5) -> -1937888 | H37: =IF(H$4="","",-H5) -> -1755910 | I37: =IF(I$4="","",-I5) -> -1472032 | J37: =IF(J$4="","",-J5) -> -1250391 | ... M37: =IF(M$4="","",-M5)
B38: Gross Margin | C38: =IF(C36="","",C36+C37) -> 6270811 | D38: =IF(D36="","",D36+D37) -> 5609405 | E38: =IF(E36="","",E36+E37) -> 4492340 | F38: =IF(F36="","",F36+F37) -> 3608565 | G38: =IF(G36="","",G36+G37) -> 2463991 | H38: =IF(H36="","",H36+H37) -> 2223386 | I38: =IF(I36="","",I36+I37) -> 1816287 | J38: =IF(J36="","",J36+J37) -> 1398790 | ... M38: =IF(M36="","",M36+M37)
B39: OPEX | C39: =IF(C$4="","",-C6) -> -3762379 | D39: =IF(D$4="","",-D6) -> -3397218 | E39: =IF(E$4="","",-E6) -> -2757447 | F39: =IF(F$4="","",-F6) -> -2225034 | G39: =IF(G$4="","",-G6) -> -1609003 | H39: =IF(H$4="","",-H6) -> -1334276 | I39: =IF(I$4="","",-I6) -> -1110451 | J39: =IF(J$4="","",-J6) -> -904264 | ... M39: =IF(M$4="","",-M6)
B40: Incl. Selling Expenses | C40: =IF(C$4="","",-C7) -> 0 | D40: =IF(D$4="","",-D7) -> 0 | E40: =IF(E$4="","",-E7) -> 0 | F40: =IF(F$4="","",-F7) -> 0 | G40: =IF(G$4="","",-G7) -> 0 | H40: =IF(H$4="","",-H7) -> 0 | I40: =IF(I$4="","",-I7) -> 0 | J40: =IF(J$4="","",-J7) -> 0 | ... M40: =IF(M$4="","",-M7)
B41: Incl. Other Opex | C41: =IF(C$4="","",C39-C40) -> -3762379 | D41: =IF(D$4="","",D39-D40) -> -3397218 | E41: =IF(E$4="","",E39-E40) -> -2757447 | F41: =IF(F$4="","",F39-F40) -> -2225034 | G41: =IF(G$4="","",G39-G40) -> -1609003 | H41: =IF(H$4="","",H39-H40) -> -1334276 | I41: =IF(I$4="","",I39-I40) -> -1110451 | J41: =IF(J$4="","",J39-J40) -> -904264 | ... M41: =IF(M$4="","",M39-M40)
B42: R&D | C42: =IF(C$4="","",-C8) -> 0 | D42: =IF(D$4="","",-D8) -> 0 | E42: =IF(E$4="","",-E8) -> 0 | F42: =IF(F$4="","",-F8) -> 0 | G42: =IF(G$4="","",-G8) -> 0 | H42: =IF(H$4="","",-H8) -> 0 | I42: =IF(I$4="","",-I8) -> 0 | J42: =IF(J$4="","",-J8) -> 0 | ... M42: =IF(M$4="","",-M8)
B43: Operating EBIT | C43: =IF(C$4="","",C38+C39+C42) -> 2508432 | D43: =IF(D$4="","",D38+D39+D42) -> 2212187 | E43: =IF(E$4="","",E38+E39+E42) -> 1734893 | F43: =IF(F$4="","",F38+F39+F42) -> 1383531 | G43: =IF(G$4="","",G38+G39+G42) -> 854988 | H43: =IF(H$4="","",H38+H39+H42) -> 889110 | I43: =IF(I$4="","",I38+I39+I42) -> 705836 | J43: =IF(J$4="","",J38+J39+J42) -> 494526 | ... M43: =IF(M$4="","",M38+M39+M42)
B44: Non-operating EBIT | C44: =IF(C$4="","",C47-C46-C45-C43) -> 67645 | D44: =IF(D$4="","",D47-D46-D45-D43) -> -36452 | E44: =IF(E$4="","",E47-E46-E45-E43) -> -402322 | F44: =IF(F$4="","",F47-F46-F45-F43) -> -49662 | G44: =IF(G$4="","",G47-G46-G45-G43) -> -35638 | H44: =IF(H$4="","",H47-H46-H45-H43) -> 8283 | I44: =IF(I$4="","",I47-I46-I45-I43) -> 9414 | J44: =IF(J$4="","",J47-J46-J45-J43) -> -34528 | ... M44: =IF(M$4="","",M47-M46-M45-M43)
B45: Net Interest Income | C45: =IF(C$4="","",C51+C52) -> 0 | D45: =IF(D$4="","",D51+D52) -> 0 | E45: =IF(E$4="","",E51+E52) -> 0 | F45: =IF(F$4="","",F51+F52) -> 0 | G45: =IF(G$4="","",G51+G52) -> 0 | H45: =IF(H$4="","",H51+H52) -> 0 | I45: =IF(I$4="","",I51+I52) -> 0 | J45: =IF(J$4="","",J51+J52) -> 0 | ... M45: =IF(M$4="","",M51+M52)
B46: Income Tax Paid | C46: =IF(C$4="","",-C14) -> -761461 | D46: =IF(D$4="","",-D14) -> -625545 | E46: =IF(E$4="","",-E14) -> -477771 | F46: =IF(F$4="","",-F14) -> -358547 | G46: =IF(G$4="","",-G14) -> -230437 | H46: =IF(H$4="","",-H14) -> -251797 | I46: =IF(I$4="","",-I14) -> -231449 | J46: =IF(J$4="","",-J14) -> -201336 | ... M46: =IF(M$4="","",-M14)
B47: Reported Net Income | C47: =IF(C$4="","",C15) -> 1814616 | D47: =IF(D$4="","",D15) -> 1550190 | E47: =IF(E$4="","",E15) -> 854800 | F47: =IF(F$4="","",F15) -> 975322 | G47: =IF(G$4="","",G15) -> 588913 | H47: =IF(H$4="","",H15) -> 645596 | I47: =IF(I$4="","",I15) -> 483801 | J47: =IF(J$4="","",J15) -> 258662 | ... M47: =IF(M$4="","",M15)
B48: Non-controling Interests | C48: =IF(C$4="","",MIN(-C16,0)) -> 0 | D48: =IF(D$4="","",MIN(-D16,0)) -> 0 | E48: =IF(E$4="","",MIN(-E16,0)) -> 0 | F48: =IF(F$4="","",MIN(-F16,0)) -> 0 | G48: =IF(G$4="","",MIN(-G16,0)) -> 0 | H48: =IF(H$4="","",MIN(-H16,0)) -> 0 | I48: =IF(I$4="","",MIN(-I16,0)) -> 0 | J48: =IF(J$4="","",MIN(-J16,0)) -> 0 | ... M48: =IF(M$4="","",MIN(-M16,0))
B50: Net Interest Income
B51: Interest Expense | C51: =IF(C$4="","",-C12) -> 0 | D51: =IF(D$4="","",-D12) -> 0 | E51: =IF(E$4="","",-E12) -> 0 | F51: =IF(F$4="","",-F12) -> 0 | G51: =IF(G$4="","",-G12) -> 0 | H51: =IF(H$4="","",-H12) -> 0 | I51: =IF(I$4="","",-I12) -> 0 | J51: =IF(J$4="","",-J12) -> 0 | ... M51: =IF(M$4="","",-M12)
B52: Interest Income | C52: =IF(C$4="","",C13) -> 0 | D52: =IF(D$4="","",D13) -> 0 | E52: =IF(E$4="","",E13) -> 0 | F52: =IF(F$4="","",F13) -> 0 | G52: =IF(G$4="","",G13) -> 0 | H52: =IF(H$4="","",H13) -> 0 | I52: =IF(I$4="","",I13) -> 0 | J52: =IF(J$4="","",J13) -> 0 | ... M52: =IF(M$4="","",M13)
B54: Non-operating EBIT
B55: Share of JV or associate Results | C55: =IF(C$4="","",C9) -> 0 | D55: =IF(D$4="","",D9) -> 0 | E55: =IF(E$4="","",E9) -> 0 | F55: =IF(F$4="","",F9) -> 0 | G55: =IF(G$4="","",G9) -> 0 | H55: =IF(H$4="","",H9) -> 0 | I55: =IF(I$4="","",I9) -> 0 | J55: =IF(J$4="","",J9) -> 0 | ... M55: =IF(M$4="","",M9)
B56: Dividend or Interests from FA | C56: =IF(C$4="","",C10) -> 0 | D56: =IF(D$4="","",D10) -> 0 | E56: =IF(E$4="","",E10) -> 0 | F56: =IF(F$4="","",F10) -> 0 | G56: =IF(G$4="","",G10) -> 0 | H56: =IF(H$4="","",H10) -> 0 | I56: =IF(I$4="","",I10) -> 0 | J56: =IF(J$4="","",J10) -> 0 | ... M56: =IF(M$4="","",M10)
B57: Investment property | C57: =IF(C$4="","",C11) -> 0 | D57: =IF(D$4="","",D11) -> 0 | E57: =IF(E$4="","",E11) -> 0 | F57: =IF(F$4="","",F11) -> 0 | G57: =IF(G$4="","",G11) -> 0 | H57: =IF(H$4="","",H11) -> 0 | I57: =IF(I$4="","",I11) -> 0 | J57: =IF(J$4="","",J11) -> 0 | ... M57: =IF(M$4="","",M11)
B58: Other Non-operating Income | C58: =IF(C$4="","",C44-C55-C56-C57) -> 67645 | D58: =IF(D$4="","",D44-D55-D56-D57) -> -36452 | E58: =IF(E$4="","",E44-E55-E56-E57) -> -402322 | F58: =IF(F$4="","",F44-F55-F56-F57) -> -49662 | G58: =IF(G$4="","",G44-G55-G56-G57) -> -35638 | H58: =IF(H$4="","",H44-H55-H56-H57) -> 8283 | I58: =IF(I$4="","",I44-I55-I56-I57) -> 9414 | J58: =IF(J$4="","",J44-J55-J56-J57) -> -34528 | ... M58: =IF(M$4="","",M44-M55-M56-M57)
B60: Cash Flow Statement
B61: D&A | C61: =IF(C$4="","",-C19) -> 0 | D61: =IF(D$4="","",-D19) -> 0 | E61: =IF(E$4="","",-E19) -> 0 | F61: =IF(F$4="","",-F19) -> 0 | G61: =IF(G$4="","",-G19) -> 0 | H61: =IF(H$4="","",-H19) -> 0 | I61: =IF(I$4="","",-I19) -> 0 | J61: =IF(J$4="","",-J19) -> 0 | ... M61: =IF(M$4="","",-M19)
B62: CAPX | C62: =IF(C$4="","",IF(C20=0,C61,-C20)) -> 0 | D62: =IF(D$4="","",IF(D20=0,D61,-D20)) -> 0 | E62: =IF(E$4="","",IF(E20=0,E61,-E20)) -> 0 | F62: =IF(F$4="","",IF(F20=0,F61,-F20)) -> 0 | G62: =IF(G$4="","",IF(G20=0,G61,-G20)) -> 0 | H62: =IF(H$4="","",IF(H20=0,H61,-H20)) -> 0 | I62: =IF(I$4="","",IF(I20=0,I61,-I20)) -> 0 | J62: =IF(J$4="","",IF(J20=0,J61,-J20)) -> 0 | ... M62: =IF(M$4="","",IF(M20=0,M61,-M20))
B63: WCInv | C63: =IF(C$4="","",-C21) -> 0 | D63: =IF(D$4="","",-D21) -> 0 | E63: =IF(E$4="","",-E21) -> 0 | F63: =IF(F$4="","",-F21) -> 0 | G63: =IF(G$4="","",-G21) -> 0 | H63: =IF(H$4="","",-H21) -> 0 | I63: =IF(I$4="","",-I21) -> 0 | J63: =IF(J$4="","",-J21) -> 0 | ... M63: =IF(M$4="","",-M21)
B64: Net Change in Cash | C64: =IF(C$4="","",C22+C23+C24) -> -177969 | D64: =IF(D$4="","",D22+D23+D24) -> 1093204 | E64: =IF(E$4="","",E22+E23+E24) -> -70961 | F64: =IF(F$4="","",F22+F23+F24) -> 116230 | G64: =IF(G$4="","",G22+G23+G24) -> 27016 | H64: =IF(H$4="","",H22+H23+H24) -> 213735 | I64: =IF(I$4="","",I22+I23+I24) -> -90229 | J64: =IF(J$4="","",J22+J23+J24) -> 218083 | ... M64: =IF(M$4="","",M22+M23+M24)
B65: Dividend per share | C65: =IF(C$4="","",C25) -> 0 | D65: =IF(D$4="","",D25) -> 0 | E65: =IF(E$4="","",E25) -> 0 | F65: =IF(F$4="","",F25) -> 0 | G65: =IF(G$4="","",G25) -> 0 | H65: =IF(H$4="","",H25) -> 0 | I65: =IF(I$4="","",I25) -> 0 | J65: =IF(J$4="","",J25) -> 0 | ... M65: =IF(M$4="","",M25)
B67: YoY %
B68: =B36 -> Sales | C68: =IF(D$36="","",C36/D36-1) -> 0.10071941 | D68: =IF(E$36="","",D36/E36-1) -> 0.18602511 | E68: =IF(F$36="","",E36/F36-1) -> 0.29631045 | F68: =IF(G$36="","",F36/G36-1) -> 0.42135143 | G68: =IF(H$36="","",G36/H36-1) -> 0.10619542 | H68: =IF(I$36="","",H36/I36-1) -> 0.21013077 | I68: =IF(J$36="","",I36/J36-1) -> 0.24125871 | J68: =IF(K$36="","",J36/K36-1) -> 0.13000769 | ... M68: =IF(N$36="","",M36/N36-1)
B69: Gross Margin | C69: =IF(D$36="","",C38/D38-1) -> 0.11791019 | D69: =IF(E$36="","",D38/E38-1) -> 0.24865994 | E69: =IF(F$36="","",E38/F38-1) -> 0.24491037 | F69: =IF(G$36="","",F38/G38-1) -> 0.46452037 | G69: =IF(H$36="","",G38/H38-1) -> 0.10821558 | H69: =IF(I$36="","",H38/I38-1) -> 0.22413804 | I69: =IF(J$36="","",I38/J38-1) -> 0.29847011 | J69: =IF(K$36="","",J38/K38-1) -> 0.16603049 | ... M69: =IF(N$36="","",M38/N38-1)
B70: =B43 -> Operating EBIT | C70: =IF(D$36="","",C43/D43-1) -> 0.13391499 | D70: =IF(E$36="","",D43/E43-1) -> 0.27511437 | E70: =IF(F$36="","",E43/F43-1) -> 0.25396034 | F70: =IF(G$36="","",F43/G43-1) -> 0.61818762 | G70: =IF(H$36="","",G43/H43-1) -> -0.038377704 | H70: =IF(I$36="","",H43/I43-1) -> 0.25965522 | I70: =IF(J$36="","",I43/J43-1) -> 0.42729806 | J70: =IF(K$36="","",J43/K43-1) -> 0.17422213 | ... M70: =IF(N$36="","",M43/N43-1)
B71: Non-operating EBIT | C71: =IF(D$36="","",C44/D44-1) -> -2.8557281 | D71: =IF(E$36="","",D44/E44-1) -> -0.90939596 | E71: =IF(F$36="","",E44/F44-1) -> 7.1012041 | F71: =IF(G$36="","",F44/G44-1) -> 0.39351254 | G71: =IF(H$36="","",G44/H44-1) -> -5.3025474 | H71: =IF(I$36="","",H44/I44-1) -> -0.12014022 | I71: =IF(J$36="","",I44/J44-1) -> -1.2726483 | J71: =IF(K$36="","",J44/K44-1) -> -22.894737 | ... M71: =IF(N$36="","",M44/N44-1)
B72: =B47 -> Reported Net Income | C72: =IF(D$36="","",C47/D47-1) -> 0.17057651 | D72: =IF(E$36="","",D47/E47-1) -> 0.81351193 | E72: =IF(F$36="","",E47/F47-1) -> -0.1235715 | F72: =IF(G$36="","",F47/G47-1) -> 0.65613936 | G72: =IF(H$36="","",G47/H47-1) -> -0.087799491 | H72: =IF(I$36="","",H47/I47-1) -> 0.33442469 | I72: =IF(J$36="","",I47/J47-1) -> 0.87039844 | J72: =IF(K$36="","",J47/K47-1) -> -0.14740211 | ... M72: =IF(N$36="","",M47/N47-1)
B74: Balance Sheet (Clean)
B75: Balance Sheet
B76: Total Assets | C76: =IF(C$4="","",C79+C80) -> 7430543 | D76: =IF(D$4="","",D79+D80) -> 7091941 | E76: =IF(E$4="","",E79+E80) -> 5607038 | F76: =IF(F$4="","",F79+F80) -> 4942478 | G76: =IF(G$4="","",G79+G80) -> 4185215 | H76: =IF(H$4="","",H79+H80) -> 3281354 | I76: =IF(I$4="","",I79+I80) -> 2084711 | J76: =IF(J$4="","",J79+J80) -> 1998483 | ... M76: =IF(M$4="","",M79+M80)
B77: Incl. ST AR | C77: =IF(C$4="","",C28) -> 0 | D77: =IF(D$4="","",D28) -> 124769 | E77: =IF(E$4="","",E28) -> 132906 | F77: =IF(F$4="","",F28) -> 77001 | G77: =IF(G$4="","",G28) -> 62399 | H77: =IF(H$4="","",H28) -> 40219
B78: Incl. ST Inventory | C78: =IF(C$4="","",C29) -> 1652091 | D78: =IF(D$4="","",D29) -> 1323602 | E78: =IF(E$4="","",E29) -> 1447367 | F78: =IF(F$4="","",F29) -> 966481 | G78: =IF(G$4="","",G29) -> 647230 | H78: =IF(H$4="","",H29) -> 518513
B79: Total Liabilities | C79: =IF(C$4="","",C30) -> 3140973 | D79: =IF(D$4="","",D30) -> 2859860 | E79: =IF(E$4="","",E30) -> 2458239 | F79: =IF(F$4="","",F30) -> 2202432 | G79: =IF(G$4="","",G30) -> 1626649 | H79: =IF(H$4="","",H30) -> 1329136 | I79: =IF(I$4="","",I30) -> 638736 | J79: =IF(J$4="","",J30) -> 401523 | ... M79: =IF(M$4="","",M30)
B80: Total Equity | C80: =IF(C$4="","",C31) -> 4289570 | D80: =IF(D$4="","",D31) -> 4232081 | E80: =IF(E$4="","",E31) -> 3148799 | F80: =IF(F$4="","",F31) -> 2740046 | G80: =IF(G$4="","",G31) -> 2558566 | H80: =IF(H$4="","",H31) -> 1952218 | I80: =IF(I$4="","",I31) -> 1445975 | J80: =IF(J$4="","",J31) -> 1596960 | ... M80: =IF(M$4="","",M31)

Sheet BS
B1: Most Recent Quarter | C1: 45781 | F1: =IF(MONTH(C1)=MONTH(Normalized_FCF!G1),"FY","Quarter")&" Report" -> Quarter Report | H1: =scaling_factor -> 1000
B2: Lastest Balance Sheet
B3: ST Operating Assets | C3: Book | D3: Valued @ | F3: ST Non-Operating Assets | G3: Book | H3: Valued @
B4: ST AR | C4: 0 | D4: 0.6 | F4: Cash and cash equivalents | G4: 1325272 | H4: 0.9
B5: Operating ST Financial Assets | C5: 0 | D5: 0.6 | F5: Restricted cash | G5: 0 | H5: 0.7
B6: Inventory | C6: 1652091 | D6: 0.5 | F6: Securities with stable income | G6: 0 | H6: 0.6
B7: Properties held for sale | C7: 0 | D7: 0.6 | F7: Other Securities | G7: 0 | H7: 0.6
B8: Properties held for income | C8: 0 | D8: 0.6 | F8: Properties with stable income | G8: 0 | H8: 0.6
B9: Prepayments and Contract Assets | C9: 0 | D9: 0.1 | F9: Other Properties | G9: 0 | H9: 0.6
B10: ST DTA | C10: 230280 | D10: 0.9
B11: Other ST Assets | C11: 374874 | D11: 0.05
B12: Operating ST Assets | C12: =SUM(C4:C11) -> 2257245 | D12: =C4*D4+C5*D5+C9*D9+C6*D6+C8*D8+C7*D7+C10*D10+C11*D11 -> 1052041.2 | F12: Non-Operating ST Assets | G12: =SUM(G4:G9) -> 1325272 | H12: =G4*H4+G5*H5+G6*H6+G7*H7+G8*H8+G9*H9 -> 1192744.8
B14: LT Operating Assets | C14: Book | D14: Valued @ | F14: LT Non-Operating Assets | G14: Book | H14: Valued @
B15: LT AR and Prepayments | C15: 0 | D15: 0.4 | F15: LT Depositis | G15: 0 | H15: 0.8
B16: Operating LT Financial Assets | C16: 0 | D16: 0.5 | F16: Securities with stable income | G16: 0 | H16: 0.6
B17: Properties held for sale | C17: 0 | D17: 0.6 | F17: Other Securities | G17: 0 | H17: 0.6
B18: Properties held for income | C18: 0 | D18: 0.6 | F18: JV or associate with stable income | G18: 0 | H18: 0.1
B19: PP&E & Right of Use Assets | C19: =1846609+1549401 -> 3396010 | D19: 0.1 | F19: Other JV or associate | G19: 0 | H19: 0.1
B20: Biological assets | C20: 0 | D20: 0.05 | F20: Properties with stable income | G20: 0 | H20: 0.2
B21: Intangible assets | C21: 0 | D21: 0.05 | F21: Other Properties | G21: 0 | H21: 0.1
B22: LT DTA | C22: 0 | D22: 0.9
B23: Other assets & Goodwill | C23: =178001+274015 -> 452016 | D23: 0
B24: Operating LT Assets | C24: =SUM(C15:C23) -> 3848026 | D24: =C15*D15+C16*D16+C18*D18+C17*D17+C19*D19+C20*D20+C21*D21+C22*D22+C23*D23 -> 339601 | F24: Non-Operating LT Assets | G24: =SUM(G15:G21) -> 0 | H24: =G15*H15+G16*H16+G17*H17+G18*H18+G19*H19+G20*H20+G21*H21 -> 0
B26: ST Liabilities | C26: Book | F26: BS Summary | G26: Book | H26: Valued @
B27: ST Borrowing | C27: 0 | F27: Total Equity | G27: =G32-G30 -> 4289570 | H27: =H32-G30 -> -556586
B28: ST Lease liabilities | C28: 281837 | F28: Incl. Minority Interest (NCI) | G28: 0
B29: ST SH Loan | C29: 0 | F29: Incl. Common Equity | G29: =G27-G28 -> 4289570 | H29: =H27-G28 -> -556586
B30: ST Financial Liabilities | C30: 0 | F30: Total Liabilities | G30: =C33+C42 -> 3140973
B31: ST Interest-bearing Debt | C31: =SUM(C27:C30) -> 281837 | F31: incl. Interest-bearing Debt | G31: =C31+C40 -> 1706782
B32: Other ST liabilities | C32: =C33-C31 -> 1290548 | F32: Total Assets | G32: =G35+G40 -> 7430543 | H32: =H35+H40 -> 2584387
B33: Current Liabilities | C33: 1572385
F34: Assets Summary | G34: Book | H34: Valued @
B35: LT Liabilities | C35: Book | F35: Operating Assets | G35: =C12+C24 -> 6105271 | H35: =D12+D24 -> 1391642.2
B36: LT Borrowing | C36: 0 | F36: incl. AR | G36: =C4+C15 -> 0
B37: LT Lease liabilities | C37: 1424945 | F37: incl. inventory | G37: =C6 -> 1652091
B38: LT SH Loan | C38: 0 | F38: incl. Properties held for sale | G38: =C7+C17 -> 0
B39: LT Financial Liabilities | C39: 0 | F39: incl. Fixed Assets | G39: =C7+C17+C19+C20 -> 3396010 | H39: =C7*D7+C17*D17+C19*D19+C20*D20 -> 339601
B40: LT Interest-bearing Debt | C40: =SUM(C36:C39) -> 1424945 | F40: Non-operating Assets | G40: =G12+G24 -> 1325272 | H40: =H12+H24 -> 1192744.8
B41: Other LT liabilities | C41: =C42-C40 -> 143643 | F41: incl. Assets with stable income | G41: =C70 -> 1325272 | H41: =H40-H42 -> 1192744.8
B42: Noncurrent Liabilities | C42: =C37+98189+45454 -> 1568588 | F42: incl. Other Assets | G42: =C82 -> 0 | H42: =D82 -> 0
B44: Balance Sheet Analysis
B45: Asset Value Stress Test | C45: Book | D45: Est. Realizable Value | F45: Notes
B46: Equity | C46: =G29 -> 4289570 | D46: =H29 -> -556586
B47: ="Equity per share ("&Market_currency&")" -> Equity per share (USD) | C47: =C46*H1/Common_Shares*Exchange_Rate -> 35.792532 | D47: =D46*H1/Common_Shares*Exchange_Rate -> -4.6442003
B49: Leverage % | C49: Normalized | D49: Latest
B50: Debt/EBIT | C50: =G31/Normalized_FCF!C8 -> 0.82752635 | D50: =G31/Normalized_FCF!G8 -> 0.68041789
B51: Common Equity/Total Asset | D51: =G29/G32 -> 0.5772889
B53: Profibility % | C53: Normalized | D53: Latest
B54: Operating Asset Yield | C54: =Normalized_FCF!C8/G35 -> 0.3378246 | D54: =Normalized_FCF!G8/G35 -> 0.41086333
B55: Non-Operating Asset Yield | C55: =Normalized_FCF!C11/G40 -> 0 | D55: =Normalized_FCF!G11/G40 -> 0
B57: Reinvestment % | C57: Normalized | D57: Latest
B58: D&A/Fixed Assets | D58: =Normalized_FCF!G9/BS!$G$39 -> 0
B59: Fixed Assets/Total Assets | D59: =G39/G32 -> 0.45703389
B61: NCI % | C61: Estimate | D61: Latest
B62: Est. of NCI Ownership Percentage | C62: =IF(G28<=0,0,G28/G29) -> 0 | D62: =G28/G29 -> 0 | F62: Rough Estimate only
B64: Non-operating Assets Analysis
B65: Non-operating Assets with stable income | C65: Book | D65: Non-Operating | F65: Notes
B66: Cash | C66: =G4+G5+G15 -> 1325272 | D66: =C66-D75 -> 655172.73 | F66: Non-Operating Cash is the Excess cash not required for operations
B67: Securities with stable income | C67: =G6+G16 -> 0
B68: JV or associate with stable income | C68: =G18 -> 0
B69: Properties with stable income | C69: =G8+G20 -> 0
B70: Non-operating Assets with stable income | C70: =SUM(C66:C69) -> 1325272
B72: Cash Management Analysis | C72: Latest | D72: Normalized
B73: Monthly Operating Expenses | C73: =(Normalized_FCF!G25+Normalized_FCF!G35-Normalized_FCF!G91)/12 -> -673307.83 | D73: =(Normalized_FCF!C25+Normalized_FCF!C35-Normalized_FCF!C91)/12 -> -670099.27 | F73: Variable + Fixed Costs & Dividends
B74: Operating Expenses Multiple (months) | C74: =-$C$66/C73 -> 1.9683003 | D74: =-$C$66/D73 -> 1.9777249 | F74: Companies typically need cash to cover 1 to 2 months of operating expenses
B75: Operating Cash Requirement | D75: =MAX(-D73*D76,G5) -> 670099.27 | F75: 1x for stable businesses, 2x for for volatile ones, 6x for cash hoarders
B76: Operating Cash Multiple (months) | D76: =IF(valuation_method="DCF",IF(D74<=3,1,IF(D74>18,6,2)),-C66/D73) -> 1 | F76: Rough Estimate
B78: Other Non-operating Assets | C78: Book | D78: Valued @
B79: Other Securities | C79: =G7+G17 -> 0 | D79: =G7*H7+G17*H17 -> 0
B80: Other JV or associate | C80: =G19 -> 0 | D80: =G19*H19 -> 0
B81: Other Properties | C81: =G9+G21 -> 0 | D81: =G9*H9+G21*H21 -> 0
B82: Other Non-operating Assets | C82: =SUM(C79:C81) -> 0 | D82: =SUM(D79:D81) -> 0
B84: Non-FCF Value of the Equity Value
B85: Non-FCF Value | D85: Per-Share
B86: Interest-bearing Debt | C86: =-DCF!C7*Exchange_Rate -> -1706782 | D86: =C86*scaling_factor/Common_Shares -> -14.241532 | E86: =Market_currency -> USD
B87: Non-operating Cash | C87: =DCF!C8*Exchange_Rate -> 655172.73 | D87: =C87*scaling_factor/Common_Shares -> 5.4668162 | E87: =Market_currency -> USD
B88: Other Non-operating Assets | C88: =DCF!C9*Exchange_Rate -> 0 | D88: =C88*scaling_factor/Common_Shares -> 0 | E88: =Market_currency -> USD
B89: Total Non-FCF Value | C89: =SUM(C86:C88) -> -1051609.3 | D89: =SUM(D86:D88) -> -8.774716 | E89: =Market_currency -> USD

Sheet Normalized_FCF
B1: =Thesis!C25 -> USD | C1: Normalized | G1: =Data!C1 -> 45688 | H1: =EOMONTH(EDATE(G1,-12),0) -> 45322 | I1: =EOMONTH(EDATE(H1,-12),0) -> 44957 | J1: =EOMONTH(EDATE(I1,-12),0) -> 44592 | K1: =EOMONTH(EDATE(J1,-12),0) -> 44227 | L1: =EOMONTH(EDATE(K1,-12),0) -> 43861 | M1: =EOMONTH(EDATE(L1,-12),0) -> 43496 | N1: =EOMONTH(EDATE(M1,-12),0) -> 43131 | O1: =EOMONTH(EDATE(N1,-12),0) -> 42766 | ... Q1: =EOMONTH(EDATE(P1,-12),0) -> 42035
B2: FCFE Analysis | E2: Notes
B3: FCFE | C3: =scaling_factor -> 1000
B4: Sales | C4: =AVERAGE(G4:H4) -> 10103702 | G4: =Data!C36 -> 10588126 | H4: =Data!D36 -> 9619278 | I4: =Data!E36 -> 8110518 | J4: =Data!F36 -> 6256617 | K4: =Data!G36 -> 4401879 | L4: =Data!H36 -> 3979296 | M4: =Data!I36 -> 3288319 | N4: =Data!J36 -> 2649181 | ... Q4: =Data!M36
B5: Variable Costs | C5: =C25 -> -4278812.3 | G5: =G25 -> -4317315 | H5: =H25 -> -4009873 | I5: =I25 -> -3618178 | J5: =J25 -> -2648052 | K5: =K25 -> -1937888 | L5: =L25 -> -1755910 | M5: =M25 -> -1472032 | N5: =N25 -> -1250391 | ... Q5: =Q25
B6: Contribution Margin | C6: =C4+C5 -> 5824889.7 | G6: =IF(G4="","",G4+G5) -> 6270811 | H6: =IF(H4="","",H4+H5) -> 5609405 | I6: =IF(I4="","",I4+I5) -> 4492340 | J6: =IF(J4="","",J4+J5) -> 3608565 | K6: =IF(K4="","",K4+K5) -> 2463991 | L6: =IF(L4="","",L4+L5) -> 2223386 | M6: =IF(M4="","",M4+M5) -> 1816287 | N6: =IF(N4="","",N4+N5) -> 1398790 | ... Q6: =IF(Q4="","",Q4+Q5)
B7: Fixed Costs | C7: =C35 -> -3762379 | G7: =G35 -> -3762379 | H7: =H35 -> -3397218 | I7: =I35 -> -2757447 | J7: =J35 -> -2225034 | K7: =K35 -> -1609003 | L7: =L35 -> -1334276 | M7: =M35 -> -1110451 | N7: =N35 -> -904264 | ... Q7: =Q35
B8: Operating EBIT | C8: =C6+C7 -> 2062510.7 | G8: =IF(G$4="","",G6+G7) -> 2508432 | H8: =IF(H$4="","",H6+H7) -> 2212187 | I8: =IF(I$4="","",I6+I7) -> 1734893 | J8: =IF(J$4="","",J6+J7) -> 1383531 | K8: =IF(K$4="","",K6+K7) -> 854988 | L8: =IF(L$4="","",L6+L7) -> 889110 | M8: =IF(M$4="","",M6+M7) -> 705836 | N8: =IF(N$4="","",N6+N7) -> 494526 | ... Q8: =IF(Q$4="","",Q6+Q7)
B9: Add Back D&A | C9: =BS!$G$39*BS!D58 -> 0 | G9: =IF(Data!C61="","",-Data!C61) -> 0 | H9: =IF(Data!D61="","",-Data!D61) -> 0 | I9: =IF(Data!E61="","",-Data!E61) -> 0 | J9: =IF(Data!F61="","",-Data!F61) -> 0 | K9: =IF(Data!G61="","",-Data!G61) -> 0 | L9: =IF(Data!H61="","",-Data!H61) -> 0 | M9: =IF(Data!I61="","",-Data!I61) -> 0 | N9: =IF(Data!J61="","",-Data!J61) -> 0 | ... Q9: =IF(Data!M61="","",-Data!M61)
B10: Maintenance Capex | C10: =-C4*C78 -> 0 | G10: =Data!C62 -> 0 | H10: =Data!D62 -> 0 | I10: =Data!E62 -> 0 | J10: =Data!F62 -> 0 | K10: =Data!G62 -> 0 | L10: =Data!H62 -> 0 | M10: =Data!I62 -> 0 | N10: =Data!J62 -> 0 | ... Q10: =Data!M62
B11: Stable Non-Operating EBIT | C11: =C63 -> 0 | G11: =G61 -> 0 | H11: =H61 -> 0 | I11: =I61 -> 0 | J11: =J61 -> 0 | K11: =K61 -> 0 | L11: =L61 -> 0 | M11: =M61 -> 0 | N11: =N61 -> 0 | ... Q11: =Q61
B12: Net Interest Income | C12: =C50 -> 0 | G12: =G50 -> 0 | H12: =H50 -> 0 | I12: =I50 -> 0 | J12: =J50 -> 0 | K12: =K50 -> 0 | L12: =L50 -> 0 | M12: =M50 -> 0 | N12: =N50 -> 0 | ... Q12: =Q50
B13: Pre-tax Profit | C13: =SUM(C8:C12) -> 2062510.7 | G13: =IF(G$4="","",SUM(G8:G12)) -> 2508432 | H13: =IF(H$4="","",SUM(H8:H12)) -> 2212187 | I13: =IF(I$4="","",SUM(I8:I12)) -> 1734893 | J13: =IF(J$4="","",SUM(J8:J12)) -> 1383531 | K13: =IF(K$4="","",SUM(K8:K12)) -> 854988 | L13: =IF(L$4="","",SUM(L8:L12)) -> 889110 | M13: =IF(M$4="","",SUM(M8:M12)) -> 705836 | N13: =IF(N$4="","",SUM(N8:N12)) -> 494526 | ... Q13: =IF(Q$4="","",SUM(Q8:Q12))
B14: Income Tax | C14: =-SUM(C8+C11,C12)*C43 -> -531509.02 | G14: =Data!C46 -> -761461 | H14: =Data!D46 -> -625545 | I14: =Data!E46 -> -477771 | J14: =Data!F46 -> -358547 | K14: =Data!G46 -> -230437 | L14: =Data!H46 -> -251797 | M14: =Data!I46 -> -231449 | N14: =Data!J46 -> -201336 | ... Q14: =Data!M46
B15: NCI’s Share of Profits | C15: =-C4*C83 -> 0 | G15: =Data!C48 -> 0 | H15: =Data!D48 -> 0 | I15: =Data!E48 -> 0 | J15: =Data!F48 -> 0 | K15: =Data!G48 -> 0 | L15: =Data!H48 -> 0 | M15: =Data!I48 -> 0 | N15: =Data!J48 -> 0 | ... Q15: =Data!M48
B16: After-tax Profit | C16: =SUM(C13:C15) -> 1531001.7 | G16: =IF(G$4="","",SUM(G13:G15)) -> 1746971 | H16: =IF(H$4="","",SUM(H13:H15)) -> 1586642 | I16: =IF(I$4="","",SUM(I13:I15)) -> 1257122 | J16: =IF(J$4="","",SUM(J13:J15)) -> 1024984 | K16: =IF(K$4="","",SUM(K13:K15)) -> 624551 | L16: =IF(L$4="","",SUM(L13:L15)) -> 637313 | M16: =IF(M$4="","",SUM(M13:M15)) -> 474387 | N16: =IF(N$4="","",SUM(N13:N15)) -> 293190 | ... Q16: =IF(Q$4="","",SUM(Q13:Q15))
B17: WCInv | C17: =-C4*C85 -> 0 | E17: WCInv is by default excluded
B18: Net Borrowing | C18: 0 | E18: Net borrowing is excluded
B19: FCFE | C19: =C16+C17 -> 1531001.7 | G19: =IF(G$4="","",G16+G17) -> 1746971 | H19: =IF(H$4="","",H16+H17) -> 1586642 | I19: =IF(I$4="","",I16+I17) -> 1257122 | J19: =IF(J$4="","",J16+J17) -> 1024984 | K19: =IF(K$4="","",K16+K17) -> 624551 | L19: =IF(L$4="","",L16+L17) -> 637313 | M19: =IF(M$4="","",M16+M17) -> 474387 | N19: =IF(N$4="","",N16+N17) -> 293190 | ... Q19: =IF(Q$4="","",Q16+Q17)
B21: Operating Cost Structure | E21: Notes
B22: Variable Costs
B23: COGS | C23: =-C4*C28 -> -4278812.3 | G23: =Data!C37 -> -4317315 | H23: =Data!D37 -> -4009873 | I23: =Data!E37 -> -3618178 | J23: =Data!F37 -> -2648052 | K23: =Data!G37 -> -1937888 | L23: =Data!H37 -> -1755910 | M23: =Data!I37 -> -1472032 | N23: =Data!J37 -> -1250391 | ... Q23: =Data!M37
B24: Selling Expenses | C24: =-C4*C29 -> 0 | G24: =Data!C40 -> 0 | H24: =Data!D40 -> 0 | I24: =Data!E40 -> 0 | J24: =Data!F40 -> 0 | K24: =Data!G40 -> 0 | L24: =Data!H40 -> 0 | M24: =Data!I40 -> 0 | N24: =Data!J40 -> 0 | ... Q24: =Data!M40
B25: Variable Costs | C25: =C23+C24 -> -4278812.3 | G25: =IF(G$4="","",G23+G24) -> -4317315 | H25: =IF(H$4="","",H23+H24) -> -4009873 | I25: =IF(I$4="","",I23+I24) -> -3618178 | J25: =IF(J$4="","",J23+J24) -> -2648052 | K25: =IF(K$4="","",K23+K24) -> -1937888 | L25: =IF(L$4="","",L23+L24) -> -1755910 | M25: =IF(M$4="","",M23+M24) -> -1472032 | N25: =IF(N$4="","",N23+N24) -> -1250391 | ... Q25: =IF(Q$4="","",Q23+Q24)
B27: Variable Costs % of Sales
B28: COGS | C28: =AVERAGE(G28:J28) -> 0.42348955 | E28: Historical Average | G28: =IF(G$4="","",ABS(G23/G$4)) -> 0.40775063 | H28: =IF(H$4="","",ABS(H23/H$4)) -> 0.416858 | I28: =IF(I$4="","",ABS(I23/I$4)) -> 0.44610936 | J28: =IF(J$4="","",ABS(J23/J$4)) -> 0.42324023 | K28: =IF(K$4="","",ABS(K23/K$4)) -> 0.44024109 | L28: =IF(L$4="","",ABS(L23/L$4)) -> 0.44126147 | M28: =IF(M$4="","",ABS(M23/M$4)) -> 0.44765487 | N28: =IF(N$4="","",ABS(N23/N$4)) -> 0.47199153 | ... Q28: =IF(Q$4="","",ABS(Q23/Q$4))
B29: =B24 -> Selling Expenses | C29: =AVERAGE(G29:J29) -> 0 | E29: Historical Average | G29: =IF(G$4="","",ABS(G24/G$4)) -> 0 | H29: =IF(H$4="","",ABS(H24/H$4)) -> 0 | I29: =IF(I$4="","",ABS(I24/I$4)) -> 0 | J29: =IF(J$4="","",ABS(J24/J$4)) -> 0 | K29: =IF(K$4="","",ABS(K24/K$4)) -> 0 | L29: =IF(L$4="","",ABS(L24/L$4)) -> 0 | M29: =IF(M$4="","",ABS(M24/M$4)) -> 0 | N29: =IF(N$4="","",ABS(N24/N$4)) -> 0 | ... Q29: =IF(Q$4="","",ABS(Q24/Q$4))
B30: Variable Costs | C30: =ABS(C25/$C$4) -> 0.42348955 | G30: =IF(G$4="","",ABS(G25/G$4)) -> 0.40775063 | H30: =IF(H$4="","",ABS(H25/H$4)) -> 0.416858 | I30: =IF(I$4="","",ABS(I25/I$4)) -> 0.44610936 | J30: =IF(J$4="","",ABS(J25/J$4)) -> 0.42324023 | K30: =IF(K$4="","",ABS(K25/K$4)) -> 0.44024109 | L30: =IF(L$4="","",ABS(L25/L$4)) -> 0.44126147 | M30: =IF(M$4="","",ABS(M25/M$4)) -> 0.44765487 | N30: =IF(N$4="","",ABS(N25/N$4)) -> 0.47199153 | ... Q30: =IF(Q$4="","",ABS(Q25/Q$4))
B32: Fixed Costs
B33: G&A and other Opex | C33: =G33 -> -3762379 | E33: Historical Average | G33: =Data!C41 -> -3762379 | H33: =Data!D41 -> -3397218 | I33: =Data!E41 -> -2757447 | J33: =Data!F41 -> -2225034 | K33: =Data!G41 -> -1609003 | L33: =Data!H41 -> -1334276 | M33: =Data!I41 -> -1110451 | N33: =Data!J41 -> -904264 | ... Q33: =Data!M41
B34: R&D | C34: =AVERAGE(G34:J34) -> 0 | E34: Historical Average | G34: =Data!C42 -> 0 | H34: =Data!D42 -> 0 | I34: =Data!E42 -> 0 | J34: =Data!F42 -> 0 | K34: =Data!G42 -> 0 | L34: =Data!H42 -> 0 | M34: =Data!I42 -> 0 | N34: =Data!J42 -> 0 | ... Q34: =Data!M42
B35: Fixed Costs | C35: =C33+C34 -> -3762379 | G35: =IF(G4="","",G33+G34) -> -3762379 | H35: =IF(H4="","",H33+H34) -> -3397218 | I35: =IF(I4="","",I33+I34) -> -2757447 | J35: =IF(J4="","",J33+J34) -> -2225034 | K35: =IF(K4="","",K33+K34) -> -1609003 | L35: =IF(L4="","",L33+L34) -> -1334276 | M35: =IF(M4="","",M33+M34) -> -1110451 | N35: =IF(N4="","",N33+N34) -> -904264 | ... Q35: =IF(Q4="","",Q33+Q34)
B37: Fixed Costs % of Sales
B38: =B33 -> G&A and other Opex | C38: =ABS(C33/$C$4) -> 0.37237628 | G38: =IF(G$4="","",ABS(G33/G$4)) -> 0.35533946 | H38: =IF(H$4="","",ABS(H33/H$4)) -> 0.35316767 | I38: =IF(I$4="","",ABS(I33/I$4)) -> 0.33998408 | J38: =IF(J$4="","",ABS(J33/J$4)) -> 0.35562893 | K38: =IF(K$4="","",ABS(K33/K$4)) -> 0.3655264 | L38: =IF(L$4="","",ABS(L33/L$4)) -> 0.33530454 | M38: =IF(M$4="","",ABS(M33/M$4)) -> 0.33769564 | N38: =IF(N$4="","",ABS(N33/N$4)) -> 0.34133719 | ... Q38: =IF(Q$4="","",ABS(Q33/Q$4))
B39: =B34 -> R&D | C39: =ABS(C34/$C$4) -> 0 | G39: =IF(G$4="","",ABS(G34/G$4)) -> 0 | H39: =IF(H$4="","",ABS(H34/H$4)) -> 0 | I39: =IF(I$4="","",ABS(I34/I$4)) -> 0 | J39: =IF(J$4="","",ABS(J34/J$4)) -> 0 | K39: =IF(K$4="","",ABS(K34/K$4)) -> 0 | L39: =IF(L$4="","",ABS(L34/L$4)) -> 0 | M39: =IF(M$4="","",ABS(M34/M$4)) -> 0 | N39: =IF(N$4="","",ABS(N34/N$4)) -> 0 | ... Q39: =IF(Q$4="","",ABS(Q34/Q$4))
B40: Fixed Costs | C40: =ABS(C35/$C$4) -> 0.37237628 | G40: =IF(G$4="","",ABS(G35/G$4)) -> 0.35533946 | H40: =IF(H$4="","",ABS(H35/H$4)) -> 0.35316767 | I40: =IF(I$4="","",ABS(I35/I$4)) -> 0.33998408 | J40: =IF(J$4="","",ABS(J35/J$4)) -> 0.35562893 | K40: =IF(K$4="","",ABS(K35/K$4)) -> 0.3655264 | L40: =IF(L$4="","",ABS(L35/L$4)) -> 0.33530454 | M40: =IF(M$4="","",ABS(M35/M$4)) -> 0.33769564 | N40: =IF(N$4="","",ABS(N35/N$4)) -> 0.34133719 | ... Q40: =IF(Q$4="","",ABS(Q35/Q$4))
B42: Tax % of Pre-tax Profit
B43: Income Tax Rate | C43: 0.2577 | E43: Use the highest past tax rate | G43: =IF(G$4="","",-G14/SUM(G8+G11,G12)) -> 0.30356055 | H43: =IF(H$4="","",-H14/SUM(H8+H11,H12)) -> 0.28277221 | I43: =IF(I$4="","",-I14/SUM(I8+I11,I12)) -> 0.27538932 | J43: =IF(J$4="","",-J14/SUM(J8+J11,J12)) -> 0.25915357 | K43: =IF(K$4="","",-K14/SUM(K8+K11,K12)) -> 0.26952074 | L43: =IF(L$4="","",-L14/SUM(L8+L11,L12)) -> 0.28320118 | M43: =IF(M$4="","",-M14/SUM(M8+M11,M12)) -> 0.32790762 | N43: =IF(N$4="","",-N14/SUM(N8+N11,N12)) -> 0.40712925 | ... Q43: =IF(Q$4="","",-Q14/SUM(Q8+Q11,Q12))
B45: Non-operating Income | E45: Notes
B46: Interest
B47: Interest Expense | C47: =-BS!G31*Normalized_FCF!C54 -> 0 | G47: =Data!C51 -> 0 | H47: =Data!D51 -> 0 | I47: =Data!E51 -> 0 | J47: =Data!F51 -> 0 | K47: =Data!G51 -> 0 | L47: =Data!H51 -> 0 | M47: =Data!I51 -> 0 | N47: =Data!J51 -> 0 | ... Q47: =Data!M51
B48: Operating Interest Income | C48: =BS!D75*C53 -> 0 | G48: =IFERROR(IF(G$4="","",($C$48/$C$49)*G49),0) -> 0 | H48: =IFERROR(IF(H$4="","",($C$48/$C$49)*H49),0) -> 0 | I48: =IFERROR(IF(I$4="","",($C$48/$C$49)*I49),0) -> 0 | J48: =IFERROR(IF(J$4="","",($C$48/$C$49)*J49),0) -> 0 | K48: =IFERROR(IF(K$4="","",($C$48/$C$49)*K49),0) -> 0 | L48: =IFERROR(IF(L$4="","",($C$48/$C$49)*L49),0) -> 0 | M48: =IFERROR(IF(M$4="","",($C$48/$C$49)*M49),0) -> 0 | N48: =IFERROR(IF(N$4="","",($C$48/$C$49)*N49),0) -> 0 | ... Q48: =IFERROR(IF(Q$4="","",($C$48/$C$49)*Q49),0)
B49: From Interest Income | C49: =BS!$C$66*C53 -> 0 | G49: =Data!C52 -> 0 | H49: =Data!D52 -> 0 | I49: =Data!E52 -> 0 | J49: =Data!F52 -> 0 | K49: =Data!G52 -> 0 | L49: =Data!H52 -> 0 | M49: =Data!I52 -> 0 | N49: =Data!J52 -> 0 | ... Q49: =Data!M52
B50: Net Interest Income | C50: =C47+C48 -> 0 | G50: =IF(G$4="","",(G47+G48)) -> 0 | H50: =IF(H$4="","",(H47+H48)) -> 0 | I50: =IF(I$4="","",(I47+I48)) -> 0 | J50: =IF(J$4="","",(J47+J48)) -> 0 | K50: =IF(K$4="","",(K47+K48)) -> 0 | L50: =IF(L$4="","",(L47+L48)) -> 0 | M50: =IF(M$4="","",(M47+M48)) -> 0 | N50: =IF(N$4="","",(N47+N48)) -> 0 | ... Q50: =IF(Q$4="","",(Q47+Q48))
B52: % Interest | G52: Latest Asset Value
B53: Interest Yield/Cash | C53: 0 | E53: Reference the market rate | G53: =IF(Normalized_FCF!G4="","",Normalized_FCF!G49/BS!$C$66) -> 0
B54: Interest Rate/Debt | C54: =G54 -> 0 | E54: Use Last year's rate | G54: =IFERROR(ABS(Normalized_FCF!G47/BS!$G$31),0) -> 0
B55: Pre-tax Profit/Interest Expense | C55: =-C8/C47 -> #DIV/0! | G55: =IF(G4="","",-G8/G47) -> #DIV/0! | H55: =IF(H4="","",-H8/H47) -> #DIV/0! | I55: =IF(I4="","",-I8/I47) -> #DIV/0! | J55: =IF(J4="","",-J8/J47) -> #DIV/0! | K55: =IF(K4="","",-K8/K47) -> #DIV/0! | L55: =IF(L4="","",-L8/L47) -> #DIV/0! | M55: =IF(M4="","",-M8/M47) -> #DIV/0! | N55: =IF(N4="","",-N8/N47) -> #DIV/0! | ... Q55: =IF(Q4="","",-Q8/Q47)
B57: Non-operating EBIT | G57: Latest Asset Value
B58: Dividend or Interests from FA | C58: =BS!$C67*C66 -> 0 | G58: =Data!C56 -> 0 | H58: =Data!D56 -> 0 | I58: =Data!E56 -> 0 | J58: =Data!F56 -> 0 | K58: =Data!G56 -> 0 | L58: =Data!H56 -> 0 | M58: =Data!I56 -> 0 | N58: =Data!J56 -> 0 | ... Q58: =Data!M56
B59: Share of JV or associate Results | C59: =BS!$C68*C67 -> 0 | G59: =Data!C55 -> 0 | H59: =Data!D55 -> 0 | I59: =Data!E55 -> 0 | J59: =Data!F55 -> 0 | K59: =Data!G55 -> 0 | L59: =Data!H55 -> 0 | M59: =Data!I55 -> 0 | N59: =Data!J55 -> 0 | ... Q59: =Data!M55
B60: Investment property | C60: =BS!$C69*C68 -> 0 | G60: =Data!C57 -> 0 | H60: =Data!D57 -> 0 | I60: =Data!E57 -> 0 | J60: =Data!F57 -> 0 | K60: =Data!G57 -> 0 | L60: =Data!H57 -> 0 | M60: =Data!I57 -> 0 | N60: =Data!J57 -> 0 | ... Q60: =Data!M57
B61: Stable Non-Operating EBIT | C61: =SUM(C58:C60) -> 0 | G61: =IF(G4="","",SUM(G58:G60)) -> 0 | H61: =IF(H4="","",SUM(H58:H60)) -> 0 | I61: =IF(I4="","",SUM(I58:I60)) -> 0 | J61: =IF(J4="","",SUM(J58:J60)) -> 0 | K61: =IF(K4="","",SUM(K58:K60)) -> 0 | L61: =IF(L4="","",SUM(L58:L60)) -> 0 | M61: =IF(M4="","",SUM(M58:M60)) -> 0 | N61: =IF(N4="","",SUM(N58:N60)) -> 0 | ... Q61: =IF(Q4="","",SUM(Q58:Q60))
B62: Other Non-operating Income | C62: 0 | E62: Assume 0 | G62: =Data!C58 -> 67645 | H62: =Data!D58 -> -36452 | I62: =Data!E58 -> -402322 | J62: =Data!F58 -> -49662 | K62: =Data!G58 -> -35638 | L62: =Data!H58 -> 8283 | M62: =Data!I58 -> 9414 | N62: =Data!J58 -> -34528 | ... Q62: =Data!M58
B63: Total Non-Operating EBIT | C63: =C61+C62 -> 0 | G63: =IF(G4="","",G61+G62) -> 67645 | H63: =IF(H4="","",H61+H62) -> -36452 | I63: =IF(I4="","",I61+I62) -> -402322 | J63: =IF(J4="","",J61+J62) -> -49662 | K63: =IF(K4="","",K61+K62) -> -35638 | L63: =IF(L4="","",L61+L62) -> 8283 | M63: =IF(M4="","",M61+M62) -> 9414 | N63: =IF(N4="","",N61+N62) -> -34528 | ... Q63: =IF(Q4="","",Q61+Q62)
B65: Non-operating Asset Yield % | G65: Latest Asset Value
B66: Dividend or Interests from FA | C66: =G66 -> 0 | G66: =IFERROR(G58/BS!$C$67,0) -> 0
B67: JV or associate | C67: =G67 -> 0 | G67: =IFERROR(G59/BS!$C$68,0) -> 0
B68: Investment property | C68: =G68 -> 0 | G68: =IFERROR(G60/BS!$C$69,0) -> 0
B69: Stable Non-Operating EBIT | C69: =C61/BS!C70 -> 0 | G69: =G61/BS!C70 -> 0
B71: P&L & Dividend Analysis | E71: Notes
B72: P&L % Sales
B73: Variable Costs | C73: =ABS(C5/C$4) -> 0.42348955 | G73: =IF(G$4="","",ABS(G5/G$4)) -> 0.40775063 | H73: =IF(H$4="","",ABS(H5/H$4)) -> 0.416858 | I73: =IF(I$4="","",ABS(I5/I$4)) -> 0.44610936 | J73: =IF(J$4="","",ABS(J5/J$4)) -> 0.42324023 | K73: =IF(K$4="","",ABS(K5/K$4)) -> 0.44024109 | L73: =IF(L$4="","",ABS(L5/L$4)) -> 0.44126147 | M73: =IF(M$4="","",ABS(M5/M$4)) -> 0.44765487 | N73: =IF(N$4="","",ABS(N5/N$4)) -> 0.47199153 | ... Q73: =IF(Q$4="","",ABS(Q5/Q$4))
B74: Contribution Margin | C74: =ABS(C6/C$4) -> 0.57651045 | G74: =IF(G$4="","",ABS(G6/G$4)) -> 0.59224937 | H74: =IF(H$4="","",ABS(H6/H$4)) -> 0.583142 | I74: =IF(I$4="","",ABS(I6/I$4)) -> 0.55389064 | J74: =IF(J$4="","",ABS(J6/J$4)) -> 0.57675977 | K74: =IF(K$4="","",ABS(K6/K$4)) -> 0.55975891 | L74: =IF(L$4="","",ABS(L6/L$4)) -> 0.55873853 | M74: =IF(M$4="","",ABS(M6/M$4)) -> 0.55234513 | N74: =IF(N$4="","",ABS(N6/N$4)) -> 0.52800847 | ... Q74: =IF(Q$4="","",ABS(Q6/Q$4))
B75: Fixed Costs | C75: =ABS(C7/C$4) -> 0.37237628 | G75: =IF(G$4="","",ABS(G7/G$4)) -> 0.35533946 | H75: =IF(H$4="","",ABS(H7/H$4)) -> 0.35316767 | I75: =IF(I$4="","",ABS(I7/I$4)) -> 0.33998408 | J75: =IF(J$4="","",ABS(J7/J$4)) -> 0.35562893 | K75: =IF(K$4="","",ABS(K7/K$4)) -> 0.3655264 | L75: =IF(L$4="","",ABS(L7/L$4)) -> 0.33530454 | M75: =IF(M$4="","",ABS(M7/M$4)) -> 0.33769564 | N75: =IF(N$4="","",ABS(N7/N$4)) -> 0.34133719 | ... Q75: =IF(Q$4="","",ABS(Q7/Q$4))
B76: Operating EBIT | C76: =ABS(C8/C$4) -> 0.20413416 | G76: =IF(G$4="","",ABS(G8/G$4)) -> 0.23690991 | H76: =IF(H$4="","",ABS(H8/H$4)) -> 0.22997433 | I76: =IF(I$4="","",ABS(I8/I$4)) -> 0.21390656 | J76: =IF(J$4="","",ABS(J8/J$4)) -> 0.22113084 | K76: =IF(K$4="","",ABS(K8/K$4)) -> 0.19423251 | L76: =IF(L$4="","",ABS(L8/L$4)) -> 0.22343399 | M76: =IF(M$4="","",ABS(M8/M$4)) -> 0.21464949 | N76: =IF(N$4="","",ABS(N8/N$4)) -> 0.18667128 | ... Q76: =IF(Q$4="","",ABS(Q8/Q$4))
B77: Add Back D&A | C77: =ABS(C9/C$4) -> 0 | G77: =IF(G$4="","",G9/G$4) -> 0 | H77: =IF(H$4="","",H9/H$4) -> 0 | I77: =IF(I$4="","",I9/I$4) -> 0 | J77: =IF(J$4="","",J9/J$4) -> 0 | K77: =IF(K$4="","",K9/K$4) -> 0 | L77: =IF(L$4="","",L9/L$4) -> 0 | M77: =IF(M$4="","",M9/M$4) -> 0 | N77: =IF(N$4="","",N9/N$4) -> 0 | ... Q77: =IF(Q$4="","",Q9/Q$4)
B78: Maintenance Capex | C78: =MAX(AVERAGE(G78:J78),C77) -> 0 | E78: Historical Average or D&A | G78: =IF(G$4="","",-G10/G$4) -> 0 | H78: =IF(H$4="","",-H10/H$4) -> 0 | I78: =IF(I$4="","",-I10/I$4) -> 0 | J78: =IF(J$4="","",-J10/J$4) -> 0 | K78: =IF(K$4="","",-K10/K$4) -> 0 | L78: =IF(L$4="","",-L10/L$4) -> 0 | M78: =IF(M$4="","",-M10/M$4) -> 0 | N78: =IF(N$4="","",-N10/N$4) -> 0 | ... Q78: =IF(Q$4="","",-Q10/Q$4)
B79: Non-Operating EBIT | C79: =ABS(C11/C$4) -> 0 | G79: =IF(G$4="","",G11/G$4) -> 0 | H79: =IF(H$4="","",H11/H$4) -> 0 | I79: =IF(I$4="","",I11/I$4) -> 0 | J79: =IF(J$4="","",J11/J$4) -> 0 | K79: =IF(K$4="","",K11/K$4) -> 0 | L79: =IF(L$4="","",L11/L$4) -> 0 | M79: =IF(M$4="","",M11/M$4) -> 0 | N79: =IF(N$4="","",N11/N$4) -> 0 | ... Q79: =IF(Q$4="","",Q11/Q$4)
B80: Net Interest Income | C80: =ABS(C12/C$4) -> 0 | G80: =IF(G$4="","",ABS(G12/G$4)) -> 0 | H80: =IF(H$4="","",ABS(H12/H$4)) -> 0 | I80: =IF(I$4="","",ABS(I12/I$4)) -> 0 | J80: =IF(J$4="","",ABS(J12/J$4)) -> 0 | K80: =IF(K$4="","",ABS(K12/K$4)) -> 0 | L80: =IF(L$4="","",ABS(L12/L$4)) -> 0 | M80: =IF(M$4="","",ABS(M12/M$4)) -> 0 | N80: =IF(N$4="","",ABS(N12/N$4)) -> 0 | ... Q80: =IF(Q$4="","",ABS(Q12/Q$4))
B81: Pre-tax Profit | C81: =C13/C4 -> 0.20413416 | G81: =IF(G$4="","",G13/G$4) -> 0.23690991 | H81: =IF(H$4="","",H13/H$4) -> 0.22997433 | I81: =IF(I$4="","",I13/I$4) -> 0.21390656 | J81: =IF(J$4="","",J13/J$4) -> 0.22113084 | K81: =IF(K$4="","",K13/K$4) -> 0.19423251 | L81: =IF(L$4="","",L13/L$4) -> 0.22343399 | M81: =IF(M$4="","",M13/M$4) -> 0.21464949 | N81: =IF(N$4="","",N13/N$4) -> 0.18667128 | ... Q81: =IF(Q$4="","",Q13/Q$4)
B82: Income Tax | C82: =ABS(C14/C$4) -> 0.052605374 | G82: =IF(G$4="","",ABS(G14/G$4)) -> 0.071916503 | H82: =IF(H$4="","",ABS(H14/H$4)) -> 0.065030348 | I82: =IF(I$4="","",ABS(I14/I$4)) -> 0.058907581 | J82: =IF(J$4="","",ABS(J14/J$4)) -> 0.057306848 | K82: =IF(K$4="","",ABS(K14/K$4)) -> 0.05234969 | L82: =IF(L$4="","",ABS(L14/L$4)) -> 0.063276771 | M82: =IF(M$4="","",ABS(M14/M$4)) -> 0.070385203 | N82: =IF(N$4="","",ABS(N14/N$4)) -> 0.075999337 | ... Q82: =IF(Q$4="","",ABS(Q14/Q$4))
B83: =B15 -> NCI’s Share of Profits | C83: =MIN(BS!C62,MAX(G83:K83)) -> 0 | G83: =IF(G$4="","",-G15/G$4) -> 0 | H83: =IF(H$4="","",-H15/H$4) -> 0 | I83: =IF(I$4="","",-I15/I$4) -> 0 | J83: =IF(J$4="","",-J15/J$4) -> 0 | K83: =IF(K$4="","",-K15/K$4) -> 0 | L83: =IF(L$4="","",-L15/L$4) -> 0 | M83: =IF(M$4="","",-M15/M$4) -> 0 | N83: =IF(N$4="","",-N15/N$4) -> 0 | ... Q83: =IF(Q$4="","",-Q15/Q$4)
B84: After-tax Profit | C84: =ABS(C16/C$4) -> 0.15152879 | G84: =IF(G$4="","",ABS(G16/G$4)) -> 0.16499341 | H84: =IF(H$4="","",ABS(H16/H$4)) -> 0.16494398 | I84: =IF(I$4="","",ABS(I16/I$4)) -> 0.15499898 | J84: =IF(J$4="","",ABS(J16/J$4)) -> 0.163824 | K84: =IF(K$4="","",ABS(K16/K$4)) -> 0.14188282 | L84: =IF(L$4="","",ABS(L16/L$4)) -> 0.16015722 | M84: =IF(M$4="","",ABS(M16/M$4)) -> 0.14426429 | N84: =IF(N$4="","",ABS(N16/N$4)) -> 0.11067194 | ... Q84: =IF(Q$4="","",ABS(Q16/Q$4))
B85: WCInv | C85: 0 | E85: =E17 -> WCInv is by default excluded
B86: Net Borrowing | C86: 0 | E86: =E18 -> Net borrowing is excluded
B87: Total FCFE | C87: =ABS(C19/C$4) -> 0.15152879 | G87: =IF(G$4="","",ABS(G19/G$4)) -> 0.16499341 | H87: =IF(H$4="","",ABS(H19/H$4)) -> 0.16494398 | I87: =IF(I$4="","",ABS(I19/I$4)) -> 0.15499898 | J87: =IF(J$4="","",ABS(J19/J$4)) -> 0.163824 | K87: =IF(K$4="","",ABS(K19/K$4)) -> 0.14188282 | L87: =IF(L$4="","",ABS(L19/L$4)) -> 0.16015722 | M87: =IF(M$4="","",ABS(M19/M$4)) -> 0.14426429 | N87: =IF(N$4="","",ABS(N19/N$4)) -> 0.11067194 | ... Q87: =IF(Q$4="","",ABS(Q19/Q$4))
B89: Dividends
B90: ="Dividend per share ("&Market_currency&")" -> Dividend per share (USD) | C90: =G90 -> 0 | G90: =Data!C65 -> 0 | H90: =Data!D65 -> 0 | I90: =Data!E65 -> 0 | J90: =Data!F65 -> 0 | K90: =Data!G65 -> 0 | L90: =Data!H65 -> 0 | M90: =Data!I65 -> 0 | N90: =Data!J65 -> 0 | ... Q90: =Data!M65
B91: ="Dividend ("&Market_currency&")" -> Dividend (USD) | C91: =C90*Common_Shares/scaling_factor -> 0 | G91: =IF(G$4="","",G90*Common_Shares/scaling_factor) -> 0 | H91: =IF(H$4="","",H90*Common_Shares/scaling_factor) -> 0 | I91: =IF(I$4="","",I90*Common_Shares/scaling_factor) -> 0 | J91: =IF(J$4="","",J90*Common_Shares/scaling_factor) -> 0 | K91: =IF(K$4="","",K90*Common_Shares/scaling_factor) -> 0 | L91: =IF(L$4="","",L90*Common_Shares/scaling_factor) -> 0 | M91: =IF(M$4="","",M90*Common_Shares/scaling_factor) -> 0 | N91: =IF(N$4="","",N90*Common_Shares/scaling_factor) -> 0 | ... Q91: =IF(Q$4="","",Q90*Common_Shares/scaling_factor)
B92: Payout Ratio | C92: =C90/(C19*scaling_factor/Common_Shares) -> 0 | G92: =IF(G$4="","",G90/(G19*scaling_factor/Common_Shares)) -> 0 | H92: =IF(H$4="","",H90/(H19*scaling_factor/Common_Shares)) -> 0 | I92: =IF(I$4="","",I90/(I19*scaling_factor/Common_Shares)) -> 0 | J92: =IF(J$4="","",J90/(J19*scaling_factor/Common_Shares)) -> 0 | K92: =IF(K$4="","",K90/(K19*scaling_factor/Common_Shares)) -> 0 | L92: =IF(L$4="","",L90/(L19*scaling_factor/Common_Shares)) -> 0 | M92: =IF(M$4="","",M90/(M19*scaling_factor/Common_Shares)) -> 0 | N92: =IF(N$4="","",N90/(N19*scaling_factor/Common_Shares)) -> 0 | ... Q92: =IF(Q$4="","",Q90/(Q19*scaling_factor/Common_Shares))
B93: Dividend tax rate | C93: 0
B94: Dividend after tax Yield | C94: =(C90*(1-dividend_tax_rate))/Market_Price -> 0 | G94: =IF(G$4="","",(G90*(1-dividend_tax_rate))/Market_Price) -> 0 | H94: =IF(H$4="","",(H90*(1-dividend_tax_rate))/Market_Price) -> 0 | I94: =IF(I$4="","",(I90*(1-dividend_tax_rate))/Market_Price) -> 0 | J94: =IF(J$4="","",(J90*(1-dividend_tax_rate))/Market_Price) -> 0 | K94: =IF(K$4="","",(K90*(1-dividend_tax_rate))/Market_Price) -> 0 | L94: =IF(L$4="","",(L90*(1-dividend_tax_rate))/Market_Price) -> 0 | M94: =IF(M$4="","",(M90*(1-dividend_tax_rate))/Market_Price) -> 0 | N94: =IF(N$4="","",(N90*(1-dividend_tax_rate))/Market_Price) -> 0 | ... Q94: =IF(Q$4="","",(Q90*(1-dividend_tax_rate))/Market_Price)
B96: YoY %
B97: Sales | C97: =C4/G4-1 -> -0.045751628 | G97: =IF(H4="","",G4/H4-1) -> 0.10071941 | H97: =IF(I4="","",H4/I4-1) -> 0.18602511 | I97: =IF(J4="","",I4/J4-1) -> 0.29631045 | J97: =IF(K4="","",J4/K4-1) -> 0.42135143 | K97: =IF(L4="","",K4/L4-1) -> 0.10619542 | L97: =IF(M4="","",L4/M4-1) -> 0.21013077 | M97: =IF(N4="","",M4/N4-1) -> 0.24125871 | N97: =IF(O4="","",N4/O4-1) -> 0.13000769 | ... Q97: =IF(R4="","",Q4/R4-1)
B98: Pre-tax Profit | C98: =C13/G13-1 -> -0.17776892 | G98: =IF(H5="","",G13/H13-1) -> 0.13391499 | H98: =IF(I5="","",H13/I13-1) -> 0.27511437 | I98: =IF(J5="","",I13/J13-1) -> 0.25396034 | J98: =IF(K5="","",J13/K13-1) -> 0.61818762 | K98: =IF(L5="","",K13/L13-1) -> -0.038377704 | L98: =IF(M5="","",L13/M13-1) -> 0.25965522 | M98: =IF(N5="","",M13/N13-1) -> 0.42729806 | N98: =IF(O5="","",N13/O13-1) -> 0.17422213 | ... Q98: =IF(R5="","",Q13/R13-1)
B100: Operating Efficiency Analysis | E100: Notes
B101: Balance Sheet | G101: Latest Asset Value
B102: Total Assets | C102: =BS!G32 -> 7430543 | G102: =IF(G$4="","",G106+G105) -> 7430543 | H102: =IF(H$4="","",H106+H105) -> 7091941 | I102: =IF(I$4="","",I106+I105) -> 5607038 | J102: =IF(J$4="","",J106+J105) -> 4942478 | K102: =IF(K$4="","",K106+K105) -> 4185215 | L102: =IF(L$4="","",L106+L105) -> 3281354 | M102: =IF(M$4="","",M106+M105) -> 2084711 | N102: =IF(N$4="","",N106+N105) -> 1998483 | ... Q102: =IF(Q$4="","",Q106+Q105)
B103: Incl. AR | C103: =BS!C4 -> 0 | G103: =IF(G$4="","",Data!D77) -> 124769 | H103: =IF(H$4="","",Data!E77) -> 132906 | I103: =IF(I$4="","",Data!F77) -> 77001 | J103: =IF(J$4="","",Data!G77) -> 62399 | K103: =IF(K$4="","",Data!H77) -> 40219 | L103: =IF(L$4="","",Data!I77) -> 0 | M103: =IF(M$4="","",Data!J77) -> 0 | N103: =IF(N$4="","",Data!K77) -> 0 | ... Q103: =IF(Q$4="","",Data!N77)
B104: Incl. Inventory | C104: =BS!C6+BS!C7 -> 1652091 | G104: =IF(G$4="","",Data!D78) -> 1323602 | H104: =IF(H$4="","",Data!E78) -> 1447367 | I104: =IF(I$4="","",Data!F78) -> 966481 | J104: =IF(J$4="","",Data!G78) -> 647230 | K104: =IF(K$4="","",Data!H78) -> 518513 | L104: =IF(L$4="","",Data!I78) -> 0 | M104: =IF(M$4="","",Data!J78) -> 0 | N104: =IF(N$4="","",Data!K78) -> 0 | ... Q104: =IF(Q$4="","",Data!N78)
B105: Total Liabilities | C105: =BS!G30 -> 3140973 | G105: =Data!C79 -> 3140973 | H105: =Data!D79 -> 2859860 | I105: =Data!E79 -> 2458239 | J105: =Data!F79 -> 2202432 | K105: =Data!G79 -> 1626649 | L105: =Data!H79 -> 1329136 | M105: =Data!I79 -> 638736 | N105: =Data!J79 -> 401523 | ... Q105: =Data!M79
B106: Total Equity | C106: =BS!G27 -> 4289570 | G106: =Data!C80 -> 4289570 | H106: =Data!D80 -> 4232081 | I106: =Data!E80 -> 3148799 | J106: =Data!F80 -> 2740046 | K106: =Data!G80 -> 2558566 | L106: =Data!H80 -> 1952218 | M106: =Data!I80 -> 1445975 | N106: =Data!J80 -> 1596960 | ... Q106: =Data!M80
B108: Operating Asset % of Sales | G108: Latest Asset Value
B109: AR | C109: =C103/C$4 -> 0 | G109: =IF(G$4="","",G103/G$4) -> 0.011783861 | H109: =IF(H$4="","",H103/H$4) -> 0.013816629 | I109: =IF(I$4="","",I103/I$4) -> 0.0094939682 | J109: =IF(J$4="","",J103/J$4) -> 0.0099732811 | K109: =IF(K$4="","",K103/K$4) -> 0.00913678 | L109: =IF(L$4="","",L103/L$4) -> 0 | M109: =IF(M$4="","",M103/M$4) -> 0 | N109: =IF(N$4="","",N103/N$4) -> 0 | ... Q109: =IF(Q$4="","",Q103/Q$4)
B110: Inventory | C110: =C104/C$4 -> 0.16351343 | G110: =IF(G$4="","",G104/G$4) -> 0.12500815 | H110: =IF(H$4="","",H104/H$4) -> 0.15046524 | I110: =IF(I$4="","",I104/I$4) -> 0.11916391 | J110: =IF(J$4="","",J104/J$4) -> 0.10344728 | K110: =IF(K$4="","",K104/K$4) -> 0.11779356 | L110: =IF(L$4="","",L104/L$4) -> 0 | M110: =IF(M$4="","",M104/M$4) -> 0 | N110: =IF(N$4="","",N104/N$4) -> 0 | ... Q110: =IF(Q$4="","",Q104/Q$4)
B111: Properties held for sale | C111: =BS!$G$38/C$4 -> 0 | G111: =BS!$G$38/G$4 -> 0
B113: Cash Flow Statement
B114: CFO/Net Income | G114: =IF(G$4="","",Data!C$22/Data!C15) -> 1.2524485 | H114: =IF(H$4="","",Data!D$22/Data!D15) -> 1.4812146 | I114: =IF(I$4="","",Data!E$22/Data!E15) -> 1.1306306 | J114: =IF(J$4="","",Data!F$22/Data!F15) -> 1.4242558 | K114: =IF(K$4="","",Data!G$22/Data!G15) -> 1.3640996 | L114: =IF(L$4="","",Data!H$22/Data!H15) -> 1.0367412 | M114: =IF(M$4="","",Data!I$22/Data!I15) -> 1.5352986 | N114: =IF(N$4="","",Data!J$22/Data!J15) -> 1.8918009 | ... Q114: =IF(Q$4="","",Data!M$22/Data!M15)
B115: CFO/FCFE | G115: =IF(G$4="","",Data!C$22/G19) -> 1.3009449 | H115: =IF(H$4="","",Data!D$22/H19) -> 1.4471847 | I115: =IF(I$4="","",Data!E$22/I19) -> 0.76879014 | J115: =IF(J$4="","",Data!F$22/J19) -> 1.3552485 | K115: =IF(K$4="","",Data!G$22/K19) -> 1.2862617 | L115: =IF(L$4="","",Data!H$22/L19) -> 1.0502155 | M115: =IF(M$4="","",Data!I$22/M19) -> 1.5657659 | N115: =IF(N$4="","",Data!J$22/N19) -> 1.6690099 | ... Q115: =IF(Q$4="","",Data!M$22/Q19)
...

Sheet DCF
B2: No-Growth DCF Valuation | H2: Notes
B3: No-Growth DCF | C3: =scaling_factor -> 1000 | E3: Special Assumption
B4: Adjusted FCFE | C4: =Normalized_FCF!C19 -> 1531001.7 | D4: =Reporting_currency -> USD | E4: Terminal Growth Rate (g): | F4: =Terminal_Growth -> 0
B5: /Equity Cost of Capital | C5: =Equity_Cost -> 0.075
B6: Stable Income Value | C6: =(C4*(1+Terminal_Growth))/(Equity_Cost-Terminal_Growth) -> 20413356 | D6: =Reporting_currency -> USD | E6: Conservative Valuation: Setting g=0 can be a conservative assumption to avoid overestimating the stock’s value, especially if future growth is uncertain or unreliable.
B7: - Interest-bearing Debt | C7: =BS!G31 -> 1706782 | D7: =Reporting_currency -> USD
B8: + Non-operating Cash | C8: =BS!D66 -> 655172.73 | D8: =Reporting_currency -> USD
B9: + Other Non-operating Assets | C9: =BS!H42 -> 0 | D9: =Reporting_currency -> USD
B10: Equity Value | C10: =C6-C7+C8+C9 -> 19361747 | D10: =Reporting_currency -> USD
B11: * Exchange rate | C11: =Exchange_Rate -> 1 | D11: =Thesis!C15 -> USD
B12: Equity Value per share | C12: =(C10*scaling_factor)/Common_Shares*Exchange_Rate -> 161.55604 | D12: =Market_currency -> USD
B14: Implied Growth Scenario Analysis
B15: FCFE Projection
B16: High Growth Period (HGP) | C16: =Scenarios!C65 -> 0.056956408
B17: High Growth Rate (HGR) | C17: =Scenarios!C64 -> 5
B18: Value Per Share | C18: =(F52-C7+C8+C9)*Exchange_Rate/Common_Shares*scaling_factor -> 177.35705 | D18: =Market_currency -> USD
B20: Year | C20: FCFE | D20: Growth Rates | E20: Discount Factor | F20: PV of FCFE
B21: 1 | C21: =C4*(1+D21) -> 1618202.1 | D21: =IF($C$17<B21,0,DCF!$C$16) -> 0.056956408 | E21: =IF($C$17<B21,0,1/(1+Equity_Cost)^B21) -> 0.93023256 | F21: =C21*E21 -> 1505304.3
B22: 2 | C22: =IF(ROW()-ROW($C$21)<$C$17, $C$21*(1+D22)^(ROW()-ROW($C$21)), 0) -> 1710369.1 | D22: =IF($C$17<B22,0,DCF!$C$16) -> 0.056956408 | E22: =IF($C$17<B22,0,1/(1+Equity_Cost)^B22) -> 0.86533261 | F22: =C22*E22 -> 1480038.1
B23: 3 | C23: =IF(ROW()-ROW($C$21)<$C$17, $C$21*(1+D23)^(ROW()-ROW($C$21)), 0) -> 1807785.5 | D23: =IF($C$17<B23,0,DCF!$C$16) -> 0.056956408 | E23: =IF($C$17<B23,0,1/(1+Equity_Cost)^B23) -> 0.80496057 | F23: =C23*E23 -> 1455196.1
B24: 4 | C24: =IF(ROW()-ROW($C$21)<$C$17, $C$21*(1+D24)^(ROW()-ROW($C$21)), 0) -> 1910750.5 | D24: =IF($C$17<B24,0,DCF!$C$16) -> 0.056956408 | E24: =IF($C$17<B24,0,1/(1+Equity_Cost)^B24) -> 0.74880053 | F24: =C24*E24 -> 1430771
B25: 5 | C25: =IF(ROW()-ROW($C$21)<$C$17, $C$21*(1+D25)^(ROW()-ROW($C$21)), 0) -> 2019580 | D25: =IF($C$17<B25,0,DCF!$C$16) -> 0.056956408 | E25: =IF($C$17<B25,0,1/(1+Equity_Cost)^B25) -> 0.69655863 | F25: =C25*E25 -> 1406755.9
B26: 6 | C26: =IF(ROW()-ROW($C$21)<$C$17, $C$21*(1+D26)^(ROW()-ROW($C$21)), 0) -> 0 | D26: =IF($C$17<B26,0,DCF!$C$16) -> 0 | E26: =IF($C$17<B26,0,1/(1+Equity_Cost)^B26) -> 0 | F26: =C26*E26 -> 0
B27: 7 | C27: =IF(ROW()-ROW($C$21)<$C$17, $C$21*(1+D27)^(ROW()-ROW($C$21)), 0) -> 0 | D27: =IF($C$17<B27,0,DCF!$C$16) -> 0 | E27: =IF($C$17<B27,0,1/(1+Equity_Cost)^B27) -> 0 | F27: =C27*E27 -> 0
B28: 8 | C28: =IF(ROW()-ROW($C$21)<$C$17, $C$21*(1+D28)^(ROW()-ROW($C$21)), 0) -> 0 | D28: =IF($C$17<B28,0,DCF!$C$16) -> 0 | E28: =IF($C$17<B28,0,1/(1+Equity_Cost)^B28) -> 0 | F28: =C28*E28 -> 0
B29: 9 | C29: =IF(ROW()-ROW($C$21)<$C$17, $C$21*(1+D29)^(ROW()-ROW($C$21)), 0) -> 0 | D29: =IF($C$17<B29,0,DCF!$C$16) -> 0 | E29: =IF($C$17<B29,0,1/(1+Equity_Cost)^B29) -> 0 | F29: =C29*E29 -> 0
B30: 10 | C30: =IF(ROW()-ROW($C$21)<$C$17, $C$21*(1+D30)^(ROW()-ROW($C$21)), 0) -> 0 | D30: =IF($C$17<B30,0,DCF!$C$16) -> 0 | E30: =IF($C$17<B30,0,1/(1+Equity_Cost)^B30) -> 0 | F30: =C30*E30 -> 0
B31: 11 | C31: =IF(ROW()-ROW($C$21)<$C$17, $C$21*(1+D31)^(ROW()-ROW($C$21)), 0) -> 0 | D31: =IF($C$17<B31,0,DCF!$C$16) -> 0 | E31: =IF($C$17<B31,0,1/(1+Equity_Cost)^B31) -> 0 | F31: =C31*E31 -> 0
B32: 12 | C32: =IF(ROW()-ROW($C$21)<$C$17, $C$21*(1+D32)^(ROW()-ROW($C$21)), 0) -> 0 | D32: =IF($C$17<B32,0,DCF!$C$16) -> 0 | E32: =IF($C$17<B32,0,1/(1+Equity_Cost)^B32) -> 0 | F32: =C32*E32 -> 0
B33: 13 | C33: =IF(ROW()-ROW($C$21)<$C$17, $C$21*(1+D33)^(ROW()-ROW($C$21)), 0) -> 0 | D33: =IF($C$17<B33,0,DCF!$C$16) -> 0 | E33: =IF($C$17<B33,0,1/(1+Equity_Cost)^B33) -> 0 | F33: =C33*E33 -> 0
... B50: 30 | C50: =IF(ROW()-ROW($C$21)<$C$17, $C$21*(1+D50)^(ROW()-ROW($C$21)), 0) -> 0 | D50: =IF($C$17<B50,0,DCF!$C$16) -> 0 | E50: =IF($C$17<B50,0,1/(1+Equity_Cost)^B50) -> 0 | F50: =C50*E50 -> 0
B51: Terminal Year | C51: =C$21*(1+Terminal_Growth)^$C$17/Equity_Cost -> 21576028 | D51: =Terminal_Growth -> 0 | E51: =1/(1+Equity_Cost)^C17 -> 0.69655863 | F51: =C51*E51 -> 15028968
E52: Total PV | F52: =SUM(F21:F51) -> 22307034
B54: Sensitivity Analysis (Enterprise Value)
A55: =F52 -> 22307034 | B55: =C78 -> 0 | C55: =C77 -> 0.02 | D55: =C76 -> 0.05 | E55: =C75 -> 0.08 | F55: =C74 -> 0.1
A56: 5 | B56: 20413356 | C56: 21060674 | D56: 22067267 | E56: 23119115 | F56: 23846940
A57: 10 | B57: 20413356 | C57: 21702573 | D57: 23881888 | E57: 26403976 | F57: 28306345
A58: 15 | B58: 20413356 | C58: 22515292 | D58: 26366953 | E58: 31289312 | F58: 35327289
A59: 20 | B59: 20413356 | C59: 23362564 | D59: 29183488 | E59: 37350437 | F59: 44609366
A60: 25 | B60: 20413356 | C60: 24168972 | D60: 32110422 | E60: 44292965 | F60: 56001413
A61: 30 | B61: 20413356 | C61: 24896978 | D61: 35007139 | E61: 51913302 | F61: 69463301
B63: Sensitivity Analysis (Equity Value per share)
B64: =B55 -> 0 | C64: =C55 -> 0.02 | D64: =D55 -> 0.05 | E64: =E55 -> 0.08 | F64: =F55 -> 0.1
A65: 0 | B65: =C12 -> 161.55604 | C65: =C12 -> 161.55604 | D65: =C12 -> 161.55604 | E65: =C12 -> 161.55604 | F65: =C12 -> 161.55604
A66: =A56 -> 5 | B66: =(B56-$C$7+$C$8+$C$9)/Common_Shares*$C$3*Exchange_Rate -> 161.55604 | C66: =(C56-$C$7+$C$8+$C$9)/Common_Shares*$C$3*Exchange_Rate -> 166.95732 | D66: =(D56-$C$7+$C$8+$C$9)/Common_Shares*$C$3*Exchange_Rate -> 175.35641 | E66: =(E56-$C$7+$C$8+$C$9)/Common_Shares*$C$3*Exchange_Rate -> 184.13312 | F66: =(F56-$C$7+$C$8+$C$9)/Common_Shares*$C$3*Exchange_Rate -> 190.20616
A67: =A57 -> 10 | B67: =(B57-$C$7+$C$8+$C$9)/Common_Shares*$C$3*Exchange_Rate -> 161.55604 | C67: =(C57-$C$7+$C$8+$C$9)/Common_Shares*$C$3*Exchange_Rate -> 172.31337 | D67: =(D57-$C$7+$C$8+$C$9)/Common_Shares*$C$3*Exchange_Rate -> 190.49776 | E67: =(E57-$C$7+$C$8+$C$9)/Common_Shares*$C$3*Exchange_Rate -> 211.54228 | F67: =(F57-$C$7+$C$8+$C$9)/Common_Shares*$C$3*Exchange_Rate -> 227.4158
A68: =A58 -> 15 | B68: =(B58-$C$7+$C$8+$C$9)/Common_Shares*$C$3*Exchange_Rate -> 161.55604 | C68: =(C58-$C$7+$C$8+$C$9)/Common_Shares*$C$3*Exchange_Rate -> 179.09477 | D68: =(D58-$C$7+$C$8+$C$9)/Common_Shares*$C$3*Exchange_Rate -> 211.23335 | E68: =(E58-$C$7+$C$8+$C$9)/Common_Shares*$C$3*Exchange_Rate -> 252.30593 | F68: =(F58-$C$7+$C$8+$C$9)/Common_Shares*$C$3*Exchange_Rate -> 285.99915
A69: =A59 -> 20 | B69: =(B59-$C$7+$C$8+$C$9)/Common_Shares*$C$3*Exchange_Rate -> 161.55604 | C69: =(C59-$C$7+$C$8+$C$9)/Common_Shares*$C$3*Exchange_Rate -> 186.16448 | D69: =(D59-$C$7+$C$8+$C$9)/Common_Shares*$C$3*Exchange_Rate -> 234.73476 | E69: =(E59-$C$7+$C$8+$C$9)/Common_Shares*$C$3*Exchange_Rate -> 302.88047 | F69: =(F59-$C$7+$C$8+$C$9)/Common_Shares*$C$3*Exchange_Rate -> 363.44958
A70: =A60 -> 25 | B70: =(B60-$C$7+$C$8+$C$9)/Common_Shares*$C$3*Exchange_Rate -> 161.55604 | C70: =(C60-$C$7+$C$8+$C$9)/Common_Shares*$C$3*Exchange_Rate -> 192.89322 | D70: =(D60-$C$7+$C$8+$C$9)/Common_Shares*$C$3*Exchange_Rate -> 259.15734 | E70: =(E60-$C$7+$C$8+$C$9)/Common_Shares*$C$3*Exchange_Rate -> 360.8095 | F70: =(F60-$C$7+$C$8+$C$9)/Common_Shares*$C$3*Exchange_Rate -> 458.50577
A71: =A61 -> 30 | B71: =(B61-$C$7+$C$8+$C$9)/Common_Shares*$C$3*Exchange_Rate -> 161.55604 | C71: =(C61-$C$7+$C$8+$C$9)/Common_Shares*$C$3*Exchange_Rate -> 198.96776 | D71: =(D61-$C$7+$C$8+$C$9)/Common_Shares*$C$3*Exchange_Rate -> 283.32779 | E71: =(E61-$C$7+$C$8+$C$9)/Common_Shares*$C$3*Exchange_Rate -> 424.39423 | F71: =(F61-$C$7+$C$8+$C$9)/Common_Shares*$C$3*Exchange_Rate -> 570.8329
B73: Scenarios | C73: HGR | D73: HGP | E73: Value per share | F73: Probabilities
B74: =Scenarios!B54 -> Snowball Scenario | C74: =Scenarios!C56 -> 0.1 | D74: =Scenarios!C55 -> 10 | E74: =INDEX(B$65:F$71, MATCH(D74, A$65:A$71, 0), MATCH(C74, B$64:F$64, 0)) -> 227.4158 | F74: =Scenarios!C58 -> 0.05
B75: =Scenarios!B36 -> Optimistic | C75: =Scenarios!C38 -> 0.08 | D75: =Scenarios!C37 -> 5 | E75: =INDEX(B$65:F$71, MATCH(D75, A$65:A$71, 0), MATCH(C75, B$64:F$64, 0)) -> 184.13312 | F75: =Scenarios!C40*(1-F$74-F$78) -> 0.18
B76: =Scenarios!B24 -> Base | C76: =Scenarios!C26 -> 0.05 | D76: =Scenarios!C25 -> 5 | E76: =INDEX(B$65:F$71, MATCH(D76, A$65:A$71, 0), MATCH(C76, B$64:F$64, 0)) -> 175.35641 | F76: =Scenarios!C28*(1-F$74-F$78) -> 0.54
B77: =Scenarios!B30 -> Pessimistic | C77: =Scenarios!C32 -> 0.02 | D77: =Scenarios!C31 -> 5 | E77: =INDEX(B$65:F$71, MATCH(D77, A$65:A$71, 0), MATCH(C77, B$64:F$64, 0)) -> 166.95732 | F77: =Scenarios!C34*(1-F$74-F$78) -> 0.18
B78: =Scenarios!B48 -> Devil's advocate | C78: =Scenarios!C50 -> 0 | D78: =Scenarios!C49 -> 10 | E78: =INDEX(B$65:F$71, MATCH(D78, A$65:A$71, 0), MATCH(C78, B$64:F$64, 0)) -> 161.55604 | F78: =Scenarios!C52 -> 0.05
B80: Note of the formulas: | C80: MATCH(1%, C65:E65, 0) finds the column number for HGR = 1%.
C81: MATCH(5, B66:B69, 0) finds the row number for HGP = 5.
C82: INDEX(C66:E69, ...) retrieves the value from the specified range.

Sheet DDM
B2: No-Growth DDM Valuation | H2: Notes
B3: No-Growth DDM | C3: =scaling_factor -> 1000 | E3: Special Assumption
B4: Dividend | C4: =Normalized_FCF!C91*(1-dividend_tax_rate) -> 0 | D4: =Market_currency -> USD | E4: Terminal Growth Rate (g): | F4: =Thesis!E22 -> 0
B5: /Equity Cost of Capital | C5: =Equity_Cost -> 0.075
B6: Dividend Value | C6: =(C4*(1+Terminal_Growth))/(Equity_Cost-Terminal_Growth) -> 0 | D6: =Reporting_currency -> USD
B7: Dividend Value per share | C7: =(C6*scaling_factor)/Common_Shares*Exchange_Rate -> 0 | D7: =Market_currency -> USD
B9: Implied Growth Scenario Analysis
B10: FCFE Projection
B11: High Growth Period (HGP) | C11: =Scenarios!C65 -> 0.056956408
B12: High Growth Rate (HGR) | C12: =Scenarios!C64 -> 5
B13: Value Per Share | C13: =F47/Common_Shares*scaling_factor -> 0 | D13: =Market_currency -> USD
B15: Year | C15: Dividends | D15: Growth Rates | E15: Discount Factor | F15: PV of Dividends
B16: 1 | C16: =C4*(1+D16) -> 0 | D16: =IF($C$12<B16,0,DDM!$C$11) -> 0.056956408 | E16: =IF($C$12<B16,0,1/(1+Equity_Cost)^B16) -> 0.93023256 | F16: =C16*E16 -> 0
B17: 2 | C17: =IF(ROW()-ROW($C$16)<$C$12, $C$16*(1+D17)^(ROW()-ROW($C$16)), 0) -> 0 | D17: =IF($C$12<B17,0,DDM!$C$11) -> 0.056956408 | E17: =IF($C$12<B17,0,1/(1+Equity_Cost)^B17) -> 0.86533261 | F17: =C17*E17 -> 0
B18: 3 | C18: =IF(ROW()-ROW($C$16)<$C$12, $C$16*(1+D18)^(ROW()-ROW($C$16)), 0) -> 0 | D18: =IF($C$12<B18,0,DDM!$C$11) -> 0.056956408 | E18: =IF($C$12<B18,0,1/(1+Equity_Cost)^B18) -> 0.80496057 | F18: =C18*E18 -> 0
B19: 4 | C19: =IF(ROW()-ROW($C$16)<$C$12, $C$16*(1+D19)^(ROW()-ROW($C$16)), 0) -> 0 | D19: =IF($C$12<B19,0,DDM!$C$11) -> 0.056956408 | E19: =IF($C$12<B19,0,1/(1+Equity_Cost)^B19) -> 0.74880053 | F19: =C19*E19 -> 0
B20: 5 | C20: =IF(ROW()-ROW($C$16)<$C$12, $C$16*(1+D20)^(ROW()-ROW($C$16)), 0) -> 0 | D20: =IF($C$12<B20,0,DDM!$C$11) -> 0.056956408 | E20: =IF($C$12<B20,0,1/(1+Equity_Cost)^B20) -> 0.69655863 | F20: =C20*E20 -> 0
B21: 6 | C21: =IF(ROW()-ROW($C$16)<$C$12, $C$16*(1+D21)^(ROW()-ROW($C$16)), 0) -> 0 | D21: =IF($C$12<B21,0,DDM!$C$11) -> 0 | E21: =IF($C$12<B21,0,1/(1+Equity_Cost)^B21) -> 0 | F21: =C21*E21 -> 0
B22: 7 | C22: =IF(ROW()-ROW($C$16)<$C$12, $C$16*(1+D22)^(ROW()-ROW($C$16)), 0) -> 0 | D22: =IF($C$12<B22,0,DDM!$C$11) -> 0 | E22: =IF($C$12<B22,0,1/(1+Equity_Cost)^B22) -> 0 | F22: =C22*E22 -> 0
B23: 8 | C23: =IF(ROW()-ROW($C$16)<$C$12, $C$16*(1+D23)^(ROW()-ROW($C$16)), 0) -> 0 | D23: =IF($C$12<B23,0,DDM!$C$11) -> 0 | E23: =IF($C$12<B23,0,1/(1+Equity_Cost)^B23) -> 0 | F23: =C23*E23 -> 0
B24: 9 | C24: =IF(ROW()-ROW($C$16)<$C$12, $C$16*(1+D24)^(ROW()-ROW($C$16)), 0) -> 0 | D24: =IF($C$12<B24,0,DDM!$C$11) -> 0 | E24: =IF($C$12<B24,0,1/(1+Equity_Cost)^B24) -> 0 | F24: =C24*E24 -> 0
B25: 10 | C25: =IF(ROW()-ROW($C$16)<$C$12, $C$16*(1+D25)^(ROW()-ROW($C$16)), 0) -> 0 | D25: =IF($C$12<B25,0,DDM!$C$11) -> 0 | E25: =IF($C$12<B25,0,1/(1+Equity_Cost)^B25) -> 0 | F25: =C25*E25 -> 0
B26: 11 | C26: =IF(ROW()-ROW($C$16)<$C$12, $C$16*(1+D26)^(ROW()-ROW($C$16)), 0) -> 0 | D26: =IF($C$12<B26,0,DDM!$C$11) -> 0 | E26: =IF($C$12<B26,0,1/(1+Equity_Cost)^B26) -> 0 | F26: =C26*E26 -> 0
B27: 12 | C27: =IF(ROW()-ROW($C$16)<$C$12, $C$16*(1+D27)^(ROW()-ROW($C$16)), 0) -> 0 | D27: =IF($C$12<B27,0,DDM!$C$11) -> 0 | E27: =IF($C$12<B27,0,1/(1+Equity_Cost)^B27) -> 0 | F27: =C27*E27 -> 0
B28: 13 | C28: =IF(ROW()-ROW($C$16)<$C$12, $C$16*(1+D28)^(ROW()-ROW($C$16)), 0) -> 0 | D28: =IF($C$12<B28,0,DDM!$C$11) -> 0 | E28: =IF($C$12<B28,0,1/(1+Equity_Cost)^B28) -> 0 | F28: =C28*E28 -> 0
... B45: 30 | C45: =IF(ROW()-ROW($C$16)<$C$12, $C$16*(1+D45)^(ROW()-ROW($C$16)), 0) -> 0 | D45: =IF($C$12<B45,0,DDM!$C$11) -> 0 | E45: =IF($C$12<B45,0,1/(1+Equity_Cost)^B45) -> 0 | F45: =C45*E45 -> 0
B46: Terminal Year | C46: =C$16*(1+F4)^$C$12/Equity_Cost -> 0 | D46: =Terminal_Growth -> 0 | E46: =1/(1+Equity_Cost)^C12 -> 0.69655863 | F46: =C46*E46 -> 0
E47: Total PV | F47: =SUM(F16:F46) -> 0
B49: Sensitivity Analysis (Enterprise Value)
A50: =F47 -> 0 | B50: =C73 -> 0 | C50: =C72 -> 0.02 | D50: =C71 -> 0.05 | E50: =C70 -> 0.08 | F50: =C69 -> 0.1
A51: 5 | B51: 0 | C51: 0 | D51: 0 | E51: 0 | F51: 0
A52: 10 | B52: 0 | C52: 0 | D52: 0 | E52: 0 | F52: 0
A53: 15 | B53: 0 | C53: 0 | D53: 0 | E53: 0 | F53: 0
A54: 20 | B54: 0 | C54: 0 | D54: 0 | E54: 0 | F54: 0
A55: 25 | B55: 0 | C55: 0 | D55: 0 | E55: 0 | F55: 0
A56: 30 | B56: 0 | C56: 0 | D56: 0 | E56: 0 | F56: 0
B58: Sensitivity Analysis (Equity Value per share)
B59: =B50 -> 0 | C59: =C50 -> 0.02 | D59: =D50 -> 0.05 | E59: =E50 -> 0.08 | F59: =F50 -> 0.1
A60: 0 | B60: =C7 -> 0 | C60: =C7 -> 0 | D60: =C7 -> 0 | E60: =C7 -> 0 | F60: =C7 -> 0
A61: =A51 -> 5 | B61: =B51/Common_Shares*$C$3*Exchange_Rate -> 0 | C61: =C51/Common_Shares*$C$3*Exchange_Rate -> 0 | D61: =D51/Common_Shares*$C$3*Exchange_Rate -> 0 | E61: =E51/Common_Shares*$C$3*Exchange_Rate -> 0 | F61: =F51/Common_Shares*$C$3*Exchange_Rate -> 0
A62: =A52 -> 10 | B62: =B52/Common_Shares*$C$3*Exchange_Rate -> 0 | C62: =C52/Common_Shares*$C$3*Exchange_Rate -> 0 | D62: =D52/Common_Shares*$C$3*Exchange_Rate -> 0 | E62: =E52/Common_Shares*$C$3*Exchange_Rate -> 0 | F62: =F52/Common_Shares*$C$3*Exchange_Rate -> 0
A63: =A53 -> 15 | B63: =B53/Common_Shares*$C$3*Exchange_Rate -> 0 | C63: =C53/Common_Shares*$C$3*Exchange_Rate -> 0 | D63: =D53/Common_Shares*$C$3*Exchange_Rate -> 0 | E63: =E53/Common_Shares*$C$3*Exchange_Rate -> 0 | F63: =F53/Common_Shares*$C$3*Exchange_Rate -> 0
A64: =A54 -> 20 | B64: =B54/Common_Shares*$C$3*Exchange_Rate -> 0 | C64: =C54/Common_Shares*$C$3*Exchange_Rate -> 0 | D64: =D54/Common_Shares*$C$3*Exchange_Rate -> 0 | E64: =E54/Common_Shares*$C$3*Exchange_Rate -> 0 | F64: =F54/Common_Shares*$C$3*Exchange_Rate -> 0
A65: =A55 -> 25 | B65: =B55/Common_Shares*$C$3*Exchange_Rate -> 0 | C65: =C55/Common_Shares*$C$3*Exchange_Rate -> 0 | D65: =D55/Common_Shares*$C$3*Exchange_Rate -> 0 | E65: =E55/Common_Shares*$C$3*Exchange_Rate -> 0 | F65: =F55/Common_Shares*$C$3*Exchange_Rate -> 0
A66: =A56 -> 30 | B66: =B56/Common_Shares*$C$3*Exchange_Rate -> 0 | C66: =C56/Common_Shares*$C$3*Exchange_Rate -> 0 | D66: =D56/Common_Shares*$C$3*Exchange_Rate -> 0 | E66: =E56/Common_Shares*$C$3*Exchange_Rate -> 0 | F66: =F56/Common_Shares*$C$3*Exchange_Rate -> 0
B68: Scenarios | C68: HGR | D68: HGP | E68: Value per share | F68: Probabilities
B69: =Scenarios!B54 -> Snowball Scenario | C69: =Scenarios!C56 -> 0.1 | D69: =Scenarios!C55 -> 10 | E69: =INDEX(B$60:F$66, MATCH(D69, A$60:A$66, 0), MATCH(C69, B$59:F$59, 0)) -> 0 | F69: =Scenarios!C58 -> 0.05
B70: =Scenarios!B36 -> Optimistic | C70: =Scenarios!C38 -> 0.08 | D70: =Scenarios!C37 -> 5 | E70: =INDEX(B$60:F$66, MATCH(D70, A$60:A$66, 0), MATCH(C70, B$59:F$59, 0)) -> 0 | F70: =Scenarios!C40*(1-F$69-F$73) -> 0.18
B71: =Scenarios!B24 -> Base | C71: =Scenarios!C26 -> 0.05 | D71: =Scenarios!C25 -> 5 | E71: =INDEX(B$60:F$66, MATCH(D71, A$60:A$66, 0), MATCH(C71, B$59:F$59, 0)) -> 0 | F71: =Scenarios!C28*(1-F$69-F$73) -> 0.54
B72: =Scenarios!B30 -> Pessimistic | C72: =Scenarios!C32 -> 0.02 | D72: =Scenarios!C31 -> 5 | E72: =INDEX(B$60:F$66, MATCH(D72, A$60:A$66, 0), MATCH(C72, B$59:F$59, 0)) -> 0 | F72: =Scenarios!C34*(1-F$69-F$73) -> 0.18
B73: =Scenarios!B48 -> Devil's advocate | C73: =Scenarios!C50 -> 0 | D73: =Scenarios!C49 -> 10 | E73: =INDEX(B$60:F$66, MATCH(D73, A$60:A$66, 0), MATCH(C73, B$59:F$59, 0)) -> 0 | F73: =Scenarios!C52 -> 0.05
B75: Note of the formulas: | C75: MATCH(1%, C65:E65, 0) finds the column number for HGR = 1%.
C76: MATCH(5, B66:B69, 0) finds the row number for HGP = 5.
C77: INDEX(C66:E69, ...) retrieves the value from the specified range.

Sheet Scenarios
B2: Current Situation | H2: Warning: Do Not Remove this logic
B3: Selection | H3: 0 | I3: =-Market_Price -> -196.45
B4: Past Years Selected | C4: 3 | E4: Tie the business story into the three levers of value: FCFE, growth and risk. | H4: 1 | I4: =IF(ROW()-3 < $C$76, $C$77, IF(ROW()-3 = $C$76, $C$77 + $C$60, "")) -> 0
H5: 2 | I5: =IF(ROW()-3 < $C$76, $C$77, IF(ROW()-3 = $C$76, $C$77 + $C$60, "")) -> 0
B6: Latest | C6: =DCF!C3 -> 1000 | E6: Prompt for fundamental Analysis | H6: 3 | I6: =IF(ROW()-3 < $C$76, $C$77, IF(ROW()-3 = $C$76, $C$77 + $C$60, "")) -> 177.33733
B7: EBIT | C7: =Normalized_FCF!G8 -> 2508432 | D7: =Reporting_currency -> USD | E7: ="Please develop three logical "&C18&"-year scenarios (Base Case, Pessimistic Case, Optimistic Case) and two extreme "&C46&"-year scenarios (Success Scenario, Devil’s Advocate Scenario) for "&Thesis!C5&"("&Thesis!C11&"). Each scenario should include the Compound Growth Rate, the Probability Assessment, and the Business Narrative." -> Please develop three logical 5-year scenarios (Base Case, Pessimistic Case, Optimistic Case) and two extreme 10-year scenarios (Success Scenario, Devil’s Advocate Scenario) for lululemon athletica inc.(LULU). Each scenario should include the Compound Growth Rate, the Probability Assessment, and the Business Narrative. | H7: 4 | I7: =IF(ROW()-3 < $C$76, $C$77, IF(ROW()-3 = $C$76, $C$77 + $C$60, ""))
B8: FCFE | C8: =Normalized_FCF!G19 -> 1746971 | D8: =Reporting_currency -> USD | H8: 5 | I8: =IF(ROW()-3 < $C$76, $C$77, IF(ROW()-3 = $C$76, $C$77 + $C$60, ""))
B9: Normalized | C9: =Normalized_FCF!C19 -> 1531001.7 | D9: =Reporting_currency -> USD | H9: 6 | I9: =IF(ROW()-3 < $C$76, $C$77, IF(ROW()-3 = $C$76, $C$77 + $C$60, ""))
H10: 7 | I10: =IF(ROW()-3 < $C$76, $C$77, IF(ROW()-3 = $C$76, $C$77 + $C$60, ""))
B11: YoY CAGR | H11: 8 | I11: =IF(ROW()-3 < $C$76, $C$77, IF(ROW()-3 = $C$76, $C$77 + $C$60, ""))
B12: Sales | C12: =(Normalized_FCF!G4/OFFSET(Normalized_FCF!G4, 0, $C$4))^(1/$C$4) - 1 -> 0.19168053 | H12: 9 | I12: =IF(ROW()-3 < $C$76, $C$77, IF(ROW()-3 = $C$76, $C$77 + $C$60, ""))
B13: Operating EBIT | C13: =(Normalized_FCF!G8/OFFSET(Normalized_FCF!G8, 0, $C$4))^(1/$C$4) - 1 -> 0.21937648 | H13: 10 | I13: =IF(ROW()-3 < $C$76, $C$77, IF(ROW()-3 = $C$76, $C$77 + $C$60, ""))
B14: FCFE | C14: =(Normalized_FCF!G19/OFFSET(Normalized_FCF!G19, 0, $C$4))^(1/$C$4) - 1 -> 0.1945093
B16: General Scenarios
B17: Assumption | E17: Guidance Note
B18: High Growth Period (HGP) | C18: 5 | E18: Fundamental analysis and market signal analysis should be combined, with fundamental analysis given priority and market signal analysis serving as a supplement. Market signal analysis predicts a company's future trend, while fundamental analysis interprets the trend and identifies relevant fundamental factors and possibilities.
B20: Reference
B21: Market Price | C21: =Market_Price -> 196.45 | D21: =Market_currency -> USD
B22: No Growth Value per share | C22: =IF(valuation_method="DCF",DCF!C12,DDM!C7) -> 161.55604 | D22: =Market_currency -> USD
B24: Base | E24: Business Story
B25: High Growth Period (HGP) | C25: =C18 -> 5
B26: High Growth Rate (HGR) | C26: 0.05
B27: Value per share | C27: =IF(valuation_method="DCF",DCF!E76,DDM!E71) -> 175.35641 | D27: =Market_currency -> USD
B28: Probabilities | C28: 0.6
B30: Pessimistic | E30: Business Story
B31: High Growth Period (HGP) | C31: =C18 -> 5
B32: High Growth Rate (HGR) | C32: 0.02
B33: Value per share | C33: =IF(valuation_method="DCF",DCF!E77,DDM!E72) -> 166.95732 | D33: =Market_currency -> USD
B34: Probabilities | C34: 0.2
B36: Optimistic | E36: Business Story
B37: High Growth Period (HGP) | C37: =C18 -> 5
B38: High Growth Rate (HGR) | C38: 0.08
B39: Value per share | C39: =IF(valuation_method="DCF",DCF!E75,DDM!E70) -> 184.13312 | D39: =Market_currency -> USD
B40: Probabilities | C40: =1-C28-C34 -> 0.2
B42: Expected Value = | C42: =C27*C28+C33*C34+C39*C40 -> 175.43193 | D42: =Market_currency -> USD
B44: Extreme Scenarios
B45: Assumption
B46: High Growth Period (HGP) | C46: 10
B48: Devil's advocate | E48: Business Story
B49: High Growth Period (HGP) | C49: =C46 -> 10
B50: High Growth Rate (HGR) | C50: 0
B51: Value per share | C51: =IF(valuation_method="DCF",DCF!E78,DDM!E73) -> 161.55604 | D51: =Market_currency -> USD
B52: Probabilities | C52: 0.05
B54: Snowball Scenario | E54: Business Story
B55: High Growth Period (HGP) | C55: =C46 -> 10
B56: High Growth Rate (HGR) | C56: 0.1
B57: Value per share | C57: =IF(valuation_method="DCF",DCF!E74,DDM!E69) -> 227.4158 | D57: =Market_currency -> USD
B58: Probabilities | C58: 0.05
B60: Expected Value = | C60: =C51*C52+C57*C58+C42*(1-C52-C58) -> 177.33733 | D60: =Market_currency -> USD | E60: is assumed to be materialized in | F60: =Thesis!F28 -> 3
B62: Growth Classification
B63: Equity Value Driving Factors | E63: Note on Manual Adjustments
B64: High Growth Period (HGP) | C64: =C18 -> 5 | E64: Use general Scenarios' HGP assumption
B65: High Growth Rate (HGR) | C65: 0.056956408 | E65: Use Excel Goal Seek to find the HGR
B66: Equity Value per share | C66: =IF(valuation_method="DCF",DCF!C18,DDM!C13) -> 177.35705 | D66: =Market_currency -> USD | E66: Set to Expected Equity Value
B68: Type of Company | E68: Note on the logic
B69: Negative Growth | C69: =IF(C60<C22,"Y","N") -> N
B70: Low Growth | C70: =IF(C69="Y","N",IF(C65>8%,"N","Y")) -> Y | E70: >8% is Categorized as High Growth
B71: High Growth | C71: =IF(C65>8%,"Y","N") -> N
B72: Asset Play | C72: =IF(F72>50%,"Y","N") -> N | E72: The Non-FCF Value is of the Expected Value, at | F72: =BS!D89/C60 -> -0.049480365
B74: Margin of Safety (MOS)
B75: Inputs
B76: Expected Holding Period | C76: =F60 -> 3
B77: After-tax Dividend per share | C77: =Normalized_FCF!C90*(1-dividend_tax_rate) -> 0 | D77: =Market_currency -> USD
B79: Target Price Output
B80: @Target Annual Return | C80: =Thesis!F29 -> 0.35
B81: PV(Dividends) | C81: =PV(C80, C76, -C77, 0) -> 0
B82: PV(Equity Value) | C82: =C60/(1+C80)^C76 -> 72.077359
B83: Buy Below | C83: =C81+C82 -> 72.077359 | D83: =Market_currency -> USD | E83: at a MOS of | F83: =(1-C83/C60) -> 0.59355789
B85: Current Return Output
B86: @Market Price | C86: =Market_Price -> 196.45 | D86: =Market_currency -> USD
B87: Annual Return | C87: =IRR(OFFSET($I$3, 0, 0, $C$76 + 1, 1)) -> -0.033542605
B89: Entry Price Output
B90: @ Entry Yield | C90: =Thesis!F30 -> 0.25
B91: PV(Dividends) | C91: =PV(C90, C76, -C77, 0) -> 0
B92: PV(Equity Value) | C92: =C60/(1+C90)^C76 -> 90.796715
B93: Buy Below | C93: =C91+C92 -> 90.796715 | D93: =Market_currency -> USD | E93: at a MOS of | F93: =(1-C93/C60) -> 0.488
B95: Sell Price Output
B96: @Selling Yield | C96: =Thesis!F31 -> 0.075
B97: PV(Dividends) | C97: =PV(C96, C76, -C77, 0) -> 0
B98: PV(Equity Value) | C98: =C60/(1+C96)^C76 -> 142.74956
B99: Sell Above | C99: =C97+C98 -> 142.74956 | D99: HKD | E99: at a MOS of | F99: =(1-C99/C60) -> 0.19503943
B101: Exit Price Output
B102: @Benchmark Yield | C102: =Thesis!F32 -> 0.1174
B103: PV(Dividends) | C103: =PV(C102, C76, -C77, 0) -> 0
B104: PV(Equity Value) | C104: =C60/(1+C102)^C76 -> 127.10838
B105: Sell Above | C105: =C103+C104 -> 127.10838 | D105: HKD | E105: at a MOS of | F105: =(1-C105/C66) -> 0.28331927
E107: Inputs Legend
E108: Font Color | F108: Fact or Verified Data
E109: Font Color | F109: Subjective Driving Factors
E110: Font Color | F110: Subjective Non-Driving Factors

Sheet Breakdown
B2: Divisional Analysis (Optional)

Sheet 投资主题
B1: 模型最后更新日期: | C1: =Thesis!C1 -> 45874 | D1: =Thesis!D1 -> INT | E1: Selected: | F1: =Thesis!F1 -> N
A2: 执行摘要
B4: 公司信息
B5: 公司名称： | C5: =Thesis!C5 -> lululemon athletica inc.
B6: 股份数量： | C6: =Common_Shares -> 119845391
B7: 报告间隔： | C7: =Thesis!C7 -> 6
B8: 下次更新日期： | C8: =EOMONTH(EDATE(BS!C1,C7+2),0) -> 46053
B10: 上市信息
B11: 股票代码： | C11: =Thesis!C11 -> LULU
B12: 市场价格： | C12: =Market_Price -> 196.45
B13: 市价货币： | C13: =Market_currency -> USD
B14: 市值： | C14: =投资主题!C12*Common_Shares/1000000 -> 23543.627 | D14: =IF(D11="","",投资主题!D12*Common_Shares/1000000)
B15: 外汇符号： | C15: =IF(C25=C13,C13,C25&"/"&C13) -> USD | D15: =IF(D11="","",IF(C25=D13,D13,C25&"/"&D13))
B16: 汇率： | C16: =Exchange_Rate -> 1
B18: 指导说明：该模型使用结构化的投资流程来评估公司，确定其内在价值和目标价格。它关注可持续的自由现金流（FCF）能力，调整财务结构，纳入增长情景，并根据得出的内在价值计算预期回报。
B20: 估值概述
B21: 增长分类: | C21: =IF(Scenarios!C69="Y",Scenarios!B69,"")&IF(Scenarios!C70="Y",Scenarios!B70,"")&IF(Scenarios!C71="Y",Scenarios!B71,"")&" "&IF(Scenarios!C72="Y",Scenarios!B72,"") -> Low Growth | D21: 估值方法 | E21: =valuation_method -> DCF
B22: 对比板块: | C22: =Thesis!C22 -> CNS_02 | D22: =IF(valuation_method="DDM","终值贴现率","") | E22: =Thesis!E22 -> 0
B23: 商业模式风险溢价: | C23: =Thesis!C23 -> N
B24: 管理风险溢价: | C24: =Thesis!C24 -> N
B25: 报告货币: | C25: =Reporting_currency -> USD | D25: =IF(D11="","",Market_currency&"/"&D13&":") | E25: =IF(D11="","",1/Exchange_Rate*D16)
B26: ="预期股权价值 ("&C13&") :" -> 预期股权价值 (USD) : | C26: =C132 -> 177.33733 | D26: 市场隐含年回报率: | E26: =Scenarios!C87 -> -0.033542605
B28: 估值输出 | C28: =C145&" ("&Market_currency&")" -> LULU (USD) | D28: =IF(D11="","",D145&" ("&D13&")") | E28: 持有期 | F28: =Thesis!F28 -> 3
B29: 目标价格 | C29: =C149 -> 72.077359 | D29: =D149 | E29: 目标回报率 | F29: =Thesis!F29 -> 0.35
B30: 入场价格 | C30: =C157 -> 90.796715 | D30: =D157 | E30: 入场收益率 | F30: =Thesis!F30 -> 0.25
B31: 卖出价格 | C31: =C165 -> 142.74956 | D31: =D165 | E31: 基础Equity Cost | F31: =Thesis!F31 -> 0.075
B32: 退出价格 | C32: =C173 -> 127.10838 | D32: =D173 | E32: 基准收益率 | F32: =Thesis!F32 -> 0.1174
A34: 步骤1：确定公司可持续盈利能力（计算标准化FCFE）
B36: 目标：量化业务持续生成的潜在自由现金流（FCFE），去除临时波动或会计选择的影响。
B37: FCFE = (Normalized Operating EBIT + Depreciation & Amortization – Capital Expenditures) + Stable Non-Operating EBIT + Net Interest Income – Taxes – NCI’s Share of Profits – Working Capital Investment
B39: 关键组成部分 | C39: =scaling_factor -> 1000
B40: • Normalized Operating EBIT：核心业务运营的税前息前利润，调整以剔除一次性或非经常性项目，形成可持续盈利基础。
B41: Normalized Operating EBIT = | C41: =Normalized_FCF!C8 -> 2062510.7 | D41: =Reporting_currency -> USD
B43: • Depreciation & Amortization (D&A): 非现金费用，加入以反映运营产生的现金。 • Capital Expenditures (Capex): 维持或扩展运营资产所需的现金流出。
B44: D&A = | C44: =Normalized_FCF!C9 -> 0 | D44: =Reporting_currency -> USD
B45: Capex = | C45: =Normalized_FCF!C10 -> 0 | D45: =Reporting_currency -> USD
B47: • Stable Non-Operating EBIT: 来自非核心资产的持续收益，如固定收益投资、支付股息的股票或租赁物业。
B48: Stable Non-Operating EBIT = | C48: =Normalized_FCF!C11 -> 0 | D48: =Reporting_currency -> USD
B50: • Net Interest Income: 利息收入减去利息支出
B51: Operating Interest Income = | C51: =Normalized_FCF!C48 -> 0 | D51: =Reporting_currency -> USD
B52: Interest Expense = | C52: =Normalized_FCF!C47 -> 0 | D52: =Reporting_currency -> USD
B53: Net Interest Income = | C53: =Normalized_FCF!C12 -> 0 | D53: =Reporting_currency -> USD
B55: • NCI’s Share of Profits: NCI代表子公司中母公司未拥有的股权部分。
B56: Est. NCI’s Share of Profits = | C56: =Normalized_FCF!C15 -> 0 | D56: =Reporting_currency -> USD
B58: • Taxes: Tax = (Normalized Operating EBIT + Stable Non-Operating EBIT + Interest Income – Interest Expense) × Tax Rate
B59: Taxes = | C59: =Normalized_FCF!C14 -> -531509.02 | D59: =Reporting_currency -> USD
B61: • Working Capital Investment (WCInv): WCInv仅在显著扭曲FCFE时纳入。
B62: WCInv = | C62: =Normalized_FCF!C17 -> 0 | D62: =Reporting_currency -> USD
B64: 关于净借款的说明：理论上，本金偿还通过净借款核算。然而，该模型旨在避免明确预测债务发行或偿还。相反，本金偿还通过有息债务在股权价值调整中反映。
B65: 洞察：这一步骤通过纳入运营和稳定的非运营来源，同时考虑税金和再投资需求，确保现金流的全面衡量。
B67: 最新FCFE = | C67: =Normalized_FCF!G19 -> 1746971 | D67: =Reporting_currency -> USD
B68: Normalized FCFE = | C68: =Normalized_FCF!C19 -> 1531001.7 | D68: =Reporting_currency -> USD
B69: Normalized FCFE/Market Cap = | C69: =Normalized_FCF!C126 -> 0.065028287
B70: After tax Dividend/Market Cap = | C70: =Normalized_FCF!C94 -> 0 | E70: 派息比率: | F70: =Normalized_FCF!C92 -> 0
B72: 杜邦分析 | C72: Normalized | D72: 最新
B73: ROE = | C73: =Normalized_FCF!C121 -> 0.48081993 | D73: =Normalized_FCF!G121 -> 0.5847747
B74: =Normalized_FCF!B118 -> Pre-tax Profit/Sales | C74: =Normalized_FCF!C118 -> 0.20413416 | D74: =Normalized_FCF!G118 -> 0.23690991
B75: =Normalized_FCF!B119 -> Sales/Total Assets | C75: =Normalized_FCF!C119 -> 1.3597528 | D75: =Normalized_FCF!G119 -> 1.4249465
B76: =Normalized_FCF!B120 -> Total Assets/Equity | C76: =Normalized_FCF!C120 -> 1.7322349 | D76: =Normalized_FCF!G120 -> 1.7322349
A78: 步骤2：计算无增长基线（计算稳定收入价值）
B80: 目标：确定内在价值，假设当前的标准化FCFE保持不变且无增长，提供保守的基线。
B81: Stable Income Value = Normalized FCFE / (Cost of Equity – Terminal Growth Rate)
B83: 关键组成部分
B84: Base Cost of Equity | C84: =F31 -> 0.075
B85: Risk Premium | C85: =IF(C23="Y",1%,0)+IF(C24="Y",1%,0) -> 0
B86: Cost of Equity = | C86: =F31+C85 -> 0.075
B88: 说明：
B89: Cost of Equity: 反映公司的风险概况，代表投资者为承担拥有此类业务一般风险所需的最低回报，而目标年回报率作为投资者要求的回报率。
B90: Terminal Growth Rate: 将g设为0%是一个保守假设，仅基于公司当前表现的盈利能力估值，不依赖潜在乐观的未来增长预测。
B92: Terminal Growth Rate (g) = | C92: 0
B93: No Growth SIV Per Share = | C93: =DCF!C6*scaling_factor*Exchange_Rate/Common_Shares -> 170.33076 | D93: =Market_currency -> USD
A95: 步骤3：调整财务结构（计算无增长股权价值）
B97: 目标：通过纳入公司的资产负债表结构，细化稳定收入价值（SIV）。
B98: Equity Value = Stable Income Value – Total Interest-Bearing Debt + Non-Operating Cash + Other Non-Operating Assets
B100: 关键组成部分
B101: 关于债务的说明：总有息债务包括本金偿还。理想情况下，应根据偿还时间表贴现。但为简单和保守起见，该模型使用总有息债务的账面价值。
B102: Total Interest-Bearing Debt = | C102: =DCF!C7 -> 1706782 | D102: =Reporting_currency -> USD
B103: Total Interest-Bearing Debt per share = | C103: =C102*scaling_factor*Exchange_Rate/Common_Shares -> 14.241532 | D103: =Market_currency -> USD
B104: Debt to Equity Ratio = | C104: =IF(BS!G31/BS!G27>300%,"nm",BS!G31/BS!G27) -> 0.39789116
B105: Debt to EBIT Ratio = | C105: =IF(BS!C50>30,"nm",BS!C50) -> 0.82752635
B107: • Non-Operating Cash: 运营不需要的超额现金
B108: Total Cash = | C108: =BS!C66 -> 1325272 | D108: =Reporting_currency -> USD
B109: Est. Non-Operating Cash = | C109: =DCF!C8 -> 655172.73 | D109: =Reporting_currency -> USD
B110: Est. Non-Operating Cash per share = | C110: =C109*scaling_factor*Exchange_Rate/Common_Shares -> 5.4668162 | D110: =Market_currency -> USD
B112: • Other Non-Operating Assets: 不贡献FCFE的资产（如非收益性投资或物业）
B113: Other Non-Operating Assets = | C113: =DCF!C9 -> 0 | D113: =Reporting_currency -> USD
B114: Other Non-Operating Assets per share = | C114: =C113*scaling_factor*Exchange_Rate/Common_Shares -> 0 | D114: =Market_currency -> USD
B116: 洞察：无增长股权价值每股代表公司在考虑未来增长潜力前，基于当前可持续运营和净财务状况的内在价值估计，作为基本锚定的估值基线。
B118: 无增长股权价值每股 = | C118: =IF(valuation_method="DCF",DCF!C12,DDM!C7) -> 161.55604 | D118: =Market_currency -> USD
B119: 估计(净资产)可变现价值 | C119: =BS!D47 -> -4.6442003 | D119: =Market_currency -> USD
A121: 步骤4：纳入未来潜力（情景分析）
B123: 目标：通过建模合理的FCFE/股息、高增长期（HGP）和高增长率（HGR）情景，并按概率加权，估计内在价值。
B125: 情景 | C125: HGR | D125: HGP | E125: 每股EV | F125: 概率
B126: =DCF!B74 -> Snowball Scenario | C126: =DCF!C74 -> 0.1 | D126: =DCF!D74 -> 10 | E126: =ROUND(IF(valuation_method="DCF",DCF!E74,DDM!E69),2)&" "&Market_currency -> 227.42 USD | F126: =DCF!F74 -> 0.05
B127: =DCF!B75 -> Optimistic | C127: =DCF!C75 -> 0.08 | D127: =DCF!D75 -> 5 | E127: =ROUND(IF(valuation_method="DCF",DCF!E75,DDM!E70),2)&" "&Market_currency -> 184.13 USD | F127: =DCF!F75 -> 0.18
B128: =DCF!B76 -> Base | C128: =DCF!C76 -> 0.05 | D128: =DCF!D76 -> 5 | E128: =ROUND(IF(valuation_method="DCF",DCF!E76,DDM!E71),2)&" "&Market_currency -> 175.36 USD | F128: =DCF!F76 -> 0.54
B129: =DCF!B77 -> Pessimistic | C129: =DCF!C77 -> 0.02 | D129: =DCF!D77 -> 5 | E129: =ROUND(IF(valuation_method="DCF",DCF!E77,DDM!E72),2)&" "&Market_currency -> 166.96 USD | F129: =DCF!F77 -> 0.18
B130: =DCF!B78 -> Devil's advocate | C130: =DCF!C78 -> 0 | D130: =DCF!D78 -> 10 | E130: =ROUND(IF(valuation_method="DCF",DCF!E78,DDM!E73),2)&" "&Market_currency -> 161.56 USD | F130: =DCF!F78 -> 0.05
B132: Expected Equity Value = | C132: =Scenarios!C60 -> 177.33733 | D132: =Market_currency -> USD
B134: 洞察：分析市场大幅波动作为市场感知结果范围的指标，包括定义“雪球”或“魔鬼代言人”等情景边界的极端情况。情景分析使用基本推理评估这些情景的可能性。
...
